---- AspectJ Properties ---
AspectJ Compiler 1.6.2 built on Saturday Oct 4, 2008 at 05:47:07 GMT
---- Dump Properties ---
Dump file: ajcore.20160604.114252.272.txt
Dump reason: org.aspectj.bridge.AbortException
Dump on exception: true
Dump at exit condition: abort
---- Exception Information ---
Message: abort trouble in: 
public abstract class org.springframework.util.ObjectUtils extends java.lang.Object:
  private static final int INITIAL_HASH = 7
  private static final int MULTIPLIER = 31
  private static final String EMPTY_STRING = ""
  private static final String NULL_STRING = "null"
  private static final String ARRAY_START = "{"
  private static final String ARRAY_END = "}"
  private static final String EMPTY_ARRAY = "{}"
  private static final String ARRAY_ELEMENT_SEPARATOR = ", "
  public void <init>():
                    ALOAD_0     // Lorg/springframework/util/ObjectUtils; this   (line 39)
                    INVOKESPECIAL java.lang.Object.<init> ()V
    constructor-execution(void org.springframework.util.ObjectUtils.<init>())
    |               RETURN
    constructor-execution(void org.springframework.util.ObjectUtils.<init>())
  end public void <init>()

  public static boolean isCheckedException(Throwable):
                    ALOAD_0     // Ljava/lang/Throwable; ex   (line 62)
                    INSTANCEOF java.lang.RuntimeException
                    IFNE L0
                    ALOAD_0     // Ljava/lang/Throwable; ex
                    INSTANCEOF java.lang.Error
                    IFEQ L1
                L0: ICONST_0
                    GOTO L2
                L1: ICONST_1
                L2: IRETURN
  end public static boolean isCheckedException(Throwable)

  public static boolean isCompatibleWithThrowsClause(Throwable, Class[]):
                    ALOAD_0     // Ljava/lang/Throwable; ex   (line 73)
                    INVOKESTATIC org.springframework.util.ObjectUtils.isCheckedException (Ljava/lang/Throwable;)Z
                    IFNE L0
                    ICONST_1   (line 74)
                    IRETURN
                L0: ALOAD_1     // [Ljava/lang/Class; declaredExceptions   (line 76)
                    IFNULL L4
                    ICONST_0   (line 77)
                    ISTORE_2
                    GOTO L3   (line 78)
                L1: ALOAD_1     // [Ljava/lang/Class; declaredExceptions   (line 79)
                    ILOAD_2     // I i
                    AALOAD
                    ALOAD_0     // Ljava/lang/Throwable; ex
                    INVOKEVIRTUAL java.lang.Object.getClass ()Ljava/lang/Class;
                    INVOKEVIRTUAL java.lang.Class.isAssignableFrom (Ljava/lang/Class;)Z
                    IFEQ L2
                    ICONST_1   (line 80)
                    IRETURN
                L2: IINC_2 1     // I i   (line 82)
                L3: ILOAD_2     // I i   (line 78)
                    ALOAD_1     // [Ljava/lang/Class; declaredExceptions
                    ARRAYLENGTH
                    IF_ICMPLT L1
                L4: ICONST_0   (line 85)
                    IRETURN
  end public static boolean isCompatibleWithThrowsClause(Throwable, Class[])

  public static boolean isArray(Object):
                    ALOAD_0     // Ljava/lang/Object; obj   (line 94)
                    IFNULL L0
                    ALOAD_0     // Ljava/lang/Object; obj
                    INVOKEVIRTUAL java.lang.Object.getClass ()Ljava/lang/Class;
                    INVOKEVIRTUAL java.lang.Class.isArray ()Z
                    IFEQ L0
                    ICONST_1
                    IRETURN
                L0: ICONST_0
                    IRETURN
  end public static boolean isArray(Object)

  public static boolean isEmpty(Object[]):
                    ALOAD_0     // [Ljava/lang/Object; array   (line 103)
                    IFNULL L0
                    ALOAD_0     // [Ljava/lang/Object; array
                    ARRAYLENGTH
                    IFEQ L0
                    ICONST_0
                    IRETURN
                L0: ICONST_1
                    IRETURN
  end public static boolean isEmpty(Object[])

  public static boolean containsElement(Object[], Object):
                    ALOAD_0     // [Ljava/lang/Object; array   (line 114)
                    IFNONNULL L0
                    ICONST_0   (line 115)
                    IRETURN
                L0: ALOAD_0     // [Ljava/lang/Object; array   (line 117)
                    DUP
                    ASTORE 5
                    ARRAYLENGTH
                    ISTORE 4
                    ICONST_0
                    ISTORE_3
                    GOTO L3
                L1: ALOAD 5
                    ILOAD_3
                    AALOAD
                    ASTORE_2
                    ALOAD_2     // Ljava/lang/Object; arrayEle   (line 118)
                    ALOAD_1     // Ljava/lang/Object; element
                    INVOKESTATIC org.springframework.util.ObjectUtils.nullSafeEquals (Ljava/lang/Object;Ljava/lang/Object;)Z
                    IFEQ L2
                    ICONST_1   (line 119)
                    IRETURN
                L2: IINC_3 1   (line 117)
                L3: ILOAD_3
                    ILOAD 4
                    IF_ICMPLT L1
                    ICONST_0   (line 122)
                    IRETURN
  end public static boolean containsElement(Object[], Object)

  public static boolean containsConstant(Enum[], String):
                    ALOAD_0     // [Ljava/lang/Enum; enumValues   (line 133)
                    ALOAD_1     // Ljava/lang/String; constant
                    ICONST_0
                    INVOKESTATIC org.springframework.util.ObjectUtils.containsConstant ([Ljava/lang/Enum;Ljava/lang/String;Z)Z
                    IRETURN
  end public static boolean containsConstant(Enum[], String)

  public static boolean containsConstant(Enum[], String, boolean):
                    ALOAD_0     // [Ljava/lang/Enum; enumValues   (line 144)
                    DUP
                    ASTORE 6
                    ARRAYLENGTH
                    ISTORE 5
                    ICONST_0
                    ISTORE 4
                    GOTO L4
                L0: ALOAD 6
                    ILOAD 4
                    AALOAD
                    ASTORE_3
                    ILOAD_2     // Z caseSensitive   (line 145)
                    IFEQ L1
                    ALOAD_3     // Ljava/lang/Enum; candidate   (line 146)
                    INVOKEVIRTUAL java.lang.Enum.toString ()Ljava/lang/String;
                    ALOAD_1     // Ljava/lang/String; constant
                    INVOKEVIRTUAL java.lang.String.equals (Ljava/lang/Object;)Z
                    IFEQ L3
                    GOTO L2
                L1: ALOAD_3     // Ljava/lang/Enum; candidate   (line 147)
                    INVOKEVIRTUAL java.lang.Enum.toString ()Ljava/lang/String;
                    ALOAD_1     // Ljava/lang/String; constant
                    INVOKEVIRTUAL java.lang.String.equalsIgnoreCase (Ljava/lang/String;)Z
                    IFEQ L3
                L2: ICONST_1   (line 148)
                    IRETURN
                L3: IINC 4 1   (line 144)
                L4: ILOAD 4
                    ILOAD 5
                    IF_ICMPLT L0
                    ICONST_0   (line 151)
                    IRETURN
  end public static boolean containsConstant(Enum[], String, boolean)

  public static Enum caseInsensitiveValueOf(Enum[], String):
                    ALOAD_0     // [Ljava/lang/Enum; enumValues   (line 163)
                    DUP
                    ASTORE 5
                    ARRAYLENGTH
                    ISTORE 4
                    ICONST_0
                    ISTORE_3
                    GOTO L2
                L0: ALOAD 5
                    ILOAD_3
                    AALOAD
                    ASTORE_2
                    ALOAD_2     // Ljava/lang/Enum; candidate   (line 164)
                    INVOKEVIRTUAL java.lang.Enum.toString ()Ljava/lang/String;
                    ALOAD_1     // Ljava/lang/String; constant
                    INVOKEVIRTUAL java.lang.String.equalsIgnoreCase (Ljava/lang/String;)Z
                    IFEQ L1
                    ALOAD_2     // Ljava/lang/Enum; candidate   (line 165)
                    ARETURN
                L1: IINC_3 1   (line 163)
                L2: ILOAD_3
                    ILOAD 4
                    IF_ICMPLT L0
                    NEW java.lang.IllegalArgumentException   (line 168)
                    DUP
                    LDC "constant [%s] does not exist in enum type %s"   (line 169)
                    ICONST_2
                    ANEWARRAY java.lang.Object
                    DUP
                    ICONST_0
                    ALOAD_1     // Ljava/lang/String; constant   (line 170)
                    AASTORE
                    DUP
                    ICONST_1
                    ALOAD_0     // [Ljava/lang/Enum; enumValues
                    INVOKEVIRTUAL java.lang.Object.getClass ()Ljava/lang/Class;
                    INVOKEVIRTUAL java.lang.Class.getComponentType ()Ljava/lang/Class;
                    INVOKEVIRTUAL java.lang.Class.getName ()Ljava/lang/String;
                    AASTORE   (line 169)
                    INVOKESTATIC java.lang.String.format (Ljava/lang/String;[Ljava/lang/Object;)Ljava/lang/String;
                    INVOKESPECIAL java.lang.IllegalArgumentException.<init> (Ljava/lang/String;)V   (line 168)
                    ATHROW
  end public static Enum caseInsensitiveValueOf(Enum[], String)

  public static Object[] addObjectToArray(Object[], Object):
                    LDC java.lang.Object   (line 181)
                    ASTORE_2
                    ALOAD_0     // [Ljava/lang/Object; array   (line 182)
                    IFNULL L0
                    ALOAD_0     // [Ljava/lang/Object; array   (line 183)
                    INVOKEVIRTUAL java.lang.Object.getClass ()Ljava/lang/Class;
                    INVOKEVIRTUAL java.lang.Class.getComponentType ()Ljava/lang/Class;
                    ASTORE_2     // Ljava/lang/Class; compType
                    GOTO L1
                L0: ALOAD_1     // Ljava/lang/Object; obj   (line 185)
                    IFNULL L1
                    ALOAD_1     // Ljava/lang/Object; obj   (line 186)
                    INVOKEVIRTUAL java.lang.Object.getClass ()Ljava/lang/Class;
                    ASTORE_2     // Ljava/lang/Class; compType
                L1: ALOAD_0     // [Ljava/lang/Object; array   (line 188)
                    IFNULL L2
                    ALOAD_0     // [Ljava/lang/Object; array
                    ARRAYLENGTH
                    ICONST_1
                    IADD
                    GOTO L3
                L2: ICONST_1
                L3: ISTORE_3
                    ALOAD_2     // Ljava/lang/Class; compType   (line 190)
                    ILOAD_3     // I newArrLength
                    INVOKESTATIC java.lang.reflect.Array.newInstance (Ljava/lang/Class;I)Ljava/lang/Object;
                    CHECKCAST [Ljava.lang.Object;
                    ASTORE 4
                    ALOAD_0     // [Ljava/lang/Object; array   (line 191)
                    IFNULL L4
                    ALOAD_0     // [Ljava/lang/Object; array   (line 192)
                    ICONST_0
                    ALOAD 4     // [Ljava/lang/Object; newArr
                    ICONST_0
                    ALOAD_0     // [Ljava/lang/Object; array
                    ARRAYLENGTH
                    INVOKESTATIC java.lang.System.arraycopy (Ljava/lang/Object;ILjava/lang/Object;II)V
                L4: ALOAD 4     // [Ljava/lang/Object; newArr   (line 194)
                    ALOAD 4     // [Ljava/lang/Object; newArr
                    ARRAYLENGTH
                    ICONST_1
                    ISUB
                    ALOAD_1     // Ljava/lang/Object; obj
                    AASTORE
                    ALOAD 4     // [Ljava/lang/Object; newArr   (line 195)
                    ARETURN
  end public static Object[] addObjectToArray(Object[], Object)

  public static Object[] toObjectArray(Object):
                    ALOAD_0     // Ljava/lang/Object; source   (line 208)
                    INSTANCEOF [Ljava.lang.Object;
                    IFEQ L0
                    ALOAD_0     // Ljava/lang/Object; source   (line 209)
                    CHECKCAST [Ljava.lang.Object;
                    ARETURN
                L0: ALOAD_0     // Ljava/lang/Object; source   (line 211)
                    IFNONNULL L1
                    ICONST_0   (line 212)
                    ANEWARRAY java.lang.Object
                    ARETURN
                L1: ALOAD_0     // Ljava/lang/Object; source   (line 214)
                    INVOKEVIRTUAL java.lang.Object.getClass ()Ljava/lang/Class;
                    INVOKEVIRTUAL java.lang.Class.isArray ()Z
                    IFNE L2
                    NEW java.lang.IllegalArgumentException   (line 215)
                    DUP
                    NEW java.lang.StringBuilder
                    DUP
                    LDC "Source is not an array: "
                    INVOKESPECIAL java.lang.StringBuilder.<init> (Ljava/lang/String;)V
                    ALOAD_0     // Ljava/lang/Object; source
                    INVOKEVIRTUAL java.lang.StringBuilder.append (Ljava/lang/Object;)Ljava/lang/StringBuilder;
                    INVOKEVIRTUAL java.lang.StringBuilder.toString ()Ljava/lang/String;
                    INVOKESPECIAL java.lang.IllegalArgumentException.<init> (Ljava/lang/String;)V
                    ATHROW
                L2: ALOAD_0     // Ljava/lang/Object; source   (line 217)
                    INVOKESTATIC java.lang.reflect.Array.getLength (Ljava/lang/Object;)I
                    ISTORE_1
                    ILOAD_1     // I length   (line 218)
                    IFNE L3
                    ICONST_0   (line 219)
                    ANEWARRAY java.lang.Object
                    ARETURN
                L3: ALOAD_0     // Ljava/lang/Object; source   (line 221)
                    ICONST_0
                    INVOKESTATIC java.lang.reflect.Array.get (Ljava/lang/Object;I)Ljava/lang/Object;
                    INVOKEVIRTUAL java.lang.Object.getClass ()Ljava/lang/Class;
                    ASTORE_2
                    ALOAD_2     // Ljava/lang/Class; wrapperType   (line 222)
                    ILOAD_1     // I length
                    INVOKESTATIC java.lang.reflect.Array.newInstance (Ljava/lang/Class;I)Ljava/lang/Object;
                    CHECKCAST [Ljava.lang.Object;
                    ASTORE_3
                    ICONST_0   (line 223)
                    ISTORE 4
                    GOTO L5
                L4: ALOAD_3     // [Ljava/lang/Object; newArray   (line 224)
                    ILOAD 4     // I i
                    ALOAD_0     // Ljava/lang/Object; source
                    ILOAD 4     // I i
                    INVOKESTATIC java.lang.reflect.Array.get (Ljava/lang/Object;I)Ljava/lang/Object;
                    AASTORE
                    IINC 4 1     // I i   (line 223)
                L5: ILOAD 4     // I i
                    ILOAD_1     // I length
                    IF_ICMPLT L4
                    ALOAD_3     // [Ljava/lang/Object; newArray   (line 226)
                    ARETURN
  end public static Object[] toObjectArray(Object)

  public static boolean nullSafeEquals(Object, Object):
                    ALOAD_0     // Ljava/lang/Object; o1   (line 246)
                    ALOAD_1     // Ljava/lang/Object; o2
                    IF_ACMPNE L0
                    ICONST_1   (line 247)
                    IRETURN
                L0: ALOAD_0     // Ljava/lang/Object; o1   (line 249)
                    IFNULL L1
                    ALOAD_1     // Ljava/lang/Object; o2
                    IFNONNULL L2
                L1: ICONST_0   (line 250)
                    IRETURN
                L2: ALOAD_0     // Ljava/lang/Object; o1   (line 252)
                    ALOAD_1     // Ljava/lang/Object; o2
                    INVOKEVIRTUAL java.lang.Object.equals (Ljava/lang/Object;)Z
                    IFEQ L3
                    ICONST_1   (line 253)
                    IRETURN
                L3: ALOAD_0     // Ljava/lang/Object; o1   (line 255)
                    INVOKEVIRTUAL java.lang.Object.getClass ()Ljava/lang/Class;
                    INVOKEVIRTUAL java.lang.Class.isArray ()Z
                    IFEQ L12
                    ALOAD_1     // Ljava/lang/Object; o2
                    INVOKEVIRTUAL java.lang.Object.getClass ()Ljava/lang/Class;
                    INVOKEVIRTUAL java.lang.Class.isArray ()Z
                    IFEQ L12
                    ALOAD_0     // Ljava/lang/Object; o1   (line 256)
                    INSTANCEOF [Ljava.lang.Object;
                    IFEQ L4
                    ALOAD_1     // Ljava/lang/Object; o2
                    INSTANCEOF [Ljava.lang.Object;
                    IFEQ L4
                    ALOAD_0     // Ljava/lang/Object; o1   (line 257)
                    CHECKCAST [Ljava.lang.Object;
                    ALOAD_1     // Ljava/lang/Object; o2
                    CHECKCAST [Ljava.lang.Object;
                    INVOKESTATIC java.util.Arrays.equals ([Ljava/lang/Object;[Ljava/lang/Object;)Z
                    IRETURN
                L4: ALOAD_0     // Ljava/lang/Object; o1   (line 259)
                    INSTANCEOF [Z
                    IFEQ L5
                    ALOAD_1     // Ljava/lang/Object; o2
                    INSTANCEOF [Z
                    IFEQ L5
                    ALOAD_0     // Ljava/lang/Object; o1   (line 260)
                    CHECKCAST [Z
                    ALOAD_1     // Ljava/lang/Object; o2
                    CHECKCAST [Z
                    INVOKESTATIC java.util.Arrays.equals ([Z[Z)Z
                    IRETURN
                L5: ALOAD_0     // Ljava/lang/Object; o1   (line 262)
                    INSTANCEOF [B
                    IFEQ L6
                    ALOAD_1     // Ljava/lang/Object; o2
                    INSTANCEOF [B
                    IFEQ L6
                    ALOAD_0     // Ljava/lang/Object; o1   (line 263)
                    CHECKCAST [B
                    ALOAD_1     // Ljava/lang/Object; o2
                    CHECKCAST [B
                    INVOKESTATIC java.util.Arrays.equals ([B[B)Z
                    IRETURN
                L6: ALOAD_0     // Ljava/lang/Object; o1   (line 265)
                    INSTANCEOF [C
                    IFEQ L7
                    ALOAD_1     // Ljava/lang/Object; o2
                    INSTANCEOF [C
                    IFEQ L7
                    ALOAD_0     // Ljava/lang/Object; o1   (line 266)
                    CHECKCAST [C
                    ALOAD_1     // Ljava/lang/Object; o2
                    CHECKCAST [C
                    INVOKESTATIC java.util.Arrays.equals ([C[C)Z
                    IRETURN
                L7: ALOAD_0     // Ljava/lang/Object; o1   (line 268)
                    INSTANCEOF [D
                    IFEQ L8
                    ALOAD_1     // Ljava/lang/Object; o2
                    INSTANCEOF [D
                    IFEQ L8
                    ALOAD_0     // Ljava/lang/Object; o1   (line 269)
                    CHECKCAST [D
                    ALOAD_1     // Ljava/lang/Object; o2
                    CHECKCAST [D
                    INVOKESTATIC java.util.Arrays.equals ([D[D)Z
                    IRETURN
                L8: ALOAD_0     // Ljava/lang/Object; o1   (line 271)
                    INSTANCEOF [F
                    IFEQ L9
                    ALOAD_1     // Ljava/lang/Object; o2
                    INSTANCEOF [F
                    IFEQ L9
                    ALOAD_0     // Ljava/lang/Object; o1   (line 272)
                    CHECKCAST [F
                    ALOAD_1     // Ljava/lang/Object; o2
                    CHECKCAST [F
                    INVOKESTATIC java.util.Arrays.equals ([F[F)Z
                    IRETURN
                L9: ALOAD_0     // Ljava/lang/Object; o1   (line 274)
                    INSTANCEOF [I
                    IFEQ L10
                    ALOAD_1     // Ljava/lang/Object; o2
                    INSTANCEOF [I
                    IFEQ L10
                    ALOAD_0     // Ljava/lang/Object; o1   (line 275)
                    CHECKCAST [I
                    ALOAD_1     // Ljava/lang/Object; o2
                    CHECKCAST [I
                    INVOKESTATIC java.util.Arrays.equals ([I[I)Z
                    IRETURN
               L10: ALOAD_0     // Ljava/lang/Object; o1   (line 277)
                    INSTANCEOF [J
                    IFEQ L11
                    ALOAD_1     // Ljava/lang/Object; o2
                    INSTANCEOF [J
                    IFEQ L11
                    ALOAD_0     // Ljava/lang/Object; o1   (line 278)
                    CHECKCAST [J
                    ALOAD_1     // Ljava/lang/Object; o2
                    CHECKCAST [J
                    INVOKESTATIC java.util.Arrays.equals ([J[J)Z
                    IRETURN
               L11: ALOAD_0     // Ljava/lang/Object; o1   (line 280)
                    INSTANCEOF [S
                    IFEQ L12
                    ALOAD_1     // Ljava/lang/Object; o2
                    INSTANCEOF [S
                    IFEQ L12
                    ALOAD_0     // Ljava/lang/Object; o1   (line 281)
                    CHECKCAST [S
                    ALOAD_1     // Ljava/lang/Object; o2
                    CHECKCAST [S
                    INVOKESTATIC java.util.Arrays.equals ([S[S)Z
                    IRETURN
               L12: ICONST_0   (line 284)
                    IRETURN
  end public static boolean nullSafeEquals(Object, Object)

  public static int nullSafeHashCode(Object):
                    ALOAD_0     // Ljava/lang/Object; obj   (line 304)
                    IFNONNULL L0
                    ICONST_0   (line 305)
                    IRETURN
                L0: ALOAD_0     // Ljava/lang/Object; obj   (line 307)
                    INVOKEVIRTUAL java.lang.Object.getClass ()Ljava/lang/Class;
                    INVOKEVIRTUAL java.lang.Class.isArray ()Z
                    IFEQ L9
                    ALOAD_0     // Ljava/lang/Object; obj   (line 308)
                    INSTANCEOF [Ljava.lang.Object;
                    IFEQ L1
                    ALOAD_0     // Ljava/lang/Object; obj   (line 309)
                    CHECKCAST [Ljava.lang.Object;
                    INVOKESTATIC org.springframework.util.ObjectUtils.nullSafeHashCode ([Ljava/lang/Object;)I
                    IRETURN
                L1: ALOAD_0     // Ljava/lang/Object; obj   (line 311)
                    INSTANCEOF [Z
                    IFEQ L2
                    ALOAD_0     // Ljava/lang/Object; obj   (line 312)
                    CHECKCAST [Z
                    INVOKESTATIC org.springframework.util.ObjectUtils.nullSafeHashCode ([Z)I
                    IRETURN
                L2: ALOAD_0     // Ljava/lang/Object; obj   (line 314)
                    INSTANCEOF [B
                    IFEQ L3
                    ALOAD_0     // Ljava/lang/Object; obj   (line 315)
                    CHECKCAST [B
                    INVOKESTATIC org.springframework.util.ObjectUtils.nullSafeHashCode ([B)I
                    IRETURN
                L3: ALOAD_0     // Ljava/lang/Object; obj   (line 317)
                    INSTANCEOF [C
                    IFEQ L4
                    ALOAD_0     // Ljava/lang/Object; obj   (line 318)
                    CHECKCAST [C
                    INVOKESTATIC org.springframework.util.ObjectUtils.nullSafeHashCode ([C)I
                    IRETURN
                L4: ALOAD_0     // Ljava/lang/Object; obj   (line 320)
                    INSTANCEOF [D
                    IFEQ L5
                    ALOAD_0     // Ljava/lang/Object; obj   (line 321)
                    CHECKCAST [D
                    INVOKESTATIC org.springframework.util.ObjectUtils.nullSafeHashCode ([D)I
                    IRETURN
                L5: ALOAD_0     // Ljava/lang/Object; obj   (line 323)
                    INSTANCEOF [F
                    IFEQ L6
                    ALOAD_0     // Ljava/lang/Object; obj   (line 324)
                    CHECKCAST [F
                    INVOKESTATIC org.springframework.util.ObjectUtils.nullSafeHashCode ([F)I
                    IRETURN
                L6: ALOAD_0     // Ljava/lang/Object; obj   (line 326)
                    INSTANCEOF [I
                    IFEQ L7
                    ALOAD_0     // Ljava/lang/Object; obj   (line 327)
                    CHECKCAST [I
                    INVOKESTATIC org.springframework.util.ObjectUtils.nullSafeHashCode ([I)I
                    IRETURN
                L7: ALOAD_0     // Ljava/lang/Object; obj   (line 329)
                    INSTANCEOF [J
                    IFEQ L8
                    ALOAD_0     // Ljava/lang/Object; obj   (line 330)
                    CHECKCAST [J
                    INVOKESTATIC org.springframework.util.ObjectUtils.nullSafeHashCode ([J)I
                    IRETURN
                L8: ALOAD_0     // Ljava/lang/Object; obj   (line 332)
                    INSTANCEOF [S
                    IFEQ L9
                    ALOAD_0     // Ljava/lang/Object; obj   (line 333)
                    CHECKCAST [S
                    INVOKESTATIC org.springframework.util.ObjectUtils.nullSafeHashCode ([S)I
                    IRETURN
                L9: ALOAD_0     // Ljava/lang/Object; obj   (line 336)
                    INVOKEVIRTUAL java.lang.Object.hashCode ()I
                    IRETURN
  end public static int nullSafeHashCode(Object)

  public static int nullSafeHashCode(Object[]):
                    ALOAD_0     // [Ljava/lang/Object; array   (line 344)
                    IFNONNULL L0
                    ICONST_0   (line 345)
                    IRETURN
                L0: BIPUSH 7   (line 347)
                    ISTORE_1
                    ALOAD_0     // [Ljava/lang/Object; array   (line 348)
                    ARRAYLENGTH
                    ISTORE_2
                    ICONST_0   (line 349)
                    ISTORE_3
                    GOTO L2
                L1: BIPUSH 31   (line 350)
                    ILOAD_1     // I hash
                    IMUL
                    ALOAD_0     // [Ljava/lang/Object; array
                    ILOAD_3     // I i
                    AALOAD
                    INVOKESTATIC org.springframework.util.ObjectUtils.nullSafeHashCode (Ljava/lang/Object;)I
                    IADD
                    ISTORE_1     // I hash
                    IINC_3 1     // I i   (line 349)
                L2: ILOAD_3     // I i
                    ILOAD_2     // I arraySize
                    IF_ICMPLT L1
                    ILOAD_1     // I hash   (line 352)
                    IRETURN
  end public static int nullSafeHashCode(Object[])

  public static int nullSafeHashCode(boolean[]):
                    ALOAD_0     // [Z array   (line 360)
                    IFNONNULL L0
                    ICONST_0   (line 361)
                    IRETURN
                L0: BIPUSH 7   (line 363)
                    ISTORE_1
                    ALOAD_0     // [Z array   (line 364)
                    ARRAYLENGTH
                    ISTORE_2
                    ICONST_0   (line 365)
                    ISTORE_3
                    GOTO L2
                L1: BIPUSH 31   (line 366)
                    ILOAD_1     // I hash
                    IMUL
                    ALOAD_0     // [Z array
                    ILOAD_3     // I i
                    BALOAD
                    INVOKESTATIC org.springframework.util.ObjectUtils.hashCode (Z)I
                    IADD
                    ISTORE_1     // I hash
                    IINC_3 1     // I i   (line 365)
                L2: ILOAD_3     // I i
                    ILOAD_2     // I arraySize
                    IF_ICMPLT L1
                    ILOAD_1     // I hash   (line 368)
                    IRETURN
  end public static int nullSafeHashCode(boolean[])

  public static int nullSafeHashCode(byte[]):
                    ALOAD_0     // [B array   (line 376)
                    IFNONNULL L0
                    ICONST_0   (line 377)
                    IRETURN
                L0: BIPUSH 7   (line 379)
                    ISTORE_1
                    ALOAD_0     // [B array   (line 380)
                    ARRAYLENGTH
                    ISTORE_2
                    ICONST_0   (line 381)
                    ISTORE_3
                    GOTO L2
                L1: BIPUSH 31   (line 382)
                    ILOAD_1     // I hash
                    IMUL
                    ALOAD_0     // [B array
                    ILOAD_3     // I i
                    BALOAD
                    IADD
                    ISTORE_1     // I hash
                    IINC_3 1     // I i   (line 381)
                L2: ILOAD_3     // I i
                    ILOAD_2     // I arraySize
                    IF_ICMPLT L1
                    ILOAD_1     // I hash   (line 384)
                    IRETURN
  end public static int nullSafeHashCode(byte[])

  public static int nullSafeHashCode(char[]):
                    ALOAD_0     // [C array   (line 392)
                    IFNONNULL L0
                    ICONST_0   (line 393)
                    IRETURN
                L0: BIPUSH 7   (line 395)
                    ISTORE_1
                    ALOAD_0     // [C array   (line 396)
                    ARRAYLENGTH
                    ISTORE_2
                    ICONST_0   (line 397)
                    ISTORE_3
                    GOTO L2
                L1: BIPUSH 31   (line 398)
                    ILOAD_1     // I hash
                    IMUL
                    ALOAD_0     // [C array
                    ILOAD_3     // I i
                    CALOAD
                    IADD
                    ISTORE_1     // I hash
                    IINC_3 1     // I i   (line 397)
                L2: ILOAD_3     // I i
                    ILOAD_2     // I arraySize
                    IF_ICMPLT L1
                    ILOAD_1     // I hash   (line 400)
                    IRETURN
  end public static int nullSafeHashCode(char[])

  public static int nullSafeHashCode(double[]):
                    ALOAD_0     // [D array   (line 408)
                    IFNONNULL L0
                    ICONST_0   (line 409)
                    IRETURN
                L0: BIPUSH 7   (line 411)
                    ISTORE_1
                    ALOAD_0     // [D array   (line 412)
                    ARRAYLENGTH
                    ISTORE_2
                    ICONST_0   (line 413)
                    ISTORE_3
                    GOTO L2
                L1: BIPUSH 31   (line 414)
                    ILOAD_1     // I hash
                    IMUL
                    ALOAD_0     // [D array
                    ILOAD_3     // I i
                    DALOAD
                    INVOKESTATIC org.springframework.util.ObjectUtils.hashCode (D)I
                    IADD
                    ISTORE_1     // I hash
                    IINC_3 1     // I i   (line 413)
                L2: ILOAD_3     // I i
                    ILOAD_2     // I arraySize
                    IF_ICMPLT L1
                    ILOAD_1     // I hash   (line 416)
                    IRETURN
  end public static int nullSafeHashCode(double[])

  public static int nullSafeHashCode(float[]):
                    ALOAD_0     // [F array   (line 424)
                    IFNONNULL L0
                    ICONST_0   (line 425)
                    IRETURN
                L0: BIPUSH 7   (line 427)
                    ISTORE_1
                    ALOAD_0     // [F array   (line 428)
                    ARRAYLENGTH
                    ISTORE_2
                    ICONST_0   (line 429)
                    ISTORE_3
                    GOTO L2
                L1: BIPUSH 31   (line 430)
                    ILOAD_1     // I hash
                    IMUL
                    ALOAD_0     // [F array
                    ILOAD_3     // I i
                    FALOAD
                    INVOKESTATIC org.springframework.util.ObjectUtils.hashCode (F)I
                    IADD
                    ISTORE_1     // I hash
                    IINC_3 1     // I i   (line 429)
                L2: ILOAD_3     // I i
                    ILOAD_2     // I arraySize
                    IF_ICMPLT L1
                    ILOAD_1     // I hash   (line 432)
                    IRETURN
  end public static int nullSafeHashCode(float[])

  public static int nullSafeHashCode(int[]):
                    ALOAD_0     // [I array   (line 440)
                    IFNONNULL L0
                    ICONST_0   (line 441)
                    IRETURN
                L0: BIPUSH 7   (line 443)
                    ISTORE_1
                    ALOAD_0     // [I array   (line 444)
                    ARRAYLENGTH
                    ISTORE_2
                    ICONST_0   (line 445)
                    ISTORE_3
                    GOTO L2
                L1: BIPUSH 31   (line 446)
                    ILOAD_1     // I hash
                    IMUL
                    ALOAD_0     // [I array
                    ILOAD_3     // I i
                    IALOAD
                    IADD
                    ISTORE_1     // I hash
                    IINC_3 1     // I i   (line 445)
                L2: ILOAD_3     // I i
                    ILOAD_2     // I arraySize
                    IF_ICMPLT L1
                    ILOAD_1     // I hash   (line 448)
                    IRETURN
  end public static int nullSafeHashCode(int[])

  public static int nullSafeHashCode(long[]):
                    ALOAD_0     // [J array   (line 456)
                    IFNONNULL L0
                    ICONST_0   (line 457)
                    IRETURN
                L0: BIPUSH 7   (line 459)
                    ISTORE_1
                    ALOAD_0     // [J array   (line 460)
                    ARRAYLENGTH
                    ISTORE_2
                    ICONST_0   (line 461)
                    ISTORE_3
                    GOTO L2
                L1: BIPUSH 31   (line 462)
                    ILOAD_1     // I hash
                    IMUL
                    ALOAD_0     // [J array
                    ILOAD_3     // I i
                    LALOAD
                    INVOKESTATIC org.springframework.util.ObjectUtils.hashCode (J)I
                    IADD
                    ISTORE_1     // I hash
                    IINC_3 1     // I i   (line 461)
                L2: ILOAD_3     // I i
                    ILOAD_2     // I arraySize
                    IF_ICMPLT L1
                    ILOAD_1     // I hash   (line 464)
                    IRETURN
  end public static int nullSafeHashCode(long[])

  public static int nullSafeHashCode(short[]):
                    ALOAD_0     // [S array   (line 472)
                    IFNONNULL L0
                    ICONST_0   (line 473)
                    IRETURN
                L0: BIPUSH 7   (line 475)
                    ISTORE_1
                    ALOAD_0     // [S array   (line 476)
                    ARRAYLENGTH
                    ISTORE_2
                    ICONST_0   (line 477)
                    ISTORE_3
                    GOTO L2
                L1: BIPUSH 31   (line 478)
                    ILOAD_1     // I hash
                    IMUL
                    ALOAD_0     // [S array
                    ILOAD_3     // I i
                    SALOAD
                    IADD
                    ISTORE_1     // I hash
                    IINC_3 1     // I i   (line 477)
                L2: ILOAD_3     // I i
                    ILOAD_2     // I arraySize
                    IF_ICMPLT L1
                    ILOAD_1     // I hash   (line 480)
                    IRETURN
  end public static int nullSafeHashCode(short[])

  public static int hashCode(boolean):
                    ILOAD_0     // Z bool   (line 488)
                    IFEQ L0
                    SIPUSH 1231
                    GOTO L1
                L0: SIPUSH 1237
                L1: IRETURN
  end public static int hashCode(boolean)

  public static int hashCode(double):
                    DLOAD_0     // D dbl   (line 496)
                    INVOKESTATIC java.lang.Double.doubleToLongBits (D)J
                    LSTORE_2
                    LLOAD_2     // J bits   (line 497)
                    INVOKESTATIC org.springframework.util.ObjectUtils.hashCode (J)I
                    IRETURN
  end public static int hashCode(double)

  public static int hashCode(float):
                    FLOAD_0     // F flt   (line 505)
                    INVOKESTATIC java.lang.Float.floatToIntBits (F)I
                    IRETURN
  end public static int hashCode(float)

  public static int hashCode(long):
                    LLOAD_0     // J lng   (line 513)
                    LLOAD_0     // J lng
                    BIPUSH 32
                    LUSHR
                    LXOR
                    L2I
                    IRETURN
  end public static int hashCode(long)

  public static String identityToString(Object):
                    ALOAD_0     // Ljava/lang/Object; obj   (line 528)
                    IFNONNULL L0
                    LDC ""   (line 529)
                    ARETURN
                L0: NEW java.lang.StringBuilder   (line 531)
                    DUP
                    ALOAD_0     // Ljava/lang/Object; obj
                    INVOKEVIRTUAL java.lang.Object.getClass ()Ljava/lang/Class;
                    INVOKEVIRTUAL java.lang.Class.getName ()Ljava/lang/String;
                    INVOKESTATIC java.lang.String.valueOf (Ljava/lang/Object;)Ljava/lang/String;
                    INVOKESPECIAL java.lang.StringBuilder.<init> (Ljava/lang/String;)V
                    LDC_W "@"
                    INVOKEVIRTUAL java.lang.StringBuilder.append (Ljava/lang/String;)Ljava/lang/StringBuilder;
                    ALOAD_0     // Ljava/lang/Object; obj
                    INVOKESTATIC org.springframework.util.ObjectUtils.getIdentityHexString (Ljava/lang/Object;)Ljava/lang/String;
                    INVOKEVIRTUAL java.lang.StringBuilder.append (Ljava/lang/String;)Ljava/lang/StringBuilder;
                    INVOKEVIRTUAL java.lang.StringBuilder.toString ()Ljava/lang/String;
                    ARETURN
  end public static String identityToString(Object)

  public static String getIdentityHexString(Object):
                    ALOAD_0     // Ljava/lang/Object; obj   (line 540)
                    INVOKESTATIC java.lang.System.identityHashCode (Ljava/lang/Object;)I
                    INVOKESTATIC java.lang.Integer.toHexString (I)Ljava/lang/String;
                    ARETURN
  end public static String getIdentityHexString(Object)

  public static String getDisplayString(Object):
                    ALOAD_0     // Ljava/lang/Object; obj   (line 553)
                    IFNONNULL L0
                    LDC ""   (line 554)
                    ARETURN
                L0: ALOAD_0     // Ljava/lang/Object; obj   (line 556)
                    INVOKESTATIC org.springframework.util.ObjectUtils.nullSafeToString (Ljava/lang/Object;)Ljava/lang/String;
                    ARETURN
  end public static String getDisplayString(Object)

  public static String nullSafeClassName(Object):
                    ALOAD_0     // Ljava/lang/Object; obj   (line 566)
                    IFNULL L0
                    ALOAD_0     // Ljava/lang/Object; obj
                    INVOKEVIRTUAL java.lang.Object.getClass ()Ljava/lang/Class;
                    INVOKEVIRTUAL java.lang.Class.getName ()Ljava/lang/String;
                    GOTO L1
                L0: LDC "null"
                L1: ARETURN
  end public static String nullSafeClassName(Object)

  public static String nullSafeToString(Object):
                    ALOAD_0     // Ljava/lang/Object; obj   (line 577)
                    IFNONNULL L0
                    LDC "null"   (line 578)
                    ARETURN
                L0: ALOAD_0     // Ljava/lang/Object; obj   (line 580)
                    INSTANCEOF java.lang.String
                    IFEQ L1
                    ALOAD_0     // Ljava/lang/Object; obj   (line 581)
                    CHECKCAST java.lang.String
                    ARETURN
                L1: ALOAD_0     // Ljava/lang/Object; obj   (line 583)
                    INSTANCEOF [Ljava.lang.Object;
                    IFEQ L2
                    ALOAD_0     // Ljava/lang/Object; obj   (line 584)
                    CHECKCAST [Ljava.lang.Object;
                    INVOKESTATIC org.springframework.util.ObjectUtils.nullSafeToString ([Ljava/lang/Object;)Ljava/lang/String;
                    ARETURN
                L2: ALOAD_0     // Ljava/lang/Object; obj   (line 586)
                    INSTANCEOF [Z
                    IFEQ L3
                    ALOAD_0     // Ljava/lang/Object; obj   (line 587)
                    CHECKCAST [Z
                    INVOKESTATIC org.springframework.util.ObjectUtils.nullSafeToString ([Z)Ljava/lang/String;
                    ARETURN
                L3: ALOAD_0     // Ljava/lang/Object; obj   (line 589)
                    INSTANCEOF [B
                    IFEQ L4
                    ALOAD_0     // Ljava/lang/Object; obj   (line 590)
                    CHECKCAST [B
                    INVOKESTATIC org.springframework.util.ObjectUtils.nullSafeToString ([B)Ljava/lang/String;
                    ARETURN
                L4: ALOAD_0     // Ljava/lang/Object; obj   (line 592)
                    INSTANCEOF [C
                    IFEQ L5
                    ALOAD_0     // Ljava/lang/Object; obj   (line 593)
                    CHECKCAST [C
                    INVOKESTATIC org.springframework.util.ObjectUtils.nullSafeToString ([C)Ljava/lang/String;
                    ARETURN
                L5: ALOAD_0     // Ljava/lang/Object; obj   (line 595)
                    INSTANCEOF [D
                    IFEQ L6
                    ALOAD_0     // Ljava/lang/Object; obj   (line 596)
                    CHECKCAST [D
                    INVOKESTATIC org.springframework.util.ObjectUtils.nullSafeToString ([D)Ljava/lang/String;
                    ARETURN
                L6: ALOAD_0     // Ljava/lang/Object; obj   (line 598)
                    INSTANCEOF [F
                    IFEQ L7
                    ALOAD_0     // Ljava/lang/Object; obj   (line 599)
                    CHECKCAST [F
                    INVOKESTATIC org.springframework.util.ObjectUtils.nullSafeToString ([F)Ljava/lang/String;
                    ARETURN
                L7: ALOAD_0     // Ljava/lang/Object; obj   (line 601)
                    INSTANCEOF [I
                    IFEQ L8
                    ALOAD_0     // Ljava/lang/Object; obj   (line 602)
                    CHECKCAST [I
                    INVOKESTATIC org.springframework.util.ObjectUtils.nullSafeToString ([I)Ljava/lang/String;
                    ARETURN
                L8: ALOAD_0     // Ljava/lang/Object; obj   (line 604)
                    INSTANCEOF [J
                    IFEQ L9
                    ALOAD_0     // Ljava/lang/Object; obj   (line 605)
                    CHECKCAST [J
                    INVOKESTATIC org.springframework.util.ObjectUtils.nullSafeToString ([J)Ljava/lang/String;
                    ARETURN
                L9: ALOAD_0     // Ljava/lang/Object; obj   (line 607)
                    INSTANCEOF [S
                    IFEQ L10
                    ALOAD_0     // Ljava/lang/Object; obj   (line 608)
                    CHECKCAST [S
                    INVOKESTATIC org.springframework.util.ObjectUtils.nullSafeToString ([S)Ljava/lang/String;
                    ARETURN
               L10: ALOAD_0     // Ljava/lang/Object; obj   (line 610)
                    INVOKEVIRTUAL java.lang.Object.toString ()Ljava/lang/String;
                    ASTORE_1
                    ALOAD_1     // Ljava/lang/String; str   (line 611)
                    IFNULL L11
                    ALOAD_1     // Ljava/lang/String; str
                    GOTO L12
               L11: LDC ""
               L12: ARETURN
  end public static String nullSafeToString(Object)

  public static String nullSafeToString(Object[]):
                    ALOAD_0     // [Ljava/lang/Object; array   (line 624)
                    IFNONNULL L0
                    LDC "null"   (line 625)
                    ARETURN
                L0: ALOAD_0     // [Ljava/lang/Object; array   (line 627)
                    ARRAYLENGTH
                    ISTORE_1
                    ILOAD_1     // I length   (line 628)
                    IFNE L1
                    LDC "{}"   (line 629)
                    ARETURN
                L1: NEW java.lang.StringBuilder   (line 631)
                    DUP
                    INVOKESPECIAL java.lang.StringBuilder.<init> ()V
                    ASTORE_2
                    ICONST_0   (line 632)
                    ISTORE_3
                    GOTO L5
                L2: ILOAD_3     // I i   (line 633)
                    IFNE L3
                    ALOAD_2     // Ljava/lang/StringBuilder; sb   (line 634)
                    LDC "{"
                    INVOKEVIRTUAL java.lang.StringBuilder.append (Ljava/lang/String;)Ljava/lang/StringBuilder;
                    POP
                    GOTO L4
                L3: ALOAD_2     // Ljava/lang/StringBuilder; sb   (line 637)
                    LDC ", "
                    INVOKEVIRTUAL java.lang.StringBuilder.append (Ljava/lang/String;)Ljava/lang/StringBuilder;
                    POP
                L4: ALOAD_2     // Ljava/lang/StringBuilder; sb   (line 639)
                    ALOAD_0     // [Ljava/lang/Object; array
                    ILOAD_3     // I i
                    AALOAD
                    INVOKESTATIC java.lang.String.valueOf (Ljava/lang/Object;)Ljava/lang/String;
                    INVOKEVIRTUAL java.lang.StringBuilder.append (Ljava/lang/String;)Ljava/lang/StringBuilder;
                    POP
                    IINC_3 1     // I i   (line 632)
                L5: ILOAD_3     // I i
                    ILOAD_1     // I length
                    IF_ICMPLT L2
                    ALOAD_2     // Ljava/lang/StringBuilder; sb   (line 641)
                    LDC "}"
                    INVOKEVIRTUAL java.lang.StringBuilder.append (Ljava/lang/String;)Ljava/lang/StringBuilder;
                    POP
                    ALOAD_2     // Ljava/lang/StringBuilder; sb   (line 642)
                    INVOKEVIRTUAL java.lang.StringBuilder.toString ()Ljava/lang/String;
                    ARETURN
  end public static String nullSafeToString(Object[])

  public static String nullSafeToString(boolean[]):
                    ALOAD_0     // [Z array   (line 655)
                    IFNONNULL L0
                    LDC "null"   (line 656)
                    ARETURN
                L0: ALOAD_0     // [Z array   (line 658)
                    ARRAYLENGTH
                    ISTORE_1
                    ILOAD_1     // I length   (line 659)
                    IFNE L1
                    LDC "{}"   (line 660)
                    ARETURN
                L1: NEW java.lang.StringBuilder   (line 662)
                    DUP
                    INVOKESPECIAL java.lang.StringBuilder.<init> ()V
                    ASTORE_2
                    ICONST_0   (line 663)
                    ISTORE_3
                    GOTO L5
                L2: ILOAD_3     // I i   (line 664)
                    IFNE L3
                    ALOAD_2     // Ljava/lang/StringBuilder; sb   (line 665)
                    LDC "{"
                    INVOKEVIRTUAL java.lang.StringBuilder.append (Ljava/lang/String;)Ljava/lang/StringBuilder;
                    POP
                    GOTO L4
                L3: ALOAD_2     // Ljava/lang/StringBuilder; sb   (line 668)
                    LDC ", "
                    INVOKEVIRTUAL java.lang.StringBuilder.append (Ljava/lang/String;)Ljava/lang/StringBuilder;
                    POP
                L4: ALOAD_2     // Ljava/lang/StringBuilder; sb   (line 671)
                    ALOAD_0     // [Z array
                    ILOAD_3     // I i
                    BALOAD
                    INVOKEVIRTUAL java.lang.StringBuilder.append (Z)Ljava/lang/StringBuilder;
                    POP
                    IINC_3 1     // I i   (line 663)
                L5: ILOAD_3     // I i
                    ILOAD_1     // I length
                    IF_ICMPLT L2
                    ALOAD_2     // Ljava/lang/StringBuilder; sb   (line 673)
                    LDC "}"
                    INVOKEVIRTUAL java.lang.StringBuilder.append (Ljava/lang/String;)Ljava/lang/StringBuilder;
                    POP
                    ALOAD_2     // Ljava/lang/StringBuilder; sb   (line 674)
                    INVOKEVIRTUAL java.lang.StringBuilder.toString ()Ljava/lang/String;
                    ARETURN
  end public static String nullSafeToString(boolean[])

  public static String nullSafeToString(byte[]):
                    ALOAD_0     // [B array   (line 687)
                    IFNONNULL L0
                    LDC "null"   (line 688)
                    ARETURN
                L0: ALOAD_0     // [B array   (line 690)
                    ARRAYLENGTH
                    ISTORE_1
                    ILOAD_1     // I length   (line 691)
                    IFNE L1
                    LDC "{}"   (line 692)
                    ARETURN
                L1: NEW java.lang.StringBuilder   (line 694)
                    DUP
                    INVOKESPECIAL java.lang.StringBuilder.<init> ()V
                    ASTORE_2
                    ICONST_0   (line 695)
                    ISTORE_3
                    GOTO L5
                L2: ILOAD_3     // I i   (line 696)
                    IFNE L3
                    ALOAD_2     // Ljava/lang/StringBuilder; sb   (line 697)
                    LDC "{"
                    INVOKEVIRTUAL java.lang.StringBuilder.append (Ljava/lang/String;)Ljava/lang/StringBuilder;
                    POP
                    GOTO L4
                L3: ALOAD_2     // Ljava/lang/StringBuilder; sb   (line 700)
                    LDC ", "
                    INVOKEVIRTUAL java.lang.StringBuilder.append (Ljava/lang/String;)Ljava/lang/StringBuilder;
                    POP
                L4: ALOAD_2     // Ljava/lang/StringBuilder; sb   (line 702)
                    ALOAD_0     // [B array
                    ILOAD_3     // I i
                    BALOAD
                    INVOKEVIRTUAL java.lang.StringBuilder.append (I)Ljava/lang/StringBuilder;
                    POP
                    IINC_3 1     // I i   (line 695)
                L5: ILOAD_3     // I i
                    ILOAD_1     // I length
                    IF_ICMPLT L2
                    ALOAD_2     // Ljava/lang/StringBuilder; sb   (line 704)
                    LDC "}"
                    INVOKEVIRTUAL java.lang.StringBuilder.append (Ljava/lang/String;)Ljava/lang/StringBuilder;
                    POP
                    ALOAD_2     // Ljava/lang/StringBuilder; sb   (line 705)
                    INVOKEVIRTUAL java.lang.StringBuilder.toString ()Ljava/lang/String;
                    ARETURN
  end public static String nullSafeToString(byte[])

  public static String nullSafeToString(char[]):
                    ALOAD_0     // [C array   (line 718)
                    IFNONNULL L0
                    LDC "null"   (line 719)
                    ARETURN
                L0: ALOAD_0     // [C array   (line 721)
                    ARRAYLENGTH
                    ISTORE_1
                    ILOAD_1     // I length   (line 722)
                    IFNE L1
                    LDC "{}"   (line 723)
                    ARETURN
                L1: NEW java.lang.StringBuilder   (line 725)
                    DUP
                    INVOKESPECIAL java.lang.StringBuilder.<init> ()V
                    ASTORE_2
                    ICONST_0   (line 726)
                    ISTORE_3
                    GOTO L5
                L2: ILOAD_3     // I i   (line 727)
                    IFNE L3
                    ALOAD_2     // Ljava/lang/StringBuilder; sb   (line 728)
                    LDC "{"
                    INVOKEVIRTUAL java.lang.StringBuilder.append (Ljava/lang/String;)Ljava/lang/StringBuilder;
                    POP
                    GOTO L4
                L3: ALOAD_2     // Ljava/lang/StringBuilder; sb   (line 731)
                    LDC ", "
                    INVOKEVIRTUAL java.lang.StringBuilder.append (Ljava/lang/String;)Ljava/lang/StringBuilder;
                    POP
                L4: ALOAD_2     // Ljava/lang/StringBuilder; sb   (line 733)
                    LDC_W "'"
                    INVOKEVIRTUAL java.lang.StringBuilder.append (Ljava/lang/String;)Ljava/lang/StringBuilder;
                    ALOAD_0     // [C array
                    ILOAD_3     // I i
                    CALOAD
                    INVOKEVIRTUAL java.lang.StringBuilder.append (C)Ljava/lang/StringBuilder;
                    LDC_W "'"
                    INVOKEVIRTUAL java.lang.StringBuilder.append (Ljava/lang/String;)Ljava/lang/StringBuilder;
                    POP
                    IINC_3 1     // I i   (line 726)
                L5: ILOAD_3     // I i
                    ILOAD_1     // I length
                    IF_ICMPLT L2
                    ALOAD_2     // Ljava/lang/StringBuilder; sb   (line 735)
                    LDC "}"
                    INVOKEVIRTUAL java.lang.StringBuilder.append (Ljava/lang/String;)Ljava/lang/StringBuilder;
                    POP
                    ALOAD_2     // Ljava/lang/StringBuilder; sb   (line 736)
                    INVOKEVIRTUAL java.lang.StringBuilder.toString ()Ljava/lang/String;
                    ARETURN
  end public static String nullSafeToString(char[])

  public static String nullSafeToString(double[]):
                    ALOAD_0     // [D array   (line 749)
                    IFNONNULL L0
                    LDC "null"   (line 750)
                    ARETURN
                L0: ALOAD_0     // [D array   (line 752)
                    ARRAYLENGTH
                    ISTORE_1
                    ILOAD_1     // I length   (line 753)
                    IFNE L1
                    LDC "{}"   (line 754)
                    ARETURN
                L1: NEW java.lang.StringBuilder   (line 756)
                    DUP
                    INVOKESPECIAL java.lang.StringBuilder.<init> ()V
                    ASTORE_2
                    ICONST_0   (line 757)
                    ISTORE_3
                    GOTO L5
                L2: ILOAD_3     // I i   (line 758)
                    IFNE L3
                    ALOAD_2     // Ljava/lang/StringBuilder; sb   (line 759)
                    LDC "{"
                    INVOKEVIRTUAL java.lang.StringBuilder.append (Ljava/lang/String;)Ljava/lang/StringBuilder;
                    POP
                    GOTO L4
                L3: ALOAD_2     // Ljava/lang/StringBuilder; sb   (line 762)
                    LDC ", "
                    INVOKEVIRTUAL java.lang.StringBuilder.append (Ljava/lang/String;)Ljava/lang/StringBuilder;
                    POP
                L4: ALOAD_2     // Ljava/lang/StringBuilder; sb   (line 765)
                    ALOAD_0     // [D array
                    ILOAD_3     // I i
                    DALOAD
                    INVOKEVIRTUAL java.lang.StringBuilder.append (D)Ljava/lang/StringBuilder;
                    POP
                    IINC_3 1     // I i   (line 757)
                L5: ILOAD_3     // I i
                    ILOAD_1     // I length
                    IF_ICMPLT L2
                    ALOAD_2     // Ljava/lang/StringBuilder; sb   (line 767)
                    LDC "}"
                    INVOKEVIRTUAL java.lang.StringBuilder.append (Ljava/lang/String;)Ljava/lang/StringBuilder;
                    POP
                    ALOAD_2     // Ljava/lang/StringBuilder; sb   (line 768)
                    INVOKEVIRTUAL java.lang.StringBuilder.toString ()Ljava/lang/String;
                    ARETURN
  end public static String nullSafeToString(double[])

  public static String nullSafeToString(float[]):
                    ALOAD_0     // [F array   (line 781)
                    IFNONNULL L0
                    LDC "null"   (line 782)
                    ARETURN
                L0: ALOAD_0     // [F array   (line 784)
                    ARRAYLENGTH
                    ISTORE_1
                    ILOAD_1     // I length   (line 785)
                    IFNE L1
                    LDC "{}"   (line 786)
                    ARETURN
                L1: NEW java.lang.StringBuilder   (line 788)
                    DUP
                    INVOKESPECIAL java.lang.StringBuilder.<init> ()V
                    ASTORE_2
                    ICONST_0   (line 789)
                    ISTORE_3
                    GOTO L5
                L2: ILOAD_3     // I i   (line 790)
                    IFNE L3
                    ALOAD_2     // Ljava/lang/StringBuilder; sb   (line 791)
                    LDC "{"
                    INVOKEVIRTUAL java.lang.StringBuilder.append (Ljava/lang/String;)Ljava/lang/StringBuilder;
                    POP
                    GOTO L4
                L3: ALOAD_2     // Ljava/lang/StringBuilder; sb   (line 794)
                    LDC ", "
                    INVOKEVIRTUAL java.lang.StringBuilder.append (Ljava/lang/String;)Ljava/lang/StringBuilder;
                    POP
                L4: ALOAD_2     // Ljava/lang/StringBuilder; sb   (line 797)
                    ALOAD_0     // [F array
                    ILOAD_3     // I i
                    FALOAD
                    INVOKEVIRTUAL java.lang.StringBuilder.append (F)Ljava/lang/StringBuilder;
                    POP
                    IINC_3 1     // I i   (line 789)
                L5: ILOAD_3     // I i
                    ILOAD_1     // I length
                    IF_ICMPLT L2
                    ALOAD_2     // Ljava/lang/StringBuilder; sb   (line 799)
                    LDC "}"
                    INVOKEVIRTUAL java.lang.StringBuilder.append (Ljava/lang/String;)Ljava/lang/StringBuilder;
                    POP
                    ALOAD_2     // Ljava/lang/StringBuilder; sb   (line 800)
                    INVOKEVIRTUAL java.lang.StringBuilder.toString ()Ljava/lang/String;
                    ARETURN
  end public static String nullSafeToString(float[])

  public static String nullSafeToString(int[]):
                    ALOAD_0     // [I array   (line 813)
                    IFNONNULL L0
                    LDC "null"   (line 814)
                    ARETURN
                L0: ALOAD_0     // [I array   (line 816)
                    ARRAYLENGTH
                    ISTORE_1
                    ILOAD_1     // I length   (line 817)
                    IFNE L1
                    LDC "{}"   (line 818)
                    ARETURN
                L1: NEW java.lang.StringBuilder   (line 820)
                    DUP
                    INVOKESPECIAL java.lang.StringBuilder.<init> ()V
                    ASTORE_2
                    ICONST_0   (line 821)
                    ISTORE_3
                    GOTO L5
                L2: ILOAD_3     // I i   (line 822)
                    IFNE L3
                    ALOAD_2     // Ljava/lang/StringBuilder; sb   (line 823)
                    LDC "{"
                    INVOKEVIRTUAL java.lang.StringBuilder.append (Ljava/lang/String;)Ljava/lang/StringBuilder;
                    POP
                    GOTO L4
                L3: ALOAD_2     // Ljava/lang/StringBuilder; sb   (line 826)
                    LDC ", "
                    INVOKEVIRTUAL java.lang.StringBuilder.append (Ljava/lang/String;)Ljava/lang/StringBuilder;
                    POP
                L4: ALOAD_2     // Ljava/lang/StringBuilder; sb   (line 828)
                    ALOAD_0     // [I array
                    ILOAD_3     // I i
                    IALOAD
                    INVOKEVIRTUAL java.lang.StringBuilder.append (I)Ljava/lang/StringBuilder;
                    POP
                    IINC_3 1     // I i   (line 821)
                L5: ILOAD_3     // I i
                    ILOAD_1     // I length
                    IF_ICMPLT L2
                    ALOAD_2     // Ljava/lang/StringBuilder; sb   (line 830)
                    LDC "}"
                    INVOKEVIRTUAL java.lang.StringBuilder.append (Ljava/lang/String;)Ljava/lang/StringBuilder;
                    POP
                    ALOAD_2     // Ljava/lang/StringBuilder; sb   (line 831)
                    INVOKEVIRTUAL java.lang.StringBuilder.toString ()Ljava/lang/String;
                    ARETURN
  end public static String nullSafeToString(int[])

  public static String nullSafeToString(long[]):
                    ALOAD_0     // [J array   (line 844)
                    IFNONNULL L0
                    LDC "null"   (line 845)
                    ARETURN
                L0: ALOAD_0     // [J array   (line 847)
                    ARRAYLENGTH
                    ISTORE_1
                    ILOAD_1     // I length   (line 848)
                    IFNE L1
                    LDC "{}"   (line 849)
                    ARETURN
                L1: NEW java.lang.StringBuilder   (line 851)
                    DUP
                    INVOKESPECIAL java.lang.StringBuilder.<init> ()V
                    ASTORE_2
                    ICONST_0   (line 852)
                    ISTORE_3
                    GOTO L5
                L2: ILOAD_3     // I i   (line 853)
                    IFNE L3
                    ALOAD_2     // Ljava/lang/StringBuilder; sb   (line 854)
                    LDC "{"
                    INVOKEVIRTUAL java.lang.StringBuilder.append (Ljava/lang/String;)Ljava/lang/StringBuilder;
                    POP
                    GOTO L4
                L3: ALOAD_2     // Ljava/lang/StringBuilder; sb   (line 857)
                    LDC ", "
                    INVOKEVIRTUAL java.lang.StringBuilder.append (Ljava/lang/String;)Ljava/lang/StringBuilder;
                    POP
                L4: ALOAD_2     // Ljava/lang/StringBuilder; sb   (line 859)
                    ALOAD_0     // [J array
                    ILOAD_3     // I i
                    LALOAD
                    INVOKEVIRTUAL java.lang.StringBuilder.append (J)Ljava/lang/StringBuilder;
                    POP
                    IINC_3 1     // I i   (line 852)
                L5: ILOAD_3     // I i
                    ILOAD_1     // I length
                    IF_ICMPLT L2
                    ALOAD_2     // Ljava/lang/StringBuilder; sb   (line 861)
                    LDC "}"
                    INVOKEVIRTUAL java.lang.StringBuilder.append (Ljava/lang/String;)Ljava/lang/StringBuilder;
                    POP
                    ALOAD_2     // Ljava/lang/StringBuilder; sb   (line 862)
                    INVOKEVIRTUAL java.lang.StringBuilder.toString ()Ljava/lang/String;
                    ARETURN
  end public static String nullSafeToString(long[])

  public static String nullSafeToString(short[]):
                    ALOAD_0     // [S array   (line 875)
                    IFNONNULL L0
                    LDC "null"   (line 876)
                    ARETURN
                L0: ALOAD_0     // [S array   (line 878)
                    ARRAYLENGTH
                    ISTORE_1
                    ILOAD_1     // I length   (line 879)
                    IFNE L1
                    LDC "{}"   (line 880)
                    ARETURN
                L1: NEW java.lang.StringBuilder   (line 882)
                    DUP
                    INVOKESPECIAL java.lang.StringBuilder.<init> ()V
                    ASTORE_2
                    ICONST_0   (line 883)
                    ISTORE_3
                    GOTO L5
                L2: ILOAD_3     // I i   (line 884)
                    IFNE L3
                    ALOAD_2     // Ljava/lang/StringBuilder; sb   (line 885)
                    LDC "{"
                    INVOKEVIRTUAL java.lang.StringBuilder.append (Ljava/lang/String;)Ljava/lang/StringBuilder;
                    POP
                    GOTO L4
                L3: ALOAD_2     // Ljava/lang/StringBuilder; sb   (line 888)
                    LDC ", "
                    INVOKEVIRTUAL java.lang.StringBuilder.append (Ljava/lang/String;)Ljava/lang/StringBuilder;
                    POP
                L4: ALOAD_2     // Ljava/lang/StringBuilder; sb   (line 890)
                    ALOAD_0     // [S array
                    ILOAD_3     // I i
                    SALOAD
                    INVOKEVIRTUAL java.lang.StringBuilder.append (I)Ljava/lang/StringBuilder;
                    POP
                    IINC_3 1     // I i   (line 883)
                L5: ILOAD_3     // I i
                    ILOAD_1     // I length
                    IF_ICMPLT L2
                    ALOAD_2     // Ljava/lang/StringBuilder; sb   (line 892)
                    LDC "}"
                    INVOKEVIRTUAL java.lang.StringBuilder.append (Ljava/lang/String;)Ljava/lang/StringBuilder;
                    POP
                    ALOAD_2     // Ljava/lang/StringBuilder; sb   (line 893)
                    INVOKEVIRTUAL java.lang.StringBuilder.toString ()Ljava/lang/String;
                    ARETURN
  end public static String nullSafeToString(short[])

end public abstract class org.springframework.util.ObjectUtils
 -- (NullPointerException) null
null
java.lang.NullPointerException
	at org.aspectj.weaver.UnresolvedType.forSignature(UnresolvedType.java:387)
	at org.aspectj.weaver.bcel.BcelObjectType.getDeclaredInterfaces(BcelObjectType.java:245)
	at org.aspectj.weaver.ReferenceType.getDeclaredInterfaces(ReferenceType.java:484)
	at org.aspectj.weaver.ResolvedType.getDirectSupertypes(ResolvedType.java:70)
	at org.aspectj.weaver.patterns.TypePattern.matchesSubtypes(TypePattern.java:165)
	at org.aspectj.weaver.patterns.TypePattern.matchesStatically(TypePattern.java:119)
	at org.aspectj.weaver.patterns.OrTypePattern.matchesStatically(OrTypePattern.java:74)
	at org.aspectj.weaver.patterns.SignaturePattern.matchesExactlyMethod(SignaturePattern.java:391)
	at org.aspectj.weaver.patterns.SignaturePattern.matchesExactly(SignaturePattern.java:336)
	at org.aspectj.weaver.patterns.SignaturePattern.matches(SignaturePattern.java:300)
	at org.aspectj.weaver.patterns.KindedPointcut.matchInternal(KindedPointcut.java:106)
	at org.aspectj.weaver.patterns.Pointcut.match(Pointcut.java:146)
	at org.aspectj.weaver.patterns.AndPointcut.matchInternal(AndPointcut.java:52)
	at org.aspectj.weaver.patterns.Pointcut.match(Pointcut.java:146)
	at org.aspectj.weaver.patterns.OrPointcut.matchInternal(OrPointcut.java:51)
	at org.aspectj.weaver.patterns.Pointcut.match(Pointcut.java:146)
	at org.aspectj.weaver.ShadowMunger.match(ShadowMunger.java:70)
	at org.aspectj.weaver.Advice.match(Advice.java:106)
	at org.aspectj.weaver.bcel.BcelAdvice.match(BcelAdvice.java:140)
	at org.aspectj.weaver.bcel.BcelClassWeaver.match(BcelClassWeaver.java:2980)
	at org.aspectj.weaver.bcel.BcelClassWeaver.match(BcelClassWeaver.java:2489)
	at org.aspectj.weaver.bcel.BcelClassWeaver.weave(BcelClassWeaver.java:486)
	at org.aspectj.weaver.bcel.BcelClassWeaver.weave(BcelClassWeaver.java:98)
	at org.aspectj.weaver.bcel.BcelWeaver.weave(BcelWeaver.java:1733)
	at org.aspectj.weaver.bcel.BcelWeaver.weaveWithoutDump(BcelWeaver.java:1694)
	at org.aspectj.weaver.bcel.BcelWeaver.weaveAndNotify(BcelWeaver.java:1464)
	at org.aspectj.weaver.bcel.BcelWeaver.weave(BcelWeaver.java:1273)
	at org.aspectj.weaver.tools.WeavingAdaptor.getWovenBytes(WeavingAdaptor.java:394)
	at org.aspectj.weaver.tools.WeavingAdaptor.weaveClass(WeavingAdaptor.java:281)
	at org.aspectj.weaver.loadtime.Aj.preProcess(Aj.java:95)
	at org.aspectj.weaver.loadtime.ClassPreProcessorAgentAdapter.transform(ClassPreProcessorAgentAdapter.java:52)
	at sun.instrument.TransformerManager.transform(TransformerManager.java:188)
	at sun.instrument.InstrumentationImpl.transform(InstrumentationImpl.java:428)
	at java.lang.ClassLoader.defineClass1(Native Method)
	at java.lang.ClassLoader.defineClass(ClassLoader.java:760)
	at java.security.SecureClassLoader.defineClass(SecureClassLoader.java:142)
	at java.net.URLClassLoader.defineClass(URLClassLoader.java:467)
	at java.net.URLClassLoader.access$100(URLClassLoader.java:73)
	at java.net.URLClassLoader$1.run(URLClassLoader.java:368)
	at java.net.URLClassLoader$1.run(URLClassLoader.java:362)
	at java.security.AccessController.doPrivileged(Native Method)
	at java.net.URLClassLoader.findClass(URLClassLoader.java:361)
	at java.lang.ClassLoader.loadClass(ClassLoader.java:424)
	at sun.misc.Launcher$AppClassLoader.loadClass(Launcher.java:331)
	at java.lang.ClassLoader.loadClass(ClassLoader.java:357)
	at org.springframework.context.support.AbstractApplicationContext.<init>(AbstractApplicationContext.java:164)
	at org.springframework.context.support.AbstractRefreshableApplicationContext.<init>(AbstractRefreshableApplicationContext.java:90)
	at org.springframework.context.support.AbstractRefreshableConfigApplicationContext.<init>(AbstractRefreshableConfigApplicationContext.java:59)
	at org.springframework.context.support.AbstractXmlApplicationContext.<init>(AbstractXmlApplicationContext.java:61)
	at org.springframework.context.support.ClassPathXmlApplicationContext.<init>(ClassPathXmlApplicationContext.java:136)
	at org.springframework.context.support.ClassPathXmlApplicationContext.<init>(ClassPathXmlApplicationContext.java:83)
	at com.curso.spring.springioc0007.Main.init(Main.java:29)
	at com.curso.spring.springioc0007.Main.main(Main.java:24)

org.aspectj.bridge.AbortException: trouble in: 
public abstract class org.springframework.util.ObjectUtils extends java.lang.Object:
  private static final int INITIAL_HASH = 7
  private static final int MULTIPLIER = 31
  private static final String EMPTY_STRING = ""
  private static final String NULL_STRING = "null"
  private static final String ARRAY_START = "{"
  private static final String ARRAY_END = "}"
  private static final String EMPTY_ARRAY = "{}"
  private static final String ARRAY_ELEMENT_SEPARATOR = ", "
  public void <init>():
                    ALOAD_0     // Lorg/springframework/util/ObjectUtils; this   (line 39)
                    INVOKESPECIAL java.lang.Object.<init> ()V
    constructor-execution(void org.springframework.util.ObjectUtils.<init>())
    |               RETURN
    constructor-execution(void org.springframework.util.ObjectUtils.<init>())
  end public void <init>()

  public static boolean isCheckedException(Throwable):
                    ALOAD_0     // Ljava/lang/Throwable; ex   (line 62)
                    INSTANCEOF java.lang.RuntimeException
                    IFNE L0
                    ALOAD_0     // Ljava/lang/Throwable; ex
                    INSTANCEOF java.lang.Error
                    IFEQ L1
                L0: ICONST_0
                    GOTO L2
                L1: ICONST_1
                L2: IRETURN
  end public static boolean isCheckedException(Throwable)

  public static boolean isCompatibleWithThrowsClause(Throwable, Class[]):
                    ALOAD_0     // Ljava/lang/Throwable; ex   (line 73)
                    INVOKESTATIC org.springframework.util.ObjectUtils.isCheckedException (Ljava/lang/Throwable;)Z
                    IFNE L0
                    ICONST_1   (line 74)
                    IRETURN
                L0: ALOAD_1     // [Ljava/lang/Class; declaredExceptions   (line 76)
                    IFNULL L4
                    ICONST_0   (line 77)
                    ISTORE_2
                    GOTO L3   (line 78)
                L1: ALOAD_1     // [Ljava/lang/Class; declaredExceptions   (line 79)
                    ILOAD_2     // I i
                    AALOAD
                    ALOAD_0     // Ljava/lang/Throwable; ex
                    INVOKEVIRTUAL java.lang.Object.getClass ()Ljava/lang/Class;
                    INVOKEVIRTUAL java.lang.Class.isAssignableFrom (Ljava/lang/Class;)Z
                    IFEQ L2
                    ICONST_1   (line 80)
                    IRETURN
                L2: IINC_2 1     // I i   (line 82)
                L3: ILOAD_2     // I i   (line 78)
                    ALOAD_1     // [Ljava/lang/Class; declaredExceptions
                    ARRAYLENGTH
                    IF_ICMPLT L1
                L4: ICONST_0   (line 85)
                    IRETURN
  end public static boolean isCompatibleWithThrowsClause(Throwable, Class[])

  public static boolean isArray(Object):
                    ALOAD_0     // Ljava/lang/Object; obj   (line 94)
                    IFNULL L0
                    ALOAD_0     // Ljava/lang/Object; obj
                    INVOKEVIRTUAL java.lang.Object.getClass ()Ljava/lang/Class;
                    INVOKEVIRTUAL java.lang.Class.isArray ()Z
                    IFEQ L0
                    ICONST_1
                    IRETURN
                L0: ICONST_0
                    IRETURN
  end public static boolean isArray(Object)

  public static boolean isEmpty(Object[]):
                    ALOAD_0     // [Ljava/lang/Object; array   (line 103)
                    IFNULL L0
                    ALOAD_0     // [Ljava/lang/Object; array
                    ARRAYLENGTH
                    IFEQ L0
                    ICONST_0
                    IRETURN
                L0: ICONST_1
                    IRETURN
  end public static boolean isEmpty(Object[])

  public static boolean containsElement(Object[], Object):
                    ALOAD_0     // [Ljava/lang/Object; array   (line 114)
                    IFNONNULL L0
                    ICONST_0   (line 115)
                    IRETURN
                L0: ALOAD_0     // [Ljava/lang/Object; array   (line 117)
                    DUP
                    ASTORE 5
                    ARRAYLENGTH
                    ISTORE 4
                    ICONST_0
                    ISTORE_3
                    GOTO L3
                L1: ALOAD 5
                    ILOAD_3
                    AALOAD
                    ASTORE_2
                    ALOAD_2     // Ljava/lang/Object; arrayEle   (line 118)
                    ALOAD_1     // Ljava/lang/Object; element
                    INVOKESTATIC org.springframework.util.ObjectUtils.nullSafeEquals (Ljava/lang/Object;Ljava/lang/Object;)Z
                    IFEQ L2
                    ICONST_1   (line 119)
                    IRETURN
                L2: IINC_3 1   (line 117)
                L3: ILOAD_3
                    ILOAD 4
                    IF_ICMPLT L1
                    ICONST_0   (line 122)
                    IRETURN
  end public static boolean containsElement(Object[], Object)

  public static boolean containsConstant(Enum[], String):
                    ALOAD_0     // [Ljava/lang/Enum; enumValues   (line 133)
                    ALOAD_1     // Ljava/lang/String; constant
                    ICONST_0
                    INVOKESTATIC org.springframework.util.ObjectUtils.containsConstant ([Ljava/lang/Enum;Ljava/lang/String;Z)Z
                    IRETURN
  end public static boolean containsConstant(Enum[], String)

  public static boolean containsConstant(Enum[], String, boolean):
                    ALOAD_0     // [Ljava/lang/Enum; enumValues   (line 144)
                    DUP
                    ASTORE 6
                    ARRAYLENGTH
                    ISTORE 5
                    ICONST_0
                    ISTORE 4
                    GOTO L4
                L0: ALOAD 6
                    ILOAD 4
                    AALOAD
                    ASTORE_3
                    ILOAD_2     // Z caseSensitive   (line 145)
                    IFEQ L1
                    ALOAD_3     // Ljava/lang/Enum; candidate   (line 146)
                    INVOKEVIRTUAL java.lang.Enum.toString ()Ljava/lang/String;
                    ALOAD_1     // Ljava/lang/String; constant
                    INVOKEVIRTUAL java.lang.String.equals (Ljava/lang/Object;)Z
                    IFEQ L3
                    GOTO L2
                L1: ALOAD_3     // Ljava/lang/Enum; candidate   (line 147)
                    INVOKEVIRTUAL java.lang.Enum.toString ()Ljava/lang/String;
                    ALOAD_1     // Ljava/lang/String; constant
                    INVOKEVIRTUAL java.lang.String.equalsIgnoreCase (Ljava/lang/String;)Z
                    IFEQ L3
                L2: ICONST_1   (line 148)
                    IRETURN
                L3: IINC 4 1   (line 144)
                L4: ILOAD 4
                    ILOAD 5
                    IF_ICMPLT L0
                    ICONST_0   (line 151)
                    IRETURN
  end public static boolean containsConstant(Enum[], String, boolean)

  public static Enum caseInsensitiveValueOf(Enum[], String):
                    ALOAD_0     // [Ljava/lang/Enum; enumValues   (line 163)
                    DUP
                    ASTORE 5
                    ARRAYLENGTH
                    ISTORE 4
                    ICONST_0
                    ISTORE_3
                    GOTO L2
                L0: ALOAD 5
                    ILOAD_3
                    AALOAD
                    ASTORE_2
                    ALOAD_2     // Ljava/lang/Enum; candidate   (line 164)
                    INVOKEVIRTUAL java.lang.Enum.toString ()Ljava/lang/String;
                    ALOAD_1     // Ljava/lang/String; constant
                    INVOKEVIRTUAL java.lang.String.equalsIgnoreCase (Ljava/lang/String;)Z
                    IFEQ L1
                    ALOAD_2     // Ljava/lang/Enum; candidate   (line 165)
                    ARETURN
                L1: IINC_3 1   (line 163)
                L2: ILOAD_3
                    ILOAD 4
                    IF_ICMPLT L0
                    NEW java.lang.IllegalArgumentException   (line 168)
                    DUP
                    LDC "constant [%s] does not exist in enum type %s"   (line 169)
                    ICONST_2
                    ANEWARRAY java.lang.Object
                    DUP
                    ICONST_0
                    ALOAD_1     // Ljava/lang/String; constant   (line 170)
                    AASTORE
                    DUP
                    ICONST_1
                    ALOAD_0     // [Ljava/lang/Enum; enumValues
                    INVOKEVIRTUAL java.lang.Object.getClass ()Ljava/lang/Class;
                    INVOKEVIRTUAL java.lang.Class.getComponentType ()Ljava/lang/Class;
                    INVOKEVIRTUAL java.lang.Class.getName ()Ljava/lang/String;
                    AASTORE   (line 169)
                    INVOKESTATIC java.lang.String.format (Ljava/lang/String;[Ljava/lang/Object;)Ljava/lang/String;
                    INVOKESPECIAL java.lang.IllegalArgumentException.<init> (Ljava/lang/String;)V   (line 168)
                    ATHROW
  end public static Enum caseInsensitiveValueOf(Enum[], String)

  public static Object[] addObjectToArray(Object[], Object):
                    LDC java.lang.Object   (line 181)
                    ASTORE_2
                    ALOAD_0     // [Ljava/lang/Object; array   (line 182)
                    IFNULL L0
                    ALOAD_0     // [Ljava/lang/Object; array   (line 183)
                    INVOKEVIRTUAL java.lang.Object.getClass ()Ljava/lang/Class;
                    INVOKEVIRTUAL java.lang.Class.getComponentType ()Ljava/lang/Class;
                    ASTORE_2     // Ljava/lang/Class; compType
                    GOTO L1
                L0: ALOAD_1     // Ljava/lang/Object; obj   (line 185)
                    IFNULL L1
                    ALOAD_1     // Ljava/lang/Object; obj   (line 186)
                    INVOKEVIRTUAL java.lang.Object.getClass ()Ljava/lang/Class;
                    ASTORE_2     // Ljava/lang/Class; compType
                L1: ALOAD_0     // [Ljava/lang/Object; array   (line 188)
                    IFNULL L2
                    ALOAD_0     // [Ljava/lang/Object; array
                    ARRAYLENGTH
                    ICONST_1
                    IADD
                    GOTO L3
                L2: ICONST_1
                L3: ISTORE_3
                    ALOAD_2     // Ljava/lang/Class; compType   (line 190)
                    ILOAD_3     // I newArrLength
                    INVOKESTATIC java.lang.reflect.Array.newInstance (Ljava/lang/Class;I)Ljava/lang/Object;
                    CHECKCAST [Ljava.lang.Object;
                    ASTORE 4
                    ALOAD_0     // [Ljava/lang/Object; array   (line 191)
                    IFNULL L4
                    ALOAD_0     // [Ljava/lang/Object; array   (line 192)
                    ICONST_0
                    ALOAD 4     // [Ljava/lang/Object; newArr
                    ICONST_0
                    ALOAD_0     // [Ljava/lang/Object; array
                    ARRAYLENGTH
                    INVOKESTATIC java.lang.System.arraycopy (Ljava/lang/Object;ILjava/lang/Object;II)V
                L4: ALOAD 4     // [Ljava/lang/Object; newArr   (line 194)
                    ALOAD 4     // [Ljava/lang/Object; newArr
                    ARRAYLENGTH
                    ICONST_1
                    ISUB
                    ALOAD_1     // Ljava/lang/Object; obj
                    AASTORE
                    ALOAD 4     // [Ljava/lang/Object; newArr   (line 195)
                    ARETURN
  end public static Object[] addObjectToArray(Object[], Object)

  public static Object[] toObjectArray(Object):
                    ALOAD_0     // Ljava/lang/Object; source   (line 208)
                    INSTANCEOF [Ljava.lang.Object;
                    IFEQ L0
                    ALOAD_0     // Ljava/lang/Object; source   (line 209)
                    CHECKCAST [Ljava.lang.Object;
                    ARETURN
                L0: ALOAD_0     // Ljava/lang/Object; source   (line 211)
                    IFNONNULL L1
                    ICONST_0   (line 212)
                    ANEWARRAY java.lang.Object
                    ARETURN
                L1: ALOAD_0     // Ljava/lang/Object; source   (line 214)
                    INVOKEVIRTUAL java.lang.Object.getClass ()Ljava/lang/Class;
                    INVOKEVIRTUAL java.lang.Class.isArray ()Z
                    IFNE L2
                    NEW java.lang.IllegalArgumentException   (line 215)
                    DUP
                    NEW java.lang.StringBuilder
                    DUP
                    LDC "Source is not an array: "
                    INVOKESPECIAL java.lang.StringBuilder.<init> (Ljava/lang/String;)V
                    ALOAD_0     // Ljava/lang/Object; source
                    INVOKEVIRTUAL java.lang.StringBuilder.append (Ljava/lang/Object;)Ljava/lang/StringBuilder;
                    INVOKEVIRTUAL java.lang.StringBuilder.toString ()Ljava/lang/String;
                    INVOKESPECIAL java.lang.IllegalArgumentException.<init> (Ljava/lang/String;)V
                    ATHROW
                L2: ALOAD_0     // Ljava/lang/Object; source   (line 217)
                    INVOKESTATIC java.lang.reflect.Array.getLength (Ljava/lang/Object;)I
                    ISTORE_1
                    ILOAD_1     // I length   (line 218)
                    IFNE L3
                    ICONST_0   (line 219)
                    ANEWARRAY java.lang.Object
                    ARETURN
                L3: ALOAD_0     // Ljava/lang/Object; source   (line 221)
                    ICONST_0
                    INVOKESTATIC java.lang.reflect.Array.get (Ljava/lang/Object;I)Ljava/lang/Object;
                    INVOKEVIRTUAL java.lang.Object.getClass ()Ljava/lang/Class;
                    ASTORE_2
                    ALOAD_2     // Ljava/lang/Class; wrapperType   (line 222)
                    ILOAD_1     // I length
                    INVOKESTATIC java.lang.reflect.Array.newInstance (Ljava/lang/Class;I)Ljava/lang/Object;
                    CHECKCAST [Ljava.lang.Object;
                    ASTORE_3
                    ICONST_0   (line 223)
                    ISTORE 4
                    GOTO L5
                L4: ALOAD_3     // [Ljava/lang/Object; newArray   (line 224)
                    ILOAD 4     // I i
                    ALOAD_0     // Ljava/lang/Object; source
                    ILOAD 4     // I i
                    INVOKESTATIC java.lang.reflect.Array.get (Ljava/lang/Object;I)Ljava/lang/Object;
                    AASTORE
                    IINC 4 1     // I i   (line 223)
                L5: ILOAD 4     // I i
                    ILOAD_1     // I length
                    IF_ICMPLT L4
                    ALOAD_3     // [Ljava/lang/Object; newArray   (line 226)
                    ARETURN
  end public static Object[] toObjectArray(Object)

  public static boolean nullSafeEquals(Object, Object):
                    ALOAD_0     // Ljava/lang/Object; o1   (line 246)
                    ALOAD_1     // Ljava/lang/Object; o2
                    IF_ACMPNE L0
                    ICONST_1   (line 247)
                    IRETURN
                L0: ALOAD_0     // Ljava/lang/Object; o1   (line 249)
                    IFNULL L1
                    ALOAD_1     // Ljava/lang/Object; o2
                    IFNONNULL L2
                L1: ICONST_0   (line 250)
                    IRETURN
                L2: ALOAD_0     // Ljava/lang/Object; o1   (line 252)
                    ALOAD_1     // Ljava/lang/Object; o2
                    INVOKEVIRTUAL java.lang.Object.equals (Ljava/lang/Object;)Z
                    IFEQ L3
                    ICONST_1   (line 253)
                    IRETURN
                L3: ALOAD_0     // Ljava/lang/Object; o1   (line 255)
                    INVOKEVIRTUAL java.lang.Object.getClass ()Ljava/lang/Class;
                    INVOKEVIRTUAL java.lang.Class.isArray ()Z
                    IFEQ L12
                    ALOAD_1     // Ljava/lang/Object; o2
                    INVOKEVIRTUAL java.lang.Object.getClass ()Ljava/lang/Class;
                    INVOKEVIRTUAL java.lang.Class.isArray ()Z
                    IFEQ L12
                    ALOAD_0     // Ljava/lang/Object; o1   (line 256)
                    INSTANCEOF [Ljava.lang.Object;
                    IFEQ L4
                    ALOAD_1     // Ljava/lang/Object; o2
                    INSTANCEOF [Ljava.lang.Object;
                    IFEQ L4
                    ALOAD_0     // Ljava/lang/Object; o1   (line 257)
                    CHECKCAST [Ljava.lang.Object;
                    ALOAD_1     // Ljava/lang/Object; o2
                    CHECKCAST [Ljava.lang.Object;
                    INVOKESTATIC java.util.Arrays.equals ([Ljava/lang/Object;[Ljava/lang/Object;)Z
                    IRETURN
                L4: ALOAD_0     // Ljava/lang/Object; o1   (line 259)
                    INSTANCEOF [Z
                    IFEQ L5
                    ALOAD_1     // Ljava/lang/Object; o2
                    INSTANCEOF [Z
                    IFEQ L5
                    ALOAD_0     // Ljava/lang/Object; o1   (line 260)
                    CHECKCAST [Z
                    ALOAD_1     // Ljava/lang/Object; o2
                    CHECKCAST [Z
                    INVOKESTATIC java.util.Arrays.equals ([Z[Z)Z
                    IRETURN
                L5: ALOAD_0     // Ljava/lang/Object; o1   (line 262)
                    INSTANCEOF [B
                    IFEQ L6
                    ALOAD_1     // Ljava/lang/Object; o2
                    INSTANCEOF [B
                    IFEQ L6
                    ALOAD_0     // Ljava/lang/Object; o1   (line 263)
                    CHECKCAST [B
                    ALOAD_1     // Ljava/lang/Object; o2
                    CHECKCAST [B
                    INVOKESTATIC java.util.Arrays.equals ([B[B)Z
                    IRETURN
                L6: ALOAD_0     // Ljava/lang/Object; o1   (line 265)
                    INSTANCEOF [C
                    IFEQ L7
                    ALOAD_1     // Ljava/lang/Object; o2
                    INSTANCEOF [C
                    IFEQ L7
                    ALOAD_0     // Ljava/lang/Object; o1   (line 266)
                    CHECKCAST [C
                    ALOAD_1     // Ljava/lang/Object; o2
                    CHECKCAST [C
                    INVOKESTATIC java.util.Arrays.equals ([C[C)Z
                    IRETURN
                L7: ALOAD_0     // Ljava/lang/Object; o1   (line 268)
                    INSTANCEOF [D
                    IFEQ L8
                    ALOAD_1     // Ljava/lang/Object; o2
                    INSTANCEOF [D
                    IFEQ L8
                    ALOAD_0     // Ljava/lang/Object; o1   (line 269)
                    CHECKCAST [D
                    ALOAD_1     // Ljava/lang/Object; o2
                    CHECKCAST [D
                    INVOKESTATIC java.util.Arrays.equals ([D[D)Z
                    IRETURN
                L8: ALOAD_0     // Ljava/lang/Object; o1   (line 271)
                    INSTANCEOF [F
                    IFEQ L9
                    ALOAD_1     // Ljava/lang/Object; o2
                    INSTANCEOF [F
                    IFEQ L9
                    ALOAD_0     // Ljava/lang/Object; o1   (line 272)
                    CHECKCAST [F
                    ALOAD_1     // Ljava/lang/Object; o2
                    CHECKCAST [F
                    INVOKESTATIC java.util.Arrays.equals ([F[F)Z
                    IRETURN
                L9: ALOAD_0     // Ljava/lang/Object; o1   (line 274)
                    INSTANCEOF [I
                    IFEQ L10
                    ALOAD_1     // Ljava/lang/Object; o2
                    INSTANCEOF [I
                    IFEQ L10
                    ALOAD_0     // Ljava/lang/Object; o1   (line 275)
                    CHECKCAST [I
                    ALOAD_1     // Ljava/lang/Object; o2
                    CHECKCAST [I
                    INVOKESTATIC java.util.Arrays.equals ([I[I)Z
                    IRETURN
               L10: ALOAD_0     // Ljava/lang/Object; o1   (line 277)
                    INSTANCEOF [J
                    IFEQ L11
                    ALOAD_1     // Ljava/lang/Object; o2
                    INSTANCEOF [J
                    IFEQ L11
                    ALOAD_0     // Ljava/lang/Object; o1   (line 278)
                    CHECKCAST [J
                    ALOAD_1     // Ljava/lang/Object; o2
                    CHECKCAST [J
                    INVOKESTATIC java.util.Arrays.equals ([J[J)Z
                    IRETURN
               L11: ALOAD_0     // Ljava/lang/Object; o1   (line 280)
                    INSTANCEOF [S
                    IFEQ L12
                    ALOAD_1     // Ljava/lang/Object; o2
                    INSTANCEOF [S
                    IFEQ L12
                    ALOAD_0     // Ljava/lang/Object; o1   (line 281)
                    CHECKCAST [S
                    ALOAD_1     // Ljava/lang/Object; o2
                    CHECKCAST [S
                    INVOKESTATIC java.util.Arrays.equals ([S[S)Z
                    IRETURN
               L12: ICONST_0   (line 284)
                    IRETURN
  end public static boolean nullSafeEquals(Object, Object)

  public static int nullSafeHashCode(Object):
                    ALOAD_0     // Ljava/lang/Object; obj   (line 304)
                    IFNONNULL L0
                    ICONST_0   (line 305)
                    IRETURN
                L0: ALOAD_0     // Ljava/lang/Object; obj   (line 307)
                    INVOKEVIRTUAL java.lang.Object.getClass ()Ljava/lang/Class;
                    INVOKEVIRTUAL java.lang.Class.isArray ()Z
                    IFEQ L9
                    ALOAD_0     // Ljava/lang/Object; obj   (line 308)
                    INSTANCEOF [Ljava.lang.Object;
                    IFEQ L1
                    ALOAD_0     // Ljava/lang/Object; obj   (line 309)
                    CHECKCAST [Ljava.lang.Object;
                    INVOKESTATIC org.springframework.util.ObjectUtils.nullSafeHashCode ([Ljava/lang/Object;)I
                    IRETURN
                L1: ALOAD_0     // Ljava/lang/Object; obj   (line 311)
                    INSTANCEOF [Z
                    IFEQ L2
                    ALOAD_0     // Ljava/lang/Object; obj   (line 312)
                    CHECKCAST [Z
                    INVOKESTATIC org.springframework.util.ObjectUtils.nullSafeHashCode ([Z)I
                    IRETURN
                L2: ALOAD_0     // Ljava/lang/Object; obj   (line 314)
                    INSTANCEOF [B
                    IFEQ L3
                    ALOAD_0     // Ljava/lang/Object; obj   (line 315)
                    CHECKCAST [B
                    INVOKESTATIC org.springframework.util.ObjectUtils.nullSafeHashCode ([B)I
                    IRETURN
                L3: ALOAD_0     // Ljava/lang/Object; obj   (line 317)
                    INSTANCEOF [C
                    IFEQ L4
                    ALOAD_0     // Ljava/lang/Object; obj   (line 318)
                    CHECKCAST [C
                    INVOKESTATIC org.springframework.util.ObjectUtils.nullSafeHashCode ([C)I
                    IRETURN
                L4: ALOAD_0     // Ljava/lang/Object; obj   (line 320)
                    INSTANCEOF [D
                    IFEQ L5
                    ALOAD_0     // Ljava/lang/Object; obj   (line 321)
                    CHECKCAST [D
                    INVOKESTATIC org.springframework.util.ObjectUtils.nullSafeHashCode ([D)I
                    IRETURN
                L5: ALOAD_0     // Ljava/lang/Object; obj   (line 323)
                    INSTANCEOF [F
                    IFEQ L6
                    ALOAD_0     // Ljava/lang/Object; obj   (line 324)
                    CHECKCAST [F
                    INVOKESTATIC org.springframework.util.ObjectUtils.nullSafeHashCode ([F)I
                    IRETURN
                L6: ALOAD_0     // Ljava/lang/Object; obj   (line 326)
                    INSTANCEOF [I
                    IFEQ L7
                    ALOAD_0     // Ljava/lang/Object; obj   (line 327)
                    CHECKCAST [I
                    INVOKESTATIC org.springframework.util.ObjectUtils.nullSafeHashCode ([I)I
                    IRETURN
                L7: ALOAD_0     // Ljava/lang/Object; obj   (line 329)
                    INSTANCEOF [J
                    IFEQ L8
                    ALOAD_0     // Ljava/lang/Object; obj   (line 330)
                    CHECKCAST [J
                    INVOKESTATIC org.springframework.util.ObjectUtils.nullSafeHashCode ([J)I
                    IRETURN
                L8: ALOAD_0     // Ljava/lang/Object; obj   (line 332)
                    INSTANCEOF [S
                    IFEQ L9
                    ALOAD_0     // Ljava/lang/Object; obj   (line 333)
                    CHECKCAST [S
                    INVOKESTATIC org.springframework.util.ObjectUtils.nullSafeHashCode ([S)I
                    IRETURN
                L9: ALOAD_0     // Ljava/lang/Object; obj   (line 336)
                    INVOKEVIRTUAL java.lang.Object.hashCode ()I
                    IRETURN
  end public static int nullSafeHashCode(Object)

  public static int nullSafeHashCode(Object[]):
                    ALOAD_0     // [Ljava/lang/Object; array   (line 344)
                    IFNONNULL L0
                    ICONST_0   (line 345)
                    IRETURN
                L0: BIPUSH 7   (line 347)
                    ISTORE_1
                    ALOAD_0     // [Ljava/lang/Object; array   (line 348)
                    ARRAYLENGTH
                    ISTORE_2
                    ICONST_0   (line 349)
                    ISTORE_3
                    GOTO L2
                L1: BIPUSH 31   (line 350)
                    ILOAD_1     // I hash
                    IMUL
                    ALOAD_0     // [Ljava/lang/Object; array
                    ILOAD_3     // I i
                    AALOAD
                    INVOKESTATIC org.springframework.util.ObjectUtils.nullSafeHashCode (Ljava/lang/Object;)I
                    IADD
                    ISTORE_1     // I hash
                    IINC_3 1     // I i   (line 349)
                L2: ILOAD_3     // I i
                    ILOAD_2     // I arraySize
                    IF_ICMPLT L1
                    ILOAD_1     // I hash   (line 352)
                    IRETURN
  end public static int nullSafeHashCode(Object[])

  public static int nullSafeHashCode(boolean[]):
                    ALOAD_0     // [Z array   (line 360)
                    IFNONNULL L0
                    ICONST_0   (line 361)
                    IRETURN
                L0: BIPUSH 7   (line 363)
                    ISTORE_1
                    ALOAD_0     // [Z array   (line 364)
                    ARRAYLENGTH
                    ISTORE_2
                    ICONST_0   (line 365)
                    ISTORE_3
                    GOTO L2
                L1: BIPUSH 31   (line 366)
                    ILOAD_1     // I hash
                    IMUL
                    ALOAD_0     // [Z array
                    ILOAD_3     // I i
                    BALOAD
                    INVOKESTATIC org.springframework.util.ObjectUtils.hashCode (Z)I
                    IADD
                    ISTORE_1     // I hash
                    IINC_3 1     // I i   (line 365)
                L2: ILOAD_3     // I i
                    ILOAD_2     // I arraySize
                    IF_ICMPLT L1
                    ILOAD_1     // I hash   (line 368)
                    IRETURN
  end public static int nullSafeHashCode(boolean[])

  public static int nullSafeHashCode(byte[]):
                    ALOAD_0     // [B array   (line 376)
                    IFNONNULL L0
                    ICONST_0   (line 377)
                    IRETURN
                L0: BIPUSH 7   (line 379)
                    ISTORE_1
                    ALOAD_0     // [B array   (line 380)
                    ARRAYLENGTH
                    ISTORE_2
                    ICONST_0   (line 381)
                    ISTORE_3
                    GOTO L2
                L1: BIPUSH 31   (line 382)
                    ILOAD_1     // I hash
                    IMUL
                    ALOAD_0     // [B array
                    ILOAD_3     // I i
                    BALOAD
                    IADD
                    ISTORE_1     // I hash
                    IINC_3 1     // I i   (line 381)
                L2: ILOAD_3     // I i
                    ILOAD_2     // I arraySize
                    IF_ICMPLT L1
                    ILOAD_1     // I hash   (line 384)
                    IRETURN
  end public static int nullSafeHashCode(byte[])

  public static int nullSafeHashCode(char[]):
                    ALOAD_0     // [C array   (line 392)
                    IFNONNULL L0
                    ICONST_0   (line 393)
                    IRETURN
                L0: BIPUSH 7   (line 395)
                    ISTORE_1
                    ALOAD_0     // [C array   (line 396)
                    ARRAYLENGTH
                    ISTORE_2
                    ICONST_0   (line 397)
                    ISTORE_3
                    GOTO L2
                L1: BIPUSH 31   (line 398)
                    ILOAD_1     // I hash
                    IMUL
                    ALOAD_0     // [C array
                    ILOAD_3     // I i
                    CALOAD
                    IADD
                    ISTORE_1     // I hash
                    IINC_3 1     // I i   (line 397)
                L2: ILOAD_3     // I i
                    ILOAD_2     // I arraySize
                    IF_ICMPLT L1
                    ILOAD_1     // I hash   (line 400)
                    IRETURN
  end public static int nullSafeHashCode(char[])

  public static int nullSafeHashCode(double[]):
                    ALOAD_0     // [D array   (line 408)
                    IFNONNULL L0
                    ICONST_0   (line 409)
                    IRETURN
                L0: BIPUSH 7   (line 411)
                    ISTORE_1
                    ALOAD_0     // [D array   (line 412)
                    ARRAYLENGTH
                    ISTORE_2
                    ICONST_0   (line 413)
                    ISTORE_3
                    GOTO L2
                L1: BIPUSH 31   (line 414)
                    ILOAD_1     // I hash
                    IMUL
                    ALOAD_0     // [D array
                    ILOAD_3     // I i
                    DALOAD
                    INVOKESTATIC org.springframework.util.ObjectUtils.hashCode (D)I
                    IADD
                    ISTORE_1     // I hash
                    IINC_3 1     // I i   (line 413)
                L2: ILOAD_3     // I i
                    ILOAD_2     // I arraySize
                    IF_ICMPLT L1
                    ILOAD_1     // I hash   (line 416)
                    IRETURN
  end public static int nullSafeHashCode(double[])

  public static int nullSafeHashCode(float[]):
                    ALOAD_0     // [F array   (line 424)
                    IFNONNULL L0
                    ICONST_0   (line 425)
                    IRETURN
                L0: BIPUSH 7   (line 427)
                    ISTORE_1
                    ALOAD_0     // [F array   (line 428)
                    ARRAYLENGTH
                    ISTORE_2
                    ICONST_0   (line 429)
                    ISTORE_3
                    GOTO L2
                L1: BIPUSH 31   (line 430)
                    ILOAD_1     // I hash
                    IMUL
                    ALOAD_0     // [F array
                    ILOAD_3     // I i
                    FALOAD
                    INVOKESTATIC org.springframework.util.ObjectUtils.hashCode (F)I
                    IADD
                    ISTORE_1     // I hash
                    IINC_3 1     // I i   (line 429)
                L2: ILOAD_3     // I i
                    ILOAD_2     // I arraySize
                    IF_ICMPLT L1
                    ILOAD_1     // I hash   (line 432)
                    IRETURN
  end public static int nullSafeHashCode(float[])

  public static int nullSafeHashCode(int[]):
                    ALOAD_0     // [I array   (line 440)
                    IFNONNULL L0
                    ICONST_0   (line 441)
                    IRETURN
                L0: BIPUSH 7   (line 443)
                    ISTORE_1
                    ALOAD_0     // [I array   (line 444)
                    ARRAYLENGTH
                    ISTORE_2
                    ICONST_0   (line 445)
                    ISTORE_3
                    GOTO L2
                L1: BIPUSH 31   (line 446)
                    ILOAD_1     // I hash
                    IMUL
                    ALOAD_0     // [I array
                    ILOAD_3     // I i
                    IALOAD
                    IADD
                    ISTORE_1     // I hash
                    IINC_3 1     // I i   (line 445)
                L2: ILOAD_3     // I i
                    ILOAD_2     // I arraySize
                    IF_ICMPLT L1
                    ILOAD_1     // I hash   (line 448)
                    IRETURN
  end public static int nullSafeHashCode(int[])

  public static int nullSafeHashCode(long[]):
                    ALOAD_0     // [J array   (line 456)
                    IFNONNULL L0
                    ICONST_0   (line 457)
                    IRETURN
                L0: BIPUSH 7   (line 459)
                    ISTORE_1
                    ALOAD_0     // [J array   (line 460)
                    ARRAYLENGTH
                    ISTORE_2
                    ICONST_0   (line 461)
                    ISTORE_3
                    GOTO L2
                L1: BIPUSH 31   (line 462)
                    ILOAD_1     // I hash
                    IMUL
                    ALOAD_0     // [J array
                    ILOAD_3     // I i
                    LALOAD
                    INVOKESTATIC org.springframework.util.ObjectUtils.hashCode (J)I
                    IADD
                    ISTORE_1     // I hash
                    IINC_3 1     // I i   (line 461)
                L2: ILOAD_3     // I i
                    ILOAD_2     // I arraySize
                    IF_ICMPLT L1
                    ILOAD_1     // I hash   (line 464)
                    IRETURN
  end public static int nullSafeHashCode(long[])

  public static int nullSafeHashCode(short[]):
                    ALOAD_0     // [S array   (line 472)
                    IFNONNULL L0
                    ICONST_0   (line 473)
                    IRETURN
                L0: BIPUSH 7   (line 475)
                    ISTORE_1
                    ALOAD_0     // [S array   (line 476)
                    ARRAYLENGTH
                    ISTORE_2
                    ICONST_0   (line 477)
                    ISTORE_3
                    GOTO L2
                L1: BIPUSH 31   (line 478)
                    ILOAD_1     // I hash
                    IMUL
                    ALOAD_0     // [S array
                    ILOAD_3     // I i
                    SALOAD
                    IADD
                    ISTORE_1     // I hash
                    IINC_3 1     // I i   (line 477)
                L2: ILOAD_3     // I i
                    ILOAD_2     // I arraySize
                    IF_ICMPLT L1
                    ILOAD_1     // I hash   (line 480)
                    IRETURN
  end public static int nullSafeHashCode(short[])

  public static int hashCode(boolean):
                    ILOAD_0     // Z bool   (line 488)
                    IFEQ L0
                    SIPUSH 1231
                    GOTO L1
                L0: SIPUSH 1237
                L1: IRETURN
  end public static int hashCode(boolean)

  public static int hashCode(double):
                    DLOAD_0     // D dbl   (line 496)
                    INVOKESTATIC java.lang.Double.doubleToLongBits (D)J
                    LSTORE_2
                    LLOAD_2     // J bits   (line 497)
                    INVOKESTATIC org.springframework.util.ObjectUtils.hashCode (J)I
                    IRETURN
  end public static int hashCode(double)

  public static int hashCode(float):
                    FLOAD_0     // F flt   (line 505)
                    INVOKESTATIC java.lang.Float.floatToIntBits (F)I
                    IRETURN
  end public static int hashCode(float)

  public static int hashCode(long):
                    LLOAD_0     // J lng   (line 513)
                    LLOAD_0     // J lng
                    BIPUSH 32
                    LUSHR
                    LXOR
                    L2I
                    IRETURN
  end public static int hashCode(long)

  public static String identityToString(Object):
                    ALOAD_0     // Ljava/lang/Object; obj   (line 528)
                    IFNONNULL L0
                    LDC ""   (line 529)
                    ARETURN
                L0: NEW java.lang.StringBuilder   (line 531)
                    DUP
                    ALOAD_0     // Ljava/lang/Object; obj
                    INVOKEVIRTUAL java.lang.Object.getClass ()Ljava/lang/Class;
                    INVOKEVIRTUAL java.lang.Class.getName ()Ljava/lang/String;
                    INVOKESTATIC java.lang.String.valueOf (Ljava/lang/Object;)Ljava/lang/String;
                    INVOKESPECIAL java.lang.StringBuilder.<init> (Ljava/lang/String;)V
                    LDC_W "@"
                    INVOKEVIRTUAL java.lang.StringBuilder.append (Ljava/lang/String;)Ljava/lang/StringBuilder;
                    ALOAD_0     // Ljava/lang/Object; obj
                    INVOKESTATIC org.springframework.util.ObjectUtils.getIdentityHexString (Ljava/lang/Object;)Ljava/lang/String;
                    INVOKEVIRTUAL java.lang.StringBuilder.append (Ljava/lang/String;)Ljava/lang/StringBuilder;
                    INVOKEVIRTUAL java.lang.StringBuilder.toString ()Ljava/lang/String;
                    ARETURN
  end public static String identityToString(Object)

  public static String getIdentityHexString(Object):
                    ALOAD_0     // Ljava/lang/Object; obj   (line 540)
                    INVOKESTATIC java.lang.System.identityHashCode (Ljava/lang/Object;)I
                    INVOKESTATIC java.lang.Integer.toHexString (I)Ljava/lang/String;
                    ARETURN
  end public static String getIdentityHexString(Object)

  public static String getDisplayString(Object):
                    ALOAD_0     // Ljava/lang/Object; obj   (line 553)
                    IFNONNULL L0
                    LDC ""   (line 554)
                    ARETURN
                L0: ALOAD_0     // Ljava/lang/Object; obj   (line 556)
                    INVOKESTATIC org.springframework.util.ObjectUtils.nullSafeToString (Ljava/lang/Object;)Ljava/lang/String;
                    ARETURN
  end public static String getDisplayString(Object)

  public static String nullSafeClassName(Object):
                    ALOAD_0     // Ljava/lang/Object; obj   (line 566)
                    IFNULL L0
                    ALOAD_0     // Ljava/lang/Object; obj
                    INVOKEVIRTUAL java.lang.Object.getClass ()Ljava/lang/Class;
                    INVOKEVIRTUAL java.lang.Class.getName ()Ljava/lang/String;
                    GOTO L1
                L0: LDC "null"
                L1: ARETURN
  end public static String nullSafeClassName(Object)

  public static String nullSafeToString(Object):
                    ALOAD_0     // Ljava/lang/Object; obj   (line 577)
                    IFNONNULL L0
                    LDC "null"   (line 578)
                    ARETURN
                L0: ALOAD_0     // Ljava/lang/Object; obj   (line 580)
                    INSTANCEOF java.lang.String
                    IFEQ L1
                    ALOAD_0     // Ljava/lang/Object; obj   (line 581)
                    CHECKCAST java.lang.String
                    ARETURN
                L1: ALOAD_0     // Ljava/lang/Object; obj   (line 583)
                    INSTANCEOF [Ljava.lang.Object;
                    IFEQ L2
                    ALOAD_0     // Ljava/lang/Object; obj   (line 584)
                    CHECKCAST [Ljava.lang.Object;
                    INVOKESTATIC org.springframework.util.ObjectUtils.nullSafeToString ([Ljava/lang/Object;)Ljava/lang/String;
                    ARETURN
                L2: ALOAD_0     // Ljava/lang/Object; obj   (line 586)
                    INSTANCEOF [Z
                    IFEQ L3
                    ALOAD_0     // Ljava/lang/Object; obj   (line 587)
                    CHECKCAST [Z
                    INVOKESTATIC org.springframework.util.ObjectUtils.nullSafeToString ([Z)Ljava/lang/String;
                    ARETURN
                L3: ALOAD_0     // Ljava/lang/Object; obj   (line 589)
                    INSTANCEOF [B
                    IFEQ L4
                    ALOAD_0     // Ljava/lang/Object; obj   (line 590)
                    CHECKCAST [B
                    INVOKESTATIC org.springframework.util.ObjectUtils.nullSafeToString ([B)Ljava/lang/String;
                    ARETURN
                L4: ALOAD_0     // Ljava/lang/Object; obj   (line 592)
                    INSTANCEOF [C
                    IFEQ L5
                    ALOAD_0     // Ljava/lang/Object; obj   (line 593)
                    CHECKCAST [C
                    INVOKESTATIC org.springframework.util.ObjectUtils.nullSafeToString ([C)Ljava/lang/String;
                    ARETURN
                L5: ALOAD_0     // Ljava/lang/Object; obj   (line 595)
                    INSTANCEOF [D
                    IFEQ L6
                    ALOAD_0     // Ljava/lang/Object; obj   (line 596)
                    CHECKCAST [D
                    INVOKESTATIC org.springframework.util.ObjectUtils.nullSafeToString ([D)Ljava/lang/String;
                    ARETURN
                L6: ALOAD_0     // Ljava/lang/Object; obj   (line 598)
                    INSTANCEOF [F
                    IFEQ L7
                    ALOAD_0     // Ljava/lang/Object; obj   (line 599)
                    CHECKCAST [F
                    INVOKESTATIC org.springframework.util.ObjectUtils.nullSafeToString ([F)Ljava/lang/String;
                    ARETURN
                L7: ALOAD_0     // Ljava/lang/Object; obj   (line 601)
                    INSTANCEOF [I
                    IFEQ L8
                    ALOAD_0     // Ljava/lang/Object; obj   (line 602)
                    CHECKCAST [I
                    INVOKESTATIC org.springframework.util.ObjectUtils.nullSafeToString ([I)Ljava/lang/String;
                    ARETURN
                L8: ALOAD_0     // Ljava/lang/Object; obj   (line 604)
                    INSTANCEOF [J
                    IFEQ L9
                    ALOAD_0     // Ljava/lang/Object; obj   (line 605)
                    CHECKCAST [J
                    INVOKESTATIC org.springframework.util.ObjectUtils.nullSafeToString ([J)Ljava/lang/String;
                    ARETURN
                L9: ALOAD_0     // Ljava/lang/Object; obj   (line 607)
                    INSTANCEOF [S
                    IFEQ L10
                    ALOAD_0     // Ljava/lang/Object; obj   (line 608)
                    CHECKCAST [S
                    INVOKESTATIC org.springframework.util.ObjectUtils.nullSafeToString ([S)Ljava/lang/String;
                    ARETURN
               L10: ALOAD_0     // Ljava/lang/Object; obj   (line 610)
                    INVOKEVIRTUAL java.lang.Object.toString ()Ljava/lang/String;
                    ASTORE_1
                    ALOAD_1     // Ljava/lang/String; str   (line 611)
                    IFNULL L11
                    ALOAD_1     // Ljava/lang/String; str
                    GOTO L12
               L11: LDC ""
               L12: ARETURN
  end public static String nullSafeToString(Object)

  public static String nullSafeToString(Object[]):
                    ALOAD_0     // [Ljava/lang/Object; array   (line 624)
                    IFNONNULL L0
                    LDC "null"   (line 625)
                    ARETURN
                L0: ALOAD_0     // [Ljava/lang/Object; array   (line 627)
                    ARRAYLENGTH
                    ISTORE_1
                    ILOAD_1     // I length   (line 628)
                    IFNE L1
                    LDC "{}"   (line 629)
                    ARETURN
                L1: NEW java.lang.StringBuilder   (line 631)
                    DUP
                    INVOKESPECIAL java.lang.StringBuilder.<init> ()V
                    ASTORE_2
                    ICONST_0   (line 632)
                    ISTORE_3
                    GOTO L5
                L2: ILOAD_3     // I i   (line 633)
                    IFNE L3
                    ALOAD_2     // Ljava/lang/StringBuilder; sb   (line 634)
                    LDC "{"
                    INVOKEVIRTUAL java.lang.StringBuilder.append (Ljava/lang/String;)Ljava/lang/StringBuilder;
                    POP
                    GOTO L4
                L3: ALOAD_2     // Ljava/lang/StringBuilder; sb   (line 637)
                    LDC ", "
                    INVOKEVIRTUAL java.lang.StringBuilder.append (Ljava/lang/String;)Ljava/lang/StringBuilder;
                    POP
                L4: ALOAD_2     // Ljava/lang/StringBuilder; sb   (line 639)
                    ALOAD_0     // [Ljava/lang/Object; array
                    ILOAD_3     // I i
                    AALOAD
                    INVOKESTATIC java.lang.String.valueOf (Ljava/lang/Object;)Ljava/lang/String;
                    INVOKEVIRTUAL java.lang.StringBuilder.append (Ljava/lang/String;)Ljava/lang/StringBuilder;
                    POP
                    IINC_3 1     // I i   (line 632)
                L5: ILOAD_3     // I i
                    ILOAD_1     // I length
                    IF_ICMPLT L2
                    ALOAD_2     // Ljava/lang/StringBuilder; sb   (line 641)
                    LDC "}"
                    INVOKEVIRTUAL java.lang.StringBuilder.append (Ljava/lang/String;)Ljava/lang/StringBuilder;
                    POP
                    ALOAD_2     // Ljava/lang/StringBuilder; sb   (line 642)
                    INVOKEVIRTUAL java.lang.StringBuilder.toString ()Ljava/lang/String;
                    ARETURN
  end public static String nullSafeToString(Object[])

  public static String nullSafeToString(boolean[]):
                    ALOAD_0     // [Z array   (line 655)
                    IFNONNULL L0
                    LDC "null"   (line 656)
                    ARETURN
                L0: ALOAD_0     // [Z array   (line 658)
                    ARRAYLENGTH
                    ISTORE_1
                    ILOAD_1     // I length   (line 659)
                    IFNE L1
                    LDC "{}"   (line 660)
                    ARETURN
                L1: NEW java.lang.StringBuilder   (line 662)
                    DUP
                    INVOKESPECIAL java.lang.StringBuilder.<init> ()V
                    ASTORE_2
                    ICONST_0   (line 663)
                    ISTORE_3
                    GOTO L5
                L2: ILOAD_3     // I i   (line 664)
                    IFNE L3
                    ALOAD_2     // Ljava/lang/StringBuilder; sb   (line 665)
                    LDC "{"
                    INVOKEVIRTUAL java.lang.StringBuilder.append (Ljava/lang/String;)Ljava/lang/StringBuilder;
                    POP
                    GOTO L4
                L3: ALOAD_2     // Ljava/lang/StringBuilder; sb   (line 668)
                    LDC ", "
                    INVOKEVIRTUAL java.lang.StringBuilder.append (Ljava/lang/String;)Ljava/lang/StringBuilder;
                    POP
                L4: ALOAD_2     // Ljava/lang/StringBuilder; sb   (line 671)
                    ALOAD_0     // [Z array
                    ILOAD_3     // I i
                    BALOAD
                    INVOKEVIRTUAL java.lang.StringBuilder.append (Z)Ljava/lang/StringBuilder;
                    POP
                    IINC_3 1     // I i   (line 663)
                L5: ILOAD_3     // I i
                    ILOAD_1     // I length
                    IF_ICMPLT L2
                    ALOAD_2     // Ljava/lang/StringBuilder; sb   (line 673)
                    LDC "}"
                    INVOKEVIRTUAL java.lang.StringBuilder.append (Ljava/lang/String;)Ljava/lang/StringBuilder;
                    POP
                    ALOAD_2     // Ljava/lang/StringBuilder; sb   (line 674)
                    INVOKEVIRTUAL java.lang.StringBuilder.toString ()Ljava/lang/String;
                    ARETURN
  end public static String nullSafeToString(boolean[])

  public static String nullSafeToString(byte[]):
                    ALOAD_0     // [B array   (line 687)
                    IFNONNULL L0
                    LDC "null"   (line 688)
                    ARETURN
                L0: ALOAD_0     // [B array   (line 690)
                    ARRAYLENGTH
                    ISTORE_1
                    ILOAD_1     // I length   (line 691)
                    IFNE L1
                    LDC "{}"   (line 692)
                    ARETURN
                L1: NEW java.lang.StringBuilder   (line 694)
                    DUP
                    INVOKESPECIAL java.lang.StringBuilder.<init> ()V
                    ASTORE_2
                    ICONST_0   (line 695)
                    ISTORE_3
                    GOTO L5
                L2: ILOAD_3     // I i   (line 696)
                    IFNE L3
                    ALOAD_2     // Ljava/lang/StringBuilder; sb   (line 697)
                    LDC "{"
                    INVOKEVIRTUAL java.lang.StringBuilder.append (Ljava/lang/String;)Ljava/lang/StringBuilder;
                    POP
                    GOTO L4
                L3: ALOAD_2     // Ljava/lang/StringBuilder; sb   (line 700)
                    LDC ", "
                    INVOKEVIRTUAL java.lang.StringBuilder.append (Ljava/lang/String;)Ljava/lang/StringBuilder;
                    POP
                L4: ALOAD_2     // Ljava/lang/StringBuilder; sb   (line 702)
                    ALOAD_0     // [B array
                    ILOAD_3     // I i
                    BALOAD
                    INVOKEVIRTUAL java.lang.StringBuilder.append (I)Ljava/lang/StringBuilder;
                    POP
                    IINC_3 1     // I i   (line 695)
                L5: ILOAD_3     // I i
                    ILOAD_1     // I length
                    IF_ICMPLT L2
                    ALOAD_2     // Ljava/lang/StringBuilder; sb   (line 704)
                    LDC "}"
                    INVOKEVIRTUAL java.lang.StringBuilder.append (Ljava/lang/String;)Ljava/lang/StringBuilder;
                    POP
                    ALOAD_2     // Ljava/lang/StringBuilder; sb   (line 705)
                    INVOKEVIRTUAL java.lang.StringBuilder.toString ()Ljava/lang/String;
                    ARETURN
  end public static String nullSafeToString(byte[])

  public static String nullSafeToString(char[]):
                    ALOAD_0     // [C array   (line 718)
                    IFNONNULL L0
                    LDC "null"   (line 719)
                    ARETURN
                L0: ALOAD_0     // [C array   (line 721)
                    ARRAYLENGTH
                    ISTORE_1
                    ILOAD_1     // I length   (line 722)
                    IFNE L1
                    LDC "{}"   (line 723)
                    ARETURN
                L1: NEW java.lang.StringBuilder   (line 725)
                    DUP
                    INVOKESPECIAL java.lang.StringBuilder.<init> ()V
                    ASTORE_2
                    ICONST_0   (line 726)
                    ISTORE_3
                    GOTO L5
                L2: ILOAD_3     // I i   (line 727)
                    IFNE L3
                    ALOAD_2     // Ljava/lang/StringBuilder; sb   (line 728)
                    LDC "{"
                    INVOKEVIRTUAL java.lang.StringBuilder.append (Ljava/lang/String;)Ljava/lang/StringBuilder;
                    POP
                    GOTO L4
                L3: ALOAD_2     // Ljava/lang/StringBuilder; sb   (line 731)
                    LDC ", "
                    INVOKEVIRTUAL java.lang.StringBuilder.append (Ljava/lang/String;)Ljava/lang/StringBuilder;
                    POP
                L4: ALOAD_2     // Ljava/lang/StringBuilder; sb   (line 733)
                    LDC_W "'"
                    INVOKEVIRTUAL java.lang.StringBuilder.append (Ljava/lang/String;)Ljava/lang/StringBuilder;
                    ALOAD_0     // [C array
                    ILOAD_3     // I i
                    CALOAD
                    INVOKEVIRTUAL java.lang.StringBuilder.append (C)Ljava/lang/StringBuilder;
                    LDC_W "'"
                    INVOKEVIRTUAL java.lang.StringBuilder.append (Ljava/lang/String;)Ljava/lang/StringBuilder;
                    POP
                    IINC_3 1     // I i   (line 726)
                L5: ILOAD_3     // I i
                    ILOAD_1     // I length
                    IF_ICMPLT L2
                    ALOAD_2     // Ljava/lang/StringBuilder; sb   (line 735)
                    LDC "}"
                    INVOKEVIRTUAL java.lang.StringBuilder.append (Ljava/lang/String;)Ljava/lang/StringBuilder;
                    POP
                    ALOAD_2     // Ljava/lang/StringBuilder; sb   (line 736)
                    INVOKEVIRTUAL java.lang.StringBuilder.toString ()Ljava/lang/String;
                    ARETURN
  end public static String nullSafeToString(char[])

  public static String nullSafeToString(double[]):
                    ALOAD_0     // [D array   (line 749)
                    IFNONNULL L0
                    LDC "null"   (line 750)
                    ARETURN
                L0: ALOAD_0     // [D array   (line 752)
                    ARRAYLENGTH
                    ISTORE_1
                    ILOAD_1     // I length   (line 753)
                    IFNE L1
                    LDC "{}"   (line 754)
                    ARETURN
                L1: NEW java.lang.StringBuilder   (line 756)
                    DUP
                    INVOKESPECIAL java.lang.StringBuilder.<init> ()V
                    ASTORE_2
                    ICONST_0   (line 757)
                    ISTORE_3
                    GOTO L5
                L2: ILOAD_3     // I i   (line 758)
                    IFNE L3
                    ALOAD_2     // Ljava/lang/StringBuilder; sb   (line 759)
                    LDC "{"
                    INVOKEVIRTUAL java.lang.StringBuilder.append (Ljava/lang/String;)Ljava/lang/StringBuilder;
                    POP
                    GOTO L4
                L3: ALOAD_2     // Ljava/lang/StringBuilder; sb   (line 762)
                    LDC ", "
                    INVOKEVIRTUAL java.lang.StringBuilder.append (Ljava/lang/String;)Ljava/lang/StringBuilder;
                    POP
                L4: ALOAD_2     // Ljava/lang/StringBuilder; sb   (line 765)
                    ALOAD_0     // [D array
                    ILOAD_3     // I i
                    DALOAD
                    INVOKEVIRTUAL java.lang.StringBuilder.append (D)Ljava/lang/StringBuilder;
                    POP
                    IINC_3 1     // I i   (line 757)
                L5: ILOAD_3     // I i
                    ILOAD_1     // I length
                    IF_ICMPLT L2
                    ALOAD_2     // Ljava/lang/StringBuilder; sb   (line 767)
                    LDC "}"
                    INVOKEVIRTUAL java.lang.StringBuilder.append (Ljava/lang/String;)Ljava/lang/StringBuilder;
                    POP
                    ALOAD_2     // Ljava/lang/StringBuilder; sb   (line 768)
                    INVOKEVIRTUAL java.lang.StringBuilder.toString ()Ljava/lang/String;
                    ARETURN
  end public static String nullSafeToString(double[])

  public static String nullSafeToString(float[]):
                    ALOAD_0     // [F array   (line 781)
                    IFNONNULL L0
                    LDC "null"   (line 782)
                    ARETURN
                L0: ALOAD_0     // [F array   (line 784)
                    ARRAYLENGTH
                    ISTORE_1
                    ILOAD_1     // I length   (line 785)
                    IFNE L1
                    LDC "{}"   (line 786)
                    ARETURN
                L1: NEW java.lang.StringBuilder   (line 788)
                    DUP
                    INVOKESPECIAL java.lang.StringBuilder.<init> ()V
                    ASTORE_2
                    ICONST_0   (line 789)
                    ISTORE_3
                    GOTO L5
                L2: ILOAD_3     // I i   (line 790)
                    IFNE L3
                    ALOAD_2     // Ljava/lang/StringBuilder; sb   (line 791)
                    LDC "{"
                    INVOKEVIRTUAL java.lang.StringBuilder.append (Ljava/lang/String;)Ljava/lang/StringBuilder;
                    POP
                    GOTO L4
                L3: ALOAD_2     // Ljava/lang/StringBuilder; sb   (line 794)
                    LDC ", "
                    INVOKEVIRTUAL java.lang.StringBuilder.append (Ljava/lang/String;)Ljava/lang/StringBuilder;
                    POP
                L4: ALOAD_2     // Ljava/lang/StringBuilder; sb   (line 797)
                    ALOAD_0     // [F array
                    ILOAD_3     // I i
                    FALOAD
                    INVOKEVIRTUAL java.lang.StringBuilder.append (F)Ljava/lang/StringBuilder;
                    POP
                    IINC_3 1     // I i   (line 789)
                L5: ILOAD_3     // I i
                    ILOAD_1     // I length
                    IF_ICMPLT L2
                    ALOAD_2     // Ljava/lang/StringBuilder; sb   (line 799)
                    LDC "}"
                    INVOKEVIRTUAL java.lang.StringBuilder.append (Ljava/lang/String;)Ljava/lang/StringBuilder;
                    POP
                    ALOAD_2     // Ljava/lang/StringBuilder; sb   (line 800)
                    INVOKEVIRTUAL java.lang.StringBuilder.toString ()Ljava/lang/String;
                    ARETURN
  end public static String nullSafeToString(float[])

  public static String nullSafeToString(int[]):
                    ALOAD_0     // [I array   (line 813)
                    IFNONNULL L0
                    LDC "null"   (line 814)
                    ARETURN
                L0: ALOAD_0     // [I array   (line 816)
                    ARRAYLENGTH
                    ISTORE_1
                    ILOAD_1     // I length   (line 817)
                    IFNE L1
                    LDC "{}"   (line 818)
                    ARETURN
                L1: NEW java.lang.StringBuilder   (line 820)
                    DUP
                    INVOKESPECIAL java.lang.StringBuilder.<init> ()V
                    ASTORE_2
                    ICONST_0   (line 821)
                    ISTORE_3
                    GOTO L5
                L2: ILOAD_3     // I i   (line 822)
                    IFNE L3
                    ALOAD_2     // Ljava/lang/StringBuilder; sb   (line 823)
                    LDC "{"
                    INVOKEVIRTUAL java.lang.StringBuilder.append (Ljava/lang/String;)Ljava/lang/StringBuilder;
                    POP
                    GOTO L4
                L3: ALOAD_2     // Ljava/lang/StringBuilder; sb   (line 826)
                    LDC ", "
                    INVOKEVIRTUAL java.lang.StringBuilder.append (Ljava/lang/String;)Ljava/lang/StringBuilder;
                    POP
                L4: ALOAD_2     // Ljava/lang/StringBuilder; sb   (line 828)
                    ALOAD_0     // [I array
                    ILOAD_3     // I i
                    IALOAD
                    INVOKEVIRTUAL java.lang.StringBuilder.append (I)Ljava/lang/StringBuilder;
                    POP
                    IINC_3 1     // I i   (line 821)
                L5: ILOAD_3     // I i
                    ILOAD_1     // I length
                    IF_ICMPLT L2
                    ALOAD_2     // Ljava/lang/StringBuilder; sb   (line 830)
                    LDC "}"
                    INVOKEVIRTUAL java.lang.StringBuilder.append (Ljava/lang/String;)Ljava/lang/StringBuilder;
                    POP
                    ALOAD_2     // Ljava/lang/StringBuilder; sb   (line 831)
                    INVOKEVIRTUAL java.lang.StringBuilder.toString ()Ljava/lang/String;
                    ARETURN
  end public static String nullSafeToString(int[])

  public static String nullSafeToString(long[]):
                    ALOAD_0     // [J array   (line 844)
                    IFNONNULL L0
                    LDC "null"   (line 845)
                    ARETURN
                L0: ALOAD_0     // [J array   (line 847)
                    ARRAYLENGTH
                    ISTORE_1
                    ILOAD_1     // I length   (line 848)
                    IFNE L1
                    LDC "{}"   (line 849)
                    ARETURN
                L1: NEW java.lang.StringBuilder   (line 851)
                    DUP
                    INVOKESPECIAL java.lang.StringBuilder.<init> ()V
                    ASTORE_2
                    ICONST_0   (line 852)
                    ISTORE_3
                    GOTO L5
                L2: ILOAD_3     // I i   (line 853)
                    IFNE L3
                    ALOAD_2     // Ljava/lang/StringBuilder; sb   (line 854)
                    LDC "{"
                    INVOKEVIRTUAL java.lang.StringBuilder.append (Ljava/lang/String;)Ljava/lang/StringBuilder;
                    POP
                    GOTO L4
                L3: ALOAD_2     // Ljava/lang/StringBuilder; sb   (line 857)
                    LDC ", "
                    INVOKEVIRTUAL java.lang.StringBuilder.append (Ljava/lang/String;)Ljava/lang/StringBuilder;
                    POP
                L4: ALOAD_2     // Ljava/lang/StringBuilder; sb   (line 859)
                    ALOAD_0     // [J array
                    ILOAD_3     // I i
                    LALOAD
                    INVOKEVIRTUAL java.lang.StringBuilder.append (J)Ljava/lang/StringBuilder;
                    POP
                    IINC_3 1     // I i   (line 852)
                L5: ILOAD_3     // I i
                    ILOAD_1     // I length
                    IF_ICMPLT L2
                    ALOAD_2     // Ljava/lang/StringBuilder; sb   (line 861)
                    LDC "}"
                    INVOKEVIRTUAL java.lang.StringBuilder.append (Ljava/lang/String;)Ljava/lang/StringBuilder;
                    POP
                    ALOAD_2     // Ljava/lang/StringBuilder; sb   (line 862)
                    INVOKEVIRTUAL java.lang.StringBuilder.toString ()Ljava/lang/String;
                    ARETURN
  end public static String nullSafeToString(long[])

  public static String nullSafeToString(short[]):
                    ALOAD_0     // [S array   (line 875)
                    IFNONNULL L0
                    LDC "null"   (line 876)
                    ARETURN
                L0: ALOAD_0     // [S array   (line 878)
                    ARRAYLENGTH
                    ISTORE_1
                    ILOAD_1     // I length   (line 879)
                    IFNE L1
                    LDC "{}"   (line 880)
                    ARETURN
                L1: NEW java.lang.StringBuilder   (line 882)
                    DUP
                    INVOKESPECIAL java.lang.StringBuilder.<init> ()V
                    ASTORE_2
                    ICONST_0   (line 883)
                    ISTORE_3
                    GOTO L5
                L2: ILOAD_3     // I i   (line 884)
                    IFNE L3
                    ALOAD_2     // Ljava/lang/StringBuilder; sb   (line 885)
                    LDC "{"
                    INVOKEVIRTUAL java.lang.StringBuilder.append (Ljava/lang/String;)Ljava/lang/StringBuilder;
                    POP
                    GOTO L4
                L3: ALOAD_2     // Ljava/lang/StringBuilder; sb   (line 888)
                    LDC ", "
                    INVOKEVIRTUAL java.lang.StringBuilder.append (Ljava/lang/String;)Ljava/lang/StringBuilder;
                    POP
                L4: ALOAD_2     // Ljava/lang/StringBuilder; sb   (line 890)
                    ALOAD_0     // [S array
                    ILOAD_3     // I i
                    SALOAD
                    INVOKEVIRTUAL java.lang.StringBuilder.append (I)Ljava/lang/StringBuilder;
                    POP
                    IINC_3 1     // I i   (line 883)
                L5: ILOAD_3     // I i
                    ILOAD_1     // I length
                    IF_ICMPLT L2
                    ALOAD_2     // Ljava/lang/StringBuilder; sb   (line 892)
                    LDC "}"
                    INVOKEVIRTUAL java.lang.StringBuilder.append (Ljava/lang/String;)Ljava/lang/StringBuilder;
                    POP
                    ALOAD_2     // Ljava/lang/StringBuilder; sb   (line 893)
                    INVOKEVIRTUAL java.lang.StringBuilder.toString ()Ljava/lang/String;
                    ARETURN
  end public static String nullSafeToString(short[])

end public abstract class org.springframework.util.ObjectUtils

	at org.aspectj.bridge.MessageWriter.handleMessage(MessageWriter.java:47)
	at org.aspectj.weaver.tools.WeavingAdaptor$WeavingAdaptorMessageWriter.handleMessage(WeavingAdaptor.java:665)
	at org.aspectj.weaver.tools.WeavingAdaptor$WeavingAdaptorMessageHolder.handleMessage(WeavingAdaptor.java:615)
	at org.aspectj.weaver.bcel.BcelWeaver.weave(BcelWeaver.java:1752)
	at org.aspectj.weaver.bcel.BcelWeaver.weaveWithoutDump(BcelWeaver.java:1694)
	at org.aspectj.weaver.bcel.BcelWeaver.weaveAndNotify(BcelWeaver.java:1464)
	at org.aspectj.weaver.bcel.BcelWeaver.weave(BcelWeaver.java:1273)
	at org.aspectj.weaver.tools.WeavingAdaptor.getWovenBytes(WeavingAdaptor.java:394)
	at org.aspectj.weaver.tools.WeavingAdaptor.weaveClass(WeavingAdaptor.java:281)
	at org.aspectj.weaver.loadtime.Aj.preProcess(Aj.java:95)
	at org.aspectj.weaver.loadtime.ClassPreProcessorAgentAdapter.transform(ClassPreProcessorAgentAdapter.java:52)
	at sun.instrument.TransformerManager.transform(TransformerManager.java:188)
	at sun.instrument.InstrumentationImpl.transform(InstrumentationImpl.java:428)
	at java.lang.ClassLoader.defineClass1(Native Method)
	at java.lang.ClassLoader.defineClass(ClassLoader.java:760)
	at java.security.SecureClassLoader.defineClass(SecureClassLoader.java:142)
	at java.net.URLClassLoader.defineClass(URLClassLoader.java:467)
	at java.net.URLClassLoader.access$100(URLClassLoader.java:73)
	at java.net.URLClassLoader$1.run(URLClassLoader.java:368)
	at java.net.URLClassLoader$1.run(URLClassLoader.java:362)
	at java.security.AccessController.doPrivileged(Native Method)
	at java.net.URLClassLoader.findClass(URLClassLoader.java:361)
	at java.lang.ClassLoader.loadClass(ClassLoader.java:424)
	at sun.misc.Launcher$AppClassLoader.loadClass(Launcher.java:331)
	at java.lang.ClassLoader.loadClass(ClassLoader.java:357)
	at org.springframework.context.support.AbstractApplicationContext.<init>(AbstractApplicationContext.java:164)
	at org.springframework.context.support.AbstractRefreshableApplicationContext.<init>(AbstractRefreshableApplicationContext.java:90)
	at org.springframework.context.support.AbstractRefreshableConfigApplicationContext.<init>(AbstractRefreshableConfigApplicationContext.java:59)
	at org.springframework.context.support.AbstractXmlApplicationContext.<init>(AbstractXmlApplicationContext.java:61)
	at org.springframework.context.support.ClassPathXmlApplicationContext.<init>(ClassPathXmlApplicationContext.java:136)
	at org.springframework.context.support.ClassPathXmlApplicationContext.<init>(ClassPathXmlApplicationContext.java:83)
	at com.curso.spring.springioc0007.Main.init(Main.java:29)
	at com.curso.spring.springioc0007.Main.main(Main.java:24)
---- System Properties ---
java.runtime.name=Java(TM) SE Runtime Environment
sun.boot.library.path=C:\Program Files\Java\jdk1.8.0_72\jre\bin
java.vm.version=25.72-b15
java.vm.vendor=Oracle Corporation
java.vendor.url=http://java.oracle.com/
path.separator=;
java.vm.name=Java HotSpot(TM) 64-Bit Server VM
file.encoding.pkg=sun.io
user.country=ES
user.script=
sun.java.launcher=SUN_STANDARD
sun.os.patch.level=
java.vm.specification.name=Java Virtual Machine Specification
user.dir=C:\Users\usuario\git\spring\aspectos\Ejemplos Relacionados\SpringIoC0007Maven
java.runtime.version=1.8.0_72-b15
java.awt.graphicsenv=sun.awt.Win32GraphicsEnvironment
java.endorsed.dirs=C:\Program Files\Java\jdk1.8.0_72\jre\lib\endorsed
os.arch=amd64
java.io.tmpdir=C:\Users\usuario\AppData\Local\Temp\
line.separator=

java.vm.specification.vendor=Oracle Corporation
user.variant=
os.name=Windows 10
sun.jnu.encoding=Cp1252
java.library.path=C:\Program Files\Java\jdk1.8.0_72\bin;C:\WINDOWS\Sun\Java\bin;C:\WINDOWS\system32;C:\WINDOWS;C:\ProgramData\Oracle\Java\javapath;C:\Program Files\CollabNet\Subversion Client;E:\bin\Sencha\Cmd\5.1.3.61;C:\Users\usuario\bin\Sencha\Cmd\5.1.3.61;C:\Program Files (x86)\Intel\iCLS Client\;C:\Program Files\Intel\iCLS Client\;C:\WINDOWS\system32;C:\WINDOWS;C:\WINDOWS\System32\Wbem;C:\WINDOWS\System32\WindowsPowerShell\v1.0\;C:\Program Files\Intel\Intel(R) Management Engine Components\DAL;C:\Program Files\Intel\Intel(R) Management Engine Components\IPT;C:\Program Files (x86)\Intel\Intel(R) Management Engine Components\DAL;C:\Program Files (x86)\Intel\Intel(R) Management Engine Components\IPT;C:\Program Files (x86)\Intel\OpenCL SDK\3.0\bin\x86;C:\Program Files (x86)\Intel\OpenCL SDK\3.0\bin\x64;C:\Program Files (x86)\sbt\\bin;C:\Program Files (x86)\Heroku\bin;C:\Program Files (x86)\git\cmd;C:\Program Files (x86)\QuickTime\QTSystem\;C:\HashiCorp\Vagrant\bin;C:\Program Files (x86)\scala\bin;C:\Program Files\nodejs\;C:\Users\usuario\AppData\Local\.meteor\;C:\Users\usuario\AppData\Roaming\npm;.
java.specification.name=Java Platform API Specification
java.class.version=52.0
sun.management.compiler=HotSpot 64-Bit Tiered Compilers
os.version=10.0
user.home=C:\Users\usuario
user.timezone=Europe/Paris
java.awt.printerjob=sun.awt.windows.WPrinterJob
file.encoding=Cp1252
java.specification.version=1.8
java.class.path=C:\Users\usuario\git\spring\aspectos\Ejemplos Relacionados\SpringIoC0007Maven\target\classes;C:\Users\usuario\.m2\repository\org\springframework\spring-context\3.1.2.RELEASE\spring-context-3.1.2.RELEASE.jar;C:\Users\usuario\.m2\repository\org\springframework\spring-aop\3.1.2.RELEASE\spring-aop-3.1.2.RELEASE.jar;C:\Users\usuario\.m2\repository\aopalliance\aopalliance\1.0\aopalliance-1.0.jar;C:\Users\usuario\.m2\repository\org\springframework\spring-beans\3.1.2.RELEASE\spring-beans-3.1.2.RELEASE.jar;C:\Users\usuario\.m2\repository\org\springframework\spring-core\3.1.2.RELEASE\spring-core-3.1.2.RELEASE.jar;C:\Users\usuario\.m2\repository\commons-logging\commons-logging\1.1.1\commons-logging-1.1.1.jar;C:\Users\usuario\.m2\repository\org\springframework\spring-expression\3.1.2.RELEASE\spring-expression-3.1.2.RELEASE.jar;C:\Users\usuario\.m2\repository\org\springframework\spring-asm\3.1.2.RELEASE\spring-asm-3.1.2.RELEASE.jar;C:\Users\usuario\.m2\repository\org\springframework\spring-aspects\3.1.2.RELEASE\spring-aspects-3.1.2.RELEASE.jar;C:\Users\usuario\.m2\repository\org\springframework\spring-context-support\3.1.2.RELEASE\spring-context-support-3.1.2.RELEASE.jar;.\..\aspectjweaver.jar
user.name=usuario
java.vm.specification.version=1.8
sun.java.command=com.curso.spring.springioc0007.Main
java.home=C:\Program Files\Java\jdk1.8.0_72\jre
sun.arch.data.model=64
user.language=es
java.specification.vendor=Oracle Corporation
awt.toolkit=sun.awt.windows.WToolkit
java.vm.info=mixed mode
java.version=1.8.0_72
java.ext.dirs=C:\Program Files\Java\jdk1.8.0_72\jre\lib\ext;C:\WINDOWS\Sun\Java\lib\ext
sun.boot.class.path=C:\Program Files\Java\jdk1.8.0_72\jre\lib\resources.jar;C:\Program Files\Java\jdk1.8.0_72\jre\lib\rt.jar;C:\Program Files\Java\jdk1.8.0_72\jre\lib\sunrsasign.jar;C:\Program Files\Java\jdk1.8.0_72\jre\lib\jsse.jar;C:\Program Files\Java\jdk1.8.0_72\jre\lib\jce.jar;C:\Program Files\Java\jdk1.8.0_72\jre\lib\charsets.jar;C:\Program Files\Java\jdk1.8.0_72\jre\lib\jfr.jar;C:\Program Files\Java\jdk1.8.0_72\jre\classes
java.vendor=Oracle Corporation
file.separator=\
java.vendor.url.bug=http://bugreport.sun.com/bugreport/
sun.io.unicode.encoding=UnicodeLittle
sun.cpu.endian=little
sun.desktop=windows
sun.cpu.isalist=amd64
---- Command Line ---
Empty
---- Full Classpath ---
Empty
---- Compiler Messages ---
Empty
---- org.aspectj.weaver.ltw.LTWWorld@28c97a5 ----
Class loader:
sun.misc.Launcher$AppClassLoader@18b4aac2
Class loader parent:
sun.misc.Launcher$ExtClassLoader@722c41f4
Shadow mungers:
(around(extraFlags: 3): ((((((((((within(@org.springframework.cache.annotation.CacheEvict *) && execution(public * @org.springframework.cache.annotation.CacheEvict *.*(..))) && this(BindingTypePattern(java.lang.Object, 0))) && persingleton(org.springframework.cache.aspectj.AnnotationCacheAspect)) || (((within(@org.springframework.cache.annotation.Caching *) && execution(public * @org.springframework.cache.annotation.Caching *.*(..))) && this(BindingTypePattern(java.lang.Object, 0))) && persingleton(org.springframework.cache.aspectj.AnnotationCacheAspect))) || (((within(@org.springframework.cache.annotation.CachePut *) && execution(public * @org.springframework.cache.annotation.CachePut *.*(..))) && this(BindingTypePattern(java.lang.Object, 0))) && persingleton(org.springframework.cache.aspectj.AnnotationCacheAspect))) || (((within(@org.springframework.cache.annotation.Cacheable *) && execution(public * @org.springframework.cache.annotation.Cacheable *.*(..))) && this(BindingTypePattern(java.lang.Object, 0))) && persingleton(org.springframework.cache.aspectj.AnnotationCacheAspect))) || ((execution(@org.springframework.cache.annotation.Caching * *(..)) && this(BindingTypePattern(java.lang.Object, 0))) && persingleton(org.springframework.cache.aspectj.AnnotationCacheAspect))) || ((execution(@org.springframework.cache.annotation.Cacheable * *(..)) && this(BindingTypePattern(java.lang.Object, 0))) && persingleton(org.springframework.cache.aspectj.AnnotationCacheAspect))) || ((execution(@org.springframework.cache.annotation.CacheEvict * *(..)) && this(BindingTypePattern(java.lang.Object, 0))) && persingleton(org.springframework.cache.aspectj.AnnotationCacheAspect))) || ((execution(@org.springframework.cache.annotation.CachePut * *(..)) && this(BindingTypePattern(java.lang.Object, 0))) && persingleton(org.springframework.cache.aspectj.AnnotationCacheAspect)))->java.lang.Object org.springframework.cache.aspectj.AbstractCacheAspect.ajc$around$org_springframework_cache_aspectj_AbstractCacheAspect$1$2bc714b5(java.lang.Object, org.aspectj.runtime.internal.AroundClosure, org.aspectj.lang.JoinPoint))
(around(extraFlags: 5): ((execution(@org.springframework.scheduling.annotation.Async (void || java.util.concurrent.Future+) *(..)) && persingleton(org.springframework.scheduling.aspectj.AnnotationAsyncExecutionAspect)) || (execution((void || java.util.concurrent.Future+) @org.springframework.scheduling.annotation.Async *.*(..)) && persingleton(org.springframework.scheduling.aspectj.AnnotationAsyncExecutionAspect)))->java.lang.Object org.springframework.scheduling.aspectj.AbstractAsyncExecutionAspect.ajc$around$org_springframework_scheduling_aspectj_AbstractAsyncExecutionAspect$1$6c004c3e(org.aspectj.runtime.internal.AroundClosure, org.aspectj.lang.JoinPoint$StaticPart))
org.aspectj.weaver.Checker@5abff562
org.aspectj.weaver.Checker@12140c1d
(before(extraFlags: 4): ((((within(@org.springframework.transaction.annotation.Transactional *) && execution(public * @org.springframework.transaction.annotation.Transactional *.*(..))) && this(BindingTypePattern(java.lang.Object, 0))) && persingleton(org.springframework.transaction.aspectj.AnnotationTransactionAspect)) || ((execution(@org.springframework.transaction.annotation.Transactional * *(..)) && this(BindingTypePattern(java.lang.Object, 0))) && persingleton(org.springframework.transaction.aspectj.AnnotationTransactionAspect)))->void org.springframework.transaction.aspectj.AbstractTransactionAspect.ajc$before$org_springframework_transaction_aspectj_AbstractTransactionAspect$1$2a73e96c(java.lang.Object, org.aspectj.lang.JoinPoint$StaticPart))
(afterThrowing(extraFlags: 1): ((((within(@org.springframework.transaction.annotation.Transactional *) && execution(public * @org.springframework.transaction.annotation.Transactional *.*(..))) && this(BindingTypePattern(java.lang.Object, 0))) && persingleton(org.springframework.transaction.aspectj.AnnotationTransactionAspect)) || ((execution(@org.springframework.transaction.annotation.Transactional * *(..)) && this(BindingTypePattern(java.lang.Object, 0))) && persingleton(org.springframework.transaction.aspectj.AnnotationTransactionAspect)))->void org.springframework.transaction.aspectj.AbstractTransactionAspect.ajc$afterThrowing$org_springframework_transaction_aspectj_AbstractTransactionAspect$2$2a73e96c(java.lang.Object, java.lang.Throwable))
(afterReturning: ((((within(@org.springframework.transaction.annotation.Transactional *) && execution(public * @org.springframework.transaction.annotation.Transactional *.*(..))) && this(BindingTypePattern(java.lang.Object, 0))) && persingleton(org.springframework.transaction.aspectj.AnnotationTransactionAspect)) || ((execution(@org.springframework.transaction.annotation.Transactional * *(..)) && this(BindingTypePattern(java.lang.Object, 0))) && persingleton(org.springframework.transaction.aspectj.AnnotationTransactionAspect)))->void org.springframework.transaction.aspectj.AbstractTransactionAspect.ajc$afterReturning$org_springframework_transaction_aspectj_AbstractTransactionAspect$3$2a73e96c(java.lang.Object))
(after: ((((within(@org.springframework.transaction.annotation.Transactional *) && execution(public * @org.springframework.transaction.annotation.Transactional *.*(..))) && this(BindingTypePattern(java.lang.Object, 0))) && persingleton(org.springframework.transaction.aspectj.AnnotationTransactionAspect)) || ((execution(@org.springframework.transaction.annotation.Transactional * *(..)) && this(BindingTypePattern(java.lang.Object, 0))) && persingleton(org.springframework.transaction.aspectj.AnnotationTransactionAspect)))->void org.springframework.transaction.aspectj.AbstractTransactionAspect.ajc$after$org_springframework_transaction_aspectj_AbstractTransactionAspect$4$2a73e96c(java.lang.Object))
(before: (((((initialization(org.springframework.beans.factory.aspectj.ConfigurableObject.new(..)) && initialization(org.springframework.beans.factory.aspectj.ConfigurableObject+.new(..))) && this(BindingTypePattern(java.lang.Object, 0))) && @this(org.springframework.beans.factory.annotation.Configurable)) && if(boolean org.springframework.beans.factory.aspectj.AnnotationBeanConfigurerAspect.ajc$if$bb0(org.springframework.beans.factory.annotation.Configurable))) && persingleton(org.springframework.beans.factory.aspectj.AnnotationBeanConfigurerAspect))->void org.springframework.beans.factory.aspectj.AbstractDependencyInjectionAspect.ajc$before$org_springframework_beans_factory_aspectj_AbstractDependencyInjectionAspect$1$e854fa65(java.lang.Object))
(afterReturning: (((((initialization(org.springframework.beans.factory.aspectj.ConfigurableObject+.new(..)) && this(BindingTypePattern(java.lang.Object, 0))) && @this(org.springframework.beans.factory.annotation.Configurable)) && !(@this(org.springframework.beans.factory.annotation.Configurable) && if(boolean org.springframework.beans.factory.aspectj.AnnotationBeanConfigurerAspect.ajc$if$bb0(org.springframework.beans.factory.annotation.Configurable)))) && if(boolean org.springframework.beans.factory.aspectj.AbstractDependencyInjectionAspect.ajc$if$6f1(org.aspectj.lang.JoinPoint))) && persingleton(org.springframework.beans.factory.aspectj.AnnotationBeanConfigurerAspect))->void org.springframework.beans.factory.aspectj.AbstractDependencyInjectionAspect.ajc$afterReturning$org_springframework_beans_factory_aspectj_AbstractDependencyInjectionAspect$2$1ea6722c(java.lang.Object))
(afterReturning: (((execution(java.lang.Object org.springframework.beans.factory.aspectj.AbstractInterfaceDrivenDependencyInjectionAspect$ConfigurableDeserializationSupport+.readResolve()) && this(BindingTypePattern(java.lang.Object, 0))) && @this(org.springframework.beans.factory.annotation.Configurable)) && persingleton(org.springframework.beans.factory.aspectj.AnnotationBeanConfigurerAspect))->void org.springframework.beans.factory.aspectj.AbstractDependencyInjectionAspect.ajc$afterReturning$org_springframework_beans_factory_aspectj_AbstractDependencyInjectionAspect$3$6aa27052(java.lang.Object))
Type mungers:
(BcelTypeMunger ResolvedTypeMunger(Method, java.lang.Object org.springframework.beans.factory.aspectj.AbstractInterfaceDrivenDependencyInjectionAspect$ConfigurableDeserializationSupport.readResolve()))
(BcelTypeMunger ExposeTypeMunger(java.lang.Object))
(BcelTypeMunger ExposeTypeMunger(java.lang.Object))
(BcelTypeMunger ExposeTypeMunger(java.lang.Object))
(BcelTypeMunger ExposeTypeMunger(org.springframework.beans.factory.aspectj.ConfigurableObject))
(BcelTypeMunger ExposeTypeMunger(org.springframework.beans.factory.aspectj.AbstractInterfaceDrivenDependencyInjectionAspect$ConfigurableDeserializationSupport))
Late Type mungers:
Empty
