---- AspectJ Properties ---
AspectJ Compiler 1.6.2 built on Saturday Oct 4, 2008 at 05:47:07 GMT
---- Dump Properties ---
Dump file: ajcore.20160604.114253.515.txt
Dump reason: org.aspectj.bridge.AbortException
Dump on exception: true
Dump at exit condition: abort
---- Exception Information ---
Message: abort trouble in: 
public abstract class org.springframework.core.GenericTypeResolver extends java.lang.Object:
  private static final java.util.Map typeVariableCache [Signature(Ljava/util/Map<Ljava/lang/Class;Ljava/lang/ref/Reference<Ljava/util/Map<Ljava/lang/reflect/TypeVariable;Ljava/lang/reflect/Type;>;>;>;)]
  static void <clinit>():
    staticinitialization(void org.springframework.core.GenericTypeResolver.<clinit>())
    |               NEW java.util.WeakHashMap   (line 50)
    |               DUP
    |               INVOKESPECIAL java.util.WeakHashMap.<init> ()V
    |               INVOKESTATIC java.util.Collections.synchronizedMap (Ljava/util/Map;)Ljava/util/Map;
    |               PUTSTATIC org.springframework.core.GenericTypeResolver.typeVariableCache Ljava/util/Map;   (line 49)
    |               RETURN   (line 46)
    staticinitialization(void org.springframework.core.GenericTypeResolver.<clinit>())
  end static void <clinit>()

  public void <init>():
                    ALOAD_0     // Lorg/springframework/core/GenericTypeResolver; this   (line 46)
                    INVOKESPECIAL java.lang.Object.<init> ()V
    constructor-execution(void org.springframework.core.GenericTypeResolver.<init>())
    |               RETURN
    constructor-execution(void org.springframework.core.GenericTypeResolver.<init>())
  end public void <init>()

  public static java.lang.reflect.Type getTargetType(org.springframework.core.MethodParameter):
                    ALOAD_0     // Lorg/springframework/core/MethodParameter; methodParam   (line 59)
                    LDC "MethodParameter must not be null"
                    INVOKESTATIC org.springframework.util.Assert.notNull (Ljava/lang/Object;Ljava/lang/String;)V
                    ALOAD_0     // Lorg/springframework/core/MethodParameter; methodParam   (line 60)
                    INVOKEVIRTUAL org.springframework.core.MethodParameter.getConstructor ()Ljava/lang/reflect/Constructor;
                    IFNULL L0
                    ALOAD_0     // Lorg/springframework/core/MethodParameter; methodParam   (line 61)
                    INVOKEVIRTUAL org.springframework.core.MethodParameter.getConstructor ()Ljava/lang/reflect/Constructor;
                    INVOKEVIRTUAL java.lang.reflect.Constructor.getGenericParameterTypes ()[Ljava/lang/reflect/Type;
                    ALOAD_0     // Lorg/springframework/core/MethodParameter; methodParam
                    INVOKEVIRTUAL org.springframework.core.MethodParameter.getParameterIndex ()I
                    AALOAD
                    ARETURN
                L0: ALOAD_0     // Lorg/springframework/core/MethodParameter; methodParam   (line 64)
                    INVOKEVIRTUAL org.springframework.core.MethodParameter.getParameterIndex ()I
                    IFLT L1
                    ALOAD_0     // Lorg/springframework/core/MethodParameter; methodParam   (line 65)
                    INVOKEVIRTUAL org.springframework.core.MethodParameter.getMethod ()Ljava/lang/reflect/Method;
                    INVOKEVIRTUAL java.lang.reflect.Method.getGenericParameterTypes ()[Ljava/lang/reflect/Type;
                    ALOAD_0     // Lorg/springframework/core/MethodParameter; methodParam
                    INVOKEVIRTUAL org.springframework.core.MethodParameter.getParameterIndex ()I
                    AALOAD
                    ARETURN
                L1: ALOAD_0     // Lorg/springframework/core/MethodParameter; methodParam   (line 68)
                    INVOKEVIRTUAL org.springframework.core.MethodParameter.getMethod ()Ljava/lang/reflect/Method;
                    INVOKEVIRTUAL java.lang.reflect.Method.getGenericReturnType ()Ljava/lang/reflect/Type;
                    ARETURN
  end public static java.lang.reflect.Type getTargetType(org.springframework.core.MethodParameter)

  public static Class resolveParameterType(org.springframework.core.MethodParameter, Class):
                    ALOAD_0     // Lorg/springframework/core/MethodParameter; methodParam   (line 80)
                    INVOKESTATIC org.springframework.core.GenericTypeResolver.getTargetType (Lorg/springframework/core/MethodParameter;)Ljava/lang/reflect/Type;
                    ASTORE_2
                    ALOAD_1     // Ljava/lang/Class; clazz   (line 81)
                    LDC "Class must not be null"
                    INVOKESTATIC org.springframework.util.Assert.notNull (Ljava/lang/Object;Ljava/lang/String;)V
                    ALOAD_1     // Ljava/lang/Class; clazz   (line 82)
                    INVOKESTATIC org.springframework.core.GenericTypeResolver.getTypeVariableMap (Ljava/lang/Class;)Ljava/util/Map;
                    ASTORE_3
                    ALOAD_2     // Ljava/lang/reflect/Type; genericType   (line 83)
                    ALOAD_3     // Ljava/util/Map; typeVariableMap
                    INVOKESTATIC org.springframework.core.GenericTypeResolver.getRawType (Ljava/lang/reflect/Type;Ljava/util/Map;)Ljava/lang/reflect/Type;
                    ASTORE 4
                    ALOAD 4     // Ljava/lang/reflect/Type; rawType   (line 84)
                    INSTANCEOF java.lang.Class
                    IFEQ L0
                    ALOAD 4     // Ljava/lang/reflect/Type; rawType
                    CHECKCAST java.lang.Class
                    GOTO L1
                L0: ALOAD_0     // Lorg/springframework/core/MethodParameter; methodParam
                    INVOKEVIRTUAL org.springframework.core.MethodParameter.getParameterType ()Ljava/lang/Class;
                L1: ASTORE 5
                    ALOAD_0     // Lorg/springframework/core/MethodParameter; methodParam   (line 85)
                    ALOAD 5     // Ljava/lang/Class; result
                    INVOKEVIRTUAL org.springframework.core.MethodParameter.setParameterType (Ljava/lang/Class;)V
                    ALOAD_0     // Lorg/springframework/core/MethodParameter; methodParam   (line 86)
                    ALOAD_3     // Ljava/util/Map; typeVariableMap
                    PUTFIELD org.springframework.core.MethodParameter.typeVariableMap Ljava/util/Map;
                    ALOAD 5     // Ljava/lang/Class; result   (line 87)
                    ARETURN
  end public static Class resolveParameterType(org.springframework.core.MethodParameter, Class)

  public static Class resolveReturnType(java.lang.reflect.Method, Class):
                    ALOAD_0     // Ljava/lang/reflect/Method; method   (line 97)
                    LDC "Method must not be null"
                    INVOKESTATIC org.springframework.util.Assert.notNull (Ljava/lang/Object;Ljava/lang/String;)V
                    ALOAD_0     // Ljava/lang/reflect/Method; method   (line 98)
                    INVOKEVIRTUAL java.lang.reflect.Method.getGenericReturnType ()Ljava/lang/reflect/Type;
                    ASTORE_2
                    ALOAD_1     // Ljava/lang/Class; clazz   (line 99)
                    LDC "Class must not be null"
                    INVOKESTATIC org.springframework.util.Assert.notNull (Ljava/lang/Object;Ljava/lang/String;)V
                    ALOAD_1     // Ljava/lang/Class; clazz   (line 100)
                    INVOKESTATIC org.springframework.core.GenericTypeResolver.getTypeVariableMap (Ljava/lang/Class;)Ljava/util/Map;
                    ASTORE_3
                    ALOAD_2     // Ljava/lang/reflect/Type; genericType   (line 101)
                    ALOAD_3     // Ljava/util/Map; typeVariableMap
                    INVOKESTATIC org.springframework.core.GenericTypeResolver.getRawType (Ljava/lang/reflect/Type;Ljava/util/Map;)Ljava/lang/reflect/Type;
                    ASTORE 4
                    ALOAD 4     // Ljava/lang/reflect/Type; rawType   (line 102)
                    INSTANCEOF java.lang.Class
                    IFEQ L0
                    ALOAD 4     // Ljava/lang/reflect/Type; rawType
                    CHECKCAST java.lang.Class
                    GOTO L1
                L0: ALOAD_0     // Ljava/lang/reflect/Method; method
                    INVOKEVIRTUAL java.lang.reflect.Method.getReturnType ()Ljava/lang/Class;
                L1: ARETURN
  end public static Class resolveReturnType(java.lang.reflect.Method, Class)

  public static Class resolveReturnTypeArgument(java.lang.reflect.Method, Class):
                    ALOAD_0     // Ljava/lang/reflect/Method; method   (line 115)
                    LDC "method must not be null"
                    INVOKESTATIC org.springframework.util.Assert.notNull (Ljava/lang/Object;Ljava/lang/String;)V
                    ALOAD_0     // Ljava/lang/reflect/Method; method   (line 116)
                    INVOKEVIRTUAL java.lang.reflect.Method.getReturnType ()Ljava/lang/Class;
                    ASTORE_2
                    ALOAD_0     // Ljava/lang/reflect/Method; method   (line 117)
                    INVOKEVIRTUAL java.lang.reflect.Method.getGenericReturnType ()Ljava/lang/reflect/Type;
                    ASTORE_3
                    ALOAD_2     // Ljava/lang/reflect/Type; returnType   (line 118)
                    ALOAD_1     // Ljava/lang/Class; genericIfc
                    INVOKEVIRTUAL java.lang.Object.equals (Ljava/lang/Object;)Z
                    IFEQ L1
                    ALOAD_3     // Ljava/lang/reflect/Type; genericReturnType   (line 119)
                    INSTANCEOF java.lang.reflect.ParameterizedType
                    IFEQ L0
                    ALOAD_3     // Ljava/lang/reflect/Type; genericReturnType   (line 120)
                    CHECKCAST java.lang.reflect.ParameterizedType
                    ASTORE 4
                    ALOAD 4     // Ljava/lang/reflect/ParameterizedType; targetType   (line 121)
                    INVOKEINTERFACE java.lang.reflect.ParameterizedType.getActualTypeArguments ()[Ljava/lang/reflect/Type;
                    ASTORE 5
                    ALOAD 5     // [Ljava/lang/reflect/Type; actualTypeArguments   (line 122)
                    ICONST_0
                    AALOAD
                    ASTORE 6
                    ALOAD 6     // Ljava/lang/reflect/Type; typeArg   (line 123)
                    INSTANCEOF java.lang.reflect.WildcardType
                    IFNE L1
                    ALOAD 6     // Ljava/lang/reflect/Type; typeArg   (line 124)
                    CHECKCAST java.lang.Class
                    ARETURN
                L0: ACONST_NULL   (line 128)
                    ARETURN
                L1: ALOAD_2     // Ljava/lang/reflect/Type; returnType   (line 131)
                    CHECKCAST java.lang.Class
                    ALOAD_1     // Ljava/lang/Class; genericIfc
                    INVOKESTATIC org.springframework.core.GenericTypeResolver.resolveTypeArgument (Ljava/lang/Class;Ljava/lang/Class;)Ljava/lang/Class;
                    ARETURN
  end public static Class resolveReturnTypeArgument(java.lang.reflect.Method, Class)

  public static Class resolveTypeArgument(Class, Class):
                    ALOAD_0     // Ljava/lang/Class; clazz   (line 143)
                    ALOAD_1     // Ljava/lang/Class; genericIfc
                    INVOKESTATIC org.springframework.core.GenericTypeResolver.resolveTypeArguments (Ljava/lang/Class;Ljava/lang/Class;)[Ljava/lang/Class;
                    ASTORE_2
                    ALOAD_2     // [Ljava/lang/Class; typeArgs   (line 144)
                    IFNONNULL L0
                    ACONST_NULL   (line 145)
                    ARETURN
                L0: ALOAD_2     // [Ljava/lang/Class; typeArgs   (line 147)
                    ARRAYLENGTH
                    ICONST_1
                    IF_ICMPEQ L1
                    NEW java.lang.IllegalArgumentException   (line 148)
                    DUP
                    NEW java.lang.StringBuilder
                    DUP
                    LDC "Expected 1 type argument on generic interface ["
                    INVOKESPECIAL java.lang.StringBuilder.<init> (Ljava/lang/String;)V
                    ALOAD_1     // Ljava/lang/Class; genericIfc   (line 149)
                    INVOKEVIRTUAL java.lang.Class.getName ()Ljava/lang/String;
                    INVOKEVIRTUAL java.lang.StringBuilder.append (Ljava/lang/String;)Ljava/lang/StringBuilder;
                    LDC "] but found "
                    INVOKEVIRTUAL java.lang.StringBuilder.append (Ljava/lang/String;)Ljava/lang/StringBuilder;
                    ALOAD_2     // [Ljava/lang/Class; typeArgs
                    ARRAYLENGTH
                    INVOKEVIRTUAL java.lang.StringBuilder.append (I)Ljava/lang/StringBuilder;
                    INVOKEVIRTUAL java.lang.StringBuilder.toString ()Ljava/lang/String;
                    INVOKESPECIAL java.lang.IllegalArgumentException.<init> (Ljava/lang/String;)V   (line 148)
                    ATHROW
                L1: ALOAD_2     // [Ljava/lang/Class; typeArgs   (line 151)
                    ICONST_0
                    AALOAD
                    ARETURN
  end public static Class resolveTypeArgument(Class, Class)

  public static Class[] resolveTypeArguments(Class, Class):
                    ALOAD_0     // Ljava/lang/Class; clazz   (line 164)
                    ALOAD_0     // Ljava/lang/Class; clazz
                    ALOAD_1     // Ljava/lang/Class; genericIfc
                    INVOKESTATIC org.springframework.core.GenericTypeResolver.doResolveTypeArguments (Ljava/lang/Class;Ljava/lang/Class;Ljava/lang/Class;)[Ljava/lang/Class;
                    ARETURN
  end public static Class[] resolveTypeArguments(Class, Class)

  private static Class[] doResolveTypeArguments(Class, Class, Class):
                    GOTO L6   (line 168)
                L0: ALOAD_2     // Ljava/lang/Class; genericIfc   (line 169)
                    INVOKEVIRTUAL java.lang.Class.isInterface ()Z
                    IFEQ L4
                    ALOAD_1     // Ljava/lang/Class; classToIntrospect   (line 170)
                    INVOKEVIRTUAL java.lang.Class.getGenericInterfaces ()[Ljava/lang/reflect/Type;
                    ASTORE_3
                    ALOAD_3     // [Ljava/lang/reflect/Type; ifcs   (line 171)
                    DUP
                    ASTORE 7
                    ARRAYLENGTH
                    ISTORE 6
                    ICONST_0
                    ISTORE 5
                    GOTO L3
                L1: ALOAD 7
                    ILOAD 5
                    AALOAD
                    ASTORE 4
                    ALOAD_0     // Ljava/lang/Class; ownerClass   (line 172)
                    ALOAD 4     // Ljava/lang/reflect/Type; ifc
                    ALOAD_2     // Ljava/lang/Class; genericIfc
                    INVOKESTATIC org.springframework.core.GenericTypeResolver.doResolveTypeArguments (Ljava/lang/Class;Ljava/lang/reflect/Type;Ljava/lang/Class;)[Ljava/lang/Class;
                    ASTORE 8
                    ALOAD 8     // [Ljava/lang/Class; result   (line 173)
                    IFNULL L2
                    ALOAD 8     // [Ljava/lang/Class; result   (line 174)
                    ARETURN
                L2: IINC 5 1   (line 171)
                L3: ILOAD 5
                    ILOAD 6
                    IF_ICMPLT L1
                    GOTO L5
                L4: ALOAD_0     // Ljava/lang/Class; ownerClass   (line 180)
                    ALOAD_1     // Ljava/lang/Class; classToIntrospect
                    INVOKEVIRTUAL java.lang.Class.getGenericSuperclass ()Ljava/lang/reflect/Type;
                    ALOAD_2     // Ljava/lang/Class; genericIfc
                    INVOKESTATIC org.springframework.core.GenericTypeResolver.doResolveTypeArguments (Ljava/lang/Class;Ljava/lang/reflect/Type;Ljava/lang/Class;)[Ljava/lang/Class;   (line 179)
                    ASTORE_3
                    ALOAD_3     // [Ljava/lang/Class; result   (line 181)
                    IFNULL L5
                    ALOAD_3     // [Ljava/lang/Class; result   (line 182)
                    ARETURN
                L5: ALOAD_1     // Ljava/lang/Class; classToIntrospect   (line 185)
                    INVOKEVIRTUAL java.lang.Class.getSuperclass ()Ljava/lang/Class;
                    ASTORE_1     // Ljava/lang/Class; classToIntrospect
                L6: ALOAD_1     // Ljava/lang/Class; classToIntrospect   (line 168)
                    IFNONNULL L0
                    ACONST_NULL   (line 187)
                    ARETURN
  end private static Class[] doResolveTypeArguments(Class, Class, Class)

  private static Class[] doResolveTypeArguments(Class, java.lang.reflect.Type, Class):
                    ALOAD_1     // Ljava/lang/reflect/Type; ifc   (line 191)
                    INSTANCEOF java.lang.reflect.ParameterizedType
                    IFEQ L3
                    ALOAD_1     // Ljava/lang/reflect/Type; ifc   (line 192)
                    CHECKCAST java.lang.reflect.ParameterizedType
                    ASTORE_3
                    ALOAD_3     // Ljava/lang/reflect/ParameterizedType; paramIfc   (line 193)
                    INVOKEINTERFACE java.lang.reflect.ParameterizedType.getRawType ()Ljava/lang/reflect/Type;
                    ASTORE 4
                    ALOAD_2     // Ljava/lang/Class; genericIfc   (line 194)
                    ALOAD 4     // Ljava/lang/reflect/Type; rawType
                    INVOKEVIRTUAL java.lang.Object.equals (Ljava/lang/Object;)Z
                    IFEQ L2
                    ALOAD_3     // Ljava/lang/reflect/ParameterizedType; paramIfc   (line 195)
                    INVOKEINTERFACE java.lang.reflect.ParameterizedType.getActualTypeArguments ()[Ljava/lang/reflect/Type;
                    ASTORE 5
                    ALOAD 5     // [Ljava/lang/reflect/Type; typeArgs   (line 196)
                    ARRAYLENGTH
                    ANEWARRAY java.lang.Class
                    ASTORE 6
                    ICONST_0   (line 197)
                    ISTORE 7
                    GOTO L1
                L0: ALOAD 5     // [Ljava/lang/reflect/Type; typeArgs   (line 198)
                    ILOAD 7     // I i
                    AALOAD
                    ASTORE 8
                    ALOAD 6     // [Ljava/lang/Class; result   (line 199)
                    ILOAD 7     // I i
                    ALOAD_0     // Ljava/lang/Class; ownerClass
                    ALOAD 8     // Ljava/lang/reflect/Type; arg
                    INVOKESTATIC org.springframework.core.GenericTypeResolver.extractClass (Ljava/lang/Class;Ljava/lang/reflect/Type;)Ljava/lang/Class;
                    AASTORE
                    IINC 7 1     // I i   (line 197)
                L1: ILOAD 7     // I i
                    ALOAD 5     // [Ljava/lang/reflect/Type; typeArgs
                    ARRAYLENGTH
                    IF_ICMPLT L0
                    ALOAD 6     // [Ljava/lang/Class; result   (line 201)
                    ARETURN
                L2: ALOAD_2     // Ljava/lang/Class; genericIfc   (line 203)
                    ALOAD 4     // Ljava/lang/reflect/Type; rawType
                    CHECKCAST java.lang.Class
                    INVOKEVIRTUAL java.lang.Class.isAssignableFrom (Ljava/lang/Class;)Z
                    IFEQ L4
                    ALOAD_0     // Ljava/lang/Class; ownerClass   (line 204)
                    ALOAD 4     // Ljava/lang/reflect/Type; rawType
                    CHECKCAST java.lang.Class
                    ALOAD_2     // Ljava/lang/Class; genericIfc
                    INVOKESTATIC org.springframework.core.GenericTypeResolver.doResolveTypeArguments (Ljava/lang/Class;Ljava/lang/Class;Ljava/lang/Class;)[Ljava/lang/Class;
                    ARETURN
                L3: ALOAD_1     // Ljava/lang/reflect/Type; ifc   (line 207)
                    IFNULL L4
                    ALOAD_2     // Ljava/lang/Class; genericIfc
                    ALOAD_1     // Ljava/lang/reflect/Type; ifc
                    CHECKCAST java.lang.Class
                    INVOKEVIRTUAL java.lang.Class.isAssignableFrom (Ljava/lang/Class;)Z
                    IFEQ L4
                    ALOAD_0     // Ljava/lang/Class; ownerClass   (line 208)
                    ALOAD_1     // Ljava/lang/reflect/Type; ifc
                    CHECKCAST java.lang.Class
                    ALOAD_2     // Ljava/lang/Class; genericIfc
                    INVOKESTATIC org.springframework.core.GenericTypeResolver.doResolveTypeArguments (Ljava/lang/Class;Ljava/lang/Class;Ljava/lang/Class;)[Ljava/lang/Class;
                    ARETURN
                L4: ACONST_NULL   (line 210)
                    ARETURN
  end private static Class[] doResolveTypeArguments(Class, java.lang.reflect.Type, Class)

  private static Class extractClass(Class, java.lang.reflect.Type):
                    ALOAD_1     // Ljava/lang/reflect/Type; arg   (line 217)
                    INSTANCEOF java.lang.reflect.ParameterizedType
                    IFEQ L0
                    ALOAD_0     // Ljava/lang/Class; ownerClass   (line 218)
                    ALOAD_1     // Ljava/lang/reflect/Type; arg
                    CHECKCAST java.lang.reflect.ParameterizedType
                    INVOKEINTERFACE java.lang.reflect.ParameterizedType.getRawType ()Ljava/lang/reflect/Type;
                    INVOKESTATIC org.springframework.core.GenericTypeResolver.extractClass (Ljava/lang/Class;Ljava/lang/reflect/Type;)Ljava/lang/Class;
                    ARETURN
                L0: ALOAD_1     // Ljava/lang/reflect/Type; arg   (line 220)
                    INSTANCEOF java.lang.reflect.GenericArrayType
                    IFEQ L1
                    ALOAD_1     // Ljava/lang/reflect/Type; arg   (line 221)
                    CHECKCAST java.lang.reflect.GenericArrayType
                    ASTORE_2
                    ALOAD_2     // Ljava/lang/reflect/GenericArrayType; gat   (line 222)
                    INVOKEINTERFACE java.lang.reflect.GenericArrayType.getGenericComponentType ()Ljava/lang/reflect/Type;
                    ASTORE_3
                    ALOAD_0     // Ljava/lang/Class; ownerClass   (line 223)
                    ALOAD_3     // Ljava/lang/reflect/Type; gt
                    INVOKESTATIC org.springframework.core.GenericTypeResolver.extractClass (Ljava/lang/Class;Ljava/lang/reflect/Type;)Ljava/lang/Class;
                    ASTORE 4
                    ALOAD 4     // Ljava/lang/Class; componentClass   (line 224)
                    ICONST_0
                    INVOKESTATIC java.lang.reflect.Array.newInstance (Ljava/lang/Class;I)Ljava/lang/Object;
                    INVOKEVIRTUAL java.lang.Object.getClass ()Ljava/lang/Class;
                    ARETURN
                L1: ALOAD_1     // Ljava/lang/reflect/Type; arg   (line 226)
                    INSTANCEOF java.lang.reflect.TypeVariable
                    IFEQ L3
                    ALOAD_1     // Ljava/lang/reflect/Type; arg   (line 227)
                    CHECKCAST java.lang.reflect.TypeVariable
                    ASTORE_2
                    ALOAD_0     // Ljava/lang/Class; ownerClass   (line 228)
                    INVOKESTATIC org.springframework.core.GenericTypeResolver.getTypeVariableMap (Ljava/lang/Class;)Ljava/util/Map;
                    ALOAD_2     // Ljava/lang/reflect/TypeVariable; tv
                    INVOKEINTERFACE java.util.Map.get (Ljava/lang/Object;)Ljava/lang/Object;
                    CHECKCAST java.lang.reflect.Type
                    ASTORE_1     // Ljava/lang/reflect/Type; arg
                    ALOAD_1     // Ljava/lang/reflect/Type; arg   (line 229)
                    IFNONNULL L2
                    ALOAD_2     // Ljava/lang/reflect/TypeVariable; tv   (line 230)
                    INVOKESTATIC org.springframework.core.GenericTypeResolver.extractBoundForTypeVariable (Ljava/lang/reflect/TypeVariable;)Ljava/lang/reflect/Type;
                    ASTORE_1     // Ljava/lang/reflect/Type; arg
                    GOTO L3
                L2: ALOAD_0     // Ljava/lang/Class; ownerClass   (line 233)
                    ALOAD_1     // Ljava/lang/reflect/Type; arg
                    INVOKESTATIC org.springframework.core.GenericTypeResolver.extractClass (Ljava/lang/Class;Ljava/lang/reflect/Type;)Ljava/lang/Class;
                    ASTORE_1     // Ljava/lang/reflect/Type; arg
                L3: ALOAD_1     // Ljava/lang/reflect/Type; arg   (line 236)
                    INSTANCEOF java.lang.Class
                    IFEQ L4
                    ALOAD_1     // Ljava/lang/reflect/Type; arg
                    CHECKCAST java.lang.Class
                    GOTO L5
                L4: LDC java.lang.Object
                L5: ARETURN
  end private static Class extractClass(Class, java.lang.reflect.Type)

  public static Class resolveType(java.lang.reflect.Type, java.util.Map):
                    ALOAD_0     // Ljava/lang/reflect/Type; genericType   (line 247)
                    ALOAD_1     // Ljava/util/Map; typeVariableMap
                    INVOKESTATIC org.springframework.core.GenericTypeResolver.getRawType (Ljava/lang/reflect/Type;Ljava/util/Map;)Ljava/lang/reflect/Type;
                    ASTORE_2
                    ALOAD_2     // Ljava/lang/reflect/Type; rawType   (line 248)
                    INSTANCEOF java.lang.Class
                    IFEQ L0
                    ALOAD_2     // Ljava/lang/reflect/Type; rawType
                    CHECKCAST java.lang.Class
                    GOTO L1
                L0: LDC java.lang.Object
                L1: ARETURN
  end public static Class resolveType(java.lang.reflect.Type, java.util.Map)

  static java.lang.reflect.Type getRawType(java.lang.reflect.Type, java.util.Map):
                    ALOAD_0     // Ljava/lang/reflect/Type; genericType   (line 258)
                    ASTORE_2
                    ALOAD_0     // Ljava/lang/reflect/Type; genericType   (line 259)
                    INSTANCEOF java.lang.reflect.TypeVariable
                    IFEQ L0
                    ALOAD_0     // Ljava/lang/reflect/Type; genericType   (line 260)
                    CHECKCAST java.lang.reflect.TypeVariable
                    ASTORE_3
                    ALOAD_1     // Ljava/util/Map; typeVariableMap   (line 261)
                    ALOAD_3     // Ljava/lang/reflect/TypeVariable; tv
                    INVOKEINTERFACE java.util.Map.get (Ljava/lang/Object;)Ljava/lang/Object;
                    CHECKCAST java.lang.reflect.Type
                    ASTORE_2     // Ljava/lang/reflect/Type; resolvedType
                    ALOAD_2     // Ljava/lang/reflect/Type; resolvedType   (line 262)
                    IFNONNULL L0
                    ALOAD_3     // Ljava/lang/reflect/TypeVariable; tv   (line 263)
                    INVOKESTATIC org.springframework.core.GenericTypeResolver.extractBoundForTypeVariable (Ljava/lang/reflect/TypeVariable;)Ljava/lang/reflect/Type;
                    ASTORE_2     // Ljava/lang/reflect/Type; resolvedType
                L0: ALOAD_2     // Ljava/lang/reflect/Type; resolvedType   (line 266)
                    INSTANCEOF java.lang.reflect.ParameterizedType
                    IFEQ L1
                    ALOAD_2     // Ljava/lang/reflect/Type; resolvedType   (line 267)
                    CHECKCAST java.lang.reflect.ParameterizedType
                    INVOKEINTERFACE java.lang.reflect.ParameterizedType.getRawType ()Ljava/lang/reflect/Type;
                    ARETURN
                L1: ALOAD_2     // Ljava/lang/reflect/Type; resolvedType   (line 270)
                    ARETURN
  end static java.lang.reflect.Type getRawType(java.lang.reflect.Type, java.util.Map)

  public static java.util.Map getTypeVariableMap(Class):
                    GETSTATIC org.springframework.core.GenericTypeResolver.typeVariableCache Ljava/util/Map;   (line 280)
                    ALOAD_0     // Ljava/lang/Class; clazz
                    INVOKEINTERFACE java.util.Map.get (Ljava/lang/Object;)Ljava/lang/Object;
                    CHECKCAST java.lang.ref.Reference
                    ASTORE_1
                    ALOAD_1     // Ljava/lang/ref/Reference; ref   (line 281)
                    IFNULL L0
                    ALOAD_1     // Ljava/lang/ref/Reference; ref
                    INVOKEVIRTUAL java.lang.ref.Reference.get ()Ljava/lang/Object;
                    CHECKCAST java.util.Map
                    GOTO L1
                L0: ACONST_NULL
                L1: ASTORE_2
                    ALOAD_2     // Ljava/util/Map; typeVariableMap   (line 283)
                    IFNONNULL L9
                    NEW java.util.HashMap   (line 284)
                    DUP
                    INVOKESPECIAL java.util.HashMap.<init> ()V
                    ASTORE_2     // Ljava/util/Map; typeVariableMap
                    ALOAD_0     // Ljava/lang/Class; clazz   (line 287)
                    INVOKEVIRTUAL java.lang.Class.getGenericInterfaces ()[Ljava/lang/reflect/Type;
                    ALOAD_2     // Ljava/util/Map; typeVariableMap
                    INVOKESTATIC org.springframework.core.GenericTypeResolver.extractTypeVariablesFromGenericInterfaces ([Ljava/lang/reflect/Type;Ljava/util/Map;)V
                    ALOAD_0     // Ljava/lang/Class; clazz   (line 290)
                    INVOKEVIRTUAL java.lang.Class.getGenericSuperclass ()Ljava/lang/reflect/Type;
                    ASTORE_3
                    ALOAD_0     // Ljava/lang/Class; clazz   (line 291)
                    INVOKEVIRTUAL java.lang.Class.getSuperclass ()Ljava/lang/Class;
                    ASTORE 4
                    GOTO L4   (line 292)
                L2: ALOAD_3     // Ljava/lang/reflect/Type; genericType   (line 293)
                    INSTANCEOF java.lang.reflect.ParameterizedType
                    IFEQ L3
                    ALOAD_3     // Ljava/lang/reflect/Type; genericType   (line 294)
                    CHECKCAST java.lang.reflect.ParameterizedType
                    ASTORE 5
                    ALOAD 5     // Ljava/lang/reflect/ParameterizedType; pt   (line 295)
                    ALOAD_2     // Ljava/util/Map; typeVariableMap
                    INVOKESTATIC org.springframework.core.GenericTypeResolver.populateTypeMapFromParameterizedType (Ljava/lang/reflect/ParameterizedType;Ljava/util/Map;)V
                L3: ALOAD 4     // Ljava/lang/Class; type   (line 297)
                    INVOKEVIRTUAL java.lang.Class.getGenericInterfaces ()[Ljava/lang/reflect/Type;
                    ALOAD_2     // Ljava/util/Map; typeVariableMap
                    INVOKESTATIC org.springframework.core.GenericTypeResolver.extractTypeVariablesFromGenericInterfaces ([Ljava/lang/reflect/Type;Ljava/util/Map;)V
                    ALOAD 4     // Ljava/lang/Class; type   (line 298)
                    INVOKEVIRTUAL java.lang.Class.getGenericSuperclass ()Ljava/lang/reflect/Type;
                    ASTORE_3     // Ljava/lang/reflect/Type; genericType
                    ALOAD 4     // Ljava/lang/Class; type   (line 299)
                    INVOKEVIRTUAL java.lang.Class.getSuperclass ()Ljava/lang/Class;
                    ASTORE 4     // Ljava/lang/Class; type
                L4: ALOAD 4     // Ljava/lang/Class; type   (line 292)
                    IFNULL L5
                    LDC java.lang.Object
                    ALOAD 4     // Ljava/lang/Class; type
                    INVOKEVIRTUAL java.lang.Object.equals (Ljava/lang/Object;)Z
                    IFEQ L2
                L5: ALOAD_0     // Ljava/lang/Class; clazz   (line 303)
                    ASTORE 4     // Ljava/lang/Class; type
                    GOTO L8   (line 304)
                L6: ALOAD 4     // Ljava/lang/Class; type   (line 305)
                    INVOKEVIRTUAL java.lang.Class.getGenericSuperclass ()Ljava/lang/reflect/Type;
                    ASTORE_3     // Ljava/lang/reflect/Type; genericType
                    ALOAD_3     // Ljava/lang/reflect/Type; genericType   (line 306)
                    INSTANCEOF java.lang.reflect.ParameterizedType
                    IFEQ L7
                    ALOAD_3     // Ljava/lang/reflect/Type; genericType   (line 307)
                    CHECKCAST java.lang.reflect.ParameterizedType
                    ASTORE 5
                    ALOAD 5     // Ljava/lang/reflect/ParameterizedType; pt   (line 308)
                    ALOAD_2     // Ljava/util/Map; typeVariableMap
                    INVOKESTATIC org.springframework.core.GenericTypeResolver.populateTypeMapFromParameterizedType (Ljava/lang/reflect/ParameterizedType;Ljava/util/Map;)V
                L7: ALOAD 4     // Ljava/lang/Class; type   (line 310)
                    INVOKEVIRTUAL java.lang.Class.getEnclosingClass ()Ljava/lang/Class;
                    ASTORE 4     // Ljava/lang/Class; type
                L8: ALOAD 4     // Ljava/lang/Class; type   (line 304)
                    INVOKEVIRTUAL java.lang.Class.isMemberClass ()Z
                    IFNE L6
                    GETSTATIC org.springframework.core.GenericTypeResolver.typeVariableCache Ljava/util/Map;   (line 313)
                    ALOAD_0     // Ljava/lang/Class; clazz
                    NEW java.lang.ref.WeakReference
                    DUP
                    ALOAD_2     // Ljava/util/Map; typeVariableMap
                    INVOKESPECIAL java.lang.ref.WeakReference.<init> (Ljava/lang/Object;)V
                    INVOKEINTERFACE java.util.Map.put (Ljava/lang/Object;Ljava/lang/Object;)Ljava/lang/Object;
                    POP
                L9: ALOAD_2     // Ljava/util/Map; typeVariableMap   (line 316)
                    ARETURN
  end public static java.util.Map getTypeVariableMap(Class)

  static java.lang.reflect.Type extractBoundForTypeVariable(java.lang.reflect.TypeVariable):
                    ALOAD_0     // Ljava/lang/reflect/TypeVariable; typeVariable   (line 323)
                    INVOKEINTERFACE java.lang.reflect.TypeVariable.getBounds ()[Ljava/lang/reflect/Type;
                    ASTORE_1
                    ALOAD_1     // [Ljava/lang/reflect/Type; bounds   (line 324)
                    ARRAYLENGTH
                    IFNE L0
                    LDC java.lang.Object   (line 325)
                    ARETURN
                L0: ALOAD_1     // [Ljava/lang/reflect/Type; bounds   (line 327)
                    ICONST_0
                    AALOAD
                    ASTORE_2
                    ALOAD_2     // Ljava/lang/reflect/Type; bound   (line 328)
                    INSTANCEOF java.lang.reflect.TypeVariable
                    IFEQ L1
                    ALOAD_2     // Ljava/lang/reflect/Type; bound   (line 329)
                    CHECKCAST java.lang.reflect.TypeVariable
                    INVOKESTATIC org.springframework.core.GenericTypeResolver.extractBoundForTypeVariable (Ljava/lang/reflect/TypeVariable;)Ljava/lang/reflect/Type;
                    ASTORE_2     // Ljava/lang/reflect/Type; bound
                L1: ALOAD_2     // Ljava/lang/reflect/Type; bound   (line 331)
                    ARETURN
  end static java.lang.reflect.Type extractBoundForTypeVariable(java.lang.reflect.TypeVariable)

  private static void extractTypeVariablesFromGenericInterfaces(java.lang.reflect.Type[], java.util.Map):
                    ALOAD_0     // [Ljava/lang/reflect/Type; genericInterfaces   (line 335)
                    DUP
                    ASTORE 5
                    ARRAYLENGTH
                    ISTORE 4
                    ICONST_0
                    ISTORE_3
                    GOTO L3
                L0: ALOAD 5
                    ILOAD_3
                    AALOAD
                    ASTORE_2
                    ALOAD_2     // Ljava/lang/reflect/Type; genericInterface   (line 336)
                    INSTANCEOF java.lang.reflect.ParameterizedType
                    IFEQ L1
                    ALOAD_2     // Ljava/lang/reflect/Type; genericInterface   (line 337)
                    CHECKCAST java.lang.reflect.ParameterizedType
                    ASTORE 6
                    ALOAD 6     // Ljava/lang/reflect/ParameterizedType; pt   (line 338)
                    ALOAD_1     // Ljava/util/Map; typeVariableMap
                    INVOKESTATIC org.springframework.core.GenericTypeResolver.populateTypeMapFromParameterizedType (Ljava/lang/reflect/ParameterizedType;Ljava/util/Map;)V
                    ALOAD 6     // Ljava/lang/reflect/ParameterizedType; pt   (line 339)
                    INVOKEINTERFACE java.lang.reflect.ParameterizedType.getRawType ()Ljava/lang/reflect/Type;
                    INSTANCEOF java.lang.Class
                    IFEQ L2
                    ALOAD 6     // Ljava/lang/reflect/ParameterizedType; pt   (line 341)
                    INVOKEINTERFACE java.lang.reflect.ParameterizedType.getRawType ()Ljava/lang/reflect/Type;
                    CHECKCAST java.lang.Class
                    INVOKEVIRTUAL java.lang.Class.getGenericInterfaces ()[Ljava/lang/reflect/Type;
                    ALOAD_1     // Ljava/util/Map; typeVariableMap
                    INVOKESTATIC org.springframework.core.GenericTypeResolver.extractTypeVariablesFromGenericInterfaces ([Ljava/lang/reflect/Type;Ljava/util/Map;)V   (line 340)
                    GOTO L2
                L1: ALOAD_2     // Ljava/lang/reflect/Type; genericInterface   (line 344)
                    INSTANCEOF java.lang.Class
                    IFEQ L2
                    ALOAD_2     // Ljava/lang/reflect/Type; genericInterface   (line 346)
                    CHECKCAST java.lang.Class
                    INVOKEVIRTUAL java.lang.Class.getGenericInterfaces ()[Ljava/lang/reflect/Type;
                    ALOAD_1     // Ljava/util/Map; typeVariableMap
                    INVOKESTATIC org.springframework.core.GenericTypeResolver.extractTypeVariablesFromGenericInterfaces ([Ljava/lang/reflect/Type;Ljava/util/Map;)V   (line 345)
                L2: IINC_3 1   (line 335)
                L3: ILOAD_3
                    ILOAD 4
                    IF_ICMPLT L0
                    RETURN   (line 349)
  end private static void extractTypeVariablesFromGenericInterfaces(java.lang.reflect.Type[], java.util.Map)

  private static void populateTypeMapFromParameterizedType(java.lang.reflect.ParameterizedType, java.util.Map):
                    ALOAD_0     // Ljava/lang/reflect/ParameterizedType; type   (line 368)
                    INVOKEINTERFACE java.lang.reflect.ParameterizedType.getRawType ()Ljava/lang/reflect/Type;
                    INSTANCEOF java.lang.Class
                    IFEQ L7
                    ALOAD_0     // Ljava/lang/reflect/ParameterizedType; type   (line 369)
                    INVOKEINTERFACE java.lang.reflect.ParameterizedType.getActualTypeArguments ()[Ljava/lang/reflect/Type;
                    ASTORE_2
                    ALOAD_0     // Ljava/lang/reflect/ParameterizedType; type   (line 370)
                    INVOKEINTERFACE java.lang.reflect.ParameterizedType.getRawType ()Ljava/lang/reflect/Type;
                    CHECKCAST java.lang.Class
                    INVOKEVIRTUAL java.lang.Class.getTypeParameters ()[Ljava/lang/reflect/TypeVariable;
                    ASTORE_3
                    ICONST_0   (line 371)
                    ISTORE 4
                    GOTO L6
                L0: ALOAD_2     // [Ljava/lang/reflect/Type; actualTypeArguments   (line 372)
                    ILOAD 4     // I i
                    AALOAD
                    ASTORE 5
                    ALOAD_3     // [Ljava/lang/reflect/TypeVariable; typeVariables   (line 373)
                    ILOAD 4     // I i
                    AALOAD
                    ASTORE 6
                    ALOAD 5     // Ljava/lang/reflect/Type; actualTypeArgument   (line 374)
                    INSTANCEOF java.lang.Class
                    IFEQ L1
                    ALOAD_1     // Ljava/util/Map; typeVariableMap   (line 375)
                    ALOAD 6     // Ljava/lang/reflect/TypeVariable; variable
                    ALOAD 5     // Ljava/lang/reflect/Type; actualTypeArgument
                    INVOKEINTERFACE java.util.Map.put (Ljava/lang/Object;Ljava/lang/Object;)Ljava/lang/Object;
                    POP
                    GOTO L5
                L1: ALOAD 5     // Ljava/lang/reflect/Type; actualTypeArgument   (line 377)
                    INSTANCEOF java.lang.reflect.GenericArrayType
                    IFEQ L2
                    ALOAD_1     // Ljava/util/Map; typeVariableMap   (line 378)
                    ALOAD 6     // Ljava/lang/reflect/TypeVariable; variable
                    ALOAD 5     // Ljava/lang/reflect/Type; actualTypeArgument
                    INVOKEINTERFACE java.util.Map.put (Ljava/lang/Object;Ljava/lang/Object;)Ljava/lang/Object;
                    POP
                    GOTO L5
                L2: ALOAD 5     // Ljava/lang/reflect/Type; actualTypeArgument   (line 380)
                    INSTANCEOF java.lang.reflect.ParameterizedType
                    IFEQ L3
                    ALOAD_1     // Ljava/util/Map; typeVariableMap   (line 381)
                    ALOAD 6     // Ljava/lang/reflect/TypeVariable; variable
                    ALOAD 5     // Ljava/lang/reflect/Type; actualTypeArgument
                    INVOKEINTERFACE java.util.Map.put (Ljava/lang/Object;Ljava/lang/Object;)Ljava/lang/Object;
                    POP
                    GOTO L5
                L3: ALOAD 5     // Ljava/lang/reflect/Type; actualTypeArgument   (line 383)
                    INSTANCEOF java.lang.reflect.TypeVariable
                    IFEQ L5
                    ALOAD 5     // Ljava/lang/reflect/Type; actualTypeArgument   (line 386)
                    CHECKCAST java.lang.reflect.TypeVariable
                    ASTORE 7
                    ALOAD_1     // Ljava/util/Map; typeVariableMap   (line 387)
                    ALOAD 7     // Ljava/lang/reflect/TypeVariable; typeVariableArgument
                    INVOKEINTERFACE java.util.Map.get (Ljava/lang/Object;)Ljava/lang/Object;
                    CHECKCAST java.lang.reflect.Type
                    ASTORE 8
                    ALOAD 8     // Ljava/lang/reflect/Type; resolvedType   (line 388)
                    IFNONNULL L4
                    ALOAD 7     // Ljava/lang/reflect/TypeVariable; typeVariableArgument   (line 389)
                    INVOKESTATIC org.springframework.core.GenericTypeResolver.extractBoundForTypeVariable (Ljava/lang/reflect/TypeVariable;)Ljava/lang/reflect/Type;
                    ASTORE 8     // Ljava/lang/reflect/Type; resolvedType
                L4: ALOAD_1     // Ljava/util/Map; typeVariableMap   (line 391)
                    ALOAD 6     // Ljava/lang/reflect/TypeVariable; variable
                    ALOAD 8     // Ljava/lang/reflect/Type; resolvedType
                    INVOKEINTERFACE java.util.Map.put (Ljava/lang/Object;Ljava/lang/Object;)Ljava/lang/Object;
                    POP
                L5: IINC 4 1     // I i   (line 371)
                L6: ILOAD 4     // I i
                    ALOAD_2     // [Ljava/lang/reflect/Type; actualTypeArguments
                    ARRAYLENGTH
                    IF_ICMPLT L0
                L7: RETURN   (line 395)
  end private static void populateTypeMapFromParameterizedType(java.lang.reflect.ParameterizedType, java.util.Map)
end public abstract class org.springframework.core.GenericTypeResolver
 -- (NullPointerException) null
null
java.lang.NullPointerException

org.aspectj.bridge.AbortException: trouble in: 
public abstract class org.springframework.core.GenericTypeResolver extends java.lang.Object:
  private static final java.util.Map typeVariableCache [Signature(Ljava/util/Map<Ljava/lang/Class;Ljava/lang/ref/Reference<Ljava/util/Map<Ljava/lang/reflect/TypeVariable;Ljava/lang/reflect/Type;>;>;>;)]
  static void <clinit>():
    staticinitialization(void org.springframework.core.GenericTypeResolver.<clinit>())
    |               NEW java.util.WeakHashMap   (line 50)
    |               DUP
    |               INVOKESPECIAL java.util.WeakHashMap.<init> ()V
    |               INVOKESTATIC java.util.Collections.synchronizedMap (Ljava/util/Map;)Ljava/util/Map;
    |               PUTSTATIC org.springframework.core.GenericTypeResolver.typeVariableCache Ljava/util/Map;   (line 49)
    |               RETURN   (line 46)
    staticinitialization(void org.springframework.core.GenericTypeResolver.<clinit>())
  end static void <clinit>()

  public void <init>():
                    ALOAD_0     // Lorg/springframework/core/GenericTypeResolver; this   (line 46)
                    INVOKESPECIAL java.lang.Object.<init> ()V
    constructor-execution(void org.springframework.core.GenericTypeResolver.<init>())
    |               RETURN
    constructor-execution(void org.springframework.core.GenericTypeResolver.<init>())
  end public void <init>()

  public static java.lang.reflect.Type getTargetType(org.springframework.core.MethodParameter):
                    ALOAD_0     // Lorg/springframework/core/MethodParameter; methodParam   (line 59)
                    LDC "MethodParameter must not be null"
                    INVOKESTATIC org.springframework.util.Assert.notNull (Ljava/lang/Object;Ljava/lang/String;)V
                    ALOAD_0     // Lorg/springframework/core/MethodParameter; methodParam   (line 60)
                    INVOKEVIRTUAL org.springframework.core.MethodParameter.getConstructor ()Ljava/lang/reflect/Constructor;
                    IFNULL L0
                    ALOAD_0     // Lorg/springframework/core/MethodParameter; methodParam   (line 61)
                    INVOKEVIRTUAL org.springframework.core.MethodParameter.getConstructor ()Ljava/lang/reflect/Constructor;
                    INVOKEVIRTUAL java.lang.reflect.Constructor.getGenericParameterTypes ()[Ljava/lang/reflect/Type;
                    ALOAD_0     // Lorg/springframework/core/MethodParameter; methodParam
                    INVOKEVIRTUAL org.springframework.core.MethodParameter.getParameterIndex ()I
                    AALOAD
                    ARETURN
                L0: ALOAD_0     // Lorg/springframework/core/MethodParameter; methodParam   (line 64)
                    INVOKEVIRTUAL org.springframework.core.MethodParameter.getParameterIndex ()I
                    IFLT L1
                    ALOAD_0     // Lorg/springframework/core/MethodParameter; methodParam   (line 65)
                    INVOKEVIRTUAL org.springframework.core.MethodParameter.getMethod ()Ljava/lang/reflect/Method;
                    INVOKEVIRTUAL java.lang.reflect.Method.getGenericParameterTypes ()[Ljava/lang/reflect/Type;
                    ALOAD_0     // Lorg/springframework/core/MethodParameter; methodParam
                    INVOKEVIRTUAL org.springframework.core.MethodParameter.getParameterIndex ()I
                    AALOAD
                    ARETURN
                L1: ALOAD_0     // Lorg/springframework/core/MethodParameter; methodParam   (line 68)
                    INVOKEVIRTUAL org.springframework.core.MethodParameter.getMethod ()Ljava/lang/reflect/Method;
                    INVOKEVIRTUAL java.lang.reflect.Method.getGenericReturnType ()Ljava/lang/reflect/Type;
                    ARETURN
  end public static java.lang.reflect.Type getTargetType(org.springframework.core.MethodParameter)

  public static Class resolveParameterType(org.springframework.core.MethodParameter, Class):
                    ALOAD_0     // Lorg/springframework/core/MethodParameter; methodParam   (line 80)
                    INVOKESTATIC org.springframework.core.GenericTypeResolver.getTargetType (Lorg/springframework/core/MethodParameter;)Ljava/lang/reflect/Type;
                    ASTORE_2
                    ALOAD_1     // Ljava/lang/Class; clazz   (line 81)
                    LDC "Class must not be null"
                    INVOKESTATIC org.springframework.util.Assert.notNull (Ljava/lang/Object;Ljava/lang/String;)V
                    ALOAD_1     // Ljava/lang/Class; clazz   (line 82)
                    INVOKESTATIC org.springframework.core.GenericTypeResolver.getTypeVariableMap (Ljava/lang/Class;)Ljava/util/Map;
                    ASTORE_3
                    ALOAD_2     // Ljava/lang/reflect/Type; genericType   (line 83)
                    ALOAD_3     // Ljava/util/Map; typeVariableMap
                    INVOKESTATIC org.springframework.core.GenericTypeResolver.getRawType (Ljava/lang/reflect/Type;Ljava/util/Map;)Ljava/lang/reflect/Type;
                    ASTORE 4
                    ALOAD 4     // Ljava/lang/reflect/Type; rawType   (line 84)
                    INSTANCEOF java.lang.Class
                    IFEQ L0
                    ALOAD 4     // Ljava/lang/reflect/Type; rawType
                    CHECKCAST java.lang.Class
                    GOTO L1
                L0: ALOAD_0     // Lorg/springframework/core/MethodParameter; methodParam
                    INVOKEVIRTUAL org.springframework.core.MethodParameter.getParameterType ()Ljava/lang/Class;
                L1: ASTORE 5
                    ALOAD_0     // Lorg/springframework/core/MethodParameter; methodParam   (line 85)
                    ALOAD 5     // Ljava/lang/Class; result
                    INVOKEVIRTUAL org.springframework.core.MethodParameter.setParameterType (Ljava/lang/Class;)V
                    ALOAD_0     // Lorg/springframework/core/MethodParameter; methodParam   (line 86)
                    ALOAD_3     // Ljava/util/Map; typeVariableMap
                    PUTFIELD org.springframework.core.MethodParameter.typeVariableMap Ljava/util/Map;
                    ALOAD 5     // Ljava/lang/Class; result   (line 87)
                    ARETURN
  end public static Class resolveParameterType(org.springframework.core.MethodParameter, Class)

  public static Class resolveReturnType(java.lang.reflect.Method, Class):
                    ALOAD_0     // Ljava/lang/reflect/Method; method   (line 97)
                    LDC "Method must not be null"
                    INVOKESTATIC org.springframework.util.Assert.notNull (Ljava/lang/Object;Ljava/lang/String;)V
                    ALOAD_0     // Ljava/lang/reflect/Method; method   (line 98)
                    INVOKEVIRTUAL java.lang.reflect.Method.getGenericReturnType ()Ljava/lang/reflect/Type;
                    ASTORE_2
                    ALOAD_1     // Ljava/lang/Class; clazz   (line 99)
                    LDC "Class must not be null"
                    INVOKESTATIC org.springframework.util.Assert.notNull (Ljava/lang/Object;Ljava/lang/String;)V
                    ALOAD_1     // Ljava/lang/Class; clazz   (line 100)
                    INVOKESTATIC org.springframework.core.GenericTypeResolver.getTypeVariableMap (Ljava/lang/Class;)Ljava/util/Map;
                    ASTORE_3
                    ALOAD_2     // Ljava/lang/reflect/Type; genericType   (line 101)
                    ALOAD_3     // Ljava/util/Map; typeVariableMap
                    INVOKESTATIC org.springframework.core.GenericTypeResolver.getRawType (Ljava/lang/reflect/Type;Ljava/util/Map;)Ljava/lang/reflect/Type;
                    ASTORE 4
                    ALOAD 4     // Ljava/lang/reflect/Type; rawType   (line 102)
                    INSTANCEOF java.lang.Class
                    IFEQ L0
                    ALOAD 4     // Ljava/lang/reflect/Type; rawType
                    CHECKCAST java.lang.Class
                    GOTO L1
                L0: ALOAD_0     // Ljava/lang/reflect/Method; method
                    INVOKEVIRTUAL java.lang.reflect.Method.getReturnType ()Ljava/lang/Class;
                L1: ARETURN
  end public static Class resolveReturnType(java.lang.reflect.Method, Class)

  public static Class resolveReturnTypeArgument(java.lang.reflect.Method, Class):
                    ALOAD_0     // Ljava/lang/reflect/Method; method   (line 115)
                    LDC "method must not be null"
                    INVOKESTATIC org.springframework.util.Assert.notNull (Ljava/lang/Object;Ljava/lang/String;)V
                    ALOAD_0     // Ljava/lang/reflect/Method; method   (line 116)
                    INVOKEVIRTUAL java.lang.reflect.Method.getReturnType ()Ljava/lang/Class;
                    ASTORE_2
                    ALOAD_0     // Ljava/lang/reflect/Method; method   (line 117)
                    INVOKEVIRTUAL java.lang.reflect.Method.getGenericReturnType ()Ljava/lang/reflect/Type;
                    ASTORE_3
                    ALOAD_2     // Ljava/lang/reflect/Type; returnType   (line 118)
                    ALOAD_1     // Ljava/lang/Class; genericIfc
                    INVOKEVIRTUAL java.lang.Object.equals (Ljava/lang/Object;)Z
                    IFEQ L1
                    ALOAD_3     // Ljava/lang/reflect/Type; genericReturnType   (line 119)
                    INSTANCEOF java.lang.reflect.ParameterizedType
                    IFEQ L0
                    ALOAD_3     // Ljava/lang/reflect/Type; genericReturnType   (line 120)
                    CHECKCAST java.lang.reflect.ParameterizedType
                    ASTORE 4
                    ALOAD 4     // Ljava/lang/reflect/ParameterizedType; targetType   (line 121)
                    INVOKEINTERFACE java.lang.reflect.ParameterizedType.getActualTypeArguments ()[Ljava/lang/reflect/Type;
                    ASTORE 5
                    ALOAD 5     // [Ljava/lang/reflect/Type; actualTypeArguments   (line 122)
                    ICONST_0
                    AALOAD
                    ASTORE 6
                    ALOAD 6     // Ljava/lang/reflect/Type; typeArg   (line 123)
                    INSTANCEOF java.lang.reflect.WildcardType
                    IFNE L1
                    ALOAD 6     // Ljava/lang/reflect/Type; typeArg   (line 124)
                    CHECKCAST java.lang.Class
                    ARETURN
                L0: ACONST_NULL   (line 128)
                    ARETURN
                L1: ALOAD_2     // Ljava/lang/reflect/Type; returnType   (line 131)
                    CHECKCAST java.lang.Class
                    ALOAD_1     // Ljava/lang/Class; genericIfc
                    INVOKESTATIC org.springframework.core.GenericTypeResolver.resolveTypeArgument (Ljava/lang/Class;Ljava/lang/Class;)Ljava/lang/Class;
                    ARETURN
  end public static Class resolveReturnTypeArgument(java.lang.reflect.Method, Class)

  public static Class resolveTypeArgument(Class, Class):
                    ALOAD_0     // Ljava/lang/Class; clazz   (line 143)
                    ALOAD_1     // Ljava/lang/Class; genericIfc
                    INVOKESTATIC org.springframework.core.GenericTypeResolver.resolveTypeArguments (Ljava/lang/Class;Ljava/lang/Class;)[Ljava/lang/Class;
                    ASTORE_2
                    ALOAD_2     // [Ljava/lang/Class; typeArgs   (line 144)
                    IFNONNULL L0
                    ACONST_NULL   (line 145)
                    ARETURN
                L0: ALOAD_2     // [Ljava/lang/Class; typeArgs   (line 147)
                    ARRAYLENGTH
                    ICONST_1
                    IF_ICMPEQ L1
                    NEW java.lang.IllegalArgumentException   (line 148)
                    DUP
                    NEW java.lang.StringBuilder
                    DUP
                    LDC "Expected 1 type argument on generic interface ["
                    INVOKESPECIAL java.lang.StringBuilder.<init> (Ljava/lang/String;)V
                    ALOAD_1     // Ljava/lang/Class; genericIfc   (line 149)
                    INVOKEVIRTUAL java.lang.Class.getName ()Ljava/lang/String;
                    INVOKEVIRTUAL java.lang.StringBuilder.append (Ljava/lang/String;)Ljava/lang/StringBuilder;
                    LDC "] but found "
                    INVOKEVIRTUAL java.lang.StringBuilder.append (Ljava/lang/String;)Ljava/lang/StringBuilder;
                    ALOAD_2     // [Ljava/lang/Class; typeArgs
                    ARRAYLENGTH
                    INVOKEVIRTUAL java.lang.StringBuilder.append (I)Ljava/lang/StringBuilder;
                    INVOKEVIRTUAL java.lang.StringBuilder.toString ()Ljava/lang/String;
                    INVOKESPECIAL java.lang.IllegalArgumentException.<init> (Ljava/lang/String;)V   (line 148)
                    ATHROW
                L1: ALOAD_2     // [Ljava/lang/Class; typeArgs   (line 151)
                    ICONST_0
                    AALOAD
                    ARETURN
  end public static Class resolveTypeArgument(Class, Class)

  public static Class[] resolveTypeArguments(Class, Class):
                    ALOAD_0     // Ljava/lang/Class; clazz   (line 164)
                    ALOAD_0     // Ljava/lang/Class; clazz
                    ALOAD_1     // Ljava/lang/Class; genericIfc
                    INVOKESTATIC org.springframework.core.GenericTypeResolver.doResolveTypeArguments (Ljava/lang/Class;Ljava/lang/Class;Ljava/lang/Class;)[Ljava/lang/Class;
                    ARETURN
  end public static Class[] resolveTypeArguments(Class, Class)

  private static Class[] doResolveTypeArguments(Class, Class, Class):
                    GOTO L6   (line 168)
                L0: ALOAD_2     // Ljava/lang/Class; genericIfc   (line 169)
                    INVOKEVIRTUAL java.lang.Class.isInterface ()Z
                    IFEQ L4
                    ALOAD_1     // Ljava/lang/Class; classToIntrospect   (line 170)
                    INVOKEVIRTUAL java.lang.Class.getGenericInterfaces ()[Ljava/lang/reflect/Type;
                    ASTORE_3
                    ALOAD_3     // [Ljava/lang/reflect/Type; ifcs   (line 171)
                    DUP
                    ASTORE 7
                    ARRAYLENGTH
                    ISTORE 6
                    ICONST_0
                    ISTORE 5
                    GOTO L3
                L1: ALOAD 7
                    ILOAD 5
                    AALOAD
                    ASTORE 4
                    ALOAD_0     // Ljava/lang/Class; ownerClass   (line 172)
                    ALOAD 4     // Ljava/lang/reflect/Type; ifc
                    ALOAD_2     // Ljava/lang/Class; genericIfc
                    INVOKESTATIC org.springframework.core.GenericTypeResolver.doResolveTypeArguments (Ljava/lang/Class;Ljava/lang/reflect/Type;Ljava/lang/Class;)[Ljava/lang/Class;
                    ASTORE 8
                    ALOAD 8     // [Ljava/lang/Class; result   (line 173)
                    IFNULL L2
                    ALOAD 8     // [Ljava/lang/Class; result   (line 174)
                    ARETURN
                L2: IINC 5 1   (line 171)
                L3: ILOAD 5
                    ILOAD 6
                    IF_ICMPLT L1
                    GOTO L5
                L4: ALOAD_0     // Ljava/lang/Class; ownerClass   (line 180)
                    ALOAD_1     // Ljava/lang/Class; classToIntrospect
                    INVOKEVIRTUAL java.lang.Class.getGenericSuperclass ()Ljava/lang/reflect/Type;
                    ALOAD_2     // Ljava/lang/Class; genericIfc
                    INVOKESTATIC org.springframework.core.GenericTypeResolver.doResolveTypeArguments (Ljava/lang/Class;Ljava/lang/reflect/Type;Ljava/lang/Class;)[Ljava/lang/Class;   (line 179)
                    ASTORE_3
                    ALOAD_3     // [Ljava/lang/Class; result   (line 181)
                    IFNULL L5
                    ALOAD_3     // [Ljava/lang/Class; result   (line 182)
                    ARETURN
                L5: ALOAD_1     // Ljava/lang/Class; classToIntrospect   (line 185)
                    INVOKEVIRTUAL java.lang.Class.getSuperclass ()Ljava/lang/Class;
                    ASTORE_1     // Ljava/lang/Class; classToIntrospect
                L6: ALOAD_1     // Ljava/lang/Class; classToIntrospect   (line 168)
                    IFNONNULL L0
                    ACONST_NULL   (line 187)
                    ARETURN
  end private static Class[] doResolveTypeArguments(Class, Class, Class)

  private static Class[] doResolveTypeArguments(Class, java.lang.reflect.Type, Class):
                    ALOAD_1     // Ljava/lang/reflect/Type; ifc   (line 191)
                    INSTANCEOF java.lang.reflect.ParameterizedType
                    IFEQ L3
                    ALOAD_1     // Ljava/lang/reflect/Type; ifc   (line 192)
                    CHECKCAST java.lang.reflect.ParameterizedType
                    ASTORE_3
                    ALOAD_3     // Ljava/lang/reflect/ParameterizedType; paramIfc   (line 193)
                    INVOKEINTERFACE java.lang.reflect.ParameterizedType.getRawType ()Ljava/lang/reflect/Type;
                    ASTORE 4
                    ALOAD_2     // Ljava/lang/Class; genericIfc   (line 194)
                    ALOAD 4     // Ljava/lang/reflect/Type; rawType
                    INVOKEVIRTUAL java.lang.Object.equals (Ljava/lang/Object;)Z
                    IFEQ L2
                    ALOAD_3     // Ljava/lang/reflect/ParameterizedType; paramIfc   (line 195)
                    INVOKEINTERFACE java.lang.reflect.ParameterizedType.getActualTypeArguments ()[Ljava/lang/reflect/Type;
                    ASTORE 5
                    ALOAD 5     // [Ljava/lang/reflect/Type; typeArgs   (line 196)
                    ARRAYLENGTH
                    ANEWARRAY java.lang.Class
                    ASTORE 6
                    ICONST_0   (line 197)
                    ISTORE 7
                    GOTO L1
                L0: ALOAD 5     // [Ljava/lang/reflect/Type; typeArgs   (line 198)
                    ILOAD 7     // I i
                    AALOAD
                    ASTORE 8
                    ALOAD 6     // [Ljava/lang/Class; result   (line 199)
                    ILOAD 7     // I i
                    ALOAD_0     // Ljava/lang/Class; ownerClass
                    ALOAD 8     // Ljava/lang/reflect/Type; arg
                    INVOKESTATIC org.springframework.core.GenericTypeResolver.extractClass (Ljava/lang/Class;Ljava/lang/reflect/Type;)Ljava/lang/Class;
                    AASTORE
                    IINC 7 1     // I i   (line 197)
                L1: ILOAD 7     // I i
                    ALOAD 5     // [Ljava/lang/reflect/Type; typeArgs
                    ARRAYLENGTH
                    IF_ICMPLT L0
                    ALOAD 6     // [Ljava/lang/Class; result   (line 201)
                    ARETURN
                L2: ALOAD_2     // Ljava/lang/Class; genericIfc   (line 203)
                    ALOAD 4     // Ljava/lang/reflect/Type; rawType
                    CHECKCAST java.lang.Class
                    INVOKEVIRTUAL java.lang.Class.isAssignableFrom (Ljava/lang/Class;)Z
                    IFEQ L4
                    ALOAD_0     // Ljava/lang/Class; ownerClass   (line 204)
                    ALOAD 4     // Ljava/lang/reflect/Type; rawType
                    CHECKCAST java.lang.Class
                    ALOAD_2     // Ljava/lang/Class; genericIfc
                    INVOKESTATIC org.springframework.core.GenericTypeResolver.doResolveTypeArguments (Ljava/lang/Class;Ljava/lang/Class;Ljava/lang/Class;)[Ljava/lang/Class;
                    ARETURN
                L3: ALOAD_1     // Ljava/lang/reflect/Type; ifc   (line 207)
                    IFNULL L4
                    ALOAD_2     // Ljava/lang/Class; genericIfc
                    ALOAD_1     // Ljava/lang/reflect/Type; ifc
                    CHECKCAST java.lang.Class
                    INVOKEVIRTUAL java.lang.Class.isAssignableFrom (Ljava/lang/Class;)Z
                    IFEQ L4
                    ALOAD_0     // Ljava/lang/Class; ownerClass   (line 208)
                    ALOAD_1     // Ljava/lang/reflect/Type; ifc
                    CHECKCAST java.lang.Class
                    ALOAD_2     // Ljava/lang/Class; genericIfc
                    INVOKESTATIC org.springframework.core.GenericTypeResolver.doResolveTypeArguments (Ljava/lang/Class;Ljava/lang/Class;Ljava/lang/Class;)[Ljava/lang/Class;
                    ARETURN
                L4: ACONST_NULL   (line 210)
                    ARETURN
  end private static Class[] doResolveTypeArguments(Class, java.lang.reflect.Type, Class)

  private static Class extractClass(Class, java.lang.reflect.Type):
                    ALOAD_1     // Ljava/lang/reflect/Type; arg   (line 217)
                    INSTANCEOF java.lang.reflect.ParameterizedType
                    IFEQ L0
                    ALOAD_0     // Ljava/lang/Class; ownerClass   (line 218)
                    ALOAD_1     // Ljava/lang/reflect/Type; arg
                    CHECKCAST java.lang.reflect.ParameterizedType
                    INVOKEINTERFACE java.lang.reflect.ParameterizedType.getRawType ()Ljava/lang/reflect/Type;
                    INVOKESTATIC org.springframework.core.GenericTypeResolver.extractClass (Ljava/lang/Class;Ljava/lang/reflect/Type;)Ljava/lang/Class;
                    ARETURN
                L0: ALOAD_1     // Ljava/lang/reflect/Type; arg   (line 220)
                    INSTANCEOF java.lang.reflect.GenericArrayType
                    IFEQ L1
                    ALOAD_1     // Ljava/lang/reflect/Type; arg   (line 221)
                    CHECKCAST java.lang.reflect.GenericArrayType
                    ASTORE_2
                    ALOAD_2     // Ljava/lang/reflect/GenericArrayType; gat   (line 222)
                    INVOKEINTERFACE java.lang.reflect.GenericArrayType.getGenericComponentType ()Ljava/lang/reflect/Type;
                    ASTORE_3
                    ALOAD_0     // Ljava/lang/Class; ownerClass   (line 223)
                    ALOAD_3     // Ljava/lang/reflect/Type; gt
                    INVOKESTATIC org.springframework.core.GenericTypeResolver.extractClass (Ljava/lang/Class;Ljava/lang/reflect/Type;)Ljava/lang/Class;
                    ASTORE 4
                    ALOAD 4     // Ljava/lang/Class; componentClass   (line 224)
                    ICONST_0
                    INVOKESTATIC java.lang.reflect.Array.newInstance (Ljava/lang/Class;I)Ljava/lang/Object;
                    INVOKEVIRTUAL java.lang.Object.getClass ()Ljava/lang/Class;
                    ARETURN
                L1: ALOAD_1     // Ljava/lang/reflect/Type; arg   (line 226)
                    INSTANCEOF java.lang.reflect.TypeVariable
                    IFEQ L3
                    ALOAD_1     // Ljava/lang/reflect/Type; arg   (line 227)
                    CHECKCAST java.lang.reflect.TypeVariable
                    ASTORE_2
                    ALOAD_0     // Ljava/lang/Class; ownerClass   (line 228)
                    INVOKESTATIC org.springframework.core.GenericTypeResolver.getTypeVariableMap (Ljava/lang/Class;)Ljava/util/Map;
                    ALOAD_2     // Ljava/lang/reflect/TypeVariable; tv
                    INVOKEINTERFACE java.util.Map.get (Ljava/lang/Object;)Ljava/lang/Object;
                    CHECKCAST java.lang.reflect.Type
                    ASTORE_1     // Ljava/lang/reflect/Type; arg
                    ALOAD_1     // Ljava/lang/reflect/Type; arg   (line 229)
                    IFNONNULL L2
                    ALOAD_2     // Ljava/lang/reflect/TypeVariable; tv   (line 230)
                    INVOKESTATIC org.springframework.core.GenericTypeResolver.extractBoundForTypeVariable (Ljava/lang/reflect/TypeVariable;)Ljava/lang/reflect/Type;
                    ASTORE_1     // Ljava/lang/reflect/Type; arg
                    GOTO L3
                L2: ALOAD_0     // Ljava/lang/Class; ownerClass   (line 233)
                    ALOAD_1     // Ljava/lang/reflect/Type; arg
                    INVOKESTATIC org.springframework.core.GenericTypeResolver.extractClass (Ljava/lang/Class;Ljava/lang/reflect/Type;)Ljava/lang/Class;
                    ASTORE_1     // Ljava/lang/reflect/Type; arg
                L3: ALOAD_1     // Ljava/lang/reflect/Type; arg   (line 236)
                    INSTANCEOF java.lang.Class
                    IFEQ L4
                    ALOAD_1     // Ljava/lang/reflect/Type; arg
                    CHECKCAST java.lang.Class
                    GOTO L5
                L4: LDC java.lang.Object
                L5: ARETURN
  end private static Class extractClass(Class, java.lang.reflect.Type)

  public static Class resolveType(java.lang.reflect.Type, java.util.Map):
                    ALOAD_0     // Ljava/lang/reflect/Type; genericType   (line 247)
                    ALOAD_1     // Ljava/util/Map; typeVariableMap
                    INVOKESTATIC org.springframework.core.GenericTypeResolver.getRawType (Ljava/lang/reflect/Type;Ljava/util/Map;)Ljava/lang/reflect/Type;
                    ASTORE_2
                    ALOAD_2     // Ljava/lang/reflect/Type; rawType   (line 248)
                    INSTANCEOF java.lang.Class
                    IFEQ L0
                    ALOAD_2     // Ljava/lang/reflect/Type; rawType
                    CHECKCAST java.lang.Class
                    GOTO L1
                L0: LDC java.lang.Object
                L1: ARETURN
  end public static Class resolveType(java.lang.reflect.Type, java.util.Map)

  static java.lang.reflect.Type getRawType(java.lang.reflect.Type, java.util.Map):
                    ALOAD_0     // Ljava/lang/reflect/Type; genericType   (line 258)
                    ASTORE_2
                    ALOAD_0     // Ljava/lang/reflect/Type; genericType   (line 259)
                    INSTANCEOF java.lang.reflect.TypeVariable
                    IFEQ L0
                    ALOAD_0     // Ljava/lang/reflect/Type; genericType   (line 260)
                    CHECKCAST java.lang.reflect.TypeVariable
                    ASTORE_3
                    ALOAD_1     // Ljava/util/Map; typeVariableMap   (line 261)
                    ALOAD_3     // Ljava/lang/reflect/TypeVariable; tv
                    INVOKEINTERFACE java.util.Map.get (Ljava/lang/Object;)Ljava/lang/Object;
                    CHECKCAST java.lang.reflect.Type
                    ASTORE_2     // Ljava/lang/reflect/Type; resolvedType
                    ALOAD_2     // Ljava/lang/reflect/Type; resolvedType   (line 262)
                    IFNONNULL L0
                    ALOAD_3     // Ljava/lang/reflect/TypeVariable; tv   (line 263)
                    INVOKESTATIC org.springframework.core.GenericTypeResolver.extractBoundForTypeVariable (Ljava/lang/reflect/TypeVariable;)Ljava/lang/reflect/Type;
                    ASTORE_2     // Ljava/lang/reflect/Type; resolvedType
                L0: ALOAD_2     // Ljava/lang/reflect/Type; resolvedType   (line 266)
                    INSTANCEOF java.lang.reflect.ParameterizedType
                    IFEQ L1
                    ALOAD_2     // Ljava/lang/reflect/Type; resolvedType   (line 267)
                    CHECKCAST java.lang.reflect.ParameterizedType
                    INVOKEINTERFACE java.lang.reflect.ParameterizedType.getRawType ()Ljava/lang/reflect/Type;
                    ARETURN
                L1: ALOAD_2     // Ljava/lang/reflect/Type; resolvedType   (line 270)
                    ARETURN
  end static java.lang.reflect.Type getRawType(java.lang.reflect.Type, java.util.Map)

  public static java.util.Map getTypeVariableMap(Class):
                    GETSTATIC org.springframework.core.GenericTypeResolver.typeVariableCache Ljava/util/Map;   (line 280)
                    ALOAD_0     // Ljava/lang/Class; clazz
                    INVOKEINTERFACE java.util.Map.get (Ljava/lang/Object;)Ljava/lang/Object;
                    CHECKCAST java.lang.ref.Reference
                    ASTORE_1
                    ALOAD_1     // Ljava/lang/ref/Reference; ref   (line 281)
                    IFNULL L0
                    ALOAD_1     // Ljava/lang/ref/Reference; ref
                    INVOKEVIRTUAL java.lang.ref.Reference.get ()Ljava/lang/Object;
                    CHECKCAST java.util.Map
                    GOTO L1
                L0: ACONST_NULL
                L1: ASTORE_2
                    ALOAD_2     // Ljava/util/Map; typeVariableMap   (line 283)
                    IFNONNULL L9
                    NEW java.util.HashMap   (line 284)
                    DUP
                    INVOKESPECIAL java.util.HashMap.<init> ()V
                    ASTORE_2     // Ljava/util/Map; typeVariableMap
                    ALOAD_0     // Ljava/lang/Class; clazz   (line 287)
                    INVOKEVIRTUAL java.lang.Class.getGenericInterfaces ()[Ljava/lang/reflect/Type;
                    ALOAD_2     // Ljava/util/Map; typeVariableMap
                    INVOKESTATIC org.springframework.core.GenericTypeResolver.extractTypeVariablesFromGenericInterfaces ([Ljava/lang/reflect/Type;Ljava/util/Map;)V
                    ALOAD_0     // Ljava/lang/Class; clazz   (line 290)
                    INVOKEVIRTUAL java.lang.Class.getGenericSuperclass ()Ljava/lang/reflect/Type;
                    ASTORE_3
                    ALOAD_0     // Ljava/lang/Class; clazz   (line 291)
                    INVOKEVIRTUAL java.lang.Class.getSuperclass ()Ljava/lang/Class;
                    ASTORE 4
                    GOTO L4   (line 292)
                L2: ALOAD_3     // Ljava/lang/reflect/Type; genericType   (line 293)
                    INSTANCEOF java.lang.reflect.ParameterizedType
                    IFEQ L3
                    ALOAD_3     // Ljava/lang/reflect/Type; genericType   (line 294)
                    CHECKCAST java.lang.reflect.ParameterizedType
                    ASTORE 5
                    ALOAD 5     // Ljava/lang/reflect/ParameterizedType; pt   (line 295)
                    ALOAD_2     // Ljava/util/Map; typeVariableMap
                    INVOKESTATIC org.springframework.core.GenericTypeResolver.populateTypeMapFromParameterizedType (Ljava/lang/reflect/ParameterizedType;Ljava/util/Map;)V
                L3: ALOAD 4     // Ljava/lang/Class; type   (line 297)
                    INVOKEVIRTUAL java.lang.Class.getGenericInterfaces ()[Ljava/lang/reflect/Type;
                    ALOAD_2     // Ljava/util/Map; typeVariableMap
                    INVOKESTATIC org.springframework.core.GenericTypeResolver.extractTypeVariablesFromGenericInterfaces ([Ljava/lang/reflect/Type;Ljava/util/Map;)V
                    ALOAD 4     // Ljava/lang/Class; type   (line 298)
                    INVOKEVIRTUAL java.lang.Class.getGenericSuperclass ()Ljava/lang/reflect/Type;
                    ASTORE_3     // Ljava/lang/reflect/Type; genericType
                    ALOAD 4     // Ljava/lang/Class; type   (line 299)
                    INVOKEVIRTUAL java.lang.Class.getSuperclass ()Ljava/lang/Class;
                    ASTORE 4     // Ljava/lang/Class; type
                L4: ALOAD 4     // Ljava/lang/Class; type   (line 292)
                    IFNULL L5
                    LDC java.lang.Object
                    ALOAD 4     // Ljava/lang/Class; type
                    INVOKEVIRTUAL java.lang.Object.equals (Ljava/lang/Object;)Z
                    IFEQ L2
                L5: ALOAD_0     // Ljava/lang/Class; clazz   (line 303)
                    ASTORE 4     // Ljava/lang/Class; type
                    GOTO L8   (line 304)
                L6: ALOAD 4     // Ljava/lang/Class; type   (line 305)
                    INVOKEVIRTUAL java.lang.Class.getGenericSuperclass ()Ljava/lang/reflect/Type;
                    ASTORE_3     // Ljava/lang/reflect/Type; genericType
                    ALOAD_3     // Ljava/lang/reflect/Type; genericType   (line 306)
                    INSTANCEOF java.lang.reflect.ParameterizedType
                    IFEQ L7
                    ALOAD_3     // Ljava/lang/reflect/Type; genericType   (line 307)
                    CHECKCAST java.lang.reflect.ParameterizedType
                    ASTORE 5
                    ALOAD 5     // Ljava/lang/reflect/ParameterizedType; pt   (line 308)
                    ALOAD_2     // Ljava/util/Map; typeVariableMap
                    INVOKESTATIC org.springframework.core.GenericTypeResolver.populateTypeMapFromParameterizedType (Ljava/lang/reflect/ParameterizedType;Ljava/util/Map;)V
                L7: ALOAD 4     // Ljava/lang/Class; type   (line 310)
                    INVOKEVIRTUAL java.lang.Class.getEnclosingClass ()Ljava/lang/Class;
                    ASTORE 4     // Ljava/lang/Class; type
                L8: ALOAD 4     // Ljava/lang/Class; type   (line 304)
                    INVOKEVIRTUAL java.lang.Class.isMemberClass ()Z
                    IFNE L6
                    GETSTATIC org.springframework.core.GenericTypeResolver.typeVariableCache Ljava/util/Map;   (line 313)
                    ALOAD_0     // Ljava/lang/Class; clazz
                    NEW java.lang.ref.WeakReference
                    DUP
                    ALOAD_2     // Ljava/util/Map; typeVariableMap
                    INVOKESPECIAL java.lang.ref.WeakReference.<init> (Ljava/lang/Object;)V
                    INVOKEINTERFACE java.util.Map.put (Ljava/lang/Object;Ljava/lang/Object;)Ljava/lang/Object;
                    POP
                L9: ALOAD_2     // Ljava/util/Map; typeVariableMap   (line 316)
                    ARETURN
  end public static java.util.Map getTypeVariableMap(Class)

  static java.lang.reflect.Type extractBoundForTypeVariable(java.lang.reflect.TypeVariable):
                    ALOAD_0     // Ljava/lang/reflect/TypeVariable; typeVariable   (line 323)
                    INVOKEINTERFACE java.lang.reflect.TypeVariable.getBounds ()[Ljava/lang/reflect/Type;
                    ASTORE_1
                    ALOAD_1     // [Ljava/lang/reflect/Type; bounds   (line 324)
                    ARRAYLENGTH
                    IFNE L0
                    LDC java.lang.Object   (line 325)
                    ARETURN
                L0: ALOAD_1     // [Ljava/lang/reflect/Type; bounds   (line 327)
                    ICONST_0
                    AALOAD
                    ASTORE_2
                    ALOAD_2     // Ljava/lang/reflect/Type; bound   (line 328)
                    INSTANCEOF java.lang.reflect.TypeVariable
                    IFEQ L1
                    ALOAD_2     // Ljava/lang/reflect/Type; bound   (line 329)
                    CHECKCAST java.lang.reflect.TypeVariable
                    INVOKESTATIC org.springframework.core.GenericTypeResolver.extractBoundForTypeVariable (Ljava/lang/reflect/TypeVariable;)Ljava/lang/reflect/Type;
                    ASTORE_2     // Ljava/lang/reflect/Type; bound
                L1: ALOAD_2     // Ljava/lang/reflect/Type; bound   (line 331)
                    ARETURN
  end static java.lang.reflect.Type extractBoundForTypeVariable(java.lang.reflect.TypeVariable)

  private static void extractTypeVariablesFromGenericInterfaces(java.lang.reflect.Type[], java.util.Map):
                    ALOAD_0     // [Ljava/lang/reflect/Type; genericInterfaces   (line 335)
                    DUP
                    ASTORE 5
                    ARRAYLENGTH
                    ISTORE 4
                    ICONST_0
                    ISTORE_3
                    GOTO L3
                L0: ALOAD 5
                    ILOAD_3
                    AALOAD
                    ASTORE_2
                    ALOAD_2     // Ljava/lang/reflect/Type; genericInterface   (line 336)
                    INSTANCEOF java.lang.reflect.ParameterizedType
                    IFEQ L1
                    ALOAD_2     // Ljava/lang/reflect/Type; genericInterface   (line 337)
                    CHECKCAST java.lang.reflect.ParameterizedType
                    ASTORE 6
                    ALOAD 6     // Ljava/lang/reflect/ParameterizedType; pt   (line 338)
                    ALOAD_1     // Ljava/util/Map; typeVariableMap
                    INVOKESTATIC org.springframework.core.GenericTypeResolver.populateTypeMapFromParameterizedType (Ljava/lang/reflect/ParameterizedType;Ljava/util/Map;)V
                    ALOAD 6     // Ljava/lang/reflect/ParameterizedType; pt   (line 339)
                    INVOKEINTERFACE java.lang.reflect.ParameterizedType.getRawType ()Ljava/lang/reflect/Type;
                    INSTANCEOF java.lang.Class
                    IFEQ L2
                    ALOAD 6     // Ljava/lang/reflect/ParameterizedType; pt   (line 341)
                    INVOKEINTERFACE java.lang.reflect.ParameterizedType.getRawType ()Ljava/lang/reflect/Type;
                    CHECKCAST java.lang.Class
                    INVOKEVIRTUAL java.lang.Class.getGenericInterfaces ()[Ljava/lang/reflect/Type;
                    ALOAD_1     // Ljava/util/Map; typeVariableMap
                    INVOKESTATIC org.springframework.core.GenericTypeResolver.extractTypeVariablesFromGenericInterfaces ([Ljava/lang/reflect/Type;Ljava/util/Map;)V   (line 340)
                    GOTO L2
                L1: ALOAD_2     // Ljava/lang/reflect/Type; genericInterface   (line 344)
                    INSTANCEOF java.lang.Class
                    IFEQ L2
                    ALOAD_2     // Ljava/lang/reflect/Type; genericInterface   (line 346)
                    CHECKCAST java.lang.Class
                    INVOKEVIRTUAL java.lang.Class.getGenericInterfaces ()[Ljava/lang/reflect/Type;
                    ALOAD_1     // Ljava/util/Map; typeVariableMap
                    INVOKESTATIC org.springframework.core.GenericTypeResolver.extractTypeVariablesFromGenericInterfaces ([Ljava/lang/reflect/Type;Ljava/util/Map;)V   (line 345)
                L2: IINC_3 1   (line 335)
                L3: ILOAD_3
                    ILOAD 4
                    IF_ICMPLT L0
                    RETURN   (line 349)
  end private static void extractTypeVariablesFromGenericInterfaces(java.lang.reflect.Type[], java.util.Map)

  private static void populateTypeMapFromParameterizedType(java.lang.reflect.ParameterizedType, java.util.Map):
                    ALOAD_0     // Ljava/lang/reflect/ParameterizedType; type   (line 368)
                    INVOKEINTERFACE java.lang.reflect.ParameterizedType.getRawType ()Ljava/lang/reflect/Type;
                    INSTANCEOF java.lang.Class
                    IFEQ L7
                    ALOAD_0     // Ljava/lang/reflect/ParameterizedType; type   (line 369)
                    INVOKEINTERFACE java.lang.reflect.ParameterizedType.getActualTypeArguments ()[Ljava/lang/reflect/Type;
                    ASTORE_2
                    ALOAD_0     // Ljava/lang/reflect/ParameterizedType; type   (line 370)
                    INVOKEINTERFACE java.lang.reflect.ParameterizedType.getRawType ()Ljava/lang/reflect/Type;
                    CHECKCAST java.lang.Class
                    INVOKEVIRTUAL java.lang.Class.getTypeParameters ()[Ljava/lang/reflect/TypeVariable;
                    ASTORE_3
                    ICONST_0   (line 371)
                    ISTORE 4
                    GOTO L6
                L0: ALOAD_2     // [Ljava/lang/reflect/Type; actualTypeArguments   (line 372)
                    ILOAD 4     // I i
                    AALOAD
                    ASTORE 5
                    ALOAD_3     // [Ljava/lang/reflect/TypeVariable; typeVariables   (line 373)
                    ILOAD 4     // I i
                    AALOAD
                    ASTORE 6
                    ALOAD 5     // Ljava/lang/reflect/Type; actualTypeArgument   (line 374)
                    INSTANCEOF java.lang.Class
                    IFEQ L1
                    ALOAD_1     // Ljava/util/Map; typeVariableMap   (line 375)
                    ALOAD 6     // Ljava/lang/reflect/TypeVariable; variable
                    ALOAD 5     // Ljava/lang/reflect/Type; actualTypeArgument
                    INVOKEINTERFACE java.util.Map.put (Ljava/lang/Object;Ljava/lang/Object;)Ljava/lang/Object;
                    POP
                    GOTO L5
                L1: ALOAD 5     // Ljava/lang/reflect/Type; actualTypeArgument   (line 377)
                    INSTANCEOF java.lang.reflect.GenericArrayType
                    IFEQ L2
                    ALOAD_1     // Ljava/util/Map; typeVariableMap   (line 378)
                    ALOAD 6     // Ljava/lang/reflect/TypeVariable; variable
                    ALOAD 5     // Ljava/lang/reflect/Type; actualTypeArgument
                    INVOKEINTERFACE java.util.Map.put (Ljava/lang/Object;Ljava/lang/Object;)Ljava/lang/Object;
                    POP
                    GOTO L5
                L2: ALOAD 5     // Ljava/lang/reflect/Type; actualTypeArgument   (line 380)
                    INSTANCEOF java.lang.reflect.ParameterizedType
                    IFEQ L3
                    ALOAD_1     // Ljava/util/Map; typeVariableMap   (line 381)
                    ALOAD 6     // Ljava/lang/reflect/TypeVariable; variable
                    ALOAD 5     // Ljava/lang/reflect/Type; actualTypeArgument
                    INVOKEINTERFACE java.util.Map.put (Ljava/lang/Object;Ljava/lang/Object;)Ljava/lang/Object;
                    POP
                    GOTO L5
                L3: ALOAD 5     // Ljava/lang/reflect/Type; actualTypeArgument   (line 383)
                    INSTANCEOF java.lang.reflect.TypeVariable
                    IFEQ L5
                    ALOAD 5     // Ljava/lang/reflect/Type; actualTypeArgument   (line 386)
                    CHECKCAST java.lang.reflect.TypeVariable
                    ASTORE 7
                    ALOAD_1     // Ljava/util/Map; typeVariableMap   (line 387)
                    ALOAD 7     // Ljava/lang/reflect/TypeVariable; typeVariableArgument
                    INVOKEINTERFACE java.util.Map.get (Ljava/lang/Object;)Ljava/lang/Object;
                    CHECKCAST java.lang.reflect.Type
                    ASTORE 8
                    ALOAD 8     // Ljava/lang/reflect/Type; resolvedType   (line 388)
                    IFNONNULL L4
                    ALOAD 7     // Ljava/lang/reflect/TypeVariable; typeVariableArgument   (line 389)
                    INVOKESTATIC org.springframework.core.GenericTypeResolver.extractBoundForTypeVariable (Ljava/lang/reflect/TypeVariable;)Ljava/lang/reflect/Type;
                    ASTORE 8     // Ljava/lang/reflect/Type; resolvedType
                L4: ALOAD_1     // Ljava/util/Map; typeVariableMap   (line 391)
                    ALOAD 6     // Ljava/lang/reflect/TypeVariable; variable
                    ALOAD 8     // Ljava/lang/reflect/Type; resolvedType
                    INVOKEINTERFACE java.util.Map.put (Ljava/lang/Object;Ljava/lang/Object;)Ljava/lang/Object;
                    POP
                L5: IINC 4 1     // I i   (line 371)
                L6: ILOAD 4     // I i
                    ALOAD_2     // [Ljava/lang/reflect/Type; actualTypeArguments
                    ARRAYLENGTH
                    IF_ICMPLT L0
                L7: RETURN   (line 395)
  end private static void populateTypeMapFromParameterizedType(java.lang.reflect.ParameterizedType, java.util.Map)
end public abstract class org.springframework.core.GenericTypeResolver

	at org.aspectj.bridge.MessageWriter.handleMessage(MessageWriter.java:47)
	at org.aspectj.weaver.tools.WeavingAdaptor$WeavingAdaptorMessageWriter.handleMessage(WeavingAdaptor.java:665)
	at org.aspectj.weaver.tools.WeavingAdaptor$WeavingAdaptorMessageHolder.handleMessage(WeavingAdaptor.java:615)
	at org.aspectj.weaver.bcel.BcelWeaver.weave(BcelWeaver.java:1752)
	at org.aspectj.weaver.bcel.BcelWeaver.weaveWithoutDump(BcelWeaver.java:1694)
	at org.aspectj.weaver.bcel.BcelWeaver.weaveAndNotify(BcelWeaver.java:1464)
	at org.aspectj.weaver.bcel.BcelWeaver.weave(BcelWeaver.java:1273)
	at org.aspectj.weaver.tools.WeavingAdaptor.getWovenBytes(WeavingAdaptor.java:394)
	at org.aspectj.weaver.tools.WeavingAdaptor.weaveClass(WeavingAdaptor.java:281)
	at org.aspectj.weaver.loadtime.Aj.preProcess(Aj.java:95)
	at org.aspectj.weaver.loadtime.ClassPreProcessorAgentAdapter.transform(ClassPreProcessorAgentAdapter.java:52)
	at sun.instrument.TransformerManager.transform(TransformerManager.java:188)
	at sun.instrument.InstrumentationImpl.transform(InstrumentationImpl.java:428)
	at java.lang.ClassLoader.defineClass1(Native Method)
	at java.lang.ClassLoader.defineClass(ClassLoader.java:760)
	at java.security.SecureClassLoader.defineClass(SecureClassLoader.java:142)
	at java.net.URLClassLoader.defineClass(URLClassLoader.java:467)
	at java.net.URLClassLoader.access$100(URLClassLoader.java:73)
	at java.net.URLClassLoader$1.run(URLClassLoader.java:368)
	at java.net.URLClassLoader$1.run(URLClassLoader.java:362)
	at java.security.AccessController.doPrivileged(Native Method)
	at java.net.URLClassLoader.findClass(URLClassLoader.java:361)
	at java.lang.ClassLoader.loadClass(ClassLoader.java:424)
	at sun.misc.Launcher$AppClassLoader.loadClass(Launcher.java:331)
	at java.lang.ClassLoader.loadClass(ClassLoader.java:357)
	at org.springframework.core.convert.support.GenericConversionService.getRequiredTypeInfo(GenericConversionService.java:275)
	at org.springframework.core.convert.support.GenericConversionService.addConverter(GenericConversionService.java:93)
	at org.springframework.core.convert.support.DefaultConversionService.addScalarConverters(DefaultConversionService.java:61)
	at org.springframework.core.convert.support.DefaultConversionService.addDefaultConverters(DefaultConversionService.java:53)
	at org.springframework.core.convert.support.DefaultConversionService.<init>(DefaultConversionService.java:42)
	at org.springframework.core.env.AbstractPropertyResolver.<init>(AbstractPropertyResolver.java:44)
	at org.springframework.core.env.PropertySourcesPropertyResolver.<init>(PropertySourcesPropertyResolver.java:42)
	at org.springframework.core.env.AbstractEnvironment.<init>(AbstractEnvironment.java:101)
	at org.springframework.core.env.StandardEnvironment.<init>(StandardEnvironment.java:54)
	at org.springframework.context.support.AbstractApplicationContext.createEnvironment(AbstractApplicationContext.java:432)
	at org.springframework.context.support.AbstractApplicationContext.<init>(AbstractApplicationContext.java:227)
	at org.springframework.context.support.AbstractRefreshableApplicationContext.<init>(AbstractRefreshableApplicationContext.java:90)
	at org.springframework.context.support.AbstractRefreshableConfigApplicationContext.<init>(AbstractRefreshableConfigApplicationContext.java:59)
	at org.springframework.context.support.AbstractXmlApplicationContext.<init>(AbstractXmlApplicationContext.java:61)
	at org.springframework.context.support.ClassPathXmlApplicationContext.<init>(ClassPathXmlApplicationContext.java:136)
	at org.springframework.context.support.ClassPathXmlApplicationContext.<init>(ClassPathXmlApplicationContext.java:83)
	at com.curso.spring.springioc0007.Main.init(Main.java:29)
	at com.curso.spring.springioc0007.Main.main(Main.java:24)
---- System Properties ---
java.runtime.name=Java(TM) SE Runtime Environment
sun.boot.library.path=C:\Program Files\Java\jdk1.8.0_72\jre\bin
java.vm.version=25.72-b15
java.vm.vendor=Oracle Corporation
java.vendor.url=http://java.oracle.com/
path.separator=;
java.vm.name=Java HotSpot(TM) 64-Bit Server VM
file.encoding.pkg=sun.io
user.country=ES
user.script=
sun.java.launcher=SUN_STANDARD
sun.os.patch.level=
java.vm.specification.name=Java Virtual Machine Specification
user.dir=C:\Users\usuario\git\spring\aspectos\Ejemplos Relacionados\SpringIoC0007Maven
java.runtime.version=1.8.0_72-b15
java.awt.graphicsenv=sun.awt.Win32GraphicsEnvironment
java.endorsed.dirs=C:\Program Files\Java\jdk1.8.0_72\jre\lib\endorsed
os.arch=amd64
java.io.tmpdir=C:\Users\usuario\AppData\Local\Temp\
line.separator=

java.vm.specification.vendor=Oracle Corporation
user.variant=
os.name=Windows 10
sun.jnu.encoding=Cp1252
java.library.path=C:\Program Files\Java\jdk1.8.0_72\bin;C:\WINDOWS\Sun\Java\bin;C:\WINDOWS\system32;C:\WINDOWS;C:\ProgramData\Oracle\Java\javapath;C:\Program Files\CollabNet\Subversion Client;E:\bin\Sencha\Cmd\5.1.3.61;C:\Users\usuario\bin\Sencha\Cmd\5.1.3.61;C:\Program Files (x86)\Intel\iCLS Client\;C:\Program Files\Intel\iCLS Client\;C:\WINDOWS\system32;C:\WINDOWS;C:\WINDOWS\System32\Wbem;C:\WINDOWS\System32\WindowsPowerShell\v1.0\;C:\Program Files\Intel\Intel(R) Management Engine Components\DAL;C:\Program Files\Intel\Intel(R) Management Engine Components\IPT;C:\Program Files (x86)\Intel\Intel(R) Management Engine Components\DAL;C:\Program Files (x86)\Intel\Intel(R) Management Engine Components\IPT;C:\Program Files (x86)\Intel\OpenCL SDK\3.0\bin\x86;C:\Program Files (x86)\Intel\OpenCL SDK\3.0\bin\x64;C:\Program Files (x86)\sbt\\bin;C:\Program Files (x86)\Heroku\bin;C:\Program Files (x86)\git\cmd;C:\Program Files (x86)\QuickTime\QTSystem\;C:\HashiCorp\Vagrant\bin;C:\Program Files (x86)\scala\bin;C:\Program Files\nodejs\;C:\Users\usuario\AppData\Local\.meteor\;C:\Users\usuario\AppData\Roaming\npm;.
java.specification.name=Java Platform API Specification
java.class.version=52.0
sun.management.compiler=HotSpot 64-Bit Tiered Compilers
os.version=10.0
user.home=C:\Users\usuario
user.timezone=Europe/Paris
java.awt.printerjob=sun.awt.windows.WPrinterJob
file.encoding=Cp1252
java.specification.version=1.8
java.class.path=C:\Users\usuario\git\spring\aspectos\Ejemplos Relacionados\SpringIoC0007Maven\target\classes;C:\Users\usuario\.m2\repository\org\springframework\spring-context\3.1.2.RELEASE\spring-context-3.1.2.RELEASE.jar;C:\Users\usuario\.m2\repository\org\springframework\spring-aop\3.1.2.RELEASE\spring-aop-3.1.2.RELEASE.jar;C:\Users\usuario\.m2\repository\aopalliance\aopalliance\1.0\aopalliance-1.0.jar;C:\Users\usuario\.m2\repository\org\springframework\spring-beans\3.1.2.RELEASE\spring-beans-3.1.2.RELEASE.jar;C:\Users\usuario\.m2\repository\org\springframework\spring-core\3.1.2.RELEASE\spring-core-3.1.2.RELEASE.jar;C:\Users\usuario\.m2\repository\commons-logging\commons-logging\1.1.1\commons-logging-1.1.1.jar;C:\Users\usuario\.m2\repository\org\springframework\spring-expression\3.1.2.RELEASE\spring-expression-3.1.2.RELEASE.jar;C:\Users\usuario\.m2\repository\org\springframework\spring-asm\3.1.2.RELEASE\spring-asm-3.1.2.RELEASE.jar;C:\Users\usuario\.m2\repository\org\springframework\spring-aspects\3.1.2.RELEASE\spring-aspects-3.1.2.RELEASE.jar;C:\Users\usuario\.m2\repository\org\springframework\spring-context-support\3.1.2.RELEASE\spring-context-support-3.1.2.RELEASE.jar;.\..\aspectjweaver.jar
user.name=usuario
java.vm.specification.version=1.8
sun.java.command=com.curso.spring.springioc0007.Main
java.home=C:\Program Files\Java\jdk1.8.0_72\jre
sun.arch.data.model=64
user.language=es
java.specification.vendor=Oracle Corporation
awt.toolkit=sun.awt.windows.WToolkit
java.vm.info=mixed mode
java.version=1.8.0_72
java.ext.dirs=C:\Program Files\Java\jdk1.8.0_72\jre\lib\ext;C:\WINDOWS\Sun\Java\lib\ext
sun.boot.class.path=C:\Program Files\Java\jdk1.8.0_72\jre\lib\resources.jar;C:\Program Files\Java\jdk1.8.0_72\jre\lib\rt.jar;C:\Program Files\Java\jdk1.8.0_72\jre\lib\sunrsasign.jar;C:\Program Files\Java\jdk1.8.0_72\jre\lib\jsse.jar;C:\Program Files\Java\jdk1.8.0_72\jre\lib\jce.jar;C:\Program Files\Java\jdk1.8.0_72\jre\lib\charsets.jar;C:\Program Files\Java\jdk1.8.0_72\jre\lib\jfr.jar;C:\Program Files\Java\jdk1.8.0_72\jre\classes
java.vendor=Oracle Corporation
file.separator=\
java.vendor.url.bug=http://bugreport.sun.com/bugreport/
sun.io.unicode.encoding=UnicodeLittle
sun.cpu.endian=little
sun.desktop=windows
sun.cpu.isalist=amd64
---- Command Line ---
Empty
---- Full Classpath ---
Empty
---- Compiler Messages ---
Empty
---- org.aspectj.weaver.ltw.LTWWorld@28c97a5 ----
Class loader:
sun.misc.Launcher$AppClassLoader@18b4aac2
Class loader parent:
sun.misc.Launcher$ExtClassLoader@722c41f4
Shadow mungers:
(around(extraFlags: 3): ((((((((((within(@org.springframework.cache.annotation.CacheEvict *) && execution(public * @org.springframework.cache.annotation.CacheEvict *.*(..))) && this(BindingTypePattern(java.lang.Object, 0))) && persingleton(org.springframework.cache.aspectj.AnnotationCacheAspect)) || (((within(@org.springframework.cache.annotation.Caching *) && execution(public * @org.springframework.cache.annotation.Caching *.*(..))) && this(BindingTypePattern(java.lang.Object, 0))) && persingleton(org.springframework.cache.aspectj.AnnotationCacheAspect))) || (((within(@org.springframework.cache.annotation.CachePut *) && execution(public * @org.springframework.cache.annotation.CachePut *.*(..))) && this(BindingTypePattern(java.lang.Object, 0))) && persingleton(org.springframework.cache.aspectj.AnnotationCacheAspect))) || (((within(@org.springframework.cache.annotation.Cacheable *) && execution(public * @org.springframework.cache.annotation.Cacheable *.*(..))) && this(BindingTypePattern(java.lang.Object, 0))) && persingleton(org.springframework.cache.aspectj.AnnotationCacheAspect))) || ((execution(@org.springframework.cache.annotation.Caching * *(..)) && this(BindingTypePattern(java.lang.Object, 0))) && persingleton(org.springframework.cache.aspectj.AnnotationCacheAspect))) || ((execution(@org.springframework.cache.annotation.Cacheable * *(..)) && this(BindingTypePattern(java.lang.Object, 0))) && persingleton(org.springframework.cache.aspectj.AnnotationCacheAspect))) || ((execution(@org.springframework.cache.annotation.CacheEvict * *(..)) && this(BindingTypePattern(java.lang.Object, 0))) && persingleton(org.springframework.cache.aspectj.AnnotationCacheAspect))) || ((execution(@org.springframework.cache.annotation.CachePut * *(..)) && this(BindingTypePattern(java.lang.Object, 0))) && persingleton(org.springframework.cache.aspectj.AnnotationCacheAspect)))->java.lang.Object org.springframework.cache.aspectj.AbstractCacheAspect.ajc$around$org_springframework_cache_aspectj_AbstractCacheAspect$1$2bc714b5(java.lang.Object, org.aspectj.runtime.internal.AroundClosure, org.aspectj.lang.JoinPoint))
(around(extraFlags: 5): ((execution(@org.springframework.scheduling.annotation.Async (void || java.util.concurrent.Future+) *(..)) && persingleton(org.springframework.scheduling.aspectj.AnnotationAsyncExecutionAspect)) || (execution((void || java.util.concurrent.Future+) @org.springframework.scheduling.annotation.Async *.*(..)) && persingleton(org.springframework.scheduling.aspectj.AnnotationAsyncExecutionAspect)))->java.lang.Object org.springframework.scheduling.aspectj.AbstractAsyncExecutionAspect.ajc$around$org_springframework_scheduling_aspectj_AbstractAsyncExecutionAspect$1$6c004c3e(org.aspectj.runtime.internal.AroundClosure, org.aspectj.lang.JoinPoint$StaticPart))
org.aspectj.weaver.Checker@5abff562
org.aspectj.weaver.Checker@12140c1d
(before(extraFlags: 4): ((((within(@org.springframework.transaction.annotation.Transactional *) && execution(public * @org.springframework.transaction.annotation.Transactional *.*(..))) && this(BindingTypePattern(java.lang.Object, 0))) && persingleton(org.springframework.transaction.aspectj.AnnotationTransactionAspect)) || ((execution(@org.springframework.transaction.annotation.Transactional * *(..)) && this(BindingTypePattern(java.lang.Object, 0))) && persingleton(org.springframework.transaction.aspectj.AnnotationTransactionAspect)))->void org.springframework.transaction.aspectj.AbstractTransactionAspect.ajc$before$org_springframework_transaction_aspectj_AbstractTransactionAspect$1$2a73e96c(java.lang.Object, org.aspectj.lang.JoinPoint$StaticPart))
(afterThrowing(extraFlags: 1): ((((within(@org.springframework.transaction.annotation.Transactional *) && execution(public * @org.springframework.transaction.annotation.Transactional *.*(..))) && this(BindingTypePattern(java.lang.Object, 0))) && persingleton(org.springframework.transaction.aspectj.AnnotationTransactionAspect)) || ((execution(@org.springframework.transaction.annotation.Transactional * *(..)) && this(BindingTypePattern(java.lang.Object, 0))) && persingleton(org.springframework.transaction.aspectj.AnnotationTransactionAspect)))->void org.springframework.transaction.aspectj.AbstractTransactionAspect.ajc$afterThrowing$org_springframework_transaction_aspectj_AbstractTransactionAspect$2$2a73e96c(java.lang.Object, java.lang.Throwable))
(afterReturning: ((((within(@org.springframework.transaction.annotation.Transactional *) && execution(public * @org.springframework.transaction.annotation.Transactional *.*(..))) && this(BindingTypePattern(java.lang.Object, 0))) && persingleton(org.springframework.transaction.aspectj.AnnotationTransactionAspect)) || ((execution(@org.springframework.transaction.annotation.Transactional * *(..)) && this(BindingTypePattern(java.lang.Object, 0))) && persingleton(org.springframework.transaction.aspectj.AnnotationTransactionAspect)))->void org.springframework.transaction.aspectj.AbstractTransactionAspect.ajc$afterReturning$org_springframework_transaction_aspectj_AbstractTransactionAspect$3$2a73e96c(java.lang.Object))
(after: ((((within(@org.springframework.transaction.annotation.Transactional *) && execution(public * @org.springframework.transaction.annotation.Transactional *.*(..))) && this(BindingTypePattern(java.lang.Object, 0))) && persingleton(org.springframework.transaction.aspectj.AnnotationTransactionAspect)) || ((execution(@org.springframework.transaction.annotation.Transactional * *(..)) && this(BindingTypePattern(java.lang.Object, 0))) && persingleton(org.springframework.transaction.aspectj.AnnotationTransactionAspect)))->void org.springframework.transaction.aspectj.AbstractTransactionAspect.ajc$after$org_springframework_transaction_aspectj_AbstractTransactionAspect$4$2a73e96c(java.lang.Object))
(before: (((((initialization(org.springframework.beans.factory.aspectj.ConfigurableObject.new(..)) && initialization(org.springframework.beans.factory.aspectj.ConfigurableObject+.new(..))) && this(BindingTypePattern(java.lang.Object, 0))) && @this(org.springframework.beans.factory.annotation.Configurable)) && if(boolean org.springframework.beans.factory.aspectj.AnnotationBeanConfigurerAspect.ajc$if$bb0(org.springframework.beans.factory.annotation.Configurable))) && persingleton(org.springframework.beans.factory.aspectj.AnnotationBeanConfigurerAspect))->void org.springframework.beans.factory.aspectj.AbstractDependencyInjectionAspect.ajc$before$org_springframework_beans_factory_aspectj_AbstractDependencyInjectionAspect$1$e854fa65(java.lang.Object))
(afterReturning: (((((initialization(org.springframework.beans.factory.aspectj.ConfigurableObject+.new(..)) && this(BindingTypePattern(java.lang.Object, 0))) && @this(org.springframework.beans.factory.annotation.Configurable)) && !(@this(org.springframework.beans.factory.annotation.Configurable) && if(boolean org.springframework.beans.factory.aspectj.AnnotationBeanConfigurerAspect.ajc$if$bb0(org.springframework.beans.factory.annotation.Configurable)))) && if(boolean org.springframework.beans.factory.aspectj.AbstractDependencyInjectionAspect.ajc$if$6f1(org.aspectj.lang.JoinPoint))) && persingleton(org.springframework.beans.factory.aspectj.AnnotationBeanConfigurerAspect))->void org.springframework.beans.factory.aspectj.AbstractDependencyInjectionAspect.ajc$afterReturning$org_springframework_beans_factory_aspectj_AbstractDependencyInjectionAspect$2$1ea6722c(java.lang.Object))
(afterReturning: (((execution(java.lang.Object org.springframework.beans.factory.aspectj.AbstractInterfaceDrivenDependencyInjectionAspect$ConfigurableDeserializationSupport+.readResolve()) && this(BindingTypePattern(java.lang.Object, 0))) && @this(org.springframework.beans.factory.annotation.Configurable)) && persingleton(org.springframework.beans.factory.aspectj.AnnotationBeanConfigurerAspect))->void org.springframework.beans.factory.aspectj.AbstractDependencyInjectionAspect.ajc$afterReturning$org_springframework_beans_factory_aspectj_AbstractDependencyInjectionAspect$3$6aa27052(java.lang.Object))
Type mungers:
(BcelTypeMunger ResolvedTypeMunger(Method, java.lang.Object org.springframework.beans.factory.aspectj.AbstractInterfaceDrivenDependencyInjectionAspect$ConfigurableDeserializationSupport.readResolve()))
(BcelTypeMunger ExposeTypeMunger(java.lang.Object))
(BcelTypeMunger ExposeTypeMunger(java.lang.Object))
(BcelTypeMunger ExposeTypeMunger(java.lang.Object))
(BcelTypeMunger ExposeTypeMunger(org.springframework.beans.factory.aspectj.ConfigurableObject))
(BcelTypeMunger ExposeTypeMunger(org.springframework.beans.factory.aspectj.AbstractInterfaceDrivenDependencyInjectionAspect$ConfigurableDeserializationSupport))
Late Type mungers:
Empty
