---- AspectJ Properties ---
AspectJ Compiler 1.6.2 built on Saturday Oct 4, 2008 at 05:47:07 GMT
---- Dump Properties ---
Dump file: ajcore.20160604.114039.376.txt
Dump reason: org.aspectj.bridge.AbortException
Dump on exception: true
Dump at exit condition: abort
---- Exception Information ---
Message: abort trouble in: 
public class org.springframework.beans.factory.xml.BeansDtdResolver extends java.lang.Object implements org.xml.sax.EntityResolver:
  private static final String DTD_EXTENSION = ".dtd"
  private static final String[] DTD_NAMES
  private static final org.apache.commons.logging.Log logger
  static void <clinit>():
    staticinitialization(void org.springframework.beans.factory.xml.BeansDtdResolver.<clinit>())
    |               ICONST_2   (line 48)
    |               ANEWARRAY java.lang.String
    |               DUP
    |               ICONST_0
    |               LDC "spring-beans-2.0"
    |               AASTORE
    |               DUP
    |               ICONST_1
    |               LDC "spring-beans"
    |               AASTORE
    |               PUTSTATIC org.springframework.beans.factory.xml.BeansDtdResolver.DTD_NAMES [Ljava/lang/String;
    |               LDC org.springframework.beans.factory.xml.BeansDtdResolver   (line 50)
    |               INVOKESTATIC org.apache.commons.logging.LogFactory.getLog (Ljava/lang/Class;)Lorg/apache/commons/logging/Log;
    |               PUTSTATIC org.springframework.beans.factory.xml.BeansDtdResolver.logger Lorg/apache/commons/logging/Log;
    |               RETURN   (line 44)
    staticinitialization(void org.springframework.beans.factory.xml.BeansDtdResolver.<clinit>())
  end static void <clinit>()

  public void <init>():
                    ALOAD_0     // Lorg/springframework/beans/factory/xml/BeansDtdResolver; this   (line 44)
                    INVOKESPECIAL java.lang.Object.<init> ()V
    constructor-execution(void org.springframework.beans.factory.xml.BeansDtdResolver.<init>())
    |               RETURN
    constructor-execution(void org.springframework.beans.factory.xml.BeansDtdResolver.<init>())
  end public void <init>()

  public org.xml.sax.InputSource resolveEntity(String, String) throws java.io.IOException:
                    GETSTATIC org.springframework.beans.factory.xml.BeansDtdResolver.logger Lorg/apache/commons/logging/Log;   (line 54)
                    INVOKEINTERFACE org.apache.commons.logging.Log.isTraceEnabled ()Z
                    IFEQ L0
                    GETSTATIC org.springframework.beans.factory.xml.BeansDtdResolver.logger Lorg/apache/commons/logging/Log;   (line 55)
                    NEW java.lang.StringBuilder
                    DUP
                    LDC "Trying to resolve XML entity with public ID ["
                    INVOKESPECIAL java.lang.StringBuilder.<init> (Ljava/lang/String;)V
                    ALOAD_1     // Ljava/lang/String; publicId
                    INVOKEVIRTUAL java.lang.StringBuilder.append (Ljava/lang/String;)Ljava/lang/StringBuilder;
                    LDC "] and system ID ["   (line 56)
                    INVOKEVIRTUAL java.lang.StringBuilder.append (Ljava/lang/String;)Ljava/lang/StringBuilder;
                    ALOAD_2     // Ljava/lang/String; systemId
                    INVOKEVIRTUAL java.lang.StringBuilder.append (Ljava/lang/String;)Ljava/lang/StringBuilder;
                    LDC "]"
                    INVOKEVIRTUAL java.lang.StringBuilder.append (Ljava/lang/String;)Ljava/lang/StringBuilder;
                    INVOKEVIRTUAL java.lang.StringBuilder.toString ()Ljava/lang/String;
                    INVOKEINTERFACE org.apache.commons.logging.Log.trace (Ljava/lang/Object;)V   (line 55)
                L0: ALOAD_2     // Ljava/lang/String; systemId   (line 58)
                    IFNULL L6
                    ALOAD_2     // Ljava/lang/String; systemId
                    LDC ".dtd"
                    INVOKEVIRTUAL java.lang.String.endsWith (Ljava/lang/String;)Z
                    IFEQ L6
                    ALOAD_2     // Ljava/lang/String; systemId   (line 59)
                    LDC "/"
                    INVOKEVIRTUAL java.lang.String.lastIndexOf (Ljava/lang/String;)I
                    ISTORE_3
                    GETSTATIC org.springframework.beans.factory.xml.BeansDtdResolver.DTD_NAMES [Ljava/lang/String;   (line 60)
                    DUP
                    ASTORE 7
                    ARRAYLENGTH
                    ISTORE 6
                    ICONST_0
                    ISTORE 5
                    GOTO L5
                L1: ALOAD 7
                    ILOAD 5
                    AALOAD
                    ASTORE 4
                    ALOAD_2     // Ljava/lang/String; systemId   (line 61)
                    ALOAD 4     // Ljava/lang/String; DTD_NAME
                    INVOKEVIRTUAL java.lang.String.indexOf (Ljava/lang/String;)I
                    ISTORE 8
                    ILOAD 8     // I dtdNameStart   (line 62)
                    ILOAD_3     // I lastPathSeparator
                    IF_ICMPLE L4
                    ALOAD_2     // Ljava/lang/String; systemId   (line 63)
                    ILOAD 8     // I dtdNameStart
                    INVOKEVIRTUAL java.lang.String.substring (I)Ljava/lang/String;
                    ASTORE 9
                    GETSTATIC org.springframework.beans.factory.xml.BeansDtdResolver.logger Lorg/apache/commons/logging/Log;   (line 64)
                    INVOKEINTERFACE org.apache.commons.logging.Log.isTraceEnabled ()Z
                    IFEQ L2
                    GETSTATIC org.springframework.beans.factory.xml.BeansDtdResolver.logger Lorg/apache/commons/logging/Log;   (line 65)
                    NEW java.lang.StringBuilder
                    DUP
                    LDC "Trying to locate ["
                    INVOKESPECIAL java.lang.StringBuilder.<init> (Ljava/lang/String;)V
                    ALOAD 9     // Ljava/lang/String; dtdFile
                    INVOKEVIRTUAL java.lang.StringBuilder.append (Ljava/lang/String;)Ljava/lang/StringBuilder;
                    LDC "] in Spring jar"
                    INVOKEVIRTUAL java.lang.StringBuilder.append (Ljava/lang/String;)Ljava/lang/StringBuilder;
                    INVOKEVIRTUAL java.lang.StringBuilder.toString ()Ljava/lang/String;
                    INVOKEINTERFACE org.apache.commons.logging.Log.trace (Ljava/lang/Object;)V
    catch java.io.IOException -> E0
    |           L2: NEW org.springframework.core.io.ClassPathResource   (line 68)
    |               DUP
    |               ALOAD 9     // Ljava/lang/String; dtdFile
    |               ALOAD_0     // Lorg/springframework/beans/factory/xml/BeansDtdResolver; this
    |               INVOKEVIRTUAL java.lang.Object.getClass ()Ljava/lang/Class;
    |               INVOKESPECIAL org.springframework.core.io.ClassPathResource.<init> (Ljava/lang/String;Ljava/lang/Class;)V
    |               ASTORE 10
    |               NEW org.xml.sax.InputSource   (line 69)
    |               DUP
    |               ALOAD 10     // Lorg/springframework/core/io/Resource; resource
    |               INVOKEINTERFACE org.springframework.core.io.Resource.getInputStream ()Ljava/io/InputStream;
    |               INVOKESPECIAL org.xml.sax.InputSource.<init> (Ljava/io/InputStream;)V
    |               ASTORE 11
    |               ALOAD 11     // Lorg/xml/sax/InputSource; source   (line 70)
    |               ALOAD_1     // Ljava/lang/String; publicId
    |               INVOKEVIRTUAL org.xml.sax.InputSource.setPublicId (Ljava/lang/String;)V
    |               ALOAD 11     // Lorg/xml/sax/InputSource; source   (line 71)
    |               ALOAD_2     // Ljava/lang/String; systemId
    |               INVOKEVIRTUAL org.xml.sax.InputSource.setSystemId (Ljava/lang/String;)V
    |               GETSTATIC org.springframework.beans.factory.xml.BeansDtdResolver.logger Lorg/apache/commons/logging/Log;   (line 72)
    |               INVOKEINTERFACE org.apache.commons.logging.Log.isDebugEnabled ()Z
    |               IFEQ L3
    |               GETSTATIC org.springframework.beans.factory.xml.BeansDtdResolver.logger Lorg/apache/commons/logging/Log;   (line 73)
    |               NEW java.lang.StringBuilder
    |               DUP
    |               LDC "Found beans DTD ["
    |               INVOKESPECIAL java.lang.StringBuilder.<init> (Ljava/lang/String;)V
    |               ALOAD_2     // Ljava/lang/String; systemId
    |               INVOKEVIRTUAL java.lang.StringBuilder.append (Ljava/lang/String;)Ljava/lang/StringBuilder;
    |               LDC "] in classpath: "
    |               INVOKEVIRTUAL java.lang.StringBuilder.append (Ljava/lang/String;)Ljava/lang/StringBuilder;
    |               ALOAD 9     // Ljava/lang/String; dtdFile
    |               INVOKEVIRTUAL java.lang.StringBuilder.append (Ljava/lang/String;)Ljava/lang/StringBuilder;
    |               INVOKEVIRTUAL java.lang.StringBuilder.toString ()Ljava/lang/String;
    |               INVOKEINTERFACE org.apache.commons.logging.Log.debug (Ljava/lang/Object;)V
    |           L3: ALOAD 11     // Lorg/xml/sax/InputSource; source   (line 75)
    catch java.io.IOException -> E0
                    ARETURN
                E0: ASTORE 10   (line 77)
                    GETSTATIC org.springframework.beans.factory.xml.BeansDtdResolver.logger Lorg/apache/commons/logging/Log;   (line 78)
                    INVOKEINTERFACE org.apache.commons.logging.Log.isDebugEnabled ()Z
                    IFEQ L4
                    GETSTATIC org.springframework.beans.factory.xml.BeansDtdResolver.logger Lorg/apache/commons/logging/Log;   (line 79)
                    NEW java.lang.StringBuilder
                    DUP
                    LDC "Could not resolve beans DTD ["
                    INVOKESPECIAL java.lang.StringBuilder.<init> (Ljava/lang/String;)V
                    ALOAD_2     // Ljava/lang/String; systemId
                    INVOKEVIRTUAL java.lang.StringBuilder.append (Ljava/lang/String;)Ljava/lang/StringBuilder;
                    LDC "]: not found in class path"
                    INVOKEVIRTUAL java.lang.StringBuilder.append (Ljava/lang/String;)Ljava/lang/StringBuilder;
                    INVOKEVIRTUAL java.lang.StringBuilder.toString ()Ljava/lang/String;
                    ALOAD 10     // Ljava/io/IOException; ex
                    INVOKEINTERFACE org.apache.commons.logging.Log.debug (Ljava/lang/Object;Ljava/lang/Throwable;)V
                L4: IINC 5 1   (line 60)
                L5: ILOAD 5
                    ILOAD 6
                    IF_ICMPLT L1
                L6: ACONST_NULL   (line 88)
                    ARETURN
  end public org.xml.sax.InputSource resolveEntity(String, String) throws java.io.IOException

  public String toString():
                    NEW java.lang.StringBuilder   (line 94)
                    DUP
                    LDC "EntityResolver for DTDs "
                    INVOKESPECIAL java.lang.StringBuilder.<init> (Ljava/lang/String;)V
                    GETSTATIC org.springframework.beans.factory.xml.BeansDtdResolver.DTD_NAMES [Ljava/lang/String;
                    INVOKESTATIC java.util.Arrays.toString ([Ljava/lang/Object;)Ljava/lang/String;
                    INVOKEVIRTUAL java.lang.StringBuilder.append (Ljava/lang/String;)Ljava/lang/StringBuilder;
                    INVOKEVIRTUAL java.lang.StringBuilder.toString ()Ljava/lang/String;
                    ARETURN
  end public String toString()
end public class org.springframework.beans.factory.xml.BeansDtdResolver
 -- (NullPointerException) null
null
java.lang.NullPointerException

org.aspectj.bridge.AbortException: trouble in: 
public class org.springframework.beans.factory.xml.BeansDtdResolver extends java.lang.Object implements org.xml.sax.EntityResolver:
  private static final String DTD_EXTENSION = ".dtd"
  private static final String[] DTD_NAMES
  private static final org.apache.commons.logging.Log logger
  static void <clinit>():
    staticinitialization(void org.springframework.beans.factory.xml.BeansDtdResolver.<clinit>())
    |               ICONST_2   (line 48)
    |               ANEWARRAY java.lang.String
    |               DUP
    |               ICONST_0
    |               LDC "spring-beans-2.0"
    |               AASTORE
    |               DUP
    |               ICONST_1
    |               LDC "spring-beans"
    |               AASTORE
    |               PUTSTATIC org.springframework.beans.factory.xml.BeansDtdResolver.DTD_NAMES [Ljava/lang/String;
    |               LDC org.springframework.beans.factory.xml.BeansDtdResolver   (line 50)
    |               INVOKESTATIC org.apache.commons.logging.LogFactory.getLog (Ljava/lang/Class;)Lorg/apache/commons/logging/Log;
    |               PUTSTATIC org.springframework.beans.factory.xml.BeansDtdResolver.logger Lorg/apache/commons/logging/Log;
    |               RETURN   (line 44)
    staticinitialization(void org.springframework.beans.factory.xml.BeansDtdResolver.<clinit>())
  end static void <clinit>()

  public void <init>():
                    ALOAD_0     // Lorg/springframework/beans/factory/xml/BeansDtdResolver; this   (line 44)
                    INVOKESPECIAL java.lang.Object.<init> ()V
    constructor-execution(void org.springframework.beans.factory.xml.BeansDtdResolver.<init>())
    |               RETURN
    constructor-execution(void org.springframework.beans.factory.xml.BeansDtdResolver.<init>())
  end public void <init>()

  public org.xml.sax.InputSource resolveEntity(String, String) throws java.io.IOException:
                    GETSTATIC org.springframework.beans.factory.xml.BeansDtdResolver.logger Lorg/apache/commons/logging/Log;   (line 54)
                    INVOKEINTERFACE org.apache.commons.logging.Log.isTraceEnabled ()Z
                    IFEQ L0
                    GETSTATIC org.springframework.beans.factory.xml.BeansDtdResolver.logger Lorg/apache/commons/logging/Log;   (line 55)
                    NEW java.lang.StringBuilder
                    DUP
                    LDC "Trying to resolve XML entity with public ID ["
                    INVOKESPECIAL java.lang.StringBuilder.<init> (Ljava/lang/String;)V
                    ALOAD_1     // Ljava/lang/String; publicId
                    INVOKEVIRTUAL java.lang.StringBuilder.append (Ljava/lang/String;)Ljava/lang/StringBuilder;
                    LDC "] and system ID ["   (line 56)
                    INVOKEVIRTUAL java.lang.StringBuilder.append (Ljava/lang/String;)Ljava/lang/StringBuilder;
                    ALOAD_2     // Ljava/lang/String; systemId
                    INVOKEVIRTUAL java.lang.StringBuilder.append (Ljava/lang/String;)Ljava/lang/StringBuilder;
                    LDC "]"
                    INVOKEVIRTUAL java.lang.StringBuilder.append (Ljava/lang/String;)Ljava/lang/StringBuilder;
                    INVOKEVIRTUAL java.lang.StringBuilder.toString ()Ljava/lang/String;
                    INVOKEINTERFACE org.apache.commons.logging.Log.trace (Ljava/lang/Object;)V   (line 55)
                L0: ALOAD_2     // Ljava/lang/String; systemId   (line 58)
                    IFNULL L6
                    ALOAD_2     // Ljava/lang/String; systemId
                    LDC ".dtd"
                    INVOKEVIRTUAL java.lang.String.endsWith (Ljava/lang/String;)Z
                    IFEQ L6
                    ALOAD_2     // Ljava/lang/String; systemId   (line 59)
                    LDC "/"
                    INVOKEVIRTUAL java.lang.String.lastIndexOf (Ljava/lang/String;)I
                    ISTORE_3
                    GETSTATIC org.springframework.beans.factory.xml.BeansDtdResolver.DTD_NAMES [Ljava/lang/String;   (line 60)
                    DUP
                    ASTORE 7
                    ARRAYLENGTH
                    ISTORE 6
                    ICONST_0
                    ISTORE 5
                    GOTO L5
                L1: ALOAD 7
                    ILOAD 5
                    AALOAD
                    ASTORE 4
                    ALOAD_2     // Ljava/lang/String; systemId   (line 61)
                    ALOAD 4     // Ljava/lang/String; DTD_NAME
                    INVOKEVIRTUAL java.lang.String.indexOf (Ljava/lang/String;)I
                    ISTORE 8
                    ILOAD 8     // I dtdNameStart   (line 62)
                    ILOAD_3     // I lastPathSeparator
                    IF_ICMPLE L4
                    ALOAD_2     // Ljava/lang/String; systemId   (line 63)
                    ILOAD 8     // I dtdNameStart
                    INVOKEVIRTUAL java.lang.String.substring (I)Ljava/lang/String;
                    ASTORE 9
                    GETSTATIC org.springframework.beans.factory.xml.BeansDtdResolver.logger Lorg/apache/commons/logging/Log;   (line 64)
                    INVOKEINTERFACE org.apache.commons.logging.Log.isTraceEnabled ()Z
                    IFEQ L2
                    GETSTATIC org.springframework.beans.factory.xml.BeansDtdResolver.logger Lorg/apache/commons/logging/Log;   (line 65)
                    NEW java.lang.StringBuilder
                    DUP
                    LDC "Trying to locate ["
                    INVOKESPECIAL java.lang.StringBuilder.<init> (Ljava/lang/String;)V
                    ALOAD 9     // Ljava/lang/String; dtdFile
                    INVOKEVIRTUAL java.lang.StringBuilder.append (Ljava/lang/String;)Ljava/lang/StringBuilder;
                    LDC "] in Spring jar"
                    INVOKEVIRTUAL java.lang.StringBuilder.append (Ljava/lang/String;)Ljava/lang/StringBuilder;
                    INVOKEVIRTUAL java.lang.StringBuilder.toString ()Ljava/lang/String;
                    INVOKEINTERFACE org.apache.commons.logging.Log.trace (Ljava/lang/Object;)V
    catch java.io.IOException -> E0
    |           L2: NEW org.springframework.core.io.ClassPathResource   (line 68)
    |               DUP
    |               ALOAD 9     // Ljava/lang/String; dtdFile
    |               ALOAD_0     // Lorg/springframework/beans/factory/xml/BeansDtdResolver; this
    |               INVOKEVIRTUAL java.lang.Object.getClass ()Ljava/lang/Class;
    |               INVOKESPECIAL org.springframework.core.io.ClassPathResource.<init> (Ljava/lang/String;Ljava/lang/Class;)V
    |               ASTORE 10
    |               NEW org.xml.sax.InputSource   (line 69)
    |               DUP
    |               ALOAD 10     // Lorg/springframework/core/io/Resource; resource
    |               INVOKEINTERFACE org.springframework.core.io.Resource.getInputStream ()Ljava/io/InputStream;
    |               INVOKESPECIAL org.xml.sax.InputSource.<init> (Ljava/io/InputStream;)V
    |               ASTORE 11
    |               ALOAD 11     // Lorg/xml/sax/InputSource; source   (line 70)
    |               ALOAD_1     // Ljava/lang/String; publicId
    |               INVOKEVIRTUAL org.xml.sax.InputSource.setPublicId (Ljava/lang/String;)V
    |               ALOAD 11     // Lorg/xml/sax/InputSource; source   (line 71)
    |               ALOAD_2     // Ljava/lang/String; systemId
    |               INVOKEVIRTUAL org.xml.sax.InputSource.setSystemId (Ljava/lang/String;)V
    |               GETSTATIC org.springframework.beans.factory.xml.BeansDtdResolver.logger Lorg/apache/commons/logging/Log;   (line 72)
    |               INVOKEINTERFACE org.apache.commons.logging.Log.isDebugEnabled ()Z
    |               IFEQ L3
    |               GETSTATIC org.springframework.beans.factory.xml.BeansDtdResolver.logger Lorg/apache/commons/logging/Log;   (line 73)
    |               NEW java.lang.StringBuilder
    |               DUP
    |               LDC "Found beans DTD ["
    |               INVOKESPECIAL java.lang.StringBuilder.<init> (Ljava/lang/String;)V
    |               ALOAD_2     // Ljava/lang/String; systemId
    |               INVOKEVIRTUAL java.lang.StringBuilder.append (Ljava/lang/String;)Ljava/lang/StringBuilder;
    |               LDC "] in classpath: "
    |               INVOKEVIRTUAL java.lang.StringBuilder.append (Ljava/lang/String;)Ljava/lang/StringBuilder;
    |               ALOAD 9     // Ljava/lang/String; dtdFile
    |               INVOKEVIRTUAL java.lang.StringBuilder.append (Ljava/lang/String;)Ljava/lang/StringBuilder;
    |               INVOKEVIRTUAL java.lang.StringBuilder.toString ()Ljava/lang/String;
    |               INVOKEINTERFACE org.apache.commons.logging.Log.debug (Ljava/lang/Object;)V
    |           L3: ALOAD 11     // Lorg/xml/sax/InputSource; source   (line 75)
    catch java.io.IOException -> E0
                    ARETURN
                E0: ASTORE 10   (line 77)
                    GETSTATIC org.springframework.beans.factory.xml.BeansDtdResolver.logger Lorg/apache/commons/logging/Log;   (line 78)
                    INVOKEINTERFACE org.apache.commons.logging.Log.isDebugEnabled ()Z
                    IFEQ L4
                    GETSTATIC org.springframework.beans.factory.xml.BeansDtdResolver.logger Lorg/apache/commons/logging/Log;   (line 79)
                    NEW java.lang.StringBuilder
                    DUP
                    LDC "Could not resolve beans DTD ["
                    INVOKESPECIAL java.lang.StringBuilder.<init> (Ljava/lang/String;)V
                    ALOAD_2     // Ljava/lang/String; systemId
                    INVOKEVIRTUAL java.lang.StringBuilder.append (Ljava/lang/String;)Ljava/lang/StringBuilder;
                    LDC "]: not found in class path"
                    INVOKEVIRTUAL java.lang.StringBuilder.append (Ljava/lang/String;)Ljava/lang/StringBuilder;
                    INVOKEVIRTUAL java.lang.StringBuilder.toString ()Ljava/lang/String;
                    ALOAD 10     // Ljava/io/IOException; ex
                    INVOKEINTERFACE org.apache.commons.logging.Log.debug (Ljava/lang/Object;Ljava/lang/Throwable;)V
                L4: IINC 5 1   (line 60)
                L5: ILOAD 5
                    ILOAD 6
                    IF_ICMPLT L1
                L6: ACONST_NULL   (line 88)
                    ARETURN
  end public org.xml.sax.InputSource resolveEntity(String, String) throws java.io.IOException

  public String toString():
                    NEW java.lang.StringBuilder   (line 94)
                    DUP
                    LDC "EntityResolver for DTDs "
                    INVOKESPECIAL java.lang.StringBuilder.<init> (Ljava/lang/String;)V
                    GETSTATIC org.springframework.beans.factory.xml.BeansDtdResolver.DTD_NAMES [Ljava/lang/String;
                    INVOKESTATIC java.util.Arrays.toString ([Ljava/lang/Object;)Ljava/lang/String;
                    INVOKEVIRTUAL java.lang.StringBuilder.append (Ljava/lang/String;)Ljava/lang/StringBuilder;
                    INVOKEVIRTUAL java.lang.StringBuilder.toString ()Ljava/lang/String;
                    ARETURN
  end public String toString()
end public class org.springframework.beans.factory.xml.BeansDtdResolver

	at org.aspectj.bridge.MessageWriter.handleMessage(MessageWriter.java:47)
	at org.aspectj.weaver.tools.WeavingAdaptor$WeavingAdaptorMessageWriter.handleMessage(WeavingAdaptor.java:665)
	at org.aspectj.weaver.tools.WeavingAdaptor$WeavingAdaptorMessageHolder.handleMessage(WeavingAdaptor.java:615)
	at org.aspectj.weaver.bcel.BcelWeaver.weave(BcelWeaver.java:1752)
	at org.aspectj.weaver.bcel.BcelWeaver.weaveWithoutDump(BcelWeaver.java:1694)
	at org.aspectj.weaver.bcel.BcelWeaver.weaveAndNotify(BcelWeaver.java:1464)
	at org.aspectj.weaver.bcel.BcelWeaver.weave(BcelWeaver.java:1273)
	at org.aspectj.weaver.tools.WeavingAdaptor.getWovenBytes(WeavingAdaptor.java:394)
	at org.aspectj.weaver.tools.WeavingAdaptor.weaveClass(WeavingAdaptor.java:281)
	at org.aspectj.weaver.loadtime.Aj.preProcess(Aj.java:95)
	at org.aspectj.weaver.loadtime.ClassPreProcessorAgentAdapter.transform(ClassPreProcessorAgentAdapter.java:52)
	at sun.instrument.TransformerManager.transform(TransformerManager.java:188)
	at sun.instrument.InstrumentationImpl.transform(InstrumentationImpl.java:428)
	at java.lang.ClassLoader.defineClass1(Native Method)
	at java.lang.ClassLoader.defineClass(ClassLoader.java:760)
	at java.security.SecureClassLoader.defineClass(SecureClassLoader.java:142)
	at java.net.URLClassLoader.defineClass(URLClassLoader.java:467)
	at java.net.URLClassLoader.access$100(URLClassLoader.java:73)
	at java.net.URLClassLoader$1.run(URLClassLoader.java:368)
	at java.net.URLClassLoader$1.run(URLClassLoader.java:362)
	at java.security.AccessController.doPrivileged(Native Method)
	at java.net.URLClassLoader.findClass(URLClassLoader.java:361)
	at java.lang.ClassLoader.loadClass(ClassLoader.java:424)
	at sun.misc.Launcher$AppClassLoader.loadClass(Launcher.java:331)
	at java.lang.ClassLoader.loadClass(ClassLoader.java:357)
	at org.springframework.beans.factory.xml.DelegatingEntityResolver.<init>(DelegatingEntityResolver.java:61)
	at org.springframework.beans.factory.xml.ResourceEntityResolver.<init>(ResourceEntityResolver.java:67)
	at org.springframework.context.support.AbstractXmlApplicationContext.loadBeanDefinitions(AbstractXmlApplicationContext.java:88)
	at org.springframework.context.support.AbstractRefreshableApplicationContext.refreshBeanFactory(AbstractRefreshableApplicationContext.java:131)
	at org.springframework.context.support.AbstractApplicationContext.obtainFreshBeanFactory(AbstractApplicationContext.java:527)
	at org.springframework.context.support.AbstractApplicationContext.refresh(AbstractApplicationContext.java:441)
	at org.springframework.context.support.ClassPathXmlApplicationContext.<init>(ClassPathXmlApplicationContext.java:139)
	at org.springframework.context.support.ClassPathXmlApplicationContext.<init>(ClassPathXmlApplicationContext.java:83)
	at com.curso.spring.springioc0007.Main.init(Main.java:29)
	at com.curso.spring.springioc0007.Main.main(Main.java:24)
---- System Properties ---
java.runtime.name=Java(TM) SE Runtime Environment
sun.boot.library.path=C:\Program Files\Java\jdk1.8.0_72\jre\bin
java.vm.version=25.72-b15
java.vm.vendor=Oracle Corporation
java.vendor.url=http://java.oracle.com/
path.separator=;
java.vm.name=Java HotSpot(TM) 64-Bit Server VM
file.encoding.pkg=sun.io
user.country=ES
user.script=
sun.java.launcher=SUN_STANDARD
sun.os.patch.level=
java.vm.specification.name=Java Virtual Machine Specification
user.dir=C:\Users\usuario\git\spring\aspectos\Ejemplos Relacionados\SpringIoC0007Maven
java.runtime.version=1.8.0_72-b15
java.awt.graphicsenv=sun.awt.Win32GraphicsEnvironment
java.endorsed.dirs=C:\Program Files\Java\jdk1.8.0_72\jre\lib\endorsed
os.arch=amd64
java.io.tmpdir=C:\Users\usuario\AppData\Local\Temp\
line.separator=

java.vm.specification.vendor=Oracle Corporation
user.variant=
os.name=Windows 10
sun.jnu.encoding=Cp1252
java.library.path=C:\Program Files\Java\jdk1.8.0_72\bin;C:\WINDOWS\Sun\Java\bin;C:\WINDOWS\system32;C:\WINDOWS;C:\ProgramData\Oracle\Java\javapath;C:\Program Files\CollabNet\Subversion Client;E:\bin\Sencha\Cmd\5.1.3.61;C:\Users\usuario\bin\Sencha\Cmd\5.1.3.61;C:\Program Files (x86)\Intel\iCLS Client\;C:\Program Files\Intel\iCLS Client\;C:\WINDOWS\system32;C:\WINDOWS;C:\WINDOWS\System32\Wbem;C:\WINDOWS\System32\WindowsPowerShell\v1.0\;C:\Program Files\Intel\Intel(R) Management Engine Components\DAL;C:\Program Files\Intel\Intel(R) Management Engine Components\IPT;C:\Program Files (x86)\Intel\Intel(R) Management Engine Components\DAL;C:\Program Files (x86)\Intel\Intel(R) Management Engine Components\IPT;C:\Program Files (x86)\Intel\OpenCL SDK\3.0\bin\x86;C:\Program Files (x86)\Intel\OpenCL SDK\3.0\bin\x64;C:\Program Files (x86)\sbt\\bin;C:\Program Files (x86)\Heroku\bin;C:\Program Files (x86)\git\cmd;C:\Program Files (x86)\QuickTime\QTSystem\;C:\HashiCorp\Vagrant\bin;C:\Program Files (x86)\scala\bin;C:\Program Files\nodejs\;C:\Users\usuario\AppData\Local\.meteor\;C:\Users\usuario\AppData\Roaming\npm;.
java.specification.name=Java Platform API Specification
java.class.version=52.0
sun.management.compiler=HotSpot 64-Bit Tiered Compilers
os.version=10.0
user.home=C:\Users\usuario
user.timezone=Europe/Paris
java.awt.printerjob=sun.awt.windows.WPrinterJob
file.encoding=Cp1252
java.specification.version=1.8
java.class.path=C:\Users\usuario\git\spring\aspectos\Ejemplos Relacionados\SpringIoC0007Maven\target\classes;C:\Users\usuario\.m2\repository\org\springframework\spring-context\3.1.2.RELEASE\spring-context-3.1.2.RELEASE.jar;C:\Users\usuario\.m2\repository\org\springframework\spring-aop\3.1.2.RELEASE\spring-aop-3.1.2.RELEASE.jar;C:\Users\usuario\.m2\repository\aopalliance\aopalliance\1.0\aopalliance-1.0.jar;C:\Users\usuario\.m2\repository\org\springframework\spring-beans\3.1.2.RELEASE\spring-beans-3.1.2.RELEASE.jar;C:\Users\usuario\.m2\repository\org\springframework\spring-core\3.1.2.RELEASE\spring-core-3.1.2.RELEASE.jar;C:\Users\usuario\.m2\repository\commons-logging\commons-logging\1.1.1\commons-logging-1.1.1.jar;C:\Users\usuario\.m2\repository\org\springframework\spring-expression\3.1.2.RELEASE\spring-expression-3.1.2.RELEASE.jar;C:\Users\usuario\.m2\repository\org\springframework\spring-asm\3.1.2.RELEASE\spring-asm-3.1.2.RELEASE.jar;C:\Users\usuario\.m2\repository\org\springframework\spring-aspects\3.1.2.RELEASE\spring-aspects-3.1.2.RELEASE.jar;C:\Users\usuario\.m2\repository\org\springframework\spring-context-support\3.1.2.RELEASE\spring-context-support-3.1.2.RELEASE.jar;.\..\aspectjweaver.jar
user.name=usuario
java.vm.specification.version=1.8
sun.java.command=com.curso.spring.springioc0007.Main
java.home=C:\Program Files\Java\jdk1.8.0_72\jre
sun.arch.data.model=64
user.language=es
java.specification.vendor=Oracle Corporation
awt.toolkit=sun.awt.windows.WToolkit
java.vm.info=mixed mode
java.version=1.8.0_72
java.ext.dirs=C:\Program Files\Java\jdk1.8.0_72\jre\lib\ext;C:\WINDOWS\Sun\Java\lib\ext
sun.boot.class.path=C:\Program Files\Java\jdk1.8.0_72\jre\lib\resources.jar;C:\Program Files\Java\jdk1.8.0_72\jre\lib\rt.jar;C:\Program Files\Java\jdk1.8.0_72\jre\lib\sunrsasign.jar;C:\Program Files\Java\jdk1.8.0_72\jre\lib\jsse.jar;C:\Program Files\Java\jdk1.8.0_72\jre\lib\jce.jar;C:\Program Files\Java\jdk1.8.0_72\jre\lib\charsets.jar;C:\Program Files\Java\jdk1.8.0_72\jre\lib\jfr.jar;C:\Program Files\Java\jdk1.8.0_72\jre\classes
java.vendor=Oracle Corporation
file.separator=\
java.vendor.url.bug=http://bugreport.sun.com/bugreport/
sun.io.unicode.encoding=UnicodeLittle
sun.cpu.endian=little
sun.desktop=windows
sun.cpu.isalist=amd64
---- Command Line ---
Empty
---- Full Classpath ---
Empty
---- Compiler Messages ---
Empty
---- org.aspectj.weaver.ltw.LTWWorld@28c97a5 ----
Class loader:
sun.misc.Launcher$AppClassLoader@18b4aac2
Class loader parent:
sun.misc.Launcher$ExtClassLoader@722c41f4
Shadow mungers:
(around(extraFlags: 3): ((((((((((within(@org.springframework.cache.annotation.CacheEvict *) && execution(public * @org.springframework.cache.annotation.CacheEvict *.*(..))) && this(BindingTypePattern(java.lang.Object, 0))) && persingleton(org.springframework.cache.aspectj.AnnotationCacheAspect)) || (((within(@org.springframework.cache.annotation.Caching *) && execution(public * @org.springframework.cache.annotation.Caching *.*(..))) && this(BindingTypePattern(java.lang.Object, 0))) && persingleton(org.springframework.cache.aspectj.AnnotationCacheAspect))) || (((within(@org.springframework.cache.annotation.CachePut *) && execution(public * @org.springframework.cache.annotation.CachePut *.*(..))) && this(BindingTypePattern(java.lang.Object, 0))) && persingleton(org.springframework.cache.aspectj.AnnotationCacheAspect))) || (((within(@org.springframework.cache.annotation.Cacheable *) && execution(public * @org.springframework.cache.annotation.Cacheable *.*(..))) && this(BindingTypePattern(java.lang.Object, 0))) && persingleton(org.springframework.cache.aspectj.AnnotationCacheAspect))) || ((execution(@org.springframework.cache.annotation.Caching * *(..)) && this(BindingTypePattern(java.lang.Object, 0))) && persingleton(org.springframework.cache.aspectj.AnnotationCacheAspect))) || ((execution(@org.springframework.cache.annotation.Cacheable * *(..)) && this(BindingTypePattern(java.lang.Object, 0))) && persingleton(org.springframework.cache.aspectj.AnnotationCacheAspect))) || ((execution(@org.springframework.cache.annotation.CacheEvict * *(..)) && this(BindingTypePattern(java.lang.Object, 0))) && persingleton(org.springframework.cache.aspectj.AnnotationCacheAspect))) || ((execution(@org.springframework.cache.annotation.CachePut * *(..)) && this(BindingTypePattern(java.lang.Object, 0))) && persingleton(org.springframework.cache.aspectj.AnnotationCacheAspect)))->java.lang.Object org.springframework.cache.aspectj.AbstractCacheAspect.ajc$around$org_springframework_cache_aspectj_AbstractCacheAspect$1$2bc714b5(java.lang.Object, org.aspectj.runtime.internal.AroundClosure, org.aspectj.lang.JoinPoint))
(around(extraFlags: 5): ((execution(@org.springframework.scheduling.annotation.Async (void || java.util.concurrent.Future+) *(..)) && persingleton(org.springframework.scheduling.aspectj.AnnotationAsyncExecutionAspect)) || (execution((void || java.util.concurrent.Future+) @org.springframework.scheduling.annotation.Async *.*(..)) && persingleton(org.springframework.scheduling.aspectj.AnnotationAsyncExecutionAspect)))->java.lang.Object org.springframework.scheduling.aspectj.AbstractAsyncExecutionAspect.ajc$around$org_springframework_scheduling_aspectj_AbstractAsyncExecutionAspect$1$6c004c3e(org.aspectj.runtime.internal.AroundClosure, org.aspectj.lang.JoinPoint$StaticPart))
org.aspectj.weaver.Checker@5abff562
org.aspectj.weaver.Checker@12140c1d
(before(extraFlags: 4): ((((within(@org.springframework.transaction.annotation.Transactional *) && execution(public * @org.springframework.transaction.annotation.Transactional *.*(..))) && this(BindingTypePattern(java.lang.Object, 0))) && persingleton(org.springframework.transaction.aspectj.AnnotationTransactionAspect)) || ((execution(@org.springframework.transaction.annotation.Transactional * *(..)) && this(BindingTypePattern(java.lang.Object, 0))) && persingleton(org.springframework.transaction.aspectj.AnnotationTransactionAspect)))->void org.springframework.transaction.aspectj.AbstractTransactionAspect.ajc$before$org_springframework_transaction_aspectj_AbstractTransactionAspect$1$2a73e96c(java.lang.Object, org.aspectj.lang.JoinPoint$StaticPart))
(afterThrowing(extraFlags: 1): ((((within(@org.springframework.transaction.annotation.Transactional *) && execution(public * @org.springframework.transaction.annotation.Transactional *.*(..))) && this(BindingTypePattern(java.lang.Object, 0))) && persingleton(org.springframework.transaction.aspectj.AnnotationTransactionAspect)) || ((execution(@org.springframework.transaction.annotation.Transactional * *(..)) && this(BindingTypePattern(java.lang.Object, 0))) && persingleton(org.springframework.transaction.aspectj.AnnotationTransactionAspect)))->void org.springframework.transaction.aspectj.AbstractTransactionAspect.ajc$afterThrowing$org_springframework_transaction_aspectj_AbstractTransactionAspect$2$2a73e96c(java.lang.Object, java.lang.Throwable))
(afterReturning: ((((within(@org.springframework.transaction.annotation.Transactional *) && execution(public * @org.springframework.transaction.annotation.Transactional *.*(..))) && this(BindingTypePattern(java.lang.Object, 0))) && persingleton(org.springframework.transaction.aspectj.AnnotationTransactionAspect)) || ((execution(@org.springframework.transaction.annotation.Transactional * *(..)) && this(BindingTypePattern(java.lang.Object, 0))) && persingleton(org.springframework.transaction.aspectj.AnnotationTransactionAspect)))->void org.springframework.transaction.aspectj.AbstractTransactionAspect.ajc$afterReturning$org_springframework_transaction_aspectj_AbstractTransactionAspect$3$2a73e96c(java.lang.Object))
(after: ((((within(@org.springframework.transaction.annotation.Transactional *) && execution(public * @org.springframework.transaction.annotation.Transactional *.*(..))) && this(BindingTypePattern(java.lang.Object, 0))) && persingleton(org.springframework.transaction.aspectj.AnnotationTransactionAspect)) || ((execution(@org.springframework.transaction.annotation.Transactional * *(..)) && this(BindingTypePattern(java.lang.Object, 0))) && persingleton(org.springframework.transaction.aspectj.AnnotationTransactionAspect)))->void org.springframework.transaction.aspectj.AbstractTransactionAspect.ajc$after$org_springframework_transaction_aspectj_AbstractTransactionAspect$4$2a73e96c(java.lang.Object))
(before: (((((initialization(org.springframework.beans.factory.aspectj.ConfigurableObject.new(..)) && initialization(org.springframework.beans.factory.aspectj.ConfigurableObject+.new(..))) && this(BindingTypePattern(java.lang.Object, 0))) && @this(org.springframework.beans.factory.annotation.Configurable)) && if(boolean org.springframework.beans.factory.aspectj.AnnotationBeanConfigurerAspect.ajc$if$bb0(org.springframework.beans.factory.annotation.Configurable))) && persingleton(org.springframework.beans.factory.aspectj.AnnotationBeanConfigurerAspect))->void org.springframework.beans.factory.aspectj.AbstractDependencyInjectionAspect.ajc$before$org_springframework_beans_factory_aspectj_AbstractDependencyInjectionAspect$1$e854fa65(java.lang.Object))
(afterReturning: (((((initialization(org.springframework.beans.factory.aspectj.ConfigurableObject+.new(..)) && this(BindingTypePattern(java.lang.Object, 0))) && @this(org.springframework.beans.factory.annotation.Configurable)) && !(@this(org.springframework.beans.factory.annotation.Configurable) && if(boolean org.springframework.beans.factory.aspectj.AnnotationBeanConfigurerAspect.ajc$if$bb0(org.springframework.beans.factory.annotation.Configurable)))) && if(boolean org.springframework.beans.factory.aspectj.AbstractDependencyInjectionAspect.ajc$if$6f1(org.aspectj.lang.JoinPoint))) && persingleton(org.springframework.beans.factory.aspectj.AnnotationBeanConfigurerAspect))->void org.springframework.beans.factory.aspectj.AbstractDependencyInjectionAspect.ajc$afterReturning$org_springframework_beans_factory_aspectj_AbstractDependencyInjectionAspect$2$1ea6722c(java.lang.Object))
(afterReturning: (((execution(java.lang.Object org.springframework.beans.factory.aspectj.AbstractInterfaceDrivenDependencyInjectionAspect$ConfigurableDeserializationSupport+.readResolve()) && this(BindingTypePattern(java.lang.Object, 0))) && @this(org.springframework.beans.factory.annotation.Configurable)) && persingleton(org.springframework.beans.factory.aspectj.AnnotationBeanConfigurerAspect))->void org.springframework.beans.factory.aspectj.AbstractDependencyInjectionAspect.ajc$afterReturning$org_springframework_beans_factory_aspectj_AbstractDependencyInjectionAspect$3$6aa27052(java.lang.Object))
Type mungers:
(BcelTypeMunger ResolvedTypeMunger(Method, java.lang.Object org.springframework.beans.factory.aspectj.AbstractInterfaceDrivenDependencyInjectionAspect$ConfigurableDeserializationSupport.readResolve()))
(BcelTypeMunger ExposeTypeMunger(java.lang.Object))
(BcelTypeMunger ExposeTypeMunger(java.lang.Object))
(BcelTypeMunger ExposeTypeMunger(java.lang.Object))
(BcelTypeMunger ExposeTypeMunger(org.springframework.beans.factory.aspectj.ConfigurableObject))
(BcelTypeMunger ExposeTypeMunger(org.springframework.beans.factory.aspectj.AbstractInterfaceDrivenDependencyInjectionAspect$ConfigurableDeserializationSupport))
Late Type mungers:
Empty
