---- AspectJ Properties ---
AspectJ Compiler 1.6.2 built on Saturday Oct 4, 2008 at 05:47:07 GMT
---- Dump Properties ---
Dump file: ajcore.20160604.114225.632.txt
Dump reason: abort
Dump on exception: true
Dump at exit condition: abort
---- System Properties ---
java.runtime.name=Java(TM) SE Runtime Environment
sun.boot.library.path=C:\Program Files\Java\jdk1.8.0_72\jre\bin
java.vm.version=25.72-b15
java.vm.vendor=Oracle Corporation
java.vendor.url=http://java.oracle.com/
path.separator=;
java.vm.name=Java HotSpot(TM) 64-Bit Server VM
file.encoding.pkg=sun.io
user.country=ES
user.script=
sun.java.launcher=SUN_STANDARD
sun.os.patch.level=
java.vm.specification.name=Java Virtual Machine Specification
user.dir=C:\Users\usuario\git\spring\aspectos\Ejemplos Relacionados\SpringIoC0007Maven
java.runtime.version=1.8.0_72-b15
java.awt.graphicsenv=sun.awt.Win32GraphicsEnvironment
java.endorsed.dirs=C:\Program Files\Java\jdk1.8.0_72\jre\lib\endorsed
os.arch=amd64
java.io.tmpdir=C:\Users\usuario\AppData\Local\Temp\
line.separator=

java.vm.specification.vendor=Oracle Corporation
user.variant=
os.name=Windows 10
sun.jnu.encoding=Cp1252
java.library.path=C:\Program Files\Java\jdk1.8.0_72\bin;C:\WINDOWS\Sun\Java\bin;C:\WINDOWS\system32;C:\WINDOWS;C:\ProgramData\Oracle\Java\javapath;C:\Program Files\CollabNet\Subversion Client;E:\bin\Sencha\Cmd\5.1.3.61;C:\Users\usuario\bin\Sencha\Cmd\5.1.3.61;C:\Program Files (x86)\Intel\iCLS Client\;C:\Program Files\Intel\iCLS Client\;C:\WINDOWS\system32;C:\WINDOWS;C:\WINDOWS\System32\Wbem;C:\WINDOWS\System32\WindowsPowerShell\v1.0\;C:\Program Files\Intel\Intel(R) Management Engine Components\DAL;C:\Program Files\Intel\Intel(R) Management Engine Components\IPT;C:\Program Files (x86)\Intel\Intel(R) Management Engine Components\DAL;C:\Program Files (x86)\Intel\Intel(R) Management Engine Components\IPT;C:\Program Files (x86)\Intel\OpenCL SDK\3.0\bin\x86;C:\Program Files (x86)\Intel\OpenCL SDK\3.0\bin\x64;C:\Program Files (x86)\sbt\\bin;C:\Program Files (x86)\Heroku\bin;C:\Program Files (x86)\git\cmd;C:\Program Files (x86)\QuickTime\QTSystem\;C:\HashiCorp\Vagrant\bin;C:\Program Files (x86)\scala\bin;C:\Program Files\nodejs\;C:\Users\usuario\AppData\Local\.meteor\;C:\Users\usuario\AppData\Roaming\npm;.
java.specification.name=Java Platform API Specification
java.class.version=52.0
sun.management.compiler=HotSpot 64-Bit Tiered Compilers
os.version=10.0
user.home=C:\Users\usuario
user.timezone=Europe/Paris
java.awt.printerjob=sun.awt.windows.WPrinterJob
file.encoding=Cp1252
java.specification.version=1.8
java.class.path=C:\Users\usuario\git\spring\aspectos\Ejemplos Relacionados\SpringIoC0007Maven\target\classes;C:\Users\usuario\.m2\repository\org\springframework\spring-context\3.1.2.RELEASE\spring-context-3.1.2.RELEASE.jar;C:\Users\usuario\.m2\repository\org\springframework\spring-aop\3.1.2.RELEASE\spring-aop-3.1.2.RELEASE.jar;C:\Users\usuario\.m2\repository\aopalliance\aopalliance\1.0\aopalliance-1.0.jar;C:\Users\usuario\.m2\repository\org\springframework\spring-beans\3.1.2.RELEASE\spring-beans-3.1.2.RELEASE.jar;C:\Users\usuario\.m2\repository\org\springframework\spring-core\3.1.2.RELEASE\spring-core-3.1.2.RELEASE.jar;C:\Users\usuario\.m2\repository\commons-logging\commons-logging\1.1.1\commons-logging-1.1.1.jar;C:\Users\usuario\.m2\repository\org\springframework\spring-expression\3.1.2.RELEASE\spring-expression-3.1.2.RELEASE.jar;C:\Users\usuario\.m2\repository\org\springframework\spring-asm\3.1.2.RELEASE\spring-asm-3.1.2.RELEASE.jar;C:\Users\usuario\.m2\repository\org\springframework\spring-aspects\3.1.2.RELEASE\spring-aspects-3.1.2.RELEASE.jar;C:\Users\usuario\.m2\repository\org\springframework\spring-context-support\3.1.2.RELEASE\spring-context-support-3.1.2.RELEASE.jar;.\..\aspectjweaver.jar
user.name=usuario
java.vm.specification.version=1.8
sun.java.command=com.curso.spring.springioc0007.Main
java.home=C:\Program Files\Java\jdk1.8.0_72\jre
sun.arch.data.model=64
user.language=es
java.specification.vendor=Oracle Corporation
awt.toolkit=sun.awt.windows.WToolkit
java.vm.info=mixed mode
java.version=1.8.0_72
java.ext.dirs=C:\Program Files\Java\jdk1.8.0_72\jre\lib\ext;C:\WINDOWS\Sun\Java\lib\ext
sun.boot.class.path=C:\Program Files\Java\jdk1.8.0_72\jre\lib\resources.jar;C:\Program Files\Java\jdk1.8.0_72\jre\lib\rt.jar;C:\Program Files\Java\jdk1.8.0_72\jre\lib\sunrsasign.jar;C:\Program Files\Java\jdk1.8.0_72\jre\lib\jsse.jar;C:\Program Files\Java\jdk1.8.0_72\jre\lib\jce.jar;C:\Program Files\Java\jdk1.8.0_72\jre\lib\charsets.jar;C:\Program Files\Java\jdk1.8.0_72\jre\lib\jfr.jar;C:\Program Files\Java\jdk1.8.0_72\jre\classes
java.vendor=Oracle Corporation
file.separator=\
java.vendor.url.bug=http://bugreport.sun.com/bugreport/
sun.io.unicode.encoding=UnicodeLittle
sun.cpu.endian=little
sun.desktop=windows
sun.cpu.isalist=amd64
---- Command Line ---
Empty
---- Full Classpath ---
Empty
---- Compiler Messages ---
info AspectJ Weaver Version 1.6.2 built on Saturday Oct 4, 2008 at 05:47:07 GMT
info register classloader sun.misc.Launcher$AppClassLoader@18b4aac2
info using configuration file:/C:/Users/usuario/.m2/repository/org/springframework/spring-aspects/3.1.2.RELEASE/spring-aspects-3.1.2.RELEASE.jar!/META-INF/aop.xml
debug weaving 'org.springframework.util.MethodInvoker'
abort trouble in: 
public class org.springframework.util.MethodInvoker extends java.lang.Object:
  private Class targetClass
  private Object targetObject
  private String targetMethod
  private String staticMethod
  private Object[] arguments
  private java.lang.reflect.Method methodObject
  public void <init>():
                    ALOAD_0     // Lorg/springframework/util/MethodInvoker; this   (line 41)
                    INVOKESPECIAL java.lang.Object.<init> ()V
    constructor-execution(void org.springframework.util.MethodInvoker.<init>())
    |               ALOAD_0     // Lorg/springframework/util/MethodInvoker; this   (line 51)
    |               ICONST_0
    |               ANEWARRAY java.lang.Object
    |               PUTFIELD org.springframework.util.MethodInvoker.arguments [Ljava/lang/Object;
    |               RETURN   (line 41)
    constructor-execution(void org.springframework.util.MethodInvoker.<init>())
  end public void <init>()

  public void setTargetClass(Class):
                    ALOAD_0     // Lorg/springframework/util/MethodInvoker; this   (line 65)
                    ALOAD_1     // Ljava/lang/Class; targetClass
                    PUTFIELD org.springframework.util.MethodInvoker.targetClass Ljava/lang/Class;
                    RETURN   (line 66)
  end public void setTargetClass(Class)

  public Class getTargetClass():
                    ALOAD_0     // Lorg/springframework/util/MethodInvoker; this   (line 72)
                    GETFIELD org.springframework.util.MethodInvoker.targetClass Ljava/lang/Class;
                    ARETURN
  end public Class getTargetClass()

  public void setTargetObject(Object):
                    ALOAD_0     // Lorg/springframework/util/MethodInvoker; this   (line 83)
                    ALOAD_1     // Ljava/lang/Object; targetObject
                    PUTFIELD org.springframework.util.MethodInvoker.targetObject Ljava/lang/Object;
                    ALOAD_1     // Ljava/lang/Object; targetObject   (line 84)
                    IFNULL L0
                    ALOAD_0     // Lorg/springframework/util/MethodInvoker; this   (line 85)
                    ALOAD_1     // Ljava/lang/Object; targetObject
                    INVOKEVIRTUAL java.lang.Object.getClass ()Ljava/lang/Class;
                    PUTFIELD org.springframework.util.MethodInvoker.targetClass Ljava/lang/Class;
                L0: RETURN   (line 87)
  end public void setTargetObject(Object)

  public Object getTargetObject():
                    ALOAD_0     // Lorg/springframework/util/MethodInvoker; this   (line 93)
                    GETFIELD org.springframework.util.MethodInvoker.targetObject Ljava/lang/Object;
                    ARETURN
  end public Object getTargetObject()

  public void setTargetMethod(String):
                    ALOAD_0     // Lorg/springframework/util/MethodInvoker; this   (line 104)
                    ALOAD_1     // Ljava/lang/String; targetMethod
                    PUTFIELD org.springframework.util.MethodInvoker.targetMethod Ljava/lang/String;
                    RETURN   (line 105)
  end public void setTargetMethod(String)

  public String getTargetMethod():
                    ALOAD_0     // Lorg/springframework/util/MethodInvoker; this   (line 111)
                    GETFIELD org.springframework.util.MethodInvoker.targetMethod Ljava/lang/String;
                    ARETURN
  end public String getTargetMethod()

  public void setStaticMethod(String):
                    ALOAD_0     // Lorg/springframework/util/MethodInvoker; this   (line 122)
                    ALOAD_1     // Ljava/lang/String; staticMethod
                    PUTFIELD org.springframework.util.MethodInvoker.staticMethod Ljava/lang/String;
                    RETURN   (line 123)
  end public void setStaticMethod(String)

  public void setArguments(Object[]):
                    ALOAD_0     // Lorg/springframework/util/MethodInvoker; this   (line 130)
                    ALOAD_1     // [Ljava/lang/Object; arguments
                    IFNULL L0
                    ALOAD_1     // [Ljava/lang/Object; arguments
                    GOTO L1
                L0: ICONST_0
                    ANEWARRAY java.lang.Object
                L1: PUTFIELD org.springframework.util.MethodInvoker.arguments [Ljava/lang/Object;
                    RETURN   (line 131)
  end public void setArguments(Object[])

  public Object[] getArguments():
                    ALOAD_0     // Lorg/springframework/util/MethodInvoker; this   (line 137)
                    GETFIELD org.springframework.util.MethodInvoker.arguments [Ljava/lang/Object;
                    ARETURN
  end public Object[] getArguments()

  public void prepare() throws java.lang.ClassNotFoundException, java.lang.NoSuchMethodException:
                    ALOAD_0     // Lorg/springframework/util/MethodInvoker; this   (line 148)
                    GETFIELD org.springframework.util.MethodInvoker.staticMethod Ljava/lang/String;
                    IFNULL L2
                    ALOAD_0     // Lorg/springframework/util/MethodInvoker; this   (line 149)
                    GETFIELD org.springframework.util.MethodInvoker.staticMethod Ljava/lang/String;
                    BIPUSH 46
                    INVOKEVIRTUAL java.lang.String.lastIndexOf (I)I
                    ISTORE_1
                    ILOAD_1     // I lastDotIndex   (line 150)
                    ICONST_M1
                    IF_ICMPEQ L0
                    ILOAD_1     // I lastDotIndex
                    ALOAD_0     // Lorg/springframework/util/MethodInvoker; this
                    GETFIELD org.springframework.util.MethodInvoker.staticMethod Ljava/lang/String;
                    INVOKEVIRTUAL java.lang.String.length ()I
                    IF_ICMPNE L1
                L0: NEW java.lang.IllegalArgumentException   (line 151)
                    DUP
                    LDC "staticMethod must be a fully qualified class plus method name: e.g. 'example.MyExampleClass.myExampleMethod'"   (line 152)
                    INVOKESPECIAL java.lang.IllegalArgumentException.<init> (Ljava/lang/String;)V   (line 151)
                    ATHROW
                L1: ALOAD_0     // Lorg/springframework/util/MethodInvoker; this   (line 155)
                    GETFIELD org.springframework.util.MethodInvoker.staticMethod Ljava/lang/String;
                    ICONST_0
                    ILOAD_1     // I lastDotIndex
                    INVOKEVIRTUAL java.lang.String.substring (II)Ljava/lang/String;
                    ASTORE_2
                    ALOAD_0     // Lorg/springframework/util/MethodInvoker; this   (line 156)
                    GETFIELD org.springframework.util.MethodInvoker.staticMethod Ljava/lang/String;
                    ILOAD_1     // I lastDotIndex
                    ICONST_1
                    IADD
                    INVOKEVIRTUAL java.lang.String.substring (I)Ljava/lang/String;
                    ASTORE_3
                    ALOAD_0     // Lorg/springframework/util/MethodInvoker; this   (line 157)
                    ALOAD_0     // Lorg/springframework/util/MethodInvoker; this
                    ALOAD_2     // Ljava/lang/String; className
                    INVOKEVIRTUAL org.springframework.util.MethodInvoker.resolveClassName (Ljava/lang/String;)Ljava/lang/Class;
                    PUTFIELD org.springframework.util.MethodInvoker.targetClass Ljava/lang/Class;
                    ALOAD_0     // Lorg/springframework/util/MethodInvoker; this   (line 158)
                    ALOAD_3     // Ljava/lang/String; methodName
                    PUTFIELD org.springframework.util.MethodInvoker.targetMethod Ljava/lang/String;
                L2: ALOAD_0     // Lorg/springframework/util/MethodInvoker; this   (line 161)
                    INVOKEVIRTUAL org.springframework.util.MethodInvoker.getTargetClass ()Ljava/lang/Class;
                    ASTORE_1
                    ALOAD_0     // Lorg/springframework/util/MethodInvoker; this   (line 162)
                    INVOKEVIRTUAL org.springframework.util.MethodInvoker.getTargetMethod ()Ljava/lang/String;
                    ASTORE_2
                    ALOAD_1     // Ljava/lang/Class; targetClass   (line 163)
                    IFNONNULL L3
                    NEW java.lang.IllegalArgumentException   (line 164)
                    DUP
                    LDC "Either 'targetClass' or 'targetObject' is required"
                    INVOKESPECIAL java.lang.IllegalArgumentException.<init> (Ljava/lang/String;)V
                    ATHROW
                L3: ALOAD_2     // Ljava/lang/String; targetMethod   (line 166)
                    IFNONNULL L4
                    NEW java.lang.IllegalArgumentException   (line 167)
                    DUP
                    LDC "Property 'targetMethod' is required"
                    INVOKESPECIAL java.lang.IllegalArgumentException.<init> (Ljava/lang/String;)V
                    ATHROW
                L4: ALOAD_0     // Lorg/springframework/util/MethodInvoker; this   (line 170)
                    INVOKEVIRTUAL org.springframework.util.MethodInvoker.getArguments ()[Ljava/lang/Object;
                    ASTORE_3
                    ALOAD_3     // [Ljava/lang/Object; arguments   (line 171)
                    ARRAYLENGTH
                    ANEWARRAY java.lang.Class
                    ASTORE 4
                    ICONST_0   (line 172)
                    ISTORE 5
                    GOTO L8
                L5: ALOAD 4     // [Ljava/lang/Class; argTypes   (line 173)
                    ILOAD 5     // I i
                    ALOAD_3     // [Ljava/lang/Object; arguments
                    ILOAD 5     // I i
                    AALOAD
                    IFNULL L6
                    ALOAD_3     // [Ljava/lang/Object; arguments
                    ILOAD 5     // I i
                    AALOAD
                    INVOKEVIRTUAL java.lang.Object.getClass ()Ljava/lang/Class;
                    GOTO L7
                L6: LDC java.lang.Object
                L7: AASTORE
                    IINC 5 1     // I i   (line 172)
                L8: ILOAD 5     // I i
                    ALOAD_3     // [Ljava/lang/Object; arguments
                    ARRAYLENGTH
                    IF_ICMPLT L5
    catch java.lang.NoSuchMethodException -> E0
    |               ALOAD_0     // Lorg/springframework/util/MethodInvoker; this   (line 178)
    |               ALOAD_1     // Ljava/lang/Class; targetClass
    |               ALOAD_2     // Ljava/lang/String; targetMethod
    |               ALOAD 4     // [Ljava/lang/Class; argTypes
    |               INVOKEVIRTUAL java.lang.Class.getMethod (Ljava/lang/String;[Ljava/lang/Class;)Ljava/lang/reflect/Method;
    |               PUTFIELD org.springframework.util.MethodInvoker.methodObject Ljava/lang/reflect/Method;
    catch java.lang.NoSuchMethodException -> E0
                    GOTO L9
                E0: ASTORE 5   (line 180)
                    ALOAD_0     // Lorg/springframework/util/MethodInvoker; this   (line 182)
                    ALOAD_0     // Lorg/springframework/util/MethodInvoker; this
                    INVOKEVIRTUAL org.springframework.util.MethodInvoker.findMatchingMethod ()Ljava/lang/reflect/Method;
                    PUTFIELD org.springframework.util.MethodInvoker.methodObject Ljava/lang/reflect/Method;
                    ALOAD_0     // Lorg/springframework/util/MethodInvoker; this   (line 183)
                    GETFIELD org.springframework.util.MethodInvoker.methodObject Ljava/lang/reflect/Method;
                    IFNONNULL L9
                    ALOAD 5     // Ljava/lang/NoSuchMethodException; ex   (line 184)
                    ATHROW
                L9: RETURN   (line 187)
  end public void prepare() throws java.lang.ClassNotFoundException, java.lang.NoSuchMethodException

  protected Class resolveClassName(String) throws java.lang.ClassNotFoundException:
                    ALOAD_1     // Ljava/lang/String; className   (line 198)
                    INVOKESTATIC org.springframework.util.ClassUtils.getDefaultClassLoader ()Ljava/lang/ClassLoader;
                    INVOKESTATIC org.springframework.util.ClassUtils.forName (Ljava/lang/String;Ljava/lang/ClassLoader;)Ljava/lang/Class;
                    ARETURN
  end protected Class resolveClassName(String) throws java.lang.ClassNotFoundException

  protected java.lang.reflect.Method findMatchingMethod():
                    ALOAD_0     // Lorg/springframework/util/MethodInvoker; this   (line 209)
                    INVOKEVIRTUAL org.springframework.util.MethodInvoker.getTargetMethod ()Ljava/lang/String;
                    ASTORE_1
                    ALOAD_0     // Lorg/springframework/util/MethodInvoker; this   (line 210)
                    INVOKEVIRTUAL org.springframework.util.MethodInvoker.getArguments ()[Ljava/lang/Object;
                    ASTORE_2
                    ALOAD_2     // [Ljava/lang/Object; arguments   (line 211)
                    ARRAYLENGTH
                    ISTORE_3
                    ALOAD_0     // Lorg/springframework/util/MethodInvoker; this   (line 213)
                    INVOKEVIRTUAL org.springframework.util.MethodInvoker.getTargetClass ()Ljava/lang/Class;
                    INVOKESTATIC org.springframework.util.ReflectionUtils.getAllDeclaredMethods (Ljava/lang/Class;)[Ljava/lang/reflect/Method;
                    ASTORE 4
                    LDC 2147483647   (line 214)
                    ISTORE 5
                    ACONST_NULL   (line 215)
                    ASTORE 6
                    ALOAD 4     // [Ljava/lang/reflect/Method; candidates   (line 217)
                    DUP
                    ASTORE 10
                    ARRAYLENGTH
                    ISTORE 9
                    ICONST_0
                    ISTORE 8
                    GOTO L2
                L0: ALOAD 10
                    ILOAD 8
                    AALOAD
                    ASTORE 7
                    ALOAD 7     // Ljava/lang/reflect/Method; candidate   (line 218)
                    INVOKEVIRTUAL java.lang.reflect.Method.getName ()Ljava/lang/String;
                    ALOAD_1     // Ljava/lang/String; targetMethod
                    INVOKEVIRTUAL java.lang.String.equals (Ljava/lang/Object;)Z
                    IFEQ L1
                    ALOAD 7     // Ljava/lang/reflect/Method; candidate   (line 219)
                    INVOKEVIRTUAL java.lang.reflect.Method.getParameterTypes ()[Ljava/lang/Class;
                    ASTORE 11
                    ALOAD 11     // [Ljava/lang/Class; paramTypes   (line 220)
                    ARRAYLENGTH
                    ILOAD_3     // I argCount
                    IF_ICMPNE L1
                    ALOAD 11     // [Ljava/lang/Class; paramTypes   (line 221)
                    ALOAD_2     // [Ljava/lang/Object; arguments
                    INVOKESTATIC org.springframework.util.MethodInvoker.getTypeDifferenceWeight ([Ljava/lang/Class;[Ljava/lang/Object;)I
                    ISTORE 12
                    ILOAD 12     // I typeDiffWeight   (line 222)
                    ILOAD 5     // I minTypeDiffWeight
                    IF_ICMPGE L1
                    ILOAD 12     // I typeDiffWeight   (line 223)
                    ISTORE 5     // I minTypeDiffWeight
                    ALOAD 7     // Ljava/lang/reflect/Method; candidate   (line 224)
                    ASTORE 6     // Ljava/lang/reflect/Method; matchingMethod
                L1: IINC 8 1   (line 217)
                L2: ILOAD 8
                    ILOAD 9
                    IF_ICMPLT L0
                    ALOAD 6     // Ljava/lang/reflect/Method; matchingMethod   (line 230)
                    ARETURN
  end protected java.lang.reflect.Method findMatchingMethod()

  public java.lang.reflect.Method getPreparedMethod() throws java.lang.IllegalStateException:
                    ALOAD_0     // Lorg/springframework/util/MethodInvoker; this   (line 242)
                    GETFIELD org.springframework.util.MethodInvoker.methodObject Ljava/lang/reflect/Method;
                    IFNONNULL L0
                    NEW java.lang.IllegalStateException   (line 243)
                    DUP
                    LDC "prepare() must be called prior to invoke() on MethodInvoker"
                    INVOKESPECIAL java.lang.IllegalStateException.<init> (Ljava/lang/String;)V
                    ATHROW
                L0: ALOAD_0     // Lorg/springframework/util/MethodInvoker; this   (line 245)
                    GETFIELD org.springframework.util.MethodInvoker.methodObject Ljava/lang/reflect/Method;
                    ARETURN
  end public java.lang.reflect.Method getPreparedMethod() throws java.lang.IllegalStateException

  public boolean isPrepared():
                    ALOAD_0     // Lorg/springframework/util/MethodInvoker; this   (line 253)
                    GETFIELD org.springframework.util.MethodInvoker.methodObject Ljava/lang/reflect/Method;
                    IFNULL L0
                    ICONST_1
                    IRETURN
                L0: ICONST_0
                    IRETURN
  end public boolean isPrepared()

  public Object invoke() throws java.lang.reflect.InvocationTargetException, java.lang.IllegalAccessException:
                    ALOAD_0     // Lorg/springframework/util/MethodInvoker; this   (line 267)
                    INVOKEVIRTUAL org.springframework.util.MethodInvoker.getTargetObject ()Ljava/lang/Object;
                    ASTORE_1
                    ALOAD_0     // Lorg/springframework/util/MethodInvoker; this   (line 268)
                    INVOKEVIRTUAL org.springframework.util.MethodInvoker.getPreparedMethod ()Ljava/lang/reflect/Method;
                    ASTORE_2
                    ALOAD_1     // Ljava/lang/Object; targetObject   (line 269)
                    IFNONNULL L0
                    ALOAD_2     // Ljava/lang/reflect/Method; preparedMethod
                    INVOKEVIRTUAL java.lang.reflect.Method.getModifiers ()I
                    INVOKESTATIC java.lang.reflect.Modifier.isStatic (I)Z
                    IFNE L0
                    NEW java.lang.IllegalArgumentException   (line 270)
                    DUP
                    LDC "Target method must not be non-static without a target"
                    INVOKESPECIAL java.lang.IllegalArgumentException.<init> (Ljava/lang/String;)V
                    ATHROW
                L0: ALOAD_2     // Ljava/lang/reflect/Method; preparedMethod   (line 272)
                    INVOKESTATIC org.springframework.util.ReflectionUtils.makeAccessible (Ljava/lang/reflect/Method;)V
                    ALOAD_2     // Ljava/lang/reflect/Method; preparedMethod   (line 273)
                    ALOAD_1     // Ljava/lang/Object; targetObject
                    ALOAD_0     // Lorg/springframework/util/MethodInvoker; this
                    INVOKEVIRTUAL org.springframework.util.MethodInvoker.getArguments ()[Ljava/lang/Object;
                    INVOKEVIRTUAL java.lang.reflect.Method.invoke (Ljava/lang/Object;[Ljava/lang/Object;)Ljava/lang/Object;
                    ARETURN
  end public Object invoke() throws java.lang.reflect.InvocationTargetException, java.lang.IllegalAccessException

  public static int getTypeDifferenceWeight(Class[], Object[]):
                    ICONST_0   (line 295)
                    ISTORE_2
                    ICONST_0   (line 296)
                    ISTORE_3
                    GOTO L7
                L0: ALOAD_0     // [Ljava/lang/Class; paramTypes   (line 297)
                    ILOAD_3     // I i
                    AALOAD
                    ALOAD_1     // [Ljava/lang/Object; args
                    ILOAD_3     // I i
                    AALOAD
                    INVOKESTATIC org.springframework.util.ClassUtils.isAssignableValue (Ljava/lang/Class;Ljava/lang/Object;)Z
                    IFNE L1
                    LDC 2147483647   (line 298)
                    IRETURN
                L1: ALOAD_1     // [Ljava/lang/Object; args   (line 300)
                    ILOAD_3     // I i
                    AALOAD
                    IFNULL L6
                    ALOAD_0     // [Ljava/lang/Class; paramTypes   (line 301)
                    ILOAD_3     // I i
                    AALOAD
                    ASTORE 4
                    ALOAD_1     // [Ljava/lang/Object; args   (line 302)
                    ILOAD_3     // I i
                    AALOAD
                    INVOKEVIRTUAL java.lang.Object.getClass ()Ljava/lang/Class;
                    INVOKEVIRTUAL java.lang.Class.getSuperclass ()Ljava/lang/Class;
                    ASTORE 5
                    GOTO L5   (line 303)
                L2: ALOAD 4     // Ljava/lang/Class; paramType   (line 304)
                    ALOAD 5     // Ljava/lang/Class; superClass
                    INVOKEVIRTUAL java.lang.Object.equals (Ljava/lang/Object;)Z
                    IFEQ L3
                    IINC_2 2     // I result   (line 305)
                    ACONST_NULL   (line 306)
                    ASTORE 5     // Ljava/lang/Class; superClass
                    GOTO L5
                L3: ALOAD 4     // Ljava/lang/Class; paramType   (line 308)
                    ALOAD 5     // Ljava/lang/Class; superClass
                    INVOKESTATIC org.springframework.util.ClassUtils.isAssignable (Ljava/lang/Class;Ljava/lang/Class;)Z
                    IFEQ L4
                    IINC_2 2     // I result   (line 309)
                    ALOAD 5     // Ljava/lang/Class; superClass   (line 310)
                    INVOKEVIRTUAL java.lang.Class.getSuperclass ()Ljava/lang/Class;
                    ASTORE 5     // Ljava/lang/Class; superClass
                    GOTO L5
                L4: ACONST_NULL   (line 313)
                    ASTORE 5     // Ljava/lang/Class; superClass
                L5: ALOAD 5     // Ljava/lang/Class; superClass   (line 303)
                    IFNONNULL L2
                    ALOAD 4     // Ljava/lang/Class; paramType   (line 316)
                    INVOKEVIRTUAL java.lang.Class.isInterface ()Z
                    IFEQ L6
                    IINC_2 1     // I result   (line 317)
                L6: IINC_3 1     // I i   (line 296)
                L7: ILOAD_3     // I i
                    ALOAD_0     // [Ljava/lang/Class; paramTypes
                    ARRAYLENGTH
                    IF_ICMPLT L0
                    ILOAD_2     // I result   (line 321)
                    IRETURN
  end public static int getTypeDifferenceWeight(Class[], Object[])

end public class org.springframework.util.MethodInvoker
 -- (NullPointerException) null
null
java.lang.NullPointerException

debug weaving 'org.springframework.beans.factory.wiring.BeanConfigurerSupport'
---- org.aspectj.weaver.ltw.LTWWorld@28c97a5 ----
Class loader:
sun.misc.Launcher$AppClassLoader@18b4aac2
Class loader parent:
sun.misc.Launcher$ExtClassLoader@722c41f4
Shadow mungers:
(around(extraFlags: 3): ((((((((((within(@org.springframework.cache.annotation.CacheEvict *) && execution(public * @org.springframework.cache.annotation.CacheEvict *.*(..))) && this(BindingTypePattern(java.lang.Object, 0))) && persingleton(org.springframework.cache.aspectj.AnnotationCacheAspect)) || (((within(@org.springframework.cache.annotation.Caching *) && execution(public * @org.springframework.cache.annotation.Caching *.*(..))) && this(BindingTypePattern(java.lang.Object, 0))) && persingleton(org.springframework.cache.aspectj.AnnotationCacheAspect))) || (((within(@org.springframework.cache.annotation.CachePut *) && execution(public * @org.springframework.cache.annotation.CachePut *.*(..))) && this(BindingTypePattern(java.lang.Object, 0))) && persingleton(org.springframework.cache.aspectj.AnnotationCacheAspect))) || (((within(@org.springframework.cache.annotation.Cacheable *) && execution(public * @org.springframework.cache.annotation.Cacheable *.*(..))) && this(BindingTypePattern(java.lang.Object, 0))) && persingleton(org.springframework.cache.aspectj.AnnotationCacheAspect))) || ((execution(@org.springframework.cache.annotation.Caching * *(..)) && this(BindingTypePattern(java.lang.Object, 0))) && persingleton(org.springframework.cache.aspectj.AnnotationCacheAspect))) || ((execution(@org.springframework.cache.annotation.Cacheable * *(..)) && this(BindingTypePattern(java.lang.Object, 0))) && persingleton(org.springframework.cache.aspectj.AnnotationCacheAspect))) || ((execution(@org.springframework.cache.annotation.CacheEvict * *(..)) && this(BindingTypePattern(java.lang.Object, 0))) && persingleton(org.springframework.cache.aspectj.AnnotationCacheAspect))) || ((execution(@org.springframework.cache.annotation.CachePut * *(..)) && this(BindingTypePattern(java.lang.Object, 0))) && persingleton(org.springframework.cache.aspectj.AnnotationCacheAspect)))->java.lang.Object org.springframework.cache.aspectj.AbstractCacheAspect.ajc$around$org_springframework_cache_aspectj_AbstractCacheAspect$1$2bc714b5(java.lang.Object, org.aspectj.runtime.internal.AroundClosure, org.aspectj.lang.JoinPoint))
(around(extraFlags: 5): ((execution(@org.springframework.scheduling.annotation.Async (void || java.util.concurrent.Future+) *(..)) && persingleton(org.springframework.scheduling.aspectj.AnnotationAsyncExecutionAspect)) || (execution((void || java.util.concurrent.Future+) @org.springframework.scheduling.annotation.Async *.*(..)) && persingleton(org.springframework.scheduling.aspectj.AnnotationAsyncExecutionAspect)))->java.lang.Object org.springframework.scheduling.aspectj.AbstractAsyncExecutionAspect.ajc$around$org_springframework_scheduling_aspectj_AbstractAsyncExecutionAspect$1$6c004c3e(org.aspectj.runtime.internal.AroundClosure, org.aspectj.lang.JoinPoint$StaticPart))
org.aspectj.weaver.Checker@5abff562
org.aspectj.weaver.Checker@12140c1d
(before(extraFlags: 4): ((((within(@org.springframework.transaction.annotation.Transactional *) && execution(public * @org.springframework.transaction.annotation.Transactional *.*(..))) && this(BindingTypePattern(java.lang.Object, 0))) && persingleton(org.springframework.transaction.aspectj.AnnotationTransactionAspect)) || ((execution(@org.springframework.transaction.annotation.Transactional * *(..)) && this(BindingTypePattern(java.lang.Object, 0))) && persingleton(org.springframework.transaction.aspectj.AnnotationTransactionAspect)))->void org.springframework.transaction.aspectj.AbstractTransactionAspect.ajc$before$org_springframework_transaction_aspectj_AbstractTransactionAspect$1$2a73e96c(java.lang.Object, org.aspectj.lang.JoinPoint$StaticPart))
(afterThrowing(extraFlags: 1): ((((within(@org.springframework.transaction.annotation.Transactional *) && execution(public * @org.springframework.transaction.annotation.Transactional *.*(..))) && this(BindingTypePattern(java.lang.Object, 0))) && persingleton(org.springframework.transaction.aspectj.AnnotationTransactionAspect)) || ((execution(@org.springframework.transaction.annotation.Transactional * *(..)) && this(BindingTypePattern(java.lang.Object, 0))) && persingleton(org.springframework.transaction.aspectj.AnnotationTransactionAspect)))->void org.springframework.transaction.aspectj.AbstractTransactionAspect.ajc$afterThrowing$org_springframework_transaction_aspectj_AbstractTransactionAspect$2$2a73e96c(java.lang.Object, java.lang.Throwable))
(afterReturning: ((((within(@org.springframework.transaction.annotation.Transactional *) && execution(public * @org.springframework.transaction.annotation.Transactional *.*(..))) && this(BindingTypePattern(java.lang.Object, 0))) && persingleton(org.springframework.transaction.aspectj.AnnotationTransactionAspect)) || ((execution(@org.springframework.transaction.annotation.Transactional * *(..)) && this(BindingTypePattern(java.lang.Object, 0))) && persingleton(org.springframework.transaction.aspectj.AnnotationTransactionAspect)))->void org.springframework.transaction.aspectj.AbstractTransactionAspect.ajc$afterReturning$org_springframework_transaction_aspectj_AbstractTransactionAspect$3$2a73e96c(java.lang.Object))
(after: ((((within(@org.springframework.transaction.annotation.Transactional *) && execution(public * @org.springframework.transaction.annotation.Transactional *.*(..))) && this(BindingTypePattern(java.lang.Object, 0))) && persingleton(org.springframework.transaction.aspectj.AnnotationTransactionAspect)) || ((execution(@org.springframework.transaction.annotation.Transactional * *(..)) && this(BindingTypePattern(java.lang.Object, 0))) && persingleton(org.springframework.transaction.aspectj.AnnotationTransactionAspect)))->void org.springframework.transaction.aspectj.AbstractTransactionAspect.ajc$after$org_springframework_transaction_aspectj_AbstractTransactionAspect$4$2a73e96c(java.lang.Object))
(before: (((((initialization(org.springframework.beans.factory.aspectj.ConfigurableObject.new(..)) && initialization(org.springframework.beans.factory.aspectj.ConfigurableObject+.new(..))) && this(BindingTypePattern(java.lang.Object, 0))) && @this(org.springframework.beans.factory.annotation.Configurable)) && if(boolean org.springframework.beans.factory.aspectj.AnnotationBeanConfigurerAspect.ajc$if$bb0(org.springframework.beans.factory.annotation.Configurable))) && persingleton(org.springframework.beans.factory.aspectj.AnnotationBeanConfigurerAspect))->void org.springframework.beans.factory.aspectj.AbstractDependencyInjectionAspect.ajc$before$org_springframework_beans_factory_aspectj_AbstractDependencyInjectionAspect$1$e854fa65(java.lang.Object))
(afterReturning: (((((initialization(org.springframework.beans.factory.aspectj.ConfigurableObject+.new(..)) && this(BindingTypePattern(java.lang.Object, 0))) && @this(org.springframework.beans.factory.annotation.Configurable)) && !(@this(org.springframework.beans.factory.annotation.Configurable) && if(boolean org.springframework.beans.factory.aspectj.AnnotationBeanConfigurerAspect.ajc$if$bb0(org.springframework.beans.factory.annotation.Configurable)))) && if(boolean org.springframework.beans.factory.aspectj.AbstractDependencyInjectionAspect.ajc$if$6f1(org.aspectj.lang.JoinPoint))) && persingleton(org.springframework.beans.factory.aspectj.AnnotationBeanConfigurerAspect))->void org.springframework.beans.factory.aspectj.AbstractDependencyInjectionAspect.ajc$afterReturning$org_springframework_beans_factory_aspectj_AbstractDependencyInjectionAspect$2$1ea6722c(java.lang.Object))
(afterReturning: (((execution(java.lang.Object org.springframework.beans.factory.aspectj.AbstractInterfaceDrivenDependencyInjectionAspect$ConfigurableDeserializationSupport+.readResolve()) && this(BindingTypePattern(java.lang.Object, 0))) && @this(org.springframework.beans.factory.annotation.Configurable)) && persingleton(org.springframework.beans.factory.aspectj.AnnotationBeanConfigurerAspect))->void org.springframework.beans.factory.aspectj.AbstractDependencyInjectionAspect.ajc$afterReturning$org_springframework_beans_factory_aspectj_AbstractDependencyInjectionAspect$3$6aa27052(java.lang.Object))
Type mungers:
(BcelTypeMunger ResolvedTypeMunger(Method, java.lang.Object org.springframework.beans.factory.aspectj.AbstractInterfaceDrivenDependencyInjectionAspect$ConfigurableDeserializationSupport.readResolve()))
(BcelTypeMunger ExposeTypeMunger(java.lang.Object))
(BcelTypeMunger ExposeTypeMunger(java.lang.Object))
(BcelTypeMunger ExposeTypeMunger(java.lang.Object))
(BcelTypeMunger ExposeTypeMunger(org.springframework.beans.factory.aspectj.ConfigurableObject))
(BcelTypeMunger ExposeTypeMunger(org.springframework.beans.factory.aspectj.AbstractInterfaceDrivenDependencyInjectionAspect$ConfigurableDeserializationSupport))
Late Type mungers:
Empty
