---- AspectJ Properties ---
AspectJ Compiler 1.6.2 built on Saturday Oct 4, 2008 at 05:47:07 GMT
---- Dump Properties ---
Dump file: ajcore.20160604.114258.455.txt
Dump reason: org.aspectj.bridge.AbortException
Dump on exception: true
Dump at exit condition: abort
---- Exception Information ---
Message: abort trouble in: 
 class org.springframework.beans.TypeConverterDelegate extends java.lang.Object:
  private static final org.apache.commons.logging.Log logger
  private final org.springframework.beans.PropertyEditorRegistrySupport propertyEditorRegistry
  private final Object targetObject
  static void <clinit>():
    staticinitialization(void org.springframework.beans.TypeConverterDelegate.<clinit>())
    |               LDC org.springframework.beans.TypeConverterDelegate   (line 53)
    |               INVOKESTATIC org.apache.commons.logging.LogFactory.getLog (Ljava/lang/Class;)Lorg/apache/commons/logging/Log;
    |               PUTSTATIC org.springframework.beans.TypeConverterDelegate.logger Lorg/apache/commons/logging/Log;
    |               RETURN   (line 51)
    staticinitialization(void org.springframework.beans.TypeConverterDelegate.<clinit>())
  end static void <clinit>()

  public void <init>(org.springframework.beans.PropertyEditorRegistrySupport):
                    ALOAD_0     // Lorg/springframework/beans/TypeConverterDelegate; this   (line 65)
                    ALOAD_1     // Lorg/springframework/beans/PropertyEditorRegistrySupport; propertyEditorRegistry
                    ACONST_NULL
                    INVOKESPECIAL org.springframework.beans.TypeConverterDelegate.<init> (Lorg/springframework/beans/PropertyEditorRegistrySupport;Ljava/lang/Object;)V
    constructor-execution(void org.springframework.beans.TypeConverterDelegate.<init>(org.springframework.beans.PropertyEditorRegistrySupport))
    |               RETURN   (line 66)
    constructor-execution(void org.springframework.beans.TypeConverterDelegate.<init>(org.springframework.beans.PropertyEditorRegistrySupport))
  end public void <init>(org.springframework.beans.PropertyEditorRegistrySupport)

  public void <init>(org.springframework.beans.PropertyEditorRegistrySupport, Object):
                    ALOAD_0     // Lorg/springframework/beans/TypeConverterDelegate; this   (line 73)
                    INVOKESPECIAL java.lang.Object.<init> ()V
    constructor-execution(void org.springframework.beans.TypeConverterDelegate.<init>(org.springframework.beans.PropertyEditorRegistrySupport, java.lang.Object))
    |               ALOAD_0     // Lorg/springframework/beans/TypeConverterDelegate; this   (line 74)
    |               ALOAD_1     // Lorg/springframework/beans/PropertyEditorRegistrySupport; propertyEditorRegistry
    |               PUTFIELD org.springframework.beans.TypeConverterDelegate.propertyEditorRegistry Lorg/springframework/beans/PropertyEditorRegistrySupport;
    |               ALOAD_0     // Lorg/springframework/beans/TypeConverterDelegate; this   (line 75)
    |               ALOAD_2     // Ljava/lang/Object; targetObject
    |               PUTFIELD org.springframework.beans.TypeConverterDelegate.targetObject Ljava/lang/Object;
    |               RETURN   (line 76)
    constructor-execution(void org.springframework.beans.TypeConverterDelegate.<init>(org.springframework.beans.PropertyEditorRegistrySupport, java.lang.Object))
  end public void <init>(org.springframework.beans.PropertyEditorRegistrySupport, Object)

  public Object convertIfNecessary(Object, Class, org.springframework.core.MethodParameter) throws java.lang.IllegalArgumentException:
                    ALOAD_0     // Lorg/springframework/beans/TypeConverterDelegate; this   (line 92)
                    ACONST_NULL
                    ACONST_NULL
                    ALOAD_1     // Ljava/lang/Object; newValue
                    ALOAD_2     // Ljava/lang/Class; requiredType
                    ALOAD_3     // Lorg/springframework/core/MethodParameter; methodParam   (line 93)
                    IFNULL L0
                    NEW org.springframework.core.convert.TypeDescriptor
                    DUP
                    ALOAD_3     // Lorg/springframework/core/MethodParameter; methodParam
                    INVOKESPECIAL org.springframework.core.convert.TypeDescriptor.<init> (Lorg/springframework/core/MethodParameter;)V
                    GOTO L1
                L0: ALOAD_2     // Ljava/lang/Class; requiredType
                    INVOKESTATIC org.springframework.core.convert.TypeDescriptor.valueOf (Ljava/lang/Class;)Lorg/springframework/core/convert/TypeDescriptor;
                L1: INVOKEVIRTUAL org.springframework.beans.TypeConverterDelegate.convertIfNecessary (Ljava/lang/String;Ljava/lang/Object;Ljava/lang/Object;Ljava/lang/Class;Lorg/springframework/core/convert/TypeDescriptor;)Ljava/lang/Object;   (line 92)
                    ARETURN
  end public Object convertIfNecessary(Object, Class, org.springframework.core.MethodParameter) throws java.lang.IllegalArgumentException

  public Object convertIfNecessary(String, Object, Object, Class) throws java.lang.IllegalArgumentException:
                    ALOAD_0     // Lorg/springframework/beans/TypeConverterDelegate; this   (line 110)
                    ALOAD_1     // Ljava/lang/String; propertyName
                    ALOAD_2     // Ljava/lang/Object; oldValue
                    ALOAD_3     // Ljava/lang/Object; newValue
                    ALOAD 4     // Ljava/lang/Class; requiredType
                    ALOAD 4     // Ljava/lang/Class; requiredType
                    INVOKESTATIC org.springframework.core.convert.TypeDescriptor.valueOf (Ljava/lang/Class;)Lorg/springframework/core/convert/TypeDescriptor;
                    INVOKEVIRTUAL org.springframework.beans.TypeConverterDelegate.convertIfNecessary (Ljava/lang/String;Ljava/lang/Object;Ljava/lang/Object;Ljava/lang/Class;Lorg/springframework/core/convert/TypeDescriptor;)Ljava/lang/Object;
                    ARETURN
  end public Object convertIfNecessary(String, Object, Object, Class) throws java.lang.IllegalArgumentException

  public Object convertIfNecessary(String, Object, Object, Class, org.springframework.core.convert.TypeDescriptor) throws java.lang.IllegalArgumentException:
                    ALOAD_3     // Ljava/lang/Object; newValue   (line 129)
                    ASTORE 6
                    ALOAD_0     // Lorg/springframework/beans/TypeConverterDelegate; this   (line 132)
                    GETFIELD org.springframework.beans.TypeConverterDelegate.propertyEditorRegistry Lorg/springframework/beans/PropertyEditorRegistrySupport;
                    ALOAD 4     // Ljava/lang/Class; requiredType
                    ALOAD_1     // Ljava/lang/String; propertyName
                    INVOKEVIRTUAL org.springframework.beans.PropertyEditorRegistrySupport.findCustomEditor (Ljava/lang/Class;Ljava/lang/String;)Ljava/beans/PropertyEditor;
                    ASTORE 7
                    ACONST_NULL   (line 134)
                    ASTORE 8
                    ALOAD_0     // Lorg/springframework/beans/TypeConverterDelegate; this   (line 137)
                    GETFIELD org.springframework.beans.TypeConverterDelegate.propertyEditorRegistry Lorg/springframework/beans/PropertyEditorRegistrySupport;
                    INVOKEVIRTUAL org.springframework.beans.PropertyEditorRegistrySupport.getConversionService ()Lorg/springframework/core/convert/ConversionService;
                    ASTORE 9
                    ALOAD 7     // Ljava/beans/PropertyEditor; editor   (line 138)
                    IFNONNULL L0
                    ALOAD 9     // Lorg/springframework/core/convert/ConversionService; conversionService
                    IFNULL L0
                    ALOAD 6     // Ljava/lang/Object; convertedValue
                    IFNULL L0
                    ALOAD 5     // Lorg/springframework/core/convert/TypeDescriptor; typeDescriptor
                    IFNULL L0
                    ALOAD_3     // Ljava/lang/Object; newValue   (line 139)
                    INVOKESTATIC org.springframework.core.convert.TypeDescriptor.forObject (Ljava/lang/Object;)Lorg/springframework/core/convert/TypeDescriptor;
                    ASTORE 10
                    ALOAD 5     // Lorg/springframework/core/convert/TypeDescriptor; typeDescriptor   (line 140)
                    ASTORE 11
                    ALOAD 9     // Lorg/springframework/core/convert/ConversionService; conversionService   (line 141)
                    ALOAD 10     // Lorg/springframework/core/convert/TypeDescriptor; sourceTypeDesc
                    ALOAD 11     // Lorg/springframework/core/convert/TypeDescriptor; targetTypeDesc
                    INVOKEINTERFACE org.springframework.core.convert.ConversionService.canConvert (Lorg/springframework/core/convert/TypeDescriptor;Lorg/springframework/core/convert/TypeDescriptor;)Z
                    IFEQ L0
    catch org.springframework.core.convert.ConversionFailedException -> E0
    |               ALOAD 9     // Lorg/springframework/core/convert/ConversionService; conversionService   (line 143)
    |               ALOAD 6     // Ljava/lang/Object; convertedValue
    |               ALOAD 10     // Lorg/springframework/core/convert/TypeDescriptor; sourceTypeDesc
    |               ALOAD 11     // Lorg/springframework/core/convert/TypeDescriptor; targetTypeDesc
    |               INVOKEINTERFACE org.springframework.core.convert.ConversionService.convert (Ljava/lang/Object;Lorg/springframework/core/convert/TypeDescriptor;Lorg/springframework/core/convert/TypeDescriptor;)Ljava/lang/Object;
    catch org.springframework.core.convert.ConversionFailedException -> E0
                    ARETURN
                E0: ASTORE 12   (line 145)
                    ALOAD 12     // Lorg/springframework/core/convert/ConversionFailedException; ex   (line 147)
                    ASTORE 8     // Lorg/springframework/core/convert/ConversionFailedException; firstAttemptEx
                L0: ALOAD 7     // Ljava/beans/PropertyEditor; editor   (line 153)
                    IFNONNULL L1
                    ALOAD 4     // Ljava/lang/Class; requiredType
                    IFNULL L4
                    ALOAD 4     // Ljava/lang/Class; requiredType
                    ALOAD 6     // Ljava/lang/Object; convertedValue
                    INVOKESTATIC org.springframework.util.ClassUtils.isAssignableValue (Ljava/lang/Class;Ljava/lang/Object;)Z
                    IFNE L4
                L1: ALOAD 4     // Ljava/lang/Class; requiredType   (line 154)
                    IFNULL L2
                    LDC java.util.Collection
                    ALOAD 4     // Ljava/lang/Class; requiredType
                    INVOKEVIRTUAL java.lang.Class.isAssignableFrom (Ljava/lang/Class;)Z
                    IFEQ L2
                    ALOAD 6     // Ljava/lang/Object; convertedValue
                    INSTANCEOF java.lang.String
                    IFEQ L2
                    ALOAD 5     // Lorg/springframework/core/convert/TypeDescriptor; typeDescriptor   (line 155)
                    INVOKEVIRTUAL org.springframework.core.convert.TypeDescriptor.getElementTypeDescriptor ()Lorg/springframework/core/convert/TypeDescriptor;
                    ASTORE 10
                    ALOAD 10     // Lorg/springframework/core/convert/TypeDescriptor; elementType   (line 156)
                    IFNULL L2
                    LDC java.lang.Enum
                    ALOAD 10     // Lorg/springframework/core/convert/TypeDescriptor; elementType
                    INVOKEVIRTUAL org.springframework.core.convert.TypeDescriptor.getType ()Ljava/lang/Class;
                    INVOKEVIRTUAL java.lang.Class.isAssignableFrom (Ljava/lang/Class;)Z
                    IFEQ L2
                    ALOAD 6     // Ljava/lang/Object; convertedValue   (line 157)
                    CHECKCAST java.lang.String
                    INVOKESTATIC org.springframework.util.StringUtils.commaDelimitedListToStringArray (Ljava/lang/String;)[Ljava/lang/String;
                    ASTORE 6     // Ljava/lang/Object; convertedValue
                L2: ALOAD 7     // Ljava/beans/PropertyEditor; editor   (line 160)
                    IFNONNULL L3
                    ALOAD_0     // Lorg/springframework/beans/TypeConverterDelegate; this   (line 161)
                    ALOAD 4     // Ljava/lang/Class; requiredType
                    ALOAD 5     // Lorg/springframework/core/convert/TypeDescriptor; typeDescriptor
                    INVOKEVIRTUAL org.springframework.beans.TypeConverterDelegate.findDefaultEditor (Ljava/lang/Class;Lorg/springframework/core/convert/TypeDescriptor;)Ljava/beans/PropertyEditor;
                    ASTORE 7     // Ljava/beans/PropertyEditor; editor
                L3: ALOAD_0     // Lorg/springframework/beans/TypeConverterDelegate; this   (line 163)
                    ALOAD_2     // Ljava/lang/Object; oldValue
                    ALOAD 6     // Ljava/lang/Object; convertedValue
                    ALOAD 4     // Ljava/lang/Class; requiredType
                    ALOAD 7     // Ljava/beans/PropertyEditor; editor
                    INVOKEVIRTUAL org.springframework.beans.TypeConverterDelegate.doConvertValue (Ljava/lang/Object;Ljava/lang/Object;Ljava/lang/Class;Ljava/beans/PropertyEditor;)Ljava/lang/Object;
                    ASTORE 6     // Ljava/lang/Object; convertedValue
                L4: ALOAD 4     // Ljava/lang/Class; requiredType   (line 166)
                    IFNULL L17
                    ALOAD 6     // Ljava/lang/Object; convertedValue   (line 169)
                    IFNULL L13
                    ALOAD 4     // Ljava/lang/Class; requiredType   (line 170)
                    INVOKEVIRTUAL java.lang.Class.isArray ()Z
                    IFEQ L6
                    ALOAD 6     // Ljava/lang/Object; convertedValue   (line 172)
                    INSTANCEOF java.lang.String
                    IFEQ L5
                    LDC java.lang.Enum
                    ALOAD 4     // Ljava/lang/Class; requiredType
                    INVOKEVIRTUAL java.lang.Class.getComponentType ()Ljava/lang/Class;
                    INVOKEVIRTUAL java.lang.Class.isAssignableFrom (Ljava/lang/Class;)Z
                    IFEQ L5
                    ALOAD 6     // Ljava/lang/Object; convertedValue   (line 173)
                    CHECKCAST java.lang.String
                    INVOKESTATIC org.springframework.util.StringUtils.commaDelimitedListToStringArray (Ljava/lang/String;)[Ljava/lang/String;
                    ASTORE 6     // Ljava/lang/Object; convertedValue
                L5: ALOAD_0     // Lorg/springframework/beans/TypeConverterDelegate; this   (line 175)
                    ALOAD 6     // Ljava/lang/Object; convertedValue
                    ALOAD_1     // Ljava/lang/String; propertyName
                    ALOAD 4     // Ljava/lang/Class; requiredType
                    INVOKEVIRTUAL java.lang.Class.getComponentType ()Ljava/lang/Class;
                    INVOKEVIRTUAL org.springframework.beans.TypeConverterDelegate.convertToTypedArray (Ljava/lang/Object;Ljava/lang/String;Ljava/lang/Class;)Ljava/lang/Object;
                    ARETURN
                L6: ALOAD 6     // Ljava/lang/Object; convertedValue   (line 177)
                    INSTANCEOF java.util.Collection
                    IFEQ L7
                    ALOAD_0     // Lorg/springframework/beans/TypeConverterDelegate; this   (line 179)
                    ALOAD 6     // Ljava/lang/Object; convertedValue   (line 180)
                    CHECKCAST java.util.Collection
                    ALOAD_1     // Ljava/lang/String; propertyName
                    ALOAD 4     // Ljava/lang/Class; requiredType
                    ALOAD 5     // Lorg/springframework/core/convert/TypeDescriptor; typeDescriptor
                    INVOKEVIRTUAL org.springframework.beans.TypeConverterDelegate.convertToTypedCollection (Ljava/util/Collection;Ljava/lang/String;Ljava/lang/Class;Lorg/springframework/core/convert/TypeDescriptor;)Ljava/util/Collection;   (line 179)
                    ASTORE 6     // Ljava/lang/Object; convertedValue
                    GOTO L8
                L7: ALOAD 6     // Ljava/lang/Object; convertedValue   (line 182)
                    INSTANCEOF java.util.Map
                    IFEQ L8
                    ALOAD_0     // Lorg/springframework/beans/TypeConverterDelegate; this   (line 184)
                    ALOAD 6     // Ljava/lang/Object; convertedValue   (line 185)
                    CHECKCAST java.util.Map
                    ALOAD_1     // Ljava/lang/String; propertyName
                    ALOAD 4     // Ljava/lang/Class; requiredType
                    ALOAD 5     // Lorg/springframework/core/convert/TypeDescriptor; typeDescriptor
                    INVOKEVIRTUAL org.springframework.beans.TypeConverterDelegate.convertToTypedMap (Ljava/util/Map;Ljava/lang/String;Ljava/lang/Class;Lorg/springframework/core/convert/TypeDescriptor;)Ljava/util/Map;   (line 184)
                    ASTORE 6     // Ljava/lang/Object; convertedValue
                L8: ALOAD 6     // Ljava/lang/Object; convertedValue   (line 187)
                    INVOKEVIRTUAL java.lang.Object.getClass ()Ljava/lang/Class;
                    INVOKEVIRTUAL java.lang.Class.isArray ()Z
                    IFEQ L9
                    ALOAD 6     // Ljava/lang/Object; convertedValue
                    INVOKESTATIC java.lang.reflect.Array.getLength (Ljava/lang/Object;)I
                    ICONST_1
                    IF_ICMPNE L9
                    ALOAD 6     // Ljava/lang/Object; convertedValue   (line 188)
                    ICONST_0
                    INVOKESTATIC java.lang.reflect.Array.get (Ljava/lang/Object;I)Ljava/lang/Object;
                    ASTORE 6     // Ljava/lang/Object; convertedValue
                L9: LDC java.lang.String   (line 190)
                    ALOAD 4     // Ljava/lang/Class; requiredType
                    INVOKEVIRTUAL java.lang.Object.equals (Ljava/lang/Object;)Z
                    IFEQ L10
                    ALOAD 6     // Ljava/lang/Object; convertedValue
                    INVOKEVIRTUAL java.lang.Object.getClass ()Ljava/lang/Class;
                    INVOKESTATIC org.springframework.util.ClassUtils.isPrimitiveOrWrapper (Ljava/lang/Class;)Z
                    IFEQ L10
                    ALOAD 6     // Ljava/lang/Object; convertedValue   (line 192)
                    INVOKEVIRTUAL java.lang.Object.toString ()Ljava/lang/String;
                    ARETURN
               L10: ALOAD 6     // Ljava/lang/Object; convertedValue   (line 194)
                    INSTANCEOF java.lang.String
                    IFEQ L13
                    ALOAD 4     // Ljava/lang/Class; requiredType
                    ALOAD 6     // Ljava/lang/Object; convertedValue
                    INVOKEVIRTUAL java.lang.Class.isInstance (Ljava/lang/Object;)Z
                    IFNE L13
                    ALOAD 4     // Ljava/lang/Class; requiredType   (line 195)
                    INVOKEVIRTUAL java.lang.Class.isInterface ()Z
                    IFNE L11
                    ALOAD 4     // Ljava/lang/Class; requiredType
                    INVOKEVIRTUAL java.lang.Class.isEnum ()Z
                    IFNE L11
    catch java.lang.Exception -> E2
    | catch java.lang.NoSuchMethodException -> E1
    | |             ALOAD 4     // Ljava/lang/Class; requiredType   (line 197)
    | |             ICONST_1
    | |             ANEWARRAY java.lang.Class
    | |             DUP
    | |             ICONST_0
    | |             LDC java.lang.String
    | |             AASTORE
    | |             INVOKEVIRTUAL java.lang.Class.getConstructor ([Ljava/lang/Class;)Ljava/lang/reflect/Constructor;
    | |             ASTORE 10
    | |             ALOAD 10     // Ljava/lang/reflect/Constructor; strCtor   (line 198)
    | |             ICONST_1
    | |             ANEWARRAY java.lang.Object
    | |             DUP
    | |             ICONST_0
    | |             ALOAD 6     // Ljava/lang/Object; convertedValue
    | |             AASTORE
    | |             INVOKESTATIC org.springframework.beans.BeanUtils.instantiateClass (Ljava/lang/reflect/Constructor;[Ljava/lang/Object;)Ljava/lang/Object;
    | catch java.lang.NoSuchMethodException -> E1
    catch java.lang.Exception -> E2
                    ARETURN
                E1: ASTORE 10   (line 200)
                    GETSTATIC org.springframework.beans.TypeConverterDelegate.logger Lorg/apache/commons/logging/Log;   (line 202)
                    INVOKEINTERFACE org.apache.commons.logging.Log.isTraceEnabled ()Z
                    IFEQ L11
                    GETSTATIC org.springframework.beans.TypeConverterDelegate.logger Lorg/apache/commons/logging/Log;   (line 203)
                    NEW java.lang.StringBuilder
                    DUP
                    LDC "No String constructor found on type ["
                    INVOKESPECIAL java.lang.StringBuilder.<init> (Ljava/lang/String;)V
                    ALOAD 4     // Ljava/lang/Class; requiredType
                    INVOKEVIRTUAL java.lang.Class.getName ()Ljava/lang/String;
                    INVOKEVIRTUAL java.lang.StringBuilder.append (Ljava/lang/String;)Ljava/lang/StringBuilder;
                    LDC "]"
                    INVOKEVIRTUAL java.lang.StringBuilder.append (Ljava/lang/String;)Ljava/lang/StringBuilder;
                    INVOKEVIRTUAL java.lang.StringBuilder.toString ()Ljava/lang/String;
                    ALOAD 10     // Ljava/lang/NoSuchMethodException; ex
                    INVOKEINTERFACE org.apache.commons.logging.Log.trace (Ljava/lang/Object;Ljava/lang/Throwable;)V
                    GOTO L11
                E2: ASTORE 10   (line 206)
                    GETSTATIC org.springframework.beans.TypeConverterDelegate.logger Lorg/apache/commons/logging/Log;   (line 207)
                    INVOKEINTERFACE org.apache.commons.logging.Log.isDebugEnabled ()Z
                    IFEQ L11
                    GETSTATIC org.springframework.beans.TypeConverterDelegate.logger Lorg/apache/commons/logging/Log;   (line 208)
                    NEW java.lang.StringBuilder
                    DUP
                    LDC "Construction via String failed for type ["
                    INVOKESPECIAL java.lang.StringBuilder.<init> (Ljava/lang/String;)V
                    ALOAD 4     // Ljava/lang/Class; requiredType
                    INVOKEVIRTUAL java.lang.Class.getName ()Ljava/lang/String;
                    INVOKEVIRTUAL java.lang.StringBuilder.append (Ljava/lang/String;)Ljava/lang/StringBuilder;
                    LDC "]"
                    INVOKEVIRTUAL java.lang.StringBuilder.append (Ljava/lang/String;)Ljava/lang/StringBuilder;
                    INVOKEVIRTUAL java.lang.StringBuilder.toString ()Ljava/lang/String;
                    ALOAD 10     // Ljava/lang/Exception; ex
                    INVOKEINTERFACE org.apache.commons.logging.Log.debug (Ljava/lang/Object;Ljava/lang/Throwable;)V
               L11: ALOAD 6     // Ljava/lang/Object; convertedValue   (line 212)
                    CHECKCAST java.lang.String
                    INVOKEVIRTUAL java.lang.String.trim ()Ljava/lang/String;
                    ASTORE 10
                    ALOAD 4     // Ljava/lang/Class; requiredType   (line 213)
                    INVOKEVIRTUAL java.lang.Class.isEnum ()Z
                    IFEQ L12
                    LDC ""
                    ALOAD 10     // Ljava/lang/String; trimmedValue
                    INVOKEVIRTUAL java.lang.String.equals (Ljava/lang/Object;)Z
                    IFEQ L12
                    ACONST_NULL   (line 215)
                    ARETURN
               L12: ALOAD_0     // Lorg/springframework/beans/TypeConverterDelegate; this   (line 218)
                    ALOAD 4     // Ljava/lang/Class; requiredType
                    ALOAD 10     // Ljava/lang/String; trimmedValue
                    ALOAD 6     // Ljava/lang/Object; convertedValue
                    INVOKESPECIAL org.springframework.beans.TypeConverterDelegate.attemptToConvertStringToEnum (Ljava/lang/Class;Ljava/lang/String;Ljava/lang/Object;)Ljava/lang/Object;
                    ASTORE 6     // Ljava/lang/Object; convertedValue
               L13: ALOAD 4     // Ljava/lang/Class; requiredType   (line 222)
                    ALOAD 6     // Ljava/lang/Object; convertedValue
                    INVOKESTATIC org.springframework.util.ClassUtils.isAssignableValue (Ljava/lang/Class;Ljava/lang/Object;)Z
                    IFNE L17
                    ALOAD 8     // Lorg/springframework/core/convert/ConversionFailedException; firstAttemptEx   (line 223)
                    IFNULL L14
                    ALOAD 8     // Lorg/springframework/core/convert/ConversionFailedException; firstAttemptEx   (line 224)
                    ATHROW
               L14: NEW java.lang.StringBuilder   (line 227)
                    DUP
                    INVOKESPECIAL java.lang.StringBuilder.<init> ()V
                    ASTORE 10
                    ALOAD 10     // Ljava/lang/StringBuilder; msg   (line 228)
                    LDC "Cannot convert value of type ["
                    INVOKEVIRTUAL java.lang.StringBuilder.append (Ljava/lang/String;)Ljava/lang/StringBuilder;
                    ALOAD_3     // Ljava/lang/Object; newValue
                    INVOKESTATIC org.springframework.util.ClassUtils.getDescriptiveType (Ljava/lang/Object;)Ljava/lang/String;
                    INVOKEVIRTUAL java.lang.StringBuilder.append (Ljava/lang/String;)Ljava/lang/StringBuilder;
                    POP
                    ALOAD 10     // Ljava/lang/StringBuilder; msg   (line 229)
                    LDC "] to required type ["
                    INVOKEVIRTUAL java.lang.StringBuilder.append (Ljava/lang/String;)Ljava/lang/StringBuilder;
                    ALOAD 4     // Ljava/lang/Class; requiredType
                    INVOKESTATIC org.springframework.util.ClassUtils.getQualifiedName (Ljava/lang/Class;)Ljava/lang/String;
                    INVOKEVIRTUAL java.lang.StringBuilder.append (Ljava/lang/String;)Ljava/lang/StringBuilder;
                    LDC "]"
                    INVOKEVIRTUAL java.lang.StringBuilder.append (Ljava/lang/String;)Ljava/lang/StringBuilder;
                    POP
                    ALOAD_1     // Ljava/lang/String; propertyName   (line 230)
                    IFNULL L15
                    ALOAD 10     // Ljava/lang/StringBuilder; msg   (line 231)
                    LDC " for property '"
                    INVOKEVIRTUAL java.lang.StringBuilder.append (Ljava/lang/String;)Ljava/lang/StringBuilder;
                    ALOAD_1     // Ljava/lang/String; propertyName
                    INVOKEVIRTUAL java.lang.StringBuilder.append (Ljava/lang/String;)Ljava/lang/StringBuilder;
                    LDC_W "'"
                    INVOKEVIRTUAL java.lang.StringBuilder.append (Ljava/lang/String;)Ljava/lang/StringBuilder;
                    POP
               L15: ALOAD 7     // Ljava/beans/PropertyEditor; editor   (line 233)
                    IFNULL L16
                    ALOAD 10     // Ljava/lang/StringBuilder; msg   (line 234)
                    LDC_W ": PropertyEditor ["
                    INVOKEVIRTUAL java.lang.StringBuilder.append (Ljava/lang/String;)Ljava/lang/StringBuilder;
                    ALOAD 7     // Ljava/beans/PropertyEditor; editor
                    INVOKEVIRTUAL java.lang.Object.getClass ()Ljava/lang/Class;
                    INVOKEVIRTUAL java.lang.Class.getName ()Ljava/lang/String;
                    INVOKEVIRTUAL java.lang.StringBuilder.append (Ljava/lang/String;)Ljava/lang/StringBuilder;
                    LDC_W "] returned inappropriate value of type ["   (line 235)
                    INVOKEVIRTUAL java.lang.StringBuilder.append (Ljava/lang/String;)Ljava/lang/StringBuilder;   (line 234)
                    ALOAD 6     // Ljava/lang/Object; convertedValue   (line 236)
                    INVOKESTATIC org.springframework.util.ClassUtils.getDescriptiveType (Ljava/lang/Object;)Ljava/lang/String;
                    INVOKEVIRTUAL java.lang.StringBuilder.append (Ljava/lang/String;)Ljava/lang/StringBuilder;   (line 235)
                    LDC "]"   (line 236)
                    INVOKEVIRTUAL java.lang.StringBuilder.append (Ljava/lang/String;)Ljava/lang/StringBuilder;
                    POP
                    NEW java.lang.IllegalArgumentException   (line 237)
                    DUP
                    ALOAD 10     // Ljava/lang/StringBuilder; msg
                    INVOKEVIRTUAL java.lang.StringBuilder.toString ()Ljava/lang/String;
                    INVOKESPECIAL java.lang.IllegalArgumentException.<init> (Ljava/lang/String;)V
                    ATHROW
               L16: ALOAD 10     // Ljava/lang/StringBuilder; msg   (line 240)
                    LDC_W ": no matching editors or conversion strategy found"
                    INVOKEVIRTUAL java.lang.StringBuilder.append (Ljava/lang/String;)Ljava/lang/StringBuilder;
                    POP
                    NEW java.lang.IllegalStateException   (line 241)
                    DUP
                    ALOAD 10     // Ljava/lang/StringBuilder; msg
                    INVOKEVIRTUAL java.lang.StringBuilder.toString ()Ljava/lang/String;
                    INVOKESPECIAL java.lang.IllegalStateException.<init> (Ljava/lang/String;)V
                    ATHROW
               L17: ALOAD 8     // Lorg/springframework/core/convert/ConversionFailedException; firstAttemptEx   (line 246)
                    IFNULL L19
                    ALOAD 7     // Ljava/beans/PropertyEditor; editor   (line 247)
                    IFNONNULL L18
                    ALOAD 6     // Ljava/lang/Object; convertedValue
                    ALOAD_3     // Ljava/lang/Object; newValue
                    IF_ACMPNE L18
                    ALOAD 8     // Lorg/springframework/core/convert/ConversionFailedException; firstAttemptEx   (line 248)
                    ATHROW
               L18: GETSTATIC org.springframework.beans.TypeConverterDelegate.logger Lorg/apache/commons/logging/Log;   (line 250)
                    LDC_W "Original ConversionService attempt failed - ignored since PropertyEditor based conversion eventually succeeded"
                    ALOAD 8     // Lorg/springframework/core/convert/ConversionFailedException; firstAttemptEx   (line 251)
                    INVOKEINTERFACE org.apache.commons.logging.Log.debug (Ljava/lang/Object;Ljava/lang/Throwable;)V   (line 250)
               L19: ALOAD 6     // Ljava/lang/Object; convertedValue   (line 254)
                    ARETURN
  end public Object convertIfNecessary(String, Object, Object, Class, org.springframework.core.convert.TypeDescriptor) throws java.lang.IllegalArgumentException

  private Object attemptToConvertStringToEnum(Class, String, Object):
                    ALOAD_3     // Ljava/lang/Object; currentConvertedValue   (line 258)
                    ASTORE 4
                    LDC java.lang.Enum   (line 260)
                    ALOAD_1     // Ljava/lang/Class; requiredType
                    INVOKEVIRTUAL java.lang.Object.equals (Ljava/lang/Object;)Z
                    IFEQ L0
                    ALOAD_2     // Ljava/lang/String; trimmedValue   (line 262)
                    LDC_W "."
                    INVOKEVIRTUAL java.lang.String.lastIndexOf (Ljava/lang/String;)I
                    ISTORE 5
                    ILOAD 5     // I index   (line 263)
                    ICONST_M1
                    IF_ICMPLE L0
                    ALOAD_2     // Ljava/lang/String; trimmedValue   (line 264)
                    ICONST_0
                    ILOAD 5     // I index
                    INVOKEVIRTUAL java.lang.String.substring (II)Ljava/lang/String;
                    ASTORE 6
                    ALOAD_2     // Ljava/lang/String; trimmedValue   (line 265)
                    ILOAD 5     // I index
                    ICONST_1
                    IADD
                    INVOKEVIRTUAL java.lang.String.substring (I)Ljava/lang/String;
                    ASTORE 7
                    ALOAD_0     // Lorg/springframework/beans/TypeConverterDelegate; this   (line 266)
                    GETFIELD org.springframework.beans.TypeConverterDelegate.targetObject Ljava/lang/Object;
                    INVOKEVIRTUAL java.lang.Object.getClass ()Ljava/lang/Class;
                    INVOKEVIRTUAL java.lang.Class.getClassLoader ()Ljava/lang/ClassLoader;
                    ASTORE 8
    catch java.lang.Throwable -> E1
    | catch java.lang.ClassNotFoundException -> E0
    | |             ALOAD 8     // Ljava/lang/ClassLoader; loader   (line 268)
    | |             ALOAD 6     // Ljava/lang/String; enumType
    | |             INVOKEVIRTUAL java.lang.ClassLoader.loadClass (Ljava/lang/String;)Ljava/lang/Class;
    | |             ASTORE 9
    | |             ALOAD 9     // Ljava/lang/Class; enumValueType   (line 269)
    | |             ALOAD 7     // Ljava/lang/String; fieldName
    | |             INVOKEVIRTUAL java.lang.Class.getField (Ljava/lang/String;)Ljava/lang/reflect/Field;
    | |             ASTORE 10
    | |             ALOAD 10     // Ljava/lang/reflect/Field; enumField   (line 270)
    | |             ACONST_NULL
    | |             INVOKEVIRTUAL java.lang.reflect.Field.get (Ljava/lang/Object;)Ljava/lang/Object;
    | |             ASTORE 4     // Ljava/lang/Object; convertedValue
    | catch java.lang.ClassNotFoundException -> E0
    catch java.lang.Throwable -> E1
                    GOTO L0
                E0: ASTORE 9   (line 272)
                    GETSTATIC org.springframework.beans.TypeConverterDelegate.logger Lorg/apache/commons/logging/Log;   (line 273)
                    INVOKEINTERFACE org.apache.commons.logging.Log.isTraceEnabled ()Z
                    IFEQ L0
                    GETSTATIC org.springframework.beans.TypeConverterDelegate.logger Lorg/apache/commons/logging/Log;   (line 274)
                    NEW java.lang.StringBuilder
                    DUP
                    LDC_W "Enum class ["
                    INVOKESPECIAL java.lang.StringBuilder.<init> (Ljava/lang/String;)V
                    ALOAD 6     // Ljava/lang/String; enumType
                    INVOKEVIRTUAL java.lang.StringBuilder.append (Ljava/lang/String;)Ljava/lang/StringBuilder;
                    LDC_W "] cannot be loaded from ["
                    INVOKEVIRTUAL java.lang.StringBuilder.append (Ljava/lang/String;)Ljava/lang/StringBuilder;
                    ALOAD 8     // Ljava/lang/ClassLoader; loader
                    INVOKEVIRTUAL java.lang.StringBuilder.append (Ljava/lang/Object;)Ljava/lang/StringBuilder;
                    LDC "]"
                    INVOKEVIRTUAL java.lang.StringBuilder.append (Ljava/lang/String;)Ljava/lang/StringBuilder;
                    INVOKEVIRTUAL java.lang.StringBuilder.toString ()Ljava/lang/String;
                    ALOAD 9     // Ljava/lang/ClassNotFoundException; ex
                    INVOKEINTERFACE org.apache.commons.logging.Log.trace (Ljava/lang/Object;Ljava/lang/Throwable;)V
                    GOTO L0
                E1: ASTORE 9   (line 277)
                    GETSTATIC org.springframework.beans.TypeConverterDelegate.logger Lorg/apache/commons/logging/Log;   (line 278)
                    INVOKEINTERFACE org.apache.commons.logging.Log.isTraceEnabled ()Z
                    IFEQ L0
                    GETSTATIC org.springframework.beans.TypeConverterDelegate.logger Lorg/apache/commons/logging/Log;   (line 279)
                    NEW java.lang.StringBuilder
                    DUP
                    LDC_W "Field ["
                    INVOKESPECIAL java.lang.StringBuilder.<init> (Ljava/lang/String;)V
                    ALOAD 7     // Ljava/lang/String; fieldName
                    INVOKEVIRTUAL java.lang.StringBuilder.append (Ljava/lang/String;)Ljava/lang/StringBuilder;
                    LDC_W "] isn't an enum value for type ["
                    INVOKEVIRTUAL java.lang.StringBuilder.append (Ljava/lang/String;)Ljava/lang/StringBuilder;
                    ALOAD 6     // Ljava/lang/String; enumType
                    INVOKEVIRTUAL java.lang.StringBuilder.append (Ljava/lang/String;)Ljava/lang/StringBuilder;
                    LDC "]"
                    INVOKEVIRTUAL java.lang.StringBuilder.append (Ljava/lang/String;)Ljava/lang/StringBuilder;
                    INVOKEVIRTUAL java.lang.StringBuilder.toString ()Ljava/lang/String;
                    ALOAD 9     // Ljava/lang/Throwable; ex
                    INVOKEINTERFACE org.apache.commons.logging.Log.trace (Ljava/lang/Object;Ljava/lang/Throwable;)V
                L0: ALOAD 4     // Ljava/lang/Object; convertedValue   (line 285)
                    ALOAD_3     // Ljava/lang/Object; currentConvertedValue
                    IF_ACMPNE L1
    catch java.lang.Throwable -> E2
    |               ALOAD_1     // Ljava/lang/Class; requiredType   (line 290)
    |               ALOAD_2     // Ljava/lang/String; trimmedValue
    |               INVOKEVIRTUAL java.lang.Class.getField (Ljava/lang/String;)Ljava/lang/reflect/Field;
    |               ASTORE 5
    |               ALOAD 5     // Ljava/lang/reflect/Field; enumField   (line 291)
    |               ACONST_NULL
    |               INVOKEVIRTUAL java.lang.reflect.Field.get (Ljava/lang/Object;)Ljava/lang/Object;
    |               ASTORE 4     // Ljava/lang/Object; convertedValue
    catch java.lang.Throwable -> E2
                    GOTO L1
                E2: ASTORE 5   (line 293)
                    GETSTATIC org.springframework.beans.TypeConverterDelegate.logger Lorg/apache/commons/logging/Log;   (line 294)
                    INVOKEINTERFACE org.apache.commons.logging.Log.isTraceEnabled ()Z
                    IFEQ L1
                    GETSTATIC org.springframework.beans.TypeConverterDelegate.logger Lorg/apache/commons/logging/Log;   (line 295)
                    NEW java.lang.StringBuilder
                    DUP
                    LDC_W "Field ["
                    INVOKESPECIAL java.lang.StringBuilder.<init> (Ljava/lang/String;)V
                    ALOAD 4     // Ljava/lang/Object; convertedValue
                    INVOKEVIRTUAL java.lang.StringBuilder.append (Ljava/lang/Object;)Ljava/lang/StringBuilder;
                    LDC_W "] isn't an enum value"
                    INVOKEVIRTUAL java.lang.StringBuilder.append (Ljava/lang/String;)Ljava/lang/StringBuilder;
                    INVOKEVIRTUAL java.lang.StringBuilder.toString ()Ljava/lang/String;
                    ALOAD 5     // Ljava/lang/Throwable; ex
                    INVOKEINTERFACE org.apache.commons.logging.Log.trace (Ljava/lang/Object;Ljava/lang/Throwable;)V
                L1: ALOAD 4     // Ljava/lang/Object; convertedValue   (line 301)
                    ARETURN
  end private Object attemptToConvertStringToEnum(Class, String, Object)

  protected java.beans.PropertyEditor findDefaultEditor(Class, org.springframework.core.convert.TypeDescriptor):
                    ACONST_NULL   (line 310)
                    ASTORE_3
                    ALOAD_3     // Ljava/beans/PropertyEditor; editor   (line 315)
                    IFNONNULL L0
                    ALOAD_1     // Ljava/lang/Class; requiredType
                    IFNULL L0
                    ALOAD_0     // Lorg/springframework/beans/TypeConverterDelegate; this   (line 317)
                    GETFIELD org.springframework.beans.TypeConverterDelegate.propertyEditorRegistry Lorg/springframework/beans/PropertyEditorRegistrySupport;
                    ALOAD_1     // Ljava/lang/Class; requiredType
                    INVOKEVIRTUAL org.springframework.beans.PropertyEditorRegistrySupport.getDefaultEditor (Ljava/lang/Class;)Ljava/beans/PropertyEditor;
                    ASTORE_3     // Ljava/beans/PropertyEditor; editor
                    ALOAD_3     // Ljava/beans/PropertyEditor; editor   (line 318)
                    IFNONNULL L0
                    LDC java.lang.String
                    ALOAD_1     // Ljava/lang/Class; requiredType
                    INVOKEVIRTUAL java.lang.Object.equals (Ljava/lang/Object;)Z
                    IFNE L0
                    ALOAD_1     // Ljava/lang/Class; requiredType   (line 320)
                    INVOKESTATIC org.springframework.beans.BeanUtils.findEditorByConvention (Ljava/lang/Class;)Ljava/beans/PropertyEditor;
                    ASTORE_3     // Ljava/beans/PropertyEditor; editor
                L0: ALOAD_3     // Ljava/beans/PropertyEditor; editor   (line 323)
                    ARETURN
  end protected java.beans.PropertyEditor findDefaultEditor(Class, org.springframework.core.convert.TypeDescriptor)

  protected Object doConvertValue(Object, Object, Class, java.beans.PropertyEditor):
                    ALOAD_2     // Ljava/lang/Object; newValue   (line 338)
                    ASTORE 5
                    ICONST_0   (line 339)
                    ISTORE 6
                    ALOAD 4     // Ljava/beans/PropertyEditor; editor   (line 341)
                    IFNULL L0
                    ALOAD_0     // Lorg/springframework/beans/TypeConverterDelegate; this   (line 342)
                    GETFIELD org.springframework.beans.TypeConverterDelegate.propertyEditorRegistry Lorg/springframework/beans/PropertyEditorRegistrySupport;
                    ALOAD 4     // Ljava/beans/PropertyEditor; editor
                    INVOKEVIRTUAL org.springframework.beans.PropertyEditorRegistrySupport.isSharedEditor (Ljava/beans/PropertyEditor;)Z
                    ISTORE 6     // Z sharedEditor
                L0: ALOAD 4     // Ljava/beans/PropertyEditor; editor   (line 345)
                    IFNULL L3
                    ALOAD 5     // Ljava/lang/Object; convertedValue
                    INSTANCEOF java.lang.String
                    IFNE L3
    catch java.lang.Exception -> E2
    |               ILOAD 6     // Z sharedEditor   (line 352)
    |               IFEQ L1
    |               ALOAD 4     // Ljava/beans/PropertyEditor; editor   (line 354)
    |               DUP
    |               ASTORE 8
    |               MONITORENTER
    | finally -> E1
    | |             ALOAD 4     // Ljava/beans/PropertyEditor; editor   (line 355)
    | |             ALOAD 5     // Ljava/lang/Object; convertedValue
    | |             INVOKEINTERFACE java.beans.PropertyEditor.setValue (Ljava/lang/Object;)V
    | |             ALOAD 4     // Ljava/beans/PropertyEditor; editor   (line 356)
    | |             INVOKEINTERFACE java.beans.PropertyEditor.getValue ()Ljava/lang/Object;
    | |             ASTORE 7
    | |             ALOAD 8   (line 354)
    | |             MONITOREXIT
    | finally -> E1
    |               GOTO L2
    | finally -> E1
    | |         E1: ALOAD 8
    | |             MONITOREXIT
    | finally -> E1
    |               ATHROW
    |           L1: ALOAD 4     // Ljava/beans/PropertyEditor; editor   (line 361)
    |               ALOAD 5     // Ljava/lang/Object; convertedValue
    |               INVOKEINTERFACE java.beans.PropertyEditor.setValue (Ljava/lang/Object;)V
    |               ALOAD 4     // Ljava/beans/PropertyEditor; editor   (line 362)
    |               INVOKEINTERFACE java.beans.PropertyEditor.getValue ()Ljava/lang/Object;
    |               ASTORE 7
    |           L2: ALOAD 7     // Ljava/lang/Object; newConvertedValue   (line 364)
    |               ALOAD 5     // Ljava/lang/Object; convertedValue
    |               IF_ACMPEQ L3
    |               ALOAD 7     // Ljava/lang/Object; newConvertedValue   (line 365)
    |               ASTORE 5     // Ljava/lang/Object; convertedValue
    |               ACONST_NULL   (line 368)
    |               ASTORE 4     // Ljava/beans/PropertyEditor; editor
    catch java.lang.Exception -> E2
                    GOTO L3
                E2: ASTORE 7   (line 371)
                    GETSTATIC org.springframework.beans.TypeConverterDelegate.logger Lorg/apache/commons/logging/Log;   (line 372)
                    INVOKEINTERFACE org.apache.commons.logging.Log.isDebugEnabled ()Z
                    IFEQ L3
                    GETSTATIC org.springframework.beans.TypeConverterDelegate.logger Lorg/apache/commons/logging/Log;   (line 373)
                    NEW java.lang.StringBuilder
                    DUP
                    LDC_W "PropertyEditor ["
                    INVOKESPECIAL java.lang.StringBuilder.<init> (Ljava/lang/String;)V
                    ALOAD 4     // Ljava/beans/PropertyEditor; editor
                    INVOKEVIRTUAL java.lang.Object.getClass ()Ljava/lang/Class;
                    INVOKEVIRTUAL java.lang.Class.getName ()Ljava/lang/String;
                    INVOKEVIRTUAL java.lang.StringBuilder.append (Ljava/lang/String;)Ljava/lang/StringBuilder;
                    LDC_W "] does not support setValue call"
                    INVOKEVIRTUAL java.lang.StringBuilder.append (Ljava/lang/String;)Ljava/lang/StringBuilder;
                    INVOKEVIRTUAL java.lang.StringBuilder.toString ()Ljava/lang/String;
                    ALOAD 7     // Ljava/lang/Exception; ex
                    INVOKEINTERFACE org.apache.commons.logging.Log.debug (Ljava/lang/Object;Ljava/lang/Throwable;)V
                L3: ALOAD 5     // Ljava/lang/Object; convertedValue   (line 379)
                    ASTORE 7
                    ALOAD_3     // Ljava/lang/Class; requiredType   (line 381)
                    IFNULL L5
                    ALOAD_3     // Ljava/lang/Class; requiredType
                    INVOKEVIRTUAL java.lang.Class.isArray ()Z
                    IFNE L5
                    ALOAD 5     // Ljava/lang/Object; convertedValue
                    INSTANCEOF [Ljava.lang.String;
                    IFEQ L5
                    GETSTATIC org.springframework.beans.TypeConverterDelegate.logger Lorg/apache/commons/logging/Log;   (line 385)
                    INVOKEINTERFACE org.apache.commons.logging.Log.isTraceEnabled ()Z
                    IFEQ L4
                    GETSTATIC org.springframework.beans.TypeConverterDelegate.logger Lorg/apache/commons/logging/Log;   (line 386)
                    NEW java.lang.StringBuilder
                    DUP
                    LDC_W "Converting String array to comma-delimited String ["
                    INVOKESPECIAL java.lang.StringBuilder.<init> (Ljava/lang/String;)V
                    ALOAD 5     // Ljava/lang/Object; convertedValue
                    INVOKEVIRTUAL java.lang.StringBuilder.append (Ljava/lang/Object;)Ljava/lang/StringBuilder;
                    LDC "]"
                    INVOKEVIRTUAL java.lang.StringBuilder.append (Ljava/lang/String;)Ljava/lang/StringBuilder;
                    INVOKEVIRTUAL java.lang.StringBuilder.toString ()Ljava/lang/String;
                    INVOKEINTERFACE org.apache.commons.logging.Log.trace (Ljava/lang/Object;)V
                L4: ALOAD 5     // Ljava/lang/Object; convertedValue   (line 388)
                    CHECKCAST [Ljava.lang.String;
                    INVOKESTATIC org.springframework.util.StringUtils.arrayToCommaDelimitedString ([Ljava/lang/Object;)Ljava/lang/String;
                    ASTORE 5     // Ljava/lang/Object; convertedValue
                L5: ALOAD 5     // Ljava/lang/Object; convertedValue   (line 391)
                    INSTANCEOF java.lang.String
                    IFEQ L9
                    ALOAD 4     // Ljava/beans/PropertyEditor; editor   (line 392)
                    IFNULL L8
                    GETSTATIC org.springframework.beans.TypeConverterDelegate.logger Lorg/apache/commons/logging/Log;   (line 394)
                    INVOKEINTERFACE org.apache.commons.logging.Log.isTraceEnabled ()Z
                    IFEQ L6
                    GETSTATIC org.springframework.beans.TypeConverterDelegate.logger Lorg/apache/commons/logging/Log;   (line 395)
                    NEW java.lang.StringBuilder
                    DUP
                    LDC_W "Converting String to ["
                    INVOKESPECIAL java.lang.StringBuilder.<init> (Ljava/lang/String;)V
                    ALOAD_3     // Ljava/lang/Class; requiredType
                    INVOKEVIRTUAL java.lang.StringBuilder.append (Ljava/lang/Object;)Ljava/lang/StringBuilder;
                    LDC_W "] using property editor ["
                    INVOKEVIRTUAL java.lang.StringBuilder.append (Ljava/lang/String;)Ljava/lang/StringBuilder;
                    ALOAD 4     // Ljava/beans/PropertyEditor; editor
                    INVOKEVIRTUAL java.lang.StringBuilder.append (Ljava/lang/Object;)Ljava/lang/StringBuilder;
                    LDC "]"
                    INVOKEVIRTUAL java.lang.StringBuilder.append (Ljava/lang/String;)Ljava/lang/StringBuilder;
                    INVOKEVIRTUAL java.lang.StringBuilder.toString ()Ljava/lang/String;
                    INVOKEINTERFACE org.apache.commons.logging.Log.trace (Ljava/lang/Object;)V
                L6: ALOAD 5     // Ljava/lang/Object; convertedValue   (line 397)
                    CHECKCAST java.lang.String
                    ASTORE 8
                    ILOAD 6     // Z sharedEditor   (line 398)
                    IFEQ L7
                    ALOAD 4     // Ljava/beans/PropertyEditor; editor   (line 400)
                    DUP
                    ASTORE 9
                    MONITORENTER
    finally -> E4
    |               ALOAD_0     // Lorg/springframework/beans/TypeConverterDelegate; this   (line 401)
    |               ALOAD_1     // Ljava/lang/Object; oldValue
    |               ALOAD 8     // Ljava/lang/String; newTextValue
    |               ALOAD 4     // Ljava/beans/PropertyEditor; editor
    |               INVOKEVIRTUAL org.springframework.beans.TypeConverterDelegate.doConvertTextValue (Ljava/lang/Object;Ljava/lang/String;Ljava/beans/PropertyEditor;)Ljava/lang/Object;
    |               ALOAD 9
    |               MONITOREXIT
    finally -> E4
                    ARETURN
    finally -> E4
    |           E4: ALOAD 9   (line 400)
    |               MONITOREXIT
    finally -> E4
                    ATHROW
                L7: ALOAD_0     // Lorg/springframework/beans/TypeConverterDelegate; this   (line 406)
                    ALOAD_1     // Ljava/lang/Object; oldValue
                    ALOAD 8     // Ljava/lang/String; newTextValue
                    ALOAD 4     // Ljava/beans/PropertyEditor; editor
                    INVOKEVIRTUAL org.springframework.beans.TypeConverterDelegate.doConvertTextValue (Ljava/lang/Object;Ljava/lang/String;Ljava/beans/PropertyEditor;)Ljava/lang/Object;
                    ARETURN
                L8: LDC java.lang.String   (line 409)
                    ALOAD_3     // Ljava/lang/Class; requiredType
                    INVOKEVIRTUAL java.lang.Object.equals (Ljava/lang/Object;)Z
                    IFEQ L9
                    ALOAD 5     // Ljava/lang/Object; convertedValue   (line 410)
                    ASTORE 7     // Ljava/lang/Object; returnValue
                L9: ALOAD 7     // Ljava/lang/Object; returnValue   (line 414)
                    ARETURN
  end protected Object doConvertValue(Object, Object, Class, java.beans.PropertyEditor)

  protected Object doConvertTextValue(Object, String, java.beans.PropertyEditor):
    catch java.lang.Exception -> E0
    |               ALOAD_3     // Ljava/beans/PropertyEditor; editor   (line 426)
    |               ALOAD_1     // Ljava/lang/Object; oldValue
    |               INVOKEINTERFACE java.beans.PropertyEditor.setValue (Ljava/lang/Object;)V
    catch java.lang.Exception -> E0
                    GOTO L0
                E0: ASTORE 4   (line 428)
                    GETSTATIC org.springframework.beans.TypeConverterDelegate.logger Lorg/apache/commons/logging/Log;   (line 429)
                    INVOKEINTERFACE org.apache.commons.logging.Log.isDebugEnabled ()Z
                    IFEQ L0
                    GETSTATIC org.springframework.beans.TypeConverterDelegate.logger Lorg/apache/commons/logging/Log;   (line 430)
                    NEW java.lang.StringBuilder
                    DUP
                    LDC_W "PropertyEditor ["
                    INVOKESPECIAL java.lang.StringBuilder.<init> (Ljava/lang/String;)V
                    ALOAD_3     // Ljava/beans/PropertyEditor; editor
                    INVOKEVIRTUAL java.lang.Object.getClass ()Ljava/lang/Class;
                    INVOKEVIRTUAL java.lang.Class.getName ()Ljava/lang/String;
                    INVOKEVIRTUAL java.lang.StringBuilder.append (Ljava/lang/String;)Ljava/lang/StringBuilder;
                    LDC_W "] does not support setValue call"
                    INVOKEVIRTUAL java.lang.StringBuilder.append (Ljava/lang/String;)Ljava/lang/StringBuilder;
                    INVOKEVIRTUAL java.lang.StringBuilder.toString ()Ljava/lang/String;
                    ALOAD 4     // Ljava/lang/Exception; ex
                    INVOKEINTERFACE org.apache.commons.logging.Log.debug (Ljava/lang/Object;Ljava/lang/Throwable;)V
                L0: ALOAD_3     // Ljava/beans/PropertyEditor; editor   (line 434)
                    ALOAD_2     // Ljava/lang/String; newTextValue
                    INVOKEINTERFACE java.beans.PropertyEditor.setAsText (Ljava/lang/String;)V
                    ALOAD_3     // Ljava/beans/PropertyEditor; editor   (line 435)
                    INVOKEINTERFACE java.beans.PropertyEditor.getValue ()Ljava/lang/Object;
                    ARETURN
  end protected Object doConvertTextValue(Object, String, java.beans.PropertyEditor)

  protected Object convertToTypedArray(Object, String, Class):
                    ALOAD_1     // Ljava/lang/Object; input   (line 439)
                    INSTANCEOF java.util.Collection
                    IFEQ L2
                    ALOAD_1     // Ljava/lang/Object; input   (line 441)
                    CHECKCAST java.util.Collection
                    ASTORE 4
                    ALOAD_3     // Ljava/lang/Class; componentType   (line 442)
                    ALOAD 4     // Ljava/util/Collection; coll
                    INVOKEINTERFACE java.util.Collection.size ()I
                    INVOKESTATIC java.lang.reflect.Array.newInstance (Ljava/lang/Class;I)Ljava/lang/Object;
                    ASTORE 5
                    ICONST_0   (line 443)
                    ISTORE 6
                    ALOAD 4     // Ljava/util/Collection; coll   (line 444)
                    INVOKEINTERFACE java.util.Collection.iterator ()Ljava/util/Iterator;
                    ASTORE 7
                    GOTO L1
                L0: ALOAD_0     // Lorg/springframework/beans/TypeConverterDelegate; this   (line 445)
                    ALOAD_0     // Lorg/springframework/beans/TypeConverterDelegate; this   (line 446)
                    ALOAD_2     // Ljava/lang/String; propertyName
                    ILOAD 6     // I i
                    INVOKESPECIAL org.springframework.beans.TypeConverterDelegate.buildIndexedPropertyName (Ljava/lang/String;I)Ljava/lang/String;
                    ACONST_NULL
                    ALOAD 7     // Ljava/util/Iterator; it
                    INVOKEINTERFACE java.util.Iterator.next ()Ljava/lang/Object;
                    ALOAD_3     // Ljava/lang/Class; componentType
                    INVOKEVIRTUAL org.springframework.beans.TypeConverterDelegate.convertIfNecessary (Ljava/lang/String;Ljava/lang/Object;Ljava/lang/Object;Ljava/lang/Class;)Ljava/lang/Object;   (line 445)
                    ASTORE 8
                    ALOAD 5     // Ljava/lang/Object; result   (line 447)
                    ILOAD 6     // I i
                    ALOAD 8     // Ljava/lang/Object; value
                    INVOKESTATIC java.lang.reflect.Array.set (Ljava/lang/Object;ILjava/lang/Object;)V
                    IINC 6 1     // I i   (line 444)
                L1: ALOAD 7     // Ljava/util/Iterator; it
                    INVOKEINTERFACE java.util.Iterator.hasNext ()Z
                    IFNE L0
                    ALOAD 5     // Ljava/lang/Object; result   (line 449)
                    ARETURN
                L2: ALOAD_1     // Ljava/lang/Object; input   (line 451)
                    INVOKEVIRTUAL java.lang.Object.getClass ()Ljava/lang/Class;
                    INVOKEVIRTUAL java.lang.Class.isArray ()Z
                    IFEQ L6
                    ALOAD_3     // Ljava/lang/Class; componentType   (line 453)
                    ALOAD_1     // Ljava/lang/Object; input
                    INVOKEVIRTUAL java.lang.Object.getClass ()Ljava/lang/Class;
                    INVOKEVIRTUAL java.lang.Class.getComponentType ()Ljava/lang/Class;
                    INVOKEVIRTUAL java.lang.Object.equals (Ljava/lang/Object;)Z
                    IFEQ L3
                    ALOAD_0     // Lorg/springframework/beans/TypeConverterDelegate; this   (line 454)
                    GETFIELD org.springframework.beans.TypeConverterDelegate.propertyEditorRegistry Lorg/springframework/beans/PropertyEditorRegistrySupport;
                    ALOAD_3     // Ljava/lang/Class; componentType
                    ALOAD_2     // Ljava/lang/String; propertyName
                    INVOKEVIRTUAL org.springframework.beans.PropertyEditorRegistrySupport.hasCustomEditorForElement (Ljava/lang/Class;Ljava/lang/String;)Z
                    IFNE L3
                    ALOAD_1     // Ljava/lang/Object; input   (line 455)
                    ARETURN
                L3: ALOAD_1     // Ljava/lang/Object; input   (line 457)
                    INVOKESTATIC java.lang.reflect.Array.getLength (Ljava/lang/Object;)I
                    ISTORE 4
                    ALOAD_3     // Ljava/lang/Class; componentType   (line 458)
                    ILOAD 4     // I arrayLength
                    INVOKESTATIC java.lang.reflect.Array.newInstance (Ljava/lang/Class;I)Ljava/lang/Object;
                    ASTORE 5
                    ICONST_0   (line 459)
                    ISTORE 6
                    GOTO L5
                L4: ALOAD_0     // Lorg/springframework/beans/TypeConverterDelegate; this   (line 460)
                    ALOAD_0     // Lorg/springframework/beans/TypeConverterDelegate; this   (line 461)
                    ALOAD_2     // Ljava/lang/String; propertyName
                    ILOAD 6     // I i
                    INVOKESPECIAL org.springframework.beans.TypeConverterDelegate.buildIndexedPropertyName (Ljava/lang/String;I)Ljava/lang/String;
                    ACONST_NULL
                    ALOAD_1     // Ljava/lang/Object; input
                    ILOAD 6     // I i
                    INVOKESTATIC java.lang.reflect.Array.get (Ljava/lang/Object;I)Ljava/lang/Object;
                    ALOAD_3     // Ljava/lang/Class; componentType
                    INVOKEVIRTUAL org.springframework.beans.TypeConverterDelegate.convertIfNecessary (Ljava/lang/String;Ljava/lang/Object;Ljava/lang/Object;Ljava/lang/Class;)Ljava/lang/Object;   (line 460)
                    ASTORE 7
                    ALOAD 5     // Ljava/lang/Object; result   (line 462)
                    ILOAD 6     // I i
                    ALOAD 7     // Ljava/lang/Object; value
                    INVOKESTATIC java.lang.reflect.Array.set (Ljava/lang/Object;ILjava/lang/Object;)V
                    IINC 6 1     // I i   (line 459)
                L5: ILOAD 6     // I i
                    ILOAD 4     // I arrayLength
                    IF_ICMPLT L4
                    ALOAD 5     // Ljava/lang/Object; result   (line 464)
                    ARETURN
                L6: ALOAD_3     // Ljava/lang/Class; componentType   (line 468)
                    ICONST_1
                    INVOKESTATIC java.lang.reflect.Array.newInstance (Ljava/lang/Class;I)Ljava/lang/Object;
                    ASTORE 4
                    ALOAD_0     // Lorg/springframework/beans/TypeConverterDelegate; this   (line 469)
                    ALOAD_0     // Lorg/springframework/beans/TypeConverterDelegate; this   (line 470)
                    ALOAD_2     // Ljava/lang/String; propertyName
                    ICONST_0
                    INVOKESPECIAL org.springframework.beans.TypeConverterDelegate.buildIndexedPropertyName (Ljava/lang/String;I)Ljava/lang/String;
                    ACONST_NULL
                    ALOAD_1     // Ljava/lang/Object; input
                    ALOAD_3     // Ljava/lang/Class; componentType
                    INVOKEVIRTUAL org.springframework.beans.TypeConverterDelegate.convertIfNecessary (Ljava/lang/String;Ljava/lang/Object;Ljava/lang/Object;Ljava/lang/Class;)Ljava/lang/Object;   (line 469)
                    ASTORE 5
                    ALOAD 4     // Ljava/lang/Object; result   (line 471)
                    ICONST_0
                    ALOAD 5     // Ljava/lang/Object; value
                    INVOKESTATIC java.lang.reflect.Array.set (Ljava/lang/Object;ILjava/lang/Object;)V
                    ALOAD 4     // Ljava/lang/Object; result   (line 472)
                    ARETURN
  end protected Object convertToTypedArray(Object, String, Class)

  protected java.util.Collection convertToTypedCollection(java.util.Collection, String, Class, org.springframework.core.convert.TypeDescriptor):
                    LDC java.util.Collection   (line 480)
                    ALOAD_3     // Ljava/lang/Class; requiredType
                    INVOKEVIRTUAL java.lang.Class.isAssignableFrom (Ljava/lang/Class;)Z
                    IFNE L0
                    ALOAD_1     // Ljava/util/Collection; original   (line 481)
                    ARETURN
                L0: ALOAD_3     // Ljava/lang/Class; requiredType   (line 484)
                    INVOKESTATIC org.springframework.core.CollectionFactory.isApproximableCollectionType (Ljava/lang/Class;)Z
                    ISTORE 5
                    ILOAD 5     // Z approximable   (line 485)
                    IFNE L2
                    ALOAD_0     // Lorg/springframework/beans/TypeConverterDelegate; this
                    ALOAD_3     // Ljava/lang/Class; requiredType
                    INVOKESPECIAL org.springframework.beans.TypeConverterDelegate.canCreateCopy (Ljava/lang/Class;)Z
                    IFNE L2
                    GETSTATIC org.springframework.beans.TypeConverterDelegate.logger Lorg/apache/commons/logging/Log;   (line 486)
                    INVOKEINTERFACE org.apache.commons.logging.Log.isDebugEnabled ()Z
                    IFEQ L1
                    GETSTATIC org.springframework.beans.TypeConverterDelegate.logger Lorg/apache/commons/logging/Log;   (line 487)
                    NEW java.lang.StringBuilder
                    DUP
                    LDC_W "Custom Collection type ["
                    INVOKESPECIAL java.lang.StringBuilder.<init> (Ljava/lang/String;)V
                    ALOAD_1     // Ljava/util/Collection; original
                    INVOKEVIRTUAL java.lang.Object.getClass ()Ljava/lang/Class;
                    INVOKEVIRTUAL java.lang.Class.getName ()Ljava/lang/String;
                    INVOKEVIRTUAL java.lang.StringBuilder.append (Ljava/lang/String;)Ljava/lang/StringBuilder;
                    LDC_W "] does not allow for creating a copy - injecting original Collection as-is"   (line 488)
                    INVOKEVIRTUAL java.lang.StringBuilder.append (Ljava/lang/String;)Ljava/lang/StringBuilder;
                    INVOKEVIRTUAL java.lang.StringBuilder.toString ()Ljava/lang/String;
                    INVOKEINTERFACE org.apache.commons.logging.Log.debug (Ljava/lang/Object;)V   (line 487)
                L1: ALOAD_1     // Ljava/util/Collection; original   (line 490)
                    ARETURN
                L2: ALOAD_3     // Ljava/lang/Class; requiredType   (line 493)
                    ALOAD_1     // Ljava/util/Collection; original
                    INVOKEVIRTUAL java.lang.Class.isInstance (Ljava/lang/Object;)Z
                    ISTORE 6
                    ALOAD 4     // Lorg/springframework/core/convert/TypeDescriptor; typeDescriptor   (line 494)
                    ALOAD_1     // Ljava/util/Collection; original
                    INVOKEVIRTUAL org.springframework.core.convert.TypeDescriptor.narrow (Ljava/lang/Object;)Lorg/springframework/core/convert/TypeDescriptor;
                    ASTORE 4     // Lorg/springframework/core/convert/TypeDescriptor; typeDescriptor
                    ALOAD 4     // Lorg/springframework/core/convert/TypeDescriptor; typeDescriptor   (line 495)
                    INVOKEVIRTUAL org.springframework.core.convert.TypeDescriptor.getElementTypeDescriptor ()Lorg/springframework/core/convert/TypeDescriptor;
                    ASTORE 7
                    ALOAD 7     // Lorg/springframework/core/convert/TypeDescriptor; elementType   (line 496)
                    IFNONNULL L3
                    ILOAD 6     // Z originalAllowed
                    IFEQ L3
                    ALOAD_0     // Lorg/springframework/beans/TypeConverterDelegate; this   (line 497)
                    GETFIELD org.springframework.beans.TypeConverterDelegate.propertyEditorRegistry Lorg/springframework/beans/PropertyEditorRegistrySupport;
                    ACONST_NULL
                    ALOAD_2     // Ljava/lang/String; propertyName
                    INVOKEVIRTUAL org.springframework.beans.PropertyEditorRegistrySupport.hasCustomEditorForElement (Ljava/lang/Class;Ljava/lang/String;)Z
                    IFNE L3
                    ALOAD_1     // Ljava/util/Collection; original   (line 498)
                    ARETURN
    catch java.lang.Throwable -> E0
    |           L3: ALOAD_1     // Ljava/util/Collection; original   (line 503)
    |               INVOKEINTERFACE java.util.Collection.iterator ()Ljava/util/Iterator;
    |               ASTORE 8
    |               ALOAD 8     // Ljava/util/Iterator; it   (line 504)
    |               IFNONNULL L6
    |               GETSTATIC org.springframework.beans.TypeConverterDelegate.logger Lorg/apache/commons/logging/Log;   (line 505)
    |               INVOKEINTERFACE org.apache.commons.logging.Log.isDebugEnabled ()Z
    |               IFEQ L4
    |               GETSTATIC org.springframework.beans.TypeConverterDelegate.logger Lorg/apache/commons/logging/Log;   (line 506)
    |               NEW java.lang.StringBuilder
    |               DUP
    |               LDC_W "Collection of type ["
    |               INVOKESPECIAL java.lang.StringBuilder.<init> (Ljava/lang/String;)V
    |               ALOAD_1     // Ljava/util/Collection; original
    |               INVOKEVIRTUAL java.lang.Object.getClass ()Ljava/lang/Class;
    |               INVOKEVIRTUAL java.lang.Class.getName ()Ljava/lang/String;
    |               INVOKEVIRTUAL java.lang.StringBuilder.append (Ljava/lang/String;)Ljava/lang/StringBuilder;
    |               LDC_W "] returned null Iterator - injecting original Collection as-is"   (line 507)
    |               INVOKEVIRTUAL java.lang.StringBuilder.append (Ljava/lang/String;)Ljava/lang/StringBuilder;
    |               INVOKEVIRTUAL java.lang.StringBuilder.toString ()Ljava/lang/String;
    |               INVOKEINTERFACE org.apache.commons.logging.Log.debug (Ljava/lang/Object;)V   (line 506)
    |           L4: ALOAD_1     // Ljava/util/Collection; original   (line 509)
    catch java.lang.Throwable -> E0
                    ARETURN
                E0: ASTORE 9   (line 512)
                    GETSTATIC org.springframework.beans.TypeConverterDelegate.logger Lorg/apache/commons/logging/Log;   (line 513)
                    INVOKEINTERFACE org.apache.commons.logging.Log.isDebugEnabled ()Z
                    IFEQ L5
                    GETSTATIC org.springframework.beans.TypeConverterDelegate.logger Lorg/apache/commons/logging/Log;   (line 514)
                    NEW java.lang.StringBuilder
                    DUP
                    LDC_W "Cannot access Collection of type ["
                    INVOKESPECIAL java.lang.StringBuilder.<init> (Ljava/lang/String;)V
                    ALOAD_1     // Ljava/util/Collection; original
                    INVOKEVIRTUAL java.lang.Object.getClass ()Ljava/lang/Class;
                    INVOKEVIRTUAL java.lang.Class.getName ()Ljava/lang/String;
                    INVOKEVIRTUAL java.lang.StringBuilder.append (Ljava/lang/String;)Ljava/lang/StringBuilder;
                    LDC_W "] - injecting original Collection as-is: "   (line 515)
                    INVOKEVIRTUAL java.lang.StringBuilder.append (Ljava/lang/String;)Ljava/lang/StringBuilder;
                    ALOAD 9     // Ljava/lang/Throwable; ex
                    INVOKEVIRTUAL java.lang.StringBuilder.append (Ljava/lang/Object;)Ljava/lang/StringBuilder;
                    INVOKEVIRTUAL java.lang.StringBuilder.toString ()Ljava/lang/String;
                    INVOKEINTERFACE org.apache.commons.logging.Log.debug (Ljava/lang/Object;)V   (line 514)
                L5: ALOAD_1     // Ljava/util/Collection; original   (line 517)
                    ARETURN
    catch java.lang.Throwable -> E1
    |           L6: ILOAD 5     // Z approximable   (line 522)
    |               IFEQ L7
    |               ALOAD_1     // Ljava/util/Collection; original   (line 523)
    |               ALOAD_1     // Ljava/util/Collection; original
    |               INVOKEINTERFACE java.util.Collection.size ()I
    |               INVOKESTATIC org.springframework.core.CollectionFactory.createApproximateCollection (Ljava/lang/Object;I)Ljava/util/Collection;
    |               ASTORE 9
    |               GOTO L9
    |           L7: ALOAD_3     // Ljava/lang/Class; requiredType   (line 526)
    |               INVOKEVIRTUAL java.lang.Class.newInstance ()Ljava/lang/Object;
    |               CHECKCAST java.util.Collection
    |               ASTORE 9
    catch java.lang.Throwable -> E1
                    GOTO L9
                E1: ASTORE 10   (line 529)
                    GETSTATIC org.springframework.beans.TypeConverterDelegate.logger Lorg/apache/commons/logging/Log;   (line 530)
                    INVOKEINTERFACE org.apache.commons.logging.Log.isDebugEnabled ()Z
                    IFEQ L8
                    GETSTATIC org.springframework.beans.TypeConverterDelegate.logger Lorg/apache/commons/logging/Log;   (line 531)
                    NEW java.lang.StringBuilder
                    DUP
                    LDC_W "Cannot create copy of Collection type ["
                    INVOKESPECIAL java.lang.StringBuilder.<init> (Ljava/lang/String;)V
                    ALOAD_1     // Ljava/util/Collection; original
                    INVOKEVIRTUAL java.lang.Object.getClass ()Ljava/lang/Class;
                    INVOKEVIRTUAL java.lang.Class.getName ()Ljava/lang/String;
                    INVOKEVIRTUAL java.lang.StringBuilder.append (Ljava/lang/String;)Ljava/lang/StringBuilder;
                    LDC_W "] - injecting original Collection as-is: "   (line 532)
                    INVOKEVIRTUAL java.lang.StringBuilder.append (Ljava/lang/String;)Ljava/lang/StringBuilder;
                    ALOAD 10     // Ljava/lang/Throwable; ex
                    INVOKEVIRTUAL java.lang.StringBuilder.append (Ljava/lang/Object;)Ljava/lang/StringBuilder;
                    INVOKEVIRTUAL java.lang.StringBuilder.toString ()Ljava/lang/String;
                    INVOKEINTERFACE org.apache.commons.logging.Log.debug (Ljava/lang/Object;)V   (line 531)
                L8: ALOAD_1     // Ljava/util/Collection; original   (line 534)
                    ARETURN
                L9: ICONST_0   (line 537)
                    ISTORE 10
                    GOTO L17   (line 538)
               L10: ALOAD 8     // Ljava/util/Iterator; it   (line 539)
                    INVOKEINTERFACE java.util.Iterator.next ()Ljava/lang/Object;
                    ASTORE 11
                    ALOAD_0     // Lorg/springframework/beans/TypeConverterDelegate; this   (line 540)
                    ALOAD_2     // Ljava/lang/String; propertyName
                    ILOAD 10     // I i
                    INVOKESPECIAL org.springframework.beans.TypeConverterDelegate.buildIndexedPropertyName (Ljava/lang/String;I)Ljava/lang/String;
                    ASTORE 12
                    ALOAD_0     // Lorg/springframework/beans/TypeConverterDelegate; this   (line 541)
                    ALOAD 12     // Ljava/lang/String; indexedPropertyName
                    ACONST_NULL
                    ALOAD 11     // Ljava/lang/Object; element
                    ALOAD 7     // Lorg/springframework/core/convert/TypeDescriptor; elementType   (line 542)
                    IFNULL L11
                    ALOAD 7     // Lorg/springframework/core/convert/TypeDescriptor; elementType
                    INVOKEVIRTUAL org.springframework.core.convert.TypeDescriptor.getType ()Ljava/lang/Class;
                    GOTO L12
               L11: ACONST_NULL
               L12: ALOAD 7     // Lorg/springframework/core/convert/TypeDescriptor; elementType
                    INVOKEVIRTUAL org.springframework.beans.TypeConverterDelegate.convertIfNecessary (Ljava/lang/String;Ljava/lang/Object;Ljava/lang/Object;Ljava/lang/Class;Lorg/springframework/core/convert/TypeDescriptor;)Ljava/lang/Object;   (line 541)
                    ASTORE 13
    catch java.lang.Throwable -> E2
    |               ALOAD 9     // Ljava/util/Collection; convertedCopy   (line 544)
    |               ALOAD 13     // Ljava/lang/Object; convertedElement
    |               INVOKEINTERFACE java.util.Collection.add (Ljava/lang/Object;)Z
    |               POP
    catch java.lang.Throwable -> E2
                    GOTO L14
                E2: ASTORE 14   (line 546)
                    GETSTATIC org.springframework.beans.TypeConverterDelegate.logger Lorg/apache/commons/logging/Log;   (line 547)
                    INVOKEINTERFACE org.apache.commons.logging.Log.isDebugEnabled ()Z
                    IFEQ L13
                    GETSTATIC org.springframework.beans.TypeConverterDelegate.logger Lorg/apache/commons/logging/Log;   (line 548)
                    NEW java.lang.StringBuilder
                    DUP
                    LDC_W "Collection type ["
                    INVOKESPECIAL java.lang.StringBuilder.<init> (Ljava/lang/String;)V
                    ALOAD_1     // Ljava/util/Collection; original
                    INVOKEVIRTUAL java.lang.Object.getClass ()Ljava/lang/Class;
                    INVOKEVIRTUAL java.lang.Class.getName ()Ljava/lang/String;
                    INVOKEVIRTUAL java.lang.StringBuilder.append (Ljava/lang/String;)Ljava/lang/StringBuilder;
                    LDC_W "] seems to be read-only - injecting original Collection as-is: "   (line 549)
                    INVOKEVIRTUAL java.lang.StringBuilder.append (Ljava/lang/String;)Ljava/lang/StringBuilder;
                    ALOAD 14     // Ljava/lang/Throwable; ex
                    INVOKEVIRTUAL java.lang.StringBuilder.append (Ljava/lang/Object;)Ljava/lang/StringBuilder;
                    INVOKEVIRTUAL java.lang.StringBuilder.toString ()Ljava/lang/String;
                    INVOKEINTERFACE org.apache.commons.logging.Log.debug (Ljava/lang/Object;)V   (line 548)
               L13: ALOAD_1     // Ljava/util/Collection; original   (line 551)
                    ARETURN
               L14: ILOAD 6     // Z originalAllowed   (line 553)
                    IFEQ L15
                    ALOAD 11     // Ljava/lang/Object; element
                    ALOAD 13     // Ljava/lang/Object; convertedElement
                    IF_ACMPNE L15
                    ICONST_1
                    GOTO L16
               L15: ICONST_0
               L16: ISTORE 6     // Z originalAllowed
                    IINC 10 1     // I i   (line 538)
               L17: ALOAD 8     // Ljava/util/Iterator; it
                    INVOKEINTERFACE java.util.Iterator.hasNext ()Z
                    IFNE L10
                    ILOAD 6     // Z originalAllowed   (line 555)
                    IFEQ L18
                    ALOAD_1     // Ljava/util/Collection; original
                    GOTO L19
               L18: ALOAD 9     // Ljava/util/Collection; convertedCopy
               L19: ARETURN
  end protected java.util.Collection convertToTypedCollection(java.util.Collection, String, Class, org.springframework.core.convert.TypeDescriptor)

  protected java.util.Map convertToTypedMap(java.util.Map, String, Class, org.springframework.core.convert.TypeDescriptor):
                    LDC java.util.Map   (line 562)
                    ALOAD_3     // Ljava/lang/Class; requiredType
                    INVOKEVIRTUAL java.lang.Class.isAssignableFrom (Ljava/lang/Class;)Z
                    IFNE L0
                    ALOAD_1     // Ljava/util/Map; original   (line 563)
                    ARETURN
                L0: ALOAD_3     // Ljava/lang/Class; requiredType   (line 566)
                    INVOKESTATIC org.springframework.core.CollectionFactory.isApproximableMapType (Ljava/lang/Class;)Z
                    ISTORE 5
                    ILOAD 5     // Z approximable   (line 567)
                    IFNE L2
                    ALOAD_0     // Lorg/springframework/beans/TypeConverterDelegate; this
                    ALOAD_3     // Ljava/lang/Class; requiredType
                    INVOKESPECIAL org.springframework.beans.TypeConverterDelegate.canCreateCopy (Ljava/lang/Class;)Z
                    IFNE L2
                    GETSTATIC org.springframework.beans.TypeConverterDelegate.logger Lorg/apache/commons/logging/Log;   (line 568)
                    INVOKEINTERFACE org.apache.commons.logging.Log.isDebugEnabled ()Z
                    IFEQ L1
                    GETSTATIC org.springframework.beans.TypeConverterDelegate.logger Lorg/apache/commons/logging/Log;   (line 569)
                    NEW java.lang.StringBuilder
                    DUP
                    LDC_W "Custom Map type ["
                    INVOKESPECIAL java.lang.StringBuilder.<init> (Ljava/lang/String;)V
                    ALOAD_1     // Ljava/util/Map; original
                    INVOKEVIRTUAL java.lang.Object.getClass ()Ljava/lang/Class;
                    INVOKEVIRTUAL java.lang.Class.getName ()Ljava/lang/String;
                    INVOKEVIRTUAL java.lang.StringBuilder.append (Ljava/lang/String;)Ljava/lang/StringBuilder;
                    LDC_W "] does not allow for creating a copy - injecting original Map as-is"   (line 570)
                    INVOKEVIRTUAL java.lang.StringBuilder.append (Ljava/lang/String;)Ljava/lang/StringBuilder;
                    INVOKEVIRTUAL java.lang.StringBuilder.toString ()Ljava/lang/String;
                    INVOKEINTERFACE org.apache.commons.logging.Log.debug (Ljava/lang/Object;)V   (line 569)
                L1: ALOAD_1     // Ljava/util/Map; original   (line 572)
                    ARETURN
                L2: ALOAD_3     // Ljava/lang/Class; requiredType   (line 575)
                    ALOAD_1     // Ljava/util/Map; original
                    INVOKEVIRTUAL java.lang.Class.isInstance (Ljava/lang/Object;)Z
                    ISTORE 6
                    ALOAD 4     // Lorg/springframework/core/convert/TypeDescriptor; typeDescriptor   (line 576)
                    ALOAD_1     // Ljava/util/Map; original
                    INVOKEVIRTUAL org.springframework.core.convert.TypeDescriptor.narrow (Ljava/lang/Object;)Lorg/springframework/core/convert/TypeDescriptor;
                    ASTORE 4     // Lorg/springframework/core/convert/TypeDescriptor; typeDescriptor
                    ALOAD 4     // Lorg/springframework/core/convert/TypeDescriptor; typeDescriptor   (line 577)
                    INVOKEVIRTUAL org.springframework.core.convert.TypeDescriptor.getMapKeyTypeDescriptor ()Lorg/springframework/core/convert/TypeDescriptor;
                    ASTORE 7
                    ALOAD 4     // Lorg/springframework/core/convert/TypeDescriptor; typeDescriptor   (line 578)
                    INVOKEVIRTUAL org.springframework.core.convert.TypeDescriptor.getMapValueTypeDescriptor ()Lorg/springframework/core/convert/TypeDescriptor;
                    ASTORE 8
                    ALOAD 7     // Lorg/springframework/core/convert/TypeDescriptor; keyType   (line 579)
                    IFNONNULL L3
                    ALOAD 8     // Lorg/springframework/core/convert/TypeDescriptor; valueType
                    IFNONNULL L3
                    ILOAD 6     // Z originalAllowed
                    IFEQ L3
                    ALOAD_0     // Lorg/springframework/beans/TypeConverterDelegate; this   (line 580)
                    GETFIELD org.springframework.beans.TypeConverterDelegate.propertyEditorRegistry Lorg/springframework/beans/PropertyEditorRegistrySupport;
                    ACONST_NULL
                    ALOAD_2     // Ljava/lang/String; propertyName
                    INVOKEVIRTUAL org.springframework.beans.PropertyEditorRegistrySupport.hasCustomEditorForElement (Ljava/lang/Class;Ljava/lang/String;)Z
                    IFNE L3
                    ALOAD_1     // Ljava/util/Map; original   (line 581)
                    ARETURN
    catch java.lang.Throwable -> E0
    |           L3: ALOAD_1     // Ljava/util/Map; original   (line 586)
    |               INVOKEINTERFACE java.util.Map.entrySet ()Ljava/util/Set;
    |               INVOKEINTERFACE java.util.Set.iterator ()Ljava/util/Iterator;
    |               ASTORE 9
    |               ALOAD 9     // Ljava/util/Iterator; it   (line 587)
    |               IFNONNULL L6
    |               GETSTATIC org.springframework.beans.TypeConverterDelegate.logger Lorg/apache/commons/logging/Log;   (line 588)
    |               INVOKEINTERFACE org.apache.commons.logging.Log.isDebugEnabled ()Z
    |               IFEQ L4
    |               GETSTATIC org.springframework.beans.TypeConverterDelegate.logger Lorg/apache/commons/logging/Log;   (line 589)
    |               NEW java.lang.StringBuilder
    |               DUP
    |               LDC_W "Map of type ["
    |               INVOKESPECIAL java.lang.StringBuilder.<init> (Ljava/lang/String;)V
    |               ALOAD_1     // Ljava/util/Map; original
    |               INVOKEVIRTUAL java.lang.Object.getClass ()Ljava/lang/Class;
    |               INVOKEVIRTUAL java.lang.Class.getName ()Ljava/lang/String;
    |               INVOKEVIRTUAL java.lang.StringBuilder.append (Ljava/lang/String;)Ljava/lang/StringBuilder;
    |               LDC_W "] returned null Iterator - injecting original Map as-is"   (line 590)
    |               INVOKEVIRTUAL java.lang.StringBuilder.append (Ljava/lang/String;)Ljava/lang/StringBuilder;
    |               INVOKEVIRTUAL java.lang.StringBuilder.toString ()Ljava/lang/String;
    |               INVOKEINTERFACE org.apache.commons.logging.Log.debug (Ljava/lang/Object;)V   (line 589)
    |           L4: ALOAD_1     // Ljava/util/Map; original   (line 592)
    catch java.lang.Throwable -> E0
                    ARETURN
                E0: ASTORE 10   (line 595)
                    GETSTATIC org.springframework.beans.TypeConverterDelegate.logger Lorg/apache/commons/logging/Log;   (line 596)
                    INVOKEINTERFACE org.apache.commons.logging.Log.isDebugEnabled ()Z
                    IFEQ L5
                    GETSTATIC org.springframework.beans.TypeConverterDelegate.logger Lorg/apache/commons/logging/Log;   (line 597)
                    NEW java.lang.StringBuilder
                    DUP
                    LDC_W "Cannot access Map of type ["
                    INVOKESPECIAL java.lang.StringBuilder.<init> (Ljava/lang/String;)V
                    ALOAD_1     // Ljava/util/Map; original
                    INVOKEVIRTUAL java.lang.Object.getClass ()Ljava/lang/Class;
                    INVOKEVIRTUAL java.lang.Class.getName ()Ljava/lang/String;
                    INVOKEVIRTUAL java.lang.StringBuilder.append (Ljava/lang/String;)Ljava/lang/StringBuilder;
                    LDC_W "] - injecting original Map as-is: "   (line 598)
                    INVOKEVIRTUAL java.lang.StringBuilder.append (Ljava/lang/String;)Ljava/lang/StringBuilder;
                    ALOAD 10     // Ljava/lang/Throwable; ex
                    INVOKEVIRTUAL java.lang.StringBuilder.append (Ljava/lang/Object;)Ljava/lang/StringBuilder;
                    INVOKEVIRTUAL java.lang.StringBuilder.toString ()Ljava/lang/String;
                    INVOKEINTERFACE org.apache.commons.logging.Log.debug (Ljava/lang/Object;)V   (line 597)
                L5: ALOAD_1     // Ljava/util/Map; original   (line 600)
                    ARETURN
    catch java.lang.Throwable -> E1
    |           L6: ILOAD 5     // Z approximable   (line 605)
    |               IFEQ L7
    |               ALOAD_1     // Ljava/util/Map; original   (line 606)
    |               ALOAD_1     // Ljava/util/Map; original
    |               INVOKEINTERFACE java.util.Map.size ()I
    |               INVOKESTATIC org.springframework.core.CollectionFactory.createApproximateMap (Ljava/lang/Object;I)Ljava/util/Map;
    |               ASTORE 10
    |               GOTO L18
    |           L7: ALOAD_3     // Ljava/lang/Class; requiredType   (line 609)
    |               INVOKEVIRTUAL java.lang.Class.newInstance ()Ljava/lang/Object;
    |               CHECKCAST java.util.Map
    |               ASTORE 10
    catch java.lang.Throwable -> E1
                    GOTO L18
                E1: ASTORE 11   (line 612)
                    GETSTATIC org.springframework.beans.TypeConverterDelegate.logger Lorg/apache/commons/logging/Log;   (line 613)
                    INVOKEINTERFACE org.apache.commons.logging.Log.isDebugEnabled ()Z
                    IFEQ L8
                    GETSTATIC org.springframework.beans.TypeConverterDelegate.logger Lorg/apache/commons/logging/Log;   (line 614)
                    NEW java.lang.StringBuilder
                    DUP
                    LDC_W "Cannot create copy of Map type ["
                    INVOKESPECIAL java.lang.StringBuilder.<init> (Ljava/lang/String;)V
                    ALOAD_1     // Ljava/util/Map; original
                    INVOKEVIRTUAL java.lang.Object.getClass ()Ljava/lang/Class;
                    INVOKEVIRTUAL java.lang.Class.getName ()Ljava/lang/String;
                    INVOKEVIRTUAL java.lang.StringBuilder.append (Ljava/lang/String;)Ljava/lang/StringBuilder;
                    LDC_W "] - injecting original Map as-is: "   (line 615)
                    INVOKEVIRTUAL java.lang.StringBuilder.append (Ljava/lang/String;)Ljava/lang/StringBuilder;
                    ALOAD 11     // Ljava/lang/Throwable; ex
                    INVOKEVIRTUAL java.lang.StringBuilder.append (Ljava/lang/Object;)Ljava/lang/StringBuilder;
                    INVOKEVIRTUAL java.lang.StringBuilder.toString ()Ljava/lang/String;
                    INVOKEINTERFACE org.apache.commons.logging.Log.debug (Ljava/lang/Object;)V   (line 614)
                L8: ALOAD_1     // Ljava/util/Map; original   (line 617)
                    ARETURN
                L9: ALOAD 9     // Ljava/util/Iterator; it   (line 621)
                    INVOKEINTERFACE java.util.Iterator.next ()Ljava/lang/Object;
                    CHECKCAST java.util.Map$Entry
                    ASTORE 11
                    ALOAD 11     // Ljava/util/Map$Entry; entry   (line 622)
                    INVOKEINTERFACE java.util.Map$Entry.getKey ()Ljava/lang/Object;
                    ASTORE 12
                    ALOAD 11     // Ljava/util/Map$Entry; entry   (line 623)
                    INVOKEINTERFACE java.util.Map$Entry.getValue ()Ljava/lang/Object;
                    ASTORE 13
                    ALOAD_0     // Lorg/springframework/beans/TypeConverterDelegate; this   (line 624)
                    ALOAD_2     // Ljava/lang/String; propertyName
                    ALOAD 12     // Ljava/lang/Object; key
                    INVOKESPECIAL org.springframework.beans.TypeConverterDelegate.buildKeyedPropertyName (Ljava/lang/String;Ljava/lang/Object;)Ljava/lang/String;
                    ASTORE 14
                    ALOAD_0     // Lorg/springframework/beans/TypeConverterDelegate; this   (line 625)
                    ALOAD 14     // Ljava/lang/String; keyedPropertyName
                    ACONST_NULL
                    ALOAD 12     // Ljava/lang/Object; key
                    ALOAD 7     // Lorg/springframework/core/convert/TypeDescriptor; keyType   (line 626)
                    IFNULL L10
                    ALOAD 7     // Lorg/springframework/core/convert/TypeDescriptor; keyType
                    INVOKEVIRTUAL org.springframework.core.convert.TypeDescriptor.getType ()Ljava/lang/Class;
                    GOTO L11
               L10: ACONST_NULL
               L11: ALOAD 7     // Lorg/springframework/core/convert/TypeDescriptor; keyType
                    INVOKEVIRTUAL org.springframework.beans.TypeConverterDelegate.convertIfNecessary (Ljava/lang/String;Ljava/lang/Object;Ljava/lang/Object;Ljava/lang/Class;Lorg/springframework/core/convert/TypeDescriptor;)Ljava/lang/Object;   (line 625)
                    ASTORE 15
                    ALOAD_0     // Lorg/springframework/beans/TypeConverterDelegate; this   (line 627)
                    ALOAD 14     // Ljava/lang/String; keyedPropertyName
                    ACONST_NULL
                    ALOAD 13     // Ljava/lang/Object; value
                    ALOAD 8     // Lorg/springframework/core/convert/TypeDescriptor; valueType   (line 628)
                    IFNULL L12
                    ALOAD 8     // Lorg/springframework/core/convert/TypeDescriptor; valueType
                    INVOKEVIRTUAL org.springframework.core.convert.TypeDescriptor.getType ()Ljava/lang/Class;
                    GOTO L13
               L12: ACONST_NULL
               L13: ALOAD 8     // Lorg/springframework/core/convert/TypeDescriptor; valueType
                    INVOKEVIRTUAL org.springframework.beans.TypeConverterDelegate.convertIfNecessary (Ljava/lang/String;Ljava/lang/Object;Ljava/lang/Object;Ljava/lang/Class;Lorg/springframework/core/convert/TypeDescriptor;)Ljava/lang/Object;   (line 627)
                    ASTORE 16
    catch java.lang.Throwable -> E2
    |               ALOAD 10     // Ljava/util/Map; convertedCopy   (line 630)
    |               ALOAD 15     // Ljava/lang/Object; convertedKey
    |               ALOAD 16     // Ljava/lang/Object; convertedValue
    |               INVOKEINTERFACE java.util.Map.put (Ljava/lang/Object;Ljava/lang/Object;)Ljava/lang/Object;
    |               POP
    catch java.lang.Throwable -> E2
                    GOTO L15
                E2: ASTORE 17   (line 632)
                    GETSTATIC org.springframework.beans.TypeConverterDelegate.logger Lorg/apache/commons/logging/Log;   (line 633)
                    INVOKEINTERFACE org.apache.commons.logging.Log.isDebugEnabled ()Z
                    IFEQ L14
                    GETSTATIC org.springframework.beans.TypeConverterDelegate.logger Lorg/apache/commons/logging/Log;   (line 634)
                    NEW java.lang.StringBuilder
                    DUP
                    LDC_W "Map type ["
                    INVOKESPECIAL java.lang.StringBuilder.<init> (Ljava/lang/String;)V
                    ALOAD_1     // Ljava/util/Map; original
                    INVOKEVIRTUAL java.lang.Object.getClass ()Ljava/lang/Class;
                    INVOKEVIRTUAL java.lang.Class.getName ()Ljava/lang/String;
                    INVOKEVIRTUAL java.lang.StringBuilder.append (Ljava/lang/String;)Ljava/lang/StringBuilder;
                    LDC_W "] seems to be read-only - injecting original Map as-is: "   (line 635)
                    INVOKEVIRTUAL java.lang.StringBuilder.append (Ljava/lang/String;)Ljava/lang/StringBuilder;
                    ALOAD 17     // Ljava/lang/Throwable; ex
                    INVOKEVIRTUAL java.lang.StringBuilder.append (Ljava/lang/Object;)Ljava/lang/StringBuilder;
                    INVOKEVIRTUAL java.lang.StringBuilder.toString ()Ljava/lang/String;
                    INVOKEINTERFACE org.apache.commons.logging.Log.debug (Ljava/lang/Object;)V   (line 634)
               L14: ALOAD_1     // Ljava/util/Map; original   (line 637)
                    ARETURN
               L15: ILOAD 6     // Z originalAllowed   (line 639)
                    IFEQ L16
                    ALOAD 12     // Ljava/lang/Object; key
                    ALOAD 15     // Ljava/lang/Object; convertedKey
                    IF_ACMPNE L16
                    ALOAD 13     // Ljava/lang/Object; value
                    ALOAD 16     // Ljava/lang/Object; convertedValue
                    IF_ACMPNE L16
                    ICONST_1
                    GOTO L17
               L16: ICONST_0
               L17: ISTORE 6     // Z originalAllowed
               L18: ALOAD 9     // Ljava/util/Iterator; it   (line 620)
                    INVOKEINTERFACE java.util.Iterator.hasNext ()Z
                    IFNE L9
                    ILOAD 6     // Z originalAllowed   (line 641)
                    IFEQ L19
                    ALOAD_1     // Ljava/util/Map; original
                    GOTO L20
               L19: ALOAD 10     // Ljava/util/Map; convertedCopy
               L20: ARETURN
  end protected java.util.Map convertToTypedMap(java.util.Map, String, Class, org.springframework.core.convert.TypeDescriptor)

  private String buildIndexedPropertyName(String, int):
                    ALOAD_1     // Ljava/lang/String; propertyName   (line 645)
                    IFNULL L0
                    NEW java.lang.StringBuilder   (line 646)
                    DUP
                    ALOAD_1     // Ljava/lang/String; propertyName
                    INVOKESTATIC java.lang.String.valueOf (Ljava/lang/Object;)Ljava/lang/String;
                    INVOKESPECIAL java.lang.StringBuilder.<init> (Ljava/lang/String;)V
                    LDC_W "["
                    INVOKEVIRTUAL java.lang.StringBuilder.append (Ljava/lang/String;)Ljava/lang/StringBuilder;
                    ILOAD_2     // I index
                    INVOKEVIRTUAL java.lang.StringBuilder.append (I)Ljava/lang/StringBuilder;
                    LDC "]"
                    INVOKEVIRTUAL java.lang.StringBuilder.append (Ljava/lang/String;)Ljava/lang/StringBuilder;
                    INVOKEVIRTUAL java.lang.StringBuilder.toString ()Ljava/lang/String;
                    GOTO L1
                L0: ACONST_NULL   (line 647)
                L1: ARETURN   (line 645)
  end private String buildIndexedPropertyName(String, int)

  private String buildKeyedPropertyName(String, Object):
                    ALOAD_1     // Ljava/lang/String; propertyName   (line 651)
                    IFNULL L0
                    NEW java.lang.StringBuilder   (line 652)
                    DUP
                    ALOAD_1     // Ljava/lang/String; propertyName
                    INVOKESTATIC java.lang.String.valueOf (Ljava/lang/Object;)Ljava/lang/String;
                    INVOKESPECIAL java.lang.StringBuilder.<init> (Ljava/lang/String;)V
                    LDC_W "["
                    INVOKEVIRTUAL java.lang.StringBuilder.append (Ljava/lang/String;)Ljava/lang/StringBuilder;
                    ALOAD_2     // Ljava/lang/Object; key
                    INVOKEVIRTUAL java.lang.StringBuilder.append (Ljava/lang/Object;)Ljava/lang/StringBuilder;
                    LDC "]"
                    INVOKEVIRTUAL java.lang.StringBuilder.append (Ljava/lang/String;)Ljava/lang/StringBuilder;
                    INVOKEVIRTUAL java.lang.StringBuilder.toString ()Ljava/lang/String;
                    GOTO L1
                L0: ACONST_NULL   (line 653)
                L1: ARETURN   (line 651)
  end private String buildKeyedPropertyName(String, Object)

  private boolean canCreateCopy(Class):
                    ALOAD_1     // Ljava/lang/Class; requiredType   (line 657)
                    INVOKEVIRTUAL java.lang.Class.isInterface ()Z
                    IFNE L0
                    ALOAD_1     // Ljava/lang/Class; requiredType
                    INVOKEVIRTUAL java.lang.Class.getModifiers ()I
                    INVOKESTATIC java.lang.reflect.Modifier.isAbstract (I)Z
                    IFNE L0
                    ALOAD_1     // Ljava/lang/Class; requiredType   (line 658)
                    INVOKEVIRTUAL java.lang.Class.getModifiers ()I
                    INVOKESTATIC java.lang.reflect.Modifier.isPublic (I)Z
                    IFEQ L0
                    ALOAD_1     // Ljava/lang/Class; requiredType
                    ICONST_0
                    ANEWARRAY java.lang.Class
                    INVOKESTATIC org.springframework.util.ClassUtils.hasConstructor (Ljava/lang/Class;[Ljava/lang/Class;)Z
                    IFEQ L0
                    ICONST_1
                    IRETURN
                L0: ICONST_0
                    IRETURN   (line 657)
  end private boolean canCreateCopy(Class)
end  class org.springframework.beans.TypeConverterDelegate
 -- (NullPointerException) null
null
java.lang.NullPointerException

org.aspectj.bridge.AbortException: trouble in: 
 class org.springframework.beans.TypeConverterDelegate extends java.lang.Object:
  private static final org.apache.commons.logging.Log logger
  private final org.springframework.beans.PropertyEditorRegistrySupport propertyEditorRegistry
  private final Object targetObject
  static void <clinit>():
    staticinitialization(void org.springframework.beans.TypeConverterDelegate.<clinit>())
    |               LDC org.springframework.beans.TypeConverterDelegate   (line 53)
    |               INVOKESTATIC org.apache.commons.logging.LogFactory.getLog (Ljava/lang/Class;)Lorg/apache/commons/logging/Log;
    |               PUTSTATIC org.springframework.beans.TypeConverterDelegate.logger Lorg/apache/commons/logging/Log;
    |               RETURN   (line 51)
    staticinitialization(void org.springframework.beans.TypeConverterDelegate.<clinit>())
  end static void <clinit>()

  public void <init>(org.springframework.beans.PropertyEditorRegistrySupport):
                    ALOAD_0     // Lorg/springframework/beans/TypeConverterDelegate; this   (line 65)
                    ALOAD_1     // Lorg/springframework/beans/PropertyEditorRegistrySupport; propertyEditorRegistry
                    ACONST_NULL
                    INVOKESPECIAL org.springframework.beans.TypeConverterDelegate.<init> (Lorg/springframework/beans/PropertyEditorRegistrySupport;Ljava/lang/Object;)V
    constructor-execution(void org.springframework.beans.TypeConverterDelegate.<init>(org.springframework.beans.PropertyEditorRegistrySupport))
    |               RETURN   (line 66)
    constructor-execution(void org.springframework.beans.TypeConverterDelegate.<init>(org.springframework.beans.PropertyEditorRegistrySupport))
  end public void <init>(org.springframework.beans.PropertyEditorRegistrySupport)

  public void <init>(org.springframework.beans.PropertyEditorRegistrySupport, Object):
                    ALOAD_0     // Lorg/springframework/beans/TypeConverterDelegate; this   (line 73)
                    INVOKESPECIAL java.lang.Object.<init> ()V
    constructor-execution(void org.springframework.beans.TypeConverterDelegate.<init>(org.springframework.beans.PropertyEditorRegistrySupport, java.lang.Object))
    |               ALOAD_0     // Lorg/springframework/beans/TypeConverterDelegate; this   (line 74)
    |               ALOAD_1     // Lorg/springframework/beans/PropertyEditorRegistrySupport; propertyEditorRegistry
    |               PUTFIELD org.springframework.beans.TypeConverterDelegate.propertyEditorRegistry Lorg/springframework/beans/PropertyEditorRegistrySupport;
    |               ALOAD_0     // Lorg/springframework/beans/TypeConverterDelegate; this   (line 75)
    |               ALOAD_2     // Ljava/lang/Object; targetObject
    |               PUTFIELD org.springframework.beans.TypeConverterDelegate.targetObject Ljava/lang/Object;
    |               RETURN   (line 76)
    constructor-execution(void org.springframework.beans.TypeConverterDelegate.<init>(org.springframework.beans.PropertyEditorRegistrySupport, java.lang.Object))
  end public void <init>(org.springframework.beans.PropertyEditorRegistrySupport, Object)

  public Object convertIfNecessary(Object, Class, org.springframework.core.MethodParameter) throws java.lang.IllegalArgumentException:
                    ALOAD_0     // Lorg/springframework/beans/TypeConverterDelegate; this   (line 92)
                    ACONST_NULL
                    ACONST_NULL
                    ALOAD_1     // Ljava/lang/Object; newValue
                    ALOAD_2     // Ljava/lang/Class; requiredType
                    ALOAD_3     // Lorg/springframework/core/MethodParameter; methodParam   (line 93)
                    IFNULL L0
                    NEW org.springframework.core.convert.TypeDescriptor
                    DUP
                    ALOAD_3     // Lorg/springframework/core/MethodParameter; methodParam
                    INVOKESPECIAL org.springframework.core.convert.TypeDescriptor.<init> (Lorg/springframework/core/MethodParameter;)V
                    GOTO L1
                L0: ALOAD_2     // Ljava/lang/Class; requiredType
                    INVOKESTATIC org.springframework.core.convert.TypeDescriptor.valueOf (Ljava/lang/Class;)Lorg/springframework/core/convert/TypeDescriptor;
                L1: INVOKEVIRTUAL org.springframework.beans.TypeConverterDelegate.convertIfNecessary (Ljava/lang/String;Ljava/lang/Object;Ljava/lang/Object;Ljava/lang/Class;Lorg/springframework/core/convert/TypeDescriptor;)Ljava/lang/Object;   (line 92)
                    ARETURN
  end public Object convertIfNecessary(Object, Class, org.springframework.core.MethodParameter) throws java.lang.IllegalArgumentException

  public Object convertIfNecessary(String, Object, Object, Class) throws java.lang.IllegalArgumentException:
                    ALOAD_0     // Lorg/springframework/beans/TypeConverterDelegate; this   (line 110)
                    ALOAD_1     // Ljava/lang/String; propertyName
                    ALOAD_2     // Ljava/lang/Object; oldValue
                    ALOAD_3     // Ljava/lang/Object; newValue
                    ALOAD 4     // Ljava/lang/Class; requiredType
                    ALOAD 4     // Ljava/lang/Class; requiredType
                    INVOKESTATIC org.springframework.core.convert.TypeDescriptor.valueOf (Ljava/lang/Class;)Lorg/springframework/core/convert/TypeDescriptor;
                    INVOKEVIRTUAL org.springframework.beans.TypeConverterDelegate.convertIfNecessary (Ljava/lang/String;Ljava/lang/Object;Ljava/lang/Object;Ljava/lang/Class;Lorg/springframework/core/convert/TypeDescriptor;)Ljava/lang/Object;
                    ARETURN
  end public Object convertIfNecessary(String, Object, Object, Class) throws java.lang.IllegalArgumentException

  public Object convertIfNecessary(String, Object, Object, Class, org.springframework.core.convert.TypeDescriptor) throws java.lang.IllegalArgumentException:
                    ALOAD_3     // Ljava/lang/Object; newValue   (line 129)
                    ASTORE 6
                    ALOAD_0     // Lorg/springframework/beans/TypeConverterDelegate; this   (line 132)
                    GETFIELD org.springframework.beans.TypeConverterDelegate.propertyEditorRegistry Lorg/springframework/beans/PropertyEditorRegistrySupport;
                    ALOAD 4     // Ljava/lang/Class; requiredType
                    ALOAD_1     // Ljava/lang/String; propertyName
                    INVOKEVIRTUAL org.springframework.beans.PropertyEditorRegistrySupport.findCustomEditor (Ljava/lang/Class;Ljava/lang/String;)Ljava/beans/PropertyEditor;
                    ASTORE 7
                    ACONST_NULL   (line 134)
                    ASTORE 8
                    ALOAD_0     // Lorg/springframework/beans/TypeConverterDelegate; this   (line 137)
                    GETFIELD org.springframework.beans.TypeConverterDelegate.propertyEditorRegistry Lorg/springframework/beans/PropertyEditorRegistrySupport;
                    INVOKEVIRTUAL org.springframework.beans.PropertyEditorRegistrySupport.getConversionService ()Lorg/springframework/core/convert/ConversionService;
                    ASTORE 9
                    ALOAD 7     // Ljava/beans/PropertyEditor; editor   (line 138)
                    IFNONNULL L0
                    ALOAD 9     // Lorg/springframework/core/convert/ConversionService; conversionService
                    IFNULL L0
                    ALOAD 6     // Ljava/lang/Object; convertedValue
                    IFNULL L0
                    ALOAD 5     // Lorg/springframework/core/convert/TypeDescriptor; typeDescriptor
                    IFNULL L0
                    ALOAD_3     // Ljava/lang/Object; newValue   (line 139)
                    INVOKESTATIC org.springframework.core.convert.TypeDescriptor.forObject (Ljava/lang/Object;)Lorg/springframework/core/convert/TypeDescriptor;
                    ASTORE 10
                    ALOAD 5     // Lorg/springframework/core/convert/TypeDescriptor; typeDescriptor   (line 140)
                    ASTORE 11
                    ALOAD 9     // Lorg/springframework/core/convert/ConversionService; conversionService   (line 141)
                    ALOAD 10     // Lorg/springframework/core/convert/TypeDescriptor; sourceTypeDesc
                    ALOAD 11     // Lorg/springframework/core/convert/TypeDescriptor; targetTypeDesc
                    INVOKEINTERFACE org.springframework.core.convert.ConversionService.canConvert (Lorg/springframework/core/convert/TypeDescriptor;Lorg/springframework/core/convert/TypeDescriptor;)Z
                    IFEQ L0
    catch org.springframework.core.convert.ConversionFailedException -> E0
    |               ALOAD 9     // Lorg/springframework/core/convert/ConversionService; conversionService   (line 143)
    |               ALOAD 6     // Ljava/lang/Object; convertedValue
    |               ALOAD 10     // Lorg/springframework/core/convert/TypeDescriptor; sourceTypeDesc
    |               ALOAD 11     // Lorg/springframework/core/convert/TypeDescriptor; targetTypeDesc
    |               INVOKEINTERFACE org.springframework.core.convert.ConversionService.convert (Ljava/lang/Object;Lorg/springframework/core/convert/TypeDescriptor;Lorg/springframework/core/convert/TypeDescriptor;)Ljava/lang/Object;
    catch org.springframework.core.convert.ConversionFailedException -> E0
                    ARETURN
                E0: ASTORE 12   (line 145)
                    ALOAD 12     // Lorg/springframework/core/convert/ConversionFailedException; ex   (line 147)
                    ASTORE 8     // Lorg/springframework/core/convert/ConversionFailedException; firstAttemptEx
                L0: ALOAD 7     // Ljava/beans/PropertyEditor; editor   (line 153)
                    IFNONNULL L1
                    ALOAD 4     // Ljava/lang/Class; requiredType
                    IFNULL L4
                    ALOAD 4     // Ljava/lang/Class; requiredType
                    ALOAD 6     // Ljava/lang/Object; convertedValue
                    INVOKESTATIC org.springframework.util.ClassUtils.isAssignableValue (Ljava/lang/Class;Ljava/lang/Object;)Z
                    IFNE L4
                L1: ALOAD 4     // Ljava/lang/Class; requiredType   (line 154)
                    IFNULL L2
                    LDC java.util.Collection
                    ALOAD 4     // Ljava/lang/Class; requiredType
                    INVOKEVIRTUAL java.lang.Class.isAssignableFrom (Ljava/lang/Class;)Z
                    IFEQ L2
                    ALOAD 6     // Ljava/lang/Object; convertedValue
                    INSTANCEOF java.lang.String
                    IFEQ L2
                    ALOAD 5     // Lorg/springframework/core/convert/TypeDescriptor; typeDescriptor   (line 155)
                    INVOKEVIRTUAL org.springframework.core.convert.TypeDescriptor.getElementTypeDescriptor ()Lorg/springframework/core/convert/TypeDescriptor;
                    ASTORE 10
                    ALOAD 10     // Lorg/springframework/core/convert/TypeDescriptor; elementType   (line 156)
                    IFNULL L2
                    LDC java.lang.Enum
                    ALOAD 10     // Lorg/springframework/core/convert/TypeDescriptor; elementType
                    INVOKEVIRTUAL org.springframework.core.convert.TypeDescriptor.getType ()Ljava/lang/Class;
                    INVOKEVIRTUAL java.lang.Class.isAssignableFrom (Ljava/lang/Class;)Z
                    IFEQ L2
                    ALOAD 6     // Ljava/lang/Object; convertedValue   (line 157)
                    CHECKCAST java.lang.String
                    INVOKESTATIC org.springframework.util.StringUtils.commaDelimitedListToStringArray (Ljava/lang/String;)[Ljava/lang/String;
                    ASTORE 6     // Ljava/lang/Object; convertedValue
                L2: ALOAD 7     // Ljava/beans/PropertyEditor; editor   (line 160)
                    IFNONNULL L3
                    ALOAD_0     // Lorg/springframework/beans/TypeConverterDelegate; this   (line 161)
                    ALOAD 4     // Ljava/lang/Class; requiredType
                    ALOAD 5     // Lorg/springframework/core/convert/TypeDescriptor; typeDescriptor
                    INVOKEVIRTUAL org.springframework.beans.TypeConverterDelegate.findDefaultEditor (Ljava/lang/Class;Lorg/springframework/core/convert/TypeDescriptor;)Ljava/beans/PropertyEditor;
                    ASTORE 7     // Ljava/beans/PropertyEditor; editor
                L3: ALOAD_0     // Lorg/springframework/beans/TypeConverterDelegate; this   (line 163)
                    ALOAD_2     // Ljava/lang/Object; oldValue
                    ALOAD 6     // Ljava/lang/Object; convertedValue
                    ALOAD 4     // Ljava/lang/Class; requiredType
                    ALOAD 7     // Ljava/beans/PropertyEditor; editor
                    INVOKEVIRTUAL org.springframework.beans.TypeConverterDelegate.doConvertValue (Ljava/lang/Object;Ljava/lang/Object;Ljava/lang/Class;Ljava/beans/PropertyEditor;)Ljava/lang/Object;
                    ASTORE 6     // Ljava/lang/Object; convertedValue
                L4: ALOAD 4     // Ljava/lang/Class; requiredType   (line 166)
                    IFNULL L17
                    ALOAD 6     // Ljava/lang/Object; convertedValue   (line 169)
                    IFNULL L13
                    ALOAD 4     // Ljava/lang/Class; requiredType   (line 170)
                    INVOKEVIRTUAL java.lang.Class.isArray ()Z
                    IFEQ L6
                    ALOAD 6     // Ljava/lang/Object; convertedValue   (line 172)
                    INSTANCEOF java.lang.String
                    IFEQ L5
                    LDC java.lang.Enum
                    ALOAD 4     // Ljava/lang/Class; requiredType
                    INVOKEVIRTUAL java.lang.Class.getComponentType ()Ljava/lang/Class;
                    INVOKEVIRTUAL java.lang.Class.isAssignableFrom (Ljava/lang/Class;)Z
                    IFEQ L5
                    ALOAD 6     // Ljava/lang/Object; convertedValue   (line 173)
                    CHECKCAST java.lang.String
                    INVOKESTATIC org.springframework.util.StringUtils.commaDelimitedListToStringArray (Ljava/lang/String;)[Ljava/lang/String;
                    ASTORE 6     // Ljava/lang/Object; convertedValue
                L5: ALOAD_0     // Lorg/springframework/beans/TypeConverterDelegate; this   (line 175)
                    ALOAD 6     // Ljava/lang/Object; convertedValue
                    ALOAD_1     // Ljava/lang/String; propertyName
                    ALOAD 4     // Ljava/lang/Class; requiredType
                    INVOKEVIRTUAL java.lang.Class.getComponentType ()Ljava/lang/Class;
                    INVOKEVIRTUAL org.springframework.beans.TypeConverterDelegate.convertToTypedArray (Ljava/lang/Object;Ljava/lang/String;Ljava/lang/Class;)Ljava/lang/Object;
                    ARETURN
                L6: ALOAD 6     // Ljava/lang/Object; convertedValue   (line 177)
                    INSTANCEOF java.util.Collection
                    IFEQ L7
                    ALOAD_0     // Lorg/springframework/beans/TypeConverterDelegate; this   (line 179)
                    ALOAD 6     // Ljava/lang/Object; convertedValue   (line 180)
                    CHECKCAST java.util.Collection
                    ALOAD_1     // Ljava/lang/String; propertyName
                    ALOAD 4     // Ljava/lang/Class; requiredType
                    ALOAD 5     // Lorg/springframework/core/convert/TypeDescriptor; typeDescriptor
                    INVOKEVIRTUAL org.springframework.beans.TypeConverterDelegate.convertToTypedCollection (Ljava/util/Collection;Ljava/lang/String;Ljava/lang/Class;Lorg/springframework/core/convert/TypeDescriptor;)Ljava/util/Collection;   (line 179)
                    ASTORE 6     // Ljava/lang/Object; convertedValue
                    GOTO L8
                L7: ALOAD 6     // Ljava/lang/Object; convertedValue   (line 182)
                    INSTANCEOF java.util.Map
                    IFEQ L8
                    ALOAD_0     // Lorg/springframework/beans/TypeConverterDelegate; this   (line 184)
                    ALOAD 6     // Ljava/lang/Object; convertedValue   (line 185)
                    CHECKCAST java.util.Map
                    ALOAD_1     // Ljava/lang/String; propertyName
                    ALOAD 4     // Ljava/lang/Class; requiredType
                    ALOAD 5     // Lorg/springframework/core/convert/TypeDescriptor; typeDescriptor
                    INVOKEVIRTUAL org.springframework.beans.TypeConverterDelegate.convertToTypedMap (Ljava/util/Map;Ljava/lang/String;Ljava/lang/Class;Lorg/springframework/core/convert/TypeDescriptor;)Ljava/util/Map;   (line 184)
                    ASTORE 6     // Ljava/lang/Object; convertedValue
                L8: ALOAD 6     // Ljava/lang/Object; convertedValue   (line 187)
                    INVOKEVIRTUAL java.lang.Object.getClass ()Ljava/lang/Class;
                    INVOKEVIRTUAL java.lang.Class.isArray ()Z
                    IFEQ L9
                    ALOAD 6     // Ljava/lang/Object; convertedValue
                    INVOKESTATIC java.lang.reflect.Array.getLength (Ljava/lang/Object;)I
                    ICONST_1
                    IF_ICMPNE L9
                    ALOAD 6     // Ljava/lang/Object; convertedValue   (line 188)
                    ICONST_0
                    INVOKESTATIC java.lang.reflect.Array.get (Ljava/lang/Object;I)Ljava/lang/Object;
                    ASTORE 6     // Ljava/lang/Object; convertedValue
                L9: LDC java.lang.String   (line 190)
                    ALOAD 4     // Ljava/lang/Class; requiredType
                    INVOKEVIRTUAL java.lang.Object.equals (Ljava/lang/Object;)Z
                    IFEQ L10
                    ALOAD 6     // Ljava/lang/Object; convertedValue
                    INVOKEVIRTUAL java.lang.Object.getClass ()Ljava/lang/Class;
                    INVOKESTATIC org.springframework.util.ClassUtils.isPrimitiveOrWrapper (Ljava/lang/Class;)Z
                    IFEQ L10
                    ALOAD 6     // Ljava/lang/Object; convertedValue   (line 192)
                    INVOKEVIRTUAL java.lang.Object.toString ()Ljava/lang/String;
                    ARETURN
               L10: ALOAD 6     // Ljava/lang/Object; convertedValue   (line 194)
                    INSTANCEOF java.lang.String
                    IFEQ L13
                    ALOAD 4     // Ljava/lang/Class; requiredType
                    ALOAD 6     // Ljava/lang/Object; convertedValue
                    INVOKEVIRTUAL java.lang.Class.isInstance (Ljava/lang/Object;)Z
                    IFNE L13
                    ALOAD 4     // Ljava/lang/Class; requiredType   (line 195)
                    INVOKEVIRTUAL java.lang.Class.isInterface ()Z
                    IFNE L11
                    ALOAD 4     // Ljava/lang/Class; requiredType
                    INVOKEVIRTUAL java.lang.Class.isEnum ()Z
                    IFNE L11
    catch java.lang.Exception -> E2
    | catch java.lang.NoSuchMethodException -> E1
    | |             ALOAD 4     // Ljava/lang/Class; requiredType   (line 197)
    | |             ICONST_1
    | |             ANEWARRAY java.lang.Class
    | |             DUP
    | |             ICONST_0
    | |             LDC java.lang.String
    | |             AASTORE
    | |             INVOKEVIRTUAL java.lang.Class.getConstructor ([Ljava/lang/Class;)Ljava/lang/reflect/Constructor;
    | |             ASTORE 10
    | |             ALOAD 10     // Ljava/lang/reflect/Constructor; strCtor   (line 198)
    | |             ICONST_1
    | |             ANEWARRAY java.lang.Object
    | |             DUP
    | |             ICONST_0
    | |             ALOAD 6     // Ljava/lang/Object; convertedValue
    | |             AASTORE
    | |             INVOKESTATIC org.springframework.beans.BeanUtils.instantiateClass (Ljava/lang/reflect/Constructor;[Ljava/lang/Object;)Ljava/lang/Object;
    | catch java.lang.NoSuchMethodException -> E1
    catch java.lang.Exception -> E2
                    ARETURN
                E1: ASTORE 10   (line 200)
                    GETSTATIC org.springframework.beans.TypeConverterDelegate.logger Lorg/apache/commons/logging/Log;   (line 202)
                    INVOKEINTERFACE org.apache.commons.logging.Log.isTraceEnabled ()Z
                    IFEQ L11
                    GETSTATIC org.springframework.beans.TypeConverterDelegate.logger Lorg/apache/commons/logging/Log;   (line 203)
                    NEW java.lang.StringBuilder
                    DUP
                    LDC "No String constructor found on type ["
                    INVOKESPECIAL java.lang.StringBuilder.<init> (Ljava/lang/String;)V
                    ALOAD 4     // Ljava/lang/Class; requiredType
                    INVOKEVIRTUAL java.lang.Class.getName ()Ljava/lang/String;
                    INVOKEVIRTUAL java.lang.StringBuilder.append (Ljava/lang/String;)Ljava/lang/StringBuilder;
                    LDC "]"
                    INVOKEVIRTUAL java.lang.StringBuilder.append (Ljava/lang/String;)Ljava/lang/StringBuilder;
                    INVOKEVIRTUAL java.lang.StringBuilder.toString ()Ljava/lang/String;
                    ALOAD 10     // Ljava/lang/NoSuchMethodException; ex
                    INVOKEINTERFACE org.apache.commons.logging.Log.trace (Ljava/lang/Object;Ljava/lang/Throwable;)V
                    GOTO L11
                E2: ASTORE 10   (line 206)
                    GETSTATIC org.springframework.beans.TypeConverterDelegate.logger Lorg/apache/commons/logging/Log;   (line 207)
                    INVOKEINTERFACE org.apache.commons.logging.Log.isDebugEnabled ()Z
                    IFEQ L11
                    GETSTATIC org.springframework.beans.TypeConverterDelegate.logger Lorg/apache/commons/logging/Log;   (line 208)
                    NEW java.lang.StringBuilder
                    DUP
                    LDC "Construction via String failed for type ["
                    INVOKESPECIAL java.lang.StringBuilder.<init> (Ljava/lang/String;)V
                    ALOAD 4     // Ljava/lang/Class; requiredType
                    INVOKEVIRTUAL java.lang.Class.getName ()Ljava/lang/String;
                    INVOKEVIRTUAL java.lang.StringBuilder.append (Ljava/lang/String;)Ljava/lang/StringBuilder;
                    LDC "]"
                    INVOKEVIRTUAL java.lang.StringBuilder.append (Ljava/lang/String;)Ljava/lang/StringBuilder;
                    INVOKEVIRTUAL java.lang.StringBuilder.toString ()Ljava/lang/String;
                    ALOAD 10     // Ljava/lang/Exception; ex
                    INVOKEINTERFACE org.apache.commons.logging.Log.debug (Ljava/lang/Object;Ljava/lang/Throwable;)V
               L11: ALOAD 6     // Ljava/lang/Object; convertedValue   (line 212)
                    CHECKCAST java.lang.String
                    INVOKEVIRTUAL java.lang.String.trim ()Ljava/lang/String;
                    ASTORE 10
                    ALOAD 4     // Ljava/lang/Class; requiredType   (line 213)
                    INVOKEVIRTUAL java.lang.Class.isEnum ()Z
                    IFEQ L12
                    LDC ""
                    ALOAD 10     // Ljava/lang/String; trimmedValue
                    INVOKEVIRTUAL java.lang.String.equals (Ljava/lang/Object;)Z
                    IFEQ L12
                    ACONST_NULL   (line 215)
                    ARETURN
               L12: ALOAD_0     // Lorg/springframework/beans/TypeConverterDelegate; this   (line 218)
                    ALOAD 4     // Ljava/lang/Class; requiredType
                    ALOAD 10     // Ljava/lang/String; trimmedValue
                    ALOAD 6     // Ljava/lang/Object; convertedValue
                    INVOKESPECIAL org.springframework.beans.TypeConverterDelegate.attemptToConvertStringToEnum (Ljava/lang/Class;Ljava/lang/String;Ljava/lang/Object;)Ljava/lang/Object;
                    ASTORE 6     // Ljava/lang/Object; convertedValue
               L13: ALOAD 4     // Ljava/lang/Class; requiredType   (line 222)
                    ALOAD 6     // Ljava/lang/Object; convertedValue
                    INVOKESTATIC org.springframework.util.ClassUtils.isAssignableValue (Ljava/lang/Class;Ljava/lang/Object;)Z
                    IFNE L17
                    ALOAD 8     // Lorg/springframework/core/convert/ConversionFailedException; firstAttemptEx   (line 223)
                    IFNULL L14
                    ALOAD 8     // Lorg/springframework/core/convert/ConversionFailedException; firstAttemptEx   (line 224)
                    ATHROW
               L14: NEW java.lang.StringBuilder   (line 227)
                    DUP
                    INVOKESPECIAL java.lang.StringBuilder.<init> ()V
                    ASTORE 10
                    ALOAD 10     // Ljava/lang/StringBuilder; msg   (line 228)
                    LDC "Cannot convert value of type ["
                    INVOKEVIRTUAL java.lang.StringBuilder.append (Ljava/lang/String;)Ljava/lang/StringBuilder;
                    ALOAD_3     // Ljava/lang/Object; newValue
                    INVOKESTATIC org.springframework.util.ClassUtils.getDescriptiveType (Ljava/lang/Object;)Ljava/lang/String;
                    INVOKEVIRTUAL java.lang.StringBuilder.append (Ljava/lang/String;)Ljava/lang/StringBuilder;
                    POP
                    ALOAD 10     // Ljava/lang/StringBuilder; msg   (line 229)
                    LDC "] to required type ["
                    INVOKEVIRTUAL java.lang.StringBuilder.append (Ljava/lang/String;)Ljava/lang/StringBuilder;
                    ALOAD 4     // Ljava/lang/Class; requiredType
                    INVOKESTATIC org.springframework.util.ClassUtils.getQualifiedName (Ljava/lang/Class;)Ljava/lang/String;
                    INVOKEVIRTUAL java.lang.StringBuilder.append (Ljava/lang/String;)Ljava/lang/StringBuilder;
                    LDC "]"
                    INVOKEVIRTUAL java.lang.StringBuilder.append (Ljava/lang/String;)Ljava/lang/StringBuilder;
                    POP
                    ALOAD_1     // Ljava/lang/String; propertyName   (line 230)
                    IFNULL L15
                    ALOAD 10     // Ljava/lang/StringBuilder; msg   (line 231)
                    LDC " for property '"
                    INVOKEVIRTUAL java.lang.StringBuilder.append (Ljava/lang/String;)Ljava/lang/StringBuilder;
                    ALOAD_1     // Ljava/lang/String; propertyName
                    INVOKEVIRTUAL java.lang.StringBuilder.append (Ljava/lang/String;)Ljava/lang/StringBuilder;
                    LDC_W "'"
                    INVOKEVIRTUAL java.lang.StringBuilder.append (Ljava/lang/String;)Ljava/lang/StringBuilder;
                    POP
               L15: ALOAD 7     // Ljava/beans/PropertyEditor; editor   (line 233)
                    IFNULL L16
                    ALOAD 10     // Ljava/lang/StringBuilder; msg   (line 234)
                    LDC_W ": PropertyEditor ["
                    INVOKEVIRTUAL java.lang.StringBuilder.append (Ljava/lang/String;)Ljava/lang/StringBuilder;
                    ALOAD 7     // Ljava/beans/PropertyEditor; editor
                    INVOKEVIRTUAL java.lang.Object.getClass ()Ljava/lang/Class;
                    INVOKEVIRTUAL java.lang.Class.getName ()Ljava/lang/String;
                    INVOKEVIRTUAL java.lang.StringBuilder.append (Ljava/lang/String;)Ljava/lang/StringBuilder;
                    LDC_W "] returned inappropriate value of type ["   (line 235)
                    INVOKEVIRTUAL java.lang.StringBuilder.append (Ljava/lang/String;)Ljava/lang/StringBuilder;   (line 234)
                    ALOAD 6     // Ljava/lang/Object; convertedValue   (line 236)
                    INVOKESTATIC org.springframework.util.ClassUtils.getDescriptiveType (Ljava/lang/Object;)Ljava/lang/String;
                    INVOKEVIRTUAL java.lang.StringBuilder.append (Ljava/lang/String;)Ljava/lang/StringBuilder;   (line 235)
                    LDC "]"   (line 236)
                    INVOKEVIRTUAL java.lang.StringBuilder.append (Ljava/lang/String;)Ljava/lang/StringBuilder;
                    POP
                    NEW java.lang.IllegalArgumentException   (line 237)
                    DUP
                    ALOAD 10     // Ljava/lang/StringBuilder; msg
                    INVOKEVIRTUAL java.lang.StringBuilder.toString ()Ljava/lang/String;
                    INVOKESPECIAL java.lang.IllegalArgumentException.<init> (Ljava/lang/String;)V
                    ATHROW
               L16: ALOAD 10     // Ljava/lang/StringBuilder; msg   (line 240)
                    LDC_W ": no matching editors or conversion strategy found"
                    INVOKEVIRTUAL java.lang.StringBuilder.append (Ljava/lang/String;)Ljava/lang/StringBuilder;
                    POP
                    NEW java.lang.IllegalStateException   (line 241)
                    DUP
                    ALOAD 10     // Ljava/lang/StringBuilder; msg
                    INVOKEVIRTUAL java.lang.StringBuilder.toString ()Ljava/lang/String;
                    INVOKESPECIAL java.lang.IllegalStateException.<init> (Ljava/lang/String;)V
                    ATHROW
               L17: ALOAD 8     // Lorg/springframework/core/convert/ConversionFailedException; firstAttemptEx   (line 246)
                    IFNULL L19
                    ALOAD 7     // Ljava/beans/PropertyEditor; editor   (line 247)
                    IFNONNULL L18
                    ALOAD 6     // Ljava/lang/Object; convertedValue
                    ALOAD_3     // Ljava/lang/Object; newValue
                    IF_ACMPNE L18
                    ALOAD 8     // Lorg/springframework/core/convert/ConversionFailedException; firstAttemptEx   (line 248)
                    ATHROW
               L18: GETSTATIC org.springframework.beans.TypeConverterDelegate.logger Lorg/apache/commons/logging/Log;   (line 250)
                    LDC_W "Original ConversionService attempt failed - ignored since PropertyEditor based conversion eventually succeeded"
                    ALOAD 8     // Lorg/springframework/core/convert/ConversionFailedException; firstAttemptEx   (line 251)
                    INVOKEINTERFACE org.apache.commons.logging.Log.debug (Ljava/lang/Object;Ljava/lang/Throwable;)V   (line 250)
               L19: ALOAD 6     // Ljava/lang/Object; convertedValue   (line 254)
                    ARETURN
  end public Object convertIfNecessary(String, Object, Object, Class, org.springframework.core.convert.TypeDescriptor) throws java.lang.IllegalArgumentException

  private Object attemptToConvertStringToEnum(Class, String, Object):
                    ALOAD_3     // Ljava/lang/Object; currentConvertedValue   (line 258)
                    ASTORE 4
                    LDC java.lang.Enum   (line 260)
                    ALOAD_1     // Ljava/lang/Class; requiredType
                    INVOKEVIRTUAL java.lang.Object.equals (Ljava/lang/Object;)Z
                    IFEQ L0
                    ALOAD_2     // Ljava/lang/String; trimmedValue   (line 262)
                    LDC_W "."
                    INVOKEVIRTUAL java.lang.String.lastIndexOf (Ljava/lang/String;)I
                    ISTORE 5
                    ILOAD 5     // I index   (line 263)
                    ICONST_M1
                    IF_ICMPLE L0
                    ALOAD_2     // Ljava/lang/String; trimmedValue   (line 264)
                    ICONST_0
                    ILOAD 5     // I index
                    INVOKEVIRTUAL java.lang.String.substring (II)Ljava/lang/String;
                    ASTORE 6
                    ALOAD_2     // Ljava/lang/String; trimmedValue   (line 265)
                    ILOAD 5     // I index
                    ICONST_1
                    IADD
                    INVOKEVIRTUAL java.lang.String.substring (I)Ljava/lang/String;
                    ASTORE 7
                    ALOAD_0     // Lorg/springframework/beans/TypeConverterDelegate; this   (line 266)
                    GETFIELD org.springframework.beans.TypeConverterDelegate.targetObject Ljava/lang/Object;
                    INVOKEVIRTUAL java.lang.Object.getClass ()Ljava/lang/Class;
                    INVOKEVIRTUAL java.lang.Class.getClassLoader ()Ljava/lang/ClassLoader;
                    ASTORE 8
    catch java.lang.Throwable -> E1
    | catch java.lang.ClassNotFoundException -> E0
    | |             ALOAD 8     // Ljava/lang/ClassLoader; loader   (line 268)
    | |             ALOAD 6     // Ljava/lang/String; enumType
    | |             INVOKEVIRTUAL java.lang.ClassLoader.loadClass (Ljava/lang/String;)Ljava/lang/Class;
    | |             ASTORE 9
    | |             ALOAD 9     // Ljava/lang/Class; enumValueType   (line 269)
    | |             ALOAD 7     // Ljava/lang/String; fieldName
    | |             INVOKEVIRTUAL java.lang.Class.getField (Ljava/lang/String;)Ljava/lang/reflect/Field;
    | |             ASTORE 10
    | |             ALOAD 10     // Ljava/lang/reflect/Field; enumField   (line 270)
    | |             ACONST_NULL
    | |             INVOKEVIRTUAL java.lang.reflect.Field.get (Ljava/lang/Object;)Ljava/lang/Object;
    | |             ASTORE 4     // Ljava/lang/Object; convertedValue
    | catch java.lang.ClassNotFoundException -> E0
    catch java.lang.Throwable -> E1
                    GOTO L0
                E0: ASTORE 9   (line 272)
                    GETSTATIC org.springframework.beans.TypeConverterDelegate.logger Lorg/apache/commons/logging/Log;   (line 273)
                    INVOKEINTERFACE org.apache.commons.logging.Log.isTraceEnabled ()Z
                    IFEQ L0
                    GETSTATIC org.springframework.beans.TypeConverterDelegate.logger Lorg/apache/commons/logging/Log;   (line 274)
                    NEW java.lang.StringBuilder
                    DUP
                    LDC_W "Enum class ["
                    INVOKESPECIAL java.lang.StringBuilder.<init> (Ljava/lang/String;)V
                    ALOAD 6     // Ljava/lang/String; enumType
                    INVOKEVIRTUAL java.lang.StringBuilder.append (Ljava/lang/String;)Ljava/lang/StringBuilder;
                    LDC_W "] cannot be loaded from ["
                    INVOKEVIRTUAL java.lang.StringBuilder.append (Ljava/lang/String;)Ljava/lang/StringBuilder;
                    ALOAD 8     // Ljava/lang/ClassLoader; loader
                    INVOKEVIRTUAL java.lang.StringBuilder.append (Ljava/lang/Object;)Ljava/lang/StringBuilder;
                    LDC "]"
                    INVOKEVIRTUAL java.lang.StringBuilder.append (Ljava/lang/String;)Ljava/lang/StringBuilder;
                    INVOKEVIRTUAL java.lang.StringBuilder.toString ()Ljava/lang/String;
                    ALOAD 9     // Ljava/lang/ClassNotFoundException; ex
                    INVOKEINTERFACE org.apache.commons.logging.Log.trace (Ljava/lang/Object;Ljava/lang/Throwable;)V
                    GOTO L0
                E1: ASTORE 9   (line 277)
                    GETSTATIC org.springframework.beans.TypeConverterDelegate.logger Lorg/apache/commons/logging/Log;   (line 278)
                    INVOKEINTERFACE org.apache.commons.logging.Log.isTraceEnabled ()Z
                    IFEQ L0
                    GETSTATIC org.springframework.beans.TypeConverterDelegate.logger Lorg/apache/commons/logging/Log;   (line 279)
                    NEW java.lang.StringBuilder
                    DUP
                    LDC_W "Field ["
                    INVOKESPECIAL java.lang.StringBuilder.<init> (Ljava/lang/String;)V
                    ALOAD 7     // Ljava/lang/String; fieldName
                    INVOKEVIRTUAL java.lang.StringBuilder.append (Ljava/lang/String;)Ljava/lang/StringBuilder;
                    LDC_W "] isn't an enum value for type ["
                    INVOKEVIRTUAL java.lang.StringBuilder.append (Ljava/lang/String;)Ljava/lang/StringBuilder;
                    ALOAD 6     // Ljava/lang/String; enumType
                    INVOKEVIRTUAL java.lang.StringBuilder.append (Ljava/lang/String;)Ljava/lang/StringBuilder;
                    LDC "]"
                    INVOKEVIRTUAL java.lang.StringBuilder.append (Ljava/lang/String;)Ljava/lang/StringBuilder;
                    INVOKEVIRTUAL java.lang.StringBuilder.toString ()Ljava/lang/String;
                    ALOAD 9     // Ljava/lang/Throwable; ex
                    INVOKEINTERFACE org.apache.commons.logging.Log.trace (Ljava/lang/Object;Ljava/lang/Throwable;)V
                L0: ALOAD 4     // Ljava/lang/Object; convertedValue   (line 285)
                    ALOAD_3     // Ljava/lang/Object; currentConvertedValue
                    IF_ACMPNE L1
    catch java.lang.Throwable -> E2
    |               ALOAD_1     // Ljava/lang/Class; requiredType   (line 290)
    |               ALOAD_2     // Ljava/lang/String; trimmedValue
    |               INVOKEVIRTUAL java.lang.Class.getField (Ljava/lang/String;)Ljava/lang/reflect/Field;
    |               ASTORE 5
    |               ALOAD 5     // Ljava/lang/reflect/Field; enumField   (line 291)
    |               ACONST_NULL
    |               INVOKEVIRTUAL java.lang.reflect.Field.get (Ljava/lang/Object;)Ljava/lang/Object;
    |               ASTORE 4     // Ljava/lang/Object; convertedValue
    catch java.lang.Throwable -> E2
                    GOTO L1
                E2: ASTORE 5   (line 293)
                    GETSTATIC org.springframework.beans.TypeConverterDelegate.logger Lorg/apache/commons/logging/Log;   (line 294)
                    INVOKEINTERFACE org.apache.commons.logging.Log.isTraceEnabled ()Z
                    IFEQ L1
                    GETSTATIC org.springframework.beans.TypeConverterDelegate.logger Lorg/apache/commons/logging/Log;   (line 295)
                    NEW java.lang.StringBuilder
                    DUP
                    LDC_W "Field ["
                    INVOKESPECIAL java.lang.StringBuilder.<init> (Ljava/lang/String;)V
                    ALOAD 4     // Ljava/lang/Object; convertedValue
                    INVOKEVIRTUAL java.lang.StringBuilder.append (Ljava/lang/Object;)Ljava/lang/StringBuilder;
                    LDC_W "] isn't an enum value"
                    INVOKEVIRTUAL java.lang.StringBuilder.append (Ljava/lang/String;)Ljava/lang/StringBuilder;
                    INVOKEVIRTUAL java.lang.StringBuilder.toString ()Ljava/lang/String;
                    ALOAD 5     // Ljava/lang/Throwable; ex
                    INVOKEINTERFACE org.apache.commons.logging.Log.trace (Ljava/lang/Object;Ljava/lang/Throwable;)V
                L1: ALOAD 4     // Ljava/lang/Object; convertedValue   (line 301)
                    ARETURN
  end private Object attemptToConvertStringToEnum(Class, String, Object)

  protected java.beans.PropertyEditor findDefaultEditor(Class, org.springframework.core.convert.TypeDescriptor):
                    ACONST_NULL   (line 310)
                    ASTORE_3
                    ALOAD_3     // Ljava/beans/PropertyEditor; editor   (line 315)
                    IFNONNULL L0
                    ALOAD_1     // Ljava/lang/Class; requiredType
                    IFNULL L0
                    ALOAD_0     // Lorg/springframework/beans/TypeConverterDelegate; this   (line 317)
                    GETFIELD org.springframework.beans.TypeConverterDelegate.propertyEditorRegistry Lorg/springframework/beans/PropertyEditorRegistrySupport;
                    ALOAD_1     // Ljava/lang/Class; requiredType
                    INVOKEVIRTUAL org.springframework.beans.PropertyEditorRegistrySupport.getDefaultEditor (Ljava/lang/Class;)Ljava/beans/PropertyEditor;
                    ASTORE_3     // Ljava/beans/PropertyEditor; editor
                    ALOAD_3     // Ljava/beans/PropertyEditor; editor   (line 318)
                    IFNONNULL L0
                    LDC java.lang.String
                    ALOAD_1     // Ljava/lang/Class; requiredType
                    INVOKEVIRTUAL java.lang.Object.equals (Ljava/lang/Object;)Z
                    IFNE L0
                    ALOAD_1     // Ljava/lang/Class; requiredType   (line 320)
                    INVOKESTATIC org.springframework.beans.BeanUtils.findEditorByConvention (Ljava/lang/Class;)Ljava/beans/PropertyEditor;
                    ASTORE_3     // Ljava/beans/PropertyEditor; editor
                L0: ALOAD_3     // Ljava/beans/PropertyEditor; editor   (line 323)
                    ARETURN
  end protected java.beans.PropertyEditor findDefaultEditor(Class, org.springframework.core.convert.TypeDescriptor)

  protected Object doConvertValue(Object, Object, Class, java.beans.PropertyEditor):
                    ALOAD_2     // Ljava/lang/Object; newValue   (line 338)
                    ASTORE 5
                    ICONST_0   (line 339)
                    ISTORE 6
                    ALOAD 4     // Ljava/beans/PropertyEditor; editor   (line 341)
                    IFNULL L0
                    ALOAD_0     // Lorg/springframework/beans/TypeConverterDelegate; this   (line 342)
                    GETFIELD org.springframework.beans.TypeConverterDelegate.propertyEditorRegistry Lorg/springframework/beans/PropertyEditorRegistrySupport;
                    ALOAD 4     // Ljava/beans/PropertyEditor; editor
                    INVOKEVIRTUAL org.springframework.beans.PropertyEditorRegistrySupport.isSharedEditor (Ljava/beans/PropertyEditor;)Z
                    ISTORE 6     // Z sharedEditor
                L0: ALOAD 4     // Ljava/beans/PropertyEditor; editor   (line 345)
                    IFNULL L3
                    ALOAD 5     // Ljava/lang/Object; convertedValue
                    INSTANCEOF java.lang.String
                    IFNE L3
    catch java.lang.Exception -> E2
    |               ILOAD 6     // Z sharedEditor   (line 352)
    |               IFEQ L1
    |               ALOAD 4     // Ljava/beans/PropertyEditor; editor   (line 354)
    |               DUP
    |               ASTORE 8
    |               MONITORENTER
    | finally -> E1
    | |             ALOAD 4     // Ljava/beans/PropertyEditor; editor   (line 355)
    | |             ALOAD 5     // Ljava/lang/Object; convertedValue
    | |             INVOKEINTERFACE java.beans.PropertyEditor.setValue (Ljava/lang/Object;)V
    | |             ALOAD 4     // Ljava/beans/PropertyEditor; editor   (line 356)
    | |             INVOKEINTERFACE java.beans.PropertyEditor.getValue ()Ljava/lang/Object;
    | |             ASTORE 7
    | |             ALOAD 8   (line 354)
    | |             MONITOREXIT
    | finally -> E1
    |               GOTO L2
    | finally -> E1
    | |         E1: ALOAD 8
    | |             MONITOREXIT
    | finally -> E1
    |               ATHROW
    |           L1: ALOAD 4     // Ljava/beans/PropertyEditor; editor   (line 361)
    |               ALOAD 5     // Ljava/lang/Object; convertedValue
    |               INVOKEINTERFACE java.beans.PropertyEditor.setValue (Ljava/lang/Object;)V
    |               ALOAD 4     // Ljava/beans/PropertyEditor; editor   (line 362)
    |               INVOKEINTERFACE java.beans.PropertyEditor.getValue ()Ljava/lang/Object;
    |               ASTORE 7
    |           L2: ALOAD 7     // Ljava/lang/Object; newConvertedValue   (line 364)
    |               ALOAD 5     // Ljava/lang/Object; convertedValue
    |               IF_ACMPEQ L3
    |               ALOAD 7     // Ljava/lang/Object; newConvertedValue   (line 365)
    |               ASTORE 5     // Ljava/lang/Object; convertedValue
    |               ACONST_NULL   (line 368)
    |               ASTORE 4     // Ljava/beans/PropertyEditor; editor
    catch java.lang.Exception -> E2
                    GOTO L3
                E2: ASTORE 7   (line 371)
                    GETSTATIC org.springframework.beans.TypeConverterDelegate.logger Lorg/apache/commons/logging/Log;   (line 372)
                    INVOKEINTERFACE org.apache.commons.logging.Log.isDebugEnabled ()Z
                    IFEQ L3
                    GETSTATIC org.springframework.beans.TypeConverterDelegate.logger Lorg/apache/commons/logging/Log;   (line 373)
                    NEW java.lang.StringBuilder
                    DUP
                    LDC_W "PropertyEditor ["
                    INVOKESPECIAL java.lang.StringBuilder.<init> (Ljava/lang/String;)V
                    ALOAD 4     // Ljava/beans/PropertyEditor; editor
                    INVOKEVIRTUAL java.lang.Object.getClass ()Ljava/lang/Class;
                    INVOKEVIRTUAL java.lang.Class.getName ()Ljava/lang/String;
                    INVOKEVIRTUAL java.lang.StringBuilder.append (Ljava/lang/String;)Ljava/lang/StringBuilder;
                    LDC_W "] does not support setValue call"
                    INVOKEVIRTUAL java.lang.StringBuilder.append (Ljava/lang/String;)Ljava/lang/StringBuilder;
                    INVOKEVIRTUAL java.lang.StringBuilder.toString ()Ljava/lang/String;
                    ALOAD 7     // Ljava/lang/Exception; ex
                    INVOKEINTERFACE org.apache.commons.logging.Log.debug (Ljava/lang/Object;Ljava/lang/Throwable;)V
                L3: ALOAD 5     // Ljava/lang/Object; convertedValue   (line 379)
                    ASTORE 7
                    ALOAD_3     // Ljava/lang/Class; requiredType   (line 381)
                    IFNULL L5
                    ALOAD_3     // Ljava/lang/Class; requiredType
                    INVOKEVIRTUAL java.lang.Class.isArray ()Z
                    IFNE L5
                    ALOAD 5     // Ljava/lang/Object; convertedValue
                    INSTANCEOF [Ljava.lang.String;
                    IFEQ L5
                    GETSTATIC org.springframework.beans.TypeConverterDelegate.logger Lorg/apache/commons/logging/Log;   (line 385)
                    INVOKEINTERFACE org.apache.commons.logging.Log.isTraceEnabled ()Z
                    IFEQ L4
                    GETSTATIC org.springframework.beans.TypeConverterDelegate.logger Lorg/apache/commons/logging/Log;   (line 386)
                    NEW java.lang.StringBuilder
                    DUP
                    LDC_W "Converting String array to comma-delimited String ["
                    INVOKESPECIAL java.lang.StringBuilder.<init> (Ljava/lang/String;)V
                    ALOAD 5     // Ljava/lang/Object; convertedValue
                    INVOKEVIRTUAL java.lang.StringBuilder.append (Ljava/lang/Object;)Ljava/lang/StringBuilder;
                    LDC "]"
                    INVOKEVIRTUAL java.lang.StringBuilder.append (Ljava/lang/String;)Ljava/lang/StringBuilder;
                    INVOKEVIRTUAL java.lang.StringBuilder.toString ()Ljava/lang/String;
                    INVOKEINTERFACE org.apache.commons.logging.Log.trace (Ljava/lang/Object;)V
                L4: ALOAD 5     // Ljava/lang/Object; convertedValue   (line 388)
                    CHECKCAST [Ljava.lang.String;
                    INVOKESTATIC org.springframework.util.StringUtils.arrayToCommaDelimitedString ([Ljava/lang/Object;)Ljava/lang/String;
                    ASTORE 5     // Ljava/lang/Object; convertedValue
                L5: ALOAD 5     // Ljava/lang/Object; convertedValue   (line 391)
                    INSTANCEOF java.lang.String
                    IFEQ L9
                    ALOAD 4     // Ljava/beans/PropertyEditor; editor   (line 392)
                    IFNULL L8
                    GETSTATIC org.springframework.beans.TypeConverterDelegate.logger Lorg/apache/commons/logging/Log;   (line 394)
                    INVOKEINTERFACE org.apache.commons.logging.Log.isTraceEnabled ()Z
                    IFEQ L6
                    GETSTATIC org.springframework.beans.TypeConverterDelegate.logger Lorg/apache/commons/logging/Log;   (line 395)
                    NEW java.lang.StringBuilder
                    DUP
                    LDC_W "Converting String to ["
                    INVOKESPECIAL java.lang.StringBuilder.<init> (Ljava/lang/String;)V
                    ALOAD_3     // Ljava/lang/Class; requiredType
                    INVOKEVIRTUAL java.lang.StringBuilder.append (Ljava/lang/Object;)Ljava/lang/StringBuilder;
                    LDC_W "] using property editor ["
                    INVOKEVIRTUAL java.lang.StringBuilder.append (Ljava/lang/String;)Ljava/lang/StringBuilder;
                    ALOAD 4     // Ljava/beans/PropertyEditor; editor
                    INVOKEVIRTUAL java.lang.StringBuilder.append (Ljava/lang/Object;)Ljava/lang/StringBuilder;
                    LDC "]"
                    INVOKEVIRTUAL java.lang.StringBuilder.append (Ljava/lang/String;)Ljava/lang/StringBuilder;
                    INVOKEVIRTUAL java.lang.StringBuilder.toString ()Ljava/lang/String;
                    INVOKEINTERFACE org.apache.commons.logging.Log.trace (Ljava/lang/Object;)V
                L6: ALOAD 5     // Ljava/lang/Object; convertedValue   (line 397)
                    CHECKCAST java.lang.String
                    ASTORE 8
                    ILOAD 6     // Z sharedEditor   (line 398)
                    IFEQ L7
                    ALOAD 4     // Ljava/beans/PropertyEditor; editor   (line 400)
                    DUP
                    ASTORE 9
                    MONITORENTER
    finally -> E4
    |               ALOAD_0     // Lorg/springframework/beans/TypeConverterDelegate; this   (line 401)
    |               ALOAD_1     // Ljava/lang/Object; oldValue
    |               ALOAD 8     // Ljava/lang/String; newTextValue
    |               ALOAD 4     // Ljava/beans/PropertyEditor; editor
    |               INVOKEVIRTUAL org.springframework.beans.TypeConverterDelegate.doConvertTextValue (Ljava/lang/Object;Ljava/lang/String;Ljava/beans/PropertyEditor;)Ljava/lang/Object;
    |               ALOAD 9
    |               MONITOREXIT
    finally -> E4
                    ARETURN
    finally -> E4
    |           E4: ALOAD 9   (line 400)
    |               MONITOREXIT
    finally -> E4
                    ATHROW
                L7: ALOAD_0     // Lorg/springframework/beans/TypeConverterDelegate; this   (line 406)
                    ALOAD_1     // Ljava/lang/Object; oldValue
                    ALOAD 8     // Ljava/lang/String; newTextValue
                    ALOAD 4     // Ljava/beans/PropertyEditor; editor
                    INVOKEVIRTUAL org.springframework.beans.TypeConverterDelegate.doConvertTextValue (Ljava/lang/Object;Ljava/lang/String;Ljava/beans/PropertyEditor;)Ljava/lang/Object;
                    ARETURN
                L8: LDC java.lang.String   (line 409)
                    ALOAD_3     // Ljava/lang/Class; requiredType
                    INVOKEVIRTUAL java.lang.Object.equals (Ljava/lang/Object;)Z
                    IFEQ L9
                    ALOAD 5     // Ljava/lang/Object; convertedValue   (line 410)
                    ASTORE 7     // Ljava/lang/Object; returnValue
                L9: ALOAD 7     // Ljava/lang/Object; returnValue   (line 414)
                    ARETURN
  end protected Object doConvertValue(Object, Object, Class, java.beans.PropertyEditor)

  protected Object doConvertTextValue(Object, String, java.beans.PropertyEditor):
    catch java.lang.Exception -> E0
    |               ALOAD_3     // Ljava/beans/PropertyEditor; editor   (line 426)
    |               ALOAD_1     // Ljava/lang/Object; oldValue
    |               INVOKEINTERFACE java.beans.PropertyEditor.setValue (Ljava/lang/Object;)V
    catch java.lang.Exception -> E0
                    GOTO L0
                E0: ASTORE 4   (line 428)
                    GETSTATIC org.springframework.beans.TypeConverterDelegate.logger Lorg/apache/commons/logging/Log;   (line 429)
                    INVOKEINTERFACE org.apache.commons.logging.Log.isDebugEnabled ()Z
                    IFEQ L0
                    GETSTATIC org.springframework.beans.TypeConverterDelegate.logger Lorg/apache/commons/logging/Log;   (line 430)
                    NEW java.lang.StringBuilder
                    DUP
                    LDC_W "PropertyEditor ["
                    INVOKESPECIAL java.lang.StringBuilder.<init> (Ljava/lang/String;)V
                    ALOAD_3     // Ljava/beans/PropertyEditor; editor
                    INVOKEVIRTUAL java.lang.Object.getClass ()Ljava/lang/Class;
                    INVOKEVIRTUAL java.lang.Class.getName ()Ljava/lang/String;
                    INVOKEVIRTUAL java.lang.StringBuilder.append (Ljava/lang/String;)Ljava/lang/StringBuilder;
                    LDC_W "] does not support setValue call"
                    INVOKEVIRTUAL java.lang.StringBuilder.append (Ljava/lang/String;)Ljava/lang/StringBuilder;
                    INVOKEVIRTUAL java.lang.StringBuilder.toString ()Ljava/lang/String;
                    ALOAD 4     // Ljava/lang/Exception; ex
                    INVOKEINTERFACE org.apache.commons.logging.Log.debug (Ljava/lang/Object;Ljava/lang/Throwable;)V
                L0: ALOAD_3     // Ljava/beans/PropertyEditor; editor   (line 434)
                    ALOAD_2     // Ljava/lang/String; newTextValue
                    INVOKEINTERFACE java.beans.PropertyEditor.setAsText (Ljava/lang/String;)V
                    ALOAD_3     // Ljava/beans/PropertyEditor; editor   (line 435)
                    INVOKEINTERFACE java.beans.PropertyEditor.getValue ()Ljava/lang/Object;
                    ARETURN
  end protected Object doConvertTextValue(Object, String, java.beans.PropertyEditor)

  protected Object convertToTypedArray(Object, String, Class):
                    ALOAD_1     // Ljava/lang/Object; input   (line 439)
                    INSTANCEOF java.util.Collection
                    IFEQ L2
                    ALOAD_1     // Ljava/lang/Object; input   (line 441)
                    CHECKCAST java.util.Collection
                    ASTORE 4
                    ALOAD_3     // Ljava/lang/Class; componentType   (line 442)
                    ALOAD 4     // Ljava/util/Collection; coll
                    INVOKEINTERFACE java.util.Collection.size ()I
                    INVOKESTATIC java.lang.reflect.Array.newInstance (Ljava/lang/Class;I)Ljava/lang/Object;
                    ASTORE 5
                    ICONST_0   (line 443)
                    ISTORE 6
                    ALOAD 4     // Ljava/util/Collection; coll   (line 444)
                    INVOKEINTERFACE java.util.Collection.iterator ()Ljava/util/Iterator;
                    ASTORE 7
                    GOTO L1
                L0: ALOAD_0     // Lorg/springframework/beans/TypeConverterDelegate; this   (line 445)
                    ALOAD_0     // Lorg/springframework/beans/TypeConverterDelegate; this   (line 446)
                    ALOAD_2     // Ljava/lang/String; propertyName
                    ILOAD 6     // I i
                    INVOKESPECIAL org.springframework.beans.TypeConverterDelegate.buildIndexedPropertyName (Ljava/lang/String;I)Ljava/lang/String;
                    ACONST_NULL
                    ALOAD 7     // Ljava/util/Iterator; it
                    INVOKEINTERFACE java.util.Iterator.next ()Ljava/lang/Object;
                    ALOAD_3     // Ljava/lang/Class; componentType
                    INVOKEVIRTUAL org.springframework.beans.TypeConverterDelegate.convertIfNecessary (Ljava/lang/String;Ljava/lang/Object;Ljava/lang/Object;Ljava/lang/Class;)Ljava/lang/Object;   (line 445)
                    ASTORE 8
                    ALOAD 5     // Ljava/lang/Object; result   (line 447)
                    ILOAD 6     // I i
                    ALOAD 8     // Ljava/lang/Object; value
                    INVOKESTATIC java.lang.reflect.Array.set (Ljava/lang/Object;ILjava/lang/Object;)V
                    IINC 6 1     // I i   (line 444)
                L1: ALOAD 7     // Ljava/util/Iterator; it
                    INVOKEINTERFACE java.util.Iterator.hasNext ()Z
                    IFNE L0
                    ALOAD 5     // Ljava/lang/Object; result   (line 449)
                    ARETURN
                L2: ALOAD_1     // Ljava/lang/Object; input   (line 451)
                    INVOKEVIRTUAL java.lang.Object.getClass ()Ljava/lang/Class;
                    INVOKEVIRTUAL java.lang.Class.isArray ()Z
                    IFEQ L6
                    ALOAD_3     // Ljava/lang/Class; componentType   (line 453)
                    ALOAD_1     // Ljava/lang/Object; input
                    INVOKEVIRTUAL java.lang.Object.getClass ()Ljava/lang/Class;
                    INVOKEVIRTUAL java.lang.Class.getComponentType ()Ljava/lang/Class;
                    INVOKEVIRTUAL java.lang.Object.equals (Ljava/lang/Object;)Z
                    IFEQ L3
                    ALOAD_0     // Lorg/springframework/beans/TypeConverterDelegate; this   (line 454)
                    GETFIELD org.springframework.beans.TypeConverterDelegate.propertyEditorRegistry Lorg/springframework/beans/PropertyEditorRegistrySupport;
                    ALOAD_3     // Ljava/lang/Class; componentType
                    ALOAD_2     // Ljava/lang/String; propertyName
                    INVOKEVIRTUAL org.springframework.beans.PropertyEditorRegistrySupport.hasCustomEditorForElement (Ljava/lang/Class;Ljava/lang/String;)Z
                    IFNE L3
                    ALOAD_1     // Ljava/lang/Object; input   (line 455)
                    ARETURN
                L3: ALOAD_1     // Ljava/lang/Object; input   (line 457)
                    INVOKESTATIC java.lang.reflect.Array.getLength (Ljava/lang/Object;)I
                    ISTORE 4
                    ALOAD_3     // Ljava/lang/Class; componentType   (line 458)
                    ILOAD 4     // I arrayLength
                    INVOKESTATIC java.lang.reflect.Array.newInstance (Ljava/lang/Class;I)Ljava/lang/Object;
                    ASTORE 5
                    ICONST_0   (line 459)
                    ISTORE 6
                    GOTO L5
                L4: ALOAD_0     // Lorg/springframework/beans/TypeConverterDelegate; this   (line 460)
                    ALOAD_0     // Lorg/springframework/beans/TypeConverterDelegate; this   (line 461)
                    ALOAD_2     // Ljava/lang/String; propertyName
                    ILOAD 6     // I i
                    INVOKESPECIAL org.springframework.beans.TypeConverterDelegate.buildIndexedPropertyName (Ljava/lang/String;I)Ljava/lang/String;
                    ACONST_NULL
                    ALOAD_1     // Ljava/lang/Object; input
                    ILOAD 6     // I i
                    INVOKESTATIC java.lang.reflect.Array.get (Ljava/lang/Object;I)Ljava/lang/Object;
                    ALOAD_3     // Ljava/lang/Class; componentType
                    INVOKEVIRTUAL org.springframework.beans.TypeConverterDelegate.convertIfNecessary (Ljava/lang/String;Ljava/lang/Object;Ljava/lang/Object;Ljava/lang/Class;)Ljava/lang/Object;   (line 460)
                    ASTORE 7
                    ALOAD 5     // Ljava/lang/Object; result   (line 462)
                    ILOAD 6     // I i
                    ALOAD 7     // Ljava/lang/Object; value
                    INVOKESTATIC java.lang.reflect.Array.set (Ljava/lang/Object;ILjava/lang/Object;)V
                    IINC 6 1     // I i   (line 459)
                L5: ILOAD 6     // I i
                    ILOAD 4     // I arrayLength
                    IF_ICMPLT L4
                    ALOAD 5     // Ljava/lang/Object; result   (line 464)
                    ARETURN
                L6: ALOAD_3     // Ljava/lang/Class; componentType   (line 468)
                    ICONST_1
                    INVOKESTATIC java.lang.reflect.Array.newInstance (Ljava/lang/Class;I)Ljava/lang/Object;
                    ASTORE 4
                    ALOAD_0     // Lorg/springframework/beans/TypeConverterDelegate; this   (line 469)
                    ALOAD_0     // Lorg/springframework/beans/TypeConverterDelegate; this   (line 470)
                    ALOAD_2     // Ljava/lang/String; propertyName
                    ICONST_0
                    INVOKESPECIAL org.springframework.beans.TypeConverterDelegate.buildIndexedPropertyName (Ljava/lang/String;I)Ljava/lang/String;
                    ACONST_NULL
                    ALOAD_1     // Ljava/lang/Object; input
                    ALOAD_3     // Ljava/lang/Class; componentType
                    INVOKEVIRTUAL org.springframework.beans.TypeConverterDelegate.convertIfNecessary (Ljava/lang/String;Ljava/lang/Object;Ljava/lang/Object;Ljava/lang/Class;)Ljava/lang/Object;   (line 469)
                    ASTORE 5
                    ALOAD 4     // Ljava/lang/Object; result   (line 471)
                    ICONST_0
                    ALOAD 5     // Ljava/lang/Object; value
                    INVOKESTATIC java.lang.reflect.Array.set (Ljava/lang/Object;ILjava/lang/Object;)V
                    ALOAD 4     // Ljava/lang/Object; result   (line 472)
                    ARETURN
  end protected Object convertToTypedArray(Object, String, Class)

  protected java.util.Collection convertToTypedCollection(java.util.Collection, String, Class, org.springframework.core.convert.TypeDescriptor):
                    LDC java.util.Collection   (line 480)
                    ALOAD_3     // Ljava/lang/Class; requiredType
                    INVOKEVIRTUAL java.lang.Class.isAssignableFrom (Ljava/lang/Class;)Z
                    IFNE L0
                    ALOAD_1     // Ljava/util/Collection; original   (line 481)
                    ARETURN
                L0: ALOAD_3     // Ljava/lang/Class; requiredType   (line 484)
                    INVOKESTATIC org.springframework.core.CollectionFactory.isApproximableCollectionType (Ljava/lang/Class;)Z
                    ISTORE 5
                    ILOAD 5     // Z approximable   (line 485)
                    IFNE L2
                    ALOAD_0     // Lorg/springframework/beans/TypeConverterDelegate; this
                    ALOAD_3     // Ljava/lang/Class; requiredType
                    INVOKESPECIAL org.springframework.beans.TypeConverterDelegate.canCreateCopy (Ljava/lang/Class;)Z
                    IFNE L2
                    GETSTATIC org.springframework.beans.TypeConverterDelegate.logger Lorg/apache/commons/logging/Log;   (line 486)
                    INVOKEINTERFACE org.apache.commons.logging.Log.isDebugEnabled ()Z
                    IFEQ L1
                    GETSTATIC org.springframework.beans.TypeConverterDelegate.logger Lorg/apache/commons/logging/Log;   (line 487)
                    NEW java.lang.StringBuilder
                    DUP
                    LDC_W "Custom Collection type ["
                    INVOKESPECIAL java.lang.StringBuilder.<init> (Ljava/lang/String;)V
                    ALOAD_1     // Ljava/util/Collection; original
                    INVOKEVIRTUAL java.lang.Object.getClass ()Ljava/lang/Class;
                    INVOKEVIRTUAL java.lang.Class.getName ()Ljava/lang/String;
                    INVOKEVIRTUAL java.lang.StringBuilder.append (Ljava/lang/String;)Ljava/lang/StringBuilder;
                    LDC_W "] does not allow for creating a copy - injecting original Collection as-is"   (line 488)
                    INVOKEVIRTUAL java.lang.StringBuilder.append (Ljava/lang/String;)Ljava/lang/StringBuilder;
                    INVOKEVIRTUAL java.lang.StringBuilder.toString ()Ljava/lang/String;
                    INVOKEINTERFACE org.apache.commons.logging.Log.debug (Ljava/lang/Object;)V   (line 487)
                L1: ALOAD_1     // Ljava/util/Collection; original   (line 490)
                    ARETURN
                L2: ALOAD_3     // Ljava/lang/Class; requiredType   (line 493)
                    ALOAD_1     // Ljava/util/Collection; original
                    INVOKEVIRTUAL java.lang.Class.isInstance (Ljava/lang/Object;)Z
                    ISTORE 6
                    ALOAD 4     // Lorg/springframework/core/convert/TypeDescriptor; typeDescriptor   (line 494)
                    ALOAD_1     // Ljava/util/Collection; original
                    INVOKEVIRTUAL org.springframework.core.convert.TypeDescriptor.narrow (Ljava/lang/Object;)Lorg/springframework/core/convert/TypeDescriptor;
                    ASTORE 4     // Lorg/springframework/core/convert/TypeDescriptor; typeDescriptor
                    ALOAD 4     // Lorg/springframework/core/convert/TypeDescriptor; typeDescriptor   (line 495)
                    INVOKEVIRTUAL org.springframework.core.convert.TypeDescriptor.getElementTypeDescriptor ()Lorg/springframework/core/convert/TypeDescriptor;
                    ASTORE 7
                    ALOAD 7     // Lorg/springframework/core/convert/TypeDescriptor; elementType   (line 496)
                    IFNONNULL L3
                    ILOAD 6     // Z originalAllowed
                    IFEQ L3
                    ALOAD_0     // Lorg/springframework/beans/TypeConverterDelegate; this   (line 497)
                    GETFIELD org.springframework.beans.TypeConverterDelegate.propertyEditorRegistry Lorg/springframework/beans/PropertyEditorRegistrySupport;
                    ACONST_NULL
                    ALOAD_2     // Ljava/lang/String; propertyName
                    INVOKEVIRTUAL org.springframework.beans.PropertyEditorRegistrySupport.hasCustomEditorForElement (Ljava/lang/Class;Ljava/lang/String;)Z
                    IFNE L3
                    ALOAD_1     // Ljava/util/Collection; original   (line 498)
                    ARETURN
    catch java.lang.Throwable -> E0
    |           L3: ALOAD_1     // Ljava/util/Collection; original   (line 503)
    |               INVOKEINTERFACE java.util.Collection.iterator ()Ljava/util/Iterator;
    |               ASTORE 8
    |               ALOAD 8     // Ljava/util/Iterator; it   (line 504)
    |               IFNONNULL L6
    |               GETSTATIC org.springframework.beans.TypeConverterDelegate.logger Lorg/apache/commons/logging/Log;   (line 505)
    |               INVOKEINTERFACE org.apache.commons.logging.Log.isDebugEnabled ()Z
    |               IFEQ L4
    |               GETSTATIC org.springframework.beans.TypeConverterDelegate.logger Lorg/apache/commons/logging/Log;   (line 506)
    |               NEW java.lang.StringBuilder
    |               DUP
    |               LDC_W "Collection of type ["
    |               INVOKESPECIAL java.lang.StringBuilder.<init> (Ljava/lang/String;)V
    |               ALOAD_1     // Ljava/util/Collection; original
    |               INVOKEVIRTUAL java.lang.Object.getClass ()Ljava/lang/Class;
    |               INVOKEVIRTUAL java.lang.Class.getName ()Ljava/lang/String;
    |               INVOKEVIRTUAL java.lang.StringBuilder.append (Ljava/lang/String;)Ljava/lang/StringBuilder;
    |               LDC_W "] returned null Iterator - injecting original Collection as-is"   (line 507)
    |               INVOKEVIRTUAL java.lang.StringBuilder.append (Ljava/lang/String;)Ljava/lang/StringBuilder;
    |               INVOKEVIRTUAL java.lang.StringBuilder.toString ()Ljava/lang/String;
    |               INVOKEINTERFACE org.apache.commons.logging.Log.debug (Ljava/lang/Object;)V   (line 506)
    |           L4: ALOAD_1     // Ljava/util/Collection; original   (line 509)
    catch java.lang.Throwable -> E0
                    ARETURN
                E0: ASTORE 9   (line 512)
                    GETSTATIC org.springframework.beans.TypeConverterDelegate.logger Lorg/apache/commons/logging/Log;   (line 513)
                    INVOKEINTERFACE org.apache.commons.logging.Log.isDebugEnabled ()Z
                    IFEQ L5
                    GETSTATIC org.springframework.beans.TypeConverterDelegate.logger Lorg/apache/commons/logging/Log;   (line 514)
                    NEW java.lang.StringBuilder
                    DUP
                    LDC_W "Cannot access Collection of type ["
                    INVOKESPECIAL java.lang.StringBuilder.<init> (Ljava/lang/String;)V
                    ALOAD_1     // Ljava/util/Collection; original
                    INVOKEVIRTUAL java.lang.Object.getClass ()Ljava/lang/Class;
                    INVOKEVIRTUAL java.lang.Class.getName ()Ljava/lang/String;
                    INVOKEVIRTUAL java.lang.StringBuilder.append (Ljava/lang/String;)Ljava/lang/StringBuilder;
                    LDC_W "] - injecting original Collection as-is: "   (line 515)
                    INVOKEVIRTUAL java.lang.StringBuilder.append (Ljava/lang/String;)Ljava/lang/StringBuilder;
                    ALOAD 9     // Ljava/lang/Throwable; ex
                    INVOKEVIRTUAL java.lang.StringBuilder.append (Ljava/lang/Object;)Ljava/lang/StringBuilder;
                    INVOKEVIRTUAL java.lang.StringBuilder.toString ()Ljava/lang/String;
                    INVOKEINTERFACE org.apache.commons.logging.Log.debug (Ljava/lang/Object;)V   (line 514)
                L5: ALOAD_1     // Ljava/util/Collection; original   (line 517)
                    ARETURN
    catch java.lang.Throwable -> E1
    |           L6: ILOAD 5     // Z approximable   (line 522)
    |               IFEQ L7
    |               ALOAD_1     // Ljava/util/Collection; original   (line 523)
    |               ALOAD_1     // Ljava/util/Collection; original
    |               INVOKEINTERFACE java.util.Collection.size ()I
    |               INVOKESTATIC org.springframework.core.CollectionFactory.createApproximateCollection (Ljava/lang/Object;I)Ljava/util/Collection;
    |               ASTORE 9
    |               GOTO L9
    |           L7: ALOAD_3     // Ljava/lang/Class; requiredType   (line 526)
    |               INVOKEVIRTUAL java.lang.Class.newInstance ()Ljava/lang/Object;
    |               CHECKCAST java.util.Collection
    |               ASTORE 9
    catch java.lang.Throwable -> E1
                    GOTO L9
                E1: ASTORE 10   (line 529)
                    GETSTATIC org.springframework.beans.TypeConverterDelegate.logger Lorg/apache/commons/logging/Log;   (line 530)
                    INVOKEINTERFACE org.apache.commons.logging.Log.isDebugEnabled ()Z
                    IFEQ L8
                    GETSTATIC org.springframework.beans.TypeConverterDelegate.logger Lorg/apache/commons/logging/Log;   (line 531)
                    NEW java.lang.StringBuilder
                    DUP
                    LDC_W "Cannot create copy of Collection type ["
                    INVOKESPECIAL java.lang.StringBuilder.<init> (Ljava/lang/String;)V
                    ALOAD_1     // Ljava/util/Collection; original
                    INVOKEVIRTUAL java.lang.Object.getClass ()Ljava/lang/Class;
                    INVOKEVIRTUAL java.lang.Class.getName ()Ljava/lang/String;
                    INVOKEVIRTUAL java.lang.StringBuilder.append (Ljava/lang/String;)Ljava/lang/StringBuilder;
                    LDC_W "] - injecting original Collection as-is: "   (line 532)
                    INVOKEVIRTUAL java.lang.StringBuilder.append (Ljava/lang/String;)Ljava/lang/StringBuilder;
                    ALOAD 10     // Ljava/lang/Throwable; ex
                    INVOKEVIRTUAL java.lang.StringBuilder.append (Ljava/lang/Object;)Ljava/lang/StringBuilder;
                    INVOKEVIRTUAL java.lang.StringBuilder.toString ()Ljava/lang/String;
                    INVOKEINTERFACE org.apache.commons.logging.Log.debug (Ljava/lang/Object;)V   (line 531)
                L8: ALOAD_1     // Ljava/util/Collection; original   (line 534)
                    ARETURN
                L9: ICONST_0   (line 537)
                    ISTORE 10
                    GOTO L17   (line 538)
               L10: ALOAD 8     // Ljava/util/Iterator; it   (line 539)
                    INVOKEINTERFACE java.util.Iterator.next ()Ljava/lang/Object;
                    ASTORE 11
                    ALOAD_0     // Lorg/springframework/beans/TypeConverterDelegate; this   (line 540)
                    ALOAD_2     // Ljava/lang/String; propertyName
                    ILOAD 10     // I i
                    INVOKESPECIAL org.springframework.beans.TypeConverterDelegate.buildIndexedPropertyName (Ljava/lang/String;I)Ljava/lang/String;
                    ASTORE 12
                    ALOAD_0     // Lorg/springframework/beans/TypeConverterDelegate; this   (line 541)
                    ALOAD 12     // Ljava/lang/String; indexedPropertyName
                    ACONST_NULL
                    ALOAD 11     // Ljava/lang/Object; element
                    ALOAD 7     // Lorg/springframework/core/convert/TypeDescriptor; elementType   (line 542)
                    IFNULL L11
                    ALOAD 7     // Lorg/springframework/core/convert/TypeDescriptor; elementType
                    INVOKEVIRTUAL org.springframework.core.convert.TypeDescriptor.getType ()Ljava/lang/Class;
                    GOTO L12
               L11: ACONST_NULL
               L12: ALOAD 7     // Lorg/springframework/core/convert/TypeDescriptor; elementType
                    INVOKEVIRTUAL org.springframework.beans.TypeConverterDelegate.convertIfNecessary (Ljava/lang/String;Ljava/lang/Object;Ljava/lang/Object;Ljava/lang/Class;Lorg/springframework/core/convert/TypeDescriptor;)Ljava/lang/Object;   (line 541)
                    ASTORE 13
    catch java.lang.Throwable -> E2
    |               ALOAD 9     // Ljava/util/Collection; convertedCopy   (line 544)
    |               ALOAD 13     // Ljava/lang/Object; convertedElement
    |               INVOKEINTERFACE java.util.Collection.add (Ljava/lang/Object;)Z
    |               POP
    catch java.lang.Throwable -> E2
                    GOTO L14
                E2: ASTORE 14   (line 546)
                    GETSTATIC org.springframework.beans.TypeConverterDelegate.logger Lorg/apache/commons/logging/Log;   (line 547)
                    INVOKEINTERFACE org.apache.commons.logging.Log.isDebugEnabled ()Z
                    IFEQ L13
                    GETSTATIC org.springframework.beans.TypeConverterDelegate.logger Lorg/apache/commons/logging/Log;   (line 548)
                    NEW java.lang.StringBuilder
                    DUP
                    LDC_W "Collection type ["
                    INVOKESPECIAL java.lang.StringBuilder.<init> (Ljava/lang/String;)V
                    ALOAD_1     // Ljava/util/Collection; original
                    INVOKEVIRTUAL java.lang.Object.getClass ()Ljava/lang/Class;
                    INVOKEVIRTUAL java.lang.Class.getName ()Ljava/lang/String;
                    INVOKEVIRTUAL java.lang.StringBuilder.append (Ljava/lang/String;)Ljava/lang/StringBuilder;
                    LDC_W "] seems to be read-only - injecting original Collection as-is: "   (line 549)
                    INVOKEVIRTUAL java.lang.StringBuilder.append (Ljava/lang/String;)Ljava/lang/StringBuilder;
                    ALOAD 14     // Ljava/lang/Throwable; ex
                    INVOKEVIRTUAL java.lang.StringBuilder.append (Ljava/lang/Object;)Ljava/lang/StringBuilder;
                    INVOKEVIRTUAL java.lang.StringBuilder.toString ()Ljava/lang/String;
                    INVOKEINTERFACE org.apache.commons.logging.Log.debug (Ljava/lang/Object;)V   (line 548)
               L13: ALOAD_1     // Ljava/util/Collection; original   (line 551)
                    ARETURN
               L14: ILOAD 6     // Z originalAllowed   (line 553)
                    IFEQ L15
                    ALOAD 11     // Ljava/lang/Object; element
                    ALOAD 13     // Ljava/lang/Object; convertedElement
                    IF_ACMPNE L15
                    ICONST_1
                    GOTO L16
               L15: ICONST_0
               L16: ISTORE 6     // Z originalAllowed
                    IINC 10 1     // I i   (line 538)
               L17: ALOAD 8     // Ljava/util/Iterator; it
                    INVOKEINTERFACE java.util.Iterator.hasNext ()Z
                    IFNE L10
                    ILOAD 6     // Z originalAllowed   (line 555)
                    IFEQ L18
                    ALOAD_1     // Ljava/util/Collection; original
                    GOTO L19
               L18: ALOAD 9     // Ljava/util/Collection; convertedCopy
               L19: ARETURN
  end protected java.util.Collection convertToTypedCollection(java.util.Collection, String, Class, org.springframework.core.convert.TypeDescriptor)

  protected java.util.Map convertToTypedMap(java.util.Map, String, Class, org.springframework.core.convert.TypeDescriptor):
                    LDC java.util.Map   (line 562)
                    ALOAD_3     // Ljava/lang/Class; requiredType
                    INVOKEVIRTUAL java.lang.Class.isAssignableFrom (Ljava/lang/Class;)Z
                    IFNE L0
                    ALOAD_1     // Ljava/util/Map; original   (line 563)
                    ARETURN
                L0: ALOAD_3     // Ljava/lang/Class; requiredType   (line 566)
                    INVOKESTATIC org.springframework.core.CollectionFactory.isApproximableMapType (Ljava/lang/Class;)Z
                    ISTORE 5
                    ILOAD 5     // Z approximable   (line 567)
                    IFNE L2
                    ALOAD_0     // Lorg/springframework/beans/TypeConverterDelegate; this
                    ALOAD_3     // Ljava/lang/Class; requiredType
                    INVOKESPECIAL org.springframework.beans.TypeConverterDelegate.canCreateCopy (Ljava/lang/Class;)Z
                    IFNE L2
                    GETSTATIC org.springframework.beans.TypeConverterDelegate.logger Lorg/apache/commons/logging/Log;   (line 568)
                    INVOKEINTERFACE org.apache.commons.logging.Log.isDebugEnabled ()Z
                    IFEQ L1
                    GETSTATIC org.springframework.beans.TypeConverterDelegate.logger Lorg/apache/commons/logging/Log;   (line 569)
                    NEW java.lang.StringBuilder
                    DUP
                    LDC_W "Custom Map type ["
                    INVOKESPECIAL java.lang.StringBuilder.<init> (Ljava/lang/String;)V
                    ALOAD_1     // Ljava/util/Map; original
                    INVOKEVIRTUAL java.lang.Object.getClass ()Ljava/lang/Class;
                    INVOKEVIRTUAL java.lang.Class.getName ()Ljava/lang/String;
                    INVOKEVIRTUAL java.lang.StringBuilder.append (Ljava/lang/String;)Ljava/lang/StringBuilder;
                    LDC_W "] does not allow for creating a copy - injecting original Map as-is"   (line 570)
                    INVOKEVIRTUAL java.lang.StringBuilder.append (Ljava/lang/String;)Ljava/lang/StringBuilder;
                    INVOKEVIRTUAL java.lang.StringBuilder.toString ()Ljava/lang/String;
                    INVOKEINTERFACE org.apache.commons.logging.Log.debug (Ljava/lang/Object;)V   (line 569)
                L1: ALOAD_1     // Ljava/util/Map; original   (line 572)
                    ARETURN
                L2: ALOAD_3     // Ljava/lang/Class; requiredType   (line 575)
                    ALOAD_1     // Ljava/util/Map; original
                    INVOKEVIRTUAL java.lang.Class.isInstance (Ljava/lang/Object;)Z
                    ISTORE 6
                    ALOAD 4     // Lorg/springframework/core/convert/TypeDescriptor; typeDescriptor   (line 576)
                    ALOAD_1     // Ljava/util/Map; original
                    INVOKEVIRTUAL org.springframework.core.convert.TypeDescriptor.narrow (Ljava/lang/Object;)Lorg/springframework/core/convert/TypeDescriptor;
                    ASTORE 4     // Lorg/springframework/core/convert/TypeDescriptor; typeDescriptor
                    ALOAD 4     // Lorg/springframework/core/convert/TypeDescriptor; typeDescriptor   (line 577)
                    INVOKEVIRTUAL org.springframework.core.convert.TypeDescriptor.getMapKeyTypeDescriptor ()Lorg/springframework/core/convert/TypeDescriptor;
                    ASTORE 7
                    ALOAD 4     // Lorg/springframework/core/convert/TypeDescriptor; typeDescriptor   (line 578)
                    INVOKEVIRTUAL org.springframework.core.convert.TypeDescriptor.getMapValueTypeDescriptor ()Lorg/springframework/core/convert/TypeDescriptor;
                    ASTORE 8
                    ALOAD 7     // Lorg/springframework/core/convert/TypeDescriptor; keyType   (line 579)
                    IFNONNULL L3
                    ALOAD 8     // Lorg/springframework/core/convert/TypeDescriptor; valueType
                    IFNONNULL L3
                    ILOAD 6     // Z originalAllowed
                    IFEQ L3
                    ALOAD_0     // Lorg/springframework/beans/TypeConverterDelegate; this   (line 580)
                    GETFIELD org.springframework.beans.TypeConverterDelegate.propertyEditorRegistry Lorg/springframework/beans/PropertyEditorRegistrySupport;
                    ACONST_NULL
                    ALOAD_2     // Ljava/lang/String; propertyName
                    INVOKEVIRTUAL org.springframework.beans.PropertyEditorRegistrySupport.hasCustomEditorForElement (Ljava/lang/Class;Ljava/lang/String;)Z
                    IFNE L3
                    ALOAD_1     // Ljava/util/Map; original   (line 581)
                    ARETURN
    catch java.lang.Throwable -> E0
    |           L3: ALOAD_1     // Ljava/util/Map; original   (line 586)
    |               INVOKEINTERFACE java.util.Map.entrySet ()Ljava/util/Set;
    |               INVOKEINTERFACE java.util.Set.iterator ()Ljava/util/Iterator;
    |               ASTORE 9
    |               ALOAD 9     // Ljava/util/Iterator; it   (line 587)
    |               IFNONNULL L6
    |               GETSTATIC org.springframework.beans.TypeConverterDelegate.logger Lorg/apache/commons/logging/Log;   (line 588)
    |               INVOKEINTERFACE org.apache.commons.logging.Log.isDebugEnabled ()Z
    |               IFEQ L4
    |               GETSTATIC org.springframework.beans.TypeConverterDelegate.logger Lorg/apache/commons/logging/Log;   (line 589)
    |               NEW java.lang.StringBuilder
    |               DUP
    |               LDC_W "Map of type ["
    |               INVOKESPECIAL java.lang.StringBuilder.<init> (Ljava/lang/String;)V
    |               ALOAD_1     // Ljava/util/Map; original
    |               INVOKEVIRTUAL java.lang.Object.getClass ()Ljava/lang/Class;
    |               INVOKEVIRTUAL java.lang.Class.getName ()Ljava/lang/String;
    |               INVOKEVIRTUAL java.lang.StringBuilder.append (Ljava/lang/String;)Ljava/lang/StringBuilder;
    |               LDC_W "] returned null Iterator - injecting original Map as-is"   (line 590)
    |               INVOKEVIRTUAL java.lang.StringBuilder.append (Ljava/lang/String;)Ljava/lang/StringBuilder;
    |               INVOKEVIRTUAL java.lang.StringBuilder.toString ()Ljava/lang/String;
    |               INVOKEINTERFACE org.apache.commons.logging.Log.debug (Ljava/lang/Object;)V   (line 589)
    |           L4: ALOAD_1     // Ljava/util/Map; original   (line 592)
    catch java.lang.Throwable -> E0
                    ARETURN
                E0: ASTORE 10   (line 595)
                    GETSTATIC org.springframework.beans.TypeConverterDelegate.logger Lorg/apache/commons/logging/Log;   (line 596)
                    INVOKEINTERFACE org.apache.commons.logging.Log.isDebugEnabled ()Z
                    IFEQ L5
                    GETSTATIC org.springframework.beans.TypeConverterDelegate.logger Lorg/apache/commons/logging/Log;   (line 597)
                    NEW java.lang.StringBuilder
                    DUP
                    LDC_W "Cannot access Map of type ["
                    INVOKESPECIAL java.lang.StringBuilder.<init> (Ljava/lang/String;)V
                    ALOAD_1     // Ljava/util/Map; original
                    INVOKEVIRTUAL java.lang.Object.getClass ()Ljava/lang/Class;
                    INVOKEVIRTUAL java.lang.Class.getName ()Ljava/lang/String;
                    INVOKEVIRTUAL java.lang.StringBuilder.append (Ljava/lang/String;)Ljava/lang/StringBuilder;
                    LDC_W "] - injecting original Map as-is: "   (line 598)
                    INVOKEVIRTUAL java.lang.StringBuilder.append (Ljava/lang/String;)Ljava/lang/StringBuilder;
                    ALOAD 10     // Ljava/lang/Throwable; ex
                    INVOKEVIRTUAL java.lang.StringBuilder.append (Ljava/lang/Object;)Ljava/lang/StringBuilder;
                    INVOKEVIRTUAL java.lang.StringBuilder.toString ()Ljava/lang/String;
                    INVOKEINTERFACE org.apache.commons.logging.Log.debug (Ljava/lang/Object;)V   (line 597)
                L5: ALOAD_1     // Ljava/util/Map; original   (line 600)
                    ARETURN
    catch java.lang.Throwable -> E1
    |           L6: ILOAD 5     // Z approximable   (line 605)
    |               IFEQ L7
    |               ALOAD_1     // Ljava/util/Map; original   (line 606)
    |               ALOAD_1     // Ljava/util/Map; original
    |               INVOKEINTERFACE java.util.Map.size ()I
    |               INVOKESTATIC org.springframework.core.CollectionFactory.createApproximateMap (Ljava/lang/Object;I)Ljava/util/Map;
    |               ASTORE 10
    |               GOTO L18
    |           L7: ALOAD_3     // Ljava/lang/Class; requiredType   (line 609)
    |               INVOKEVIRTUAL java.lang.Class.newInstance ()Ljava/lang/Object;
    |               CHECKCAST java.util.Map
    |               ASTORE 10
    catch java.lang.Throwable -> E1
                    GOTO L18
                E1: ASTORE 11   (line 612)
                    GETSTATIC org.springframework.beans.TypeConverterDelegate.logger Lorg/apache/commons/logging/Log;   (line 613)
                    INVOKEINTERFACE org.apache.commons.logging.Log.isDebugEnabled ()Z
                    IFEQ L8
                    GETSTATIC org.springframework.beans.TypeConverterDelegate.logger Lorg/apache/commons/logging/Log;   (line 614)
                    NEW java.lang.StringBuilder
                    DUP
                    LDC_W "Cannot create copy of Map type ["
                    INVOKESPECIAL java.lang.StringBuilder.<init> (Ljava/lang/String;)V
                    ALOAD_1     // Ljava/util/Map; original
                    INVOKEVIRTUAL java.lang.Object.getClass ()Ljava/lang/Class;
                    INVOKEVIRTUAL java.lang.Class.getName ()Ljava/lang/String;
                    INVOKEVIRTUAL java.lang.StringBuilder.append (Ljava/lang/String;)Ljava/lang/StringBuilder;
                    LDC_W "] - injecting original Map as-is: "   (line 615)
                    INVOKEVIRTUAL java.lang.StringBuilder.append (Ljava/lang/String;)Ljava/lang/StringBuilder;
                    ALOAD 11     // Ljava/lang/Throwable; ex
                    INVOKEVIRTUAL java.lang.StringBuilder.append (Ljava/lang/Object;)Ljava/lang/StringBuilder;
                    INVOKEVIRTUAL java.lang.StringBuilder.toString ()Ljava/lang/String;
                    INVOKEINTERFACE org.apache.commons.logging.Log.debug (Ljava/lang/Object;)V   (line 614)
                L8: ALOAD_1     // Ljava/util/Map; original   (line 617)
                    ARETURN
                L9: ALOAD 9     // Ljava/util/Iterator; it   (line 621)
                    INVOKEINTERFACE java.util.Iterator.next ()Ljava/lang/Object;
                    CHECKCAST java.util.Map$Entry
                    ASTORE 11
                    ALOAD 11     // Ljava/util/Map$Entry; entry   (line 622)
                    INVOKEINTERFACE java.util.Map$Entry.getKey ()Ljava/lang/Object;
                    ASTORE 12
                    ALOAD 11     // Ljava/util/Map$Entry; entry   (line 623)
                    INVOKEINTERFACE java.util.Map$Entry.getValue ()Ljava/lang/Object;
                    ASTORE 13
                    ALOAD_0     // Lorg/springframework/beans/TypeConverterDelegate; this   (line 624)
                    ALOAD_2     // Ljava/lang/String; propertyName
                    ALOAD 12     // Ljava/lang/Object; key
                    INVOKESPECIAL org.springframework.beans.TypeConverterDelegate.buildKeyedPropertyName (Ljava/lang/String;Ljava/lang/Object;)Ljava/lang/String;
                    ASTORE 14
                    ALOAD_0     // Lorg/springframework/beans/TypeConverterDelegate; this   (line 625)
                    ALOAD 14     // Ljava/lang/String; keyedPropertyName
                    ACONST_NULL
                    ALOAD 12     // Ljava/lang/Object; key
                    ALOAD 7     // Lorg/springframework/core/convert/TypeDescriptor; keyType   (line 626)
                    IFNULL L10
                    ALOAD 7     // Lorg/springframework/core/convert/TypeDescriptor; keyType
                    INVOKEVIRTUAL org.springframework.core.convert.TypeDescriptor.getType ()Ljava/lang/Class;
                    GOTO L11
               L10: ACONST_NULL
               L11: ALOAD 7     // Lorg/springframework/core/convert/TypeDescriptor; keyType
                    INVOKEVIRTUAL org.springframework.beans.TypeConverterDelegate.convertIfNecessary (Ljava/lang/String;Ljava/lang/Object;Ljava/lang/Object;Ljava/lang/Class;Lorg/springframework/core/convert/TypeDescriptor;)Ljava/lang/Object;   (line 625)
                    ASTORE 15
                    ALOAD_0     // Lorg/springframework/beans/TypeConverterDelegate; this   (line 627)
                    ALOAD 14     // Ljava/lang/String; keyedPropertyName
                    ACONST_NULL
                    ALOAD 13     // Ljava/lang/Object; value
                    ALOAD 8     // Lorg/springframework/core/convert/TypeDescriptor; valueType   (line 628)
                    IFNULL L12
                    ALOAD 8     // Lorg/springframework/core/convert/TypeDescriptor; valueType
                    INVOKEVIRTUAL org.springframework.core.convert.TypeDescriptor.getType ()Ljava/lang/Class;
                    GOTO L13
               L12: ACONST_NULL
               L13: ALOAD 8     // Lorg/springframework/core/convert/TypeDescriptor; valueType
                    INVOKEVIRTUAL org.springframework.beans.TypeConverterDelegate.convertIfNecessary (Ljava/lang/String;Ljava/lang/Object;Ljava/lang/Object;Ljava/lang/Class;Lorg/springframework/core/convert/TypeDescriptor;)Ljava/lang/Object;   (line 627)
                    ASTORE 16
    catch java.lang.Throwable -> E2
    |               ALOAD 10     // Ljava/util/Map; convertedCopy   (line 630)
    |               ALOAD 15     // Ljava/lang/Object; convertedKey
    |               ALOAD 16     // Ljava/lang/Object; convertedValue
    |               INVOKEINTERFACE java.util.Map.put (Ljava/lang/Object;Ljava/lang/Object;)Ljava/lang/Object;
    |               POP
    catch java.lang.Throwable -> E2
                    GOTO L15
                E2: ASTORE 17   (line 632)
                    GETSTATIC org.springframework.beans.TypeConverterDelegate.logger Lorg/apache/commons/logging/Log;   (line 633)
                    INVOKEINTERFACE org.apache.commons.logging.Log.isDebugEnabled ()Z
                    IFEQ L14
                    GETSTATIC org.springframework.beans.TypeConverterDelegate.logger Lorg/apache/commons/logging/Log;   (line 634)
                    NEW java.lang.StringBuilder
                    DUP
                    LDC_W "Map type ["
                    INVOKESPECIAL java.lang.StringBuilder.<init> (Ljava/lang/String;)V
                    ALOAD_1     // Ljava/util/Map; original
                    INVOKEVIRTUAL java.lang.Object.getClass ()Ljava/lang/Class;
                    INVOKEVIRTUAL java.lang.Class.getName ()Ljava/lang/String;
                    INVOKEVIRTUAL java.lang.StringBuilder.append (Ljava/lang/String;)Ljava/lang/StringBuilder;
                    LDC_W "] seems to be read-only - injecting original Map as-is: "   (line 635)
                    INVOKEVIRTUAL java.lang.StringBuilder.append (Ljava/lang/String;)Ljava/lang/StringBuilder;
                    ALOAD 17     // Ljava/lang/Throwable; ex
                    INVOKEVIRTUAL java.lang.StringBuilder.append (Ljava/lang/Object;)Ljava/lang/StringBuilder;
                    INVOKEVIRTUAL java.lang.StringBuilder.toString ()Ljava/lang/String;
                    INVOKEINTERFACE org.apache.commons.logging.Log.debug (Ljava/lang/Object;)V   (line 634)
               L14: ALOAD_1     // Ljava/util/Map; original   (line 637)
                    ARETURN
               L15: ILOAD 6     // Z originalAllowed   (line 639)
                    IFEQ L16
                    ALOAD 12     // Ljava/lang/Object; key
                    ALOAD 15     // Ljava/lang/Object; convertedKey
                    IF_ACMPNE L16
                    ALOAD 13     // Ljava/lang/Object; value
                    ALOAD 16     // Ljava/lang/Object; convertedValue
                    IF_ACMPNE L16
                    ICONST_1
                    GOTO L17
               L16: ICONST_0
               L17: ISTORE 6     // Z originalAllowed
               L18: ALOAD 9     // Ljava/util/Iterator; it   (line 620)
                    INVOKEINTERFACE java.util.Iterator.hasNext ()Z
                    IFNE L9
                    ILOAD 6     // Z originalAllowed   (line 641)
                    IFEQ L19
                    ALOAD_1     // Ljava/util/Map; original
                    GOTO L20
               L19: ALOAD 10     // Ljava/util/Map; convertedCopy
               L20: ARETURN
  end protected java.util.Map convertToTypedMap(java.util.Map, String, Class, org.springframework.core.convert.TypeDescriptor)

  private String buildIndexedPropertyName(String, int):
                    ALOAD_1     // Ljava/lang/String; propertyName   (line 645)
                    IFNULL L0
                    NEW java.lang.StringBuilder   (line 646)
                    DUP
                    ALOAD_1     // Ljava/lang/String; propertyName
                    INVOKESTATIC java.lang.String.valueOf (Ljava/lang/Object;)Ljava/lang/String;
                    INVOKESPECIAL java.lang.StringBuilder.<init> (Ljava/lang/String;)V
                    LDC_W "["
                    INVOKEVIRTUAL java.lang.StringBuilder.append (Ljava/lang/String;)Ljava/lang/StringBuilder;
                    ILOAD_2     // I index
                    INVOKEVIRTUAL java.lang.StringBuilder.append (I)Ljava/lang/StringBuilder;
                    LDC "]"
                    INVOKEVIRTUAL java.lang.StringBuilder.append (Ljava/lang/String;)Ljava/lang/StringBuilder;
                    INVOKEVIRTUAL java.lang.StringBuilder.toString ()Ljava/lang/String;
                    GOTO L1
                L0: ACONST_NULL   (line 647)
                L1: ARETURN   (line 645)
  end private String buildIndexedPropertyName(String, int)

  private String buildKeyedPropertyName(String, Object):
                    ALOAD_1     // Ljava/lang/String; propertyName   (line 651)
                    IFNULL L0
                    NEW java.lang.StringBuilder   (line 652)
                    DUP
                    ALOAD_1     // Ljava/lang/String; propertyName
                    INVOKESTATIC java.lang.String.valueOf (Ljava/lang/Object;)Ljava/lang/String;
                    INVOKESPECIAL java.lang.StringBuilder.<init> (Ljava/lang/String;)V
                    LDC_W "["
                    INVOKEVIRTUAL java.lang.StringBuilder.append (Ljava/lang/String;)Ljava/lang/StringBuilder;
                    ALOAD_2     // Ljava/lang/Object; key
                    INVOKEVIRTUAL java.lang.StringBuilder.append (Ljava/lang/Object;)Ljava/lang/StringBuilder;
                    LDC "]"
                    INVOKEVIRTUAL java.lang.StringBuilder.append (Ljava/lang/String;)Ljava/lang/StringBuilder;
                    INVOKEVIRTUAL java.lang.StringBuilder.toString ()Ljava/lang/String;
                    GOTO L1
                L0: ACONST_NULL   (line 653)
                L1: ARETURN   (line 651)
  end private String buildKeyedPropertyName(String, Object)

  private boolean canCreateCopy(Class):
                    ALOAD_1     // Ljava/lang/Class; requiredType   (line 657)
                    INVOKEVIRTUAL java.lang.Class.isInterface ()Z
                    IFNE L0
                    ALOAD_1     // Ljava/lang/Class; requiredType
                    INVOKEVIRTUAL java.lang.Class.getModifiers ()I
                    INVOKESTATIC java.lang.reflect.Modifier.isAbstract (I)Z
                    IFNE L0
                    ALOAD_1     // Ljava/lang/Class; requiredType   (line 658)
                    INVOKEVIRTUAL java.lang.Class.getModifiers ()I
                    INVOKESTATIC java.lang.reflect.Modifier.isPublic (I)Z
                    IFEQ L0
                    ALOAD_1     // Ljava/lang/Class; requiredType
                    ICONST_0
                    ANEWARRAY java.lang.Class
                    INVOKESTATIC org.springframework.util.ClassUtils.hasConstructor (Ljava/lang/Class;[Ljava/lang/Class;)Z
                    IFEQ L0
                    ICONST_1
                    IRETURN
                L0: ICONST_0
                    IRETURN   (line 657)
  end private boolean canCreateCopy(Class)
end  class org.springframework.beans.TypeConverterDelegate

	at org.aspectj.bridge.MessageWriter.handleMessage(MessageWriter.java:47)
	at org.aspectj.weaver.tools.WeavingAdaptor$WeavingAdaptorMessageWriter.handleMessage(WeavingAdaptor.java:665)
	at org.aspectj.weaver.tools.WeavingAdaptor$WeavingAdaptorMessageHolder.handleMessage(WeavingAdaptor.java:615)
	at org.aspectj.weaver.bcel.BcelWeaver.weave(BcelWeaver.java:1752)
	at org.aspectj.weaver.bcel.BcelWeaver.weaveWithoutDump(BcelWeaver.java:1694)
	at org.aspectj.weaver.bcel.BcelWeaver.weaveAndNotify(BcelWeaver.java:1464)
	at org.aspectj.weaver.bcel.BcelWeaver.weave(BcelWeaver.java:1273)
	at org.aspectj.weaver.tools.WeavingAdaptor.getWovenBytes(WeavingAdaptor.java:394)
	at org.aspectj.weaver.tools.WeavingAdaptor.weaveClass(WeavingAdaptor.java:281)
	at org.aspectj.weaver.loadtime.Aj.preProcess(Aj.java:95)
	at org.aspectj.weaver.loadtime.ClassPreProcessorAgentAdapter.transform(ClassPreProcessorAgentAdapter.java:52)
	at sun.instrument.TransformerManager.transform(TransformerManager.java:188)
	at sun.instrument.InstrumentationImpl.transform(InstrumentationImpl.java:428)
	at java.lang.ClassLoader.defineClass1(Native Method)
	at java.lang.ClassLoader.defineClass(ClassLoader.java:760)
	at java.security.SecureClassLoader.defineClass(SecureClassLoader.java:142)
	at java.net.URLClassLoader.defineClass(URLClassLoader.java:467)
	at java.net.URLClassLoader.access$100(URLClassLoader.java:73)
	at java.net.URLClassLoader$1.run(URLClassLoader.java:368)
	at java.net.URLClassLoader$1.run(URLClassLoader.java:362)
	at java.security.AccessController.doPrivileged(Native Method)
	at java.net.URLClassLoader.findClass(URLClassLoader.java:361)
	at java.lang.ClassLoader.loadClass(ClassLoader.java:424)
	at sun.misc.Launcher$AppClassLoader.loadClass(Launcher.java:331)
	at java.lang.ClassLoader.loadClass(ClassLoader.java:357)
	at org.springframework.beans.BeanWrapperImpl.setWrappedInstance(BeanWrapperImpl.java:221)
	at org.springframework.beans.BeanWrapperImpl.setWrappedInstance(BeanWrapperImpl.java:205)
	at org.springframework.beans.BeanWrapperImpl.<init>(BeanWrapperImpl.java:154)
	at org.springframework.beans.factory.support.AbstractAutowireCapableBeanFactory.instantiateBean(AbstractAutowireCapableBeanFactory.java:992)
	at org.springframework.beans.factory.support.AbstractAutowireCapableBeanFactory.createBeanInstance(AbstractAutowireCapableBeanFactory.java:943)
	at org.springframework.beans.factory.support.AbstractAutowireCapableBeanFactory.doCreateBean(AbstractAutowireCapableBeanFactory.java:485)
	at org.springframework.beans.factory.support.AbstractAutowireCapableBeanFactory.createBean(AbstractAutowireCapableBeanFactory.java:456)
	at org.springframework.beans.factory.support.AbstractBeanFactory$1.getObject(AbstractBeanFactory.java:294)
	at org.springframework.beans.factory.support.DefaultSingletonBeanRegistry.getSingleton(DefaultSingletonBeanRegistry.java:225)
	at org.springframework.beans.factory.support.AbstractBeanFactory.doGetBean(AbstractBeanFactory.java:291)
	at org.springframework.beans.factory.support.AbstractBeanFactory.getBean(AbstractBeanFactory.java:197)
	at org.springframework.context.support.AbstractApplicationContext.invokeBeanFactoryPostProcessors(AbstractApplicationContext.java:649)
	at org.springframework.context.support.AbstractApplicationContext.refresh(AbstractApplicationContext.java:451)
	at org.springframework.context.support.ClassPathXmlApplicationContext.<init>(ClassPathXmlApplicationContext.java:139)
	at org.springframework.context.support.ClassPathXmlApplicationContext.<init>(ClassPathXmlApplicationContext.java:83)
	at com.curso.spring.springioc0007.Main.init(Main.java:29)
	at com.curso.spring.springioc0007.Main.main(Main.java:24)
---- System Properties ---
java.runtime.name=Java(TM) SE Runtime Environment
sun.boot.library.path=C:\Program Files\Java\jdk1.8.0_72\jre\bin
java.vm.version=25.72-b15
java.vm.vendor=Oracle Corporation
java.vendor.url=http://java.oracle.com/
path.separator=;
java.vm.name=Java HotSpot(TM) 64-Bit Server VM
file.encoding.pkg=sun.io
user.country=ES
user.script=
sun.java.launcher=SUN_STANDARD
sun.os.patch.level=
java.vm.specification.name=Java Virtual Machine Specification
user.dir=C:\Users\usuario\git\spring\aspectos\Ejemplos Relacionados\SpringIoC0007Maven
java.runtime.version=1.8.0_72-b15
java.awt.graphicsenv=sun.awt.Win32GraphicsEnvironment
java.endorsed.dirs=C:\Program Files\Java\jdk1.8.0_72\jre\lib\endorsed
os.arch=amd64
java.io.tmpdir=C:\Users\usuario\AppData\Local\Temp\
line.separator=

java.vm.specification.vendor=Oracle Corporation
user.variant=
os.name=Windows 10
sun.jnu.encoding=Cp1252
java.library.path=C:\Program Files\Java\jdk1.8.0_72\bin;C:\WINDOWS\Sun\Java\bin;C:\WINDOWS\system32;C:\WINDOWS;C:\ProgramData\Oracle\Java\javapath;C:\Program Files\CollabNet\Subversion Client;E:\bin\Sencha\Cmd\5.1.3.61;C:\Users\usuario\bin\Sencha\Cmd\5.1.3.61;C:\Program Files (x86)\Intel\iCLS Client\;C:\Program Files\Intel\iCLS Client\;C:\WINDOWS\system32;C:\WINDOWS;C:\WINDOWS\System32\Wbem;C:\WINDOWS\System32\WindowsPowerShell\v1.0\;C:\Program Files\Intel\Intel(R) Management Engine Components\DAL;C:\Program Files\Intel\Intel(R) Management Engine Components\IPT;C:\Program Files (x86)\Intel\Intel(R) Management Engine Components\DAL;C:\Program Files (x86)\Intel\Intel(R) Management Engine Components\IPT;C:\Program Files (x86)\Intel\OpenCL SDK\3.0\bin\x86;C:\Program Files (x86)\Intel\OpenCL SDK\3.0\bin\x64;C:\Program Files (x86)\sbt\\bin;C:\Program Files (x86)\Heroku\bin;C:\Program Files (x86)\git\cmd;C:\Program Files (x86)\QuickTime\QTSystem\;C:\HashiCorp\Vagrant\bin;C:\Program Files (x86)\scala\bin;C:\Program Files\nodejs\;C:\Users\usuario\AppData\Local\.meteor\;C:\Users\usuario\AppData\Roaming\npm;.
java.specification.name=Java Platform API Specification
java.class.version=52.0
sun.management.compiler=HotSpot 64-Bit Tiered Compilers
os.version=10.0
user.home=C:\Users\usuario
user.timezone=Europe/Paris
java.awt.printerjob=sun.awt.windows.WPrinterJob
file.encoding=Cp1252
java.specification.version=1.8
java.class.path=C:\Users\usuario\git\spring\aspectos\Ejemplos Relacionados\SpringIoC0007Maven\target\classes;C:\Users\usuario\.m2\repository\org\springframework\spring-context\3.1.2.RELEASE\spring-context-3.1.2.RELEASE.jar;C:\Users\usuario\.m2\repository\org\springframework\spring-aop\3.1.2.RELEASE\spring-aop-3.1.2.RELEASE.jar;C:\Users\usuario\.m2\repository\aopalliance\aopalliance\1.0\aopalliance-1.0.jar;C:\Users\usuario\.m2\repository\org\springframework\spring-beans\3.1.2.RELEASE\spring-beans-3.1.2.RELEASE.jar;C:\Users\usuario\.m2\repository\org\springframework\spring-core\3.1.2.RELEASE\spring-core-3.1.2.RELEASE.jar;C:\Users\usuario\.m2\repository\commons-logging\commons-logging\1.1.1\commons-logging-1.1.1.jar;C:\Users\usuario\.m2\repository\org\springframework\spring-expression\3.1.2.RELEASE\spring-expression-3.1.2.RELEASE.jar;C:\Users\usuario\.m2\repository\org\springframework\spring-asm\3.1.2.RELEASE\spring-asm-3.1.2.RELEASE.jar;C:\Users\usuario\.m2\repository\org\springframework\spring-aspects\3.1.2.RELEASE\spring-aspects-3.1.2.RELEASE.jar;C:\Users\usuario\.m2\repository\org\springframework\spring-context-support\3.1.2.RELEASE\spring-context-support-3.1.2.RELEASE.jar;.\..\aspectjweaver.jar
user.name=usuario
java.vm.specification.version=1.8
sun.java.command=com.curso.spring.springioc0007.Main
java.home=C:\Program Files\Java\jdk1.8.0_72\jre
sun.arch.data.model=64
user.language=es
java.specification.vendor=Oracle Corporation
awt.toolkit=sun.awt.windows.WToolkit
java.vm.info=mixed mode
java.version=1.8.0_72
java.ext.dirs=C:\Program Files\Java\jdk1.8.0_72\jre\lib\ext;C:\WINDOWS\Sun\Java\lib\ext
sun.boot.class.path=C:\Program Files\Java\jdk1.8.0_72\jre\lib\resources.jar;C:\Program Files\Java\jdk1.8.0_72\jre\lib\rt.jar;C:\Program Files\Java\jdk1.8.0_72\jre\lib\sunrsasign.jar;C:\Program Files\Java\jdk1.8.0_72\jre\lib\jsse.jar;C:\Program Files\Java\jdk1.8.0_72\jre\lib\jce.jar;C:\Program Files\Java\jdk1.8.0_72\jre\lib\charsets.jar;C:\Program Files\Java\jdk1.8.0_72\jre\lib\jfr.jar;C:\Program Files\Java\jdk1.8.0_72\jre\classes
java.vendor=Oracle Corporation
file.separator=\
java.vendor.url.bug=http://bugreport.sun.com/bugreport/
sun.io.unicode.encoding=UnicodeLittle
sun.cpu.endian=little
sun.desktop=windows
sun.cpu.isalist=amd64
---- Command Line ---
Empty
---- Full Classpath ---
Empty
---- Compiler Messages ---
Empty
---- org.aspectj.weaver.ltw.LTWWorld@28c97a5 ----
Class loader:
sun.misc.Launcher$AppClassLoader@18b4aac2
Class loader parent:
sun.misc.Launcher$ExtClassLoader@722c41f4
Shadow mungers:
(around(extraFlags: 3): ((((((((((within(@org.springframework.cache.annotation.CacheEvict *) && execution(public * @org.springframework.cache.annotation.CacheEvict *.*(..))) && this(BindingTypePattern(java.lang.Object, 0))) && persingleton(org.springframework.cache.aspectj.AnnotationCacheAspect)) || (((within(@org.springframework.cache.annotation.Caching *) && execution(public * @org.springframework.cache.annotation.Caching *.*(..))) && this(BindingTypePattern(java.lang.Object, 0))) && persingleton(org.springframework.cache.aspectj.AnnotationCacheAspect))) || (((within(@org.springframework.cache.annotation.CachePut *) && execution(public * @org.springframework.cache.annotation.CachePut *.*(..))) && this(BindingTypePattern(java.lang.Object, 0))) && persingleton(org.springframework.cache.aspectj.AnnotationCacheAspect))) || (((within(@org.springframework.cache.annotation.Cacheable *) && execution(public * @org.springframework.cache.annotation.Cacheable *.*(..))) && this(BindingTypePattern(java.lang.Object, 0))) && persingleton(org.springframework.cache.aspectj.AnnotationCacheAspect))) || ((execution(@org.springframework.cache.annotation.Caching * *(..)) && this(BindingTypePattern(java.lang.Object, 0))) && persingleton(org.springframework.cache.aspectj.AnnotationCacheAspect))) || ((execution(@org.springframework.cache.annotation.Cacheable * *(..)) && this(BindingTypePattern(java.lang.Object, 0))) && persingleton(org.springframework.cache.aspectj.AnnotationCacheAspect))) || ((execution(@org.springframework.cache.annotation.CacheEvict * *(..)) && this(BindingTypePattern(java.lang.Object, 0))) && persingleton(org.springframework.cache.aspectj.AnnotationCacheAspect))) || ((execution(@org.springframework.cache.annotation.CachePut * *(..)) && this(BindingTypePattern(java.lang.Object, 0))) && persingleton(org.springframework.cache.aspectj.AnnotationCacheAspect)))->java.lang.Object org.springframework.cache.aspectj.AbstractCacheAspect.ajc$around$org_springframework_cache_aspectj_AbstractCacheAspect$1$2bc714b5(java.lang.Object, org.aspectj.runtime.internal.AroundClosure, org.aspectj.lang.JoinPoint))
(around(extraFlags: 5): ((execution(@org.springframework.scheduling.annotation.Async (void || java.util.concurrent.Future+) *(..)) && persingleton(org.springframework.scheduling.aspectj.AnnotationAsyncExecutionAspect)) || (execution((void || java.util.concurrent.Future+) @org.springframework.scheduling.annotation.Async *.*(..)) && persingleton(org.springframework.scheduling.aspectj.AnnotationAsyncExecutionAspect)))->java.lang.Object org.springframework.scheduling.aspectj.AbstractAsyncExecutionAspect.ajc$around$org_springframework_scheduling_aspectj_AbstractAsyncExecutionAspect$1$6c004c3e(org.aspectj.runtime.internal.AroundClosure, org.aspectj.lang.JoinPoint$StaticPart))
org.aspectj.weaver.Checker@5abff562
org.aspectj.weaver.Checker@12140c1d
(before(extraFlags: 4): ((((within(@org.springframework.transaction.annotation.Transactional *) && execution(public * @org.springframework.transaction.annotation.Transactional *.*(..))) && this(BindingTypePattern(java.lang.Object, 0))) && persingleton(org.springframework.transaction.aspectj.AnnotationTransactionAspect)) || ((execution(@org.springframework.transaction.annotation.Transactional * *(..)) && this(BindingTypePattern(java.lang.Object, 0))) && persingleton(org.springframework.transaction.aspectj.AnnotationTransactionAspect)))->void org.springframework.transaction.aspectj.AbstractTransactionAspect.ajc$before$org_springframework_transaction_aspectj_AbstractTransactionAspect$1$2a73e96c(java.lang.Object, org.aspectj.lang.JoinPoint$StaticPart))
(afterThrowing(extraFlags: 1): ((((within(@org.springframework.transaction.annotation.Transactional *) && execution(public * @org.springframework.transaction.annotation.Transactional *.*(..))) && this(BindingTypePattern(java.lang.Object, 0))) && persingleton(org.springframework.transaction.aspectj.AnnotationTransactionAspect)) || ((execution(@org.springframework.transaction.annotation.Transactional * *(..)) && this(BindingTypePattern(java.lang.Object, 0))) && persingleton(org.springframework.transaction.aspectj.AnnotationTransactionAspect)))->void org.springframework.transaction.aspectj.AbstractTransactionAspect.ajc$afterThrowing$org_springframework_transaction_aspectj_AbstractTransactionAspect$2$2a73e96c(java.lang.Object, java.lang.Throwable))
(afterReturning: ((((within(@org.springframework.transaction.annotation.Transactional *) && execution(public * @org.springframework.transaction.annotation.Transactional *.*(..))) && this(BindingTypePattern(java.lang.Object, 0))) && persingleton(org.springframework.transaction.aspectj.AnnotationTransactionAspect)) || ((execution(@org.springframework.transaction.annotation.Transactional * *(..)) && this(BindingTypePattern(java.lang.Object, 0))) && persingleton(org.springframework.transaction.aspectj.AnnotationTransactionAspect)))->void org.springframework.transaction.aspectj.AbstractTransactionAspect.ajc$afterReturning$org_springframework_transaction_aspectj_AbstractTransactionAspect$3$2a73e96c(java.lang.Object))
(after: ((((within(@org.springframework.transaction.annotation.Transactional *) && execution(public * @org.springframework.transaction.annotation.Transactional *.*(..))) && this(BindingTypePattern(java.lang.Object, 0))) && persingleton(org.springframework.transaction.aspectj.AnnotationTransactionAspect)) || ((execution(@org.springframework.transaction.annotation.Transactional * *(..)) && this(BindingTypePattern(java.lang.Object, 0))) && persingleton(org.springframework.transaction.aspectj.AnnotationTransactionAspect)))->void org.springframework.transaction.aspectj.AbstractTransactionAspect.ajc$after$org_springframework_transaction_aspectj_AbstractTransactionAspect$4$2a73e96c(java.lang.Object))
(before: (((((initialization(org.springframework.beans.factory.aspectj.ConfigurableObject.new(..)) && initialization(org.springframework.beans.factory.aspectj.ConfigurableObject+.new(..))) && this(BindingTypePattern(java.lang.Object, 0))) && @this(org.springframework.beans.factory.annotation.Configurable)) && if(boolean org.springframework.beans.factory.aspectj.AnnotationBeanConfigurerAspect.ajc$if$bb0(org.springframework.beans.factory.annotation.Configurable))) && persingleton(org.springframework.beans.factory.aspectj.AnnotationBeanConfigurerAspect))->void org.springframework.beans.factory.aspectj.AbstractDependencyInjectionAspect.ajc$before$org_springframework_beans_factory_aspectj_AbstractDependencyInjectionAspect$1$e854fa65(java.lang.Object))
(afterReturning: (((((initialization(org.springframework.beans.factory.aspectj.ConfigurableObject+.new(..)) && this(BindingTypePattern(java.lang.Object, 0))) && @this(org.springframework.beans.factory.annotation.Configurable)) && !(@this(org.springframework.beans.factory.annotation.Configurable) && if(boolean org.springframework.beans.factory.aspectj.AnnotationBeanConfigurerAspect.ajc$if$bb0(org.springframework.beans.factory.annotation.Configurable)))) && if(boolean org.springframework.beans.factory.aspectj.AbstractDependencyInjectionAspect.ajc$if$6f1(org.aspectj.lang.JoinPoint))) && persingleton(org.springframework.beans.factory.aspectj.AnnotationBeanConfigurerAspect))->void org.springframework.beans.factory.aspectj.AbstractDependencyInjectionAspect.ajc$afterReturning$org_springframework_beans_factory_aspectj_AbstractDependencyInjectionAspect$2$1ea6722c(java.lang.Object))
(afterReturning: (((execution(java.lang.Object org.springframework.beans.factory.aspectj.AbstractInterfaceDrivenDependencyInjectionAspect$ConfigurableDeserializationSupport+.readResolve()) && this(BindingTypePattern(java.lang.Object, 0))) && @this(org.springframework.beans.factory.annotation.Configurable)) && persingleton(org.springframework.beans.factory.aspectj.AnnotationBeanConfigurerAspect))->void org.springframework.beans.factory.aspectj.AbstractDependencyInjectionAspect.ajc$afterReturning$org_springframework_beans_factory_aspectj_AbstractDependencyInjectionAspect$3$6aa27052(java.lang.Object))
Type mungers:
(BcelTypeMunger ResolvedTypeMunger(Method, java.lang.Object org.springframework.beans.factory.aspectj.AbstractInterfaceDrivenDependencyInjectionAspect$ConfigurableDeserializationSupport.readResolve()))
(BcelTypeMunger ExposeTypeMunger(java.lang.Object))
(BcelTypeMunger ExposeTypeMunger(java.lang.Object))
(BcelTypeMunger ExposeTypeMunger(java.lang.Object))
(BcelTypeMunger ExposeTypeMunger(org.springframework.beans.factory.aspectj.ConfigurableObject))
(BcelTypeMunger ExposeTypeMunger(org.springframework.beans.factory.aspectj.AbstractInterfaceDrivenDependencyInjectionAspect$ConfigurableDeserializationSupport))
Late Type mungers:
Empty
