---- AspectJ Properties ---
AspectJ Compiler 1.6.2 built on Saturday Oct 4, 2008 at 05:47:07 GMT
---- Dump Properties ---
Dump file: ajcore.20160604.114223.556.txt
Dump reason: org.aspectj.bridge.AbortException
Dump on exception: true
Dump at exit condition: abort
---- Exception Information ---
Message: abort trouble in: 
public class org.springframework.beans.PropertyEditorRegistrySupport extends java.lang.Object implements org.springframework.beans.PropertyEditorRegistry:
  private org.springframework.core.convert.ConversionService conversionService
  private boolean defaultEditorsActive
  private boolean configValueEditorsActive
  private java.util.Map defaultEditors [Signature(Ljava/util/Map<Ljava/lang/Class<*>;Ljava/beans/PropertyEditor;>;)]
  private java.util.Map overriddenDefaultEditors [Signature(Ljava/util/Map<Ljava/lang/Class<*>;Ljava/beans/PropertyEditor;>;)]
  private java.util.Map customEditors [Signature(Ljava/util/Map<Ljava/lang/Class<*>;Ljava/beans/PropertyEditor;>;)]
  private java.util.Map customEditorsForPath [Signature(Ljava/util/Map<Ljava/lang/String;Lorg/springframework/beans/PropertyEditorRegistrySupport$CustomEditorHolder;>;)]
  private java.util.Set sharedEditors [Signature(Ljava/util/Set<Ljava/beans/PropertyEditor;>;)]
  private java.util.Map customEditorCache [Signature(Ljava/util/Map<Ljava/lang/Class<*>;Ljava/beans/PropertyEditor;>;)]
  public void <init>():
                    ALOAD_0     // Lorg/springframework/beans/PropertyEditorRegistrySupport; this   (line 86)
                    INVOKESPECIAL java.lang.Object.<init> ()V
    constructor-execution(void org.springframework.beans.PropertyEditorRegistrySupport.<init>())
    |               ALOAD_0     // Lorg/springframework/beans/PropertyEditorRegistrySupport; this   (line 90)
    |               ICONST_0
    |               PUTFIELD org.springframework.beans.PropertyEditorRegistrySupport.defaultEditorsActive Z
    |               ALOAD_0     // Lorg/springframework/beans/PropertyEditorRegistrySupport; this   (line 92)
    |               ICONST_0
    |               PUTFIELD org.springframework.beans.PropertyEditorRegistrySupport.configValueEditorsActive Z
    |               RETURN   (line 86)
    constructor-execution(void org.springframework.beans.PropertyEditorRegistrySupport.<init>())
  end public void <init>()

  public void setConversionService(org.springframework.core.convert.ConversionService):
                    ALOAD_0     // Lorg/springframework/beans/PropertyEditorRegistrySupport; this   (line 112)
                    ALOAD_1     // Lorg/springframework/core/convert/ConversionService; conversionService
                    PUTFIELD org.springframework.beans.PropertyEditorRegistrySupport.conversionService Lorg/springframework/core/convert/ConversionService;
                    RETURN   (line 113)
  end public void setConversionService(org.springframework.core.convert.ConversionService)

  public org.springframework.core.convert.ConversionService getConversionService():
                    ALOAD_0     // Lorg/springframework/beans/PropertyEditorRegistrySupport; this   (line 119)
                    GETFIELD org.springframework.beans.PropertyEditorRegistrySupport.conversionService Lorg/springframework/core/convert/ConversionService;
                    ARETURN
  end public org.springframework.core.convert.ConversionService getConversionService()

  protected void registerDefaultEditors():
                    ALOAD_0     // Lorg/springframework/beans/PropertyEditorRegistrySupport; this   (line 132)
                    ICONST_1
                    PUTFIELD org.springframework.beans.PropertyEditorRegistrySupport.defaultEditorsActive Z
                    RETURN   (line 133)
  end protected void registerDefaultEditors()

  public void useConfigValueEditors():
                    ALOAD_0     // Lorg/springframework/beans/PropertyEditorRegistrySupport; this   (line 143)
                    ICONST_1
                    PUTFIELD org.springframework.beans.PropertyEditorRegistrySupport.configValueEditorsActive Z
                    RETURN   (line 144)
  end public void useConfigValueEditors()

  public void overrideDefaultEditor(Class, java.beans.PropertyEditor):
                    ALOAD_0     // Lorg/springframework/beans/PropertyEditorRegistrySupport; this   (line 156)
                    GETFIELD org.springframework.beans.PropertyEditorRegistrySupport.overriddenDefaultEditors Ljava/util/Map;
                    IFNONNULL L0
                    ALOAD_0     // Lorg/springframework/beans/PropertyEditorRegistrySupport; this   (line 157)
                    NEW java.util.HashMap
                    DUP
                    INVOKESPECIAL java.util.HashMap.<init> ()V
                    PUTFIELD org.springframework.beans.PropertyEditorRegistrySupport.overriddenDefaultEditors Ljava/util/Map;
                L0: ALOAD_0     // Lorg/springframework/beans/PropertyEditorRegistrySupport; this   (line 159)
                    GETFIELD org.springframework.beans.PropertyEditorRegistrySupport.overriddenDefaultEditors Ljava/util/Map;
                    ALOAD_1     // Ljava/lang/Class; requiredType
                    ALOAD_2     // Ljava/beans/PropertyEditor; propertyEditor
                    INVOKEINTERFACE java.util.Map.put (Ljava/lang/Object;Ljava/lang/Object;)Ljava/lang/Object;
                    POP
                    RETURN   (line 160)
  end public void overrideDefaultEditor(Class, java.beans.PropertyEditor)

  public java.beans.PropertyEditor getDefaultEditor(Class):
                    ALOAD_0     // Lorg/springframework/beans/PropertyEditorRegistrySupport; this   (line 170)
                    GETFIELD org.springframework.beans.PropertyEditorRegistrySupport.defaultEditorsActive Z
                    IFNE L0
                    ACONST_NULL   (line 171)
                    ARETURN
                L0: ALOAD_0     // Lorg/springframework/beans/PropertyEditorRegistrySupport; this   (line 173)
                    GETFIELD org.springframework.beans.PropertyEditorRegistrySupport.overriddenDefaultEditors Ljava/util/Map;
                    IFNULL L1
                    ALOAD_0     // Lorg/springframework/beans/PropertyEditorRegistrySupport; this   (line 174)
                    GETFIELD org.springframework.beans.PropertyEditorRegistrySupport.overriddenDefaultEditors Ljava/util/Map;
                    ALOAD_1     // Ljava/lang/Class; requiredType
                    INVOKEINTERFACE java.util.Map.get (Ljava/lang/Object;)Ljava/lang/Object;
                    CHECKCAST java.beans.PropertyEditor
                    ASTORE_2
                    ALOAD_2     // Ljava/beans/PropertyEditor; editor   (line 175)
                    IFNULL L1
                    ALOAD_2     // Ljava/beans/PropertyEditor; editor   (line 176)
                    ARETURN
                L1: ALOAD_0     // Lorg/springframework/beans/PropertyEditorRegistrySupport; this   (line 179)
                    GETFIELD org.springframework.beans.PropertyEditorRegistrySupport.defaultEditors Ljava/util/Map;
                    IFNONNULL L2
                    ALOAD_0     // Lorg/springframework/beans/PropertyEditorRegistrySupport; this   (line 180)
                    INVOKESPECIAL org.springframework.beans.PropertyEditorRegistrySupport.createDefaultEditors ()V
                L2: ALOAD_0     // Lorg/springframework/beans/PropertyEditorRegistrySupport; this   (line 182)
                    GETFIELD org.springframework.beans.PropertyEditorRegistrySupport.defaultEditors Ljava/util/Map;
                    ALOAD_1     // Ljava/lang/Class; requiredType
                    INVOKEINTERFACE java.util.Map.get (Ljava/lang/Object;)Ljava/lang/Object;
                    CHECKCAST java.beans.PropertyEditor
                    ARETURN
  end public java.beans.PropertyEditor getDefaultEditor(Class)

  private void createDefaultEditors():
                    ALOAD_0     // Lorg/springframework/beans/PropertyEditorRegistrySupport; this   (line 189)
                    NEW java.util.HashMap
                    DUP
                    BIPUSH 64
                    INVOKESPECIAL java.util.HashMap.<init> (I)V
                    PUTFIELD org.springframework.beans.PropertyEditorRegistrySupport.defaultEditors Ljava/util/Map;
                    ALOAD_0     // Lorg/springframework/beans/PropertyEditorRegistrySupport; this   (line 193)
                    GETFIELD org.springframework.beans.PropertyEditorRegistrySupport.defaultEditors Ljava/util/Map;
                    LDC java.nio.charset.Charset
                    NEW org.springframework.beans.propertyeditors.CharsetEditor
                    DUP
                    INVOKESPECIAL org.springframework.beans.propertyeditors.CharsetEditor.<init> ()V
                    INVOKEINTERFACE java.util.Map.put (Ljava/lang/Object;Ljava/lang/Object;)Ljava/lang/Object;
                    POP
                    ALOAD_0     // Lorg/springframework/beans/PropertyEditorRegistrySupport; this   (line 194)
                    GETFIELD org.springframework.beans.PropertyEditorRegistrySupport.defaultEditors Ljava/util/Map;
                    LDC java.lang.Class
                    NEW org.springframework.beans.propertyeditors.ClassEditor
                    DUP
                    INVOKESPECIAL org.springframework.beans.propertyeditors.ClassEditor.<init> ()V
                    INVOKEINTERFACE java.util.Map.put (Ljava/lang/Object;Ljava/lang/Object;)Ljava/lang/Object;
                    POP
                    ALOAD_0     // Lorg/springframework/beans/PropertyEditorRegistrySupport; this   (line 195)
                    GETFIELD org.springframework.beans.PropertyEditorRegistrySupport.defaultEditors Ljava/util/Map;
                    LDC [Ljava.lang.Class;
                    NEW org.springframework.beans.propertyeditors.ClassArrayEditor
                    DUP
                    INVOKESPECIAL org.springframework.beans.propertyeditors.ClassArrayEditor.<init> ()V
                    INVOKEINTERFACE java.util.Map.put (Ljava/lang/Object;Ljava/lang/Object;)Ljava/lang/Object;
                    POP
                    ALOAD_0     // Lorg/springframework/beans/PropertyEditorRegistrySupport; this   (line 196)
                    GETFIELD org.springframework.beans.PropertyEditorRegistrySupport.defaultEditors Ljava/util/Map;
                    LDC java.util.Currency
                    NEW org.springframework.beans.propertyeditors.CurrencyEditor
                    DUP
                    INVOKESPECIAL org.springframework.beans.propertyeditors.CurrencyEditor.<init> ()V
                    INVOKEINTERFACE java.util.Map.put (Ljava/lang/Object;Ljava/lang/Object;)Ljava/lang/Object;
                    POP
                    ALOAD_0     // Lorg/springframework/beans/PropertyEditorRegistrySupport; this   (line 197)
                    GETFIELD org.springframework.beans.PropertyEditorRegistrySupport.defaultEditors Ljava/util/Map;
                    LDC java.io.File
                    NEW org.springframework.beans.propertyeditors.FileEditor
                    DUP
                    INVOKESPECIAL org.springframework.beans.propertyeditors.FileEditor.<init> ()V
                    INVOKEINTERFACE java.util.Map.put (Ljava/lang/Object;Ljava/lang/Object;)Ljava/lang/Object;
                    POP
                    ALOAD_0     // Lorg/springframework/beans/PropertyEditorRegistrySupport; this   (line 198)
                    GETFIELD org.springframework.beans.PropertyEditorRegistrySupport.defaultEditors Ljava/util/Map;
                    LDC java.io.InputStream
                    NEW org.springframework.beans.propertyeditors.InputStreamEditor
                    DUP
                    INVOKESPECIAL org.springframework.beans.propertyeditors.InputStreamEditor.<init> ()V
                    INVOKEINTERFACE java.util.Map.put (Ljava/lang/Object;Ljava/lang/Object;)Ljava/lang/Object;
                    POP
                    ALOAD_0     // Lorg/springframework/beans/PropertyEditorRegistrySupport; this   (line 199)
                    GETFIELD org.springframework.beans.PropertyEditorRegistrySupport.defaultEditors Ljava/util/Map;
                    LDC org.xml.sax.InputSource
                    NEW org.springframework.beans.propertyeditors.InputSourceEditor
                    DUP
                    INVOKESPECIAL org.springframework.beans.propertyeditors.InputSourceEditor.<init> ()V
                    INVOKEINTERFACE java.util.Map.put (Ljava/lang/Object;Ljava/lang/Object;)Ljava/lang/Object;
                    POP
                    ALOAD_0     // Lorg/springframework/beans/PropertyEditorRegistrySupport; this   (line 200)
                    GETFIELD org.springframework.beans.PropertyEditorRegistrySupport.defaultEditors Ljava/util/Map;
                    LDC java.util.Locale
                    NEW org.springframework.beans.propertyeditors.LocaleEditor
                    DUP
                    INVOKESPECIAL org.springframework.beans.propertyeditors.LocaleEditor.<init> ()V
                    INVOKEINTERFACE java.util.Map.put (Ljava/lang/Object;Ljava/lang/Object;)Ljava/lang/Object;
                    POP
                    ALOAD_0     // Lorg/springframework/beans/PropertyEditorRegistrySupport; this   (line 201)
                    GETFIELD org.springframework.beans.PropertyEditorRegistrySupport.defaultEditors Ljava/util/Map;
                    LDC java.util.regex.Pattern
                    NEW org.springframework.beans.propertyeditors.PatternEditor
                    DUP
                    INVOKESPECIAL org.springframework.beans.propertyeditors.PatternEditor.<init> ()V
                    INVOKEINTERFACE java.util.Map.put (Ljava/lang/Object;Ljava/lang/Object;)Ljava/lang/Object;
                    POP
                    ALOAD_0     // Lorg/springframework/beans/PropertyEditorRegistrySupport; this   (line 202)
                    GETFIELD org.springframework.beans.PropertyEditorRegistrySupport.defaultEditors Ljava/util/Map;
                    LDC java.util.Properties
                    NEW org.springframework.beans.propertyeditors.PropertiesEditor
                    DUP
                    INVOKESPECIAL org.springframework.beans.propertyeditors.PropertiesEditor.<init> ()V
                    INVOKEINTERFACE java.util.Map.put (Ljava/lang/Object;Ljava/lang/Object;)Ljava/lang/Object;
                    POP
                    ALOAD_0     // Lorg/springframework/beans/PropertyEditorRegistrySupport; this   (line 203)
                    GETFIELD org.springframework.beans.PropertyEditorRegistrySupport.defaultEditors Ljava/util/Map;
                    LDC [Lorg.springframework.core.io.Resource;
                    NEW org.springframework.core.io.support.ResourceArrayPropertyEditor
                    DUP
                    INVOKESPECIAL org.springframework.core.io.support.ResourceArrayPropertyEditor.<init> ()V
                    INVOKEINTERFACE java.util.Map.put (Ljava/lang/Object;Ljava/lang/Object;)Ljava/lang/Object;
                    POP
                    ALOAD_0     // Lorg/springframework/beans/PropertyEditorRegistrySupport; this   (line 204)
                    GETFIELD org.springframework.beans.PropertyEditorRegistrySupport.defaultEditors Ljava/util/Map;
                    LDC java.util.TimeZone
                    NEW org.springframework.beans.propertyeditors.TimeZoneEditor
                    DUP
                    INVOKESPECIAL org.springframework.beans.propertyeditors.TimeZoneEditor.<init> ()V
                    INVOKEINTERFACE java.util.Map.put (Ljava/lang/Object;Ljava/lang/Object;)Ljava/lang/Object;
                    POP
                    ALOAD_0     // Lorg/springframework/beans/PropertyEditorRegistrySupport; this   (line 205)
                    GETFIELD org.springframework.beans.PropertyEditorRegistrySupport.defaultEditors Ljava/util/Map;
                    LDC java.net.URI
                    NEW org.springframework.beans.propertyeditors.URIEditor
                    DUP
                    INVOKESPECIAL org.springframework.beans.propertyeditors.URIEditor.<init> ()V
                    INVOKEINTERFACE java.util.Map.put (Ljava/lang/Object;Ljava/lang/Object;)Ljava/lang/Object;
                    POP
                    ALOAD_0     // Lorg/springframework/beans/PropertyEditorRegistrySupport; this   (line 206)
                    GETFIELD org.springframework.beans.PropertyEditorRegistrySupport.defaultEditors Ljava/util/Map;
                    LDC java.net.URL
                    NEW org.springframework.beans.propertyeditors.URLEditor
                    DUP
                    INVOKESPECIAL org.springframework.beans.propertyeditors.URLEditor.<init> ()V
                    INVOKEINTERFACE java.util.Map.put (Ljava/lang/Object;Ljava/lang/Object;)Ljava/lang/Object;
                    POP
                    ALOAD_0     // Lorg/springframework/beans/PropertyEditorRegistrySupport; this   (line 207)
                    GETFIELD org.springframework.beans.PropertyEditorRegistrySupport.defaultEditors Ljava/util/Map;
                    LDC java.util.UUID
                    NEW org.springframework.beans.propertyeditors.UUIDEditor
                    DUP
                    INVOKESPECIAL org.springframework.beans.propertyeditors.UUIDEditor.<init> ()V
                    INVOKEINTERFACE java.util.Map.put (Ljava/lang/Object;Ljava/lang/Object;)Ljava/lang/Object;
                    POP
                    ALOAD_0     // Lorg/springframework/beans/PropertyEditorRegistrySupport; this   (line 211)
                    GETFIELD org.springframework.beans.PropertyEditorRegistrySupport.defaultEditors Ljava/util/Map;
                    LDC java.util.Collection
                    NEW org.springframework.beans.propertyeditors.CustomCollectionEditor
                    DUP
                    LDC java.util.Collection
                    INVOKESPECIAL org.springframework.beans.propertyeditors.CustomCollectionEditor.<init> (Ljava/lang/Class;)V
                    INVOKEINTERFACE java.util.Map.put (Ljava/lang/Object;Ljava/lang/Object;)Ljava/lang/Object;
                    POP
                    ALOAD_0     // Lorg/springframework/beans/PropertyEditorRegistrySupport; this   (line 212)
                    GETFIELD org.springframework.beans.PropertyEditorRegistrySupport.defaultEditors Ljava/util/Map;
                    LDC java.util.Set
                    NEW org.springframework.beans.propertyeditors.CustomCollectionEditor
                    DUP
                    LDC java.util.Set
                    INVOKESPECIAL org.springframework.beans.propertyeditors.CustomCollectionEditor.<init> (Ljava/lang/Class;)V
                    INVOKEINTERFACE java.util.Map.put (Ljava/lang/Object;Ljava/lang/Object;)Ljava/lang/Object;
                    POP
                    ALOAD_0     // Lorg/springframework/beans/PropertyEditorRegistrySupport; this   (line 213)
                    GETFIELD org.springframework.beans.PropertyEditorRegistrySupport.defaultEditors Ljava/util/Map;
                    LDC java.util.SortedSet
                    NEW org.springframework.beans.propertyeditors.CustomCollectionEditor
                    DUP
                    LDC java.util.SortedSet
                    INVOKESPECIAL org.springframework.beans.propertyeditors.CustomCollectionEditor.<init> (Ljava/lang/Class;)V
                    INVOKEINTERFACE java.util.Map.put (Ljava/lang/Object;Ljava/lang/Object;)Ljava/lang/Object;
                    POP
                    ALOAD_0     // Lorg/springframework/beans/PropertyEditorRegistrySupport; this   (line 214)
                    GETFIELD org.springframework.beans.PropertyEditorRegistrySupport.defaultEditors Ljava/util/Map;
                    LDC java.util.List
                    NEW org.springframework.beans.propertyeditors.CustomCollectionEditor
                    DUP
                    LDC java.util.List
                    INVOKESPECIAL org.springframework.beans.propertyeditors.CustomCollectionEditor.<init> (Ljava/lang/Class;)V
                    INVOKEINTERFACE java.util.Map.put (Ljava/lang/Object;Ljava/lang/Object;)Ljava/lang/Object;
                    POP
                    ALOAD_0     // Lorg/springframework/beans/PropertyEditorRegistrySupport; this   (line 215)
                    GETFIELD org.springframework.beans.PropertyEditorRegistrySupport.defaultEditors Ljava/util/Map;
                    LDC java.util.SortedMap
                    NEW org.springframework.beans.propertyeditors.CustomMapEditor
                    DUP
                    LDC java.util.SortedMap
                    INVOKESPECIAL org.springframework.beans.propertyeditors.CustomMapEditor.<init> (Ljava/lang/Class;)V
                    INVOKEINTERFACE java.util.Map.put (Ljava/lang/Object;Ljava/lang/Object;)Ljava/lang/Object;
                    POP
                    ALOAD_0     // Lorg/springframework/beans/PropertyEditorRegistrySupport; this   (line 218)
                    GETFIELD org.springframework.beans.PropertyEditorRegistrySupport.defaultEditors Ljava/util/Map;
                    LDC [B
                    NEW org.springframework.beans.propertyeditors.ByteArrayPropertyEditor
                    DUP
                    INVOKESPECIAL org.springframework.beans.propertyeditors.ByteArrayPropertyEditor.<init> ()V
                    INVOKEINTERFACE java.util.Map.put (Ljava/lang/Object;Ljava/lang/Object;)Ljava/lang/Object;
                    POP
                    ALOAD_0     // Lorg/springframework/beans/PropertyEditorRegistrySupport; this   (line 219)
                    GETFIELD org.springframework.beans.PropertyEditorRegistrySupport.defaultEditors Ljava/util/Map;
                    LDC [C
                    NEW org.springframework.beans.propertyeditors.CharArrayPropertyEditor
                    DUP
                    INVOKESPECIAL org.springframework.beans.propertyeditors.CharArrayPropertyEditor.<init> ()V
                    INVOKEINTERFACE java.util.Map.put (Ljava/lang/Object;Ljava/lang/Object;)Ljava/lang/Object;
                    POP
                    ALOAD_0     // Lorg/springframework/beans/PropertyEditorRegistrySupport; this   (line 222)
                    GETFIELD org.springframework.beans.PropertyEditorRegistrySupport.defaultEditors Ljava/util/Map;
                    GETSTATIC java.lang.Character.TYPE Ljava/lang/Class;
                    NEW org.springframework.beans.propertyeditors.CharacterEditor
                    DUP
                    ICONST_0
                    INVOKESPECIAL org.springframework.beans.propertyeditors.CharacterEditor.<init> (Z)V
                    INVOKEINTERFACE java.util.Map.put (Ljava/lang/Object;Ljava/lang/Object;)Ljava/lang/Object;
                    POP
                    ALOAD_0     // Lorg/springframework/beans/PropertyEditorRegistrySupport; this   (line 223)
                    GETFIELD org.springframework.beans.PropertyEditorRegistrySupport.defaultEditors Ljava/util/Map;
                    LDC java.lang.Character
                    NEW org.springframework.beans.propertyeditors.CharacterEditor
                    DUP
                    ICONST_1
                    INVOKESPECIAL org.springframework.beans.propertyeditors.CharacterEditor.<init> (Z)V
                    INVOKEINTERFACE java.util.Map.put (Ljava/lang/Object;Ljava/lang/Object;)Ljava/lang/Object;
                    POP
                    ALOAD_0     // Lorg/springframework/beans/PropertyEditorRegistrySupport; this   (line 226)
                    GETFIELD org.springframework.beans.PropertyEditorRegistrySupport.defaultEditors Ljava/util/Map;
                    GETSTATIC java.lang.Boolean.TYPE Ljava/lang/Class;
                    NEW org.springframework.beans.propertyeditors.CustomBooleanEditor
                    DUP
                    ICONST_0
                    INVOKESPECIAL org.springframework.beans.propertyeditors.CustomBooleanEditor.<init> (Z)V
                    INVOKEINTERFACE java.util.Map.put (Ljava/lang/Object;Ljava/lang/Object;)Ljava/lang/Object;
                    POP
                    ALOAD_0     // Lorg/springframework/beans/PropertyEditorRegistrySupport; this   (line 227)
                    GETFIELD org.springframework.beans.PropertyEditorRegistrySupport.defaultEditors Ljava/util/Map;
                    LDC java.lang.Boolean
                    NEW org.springframework.beans.propertyeditors.CustomBooleanEditor
                    DUP
                    ICONST_1
                    INVOKESPECIAL org.springframework.beans.propertyeditors.CustomBooleanEditor.<init> (Z)V
                    INVOKEINTERFACE java.util.Map.put (Ljava/lang/Object;Ljava/lang/Object;)Ljava/lang/Object;
                    POP
                    ALOAD_0     // Lorg/springframework/beans/PropertyEditorRegistrySupport; this   (line 231)
                    GETFIELD org.springframework.beans.PropertyEditorRegistrySupport.defaultEditors Ljava/util/Map;
                    GETSTATIC java.lang.Byte.TYPE Ljava/lang/Class;
                    NEW org.springframework.beans.propertyeditors.CustomNumberEditor
                    DUP
                    LDC java.lang.Byte
                    ICONST_0
                    INVOKESPECIAL org.springframework.beans.propertyeditors.CustomNumberEditor.<init> (Ljava/lang/Class;Z)V
                    INVOKEINTERFACE java.util.Map.put (Ljava/lang/Object;Ljava/lang/Object;)Ljava/lang/Object;
                    POP
                    ALOAD_0     // Lorg/springframework/beans/PropertyEditorRegistrySupport; this   (line 232)
                    GETFIELD org.springframework.beans.PropertyEditorRegistrySupport.defaultEditors Ljava/util/Map;
                    LDC java.lang.Byte
                    NEW org.springframework.beans.propertyeditors.CustomNumberEditor
                    DUP
                    LDC java.lang.Byte
                    ICONST_1
                    INVOKESPECIAL org.springframework.beans.propertyeditors.CustomNumberEditor.<init> (Ljava/lang/Class;Z)V
                    INVOKEINTERFACE java.util.Map.put (Ljava/lang/Object;Ljava/lang/Object;)Ljava/lang/Object;
                    POP
                    ALOAD_0     // Lorg/springframework/beans/PropertyEditorRegistrySupport; this   (line 233)
                    GETFIELD org.springframework.beans.PropertyEditorRegistrySupport.defaultEditors Ljava/util/Map;
                    GETSTATIC java.lang.Short.TYPE Ljava/lang/Class;
                    NEW org.springframework.beans.propertyeditors.CustomNumberEditor
                    DUP
                    LDC java.lang.Short
                    ICONST_0
                    INVOKESPECIAL org.springframework.beans.propertyeditors.CustomNumberEditor.<init> (Ljava/lang/Class;Z)V
                    INVOKEINTERFACE java.util.Map.put (Ljava/lang/Object;Ljava/lang/Object;)Ljava/lang/Object;
                    POP
                    ALOAD_0     // Lorg/springframework/beans/PropertyEditorRegistrySupport; this   (line 234)
                    GETFIELD org.springframework.beans.PropertyEditorRegistrySupport.defaultEditors Ljava/util/Map;
                    LDC java.lang.Short
                    NEW org.springframework.beans.propertyeditors.CustomNumberEditor
                    DUP
                    LDC java.lang.Short
                    ICONST_1
                    INVOKESPECIAL org.springframework.beans.propertyeditors.CustomNumberEditor.<init> (Ljava/lang/Class;Z)V
                    INVOKEINTERFACE java.util.Map.put (Ljava/lang/Object;Ljava/lang/Object;)Ljava/lang/Object;
                    POP
                    ALOAD_0     // Lorg/springframework/beans/PropertyEditorRegistrySupport; this   (line 235)
                    GETFIELD org.springframework.beans.PropertyEditorRegistrySupport.defaultEditors Ljava/util/Map;
                    GETSTATIC java.lang.Integer.TYPE Ljava/lang/Class;
                    NEW org.springframework.beans.propertyeditors.CustomNumberEditor
                    DUP
                    LDC java.lang.Integer
                    ICONST_0
                    INVOKESPECIAL org.springframework.beans.propertyeditors.CustomNumberEditor.<init> (Ljava/lang/Class;Z)V
                    INVOKEINTERFACE java.util.Map.put (Ljava/lang/Object;Ljava/lang/Object;)Ljava/lang/Object;
                    POP
                    ALOAD_0     // Lorg/springframework/beans/PropertyEditorRegistrySupport; this   (line 236)
                    GETFIELD org.springframework.beans.PropertyEditorRegistrySupport.defaultEditors Ljava/util/Map;
                    LDC java.lang.Integer
                    NEW org.springframework.beans.propertyeditors.CustomNumberEditor
                    DUP
                    LDC java.lang.Integer
                    ICONST_1
                    INVOKESPECIAL org.springframework.beans.propertyeditors.CustomNumberEditor.<init> (Ljava/lang/Class;Z)V
                    INVOKEINTERFACE java.util.Map.put (Ljava/lang/Object;Ljava/lang/Object;)Ljava/lang/Object;
                    POP
                    ALOAD_0     // Lorg/springframework/beans/PropertyEditorRegistrySupport; this   (line 237)
                    GETFIELD org.springframework.beans.PropertyEditorRegistrySupport.defaultEditors Ljava/util/Map;
                    GETSTATIC java.lang.Long.TYPE Ljava/lang/Class;
                    NEW org.springframework.beans.propertyeditors.CustomNumberEditor
                    DUP
                    LDC java.lang.Long
                    ICONST_0
                    INVOKESPECIAL org.springframework.beans.propertyeditors.CustomNumberEditor.<init> (Ljava/lang/Class;Z)V
                    INVOKEINTERFACE java.util.Map.put (Ljava/lang/Object;Ljava/lang/Object;)Ljava/lang/Object;
                    POP
                    ALOAD_0     // Lorg/springframework/beans/PropertyEditorRegistrySupport; this   (line 238)
                    GETFIELD org.springframework.beans.PropertyEditorRegistrySupport.defaultEditors Ljava/util/Map;
                    LDC java.lang.Long
                    NEW org.springframework.beans.propertyeditors.CustomNumberEditor
                    DUP
                    LDC java.lang.Long
                    ICONST_1
                    INVOKESPECIAL org.springframework.beans.propertyeditors.CustomNumberEditor.<init> (Ljava/lang/Class;Z)V
                    INVOKEINTERFACE java.util.Map.put (Ljava/lang/Object;Ljava/lang/Object;)Ljava/lang/Object;
                    POP
                    ALOAD_0     // Lorg/springframework/beans/PropertyEditorRegistrySupport; this   (line 239)
                    GETFIELD org.springframework.beans.PropertyEditorRegistrySupport.defaultEditors Ljava/util/Map;
                    GETSTATIC java.lang.Float.TYPE Ljava/lang/Class;
                    NEW org.springframework.beans.propertyeditors.CustomNumberEditor
                    DUP
                    LDC java.lang.Float
                    ICONST_0
                    INVOKESPECIAL org.springframework.beans.propertyeditors.CustomNumberEditor.<init> (Ljava/lang/Class;Z)V
                    INVOKEINTERFACE java.util.Map.put (Ljava/lang/Object;Ljava/lang/Object;)Ljava/lang/Object;
                    POP
                    ALOAD_0     // Lorg/springframework/beans/PropertyEditorRegistrySupport; this   (line 240)
                    GETFIELD org.springframework.beans.PropertyEditorRegistrySupport.defaultEditors Ljava/util/Map;
                    LDC java.lang.Float
                    NEW org.springframework.beans.propertyeditors.CustomNumberEditor
                    DUP
                    LDC java.lang.Float
                    ICONST_1
                    INVOKESPECIAL org.springframework.beans.propertyeditors.CustomNumberEditor.<init> (Ljava/lang/Class;Z)V
                    INVOKEINTERFACE java.util.Map.put (Ljava/lang/Object;Ljava/lang/Object;)Ljava/lang/Object;
                    POP
                    ALOAD_0     // Lorg/springframework/beans/PropertyEditorRegistrySupport; this   (line 241)
                    GETFIELD org.springframework.beans.PropertyEditorRegistrySupport.defaultEditors Ljava/util/Map;
                    GETSTATIC java.lang.Double.TYPE Ljava/lang/Class;
                    NEW org.springframework.beans.propertyeditors.CustomNumberEditor
                    DUP
                    LDC java.lang.Double
                    ICONST_0
                    INVOKESPECIAL org.springframework.beans.propertyeditors.CustomNumberEditor.<init> (Ljava/lang/Class;Z)V
                    INVOKEINTERFACE java.util.Map.put (Ljava/lang/Object;Ljava/lang/Object;)Ljava/lang/Object;
                    POP
                    ALOAD_0     // Lorg/springframework/beans/PropertyEditorRegistrySupport; this   (line 242)
                    GETFIELD org.springframework.beans.PropertyEditorRegistrySupport.defaultEditors Ljava/util/Map;
                    LDC java.lang.Double
                    NEW org.springframework.beans.propertyeditors.CustomNumberEditor
                    DUP
                    LDC java.lang.Double
                    ICONST_1
                    INVOKESPECIAL org.springframework.beans.propertyeditors.CustomNumberEditor.<init> (Ljava/lang/Class;Z)V
                    INVOKEINTERFACE java.util.Map.put (Ljava/lang/Object;Ljava/lang/Object;)Ljava/lang/Object;
                    POP
                    ALOAD_0     // Lorg/springframework/beans/PropertyEditorRegistrySupport; this   (line 243)
                    GETFIELD org.springframework.beans.PropertyEditorRegistrySupport.defaultEditors Ljava/util/Map;
                    LDC java.math.BigDecimal
                    NEW org.springframework.beans.propertyeditors.CustomNumberEditor
                    DUP
                    LDC java.math.BigDecimal
                    ICONST_1
                    INVOKESPECIAL org.springframework.beans.propertyeditors.CustomNumberEditor.<init> (Ljava/lang/Class;Z)V
                    INVOKEINTERFACE java.util.Map.put (Ljava/lang/Object;Ljava/lang/Object;)Ljava/lang/Object;
                    POP
                    ALOAD_0     // Lorg/springframework/beans/PropertyEditorRegistrySupport; this   (line 244)
                    GETFIELD org.springframework.beans.PropertyEditorRegistrySupport.defaultEditors Ljava/util/Map;
                    LDC java.math.BigInteger
                    NEW org.springframework.beans.propertyeditors.CustomNumberEditor
                    DUP
                    LDC java.math.BigInteger
                    ICONST_1
                    INVOKESPECIAL org.springframework.beans.propertyeditors.CustomNumberEditor.<init> (Ljava/lang/Class;Z)V
                    INVOKEINTERFACE java.util.Map.put (Ljava/lang/Object;Ljava/lang/Object;)Ljava/lang/Object;
                    POP
                    ALOAD_0     // Lorg/springframework/beans/PropertyEditorRegistrySupport; this   (line 247)
                    GETFIELD org.springframework.beans.PropertyEditorRegistrySupport.configValueEditorsActive Z
                    IFEQ L0
                    NEW org.springframework.beans.propertyeditors.StringArrayPropertyEditor   (line 248)
                    DUP
                    INVOKESPECIAL org.springframework.beans.propertyeditors.StringArrayPropertyEditor.<init> ()V
                    ASTORE_1
                    ALOAD_0     // Lorg/springframework/beans/PropertyEditorRegistrySupport; this   (line 249)
                    GETFIELD org.springframework.beans.PropertyEditorRegistrySupport.defaultEditors Ljava/util/Map;
                    LDC [Ljava.lang.String;
                    ALOAD_1     // Lorg/springframework/beans/propertyeditors/StringArrayPropertyEditor; sae
                    INVOKEINTERFACE java.util.Map.put (Ljava/lang/Object;Ljava/lang/Object;)Ljava/lang/Object;
                    POP
                    ALOAD_0     // Lorg/springframework/beans/PropertyEditorRegistrySupport; this   (line 250)
                    GETFIELD org.springframework.beans.PropertyEditorRegistrySupport.defaultEditors Ljava/util/Map;
                    LDC [S
                    ALOAD_1     // Lorg/springframework/beans/propertyeditors/StringArrayPropertyEditor; sae
                    INVOKEINTERFACE java.util.Map.put (Ljava/lang/Object;Ljava/lang/Object;)Ljava/lang/Object;
                    POP
                    ALOAD_0     // Lorg/springframework/beans/PropertyEditorRegistrySupport; this   (line 251)
                    GETFIELD org.springframework.beans.PropertyEditorRegistrySupport.defaultEditors Ljava/util/Map;
                    LDC [I
                    ALOAD_1     // Lorg/springframework/beans/propertyeditors/StringArrayPropertyEditor; sae
                    INVOKEINTERFACE java.util.Map.put (Ljava/lang/Object;Ljava/lang/Object;)Ljava/lang/Object;
                    POP
                    ALOAD_0     // Lorg/springframework/beans/PropertyEditorRegistrySupport; this   (line 252)
                    GETFIELD org.springframework.beans.PropertyEditorRegistrySupport.defaultEditors Ljava/util/Map;
                    LDC [J
                    ALOAD_1     // Lorg/springframework/beans/propertyeditors/StringArrayPropertyEditor; sae
                    INVOKEINTERFACE java.util.Map.put (Ljava/lang/Object;Ljava/lang/Object;)Ljava/lang/Object;
                    POP
                L0: RETURN   (line 254)
  end private void createDefaultEditors()

  protected void copyDefaultEditorsTo(org.springframework.beans.PropertyEditorRegistrySupport):
                    ALOAD_1     // Lorg/springframework/beans/PropertyEditorRegistrySupport; target   (line 261)
                    ALOAD_0     // Lorg/springframework/beans/PropertyEditorRegistrySupport; this
                    GETFIELD org.springframework.beans.PropertyEditorRegistrySupport.defaultEditorsActive Z
                    PUTFIELD org.springframework.beans.PropertyEditorRegistrySupport.defaultEditorsActive Z
                    ALOAD_1     // Lorg/springframework/beans/PropertyEditorRegistrySupport; target   (line 262)
                    ALOAD_0     // Lorg/springframework/beans/PropertyEditorRegistrySupport; this
                    GETFIELD org.springframework.beans.PropertyEditorRegistrySupport.configValueEditorsActive Z
                    PUTFIELD org.springframework.beans.PropertyEditorRegistrySupport.configValueEditorsActive Z
                    ALOAD_1     // Lorg/springframework/beans/PropertyEditorRegistrySupport; target   (line 263)
                    ALOAD_0     // Lorg/springframework/beans/PropertyEditorRegistrySupport; this
                    GETFIELD org.springframework.beans.PropertyEditorRegistrySupport.defaultEditors Ljava/util/Map;
                    PUTFIELD org.springframework.beans.PropertyEditorRegistrySupport.defaultEditors Ljava/util/Map;
                    ALOAD_1     // Lorg/springframework/beans/PropertyEditorRegistrySupport; target   (line 264)
                    ALOAD_0     // Lorg/springframework/beans/PropertyEditorRegistrySupport; this
                    GETFIELD org.springframework.beans.PropertyEditorRegistrySupport.overriddenDefaultEditors Ljava/util/Map;
                    PUTFIELD org.springframework.beans.PropertyEditorRegistrySupport.overriddenDefaultEditors Ljava/util/Map;
                    RETURN   (line 265)
  end protected void copyDefaultEditorsTo(org.springframework.beans.PropertyEditorRegistrySupport)

  public void registerCustomEditor(Class, java.beans.PropertyEditor):
                    ALOAD_0     // Lorg/springframework/beans/PropertyEditorRegistrySupport; this   (line 273)
                    ALOAD_1     // Ljava/lang/Class; requiredType
                    ACONST_NULL
                    ALOAD_2     // Ljava/beans/PropertyEditor; propertyEditor
                    INVOKEVIRTUAL org.springframework.beans.PropertyEditorRegistrySupport.registerCustomEditor (Ljava/lang/Class;Ljava/lang/String;Ljava/beans/PropertyEditor;)V
                    RETURN   (line 274)
  end public void registerCustomEditor(Class, java.beans.PropertyEditor)

  public void registerCustomEditor(Class, String, java.beans.PropertyEditor):
                    ALOAD_1     // Ljava/lang/Class; requiredType   (line 277)
                    IFNONNULL L0
                    ALOAD_2     // Ljava/lang/String; propertyPath
                    IFNONNULL L0
                    NEW java.lang.IllegalArgumentException   (line 278)
                    DUP
                    LDC "Either requiredType or propertyPath is required"
                    INVOKESPECIAL java.lang.IllegalArgumentException.<init> (Ljava/lang/String;)V
                    ATHROW
                L0: ALOAD_2     // Ljava/lang/String; propertyPath   (line 280)
                    IFNULL L2
                    ALOAD_0     // Lorg/springframework/beans/PropertyEditorRegistrySupport; this   (line 281)
                    GETFIELD org.springframework.beans.PropertyEditorRegistrySupport.customEditorsForPath Ljava/util/Map;
                    IFNONNULL L1
                    ALOAD_0     // Lorg/springframework/beans/PropertyEditorRegistrySupport; this   (line 282)
                    NEW java.util.LinkedHashMap
                    DUP
                    BIPUSH 16
                    INVOKESPECIAL java.util.LinkedHashMap.<init> (I)V
                    PUTFIELD org.springframework.beans.PropertyEditorRegistrySupport.customEditorsForPath Ljava/util/Map;
                L1: ALOAD_0     // Lorg/springframework/beans/PropertyEditorRegistrySupport; this   (line 284)
                    GETFIELD org.springframework.beans.PropertyEditorRegistrySupport.customEditorsForPath Ljava/util/Map;
                    ALOAD_2     // Ljava/lang/String; propertyPath
                    NEW org.springframework.beans.PropertyEditorRegistrySupport$CustomEditorHolder
                    DUP
                    ALOAD_3     // Ljava/beans/PropertyEditor; propertyEditor
                    ALOAD_1     // Ljava/lang/Class; requiredType
                    ACONST_NULL
                    INVOKESPECIAL org.springframework.beans.PropertyEditorRegistrySupport$CustomEditorHolder.<init> (Ljava/beans/PropertyEditor;Ljava/lang/Class;Lorg/springframework/beans/PropertyEditorRegistrySupport$CustomEditorHolder;)V
                    INVOKEINTERFACE java.util.Map.put (Ljava/lang/Object;Ljava/lang/Object;)Ljava/lang/Object;
                    POP
                    GOTO L4
                L2: ALOAD_0     // Lorg/springframework/beans/PropertyEditorRegistrySupport; this   (line 287)
                    GETFIELD org.springframework.beans.PropertyEditorRegistrySupport.customEditors Ljava/util/Map;
                    IFNONNULL L3
                    ALOAD_0     // Lorg/springframework/beans/PropertyEditorRegistrySupport; this   (line 288)
                    NEW java.util.LinkedHashMap
                    DUP
                    BIPUSH 16
                    INVOKESPECIAL java.util.LinkedHashMap.<init> (I)V
                    PUTFIELD org.springframework.beans.PropertyEditorRegistrySupport.customEditors Ljava/util/Map;
                L3: ALOAD_0     // Lorg/springframework/beans/PropertyEditorRegistrySupport; this   (line 290)
                    GETFIELD org.springframework.beans.PropertyEditorRegistrySupport.customEditors Ljava/util/Map;
                    ALOAD_1     // Ljava/lang/Class; requiredType
                    ALOAD_3     // Ljava/beans/PropertyEditor; propertyEditor
                    INVOKEINTERFACE java.util.Map.put (Ljava/lang/Object;Ljava/lang/Object;)Ljava/lang/Object;
                    POP
                    ALOAD_0     // Lorg/springframework/beans/PropertyEditorRegistrySupport; this   (line 291)
                    ACONST_NULL
                    PUTFIELD org.springframework.beans.PropertyEditorRegistrySupport.customEditorCache Ljava/util/Map;
                L4: RETURN   (line 293)
  end public void registerCustomEditor(Class, String, java.beans.PropertyEditor)

  public void registerSharedEditor(Class, java.beans.PropertyEditor):
                    ALOAD_0     // Lorg/springframework/beans/PropertyEditorRegistrySupport; this   (line 305)
                    ALOAD_1     // Ljava/lang/Class; requiredType
                    ACONST_NULL
                    ALOAD_2     // Ljava/beans/PropertyEditor; propertyEditor
                    INVOKEVIRTUAL org.springframework.beans.PropertyEditorRegistrySupport.registerCustomEditor (Ljava/lang/Class;Ljava/lang/String;Ljava/beans/PropertyEditor;)V
                    ALOAD_0     // Lorg/springframework/beans/PropertyEditorRegistrySupport; this   (line 306)
                    GETFIELD org.springframework.beans.PropertyEditorRegistrySupport.sharedEditors Ljava/util/Set;
                    IFNONNULL L0
                    ALOAD_0     // Lorg/springframework/beans/PropertyEditorRegistrySupport; this   (line 307)
                    NEW java.util.HashSet
                    DUP
                    INVOKESPECIAL java.util.HashSet.<init> ()V
                    PUTFIELD org.springframework.beans.PropertyEditorRegistrySupport.sharedEditors Ljava/util/Set;
                L0: ALOAD_0     // Lorg/springframework/beans/PropertyEditorRegistrySupport; this   (line 309)
                    GETFIELD org.springframework.beans.PropertyEditorRegistrySupport.sharedEditors Ljava/util/Set;
                    ALOAD_2     // Ljava/beans/PropertyEditor; propertyEditor
                    INVOKEINTERFACE java.util.Set.add (Ljava/lang/Object;)Z
                    POP
                    RETURN   (line 310)
  end public void registerSharedEditor(Class, java.beans.PropertyEditor)

  public boolean isSharedEditor(java.beans.PropertyEditor):
                    ALOAD_0     // Lorg/springframework/beans/PropertyEditorRegistrySupport; this   (line 319)
                    GETFIELD org.springframework.beans.PropertyEditorRegistrySupport.sharedEditors Ljava/util/Set;
                    IFNULL L0
                    ALOAD_0     // Lorg/springframework/beans/PropertyEditorRegistrySupport; this
                    GETFIELD org.springframework.beans.PropertyEditorRegistrySupport.sharedEditors Ljava/util/Set;
                    ALOAD_1     // Ljava/beans/PropertyEditor; propertyEditor
                    INVOKEINTERFACE java.util.Set.contains (Ljava/lang/Object;)Z
                    IFEQ L0
                    ICONST_1
                    IRETURN
                L0: ICONST_0
                    IRETURN
  end public boolean isSharedEditor(java.beans.PropertyEditor)

  public java.beans.PropertyEditor findCustomEditor(Class, String):
                    ALOAD_1     // Ljava/lang/Class; requiredType   (line 323)
                    ASTORE_3
                    ALOAD_2     // Ljava/lang/String; propertyPath   (line 324)
                    IFNULL L4
                    ALOAD_0     // Lorg/springframework/beans/PropertyEditorRegistrySupport; this   (line 325)
                    GETFIELD org.springframework.beans.PropertyEditorRegistrySupport.customEditorsForPath Ljava/util/Map;
                    IFNULL L3
                    ALOAD_0     // Lorg/springframework/beans/PropertyEditorRegistrySupport; this   (line 327)
                    ALOAD_2     // Ljava/lang/String; propertyPath
                    ALOAD_1     // Ljava/lang/Class; requiredType
                    INVOKESPECIAL org.springframework.beans.PropertyEditorRegistrySupport.getCustomEditor (Ljava/lang/String;Ljava/lang/Class;)Ljava/beans/PropertyEditor;
                    ASTORE 4
                    ALOAD 4     // Ljava/beans/PropertyEditor; editor   (line 328)
                    IFNONNULL L2
                    NEW java.util.LinkedList   (line 329)
                    DUP
                    INVOKESPECIAL java.util.LinkedList.<init> ()V
                    ASTORE 5
                    ALOAD_0     // Lorg/springframework/beans/PropertyEditorRegistrySupport; this   (line 330)
                    ALOAD 5     // Ljava/util/List; strippedPaths
                    LDC_W ""
                    ALOAD_2     // Ljava/lang/String; propertyPath
                    INVOKESPECIAL org.springframework.beans.PropertyEditorRegistrySupport.addStrippedPropertyPaths (Ljava/util/List;Ljava/lang/String;Ljava/lang/String;)V
                    ALOAD 5     // Ljava/util/List; strippedPaths   (line 331)
                    INVOKEINTERFACE java.util.List.iterator ()Ljava/util/Iterator;
                    ASTORE 6
                    GOTO L1
                L0: ALOAD 6     // Ljava/util/Iterator; it   (line 332)
                    INVOKEINTERFACE java.util.Iterator.next ()Ljava/lang/Object;
                    CHECKCAST java.lang.String
                    ASTORE 7
                    ALOAD_0     // Lorg/springframework/beans/PropertyEditorRegistrySupport; this   (line 333)
                    ALOAD 7     // Ljava/lang/String; strippedPath
                    ALOAD_1     // Ljava/lang/Class; requiredType
                    INVOKESPECIAL org.springframework.beans.PropertyEditorRegistrySupport.getCustomEditor (Ljava/lang/String;Ljava/lang/Class;)Ljava/beans/PropertyEditor;
                    ASTORE 4     // Ljava/beans/PropertyEditor; editor
                L1: ALOAD 6     // Ljava/util/Iterator; it   (line 331)
                    INVOKEINTERFACE java.util.Iterator.hasNext ()Z
                    IFEQ L2
                    ALOAD 4     // Ljava/beans/PropertyEditor; editor
                    IFNULL L0
                L2: ALOAD 4     // Ljava/beans/PropertyEditor; editor   (line 336)
                    IFNULL L3
                    ALOAD 4     // Ljava/beans/PropertyEditor; editor   (line 337)
                    ARETURN
                L3: ALOAD_1     // Ljava/lang/Class; requiredType   (line 340)
                    IFNONNULL L4
                    ALOAD_0     // Lorg/springframework/beans/PropertyEditorRegistrySupport; this   (line 341)
                    ALOAD_2     // Ljava/lang/String; propertyPath
                    INVOKEVIRTUAL org.springframework.beans.PropertyEditorRegistrySupport.getPropertyType (Ljava/lang/String;)Ljava/lang/Class;
                    ASTORE_3     // Ljava/lang/Class; requiredTypeToUse
                L4: ALOAD_0     // Lorg/springframework/beans/PropertyEditorRegistrySupport; this   (line 345)
                    ALOAD_3     // Ljava/lang/Class; requiredTypeToUse
                    INVOKESPECIAL org.springframework.beans.PropertyEditorRegistrySupport.getCustomEditor (Ljava/lang/Class;)Ljava/beans/PropertyEditor;
                    ARETURN
  end public java.beans.PropertyEditor findCustomEditor(Class, String)

  public boolean hasCustomEditorForElement(Class, String):
                    ALOAD_2     // Ljava/lang/String; propertyPath   (line 358)
                    IFNULL L2
                    ALOAD_0     // Lorg/springframework/beans/PropertyEditorRegistrySupport; this
                    GETFIELD org.springframework.beans.PropertyEditorRegistrySupport.customEditorsForPath Ljava/util/Map;
                    IFNULL L2
                    ALOAD_0     // Lorg/springframework/beans/PropertyEditorRegistrySupport; this   (line 359)
                    GETFIELD org.springframework.beans.PropertyEditorRegistrySupport.customEditorsForPath Ljava/util/Map;
                    INVOKEINTERFACE java.util.Map.entrySet ()Ljava/util/Set;
                    INVOKEINTERFACE java.util.Set.iterator ()Ljava/util/Iterator;
                    ASTORE 4
                    GOTO L1
                L0: ALOAD 4
                    INVOKEINTERFACE java.util.Iterator.next ()Ljava/lang/Object;
                    CHECKCAST java.util.Map$Entry
                    ASTORE_3
                    ALOAD_3     // Ljava/util/Map$Entry; entry   (line 360)
                    INVOKEINTERFACE java.util.Map$Entry.getKey ()Ljava/lang/Object;
                    CHECKCAST java.lang.String
                    ALOAD_2     // Ljava/lang/String; propertyPath
                    INVOKESTATIC org.springframework.beans.PropertyAccessorUtils.matchesProperty (Ljava/lang/String;Ljava/lang/String;)Z
                    IFEQ L1
                    ALOAD_3     // Ljava/util/Map$Entry; entry   (line 361)
                    INVOKEINTERFACE java.util.Map$Entry.getValue ()Ljava/lang/Object;
                    CHECKCAST org.springframework.beans.PropertyEditorRegistrySupport$CustomEditorHolder
                    ALOAD_1     // Ljava/lang/Class; elementType
                    INVOKESTATIC org.springframework.beans.PropertyEditorRegistrySupport$CustomEditorHolder.access$1 (Lorg/springframework/beans/PropertyEditorRegistrySupport$CustomEditorHolder;Ljava/lang/Class;)Ljava/beans/PropertyEditor;
                    IFNULL L1
                    ICONST_1   (line 362)
                    IRETURN
                L1: ALOAD 4   (line 359)
                    INVOKEINTERFACE java.util.Iterator.hasNext ()Z
                    IFNE L0
                L2: ALOAD_1     // Ljava/lang/Class; elementType   (line 368)
                    IFNULL L3
                    ALOAD_0     // Lorg/springframework/beans/PropertyEditorRegistrySupport; this
                    GETFIELD org.springframework.beans.PropertyEditorRegistrySupport.customEditors Ljava/util/Map;
                    IFNULL L3
                    ALOAD_0     // Lorg/springframework/beans/PropertyEditorRegistrySupport; this
                    GETFIELD org.springframework.beans.PropertyEditorRegistrySupport.customEditors Ljava/util/Map;
                    ALOAD_1     // Ljava/lang/Class; elementType
                    INVOKEINTERFACE java.util.Map.containsKey (Ljava/lang/Object;)Z
                    IFEQ L3
                    ICONST_1
                    IRETURN
                L3: ICONST_0
                    IRETURN
  end public boolean hasCustomEditorForElement(Class, String)

  protected Class getPropertyType(String):
                    ACONST_NULL   (line 383)
                    ARETURN
  end protected Class getPropertyType(String)

  private java.beans.PropertyEditor getCustomEditor(String, Class):
                    ALOAD_0     // Lorg/springframework/beans/PropertyEditorRegistrySupport; this   (line 393)
                    GETFIELD org.springframework.beans.PropertyEditorRegistrySupport.customEditorsForPath Ljava/util/Map;
                    ALOAD_1     // Ljava/lang/String; propertyName
                    INVOKEINTERFACE java.util.Map.get (Ljava/lang/Object;)Ljava/lang/Object;
                    CHECKCAST org.springframework.beans.PropertyEditorRegistrySupport$CustomEditorHolder
                    ASTORE_3
                    ALOAD_3     // Lorg/springframework/beans/PropertyEditorRegistrySupport$CustomEditorHolder; holder   (line 394)
                    IFNULL L0
                    ALOAD_3     // Lorg/springframework/beans/PropertyEditorRegistrySupport$CustomEditorHolder; holder
                    ALOAD_2     // Ljava/lang/Class; requiredType
                    INVOKESTATIC org.springframework.beans.PropertyEditorRegistrySupport$CustomEditorHolder.access$1 (Lorg/springframework/beans/PropertyEditorRegistrySupport$CustomEditorHolder;Ljava/lang/Class;)Ljava/beans/PropertyEditor;
                    GOTO L1
                L0: ACONST_NULL
                L1: ARETURN
  end private java.beans.PropertyEditor getCustomEditor(String, Class)

  private java.beans.PropertyEditor getCustomEditor(Class):
                    ALOAD_1     // Ljava/lang/Class; requiredType   (line 406)
                    IFNULL L0
                    ALOAD_0     // Lorg/springframework/beans/PropertyEditorRegistrySupport; this
                    GETFIELD org.springframework.beans.PropertyEditorRegistrySupport.customEditors Ljava/util/Map;
                    IFNONNULL L1
                L0: ACONST_NULL   (line 407)
                    ARETURN
                L1: ALOAD_0     // Lorg/springframework/beans/PropertyEditorRegistrySupport; this   (line 410)
                    GETFIELD org.springframework.beans.PropertyEditorRegistrySupport.customEditors Ljava/util/Map;
                    ALOAD_1     // Ljava/lang/Class; requiredType
                    INVOKEINTERFACE java.util.Map.get (Ljava/lang/Object;)Ljava/lang/Object;
                    CHECKCAST java.beans.PropertyEditor
                    ASTORE_2
                    ALOAD_2     // Ljava/beans/PropertyEditor; editor   (line 411)
                    IFNONNULL L6
                    ALOAD_0     // Lorg/springframework/beans/PropertyEditorRegistrySupport; this   (line 413)
                    GETFIELD org.springframework.beans.PropertyEditorRegistrySupport.customEditorCache Ljava/util/Map;
                    IFNULL L2
                    ALOAD_0     // Lorg/springframework/beans/PropertyEditorRegistrySupport; this   (line 414)
                    GETFIELD org.springframework.beans.PropertyEditorRegistrySupport.customEditorCache Ljava/util/Map;
                    ALOAD_1     // Ljava/lang/Class; requiredType
                    INVOKEINTERFACE java.util.Map.get (Ljava/lang/Object;)Ljava/lang/Object;
                    CHECKCAST java.beans.PropertyEditor
                    ASTORE_2     // Ljava/beans/PropertyEditor; editor
                L2: ALOAD_2     // Ljava/beans/PropertyEditor; editor   (line 416)
                    IFNONNULL L6
                    ALOAD_0     // Lorg/springframework/beans/PropertyEditorRegistrySupport; this   (line 418)
                    GETFIELD org.springframework.beans.PropertyEditorRegistrySupport.customEditors Ljava/util/Map;
                    INVOKEINTERFACE java.util.Map.keySet ()Ljava/util/Set;
                    INVOKEINTERFACE java.util.Set.iterator ()Ljava/util/Iterator;
                    ASTORE_3
                    GOTO L5
                L3: ALOAD_3     // Ljava/util/Iterator; it   (line 419)
                    INVOKEINTERFACE java.util.Iterator.next ()Ljava/lang/Object;
                    CHECKCAST java.lang.Class
                    ASTORE 4
                    ALOAD 4     // Ljava/lang/Class; key   (line 420)
                    ALOAD_1     // Ljava/lang/Class; requiredType
                    INVOKEVIRTUAL java.lang.Class.isAssignableFrom (Ljava/lang/Class;)Z
                    IFEQ L5
                    ALOAD_0     // Lorg/springframework/beans/PropertyEditorRegistrySupport; this   (line 421)
                    GETFIELD org.springframework.beans.PropertyEditorRegistrySupport.customEditors Ljava/util/Map;
                    ALOAD 4     // Ljava/lang/Class; key
                    INVOKEINTERFACE java.util.Map.get (Ljava/lang/Object;)Ljava/lang/Object;
                    CHECKCAST java.beans.PropertyEditor
                    ASTORE_2     // Ljava/beans/PropertyEditor; editor
                    ALOAD_0     // Lorg/springframework/beans/PropertyEditorRegistrySupport; this   (line 424)
                    GETFIELD org.springframework.beans.PropertyEditorRegistrySupport.customEditorCache Ljava/util/Map;
                    IFNONNULL L4
                    ALOAD_0     // Lorg/springframework/beans/PropertyEditorRegistrySupport; this   (line 425)
                    NEW java.util.HashMap
                    DUP
                    INVOKESPECIAL java.util.HashMap.<init> ()V
                    PUTFIELD org.springframework.beans.PropertyEditorRegistrySupport.customEditorCache Ljava/util/Map;
                L4: ALOAD_0     // Lorg/springframework/beans/PropertyEditorRegistrySupport; this   (line 427)
                    GETFIELD org.springframework.beans.PropertyEditorRegistrySupport.customEditorCache Ljava/util/Map;
                    ALOAD_1     // Ljava/lang/Class; requiredType
                    ALOAD_2     // Ljava/beans/PropertyEditor; editor
                    INVOKEINTERFACE java.util.Map.put (Ljava/lang/Object;Ljava/lang/Object;)Ljava/lang/Object;
                    POP
                L5: ALOAD_3     // Ljava/util/Iterator; it   (line 418)
                    INVOKEINTERFACE java.util.Iterator.hasNext ()Z
                    IFEQ L6
                    ALOAD_2     // Ljava/beans/PropertyEditor; editor
                    IFNULL L3
                L6: ALOAD_2     // Ljava/beans/PropertyEditor; editor   (line 432)
                    ARETURN
  end private java.beans.PropertyEditor getCustomEditor(Class)

  protected Class guessPropertyTypeFromEditors(String):
                    ALOAD_0     // Lorg/springframework/beans/PropertyEditorRegistrySupport; this   (line 442)
                    GETFIELD org.springframework.beans.PropertyEditorRegistrySupport.customEditorsForPath Ljava/util/Map;
                    IFNULL L3
                    ALOAD_0     // Lorg/springframework/beans/PropertyEditorRegistrySupport; this   (line 443)
                    GETFIELD org.springframework.beans.PropertyEditorRegistrySupport.customEditorsForPath Ljava/util/Map;
                    ALOAD_1     // Ljava/lang/String; propertyName
                    INVOKEINTERFACE java.util.Map.get (Ljava/lang/Object;)Ljava/lang/Object;
                    CHECKCAST org.springframework.beans.PropertyEditorRegistrySupport$CustomEditorHolder
                    ASTORE_2
                    ALOAD_2     // Lorg/springframework/beans/PropertyEditorRegistrySupport$CustomEditorHolder; editorHolder   (line 444)
                    IFNONNULL L2
                    NEW java.util.LinkedList   (line 445)
                    DUP
                    INVOKESPECIAL java.util.LinkedList.<init> ()V
                    ASTORE_3
                    ALOAD_0     // Lorg/springframework/beans/PropertyEditorRegistrySupport; this   (line 446)
                    ALOAD_3     // Ljava/util/List; strippedPaths
                    LDC_W ""
                    ALOAD_1     // Ljava/lang/String; propertyName
                    INVOKESPECIAL org.springframework.beans.PropertyEditorRegistrySupport.addStrippedPropertyPaths (Ljava/util/List;Ljava/lang/String;Ljava/lang/String;)V
                    ALOAD_3     // Ljava/util/List; strippedPaths   (line 447)
                    INVOKEINTERFACE java.util.List.iterator ()Ljava/util/Iterator;
                    ASTORE 4
                    GOTO L1
                L0: ALOAD 4     // Ljava/util/Iterator; it   (line 448)
                    INVOKEINTERFACE java.util.Iterator.next ()Ljava/lang/Object;
                    CHECKCAST java.lang.String
                    ASTORE 5
                    ALOAD_0     // Lorg/springframework/beans/PropertyEditorRegistrySupport; this   (line 449)
                    GETFIELD org.springframework.beans.PropertyEditorRegistrySupport.customEditorsForPath Ljava/util/Map;
                    ALOAD 5     // Ljava/lang/String; strippedName
                    INVOKEINTERFACE java.util.Map.get (Ljava/lang/Object;)Ljava/lang/Object;
                    CHECKCAST org.springframework.beans.PropertyEditorRegistrySupport$CustomEditorHolder
                    ASTORE_2     // Lorg/springframework/beans/PropertyEditorRegistrySupport$CustomEditorHolder; editorHolder
                L1: ALOAD 4     // Ljava/util/Iterator; it   (line 447)
                    INVOKEINTERFACE java.util.Iterator.hasNext ()Z
                    IFEQ L2
                    ALOAD_2     // Lorg/springframework/beans/PropertyEditorRegistrySupport$CustomEditorHolder; editorHolder
                    IFNULL L0
                L2: ALOAD_2     // Lorg/springframework/beans/PropertyEditorRegistrySupport$CustomEditorHolder; editorHolder   (line 452)
                    IFNULL L3
                    ALOAD_2     // Lorg/springframework/beans/PropertyEditorRegistrySupport$CustomEditorHolder; editorHolder   (line 453)
                    INVOKESTATIC org.springframework.beans.PropertyEditorRegistrySupport$CustomEditorHolder.access$2 (Lorg/springframework/beans/PropertyEditorRegistrySupport$CustomEditorHolder;)Ljava/lang/Class;
                    ARETURN
                L3: ACONST_NULL   (line 456)
                    ARETURN
  end protected Class guessPropertyTypeFromEditors(String)

  protected void copyCustomEditorsTo(org.springframework.beans.PropertyEditorRegistry, String):
                    ALOAD_2     // Ljava/lang/String; nestedProperty   (line 468)
                    IFNULL L0
                    ALOAD_2     // Ljava/lang/String; nestedProperty
                    INVOKESTATIC org.springframework.beans.PropertyAccessorUtils.getPropertyName (Ljava/lang/String;)Ljava/lang/String;
                    GOTO L1
                L0: ACONST_NULL
                L1: ASTORE_3   (line 467)
                    ALOAD_0     // Lorg/springframework/beans/PropertyEditorRegistrySupport; this   (line 469)
                    GETFIELD org.springframework.beans.PropertyEditorRegistrySupport.customEditors Ljava/util/Map;
                    IFNULL L4
                    ALOAD_0     // Lorg/springframework/beans/PropertyEditorRegistrySupport; this   (line 470)
                    GETFIELD org.springframework.beans.PropertyEditorRegistrySupport.customEditors Ljava/util/Map;
                    INVOKEINTERFACE java.util.Map.entrySet ()Ljava/util/Set;
                    INVOKEINTERFACE java.util.Set.iterator ()Ljava/util/Iterator;
                    ASTORE 5
                    GOTO L3
                L2: ALOAD 5
                    INVOKEINTERFACE java.util.Iterator.next ()Ljava/lang/Object;
                    CHECKCAST java.util.Map$Entry
                    ASTORE 4
                    ALOAD_1     // Lorg/springframework/beans/PropertyEditorRegistry; target   (line 471)
                    ALOAD 4     // Ljava/util/Map$Entry; entry
                    INVOKEINTERFACE java.util.Map$Entry.getKey ()Ljava/lang/Object;
                    CHECKCAST java.lang.Class
                    ALOAD 4     // Ljava/util/Map$Entry; entry
                    INVOKEINTERFACE java.util.Map$Entry.getValue ()Ljava/lang/Object;
                    CHECKCAST java.beans.PropertyEditor
                    INVOKEINTERFACE org.springframework.beans.PropertyEditorRegistry.registerCustomEditor (Ljava/lang/Class;Ljava/beans/PropertyEditor;)V
                L3: ALOAD 5   (line 470)
                    INVOKEINTERFACE java.util.Iterator.hasNext ()Z
                    IFNE L2
                L4: ALOAD_0     // Lorg/springframework/beans/PropertyEditorRegistrySupport; this   (line 474)
                    GETFIELD org.springframework.beans.PropertyEditorRegistrySupport.customEditorsForPath Ljava/util/Map;
                    IFNULL L9
                    ALOAD_0     // Lorg/springframework/beans/PropertyEditorRegistrySupport; this   (line 475)
                    GETFIELD org.springframework.beans.PropertyEditorRegistrySupport.customEditorsForPath Ljava/util/Map;
                    INVOKEINTERFACE java.util.Map.entrySet ()Ljava/util/Set;
                    INVOKEINTERFACE java.util.Set.iterator ()Ljava/util/Iterator;
                    ASTORE 5
                    GOTO L8
                L5: ALOAD 5
                    INVOKEINTERFACE java.util.Iterator.next ()Ljava/lang/Object;
                    CHECKCAST java.util.Map$Entry
                    ASTORE 4
                    ALOAD 4     // Ljava/util/Map$Entry; entry   (line 476)
                    INVOKEINTERFACE java.util.Map$Entry.getKey ()Ljava/lang/Object;
                    CHECKCAST java.lang.String
                    ASTORE 6
                    ALOAD 4     // Ljava/util/Map$Entry; entry   (line 477)
                    INVOKEINTERFACE java.util.Map$Entry.getValue ()Ljava/lang/Object;
                    CHECKCAST org.springframework.beans.PropertyEditorRegistrySupport$CustomEditorHolder
                    ASTORE 7
                    ALOAD_2     // Ljava/lang/String; nestedProperty   (line 478)
                    IFNULL L7
                    ALOAD 6     // Ljava/lang/String; editorPath   (line 479)
                    INVOKESTATIC org.springframework.beans.PropertyAccessorUtils.getFirstNestedPropertySeparatorIndex (Ljava/lang/String;)I
                    ISTORE 8
                    ILOAD 8     // I pos   (line 480)
                    ICONST_M1
                    IF_ICMPEQ L8
                    ALOAD 6     // Ljava/lang/String; editorPath   (line 481)
                    ICONST_0
                    ILOAD 8     // I pos
                    INVOKEVIRTUAL java.lang.String.substring (II)Ljava/lang/String;
                    ASTORE 9
                    ALOAD 6     // Ljava/lang/String; editorPath   (line 482)
                    ILOAD 8     // I pos
                    ICONST_1
                    IADD
                    INVOKEVIRTUAL java.lang.String.substring (I)Ljava/lang/String;
                    ASTORE 10
                    ALOAD 9     // Ljava/lang/String; editorNestedProperty   (line 483)
                    ALOAD_2     // Ljava/lang/String; nestedProperty
                    INVOKEVIRTUAL java.lang.String.equals (Ljava/lang/Object;)Z
                    IFNE L6
                    ALOAD 9     // Ljava/lang/String; editorNestedProperty
                    ALOAD_3     // Ljava/lang/String; actualPropertyName
                    INVOKEVIRTUAL java.lang.String.equals (Ljava/lang/Object;)Z
                    IFEQ L8
                L6: ALOAD_1     // Lorg/springframework/beans/PropertyEditorRegistry; target   (line 484)
                    ALOAD 7     // Lorg/springframework/beans/PropertyEditorRegistrySupport$CustomEditorHolder; editorHolder   (line 485)
                    INVOKESTATIC org.springframework.beans.PropertyEditorRegistrySupport$CustomEditorHolder.access$2 (Lorg/springframework/beans/PropertyEditorRegistrySupport$CustomEditorHolder;)Ljava/lang/Class;
                    ALOAD 10     // Ljava/lang/String; editorNestedPath
                    ALOAD 7     // Lorg/springframework/beans/PropertyEditorRegistrySupport$CustomEditorHolder; editorHolder
                    INVOKESTATIC org.springframework.beans.PropertyEditorRegistrySupport$CustomEditorHolder.access$3 (Lorg/springframework/beans/PropertyEditorRegistrySupport$CustomEditorHolder;)Ljava/beans/PropertyEditor;
                    INVOKEINTERFACE org.springframework.beans.PropertyEditorRegistry.registerCustomEditor (Ljava/lang/Class;Ljava/lang/String;Ljava/beans/PropertyEditor;)V   (line 484)
                    GOTO L8
                L7: ALOAD_1     // Lorg/springframework/beans/PropertyEditorRegistry; target   (line 490)
                    ALOAD 7     // Lorg/springframework/beans/PropertyEditorRegistrySupport$CustomEditorHolder; editorHolder   (line 491)
                    INVOKESTATIC org.springframework.beans.PropertyEditorRegistrySupport$CustomEditorHolder.access$2 (Lorg/springframework/beans/PropertyEditorRegistrySupport$CustomEditorHolder;)Ljava/lang/Class;
                    ALOAD 6     // Ljava/lang/String; editorPath
                    ALOAD 7     // Lorg/springframework/beans/PropertyEditorRegistrySupport$CustomEditorHolder; editorHolder
                    INVOKESTATIC org.springframework.beans.PropertyEditorRegistrySupport$CustomEditorHolder.access$3 (Lorg/springframework/beans/PropertyEditorRegistrySupport$CustomEditorHolder;)Ljava/beans/PropertyEditor;
                    INVOKEINTERFACE org.springframework.beans.PropertyEditorRegistry.registerCustomEditor (Ljava/lang/Class;Ljava/lang/String;Ljava/beans/PropertyEditor;)V   (line 490)
                L8: ALOAD 5   (line 475)
                    INVOKEINTERFACE java.util.Iterator.hasNext ()Z
                    IFNE L5
                L9: RETURN   (line 495)
  end protected void copyCustomEditorsTo(org.springframework.beans.PropertyEditorRegistry, String)

  private void addStrippedPropertyPaths(java.util.List, String, String):
                    ALOAD_3     // Ljava/lang/String; propertyPath   (line 506)
                    BIPUSH 91
                    INVOKEVIRTUAL java.lang.String.indexOf (I)I
                    ISTORE 4
                    ILOAD 4     // I startIndex   (line 507)
                    ICONST_M1
                    IF_ICMPEQ L0
                    ALOAD_3     // Ljava/lang/String; propertyPath   (line 508)
                    BIPUSH 93
                    INVOKEVIRTUAL java.lang.String.indexOf (I)I
                    ISTORE 5
                    ILOAD 5     // I endIndex   (line 509)
                    ICONST_M1
                    IF_ICMPEQ L0
                    ALOAD_3     // Ljava/lang/String; propertyPath   (line 510)
                    ICONST_0
                    ILOAD 4     // I startIndex
                    INVOKEVIRTUAL java.lang.String.substring (II)Ljava/lang/String;
                    ASTORE 6
                    ALOAD_3     // Ljava/lang/String; propertyPath   (line 511)
                    ILOAD 4     // I startIndex
                    ILOAD 5     // I endIndex
                    ICONST_1
                    IADD
                    INVOKEVIRTUAL java.lang.String.substring (II)Ljava/lang/String;
                    ASTORE 7
                    ALOAD_3     // Ljava/lang/String; propertyPath   (line 512)
                    ILOAD 5     // I endIndex
                    ICONST_1
                    IADD
                    ALOAD_3     // Ljava/lang/String; propertyPath
                    INVOKEVIRTUAL java.lang.String.length ()I
                    INVOKEVIRTUAL java.lang.String.substring (II)Ljava/lang/String;
                    ASTORE 8
                    ALOAD_1     // Ljava/util/List; strippedPaths   (line 514)
                    NEW java.lang.StringBuilder
                    DUP
                    ALOAD_2     // Ljava/lang/String; nestedPath
                    INVOKESTATIC java.lang.String.valueOf (Ljava/lang/Object;)Ljava/lang/String;
                    INVOKESPECIAL java.lang.StringBuilder.<init> (Ljava/lang/String;)V
                    ALOAD 6     // Ljava/lang/String; prefix
                    INVOKEVIRTUAL java.lang.StringBuilder.append (Ljava/lang/String;)Ljava/lang/StringBuilder;
                    ALOAD 8     // Ljava/lang/String; suffix
                    INVOKEVIRTUAL java.lang.StringBuilder.append (Ljava/lang/String;)Ljava/lang/StringBuilder;
                    INVOKEVIRTUAL java.lang.StringBuilder.toString ()Ljava/lang/String;
                    INVOKEINTERFACE java.util.List.add (Ljava/lang/Object;)Z
                    POP
                    ALOAD_0     // Lorg/springframework/beans/PropertyEditorRegistrySupport; this   (line 516)
                    ALOAD_1     // Ljava/util/List; strippedPaths
                    NEW java.lang.StringBuilder
                    DUP
                    ALOAD_2     // Ljava/lang/String; nestedPath
                    INVOKESTATIC java.lang.String.valueOf (Ljava/lang/Object;)Ljava/lang/String;
                    INVOKESPECIAL java.lang.StringBuilder.<init> (Ljava/lang/String;)V
                    ALOAD 6     // Ljava/lang/String; prefix
                    INVOKEVIRTUAL java.lang.StringBuilder.append (Ljava/lang/String;)Ljava/lang/StringBuilder;
                    INVOKEVIRTUAL java.lang.StringBuilder.toString ()Ljava/lang/String;
                    ALOAD 8     // Ljava/lang/String; suffix
                    INVOKESPECIAL org.springframework.beans.PropertyEditorRegistrySupport.addStrippedPropertyPaths (Ljava/util/List;Ljava/lang/String;Ljava/lang/String;)V
                    ALOAD_0     // Lorg/springframework/beans/PropertyEditorRegistrySupport; this   (line 518)
                    ALOAD_1     // Ljava/util/List; strippedPaths
                    NEW java.lang.StringBuilder
                    DUP
                    ALOAD_2     // Ljava/lang/String; nestedPath
                    INVOKESTATIC java.lang.String.valueOf (Ljava/lang/Object;)Ljava/lang/String;
                    INVOKESPECIAL java.lang.StringBuilder.<init> (Ljava/lang/String;)V
                    ALOAD 6     // Ljava/lang/String; prefix
                    INVOKEVIRTUAL java.lang.StringBuilder.append (Ljava/lang/String;)Ljava/lang/StringBuilder;
                    ALOAD 7     // Ljava/lang/String; key
                    INVOKEVIRTUAL java.lang.StringBuilder.append (Ljava/lang/String;)Ljava/lang/StringBuilder;
                    INVOKEVIRTUAL java.lang.StringBuilder.toString ()Ljava/lang/String;
                    ALOAD 8     // Ljava/lang/String; suffix
                    INVOKESPECIAL org.springframework.beans.PropertyEditorRegistrySupport.addStrippedPropertyPaths (Ljava/util/List;Ljava/lang/String;Ljava/lang/String;)V
                L0: RETURN   (line 521)
  end private void addStrippedPropertyPaths(java.util.List, String, String)

end public class org.springframework.beans.PropertyEditorRegistrySupport
 -- (NullPointerException) null
null
java.lang.NullPointerException

org.aspectj.bridge.AbortException: trouble in: 
public class org.springframework.beans.PropertyEditorRegistrySupport extends java.lang.Object implements org.springframework.beans.PropertyEditorRegistry:
  private org.springframework.core.convert.ConversionService conversionService
  private boolean defaultEditorsActive
  private boolean configValueEditorsActive
  private java.util.Map defaultEditors [Signature(Ljava/util/Map<Ljava/lang/Class<*>;Ljava/beans/PropertyEditor;>;)]
  private java.util.Map overriddenDefaultEditors [Signature(Ljava/util/Map<Ljava/lang/Class<*>;Ljava/beans/PropertyEditor;>;)]
  private java.util.Map customEditors [Signature(Ljava/util/Map<Ljava/lang/Class<*>;Ljava/beans/PropertyEditor;>;)]
  private java.util.Map customEditorsForPath [Signature(Ljava/util/Map<Ljava/lang/String;Lorg/springframework/beans/PropertyEditorRegistrySupport$CustomEditorHolder;>;)]
  private java.util.Set sharedEditors [Signature(Ljava/util/Set<Ljava/beans/PropertyEditor;>;)]
  private java.util.Map customEditorCache [Signature(Ljava/util/Map<Ljava/lang/Class<*>;Ljava/beans/PropertyEditor;>;)]
  public void <init>():
                    ALOAD_0     // Lorg/springframework/beans/PropertyEditorRegistrySupport; this   (line 86)
                    INVOKESPECIAL java.lang.Object.<init> ()V
    constructor-execution(void org.springframework.beans.PropertyEditorRegistrySupport.<init>())
    |               ALOAD_0     // Lorg/springframework/beans/PropertyEditorRegistrySupport; this   (line 90)
    |               ICONST_0
    |               PUTFIELD org.springframework.beans.PropertyEditorRegistrySupport.defaultEditorsActive Z
    |               ALOAD_0     // Lorg/springframework/beans/PropertyEditorRegistrySupport; this   (line 92)
    |               ICONST_0
    |               PUTFIELD org.springframework.beans.PropertyEditorRegistrySupport.configValueEditorsActive Z
    |               RETURN   (line 86)
    constructor-execution(void org.springframework.beans.PropertyEditorRegistrySupport.<init>())
  end public void <init>()

  public void setConversionService(org.springframework.core.convert.ConversionService):
                    ALOAD_0     // Lorg/springframework/beans/PropertyEditorRegistrySupport; this   (line 112)
                    ALOAD_1     // Lorg/springframework/core/convert/ConversionService; conversionService
                    PUTFIELD org.springframework.beans.PropertyEditorRegistrySupport.conversionService Lorg/springframework/core/convert/ConversionService;
                    RETURN   (line 113)
  end public void setConversionService(org.springframework.core.convert.ConversionService)

  public org.springframework.core.convert.ConversionService getConversionService():
                    ALOAD_0     // Lorg/springframework/beans/PropertyEditorRegistrySupport; this   (line 119)
                    GETFIELD org.springframework.beans.PropertyEditorRegistrySupport.conversionService Lorg/springframework/core/convert/ConversionService;
                    ARETURN
  end public org.springframework.core.convert.ConversionService getConversionService()

  protected void registerDefaultEditors():
                    ALOAD_0     // Lorg/springframework/beans/PropertyEditorRegistrySupport; this   (line 132)
                    ICONST_1
                    PUTFIELD org.springframework.beans.PropertyEditorRegistrySupport.defaultEditorsActive Z
                    RETURN   (line 133)
  end protected void registerDefaultEditors()

  public void useConfigValueEditors():
                    ALOAD_0     // Lorg/springframework/beans/PropertyEditorRegistrySupport; this   (line 143)
                    ICONST_1
                    PUTFIELD org.springframework.beans.PropertyEditorRegistrySupport.configValueEditorsActive Z
                    RETURN   (line 144)
  end public void useConfigValueEditors()

  public void overrideDefaultEditor(Class, java.beans.PropertyEditor):
                    ALOAD_0     // Lorg/springframework/beans/PropertyEditorRegistrySupport; this   (line 156)
                    GETFIELD org.springframework.beans.PropertyEditorRegistrySupport.overriddenDefaultEditors Ljava/util/Map;
                    IFNONNULL L0
                    ALOAD_0     // Lorg/springframework/beans/PropertyEditorRegistrySupport; this   (line 157)
                    NEW java.util.HashMap
                    DUP
                    INVOKESPECIAL java.util.HashMap.<init> ()V
                    PUTFIELD org.springframework.beans.PropertyEditorRegistrySupport.overriddenDefaultEditors Ljava/util/Map;
                L0: ALOAD_0     // Lorg/springframework/beans/PropertyEditorRegistrySupport; this   (line 159)
                    GETFIELD org.springframework.beans.PropertyEditorRegistrySupport.overriddenDefaultEditors Ljava/util/Map;
                    ALOAD_1     // Ljava/lang/Class; requiredType
                    ALOAD_2     // Ljava/beans/PropertyEditor; propertyEditor
                    INVOKEINTERFACE java.util.Map.put (Ljava/lang/Object;Ljava/lang/Object;)Ljava/lang/Object;
                    POP
                    RETURN   (line 160)
  end public void overrideDefaultEditor(Class, java.beans.PropertyEditor)

  public java.beans.PropertyEditor getDefaultEditor(Class):
                    ALOAD_0     // Lorg/springframework/beans/PropertyEditorRegistrySupport; this   (line 170)
                    GETFIELD org.springframework.beans.PropertyEditorRegistrySupport.defaultEditorsActive Z
                    IFNE L0
                    ACONST_NULL   (line 171)
                    ARETURN
                L0: ALOAD_0     // Lorg/springframework/beans/PropertyEditorRegistrySupport; this   (line 173)
                    GETFIELD org.springframework.beans.PropertyEditorRegistrySupport.overriddenDefaultEditors Ljava/util/Map;
                    IFNULL L1
                    ALOAD_0     // Lorg/springframework/beans/PropertyEditorRegistrySupport; this   (line 174)
                    GETFIELD org.springframework.beans.PropertyEditorRegistrySupport.overriddenDefaultEditors Ljava/util/Map;
                    ALOAD_1     // Ljava/lang/Class; requiredType
                    INVOKEINTERFACE java.util.Map.get (Ljava/lang/Object;)Ljava/lang/Object;
                    CHECKCAST java.beans.PropertyEditor
                    ASTORE_2
                    ALOAD_2     // Ljava/beans/PropertyEditor; editor   (line 175)
                    IFNULL L1
                    ALOAD_2     // Ljava/beans/PropertyEditor; editor   (line 176)
                    ARETURN
                L1: ALOAD_0     // Lorg/springframework/beans/PropertyEditorRegistrySupport; this   (line 179)
                    GETFIELD org.springframework.beans.PropertyEditorRegistrySupport.defaultEditors Ljava/util/Map;
                    IFNONNULL L2
                    ALOAD_0     // Lorg/springframework/beans/PropertyEditorRegistrySupport; this   (line 180)
                    INVOKESPECIAL org.springframework.beans.PropertyEditorRegistrySupport.createDefaultEditors ()V
                L2: ALOAD_0     // Lorg/springframework/beans/PropertyEditorRegistrySupport; this   (line 182)
                    GETFIELD org.springframework.beans.PropertyEditorRegistrySupport.defaultEditors Ljava/util/Map;
                    ALOAD_1     // Ljava/lang/Class; requiredType
                    INVOKEINTERFACE java.util.Map.get (Ljava/lang/Object;)Ljava/lang/Object;
                    CHECKCAST java.beans.PropertyEditor
                    ARETURN
  end public java.beans.PropertyEditor getDefaultEditor(Class)

  private void createDefaultEditors():
                    ALOAD_0     // Lorg/springframework/beans/PropertyEditorRegistrySupport; this   (line 189)
                    NEW java.util.HashMap
                    DUP
                    BIPUSH 64
                    INVOKESPECIAL java.util.HashMap.<init> (I)V
                    PUTFIELD org.springframework.beans.PropertyEditorRegistrySupport.defaultEditors Ljava/util/Map;
                    ALOAD_0     // Lorg/springframework/beans/PropertyEditorRegistrySupport; this   (line 193)
                    GETFIELD org.springframework.beans.PropertyEditorRegistrySupport.defaultEditors Ljava/util/Map;
                    LDC java.nio.charset.Charset
                    NEW org.springframework.beans.propertyeditors.CharsetEditor
                    DUP
                    INVOKESPECIAL org.springframework.beans.propertyeditors.CharsetEditor.<init> ()V
                    INVOKEINTERFACE java.util.Map.put (Ljava/lang/Object;Ljava/lang/Object;)Ljava/lang/Object;
                    POP
                    ALOAD_0     // Lorg/springframework/beans/PropertyEditorRegistrySupport; this   (line 194)
                    GETFIELD org.springframework.beans.PropertyEditorRegistrySupport.defaultEditors Ljava/util/Map;
                    LDC java.lang.Class
                    NEW org.springframework.beans.propertyeditors.ClassEditor
                    DUP
                    INVOKESPECIAL org.springframework.beans.propertyeditors.ClassEditor.<init> ()V
                    INVOKEINTERFACE java.util.Map.put (Ljava/lang/Object;Ljava/lang/Object;)Ljava/lang/Object;
                    POP
                    ALOAD_0     // Lorg/springframework/beans/PropertyEditorRegistrySupport; this   (line 195)
                    GETFIELD org.springframework.beans.PropertyEditorRegistrySupport.defaultEditors Ljava/util/Map;
                    LDC [Ljava.lang.Class;
                    NEW org.springframework.beans.propertyeditors.ClassArrayEditor
                    DUP
                    INVOKESPECIAL org.springframework.beans.propertyeditors.ClassArrayEditor.<init> ()V
                    INVOKEINTERFACE java.util.Map.put (Ljava/lang/Object;Ljava/lang/Object;)Ljava/lang/Object;
                    POP
                    ALOAD_0     // Lorg/springframework/beans/PropertyEditorRegistrySupport; this   (line 196)
                    GETFIELD org.springframework.beans.PropertyEditorRegistrySupport.defaultEditors Ljava/util/Map;
                    LDC java.util.Currency
                    NEW org.springframework.beans.propertyeditors.CurrencyEditor
                    DUP
                    INVOKESPECIAL org.springframework.beans.propertyeditors.CurrencyEditor.<init> ()V
                    INVOKEINTERFACE java.util.Map.put (Ljava/lang/Object;Ljava/lang/Object;)Ljava/lang/Object;
                    POP
                    ALOAD_0     // Lorg/springframework/beans/PropertyEditorRegistrySupport; this   (line 197)
                    GETFIELD org.springframework.beans.PropertyEditorRegistrySupport.defaultEditors Ljava/util/Map;
                    LDC java.io.File
                    NEW org.springframework.beans.propertyeditors.FileEditor
                    DUP
                    INVOKESPECIAL org.springframework.beans.propertyeditors.FileEditor.<init> ()V
                    INVOKEINTERFACE java.util.Map.put (Ljava/lang/Object;Ljava/lang/Object;)Ljava/lang/Object;
                    POP
                    ALOAD_0     // Lorg/springframework/beans/PropertyEditorRegistrySupport; this   (line 198)
                    GETFIELD org.springframework.beans.PropertyEditorRegistrySupport.defaultEditors Ljava/util/Map;
                    LDC java.io.InputStream
                    NEW org.springframework.beans.propertyeditors.InputStreamEditor
                    DUP
                    INVOKESPECIAL org.springframework.beans.propertyeditors.InputStreamEditor.<init> ()V
                    INVOKEINTERFACE java.util.Map.put (Ljava/lang/Object;Ljava/lang/Object;)Ljava/lang/Object;
                    POP
                    ALOAD_0     // Lorg/springframework/beans/PropertyEditorRegistrySupport; this   (line 199)
                    GETFIELD org.springframework.beans.PropertyEditorRegistrySupport.defaultEditors Ljava/util/Map;
                    LDC org.xml.sax.InputSource
                    NEW org.springframework.beans.propertyeditors.InputSourceEditor
                    DUP
                    INVOKESPECIAL org.springframework.beans.propertyeditors.InputSourceEditor.<init> ()V
                    INVOKEINTERFACE java.util.Map.put (Ljava/lang/Object;Ljava/lang/Object;)Ljava/lang/Object;
                    POP
                    ALOAD_0     // Lorg/springframework/beans/PropertyEditorRegistrySupport; this   (line 200)
                    GETFIELD org.springframework.beans.PropertyEditorRegistrySupport.defaultEditors Ljava/util/Map;
                    LDC java.util.Locale
                    NEW org.springframework.beans.propertyeditors.LocaleEditor
                    DUP
                    INVOKESPECIAL org.springframework.beans.propertyeditors.LocaleEditor.<init> ()V
                    INVOKEINTERFACE java.util.Map.put (Ljava/lang/Object;Ljava/lang/Object;)Ljava/lang/Object;
                    POP
                    ALOAD_0     // Lorg/springframework/beans/PropertyEditorRegistrySupport; this   (line 201)
                    GETFIELD org.springframework.beans.PropertyEditorRegistrySupport.defaultEditors Ljava/util/Map;
                    LDC java.util.regex.Pattern
                    NEW org.springframework.beans.propertyeditors.PatternEditor
                    DUP
                    INVOKESPECIAL org.springframework.beans.propertyeditors.PatternEditor.<init> ()V
                    INVOKEINTERFACE java.util.Map.put (Ljava/lang/Object;Ljava/lang/Object;)Ljava/lang/Object;
                    POP
                    ALOAD_0     // Lorg/springframework/beans/PropertyEditorRegistrySupport; this   (line 202)
                    GETFIELD org.springframework.beans.PropertyEditorRegistrySupport.defaultEditors Ljava/util/Map;
                    LDC java.util.Properties
                    NEW org.springframework.beans.propertyeditors.PropertiesEditor
                    DUP
                    INVOKESPECIAL org.springframework.beans.propertyeditors.PropertiesEditor.<init> ()V
                    INVOKEINTERFACE java.util.Map.put (Ljava/lang/Object;Ljava/lang/Object;)Ljava/lang/Object;
                    POP
                    ALOAD_0     // Lorg/springframework/beans/PropertyEditorRegistrySupport; this   (line 203)
                    GETFIELD org.springframework.beans.PropertyEditorRegistrySupport.defaultEditors Ljava/util/Map;
                    LDC [Lorg.springframework.core.io.Resource;
                    NEW org.springframework.core.io.support.ResourceArrayPropertyEditor
                    DUP
                    INVOKESPECIAL org.springframework.core.io.support.ResourceArrayPropertyEditor.<init> ()V
                    INVOKEINTERFACE java.util.Map.put (Ljava/lang/Object;Ljava/lang/Object;)Ljava/lang/Object;
                    POP
                    ALOAD_0     // Lorg/springframework/beans/PropertyEditorRegistrySupport; this   (line 204)
                    GETFIELD org.springframework.beans.PropertyEditorRegistrySupport.defaultEditors Ljava/util/Map;
                    LDC java.util.TimeZone
                    NEW org.springframework.beans.propertyeditors.TimeZoneEditor
                    DUP
                    INVOKESPECIAL org.springframework.beans.propertyeditors.TimeZoneEditor.<init> ()V
                    INVOKEINTERFACE java.util.Map.put (Ljava/lang/Object;Ljava/lang/Object;)Ljava/lang/Object;
                    POP
                    ALOAD_0     // Lorg/springframework/beans/PropertyEditorRegistrySupport; this   (line 205)
                    GETFIELD org.springframework.beans.PropertyEditorRegistrySupport.defaultEditors Ljava/util/Map;
                    LDC java.net.URI
                    NEW org.springframework.beans.propertyeditors.URIEditor
                    DUP
                    INVOKESPECIAL org.springframework.beans.propertyeditors.URIEditor.<init> ()V
                    INVOKEINTERFACE java.util.Map.put (Ljava/lang/Object;Ljava/lang/Object;)Ljava/lang/Object;
                    POP
                    ALOAD_0     // Lorg/springframework/beans/PropertyEditorRegistrySupport; this   (line 206)
                    GETFIELD org.springframework.beans.PropertyEditorRegistrySupport.defaultEditors Ljava/util/Map;
                    LDC java.net.URL
                    NEW org.springframework.beans.propertyeditors.URLEditor
                    DUP
                    INVOKESPECIAL org.springframework.beans.propertyeditors.URLEditor.<init> ()V
                    INVOKEINTERFACE java.util.Map.put (Ljava/lang/Object;Ljava/lang/Object;)Ljava/lang/Object;
                    POP
                    ALOAD_0     // Lorg/springframework/beans/PropertyEditorRegistrySupport; this   (line 207)
                    GETFIELD org.springframework.beans.PropertyEditorRegistrySupport.defaultEditors Ljava/util/Map;
                    LDC java.util.UUID
                    NEW org.springframework.beans.propertyeditors.UUIDEditor
                    DUP
                    INVOKESPECIAL org.springframework.beans.propertyeditors.UUIDEditor.<init> ()V
                    INVOKEINTERFACE java.util.Map.put (Ljava/lang/Object;Ljava/lang/Object;)Ljava/lang/Object;
                    POP
                    ALOAD_0     // Lorg/springframework/beans/PropertyEditorRegistrySupport; this   (line 211)
                    GETFIELD org.springframework.beans.PropertyEditorRegistrySupport.defaultEditors Ljava/util/Map;
                    LDC java.util.Collection
                    NEW org.springframework.beans.propertyeditors.CustomCollectionEditor
                    DUP
                    LDC java.util.Collection
                    INVOKESPECIAL org.springframework.beans.propertyeditors.CustomCollectionEditor.<init> (Ljava/lang/Class;)V
                    INVOKEINTERFACE java.util.Map.put (Ljava/lang/Object;Ljava/lang/Object;)Ljava/lang/Object;
                    POP
                    ALOAD_0     // Lorg/springframework/beans/PropertyEditorRegistrySupport; this   (line 212)
                    GETFIELD org.springframework.beans.PropertyEditorRegistrySupport.defaultEditors Ljava/util/Map;
                    LDC java.util.Set
                    NEW org.springframework.beans.propertyeditors.CustomCollectionEditor
                    DUP
                    LDC java.util.Set
                    INVOKESPECIAL org.springframework.beans.propertyeditors.CustomCollectionEditor.<init> (Ljava/lang/Class;)V
                    INVOKEINTERFACE java.util.Map.put (Ljava/lang/Object;Ljava/lang/Object;)Ljava/lang/Object;
                    POP
                    ALOAD_0     // Lorg/springframework/beans/PropertyEditorRegistrySupport; this   (line 213)
                    GETFIELD org.springframework.beans.PropertyEditorRegistrySupport.defaultEditors Ljava/util/Map;
                    LDC java.util.SortedSet
                    NEW org.springframework.beans.propertyeditors.CustomCollectionEditor
                    DUP
                    LDC java.util.SortedSet
                    INVOKESPECIAL org.springframework.beans.propertyeditors.CustomCollectionEditor.<init> (Ljava/lang/Class;)V
                    INVOKEINTERFACE java.util.Map.put (Ljava/lang/Object;Ljava/lang/Object;)Ljava/lang/Object;
                    POP
                    ALOAD_0     // Lorg/springframework/beans/PropertyEditorRegistrySupport; this   (line 214)
                    GETFIELD org.springframework.beans.PropertyEditorRegistrySupport.defaultEditors Ljava/util/Map;
                    LDC java.util.List
                    NEW org.springframework.beans.propertyeditors.CustomCollectionEditor
                    DUP
                    LDC java.util.List
                    INVOKESPECIAL org.springframework.beans.propertyeditors.CustomCollectionEditor.<init> (Ljava/lang/Class;)V
                    INVOKEINTERFACE java.util.Map.put (Ljava/lang/Object;Ljava/lang/Object;)Ljava/lang/Object;
                    POP
                    ALOAD_0     // Lorg/springframework/beans/PropertyEditorRegistrySupport; this   (line 215)
                    GETFIELD org.springframework.beans.PropertyEditorRegistrySupport.defaultEditors Ljava/util/Map;
                    LDC java.util.SortedMap
                    NEW org.springframework.beans.propertyeditors.CustomMapEditor
                    DUP
                    LDC java.util.SortedMap
                    INVOKESPECIAL org.springframework.beans.propertyeditors.CustomMapEditor.<init> (Ljava/lang/Class;)V
                    INVOKEINTERFACE java.util.Map.put (Ljava/lang/Object;Ljava/lang/Object;)Ljava/lang/Object;
                    POP
                    ALOAD_0     // Lorg/springframework/beans/PropertyEditorRegistrySupport; this   (line 218)
                    GETFIELD org.springframework.beans.PropertyEditorRegistrySupport.defaultEditors Ljava/util/Map;
                    LDC [B
                    NEW org.springframework.beans.propertyeditors.ByteArrayPropertyEditor
                    DUP
                    INVOKESPECIAL org.springframework.beans.propertyeditors.ByteArrayPropertyEditor.<init> ()V
                    INVOKEINTERFACE java.util.Map.put (Ljava/lang/Object;Ljava/lang/Object;)Ljava/lang/Object;
                    POP
                    ALOAD_0     // Lorg/springframework/beans/PropertyEditorRegistrySupport; this   (line 219)
                    GETFIELD org.springframework.beans.PropertyEditorRegistrySupport.defaultEditors Ljava/util/Map;
                    LDC [C
                    NEW org.springframework.beans.propertyeditors.CharArrayPropertyEditor
                    DUP
                    INVOKESPECIAL org.springframework.beans.propertyeditors.CharArrayPropertyEditor.<init> ()V
                    INVOKEINTERFACE java.util.Map.put (Ljava/lang/Object;Ljava/lang/Object;)Ljava/lang/Object;
                    POP
                    ALOAD_0     // Lorg/springframework/beans/PropertyEditorRegistrySupport; this   (line 222)
                    GETFIELD org.springframework.beans.PropertyEditorRegistrySupport.defaultEditors Ljava/util/Map;
                    GETSTATIC java.lang.Character.TYPE Ljava/lang/Class;
                    NEW org.springframework.beans.propertyeditors.CharacterEditor
                    DUP
                    ICONST_0
                    INVOKESPECIAL org.springframework.beans.propertyeditors.CharacterEditor.<init> (Z)V
                    INVOKEINTERFACE java.util.Map.put (Ljava/lang/Object;Ljava/lang/Object;)Ljava/lang/Object;
                    POP
                    ALOAD_0     // Lorg/springframework/beans/PropertyEditorRegistrySupport; this   (line 223)
                    GETFIELD org.springframework.beans.PropertyEditorRegistrySupport.defaultEditors Ljava/util/Map;
                    LDC java.lang.Character
                    NEW org.springframework.beans.propertyeditors.CharacterEditor
                    DUP
                    ICONST_1
                    INVOKESPECIAL org.springframework.beans.propertyeditors.CharacterEditor.<init> (Z)V
                    INVOKEINTERFACE java.util.Map.put (Ljava/lang/Object;Ljava/lang/Object;)Ljava/lang/Object;
                    POP
                    ALOAD_0     // Lorg/springframework/beans/PropertyEditorRegistrySupport; this   (line 226)
                    GETFIELD org.springframework.beans.PropertyEditorRegistrySupport.defaultEditors Ljava/util/Map;
                    GETSTATIC java.lang.Boolean.TYPE Ljava/lang/Class;
                    NEW org.springframework.beans.propertyeditors.CustomBooleanEditor
                    DUP
                    ICONST_0
                    INVOKESPECIAL org.springframework.beans.propertyeditors.CustomBooleanEditor.<init> (Z)V
                    INVOKEINTERFACE java.util.Map.put (Ljava/lang/Object;Ljava/lang/Object;)Ljava/lang/Object;
                    POP
                    ALOAD_0     // Lorg/springframework/beans/PropertyEditorRegistrySupport; this   (line 227)
                    GETFIELD org.springframework.beans.PropertyEditorRegistrySupport.defaultEditors Ljava/util/Map;
                    LDC java.lang.Boolean
                    NEW org.springframework.beans.propertyeditors.CustomBooleanEditor
                    DUP
                    ICONST_1
                    INVOKESPECIAL org.springframework.beans.propertyeditors.CustomBooleanEditor.<init> (Z)V
                    INVOKEINTERFACE java.util.Map.put (Ljava/lang/Object;Ljava/lang/Object;)Ljava/lang/Object;
                    POP
                    ALOAD_0     // Lorg/springframework/beans/PropertyEditorRegistrySupport; this   (line 231)
                    GETFIELD org.springframework.beans.PropertyEditorRegistrySupport.defaultEditors Ljava/util/Map;
                    GETSTATIC java.lang.Byte.TYPE Ljava/lang/Class;
                    NEW org.springframework.beans.propertyeditors.CustomNumberEditor
                    DUP
                    LDC java.lang.Byte
                    ICONST_0
                    INVOKESPECIAL org.springframework.beans.propertyeditors.CustomNumberEditor.<init> (Ljava/lang/Class;Z)V
                    INVOKEINTERFACE java.util.Map.put (Ljava/lang/Object;Ljava/lang/Object;)Ljava/lang/Object;
                    POP
                    ALOAD_0     // Lorg/springframework/beans/PropertyEditorRegistrySupport; this   (line 232)
                    GETFIELD org.springframework.beans.PropertyEditorRegistrySupport.defaultEditors Ljava/util/Map;
                    LDC java.lang.Byte
                    NEW org.springframework.beans.propertyeditors.CustomNumberEditor
                    DUP
                    LDC java.lang.Byte
                    ICONST_1
                    INVOKESPECIAL org.springframework.beans.propertyeditors.CustomNumberEditor.<init> (Ljava/lang/Class;Z)V
                    INVOKEINTERFACE java.util.Map.put (Ljava/lang/Object;Ljava/lang/Object;)Ljava/lang/Object;
                    POP
                    ALOAD_0     // Lorg/springframework/beans/PropertyEditorRegistrySupport; this   (line 233)
                    GETFIELD org.springframework.beans.PropertyEditorRegistrySupport.defaultEditors Ljava/util/Map;
                    GETSTATIC java.lang.Short.TYPE Ljava/lang/Class;
                    NEW org.springframework.beans.propertyeditors.CustomNumberEditor
                    DUP
                    LDC java.lang.Short
                    ICONST_0
                    INVOKESPECIAL org.springframework.beans.propertyeditors.CustomNumberEditor.<init> (Ljava/lang/Class;Z)V
                    INVOKEINTERFACE java.util.Map.put (Ljava/lang/Object;Ljava/lang/Object;)Ljava/lang/Object;
                    POP
                    ALOAD_0     // Lorg/springframework/beans/PropertyEditorRegistrySupport; this   (line 234)
                    GETFIELD org.springframework.beans.PropertyEditorRegistrySupport.defaultEditors Ljava/util/Map;
                    LDC java.lang.Short
                    NEW org.springframework.beans.propertyeditors.CustomNumberEditor
                    DUP
                    LDC java.lang.Short
                    ICONST_1
                    INVOKESPECIAL org.springframework.beans.propertyeditors.CustomNumberEditor.<init> (Ljava/lang/Class;Z)V
                    INVOKEINTERFACE java.util.Map.put (Ljava/lang/Object;Ljava/lang/Object;)Ljava/lang/Object;
                    POP
                    ALOAD_0     // Lorg/springframework/beans/PropertyEditorRegistrySupport; this   (line 235)
                    GETFIELD org.springframework.beans.PropertyEditorRegistrySupport.defaultEditors Ljava/util/Map;
                    GETSTATIC java.lang.Integer.TYPE Ljava/lang/Class;
                    NEW org.springframework.beans.propertyeditors.CustomNumberEditor
                    DUP
                    LDC java.lang.Integer
                    ICONST_0
                    INVOKESPECIAL org.springframework.beans.propertyeditors.CustomNumberEditor.<init> (Ljava/lang/Class;Z)V
                    INVOKEINTERFACE java.util.Map.put (Ljava/lang/Object;Ljava/lang/Object;)Ljava/lang/Object;
                    POP
                    ALOAD_0     // Lorg/springframework/beans/PropertyEditorRegistrySupport; this   (line 236)
                    GETFIELD org.springframework.beans.PropertyEditorRegistrySupport.defaultEditors Ljava/util/Map;
                    LDC java.lang.Integer
                    NEW org.springframework.beans.propertyeditors.CustomNumberEditor
                    DUP
                    LDC java.lang.Integer
                    ICONST_1
                    INVOKESPECIAL org.springframework.beans.propertyeditors.CustomNumberEditor.<init> (Ljava/lang/Class;Z)V
                    INVOKEINTERFACE java.util.Map.put (Ljava/lang/Object;Ljava/lang/Object;)Ljava/lang/Object;
                    POP
                    ALOAD_0     // Lorg/springframework/beans/PropertyEditorRegistrySupport; this   (line 237)
                    GETFIELD org.springframework.beans.PropertyEditorRegistrySupport.defaultEditors Ljava/util/Map;
                    GETSTATIC java.lang.Long.TYPE Ljava/lang/Class;
                    NEW org.springframework.beans.propertyeditors.CustomNumberEditor
                    DUP
                    LDC java.lang.Long
                    ICONST_0
                    INVOKESPECIAL org.springframework.beans.propertyeditors.CustomNumberEditor.<init> (Ljava/lang/Class;Z)V
                    INVOKEINTERFACE java.util.Map.put (Ljava/lang/Object;Ljava/lang/Object;)Ljava/lang/Object;
                    POP
                    ALOAD_0     // Lorg/springframework/beans/PropertyEditorRegistrySupport; this   (line 238)
                    GETFIELD org.springframework.beans.PropertyEditorRegistrySupport.defaultEditors Ljava/util/Map;
                    LDC java.lang.Long
                    NEW org.springframework.beans.propertyeditors.CustomNumberEditor
                    DUP
                    LDC java.lang.Long
                    ICONST_1
                    INVOKESPECIAL org.springframework.beans.propertyeditors.CustomNumberEditor.<init> (Ljava/lang/Class;Z)V
                    INVOKEINTERFACE java.util.Map.put (Ljava/lang/Object;Ljava/lang/Object;)Ljava/lang/Object;
                    POP
                    ALOAD_0     // Lorg/springframework/beans/PropertyEditorRegistrySupport; this   (line 239)
                    GETFIELD org.springframework.beans.PropertyEditorRegistrySupport.defaultEditors Ljava/util/Map;
                    GETSTATIC java.lang.Float.TYPE Ljava/lang/Class;
                    NEW org.springframework.beans.propertyeditors.CustomNumberEditor
                    DUP
                    LDC java.lang.Float
                    ICONST_0
                    INVOKESPECIAL org.springframework.beans.propertyeditors.CustomNumberEditor.<init> (Ljava/lang/Class;Z)V
                    INVOKEINTERFACE java.util.Map.put (Ljava/lang/Object;Ljava/lang/Object;)Ljava/lang/Object;
                    POP
                    ALOAD_0     // Lorg/springframework/beans/PropertyEditorRegistrySupport; this   (line 240)
                    GETFIELD org.springframework.beans.PropertyEditorRegistrySupport.defaultEditors Ljava/util/Map;
                    LDC java.lang.Float
                    NEW org.springframework.beans.propertyeditors.CustomNumberEditor
                    DUP
                    LDC java.lang.Float
                    ICONST_1
                    INVOKESPECIAL org.springframework.beans.propertyeditors.CustomNumberEditor.<init> (Ljava/lang/Class;Z)V
                    INVOKEINTERFACE java.util.Map.put (Ljava/lang/Object;Ljava/lang/Object;)Ljava/lang/Object;
                    POP
                    ALOAD_0     // Lorg/springframework/beans/PropertyEditorRegistrySupport; this   (line 241)
                    GETFIELD org.springframework.beans.PropertyEditorRegistrySupport.defaultEditors Ljava/util/Map;
                    GETSTATIC java.lang.Double.TYPE Ljava/lang/Class;
                    NEW org.springframework.beans.propertyeditors.CustomNumberEditor
                    DUP
                    LDC java.lang.Double
                    ICONST_0
                    INVOKESPECIAL org.springframework.beans.propertyeditors.CustomNumberEditor.<init> (Ljava/lang/Class;Z)V
                    INVOKEINTERFACE java.util.Map.put (Ljava/lang/Object;Ljava/lang/Object;)Ljava/lang/Object;
                    POP
                    ALOAD_0     // Lorg/springframework/beans/PropertyEditorRegistrySupport; this   (line 242)
                    GETFIELD org.springframework.beans.PropertyEditorRegistrySupport.defaultEditors Ljava/util/Map;
                    LDC java.lang.Double
                    NEW org.springframework.beans.propertyeditors.CustomNumberEditor
                    DUP
                    LDC java.lang.Double
                    ICONST_1
                    INVOKESPECIAL org.springframework.beans.propertyeditors.CustomNumberEditor.<init> (Ljava/lang/Class;Z)V
                    INVOKEINTERFACE java.util.Map.put (Ljava/lang/Object;Ljava/lang/Object;)Ljava/lang/Object;
                    POP
                    ALOAD_0     // Lorg/springframework/beans/PropertyEditorRegistrySupport; this   (line 243)
                    GETFIELD org.springframework.beans.PropertyEditorRegistrySupport.defaultEditors Ljava/util/Map;
                    LDC java.math.BigDecimal
                    NEW org.springframework.beans.propertyeditors.CustomNumberEditor
                    DUP
                    LDC java.math.BigDecimal
                    ICONST_1
                    INVOKESPECIAL org.springframework.beans.propertyeditors.CustomNumberEditor.<init> (Ljava/lang/Class;Z)V
                    INVOKEINTERFACE java.util.Map.put (Ljava/lang/Object;Ljava/lang/Object;)Ljava/lang/Object;
                    POP
                    ALOAD_0     // Lorg/springframework/beans/PropertyEditorRegistrySupport; this   (line 244)
                    GETFIELD org.springframework.beans.PropertyEditorRegistrySupport.defaultEditors Ljava/util/Map;
                    LDC java.math.BigInteger
                    NEW org.springframework.beans.propertyeditors.CustomNumberEditor
                    DUP
                    LDC java.math.BigInteger
                    ICONST_1
                    INVOKESPECIAL org.springframework.beans.propertyeditors.CustomNumberEditor.<init> (Ljava/lang/Class;Z)V
                    INVOKEINTERFACE java.util.Map.put (Ljava/lang/Object;Ljava/lang/Object;)Ljava/lang/Object;
                    POP
                    ALOAD_0     // Lorg/springframework/beans/PropertyEditorRegistrySupport; this   (line 247)
                    GETFIELD org.springframework.beans.PropertyEditorRegistrySupport.configValueEditorsActive Z
                    IFEQ L0
                    NEW org.springframework.beans.propertyeditors.StringArrayPropertyEditor   (line 248)
                    DUP
                    INVOKESPECIAL org.springframework.beans.propertyeditors.StringArrayPropertyEditor.<init> ()V
                    ASTORE_1
                    ALOAD_0     // Lorg/springframework/beans/PropertyEditorRegistrySupport; this   (line 249)
                    GETFIELD org.springframework.beans.PropertyEditorRegistrySupport.defaultEditors Ljava/util/Map;
                    LDC [Ljava.lang.String;
                    ALOAD_1     // Lorg/springframework/beans/propertyeditors/StringArrayPropertyEditor; sae
                    INVOKEINTERFACE java.util.Map.put (Ljava/lang/Object;Ljava/lang/Object;)Ljava/lang/Object;
                    POP
                    ALOAD_0     // Lorg/springframework/beans/PropertyEditorRegistrySupport; this   (line 250)
                    GETFIELD org.springframework.beans.PropertyEditorRegistrySupport.defaultEditors Ljava/util/Map;
                    LDC [S
                    ALOAD_1     // Lorg/springframework/beans/propertyeditors/StringArrayPropertyEditor; sae
                    INVOKEINTERFACE java.util.Map.put (Ljava/lang/Object;Ljava/lang/Object;)Ljava/lang/Object;
                    POP
                    ALOAD_0     // Lorg/springframework/beans/PropertyEditorRegistrySupport; this   (line 251)
                    GETFIELD org.springframework.beans.PropertyEditorRegistrySupport.defaultEditors Ljava/util/Map;
                    LDC [I
                    ALOAD_1     // Lorg/springframework/beans/propertyeditors/StringArrayPropertyEditor; sae
                    INVOKEINTERFACE java.util.Map.put (Ljava/lang/Object;Ljava/lang/Object;)Ljava/lang/Object;
                    POP
                    ALOAD_0     // Lorg/springframework/beans/PropertyEditorRegistrySupport; this   (line 252)
                    GETFIELD org.springframework.beans.PropertyEditorRegistrySupport.defaultEditors Ljava/util/Map;
                    LDC [J
                    ALOAD_1     // Lorg/springframework/beans/propertyeditors/StringArrayPropertyEditor; sae
                    INVOKEINTERFACE java.util.Map.put (Ljava/lang/Object;Ljava/lang/Object;)Ljava/lang/Object;
                    POP
                L0: RETURN   (line 254)
  end private void createDefaultEditors()

  protected void copyDefaultEditorsTo(org.springframework.beans.PropertyEditorRegistrySupport):
                    ALOAD_1     // Lorg/springframework/beans/PropertyEditorRegistrySupport; target   (line 261)
                    ALOAD_0     // Lorg/springframework/beans/PropertyEditorRegistrySupport; this
                    GETFIELD org.springframework.beans.PropertyEditorRegistrySupport.defaultEditorsActive Z
                    PUTFIELD org.springframework.beans.PropertyEditorRegistrySupport.defaultEditorsActive Z
                    ALOAD_1     // Lorg/springframework/beans/PropertyEditorRegistrySupport; target   (line 262)
                    ALOAD_0     // Lorg/springframework/beans/PropertyEditorRegistrySupport; this
                    GETFIELD org.springframework.beans.PropertyEditorRegistrySupport.configValueEditorsActive Z
                    PUTFIELD org.springframework.beans.PropertyEditorRegistrySupport.configValueEditorsActive Z
                    ALOAD_1     // Lorg/springframework/beans/PropertyEditorRegistrySupport; target   (line 263)
                    ALOAD_0     // Lorg/springframework/beans/PropertyEditorRegistrySupport; this
                    GETFIELD org.springframework.beans.PropertyEditorRegistrySupport.defaultEditors Ljava/util/Map;
                    PUTFIELD org.springframework.beans.PropertyEditorRegistrySupport.defaultEditors Ljava/util/Map;
                    ALOAD_1     // Lorg/springframework/beans/PropertyEditorRegistrySupport; target   (line 264)
                    ALOAD_0     // Lorg/springframework/beans/PropertyEditorRegistrySupport; this
                    GETFIELD org.springframework.beans.PropertyEditorRegistrySupport.overriddenDefaultEditors Ljava/util/Map;
                    PUTFIELD org.springframework.beans.PropertyEditorRegistrySupport.overriddenDefaultEditors Ljava/util/Map;
                    RETURN   (line 265)
  end protected void copyDefaultEditorsTo(org.springframework.beans.PropertyEditorRegistrySupport)

  public void registerCustomEditor(Class, java.beans.PropertyEditor):
                    ALOAD_0     // Lorg/springframework/beans/PropertyEditorRegistrySupport; this   (line 273)
                    ALOAD_1     // Ljava/lang/Class; requiredType
                    ACONST_NULL
                    ALOAD_2     // Ljava/beans/PropertyEditor; propertyEditor
                    INVOKEVIRTUAL org.springframework.beans.PropertyEditorRegistrySupport.registerCustomEditor (Ljava/lang/Class;Ljava/lang/String;Ljava/beans/PropertyEditor;)V
                    RETURN   (line 274)
  end public void registerCustomEditor(Class, java.beans.PropertyEditor)

  public void registerCustomEditor(Class, String, java.beans.PropertyEditor):
                    ALOAD_1     // Ljava/lang/Class; requiredType   (line 277)
                    IFNONNULL L0
                    ALOAD_2     // Ljava/lang/String; propertyPath
                    IFNONNULL L0
                    NEW java.lang.IllegalArgumentException   (line 278)
                    DUP
                    LDC "Either requiredType or propertyPath is required"
                    INVOKESPECIAL java.lang.IllegalArgumentException.<init> (Ljava/lang/String;)V
                    ATHROW
                L0: ALOAD_2     // Ljava/lang/String; propertyPath   (line 280)
                    IFNULL L2
                    ALOAD_0     // Lorg/springframework/beans/PropertyEditorRegistrySupport; this   (line 281)
                    GETFIELD org.springframework.beans.PropertyEditorRegistrySupport.customEditorsForPath Ljava/util/Map;
                    IFNONNULL L1
                    ALOAD_0     // Lorg/springframework/beans/PropertyEditorRegistrySupport; this   (line 282)
                    NEW java.util.LinkedHashMap
                    DUP
                    BIPUSH 16
                    INVOKESPECIAL java.util.LinkedHashMap.<init> (I)V
                    PUTFIELD org.springframework.beans.PropertyEditorRegistrySupport.customEditorsForPath Ljava/util/Map;
                L1: ALOAD_0     // Lorg/springframework/beans/PropertyEditorRegistrySupport; this   (line 284)
                    GETFIELD org.springframework.beans.PropertyEditorRegistrySupport.customEditorsForPath Ljava/util/Map;
                    ALOAD_2     // Ljava/lang/String; propertyPath
                    NEW org.springframework.beans.PropertyEditorRegistrySupport$CustomEditorHolder
                    DUP
                    ALOAD_3     // Ljava/beans/PropertyEditor; propertyEditor
                    ALOAD_1     // Ljava/lang/Class; requiredType
                    ACONST_NULL
                    INVOKESPECIAL org.springframework.beans.PropertyEditorRegistrySupport$CustomEditorHolder.<init> (Ljava/beans/PropertyEditor;Ljava/lang/Class;Lorg/springframework/beans/PropertyEditorRegistrySupport$CustomEditorHolder;)V
                    INVOKEINTERFACE java.util.Map.put (Ljava/lang/Object;Ljava/lang/Object;)Ljava/lang/Object;
                    POP
                    GOTO L4
                L2: ALOAD_0     // Lorg/springframework/beans/PropertyEditorRegistrySupport; this   (line 287)
                    GETFIELD org.springframework.beans.PropertyEditorRegistrySupport.customEditors Ljava/util/Map;
                    IFNONNULL L3
                    ALOAD_0     // Lorg/springframework/beans/PropertyEditorRegistrySupport; this   (line 288)
                    NEW java.util.LinkedHashMap
                    DUP
                    BIPUSH 16
                    INVOKESPECIAL java.util.LinkedHashMap.<init> (I)V
                    PUTFIELD org.springframework.beans.PropertyEditorRegistrySupport.customEditors Ljava/util/Map;
                L3: ALOAD_0     // Lorg/springframework/beans/PropertyEditorRegistrySupport; this   (line 290)
                    GETFIELD org.springframework.beans.PropertyEditorRegistrySupport.customEditors Ljava/util/Map;
                    ALOAD_1     // Ljava/lang/Class; requiredType
                    ALOAD_3     // Ljava/beans/PropertyEditor; propertyEditor
                    INVOKEINTERFACE java.util.Map.put (Ljava/lang/Object;Ljava/lang/Object;)Ljava/lang/Object;
                    POP
                    ALOAD_0     // Lorg/springframework/beans/PropertyEditorRegistrySupport; this   (line 291)
                    ACONST_NULL
                    PUTFIELD org.springframework.beans.PropertyEditorRegistrySupport.customEditorCache Ljava/util/Map;
                L4: RETURN   (line 293)
  end public void registerCustomEditor(Class, String, java.beans.PropertyEditor)

  public void registerSharedEditor(Class, java.beans.PropertyEditor):
                    ALOAD_0     // Lorg/springframework/beans/PropertyEditorRegistrySupport; this   (line 305)
                    ALOAD_1     // Ljava/lang/Class; requiredType
                    ACONST_NULL
                    ALOAD_2     // Ljava/beans/PropertyEditor; propertyEditor
                    INVOKEVIRTUAL org.springframework.beans.PropertyEditorRegistrySupport.registerCustomEditor (Ljava/lang/Class;Ljava/lang/String;Ljava/beans/PropertyEditor;)V
                    ALOAD_0     // Lorg/springframework/beans/PropertyEditorRegistrySupport; this   (line 306)
                    GETFIELD org.springframework.beans.PropertyEditorRegistrySupport.sharedEditors Ljava/util/Set;
                    IFNONNULL L0
                    ALOAD_0     // Lorg/springframework/beans/PropertyEditorRegistrySupport; this   (line 307)
                    NEW java.util.HashSet
                    DUP
                    INVOKESPECIAL java.util.HashSet.<init> ()V
                    PUTFIELD org.springframework.beans.PropertyEditorRegistrySupport.sharedEditors Ljava/util/Set;
                L0: ALOAD_0     // Lorg/springframework/beans/PropertyEditorRegistrySupport; this   (line 309)
                    GETFIELD org.springframework.beans.PropertyEditorRegistrySupport.sharedEditors Ljava/util/Set;
                    ALOAD_2     // Ljava/beans/PropertyEditor; propertyEditor
                    INVOKEINTERFACE java.util.Set.add (Ljava/lang/Object;)Z
                    POP
                    RETURN   (line 310)
  end public void registerSharedEditor(Class, java.beans.PropertyEditor)

  public boolean isSharedEditor(java.beans.PropertyEditor):
                    ALOAD_0     // Lorg/springframework/beans/PropertyEditorRegistrySupport; this   (line 319)
                    GETFIELD org.springframework.beans.PropertyEditorRegistrySupport.sharedEditors Ljava/util/Set;
                    IFNULL L0
                    ALOAD_0     // Lorg/springframework/beans/PropertyEditorRegistrySupport; this
                    GETFIELD org.springframework.beans.PropertyEditorRegistrySupport.sharedEditors Ljava/util/Set;
                    ALOAD_1     // Ljava/beans/PropertyEditor; propertyEditor
                    INVOKEINTERFACE java.util.Set.contains (Ljava/lang/Object;)Z
                    IFEQ L0
                    ICONST_1
                    IRETURN
                L0: ICONST_0
                    IRETURN
  end public boolean isSharedEditor(java.beans.PropertyEditor)

  public java.beans.PropertyEditor findCustomEditor(Class, String):
                    ALOAD_1     // Ljava/lang/Class; requiredType   (line 323)
                    ASTORE_3
                    ALOAD_2     // Ljava/lang/String; propertyPath   (line 324)
                    IFNULL L4
                    ALOAD_0     // Lorg/springframework/beans/PropertyEditorRegistrySupport; this   (line 325)
                    GETFIELD org.springframework.beans.PropertyEditorRegistrySupport.customEditorsForPath Ljava/util/Map;
                    IFNULL L3
                    ALOAD_0     // Lorg/springframework/beans/PropertyEditorRegistrySupport; this   (line 327)
                    ALOAD_2     // Ljava/lang/String; propertyPath
                    ALOAD_1     // Ljava/lang/Class; requiredType
                    INVOKESPECIAL org.springframework.beans.PropertyEditorRegistrySupport.getCustomEditor (Ljava/lang/String;Ljava/lang/Class;)Ljava/beans/PropertyEditor;
                    ASTORE 4
                    ALOAD 4     // Ljava/beans/PropertyEditor; editor   (line 328)
                    IFNONNULL L2
                    NEW java.util.LinkedList   (line 329)
                    DUP
                    INVOKESPECIAL java.util.LinkedList.<init> ()V
                    ASTORE 5
                    ALOAD_0     // Lorg/springframework/beans/PropertyEditorRegistrySupport; this   (line 330)
                    ALOAD 5     // Ljava/util/List; strippedPaths
                    LDC_W ""
                    ALOAD_2     // Ljava/lang/String; propertyPath
                    INVOKESPECIAL org.springframework.beans.PropertyEditorRegistrySupport.addStrippedPropertyPaths (Ljava/util/List;Ljava/lang/String;Ljava/lang/String;)V
                    ALOAD 5     // Ljava/util/List; strippedPaths   (line 331)
                    INVOKEINTERFACE java.util.List.iterator ()Ljava/util/Iterator;
                    ASTORE 6
                    GOTO L1
                L0: ALOAD 6     // Ljava/util/Iterator; it   (line 332)
                    INVOKEINTERFACE java.util.Iterator.next ()Ljava/lang/Object;
                    CHECKCAST java.lang.String
                    ASTORE 7
                    ALOAD_0     // Lorg/springframework/beans/PropertyEditorRegistrySupport; this   (line 333)
                    ALOAD 7     // Ljava/lang/String; strippedPath
                    ALOAD_1     // Ljava/lang/Class; requiredType
                    INVOKESPECIAL org.springframework.beans.PropertyEditorRegistrySupport.getCustomEditor (Ljava/lang/String;Ljava/lang/Class;)Ljava/beans/PropertyEditor;
                    ASTORE 4     // Ljava/beans/PropertyEditor; editor
                L1: ALOAD 6     // Ljava/util/Iterator; it   (line 331)
                    INVOKEINTERFACE java.util.Iterator.hasNext ()Z
                    IFEQ L2
                    ALOAD 4     // Ljava/beans/PropertyEditor; editor
                    IFNULL L0
                L2: ALOAD 4     // Ljava/beans/PropertyEditor; editor   (line 336)
                    IFNULL L3
                    ALOAD 4     // Ljava/beans/PropertyEditor; editor   (line 337)
                    ARETURN
                L3: ALOAD_1     // Ljava/lang/Class; requiredType   (line 340)
                    IFNONNULL L4
                    ALOAD_0     // Lorg/springframework/beans/PropertyEditorRegistrySupport; this   (line 341)
                    ALOAD_2     // Ljava/lang/String; propertyPath
                    INVOKEVIRTUAL org.springframework.beans.PropertyEditorRegistrySupport.getPropertyType (Ljava/lang/String;)Ljava/lang/Class;
                    ASTORE_3     // Ljava/lang/Class; requiredTypeToUse
                L4: ALOAD_0     // Lorg/springframework/beans/PropertyEditorRegistrySupport; this   (line 345)
                    ALOAD_3     // Ljava/lang/Class; requiredTypeToUse
                    INVOKESPECIAL org.springframework.beans.PropertyEditorRegistrySupport.getCustomEditor (Ljava/lang/Class;)Ljava/beans/PropertyEditor;
                    ARETURN
  end public java.beans.PropertyEditor findCustomEditor(Class, String)

  public boolean hasCustomEditorForElement(Class, String):
                    ALOAD_2     // Ljava/lang/String; propertyPath   (line 358)
                    IFNULL L2
                    ALOAD_0     // Lorg/springframework/beans/PropertyEditorRegistrySupport; this
                    GETFIELD org.springframework.beans.PropertyEditorRegistrySupport.customEditorsForPath Ljava/util/Map;
                    IFNULL L2
                    ALOAD_0     // Lorg/springframework/beans/PropertyEditorRegistrySupport; this   (line 359)
                    GETFIELD org.springframework.beans.PropertyEditorRegistrySupport.customEditorsForPath Ljava/util/Map;
                    INVOKEINTERFACE java.util.Map.entrySet ()Ljava/util/Set;
                    INVOKEINTERFACE java.util.Set.iterator ()Ljava/util/Iterator;
                    ASTORE 4
                    GOTO L1
                L0: ALOAD 4
                    INVOKEINTERFACE java.util.Iterator.next ()Ljava/lang/Object;
                    CHECKCAST java.util.Map$Entry
                    ASTORE_3
                    ALOAD_3     // Ljava/util/Map$Entry; entry   (line 360)
                    INVOKEINTERFACE java.util.Map$Entry.getKey ()Ljava/lang/Object;
                    CHECKCAST java.lang.String
                    ALOAD_2     // Ljava/lang/String; propertyPath
                    INVOKESTATIC org.springframework.beans.PropertyAccessorUtils.matchesProperty (Ljava/lang/String;Ljava/lang/String;)Z
                    IFEQ L1
                    ALOAD_3     // Ljava/util/Map$Entry; entry   (line 361)
                    INVOKEINTERFACE java.util.Map$Entry.getValue ()Ljava/lang/Object;
                    CHECKCAST org.springframework.beans.PropertyEditorRegistrySupport$CustomEditorHolder
                    ALOAD_1     // Ljava/lang/Class; elementType
                    INVOKESTATIC org.springframework.beans.PropertyEditorRegistrySupport$CustomEditorHolder.access$1 (Lorg/springframework/beans/PropertyEditorRegistrySupport$CustomEditorHolder;Ljava/lang/Class;)Ljava/beans/PropertyEditor;
                    IFNULL L1
                    ICONST_1   (line 362)
                    IRETURN
                L1: ALOAD 4   (line 359)
                    INVOKEINTERFACE java.util.Iterator.hasNext ()Z
                    IFNE L0
                L2: ALOAD_1     // Ljava/lang/Class; elementType   (line 368)
                    IFNULL L3
                    ALOAD_0     // Lorg/springframework/beans/PropertyEditorRegistrySupport; this
                    GETFIELD org.springframework.beans.PropertyEditorRegistrySupport.customEditors Ljava/util/Map;
                    IFNULL L3
                    ALOAD_0     // Lorg/springframework/beans/PropertyEditorRegistrySupport; this
                    GETFIELD org.springframework.beans.PropertyEditorRegistrySupport.customEditors Ljava/util/Map;
                    ALOAD_1     // Ljava/lang/Class; elementType
                    INVOKEINTERFACE java.util.Map.containsKey (Ljava/lang/Object;)Z
                    IFEQ L3
                    ICONST_1
                    IRETURN
                L3: ICONST_0
                    IRETURN
  end public boolean hasCustomEditorForElement(Class, String)

  protected Class getPropertyType(String):
                    ACONST_NULL   (line 383)
                    ARETURN
  end protected Class getPropertyType(String)

  private java.beans.PropertyEditor getCustomEditor(String, Class):
                    ALOAD_0     // Lorg/springframework/beans/PropertyEditorRegistrySupport; this   (line 393)
                    GETFIELD org.springframework.beans.PropertyEditorRegistrySupport.customEditorsForPath Ljava/util/Map;
                    ALOAD_1     // Ljava/lang/String; propertyName
                    INVOKEINTERFACE java.util.Map.get (Ljava/lang/Object;)Ljava/lang/Object;
                    CHECKCAST org.springframework.beans.PropertyEditorRegistrySupport$CustomEditorHolder
                    ASTORE_3
                    ALOAD_3     // Lorg/springframework/beans/PropertyEditorRegistrySupport$CustomEditorHolder; holder   (line 394)
                    IFNULL L0
                    ALOAD_3     // Lorg/springframework/beans/PropertyEditorRegistrySupport$CustomEditorHolder; holder
                    ALOAD_2     // Ljava/lang/Class; requiredType
                    INVOKESTATIC org.springframework.beans.PropertyEditorRegistrySupport$CustomEditorHolder.access$1 (Lorg/springframework/beans/PropertyEditorRegistrySupport$CustomEditorHolder;Ljava/lang/Class;)Ljava/beans/PropertyEditor;
                    GOTO L1
                L0: ACONST_NULL
                L1: ARETURN
  end private java.beans.PropertyEditor getCustomEditor(String, Class)

  private java.beans.PropertyEditor getCustomEditor(Class):
                    ALOAD_1     // Ljava/lang/Class; requiredType   (line 406)
                    IFNULL L0
                    ALOAD_0     // Lorg/springframework/beans/PropertyEditorRegistrySupport; this
                    GETFIELD org.springframework.beans.PropertyEditorRegistrySupport.customEditors Ljava/util/Map;
                    IFNONNULL L1
                L0: ACONST_NULL   (line 407)
                    ARETURN
                L1: ALOAD_0     // Lorg/springframework/beans/PropertyEditorRegistrySupport; this   (line 410)
                    GETFIELD org.springframework.beans.PropertyEditorRegistrySupport.customEditors Ljava/util/Map;
                    ALOAD_1     // Ljava/lang/Class; requiredType
                    INVOKEINTERFACE java.util.Map.get (Ljava/lang/Object;)Ljava/lang/Object;
                    CHECKCAST java.beans.PropertyEditor
                    ASTORE_2
                    ALOAD_2     // Ljava/beans/PropertyEditor; editor   (line 411)
                    IFNONNULL L6
                    ALOAD_0     // Lorg/springframework/beans/PropertyEditorRegistrySupport; this   (line 413)
                    GETFIELD org.springframework.beans.PropertyEditorRegistrySupport.customEditorCache Ljava/util/Map;
                    IFNULL L2
                    ALOAD_0     // Lorg/springframework/beans/PropertyEditorRegistrySupport; this   (line 414)
                    GETFIELD org.springframework.beans.PropertyEditorRegistrySupport.customEditorCache Ljava/util/Map;
                    ALOAD_1     // Ljava/lang/Class; requiredType
                    INVOKEINTERFACE java.util.Map.get (Ljava/lang/Object;)Ljava/lang/Object;
                    CHECKCAST java.beans.PropertyEditor
                    ASTORE_2     // Ljava/beans/PropertyEditor; editor
                L2: ALOAD_2     // Ljava/beans/PropertyEditor; editor   (line 416)
                    IFNONNULL L6
                    ALOAD_0     // Lorg/springframework/beans/PropertyEditorRegistrySupport; this   (line 418)
                    GETFIELD org.springframework.beans.PropertyEditorRegistrySupport.customEditors Ljava/util/Map;
                    INVOKEINTERFACE java.util.Map.keySet ()Ljava/util/Set;
                    INVOKEINTERFACE java.util.Set.iterator ()Ljava/util/Iterator;
                    ASTORE_3
                    GOTO L5
                L3: ALOAD_3     // Ljava/util/Iterator; it   (line 419)
                    INVOKEINTERFACE java.util.Iterator.next ()Ljava/lang/Object;
                    CHECKCAST java.lang.Class
                    ASTORE 4
                    ALOAD 4     // Ljava/lang/Class; key   (line 420)
                    ALOAD_1     // Ljava/lang/Class; requiredType
                    INVOKEVIRTUAL java.lang.Class.isAssignableFrom (Ljava/lang/Class;)Z
                    IFEQ L5
                    ALOAD_0     // Lorg/springframework/beans/PropertyEditorRegistrySupport; this   (line 421)
                    GETFIELD org.springframework.beans.PropertyEditorRegistrySupport.customEditors Ljava/util/Map;
                    ALOAD 4     // Ljava/lang/Class; key
                    INVOKEINTERFACE java.util.Map.get (Ljava/lang/Object;)Ljava/lang/Object;
                    CHECKCAST java.beans.PropertyEditor
                    ASTORE_2     // Ljava/beans/PropertyEditor; editor
                    ALOAD_0     // Lorg/springframework/beans/PropertyEditorRegistrySupport; this   (line 424)
                    GETFIELD org.springframework.beans.PropertyEditorRegistrySupport.customEditorCache Ljava/util/Map;
                    IFNONNULL L4
                    ALOAD_0     // Lorg/springframework/beans/PropertyEditorRegistrySupport; this   (line 425)
                    NEW java.util.HashMap
                    DUP
                    INVOKESPECIAL java.util.HashMap.<init> ()V
                    PUTFIELD org.springframework.beans.PropertyEditorRegistrySupport.customEditorCache Ljava/util/Map;
                L4: ALOAD_0     // Lorg/springframework/beans/PropertyEditorRegistrySupport; this   (line 427)
                    GETFIELD org.springframework.beans.PropertyEditorRegistrySupport.customEditorCache Ljava/util/Map;
                    ALOAD_1     // Ljava/lang/Class; requiredType
                    ALOAD_2     // Ljava/beans/PropertyEditor; editor
                    INVOKEINTERFACE java.util.Map.put (Ljava/lang/Object;Ljava/lang/Object;)Ljava/lang/Object;
                    POP
                L5: ALOAD_3     // Ljava/util/Iterator; it   (line 418)
                    INVOKEINTERFACE java.util.Iterator.hasNext ()Z
                    IFEQ L6
                    ALOAD_2     // Ljava/beans/PropertyEditor; editor
                    IFNULL L3
                L6: ALOAD_2     // Ljava/beans/PropertyEditor; editor   (line 432)
                    ARETURN
  end private java.beans.PropertyEditor getCustomEditor(Class)

  protected Class guessPropertyTypeFromEditors(String):
                    ALOAD_0     // Lorg/springframework/beans/PropertyEditorRegistrySupport; this   (line 442)
                    GETFIELD org.springframework.beans.PropertyEditorRegistrySupport.customEditorsForPath Ljava/util/Map;
                    IFNULL L3
                    ALOAD_0     // Lorg/springframework/beans/PropertyEditorRegistrySupport; this   (line 443)
                    GETFIELD org.springframework.beans.PropertyEditorRegistrySupport.customEditorsForPath Ljava/util/Map;
                    ALOAD_1     // Ljava/lang/String; propertyName
                    INVOKEINTERFACE java.util.Map.get (Ljava/lang/Object;)Ljava/lang/Object;
                    CHECKCAST org.springframework.beans.PropertyEditorRegistrySupport$CustomEditorHolder
                    ASTORE_2
                    ALOAD_2     // Lorg/springframework/beans/PropertyEditorRegistrySupport$CustomEditorHolder; editorHolder   (line 444)
                    IFNONNULL L2
                    NEW java.util.LinkedList   (line 445)
                    DUP
                    INVOKESPECIAL java.util.LinkedList.<init> ()V
                    ASTORE_3
                    ALOAD_0     // Lorg/springframework/beans/PropertyEditorRegistrySupport; this   (line 446)
                    ALOAD_3     // Ljava/util/List; strippedPaths
                    LDC_W ""
                    ALOAD_1     // Ljava/lang/String; propertyName
                    INVOKESPECIAL org.springframework.beans.PropertyEditorRegistrySupport.addStrippedPropertyPaths (Ljava/util/List;Ljava/lang/String;Ljava/lang/String;)V
                    ALOAD_3     // Ljava/util/List; strippedPaths   (line 447)
                    INVOKEINTERFACE java.util.List.iterator ()Ljava/util/Iterator;
                    ASTORE 4
                    GOTO L1
                L0: ALOAD 4     // Ljava/util/Iterator; it   (line 448)
                    INVOKEINTERFACE java.util.Iterator.next ()Ljava/lang/Object;
                    CHECKCAST java.lang.String
                    ASTORE 5
                    ALOAD_0     // Lorg/springframework/beans/PropertyEditorRegistrySupport; this   (line 449)
                    GETFIELD org.springframework.beans.PropertyEditorRegistrySupport.customEditorsForPath Ljava/util/Map;
                    ALOAD 5     // Ljava/lang/String; strippedName
                    INVOKEINTERFACE java.util.Map.get (Ljava/lang/Object;)Ljava/lang/Object;
                    CHECKCAST org.springframework.beans.PropertyEditorRegistrySupport$CustomEditorHolder
                    ASTORE_2     // Lorg/springframework/beans/PropertyEditorRegistrySupport$CustomEditorHolder; editorHolder
                L1: ALOAD 4     // Ljava/util/Iterator; it   (line 447)
                    INVOKEINTERFACE java.util.Iterator.hasNext ()Z
                    IFEQ L2
                    ALOAD_2     // Lorg/springframework/beans/PropertyEditorRegistrySupport$CustomEditorHolder; editorHolder
                    IFNULL L0
                L2: ALOAD_2     // Lorg/springframework/beans/PropertyEditorRegistrySupport$CustomEditorHolder; editorHolder   (line 452)
                    IFNULL L3
                    ALOAD_2     // Lorg/springframework/beans/PropertyEditorRegistrySupport$CustomEditorHolder; editorHolder   (line 453)
                    INVOKESTATIC org.springframework.beans.PropertyEditorRegistrySupport$CustomEditorHolder.access$2 (Lorg/springframework/beans/PropertyEditorRegistrySupport$CustomEditorHolder;)Ljava/lang/Class;
                    ARETURN
                L3: ACONST_NULL   (line 456)
                    ARETURN
  end protected Class guessPropertyTypeFromEditors(String)

  protected void copyCustomEditorsTo(org.springframework.beans.PropertyEditorRegistry, String):
                    ALOAD_2     // Ljava/lang/String; nestedProperty   (line 468)
                    IFNULL L0
                    ALOAD_2     // Ljava/lang/String; nestedProperty
                    INVOKESTATIC org.springframework.beans.PropertyAccessorUtils.getPropertyName (Ljava/lang/String;)Ljava/lang/String;
                    GOTO L1
                L0: ACONST_NULL
                L1: ASTORE_3   (line 467)
                    ALOAD_0     // Lorg/springframework/beans/PropertyEditorRegistrySupport; this   (line 469)
                    GETFIELD org.springframework.beans.PropertyEditorRegistrySupport.customEditors Ljava/util/Map;
                    IFNULL L4
                    ALOAD_0     // Lorg/springframework/beans/PropertyEditorRegistrySupport; this   (line 470)
                    GETFIELD org.springframework.beans.PropertyEditorRegistrySupport.customEditors Ljava/util/Map;
                    INVOKEINTERFACE java.util.Map.entrySet ()Ljava/util/Set;
                    INVOKEINTERFACE java.util.Set.iterator ()Ljava/util/Iterator;
                    ASTORE 5
                    GOTO L3
                L2: ALOAD 5
                    INVOKEINTERFACE java.util.Iterator.next ()Ljava/lang/Object;
                    CHECKCAST java.util.Map$Entry
                    ASTORE 4
                    ALOAD_1     // Lorg/springframework/beans/PropertyEditorRegistry; target   (line 471)
                    ALOAD 4     // Ljava/util/Map$Entry; entry
                    INVOKEINTERFACE java.util.Map$Entry.getKey ()Ljava/lang/Object;
                    CHECKCAST java.lang.Class
                    ALOAD 4     // Ljava/util/Map$Entry; entry
                    INVOKEINTERFACE java.util.Map$Entry.getValue ()Ljava/lang/Object;
                    CHECKCAST java.beans.PropertyEditor
                    INVOKEINTERFACE org.springframework.beans.PropertyEditorRegistry.registerCustomEditor (Ljava/lang/Class;Ljava/beans/PropertyEditor;)V
                L3: ALOAD 5   (line 470)
                    INVOKEINTERFACE java.util.Iterator.hasNext ()Z
                    IFNE L2
                L4: ALOAD_0     // Lorg/springframework/beans/PropertyEditorRegistrySupport; this   (line 474)
                    GETFIELD org.springframework.beans.PropertyEditorRegistrySupport.customEditorsForPath Ljava/util/Map;
                    IFNULL L9
                    ALOAD_0     // Lorg/springframework/beans/PropertyEditorRegistrySupport; this   (line 475)
                    GETFIELD org.springframework.beans.PropertyEditorRegistrySupport.customEditorsForPath Ljava/util/Map;
                    INVOKEINTERFACE java.util.Map.entrySet ()Ljava/util/Set;
                    INVOKEINTERFACE java.util.Set.iterator ()Ljava/util/Iterator;
                    ASTORE 5
                    GOTO L8
                L5: ALOAD 5
                    INVOKEINTERFACE java.util.Iterator.next ()Ljava/lang/Object;
                    CHECKCAST java.util.Map$Entry
                    ASTORE 4
                    ALOAD 4     // Ljava/util/Map$Entry; entry   (line 476)
                    INVOKEINTERFACE java.util.Map$Entry.getKey ()Ljava/lang/Object;
                    CHECKCAST java.lang.String
                    ASTORE 6
                    ALOAD 4     // Ljava/util/Map$Entry; entry   (line 477)
                    INVOKEINTERFACE java.util.Map$Entry.getValue ()Ljava/lang/Object;
                    CHECKCAST org.springframework.beans.PropertyEditorRegistrySupport$CustomEditorHolder
                    ASTORE 7
                    ALOAD_2     // Ljava/lang/String; nestedProperty   (line 478)
                    IFNULL L7
                    ALOAD 6     // Ljava/lang/String; editorPath   (line 479)
                    INVOKESTATIC org.springframework.beans.PropertyAccessorUtils.getFirstNestedPropertySeparatorIndex (Ljava/lang/String;)I
                    ISTORE 8
                    ILOAD 8     // I pos   (line 480)
                    ICONST_M1
                    IF_ICMPEQ L8
                    ALOAD 6     // Ljava/lang/String; editorPath   (line 481)
                    ICONST_0
                    ILOAD 8     // I pos
                    INVOKEVIRTUAL java.lang.String.substring (II)Ljava/lang/String;
                    ASTORE 9
                    ALOAD 6     // Ljava/lang/String; editorPath   (line 482)
                    ILOAD 8     // I pos
                    ICONST_1
                    IADD
                    INVOKEVIRTUAL java.lang.String.substring (I)Ljava/lang/String;
                    ASTORE 10
                    ALOAD 9     // Ljava/lang/String; editorNestedProperty   (line 483)
                    ALOAD_2     // Ljava/lang/String; nestedProperty
                    INVOKEVIRTUAL java.lang.String.equals (Ljava/lang/Object;)Z
                    IFNE L6
                    ALOAD 9     // Ljava/lang/String; editorNestedProperty
                    ALOAD_3     // Ljava/lang/String; actualPropertyName
                    INVOKEVIRTUAL java.lang.String.equals (Ljava/lang/Object;)Z
                    IFEQ L8
                L6: ALOAD_1     // Lorg/springframework/beans/PropertyEditorRegistry; target   (line 484)
                    ALOAD 7     // Lorg/springframework/beans/PropertyEditorRegistrySupport$CustomEditorHolder; editorHolder   (line 485)
                    INVOKESTATIC org.springframework.beans.PropertyEditorRegistrySupport$CustomEditorHolder.access$2 (Lorg/springframework/beans/PropertyEditorRegistrySupport$CustomEditorHolder;)Ljava/lang/Class;
                    ALOAD 10     // Ljava/lang/String; editorNestedPath
                    ALOAD 7     // Lorg/springframework/beans/PropertyEditorRegistrySupport$CustomEditorHolder; editorHolder
                    INVOKESTATIC org.springframework.beans.PropertyEditorRegistrySupport$CustomEditorHolder.access$3 (Lorg/springframework/beans/PropertyEditorRegistrySupport$CustomEditorHolder;)Ljava/beans/PropertyEditor;
                    INVOKEINTERFACE org.springframework.beans.PropertyEditorRegistry.registerCustomEditor (Ljava/lang/Class;Ljava/lang/String;Ljava/beans/PropertyEditor;)V   (line 484)
                    GOTO L8
                L7: ALOAD_1     // Lorg/springframework/beans/PropertyEditorRegistry; target   (line 490)
                    ALOAD 7     // Lorg/springframework/beans/PropertyEditorRegistrySupport$CustomEditorHolder; editorHolder   (line 491)
                    INVOKESTATIC org.springframework.beans.PropertyEditorRegistrySupport$CustomEditorHolder.access$2 (Lorg/springframework/beans/PropertyEditorRegistrySupport$CustomEditorHolder;)Ljava/lang/Class;
                    ALOAD 6     // Ljava/lang/String; editorPath
                    ALOAD 7     // Lorg/springframework/beans/PropertyEditorRegistrySupport$CustomEditorHolder; editorHolder
                    INVOKESTATIC org.springframework.beans.PropertyEditorRegistrySupport$CustomEditorHolder.access$3 (Lorg/springframework/beans/PropertyEditorRegistrySupport$CustomEditorHolder;)Ljava/beans/PropertyEditor;
                    INVOKEINTERFACE org.springframework.beans.PropertyEditorRegistry.registerCustomEditor (Ljava/lang/Class;Ljava/lang/String;Ljava/beans/PropertyEditor;)V   (line 490)
                L8: ALOAD 5   (line 475)
                    INVOKEINTERFACE java.util.Iterator.hasNext ()Z
                    IFNE L5
                L9: RETURN   (line 495)
  end protected void copyCustomEditorsTo(org.springframework.beans.PropertyEditorRegistry, String)

  private void addStrippedPropertyPaths(java.util.List, String, String):
                    ALOAD_3     // Ljava/lang/String; propertyPath   (line 506)
                    BIPUSH 91
                    INVOKEVIRTUAL java.lang.String.indexOf (I)I
                    ISTORE 4
                    ILOAD 4     // I startIndex   (line 507)
                    ICONST_M1
                    IF_ICMPEQ L0
                    ALOAD_3     // Ljava/lang/String; propertyPath   (line 508)
                    BIPUSH 93
                    INVOKEVIRTUAL java.lang.String.indexOf (I)I
                    ISTORE 5
                    ILOAD 5     // I endIndex   (line 509)
                    ICONST_M1
                    IF_ICMPEQ L0
                    ALOAD_3     // Ljava/lang/String; propertyPath   (line 510)
                    ICONST_0
                    ILOAD 4     // I startIndex
                    INVOKEVIRTUAL java.lang.String.substring (II)Ljava/lang/String;
                    ASTORE 6
                    ALOAD_3     // Ljava/lang/String; propertyPath   (line 511)
                    ILOAD 4     // I startIndex
                    ILOAD 5     // I endIndex
                    ICONST_1
                    IADD
                    INVOKEVIRTUAL java.lang.String.substring (II)Ljava/lang/String;
                    ASTORE 7
                    ALOAD_3     // Ljava/lang/String; propertyPath   (line 512)
                    ILOAD 5     // I endIndex
                    ICONST_1
                    IADD
                    ALOAD_3     // Ljava/lang/String; propertyPath
                    INVOKEVIRTUAL java.lang.String.length ()I
                    INVOKEVIRTUAL java.lang.String.substring (II)Ljava/lang/String;
                    ASTORE 8
                    ALOAD_1     // Ljava/util/List; strippedPaths   (line 514)
                    NEW java.lang.StringBuilder
                    DUP
                    ALOAD_2     // Ljava/lang/String; nestedPath
                    INVOKESTATIC java.lang.String.valueOf (Ljava/lang/Object;)Ljava/lang/String;
                    INVOKESPECIAL java.lang.StringBuilder.<init> (Ljava/lang/String;)V
                    ALOAD 6     // Ljava/lang/String; prefix
                    INVOKEVIRTUAL java.lang.StringBuilder.append (Ljava/lang/String;)Ljava/lang/StringBuilder;
                    ALOAD 8     // Ljava/lang/String; suffix
                    INVOKEVIRTUAL java.lang.StringBuilder.append (Ljava/lang/String;)Ljava/lang/StringBuilder;
                    INVOKEVIRTUAL java.lang.StringBuilder.toString ()Ljava/lang/String;
                    INVOKEINTERFACE java.util.List.add (Ljava/lang/Object;)Z
                    POP
                    ALOAD_0     // Lorg/springframework/beans/PropertyEditorRegistrySupport; this   (line 516)
                    ALOAD_1     // Ljava/util/List; strippedPaths
                    NEW java.lang.StringBuilder
                    DUP
                    ALOAD_2     // Ljava/lang/String; nestedPath
                    INVOKESTATIC java.lang.String.valueOf (Ljava/lang/Object;)Ljava/lang/String;
                    INVOKESPECIAL java.lang.StringBuilder.<init> (Ljava/lang/String;)V
                    ALOAD 6     // Ljava/lang/String; prefix
                    INVOKEVIRTUAL java.lang.StringBuilder.append (Ljava/lang/String;)Ljava/lang/StringBuilder;
                    INVOKEVIRTUAL java.lang.StringBuilder.toString ()Ljava/lang/String;
                    ALOAD 8     // Ljava/lang/String; suffix
                    INVOKESPECIAL org.springframework.beans.PropertyEditorRegistrySupport.addStrippedPropertyPaths (Ljava/util/List;Ljava/lang/String;Ljava/lang/String;)V
                    ALOAD_0     // Lorg/springframework/beans/PropertyEditorRegistrySupport; this   (line 518)
                    ALOAD_1     // Ljava/util/List; strippedPaths
                    NEW java.lang.StringBuilder
                    DUP
                    ALOAD_2     // Ljava/lang/String; nestedPath
                    INVOKESTATIC java.lang.String.valueOf (Ljava/lang/Object;)Ljava/lang/String;
                    INVOKESPECIAL java.lang.StringBuilder.<init> (Ljava/lang/String;)V
                    ALOAD 6     // Ljava/lang/String; prefix
                    INVOKEVIRTUAL java.lang.StringBuilder.append (Ljava/lang/String;)Ljava/lang/StringBuilder;
                    ALOAD 7     // Ljava/lang/String; key
                    INVOKEVIRTUAL java.lang.StringBuilder.append (Ljava/lang/String;)Ljava/lang/StringBuilder;
                    INVOKEVIRTUAL java.lang.StringBuilder.toString ()Ljava/lang/String;
                    ALOAD 8     // Ljava/lang/String; suffix
                    INVOKESPECIAL org.springframework.beans.PropertyEditorRegistrySupport.addStrippedPropertyPaths (Ljava/util/List;Ljava/lang/String;Ljava/lang/String;)V
                L0: RETURN   (line 521)
  end private void addStrippedPropertyPaths(java.util.List, String, String)

end public class org.springframework.beans.PropertyEditorRegistrySupport

	at org.aspectj.bridge.MessageWriter.handleMessage(MessageWriter.java:47)
	at org.aspectj.weaver.tools.WeavingAdaptor$WeavingAdaptorMessageWriter.handleMessage(WeavingAdaptor.java:665)
	at org.aspectj.weaver.tools.WeavingAdaptor$WeavingAdaptorMessageHolder.handleMessage(WeavingAdaptor.java:615)
	at org.aspectj.weaver.bcel.BcelWeaver.weave(BcelWeaver.java:1752)
	at org.aspectj.weaver.bcel.BcelWeaver.weaveWithoutDump(BcelWeaver.java:1694)
	at org.aspectj.weaver.bcel.BcelWeaver.weaveAndNotify(BcelWeaver.java:1464)
	at org.aspectj.weaver.bcel.BcelWeaver.weave(BcelWeaver.java:1273)
	at org.aspectj.weaver.tools.WeavingAdaptor.getWovenBytes(WeavingAdaptor.java:394)
	at org.aspectj.weaver.tools.WeavingAdaptor.weaveClass(WeavingAdaptor.java:281)
	at org.aspectj.weaver.loadtime.Aj.preProcess(Aj.java:95)
	at org.aspectj.weaver.loadtime.ClassPreProcessorAgentAdapter.transform(ClassPreProcessorAgentAdapter.java:52)
	at sun.instrument.TransformerManager.transform(TransformerManager.java:188)
	at sun.instrument.InstrumentationImpl.transform(InstrumentationImpl.java:428)
	at java.lang.ClassLoader.defineClass1(Native Method)
	at java.lang.ClassLoader.defineClass(ClassLoader.java:760)
	at java.security.SecureClassLoader.defineClass(SecureClassLoader.java:142)
	at java.net.URLClassLoader.defineClass(URLClassLoader.java:467)
	at java.net.URLClassLoader.access$100(URLClassLoader.java:73)
	at java.net.URLClassLoader$1.run(URLClassLoader.java:368)
	at java.net.URLClassLoader$1.run(URLClassLoader.java:362)
	at java.security.AccessController.doPrivileged(Native Method)
	at java.net.URLClassLoader.findClass(URLClassLoader.java:361)
	at java.lang.ClassLoader.loadClass(ClassLoader.java:424)
	at sun.misc.Launcher$AppClassLoader.loadClass(Launcher.java:331)
	at java.lang.ClassLoader.loadClass(ClassLoader.java:357)
	at java.lang.ClassLoader.defineClass1(Native Method)
	at java.lang.ClassLoader.defineClass(ClassLoader.java:760)
	at java.security.SecureClassLoader.defineClass(SecureClassLoader.java:142)
	at java.net.URLClassLoader.defineClass(URLClassLoader.java:467)
	at java.net.URLClassLoader.access$100(URLClassLoader.java:73)
	at java.net.URLClassLoader$1.run(URLClassLoader.java:368)
	at java.net.URLClassLoader$1.run(URLClassLoader.java:362)
	at java.security.AccessController.doPrivileged(Native Method)
	at java.net.URLClassLoader.findClass(URLClassLoader.java:361)
	at java.lang.ClassLoader.loadClass(ClassLoader.java:424)
	at sun.misc.Launcher$AppClassLoader.loadClass(Launcher.java:331)
	at java.lang.ClassLoader.loadClass(ClassLoader.java:357)
	at java.lang.ClassLoader.defineClass1(Native Method)
	at java.lang.ClassLoader.defineClass(ClassLoader.java:760)
	at java.security.SecureClassLoader.defineClass(SecureClassLoader.java:142)
	at java.net.URLClassLoader.defineClass(URLClassLoader.java:467)
	at java.net.URLClassLoader.access$100(URLClassLoader.java:73)
	at java.net.URLClassLoader$1.run(URLClassLoader.java:368)
	at java.net.URLClassLoader$1.run(URLClassLoader.java:362)
	at java.security.AccessController.doPrivileged(Native Method)
	at java.net.URLClassLoader.findClass(URLClassLoader.java:361)
	at java.lang.ClassLoader.loadClass(ClassLoader.java:424)
	at sun.misc.Launcher$AppClassLoader.loadClass(Launcher.java:331)
	at java.lang.ClassLoader.loadClass(ClassLoader.java:357)
	at org.springframework.beans.factory.support.AbstractAutowireCapableBeanFactory.instantiateBean(AbstractAutowireCapableBeanFactory.java:992)
	at org.springframework.beans.factory.support.AbstractAutowireCapableBeanFactory.createBeanInstance(AbstractAutowireCapableBeanFactory.java:943)
	at org.springframework.beans.factory.support.AbstractAutowireCapableBeanFactory.doCreateBean(AbstractAutowireCapableBeanFactory.java:485)
	at org.springframework.beans.factory.support.AbstractAutowireCapableBeanFactory.createBean(AbstractAutowireCapableBeanFactory.java:456)
	at org.springframework.beans.factory.support.AbstractBeanFactory$1.getObject(AbstractBeanFactory.java:294)
	at org.springframework.beans.factory.support.DefaultSingletonBeanRegistry.getSingleton(DefaultSingletonBeanRegistry.java:225)
	at org.springframework.beans.factory.support.AbstractBeanFactory.doGetBean(AbstractBeanFactory.java:291)
	at org.springframework.beans.factory.support.AbstractBeanFactory.getBean(AbstractBeanFactory.java:197)
	at org.springframework.context.support.AbstractApplicationContext.invokeBeanFactoryPostProcessors(AbstractApplicationContext.java:649)
	at org.springframework.context.support.AbstractApplicationContext.refresh(AbstractApplicationContext.java:451)
	at org.springframework.context.support.ClassPathXmlApplicationContext.<init>(ClassPathXmlApplicationContext.java:139)
	at org.springframework.context.support.ClassPathXmlApplicationContext.<init>(ClassPathXmlApplicationContext.java:83)
	at com.curso.spring.springioc0007.Main.init(Main.java:29)
	at com.curso.spring.springioc0007.Main.main(Main.java:24)
---- System Properties ---
java.runtime.name=Java(TM) SE Runtime Environment
sun.boot.library.path=C:\Program Files\Java\jdk1.8.0_72\jre\bin
java.vm.version=25.72-b15
java.vm.vendor=Oracle Corporation
java.vendor.url=http://java.oracle.com/
path.separator=;
java.vm.name=Java HotSpot(TM) 64-Bit Server VM
file.encoding.pkg=sun.io
user.country=ES
user.script=
sun.java.launcher=SUN_STANDARD
sun.os.patch.level=
java.vm.specification.name=Java Virtual Machine Specification
user.dir=C:\Users\usuario\git\spring\aspectos\Ejemplos Relacionados\SpringIoC0007Maven
java.runtime.version=1.8.0_72-b15
java.awt.graphicsenv=sun.awt.Win32GraphicsEnvironment
java.endorsed.dirs=C:\Program Files\Java\jdk1.8.0_72\jre\lib\endorsed
os.arch=amd64
java.io.tmpdir=C:\Users\usuario\AppData\Local\Temp\
line.separator=

java.vm.specification.vendor=Oracle Corporation
user.variant=
os.name=Windows 10
sun.jnu.encoding=Cp1252
java.library.path=C:\Program Files\Java\jdk1.8.0_72\bin;C:\WINDOWS\Sun\Java\bin;C:\WINDOWS\system32;C:\WINDOWS;C:\ProgramData\Oracle\Java\javapath;C:\Program Files\CollabNet\Subversion Client;E:\bin\Sencha\Cmd\5.1.3.61;C:\Users\usuario\bin\Sencha\Cmd\5.1.3.61;C:\Program Files (x86)\Intel\iCLS Client\;C:\Program Files\Intel\iCLS Client\;C:\WINDOWS\system32;C:\WINDOWS;C:\WINDOWS\System32\Wbem;C:\WINDOWS\System32\WindowsPowerShell\v1.0\;C:\Program Files\Intel\Intel(R) Management Engine Components\DAL;C:\Program Files\Intel\Intel(R) Management Engine Components\IPT;C:\Program Files (x86)\Intel\Intel(R) Management Engine Components\DAL;C:\Program Files (x86)\Intel\Intel(R) Management Engine Components\IPT;C:\Program Files (x86)\Intel\OpenCL SDK\3.0\bin\x86;C:\Program Files (x86)\Intel\OpenCL SDK\3.0\bin\x64;C:\Program Files (x86)\sbt\\bin;C:\Program Files (x86)\Heroku\bin;C:\Program Files (x86)\git\cmd;C:\Program Files (x86)\QuickTime\QTSystem\;C:\HashiCorp\Vagrant\bin;C:\Program Files (x86)\scala\bin;C:\Program Files\nodejs\;C:\Users\usuario\AppData\Local\.meteor\;C:\Users\usuario\AppData\Roaming\npm;.
java.specification.name=Java Platform API Specification
java.class.version=52.0
sun.management.compiler=HotSpot 64-Bit Tiered Compilers
os.version=10.0
user.home=C:\Users\usuario
user.timezone=Europe/Paris
java.awt.printerjob=sun.awt.windows.WPrinterJob
file.encoding=Cp1252
java.specification.version=1.8
java.class.path=C:\Users\usuario\git\spring\aspectos\Ejemplos Relacionados\SpringIoC0007Maven\target\classes;C:\Users\usuario\.m2\repository\org\springframework\spring-context\3.1.2.RELEASE\spring-context-3.1.2.RELEASE.jar;C:\Users\usuario\.m2\repository\org\springframework\spring-aop\3.1.2.RELEASE\spring-aop-3.1.2.RELEASE.jar;C:\Users\usuario\.m2\repository\aopalliance\aopalliance\1.0\aopalliance-1.0.jar;C:\Users\usuario\.m2\repository\org\springframework\spring-beans\3.1.2.RELEASE\spring-beans-3.1.2.RELEASE.jar;C:\Users\usuario\.m2\repository\org\springframework\spring-core\3.1.2.RELEASE\spring-core-3.1.2.RELEASE.jar;C:\Users\usuario\.m2\repository\commons-logging\commons-logging\1.1.1\commons-logging-1.1.1.jar;C:\Users\usuario\.m2\repository\org\springframework\spring-expression\3.1.2.RELEASE\spring-expression-3.1.2.RELEASE.jar;C:\Users\usuario\.m2\repository\org\springframework\spring-asm\3.1.2.RELEASE\spring-asm-3.1.2.RELEASE.jar;C:\Users\usuario\.m2\repository\org\springframework\spring-aspects\3.1.2.RELEASE\spring-aspects-3.1.2.RELEASE.jar;C:\Users\usuario\.m2\repository\org\springframework\spring-context-support\3.1.2.RELEASE\spring-context-support-3.1.2.RELEASE.jar;.\..\aspectjweaver.jar
user.name=usuario
java.vm.specification.version=1.8
sun.java.command=com.curso.spring.springioc0007.Main
java.home=C:\Program Files\Java\jdk1.8.0_72\jre
sun.arch.data.model=64
user.language=es
java.specification.vendor=Oracle Corporation
awt.toolkit=sun.awt.windows.WToolkit
java.vm.info=mixed mode
java.version=1.8.0_72
java.ext.dirs=C:\Program Files\Java\jdk1.8.0_72\jre\lib\ext;C:\WINDOWS\Sun\Java\lib\ext
sun.boot.class.path=C:\Program Files\Java\jdk1.8.0_72\jre\lib\resources.jar;C:\Program Files\Java\jdk1.8.0_72\jre\lib\rt.jar;C:\Program Files\Java\jdk1.8.0_72\jre\lib\sunrsasign.jar;C:\Program Files\Java\jdk1.8.0_72\jre\lib\jsse.jar;C:\Program Files\Java\jdk1.8.0_72\jre\lib\jce.jar;C:\Program Files\Java\jdk1.8.0_72\jre\lib\charsets.jar;C:\Program Files\Java\jdk1.8.0_72\jre\lib\jfr.jar;C:\Program Files\Java\jdk1.8.0_72\jre\classes
java.vendor=Oracle Corporation
file.separator=\
java.vendor.url.bug=http://bugreport.sun.com/bugreport/
sun.io.unicode.encoding=UnicodeLittle
sun.cpu.endian=little
sun.desktop=windows
sun.cpu.isalist=amd64
---- Command Line ---
Empty
---- Full Classpath ---
Empty
---- Compiler Messages ---
Empty
---- org.aspectj.weaver.ltw.LTWWorld@28c97a5 ----
Class loader:
sun.misc.Launcher$AppClassLoader@18b4aac2
Class loader parent:
sun.misc.Launcher$ExtClassLoader@722c41f4
Shadow mungers:
(around(extraFlags: 3): ((((((((((within(@org.springframework.cache.annotation.CacheEvict *) && execution(public * @org.springframework.cache.annotation.CacheEvict *.*(..))) && this(BindingTypePattern(java.lang.Object, 0))) && persingleton(org.springframework.cache.aspectj.AnnotationCacheAspect)) || (((within(@org.springframework.cache.annotation.Caching *) && execution(public * @org.springframework.cache.annotation.Caching *.*(..))) && this(BindingTypePattern(java.lang.Object, 0))) && persingleton(org.springframework.cache.aspectj.AnnotationCacheAspect))) || (((within(@org.springframework.cache.annotation.CachePut *) && execution(public * @org.springframework.cache.annotation.CachePut *.*(..))) && this(BindingTypePattern(java.lang.Object, 0))) && persingleton(org.springframework.cache.aspectj.AnnotationCacheAspect))) || (((within(@org.springframework.cache.annotation.Cacheable *) && execution(public * @org.springframework.cache.annotation.Cacheable *.*(..))) && this(BindingTypePattern(java.lang.Object, 0))) && persingleton(org.springframework.cache.aspectj.AnnotationCacheAspect))) || ((execution(@org.springframework.cache.annotation.Caching * *(..)) && this(BindingTypePattern(java.lang.Object, 0))) && persingleton(org.springframework.cache.aspectj.AnnotationCacheAspect))) || ((execution(@org.springframework.cache.annotation.Cacheable * *(..)) && this(BindingTypePattern(java.lang.Object, 0))) && persingleton(org.springframework.cache.aspectj.AnnotationCacheAspect))) || ((execution(@org.springframework.cache.annotation.CacheEvict * *(..)) && this(BindingTypePattern(java.lang.Object, 0))) && persingleton(org.springframework.cache.aspectj.AnnotationCacheAspect))) || ((execution(@org.springframework.cache.annotation.CachePut * *(..)) && this(BindingTypePattern(java.lang.Object, 0))) && persingleton(org.springframework.cache.aspectj.AnnotationCacheAspect)))->java.lang.Object org.springframework.cache.aspectj.AbstractCacheAspect.ajc$around$org_springframework_cache_aspectj_AbstractCacheAspect$1$2bc714b5(java.lang.Object, org.aspectj.runtime.internal.AroundClosure, org.aspectj.lang.JoinPoint))
(around(extraFlags: 5): ((execution(@org.springframework.scheduling.annotation.Async (void || java.util.concurrent.Future+) *(..)) && persingleton(org.springframework.scheduling.aspectj.AnnotationAsyncExecutionAspect)) || (execution((void || java.util.concurrent.Future+) @org.springframework.scheduling.annotation.Async *.*(..)) && persingleton(org.springframework.scheduling.aspectj.AnnotationAsyncExecutionAspect)))->java.lang.Object org.springframework.scheduling.aspectj.AbstractAsyncExecutionAspect.ajc$around$org_springframework_scheduling_aspectj_AbstractAsyncExecutionAspect$1$6c004c3e(org.aspectj.runtime.internal.AroundClosure, org.aspectj.lang.JoinPoint$StaticPart))
org.aspectj.weaver.Checker@5abff562
org.aspectj.weaver.Checker@12140c1d
(before(extraFlags: 4): ((((within(@org.springframework.transaction.annotation.Transactional *) && execution(public * @org.springframework.transaction.annotation.Transactional *.*(..))) && this(BindingTypePattern(java.lang.Object, 0))) && persingleton(org.springframework.transaction.aspectj.AnnotationTransactionAspect)) || ((execution(@org.springframework.transaction.annotation.Transactional * *(..)) && this(BindingTypePattern(java.lang.Object, 0))) && persingleton(org.springframework.transaction.aspectj.AnnotationTransactionAspect)))->void org.springframework.transaction.aspectj.AbstractTransactionAspect.ajc$before$org_springframework_transaction_aspectj_AbstractTransactionAspect$1$2a73e96c(java.lang.Object, org.aspectj.lang.JoinPoint$StaticPart))
(afterThrowing(extraFlags: 1): ((((within(@org.springframework.transaction.annotation.Transactional *) && execution(public * @org.springframework.transaction.annotation.Transactional *.*(..))) && this(BindingTypePattern(java.lang.Object, 0))) && persingleton(org.springframework.transaction.aspectj.AnnotationTransactionAspect)) || ((execution(@org.springframework.transaction.annotation.Transactional * *(..)) && this(BindingTypePattern(java.lang.Object, 0))) && persingleton(org.springframework.transaction.aspectj.AnnotationTransactionAspect)))->void org.springframework.transaction.aspectj.AbstractTransactionAspect.ajc$afterThrowing$org_springframework_transaction_aspectj_AbstractTransactionAspect$2$2a73e96c(java.lang.Object, java.lang.Throwable))
(afterReturning: ((((within(@org.springframework.transaction.annotation.Transactional *) && execution(public * @org.springframework.transaction.annotation.Transactional *.*(..))) && this(BindingTypePattern(java.lang.Object, 0))) && persingleton(org.springframework.transaction.aspectj.AnnotationTransactionAspect)) || ((execution(@org.springframework.transaction.annotation.Transactional * *(..)) && this(BindingTypePattern(java.lang.Object, 0))) && persingleton(org.springframework.transaction.aspectj.AnnotationTransactionAspect)))->void org.springframework.transaction.aspectj.AbstractTransactionAspect.ajc$afterReturning$org_springframework_transaction_aspectj_AbstractTransactionAspect$3$2a73e96c(java.lang.Object))
(after: ((((within(@org.springframework.transaction.annotation.Transactional *) && execution(public * @org.springframework.transaction.annotation.Transactional *.*(..))) && this(BindingTypePattern(java.lang.Object, 0))) && persingleton(org.springframework.transaction.aspectj.AnnotationTransactionAspect)) || ((execution(@org.springframework.transaction.annotation.Transactional * *(..)) && this(BindingTypePattern(java.lang.Object, 0))) && persingleton(org.springframework.transaction.aspectj.AnnotationTransactionAspect)))->void org.springframework.transaction.aspectj.AbstractTransactionAspect.ajc$after$org_springframework_transaction_aspectj_AbstractTransactionAspect$4$2a73e96c(java.lang.Object))
(before: (((((initialization(org.springframework.beans.factory.aspectj.ConfigurableObject.new(..)) && initialization(org.springframework.beans.factory.aspectj.ConfigurableObject+.new(..))) && this(BindingTypePattern(java.lang.Object, 0))) && @this(org.springframework.beans.factory.annotation.Configurable)) && if(boolean org.springframework.beans.factory.aspectj.AnnotationBeanConfigurerAspect.ajc$if$bb0(org.springframework.beans.factory.annotation.Configurable))) && persingleton(org.springframework.beans.factory.aspectj.AnnotationBeanConfigurerAspect))->void org.springframework.beans.factory.aspectj.AbstractDependencyInjectionAspect.ajc$before$org_springframework_beans_factory_aspectj_AbstractDependencyInjectionAspect$1$e854fa65(java.lang.Object))
(afterReturning: (((((initialization(org.springframework.beans.factory.aspectj.ConfigurableObject+.new(..)) && this(BindingTypePattern(java.lang.Object, 0))) && @this(org.springframework.beans.factory.annotation.Configurable)) && !(@this(org.springframework.beans.factory.annotation.Configurable) && if(boolean org.springframework.beans.factory.aspectj.AnnotationBeanConfigurerAspect.ajc$if$bb0(org.springframework.beans.factory.annotation.Configurable)))) && if(boolean org.springframework.beans.factory.aspectj.AbstractDependencyInjectionAspect.ajc$if$6f1(org.aspectj.lang.JoinPoint))) && persingleton(org.springframework.beans.factory.aspectj.AnnotationBeanConfigurerAspect))->void org.springframework.beans.factory.aspectj.AbstractDependencyInjectionAspect.ajc$afterReturning$org_springframework_beans_factory_aspectj_AbstractDependencyInjectionAspect$2$1ea6722c(java.lang.Object))
(afterReturning: (((execution(java.lang.Object org.springframework.beans.factory.aspectj.AbstractInterfaceDrivenDependencyInjectionAspect$ConfigurableDeserializationSupport+.readResolve()) && this(BindingTypePattern(java.lang.Object, 0))) && @this(org.springframework.beans.factory.annotation.Configurable)) && persingleton(org.springframework.beans.factory.aspectj.AnnotationBeanConfigurerAspect))->void org.springframework.beans.factory.aspectj.AbstractDependencyInjectionAspect.ajc$afterReturning$org_springframework_beans_factory_aspectj_AbstractDependencyInjectionAspect$3$6aa27052(java.lang.Object))
Type mungers:
(BcelTypeMunger ResolvedTypeMunger(Method, java.lang.Object org.springframework.beans.factory.aspectj.AbstractInterfaceDrivenDependencyInjectionAspect$ConfigurableDeserializationSupport.readResolve()))
(BcelTypeMunger ExposeTypeMunger(java.lang.Object))
(BcelTypeMunger ExposeTypeMunger(java.lang.Object))
(BcelTypeMunger ExposeTypeMunger(java.lang.Object))
(BcelTypeMunger ExposeTypeMunger(org.springframework.beans.factory.aspectj.ConfigurableObject))
(BcelTypeMunger ExposeTypeMunger(org.springframework.beans.factory.aspectj.AbstractInterfaceDrivenDependencyInjectionAspect$ConfigurableDeserializationSupport))
Late Type mungers:
Empty
