---- AspectJ Properties ---
AspectJ Compiler 1.6.2 built on Saturday Oct 4, 2008 at 05:47:07 GMT
---- Dump Properties ---
Dump file: ajcore.20160604.114043.326.txt
Dump reason: org.aspectj.bridge.AbortException
Dump on exception: true
Dump at exit condition: abort
---- Exception Information ---
Message: abort trouble in: 
public abstract class org.springframework.core.BridgeMethodResolver extends java.lang.Object:
  public void <init>():
                    ALOAD_0     // Lorg/springframework/core/BridgeMethodResolver; this   (line 50)
                    INVOKESPECIAL java.lang.Object.<init> ()V
    constructor-execution(void org.springframework.core.BridgeMethodResolver.<init>())
    |               RETURN
    constructor-execution(void org.springframework.core.BridgeMethodResolver.<init>())
  end public void <init>()

  public static java.lang.reflect.Method findBridgedMethod(java.lang.reflect.Method):
                    ALOAD_0     // Ljava/lang/reflect/Method; bridgeMethod   (line 62)
                    IFNULL L0
                    ALOAD_0     // Ljava/lang/reflect/Method; bridgeMethod
                    INVOKEVIRTUAL java.lang.reflect.Method.isBridge ()Z
                    IFNE L1
                L0: ALOAD_0     // Ljava/lang/reflect/Method; bridgeMethod   (line 63)
                    ARETURN
                L1: NEW java.util.ArrayList   (line 66)
                    DUP
                    INVOKESPECIAL java.util.ArrayList.<init> ()V
                    ASTORE_1
                    ALOAD_0     // Ljava/lang/reflect/Method; bridgeMethod   (line 67)
                    INVOKEVIRTUAL java.lang.reflect.Method.getDeclaringClass ()Ljava/lang/Class;
                    INVOKESTATIC org.springframework.util.ReflectionUtils.getAllDeclaredMethods (Ljava/lang/Class;)[Ljava/lang/reflect/Method;
                    ASTORE_2
                    ALOAD_2     // [Ljava/lang/reflect/Method; methods   (line 68)
                    DUP
                    ASTORE 6
                    ARRAYLENGTH
                    ISTORE 5
                    ICONST_0
                    ISTORE 4
                    GOTO L4
                L2: ALOAD 6
                    ILOAD 4
                    AALOAD
                    ASTORE_3
                    ALOAD_3     // Ljava/lang/reflect/Method; candidateMethod   (line 69)
                    ALOAD_0     // Ljava/lang/reflect/Method; bridgeMethod
                    INVOKESTATIC org.springframework.core.BridgeMethodResolver.isBridgedCandidateFor (Ljava/lang/reflect/Method;Ljava/lang/reflect/Method;)Z
                    IFEQ L3
                    ALOAD_1     // Ljava/util/List; candidateMethods   (line 70)
                    ALOAD_3     // Ljava/lang/reflect/Method; candidateMethod
                    INVOKEINTERFACE java.util.List.add (Ljava/lang/Object;)Z
                    POP
                L3: IINC 4 1   (line 68)
                L4: ILOAD 4
                    ILOAD 5
                    IF_ICMPLT L2
                    ALOAD_1     // Ljava/util/List; candidateMethods   (line 74)
                    INVOKEINTERFACE java.util.List.size ()I
                    ICONST_1
                    IF_ICMPNE L5
                    ALOAD_1     // Ljava/util/List; candidateMethods   (line 75)
                    ICONST_0
                    INVOKEINTERFACE java.util.List.get (I)Ljava/lang/Object;
                    CHECKCAST java.lang.reflect.Method
                    ARETURN
                L5: ALOAD_1     // Ljava/util/List; candidateMethods   (line 78)
                    ALOAD_0     // Ljava/lang/reflect/Method; bridgeMethod
                    INVOKESTATIC org.springframework.core.BridgeMethodResolver.searchCandidates (Ljava/util/List;Ljava/lang/reflect/Method;)Ljava/lang/reflect/Method;
                    ASTORE_3
                    ALOAD_3     // Ljava/lang/reflect/Method; bridgedMethod   (line 79)
                    IFNULL L6
                    ALOAD_3     // Ljava/lang/reflect/Method; bridgedMethod   (line 81)
                    ARETURN
                L6: ALOAD_0     // Ljava/lang/reflect/Method; bridgeMethod   (line 86)
                    ARETURN
  end public static java.lang.reflect.Method findBridgedMethod(java.lang.reflect.Method)

  private static java.lang.reflect.Method searchCandidates(java.util.List, java.lang.reflect.Method):
                    ALOAD_0     // Ljava/util/List; candidateMethods   (line 97)
                    INVOKEINTERFACE java.util.List.isEmpty ()Z
                    IFEQ L0
                    ACONST_NULL   (line 98)
                    ARETURN
                L0: ALOAD_1     // Ljava/lang/reflect/Method; bridgeMethod   (line 100)
                    INVOKEVIRTUAL java.lang.reflect.Method.getDeclaringClass ()Ljava/lang/Class;
                    INVOKESTATIC org.springframework.core.GenericTypeResolver.getTypeVariableMap (Ljava/lang/Class;)Ljava/util/Map;
                    ASTORE_2
                    ACONST_NULL   (line 101)
                    ASTORE_3
                    ICONST_1   (line 102)
                    ISTORE 4
                    ALOAD_0     // Ljava/util/List; candidateMethods   (line 103)
                    INVOKEINTERFACE java.util.List.iterator ()Ljava/util/Iterator;
                    ASTORE 6
                    GOTO L6
                L1: ALOAD 6
                    INVOKEINTERFACE java.util.Iterator.next ()Ljava/lang/Object;
                    CHECKCAST java.lang.reflect.Method
                    ASTORE 5
                    ALOAD_1     // Ljava/lang/reflect/Method; bridgeMethod   (line 104)
                    ALOAD 5     // Ljava/lang/reflect/Method; candidateMethod
                    ALOAD_2     // Ljava/util/Map; typeParameterMap
                    INVOKESTATIC org.springframework.core.BridgeMethodResolver.isBridgeMethodFor (Ljava/lang/reflect/Method;Ljava/lang/reflect/Method;Ljava/util/Map;)Z
                    IFEQ L2
                    ALOAD 5     // Ljava/lang/reflect/Method; candidateMethod   (line 105)
                    ARETURN
                L2: ALOAD_3     // Ljava/lang/reflect/Method; previousMethod   (line 107)
                    IFNULL L5
                    ILOAD 4     // Z sameSig   (line 108)
                    IFEQ L3
                    ALOAD 5     // Ljava/lang/reflect/Method; candidateMethod   (line 109)
                    INVOKEVIRTUAL java.lang.reflect.Method.getGenericParameterTypes ()[Ljava/lang/reflect/Type;
                    ALOAD_3     // Ljava/lang/reflect/Method; previousMethod
                    INVOKEVIRTUAL java.lang.reflect.Method.getGenericParameterTypes ()[Ljava/lang/reflect/Type;
                    INVOKESTATIC java.util.Arrays.equals ([Ljava/lang/Object;[Ljava/lang/Object;)Z
                    IFEQ L3
                    ICONST_1
                    GOTO L4
                L3: ICONST_0
                L4: ISTORE 4     // Z sameSig   (line 108)
                L5: ALOAD 5     // Ljava/lang/reflect/Method; candidateMethod   (line 111)
                    ASTORE_3     // Ljava/lang/reflect/Method; previousMethod
                L6: ALOAD 6   (line 103)
                    INVOKEINTERFACE java.util.Iterator.hasNext ()Z
                    IFNE L1
                    ILOAD 4     // Z sameSig   (line 113)
                    IFEQ L7
                    ALOAD_0     // Ljava/util/List; candidateMethods
                    ICONST_0
                    INVOKEINTERFACE java.util.List.get (I)Ljava/lang/Object;
                    CHECKCAST java.lang.reflect.Method
                    GOTO L8
                L7: ACONST_NULL
                L8: ARETURN
  end private static java.lang.reflect.Method searchCandidates(java.util.List, java.lang.reflect.Method)

  private static boolean isBridgedCandidateFor(java.lang.reflect.Method, java.lang.reflect.Method):
                    ALOAD_0     // Ljava/lang/reflect/Method; candidateMethod   (line 123)
                    INVOKEVIRTUAL java.lang.reflect.Method.isBridge ()Z
                    IFNE L0
                    ALOAD_0     // Ljava/lang/reflect/Method; candidateMethod
                    ALOAD_1     // Ljava/lang/reflect/Method; bridgeMethod
                    INVOKEVIRTUAL java.lang.reflect.Method.equals (Ljava/lang/Object;)Z
                    IFNE L0
                    ALOAD_0     // Ljava/lang/reflect/Method; candidateMethod   (line 124)
                    INVOKEVIRTUAL java.lang.reflect.Method.getName ()Ljava/lang/String;
                    ALOAD_1     // Ljava/lang/reflect/Method; bridgeMethod
                    INVOKEVIRTUAL java.lang.reflect.Method.getName ()Ljava/lang/String;
                    INVOKEVIRTUAL java.lang.String.equals (Ljava/lang/Object;)Z
                    IFEQ L0
                    ALOAD_0     // Ljava/lang/reflect/Method; candidateMethod   (line 125)
                    INVOKEVIRTUAL java.lang.reflect.Method.getParameterTypes ()[Ljava/lang/Class;
                    ARRAYLENGTH
                    ALOAD_1     // Ljava/lang/reflect/Method; bridgeMethod
                    INVOKEVIRTUAL java.lang.reflect.Method.getParameterTypes ()[Ljava/lang/Class;
                    ARRAYLENGTH
                    IF_ICMPNE L0
                    ICONST_1
                    IRETURN
                L0: ICONST_0
                    IRETURN   (line 123)
  end private static boolean isBridgedCandidateFor(java.lang.reflect.Method, java.lang.reflect.Method)

  static boolean isBridgeMethodFor(java.lang.reflect.Method, java.lang.reflect.Method, java.util.Map):
                    ALOAD_1     // Ljava/lang/reflect/Method; candidateMethod   (line 133)
                    ALOAD_0     // Ljava/lang/reflect/Method; bridgeMethod
                    ALOAD_2     // Ljava/util/Map; typeVariableMap
                    INVOKESTATIC org.springframework.core.BridgeMethodResolver.isResolvedTypeMatch (Ljava/lang/reflect/Method;Ljava/lang/reflect/Method;Ljava/util/Map;)Z
                    IFEQ L0
                    ICONST_1   (line 134)
                    IRETURN
                L0: ALOAD_0     // Ljava/lang/reflect/Method; bridgeMethod   (line 136)
                    INVOKESTATIC org.springframework.core.BridgeMethodResolver.findGenericDeclaration (Ljava/lang/reflect/Method;)Ljava/lang/reflect/Method;
                    ASTORE_3
                    ALOAD_3     // Ljava/lang/reflect/Method; method   (line 137)
                    IFNULL L1
                    ALOAD_3     // Ljava/lang/reflect/Method; method
                    ALOAD_1     // Ljava/lang/reflect/Method; candidateMethod
                    ALOAD_2     // Ljava/util/Map; typeVariableMap
                    INVOKESTATIC org.springframework.core.BridgeMethodResolver.isResolvedTypeMatch (Ljava/lang/reflect/Method;Ljava/lang/reflect/Method;Ljava/util/Map;)Z
                    IFEQ L1
                    ICONST_1
                    IRETURN
                L1: ICONST_0
                    IRETURN
  end static boolean isBridgeMethodFor(java.lang.reflect.Method, java.lang.reflect.Method, java.util.Map)

  private static java.lang.reflect.Method findGenericDeclaration(java.lang.reflect.Method):
                    ALOAD_0     // Ljava/lang/reflect/Method; bridgeMethod   (line 147)
                    INVOKEVIRTUAL java.lang.reflect.Method.getDeclaringClass ()Ljava/lang/Class;
                    INVOKEVIRTUAL java.lang.Class.getSuperclass ()Ljava/lang/Class;
                    ASTORE_1
                    GOTO L2   (line 148)
                L0: ALOAD_1     // Ljava/lang/Class; superclass   (line 149)
                    ALOAD_0     // Ljava/lang/reflect/Method; bridgeMethod
                    INVOKESTATIC org.springframework.core.BridgeMethodResolver.searchForMatch (Ljava/lang/Class;Ljava/lang/reflect/Method;)Ljava/lang/reflect/Method;
                    ASTORE_2
                    ALOAD_2     // Ljava/lang/reflect/Method; method   (line 150)
                    IFNULL L1
                    ALOAD_2     // Ljava/lang/reflect/Method; method
                    INVOKEVIRTUAL java.lang.reflect.Method.isBridge ()Z
                    IFNE L1
                    ALOAD_2     // Ljava/lang/reflect/Method; method   (line 151)
                    ARETURN
                L1: ALOAD_1     // Ljava/lang/Class; superclass   (line 153)
                    INVOKEVIRTUAL java.lang.Class.getSuperclass ()Ljava/lang/Class;
                    ASTORE_1     // Ljava/lang/Class; superclass
                L2: LDC java.lang.Object   (line 148)
                    ALOAD_1     // Ljava/lang/Class; superclass
                    INVOKEVIRTUAL java.lang.Object.equals (Ljava/lang/Object;)Z
                    IFEQ L0
                    ALOAD_0     // Ljava/lang/reflect/Method; bridgeMethod   (line 157)
                    INVOKEVIRTUAL java.lang.reflect.Method.getDeclaringClass ()Ljava/lang/Class;
                    INVOKESTATIC org.springframework.util.ClassUtils.getAllInterfacesForClass (Ljava/lang/Class;)[Ljava/lang/Class;
                    ASTORE_2
                    ALOAD_2     // [Ljava/lang/Class; interfaces   (line 158)
                    DUP
                    ASTORE 6
                    ARRAYLENGTH
                    ISTORE 5
                    ICONST_0
                    ISTORE 4
                    GOTO L5
                L3: ALOAD 6
                    ILOAD 4
                    AALOAD
                    ASTORE_3
                    ALOAD_3     // Ljava/lang/Class; ifc   (line 159)
                    ALOAD_0     // Ljava/lang/reflect/Method; bridgeMethod
                    INVOKESTATIC org.springframework.core.BridgeMethodResolver.searchForMatch (Ljava/lang/Class;Ljava/lang/reflect/Method;)Ljava/lang/reflect/Method;
                    ASTORE 7
                    ALOAD 7     // Ljava/lang/reflect/Method; method   (line 160)
                    IFNULL L4
                    ALOAD 7     // Ljava/lang/reflect/Method; method
                    INVOKEVIRTUAL java.lang.reflect.Method.isBridge ()Z
                    IFNE L4
                    ALOAD 7     // Ljava/lang/reflect/Method; method   (line 161)
                    ARETURN
                L4: IINC 4 1   (line 158)
                L5: ILOAD 4
                    ILOAD 5
                    IF_ICMPLT L3
                    ACONST_NULL   (line 165)
                    ARETURN
  end private static java.lang.reflect.Method findGenericDeclaration(java.lang.reflect.Method)

  private static boolean isResolvedTypeMatch(java.lang.reflect.Method, java.lang.reflect.Method, java.util.Map):
                    ALOAD_0     // Ljava/lang/reflect/Method; genericMethod   (line 177)
                    INVOKEVIRTUAL java.lang.reflect.Method.getGenericParameterTypes ()[Ljava/lang/reflect/Type;
                    ASTORE_3
                    ALOAD_1     // Ljava/lang/reflect/Method; candidateMethod   (line 178)
                    INVOKEVIRTUAL java.lang.reflect.Method.getParameterTypes ()[Ljava/lang/Class;
                    ASTORE 4
                    ALOAD_3     // [Ljava/lang/reflect/Type; genericParameters   (line 179)
                    ARRAYLENGTH
                    ALOAD 4     // [Ljava/lang/Class; candidateParameters
                    ARRAYLENGTH
                    IF_ICMPEQ L0
                    ICONST_0   (line 180)
                    IRETURN
                L0: ICONST_0   (line 182)
                    ISTORE 5
                    GOTO L4
                L1: ALOAD_3     // [Ljava/lang/reflect/Type; genericParameters   (line 183)
                    ILOAD 5     // I i
                    AALOAD
                    ASTORE 6
                    ALOAD 4     // [Ljava/lang/Class; candidateParameters   (line 184)
                    ILOAD 5     // I i
                    AALOAD
                    ASTORE 7
                    ALOAD 7     // Ljava/lang/Class; candidateParameter   (line 185)
                    INVOKEVIRTUAL java.lang.Class.isArray ()Z
                    IFEQ L2
                    ALOAD 6     // Ljava/lang/reflect/Type; genericParameter   (line 187)
                    ALOAD_2     // Ljava/util/Map; typeVariableMap
                    INVOKESTATIC org.springframework.core.GenericTypeResolver.getRawType (Ljava/lang/reflect/Type;Ljava/util/Map;)Ljava/lang/reflect/Type;
                    ASTORE 8
                    ALOAD 8     // Ljava/lang/reflect/Type; rawType   (line 188)
                    INSTANCEOF java.lang.reflect.GenericArrayType
                    IFEQ L2
                    ALOAD 7     // Ljava/lang/Class; candidateParameter   (line 189)
                    INVOKEVIRTUAL java.lang.Class.getComponentType ()Ljava/lang/Class;
                    ALOAD 8     // Ljava/lang/reflect/Type; rawType   (line 190)
                    CHECKCAST java.lang.reflect.GenericArrayType
                    INVOKEINTERFACE java.lang.reflect.GenericArrayType.getGenericComponentType ()Ljava/lang/reflect/Type;
                    ALOAD_2     // Ljava/util/Map; typeVariableMap
                    INVOKESTATIC org.springframework.core.GenericTypeResolver.resolveType (Ljava/lang/reflect/Type;Ljava/util/Map;)Ljava/lang/Class;
                    INVOKEVIRTUAL java.lang.Object.equals (Ljava/lang/Object;)Z   (line 189)
                    IFNE L5
                    ICONST_0   (line 191)
                    IRETURN
                L2: ALOAD 6     // Ljava/lang/reflect/Type; genericParameter   (line 197)
                    ALOAD_2     // Ljava/util/Map; typeVariableMap
                    INVOKESTATIC org.springframework.core.GenericTypeResolver.resolveType (Ljava/lang/reflect/Type;Ljava/util/Map;)Ljava/lang/Class;
                    ASTORE 8
                    ALOAD 7     // Ljava/lang/Class; candidateParameter   (line 198)
                    ALOAD 8     // Ljava/lang/Class; resolvedParameter
                    INVOKEVIRTUAL java.lang.Object.equals (Ljava/lang/Object;)Z
                    IFNE L3
                    ICONST_0   (line 199)
                    IRETURN
                L3: IINC 5 1     // I i   (line 182)
                L4: ILOAD 5     // I i
                    ALOAD_3     // [Ljava/lang/reflect/Type; genericParameters
                    ARRAYLENGTH
                    IF_ICMPLT L1
                L5: ICONST_1   (line 202)
                    IRETURN
  end private static boolean isResolvedTypeMatch(java.lang.reflect.Method, java.lang.reflect.Method, java.util.Map)

  private static java.lang.reflect.Method searchForMatch(Class, java.lang.reflect.Method):
                    ALOAD_0     // Ljava/lang/Class; type   (line 211)
                    ALOAD_1     // Ljava/lang/reflect/Method; bridgeMethod
                    INVOKEVIRTUAL java.lang.reflect.Method.getName ()Ljava/lang/String;
                    ALOAD_1     // Ljava/lang/reflect/Method; bridgeMethod
                    INVOKEVIRTUAL java.lang.reflect.Method.getParameterTypes ()[Ljava/lang/Class;
                    INVOKESTATIC org.springframework.util.ReflectionUtils.findMethod (Ljava/lang/Class;Ljava/lang/String;[Ljava/lang/Class;)Ljava/lang/reflect/Method;
                    ARETURN
  end private static java.lang.reflect.Method searchForMatch(Class, java.lang.reflect.Method)

  public static boolean isVisibilityBridgeMethodPair(java.lang.reflect.Method, java.lang.reflect.Method):
                    ALOAD_0     // Ljava/lang/reflect/Method; bridgeMethod   (line 222)
                    IFNULL L0
                    ICONST_1
                    GOTO L1
                L0: ICONST_0
                L1: INVOKESTATIC org.springframework.util.Assert.isTrue (Z)V
                    ALOAD_1     // Ljava/lang/reflect/Method; bridgedMethod   (line 223)
                    IFNULL L2
                    ICONST_1
                    GOTO L3
                L2: ICONST_0
                L3: INVOKESTATIC org.springframework.util.Assert.isTrue (Z)V
                    ALOAD_0     // Ljava/lang/reflect/Method; bridgeMethod   (line 224)
                    ALOAD_1     // Ljava/lang/reflect/Method; bridgedMethod
                    IF_ACMPNE L4
                    ICONST_1   (line 225)
                    IRETURN
                L4: ALOAD_0     // Ljava/lang/reflect/Method; bridgeMethod   (line 227)
                    INVOKEVIRTUAL java.lang.reflect.Method.getParameterTypes ()[Ljava/lang/Class;
                    ALOAD_1     // Ljava/lang/reflect/Method; bridgedMethod
                    INVOKEVIRTUAL java.lang.reflect.Method.getParameterTypes ()[Ljava/lang/Class;
                    INVOKESTATIC java.util.Arrays.equals ([Ljava/lang/Object;[Ljava/lang/Object;)Z
                    IFEQ L5
                    ALOAD_0     // Ljava/lang/reflect/Method; bridgeMethod   (line 228)
                    INVOKEVIRTUAL java.lang.reflect.Method.getReturnType ()Ljava/lang/Class;
                    ALOAD_1     // Ljava/lang/reflect/Method; bridgedMethod
                    INVOKEVIRTUAL java.lang.reflect.Method.getReturnType ()Ljava/lang/Class;
                    INVOKEVIRTUAL java.lang.Object.equals (Ljava/lang/Object;)Z
                    IFEQ L5
                    ICONST_1
                    IRETURN
                L5: ICONST_0
                    IRETURN   (line 227)
  end public static boolean isVisibilityBridgeMethodPair(java.lang.reflect.Method, java.lang.reflect.Method)

end public abstract class org.springframework.core.BridgeMethodResolver
 -- (NullPointerException) null
null
java.lang.NullPointerException

org.aspectj.bridge.AbortException: trouble in: 
public abstract class org.springframework.core.BridgeMethodResolver extends java.lang.Object:
  public void <init>():
                    ALOAD_0     // Lorg/springframework/core/BridgeMethodResolver; this   (line 50)
                    INVOKESPECIAL java.lang.Object.<init> ()V
    constructor-execution(void org.springframework.core.BridgeMethodResolver.<init>())
    |               RETURN
    constructor-execution(void org.springframework.core.BridgeMethodResolver.<init>())
  end public void <init>()

  public static java.lang.reflect.Method findBridgedMethod(java.lang.reflect.Method):
                    ALOAD_0     // Ljava/lang/reflect/Method; bridgeMethod   (line 62)
                    IFNULL L0
                    ALOAD_0     // Ljava/lang/reflect/Method; bridgeMethod
                    INVOKEVIRTUAL java.lang.reflect.Method.isBridge ()Z
                    IFNE L1
                L0: ALOAD_0     // Ljava/lang/reflect/Method; bridgeMethod   (line 63)
                    ARETURN
                L1: NEW java.util.ArrayList   (line 66)
                    DUP
                    INVOKESPECIAL java.util.ArrayList.<init> ()V
                    ASTORE_1
                    ALOAD_0     // Ljava/lang/reflect/Method; bridgeMethod   (line 67)
                    INVOKEVIRTUAL java.lang.reflect.Method.getDeclaringClass ()Ljava/lang/Class;
                    INVOKESTATIC org.springframework.util.ReflectionUtils.getAllDeclaredMethods (Ljava/lang/Class;)[Ljava/lang/reflect/Method;
                    ASTORE_2
                    ALOAD_2     // [Ljava/lang/reflect/Method; methods   (line 68)
                    DUP
                    ASTORE 6
                    ARRAYLENGTH
                    ISTORE 5
                    ICONST_0
                    ISTORE 4
                    GOTO L4
                L2: ALOAD 6
                    ILOAD 4
                    AALOAD
                    ASTORE_3
                    ALOAD_3     // Ljava/lang/reflect/Method; candidateMethod   (line 69)
                    ALOAD_0     // Ljava/lang/reflect/Method; bridgeMethod
                    INVOKESTATIC org.springframework.core.BridgeMethodResolver.isBridgedCandidateFor (Ljava/lang/reflect/Method;Ljava/lang/reflect/Method;)Z
                    IFEQ L3
                    ALOAD_1     // Ljava/util/List; candidateMethods   (line 70)
                    ALOAD_3     // Ljava/lang/reflect/Method; candidateMethod
                    INVOKEINTERFACE java.util.List.add (Ljava/lang/Object;)Z
                    POP
                L3: IINC 4 1   (line 68)
                L4: ILOAD 4
                    ILOAD 5
                    IF_ICMPLT L2
                    ALOAD_1     // Ljava/util/List; candidateMethods   (line 74)
                    INVOKEINTERFACE java.util.List.size ()I
                    ICONST_1
                    IF_ICMPNE L5
                    ALOAD_1     // Ljava/util/List; candidateMethods   (line 75)
                    ICONST_0
                    INVOKEINTERFACE java.util.List.get (I)Ljava/lang/Object;
                    CHECKCAST java.lang.reflect.Method
                    ARETURN
                L5: ALOAD_1     // Ljava/util/List; candidateMethods   (line 78)
                    ALOAD_0     // Ljava/lang/reflect/Method; bridgeMethod
                    INVOKESTATIC org.springframework.core.BridgeMethodResolver.searchCandidates (Ljava/util/List;Ljava/lang/reflect/Method;)Ljava/lang/reflect/Method;
                    ASTORE_3
                    ALOAD_3     // Ljava/lang/reflect/Method; bridgedMethod   (line 79)
                    IFNULL L6
                    ALOAD_3     // Ljava/lang/reflect/Method; bridgedMethod   (line 81)
                    ARETURN
                L6: ALOAD_0     // Ljava/lang/reflect/Method; bridgeMethod   (line 86)
                    ARETURN
  end public static java.lang.reflect.Method findBridgedMethod(java.lang.reflect.Method)

  private static java.lang.reflect.Method searchCandidates(java.util.List, java.lang.reflect.Method):
                    ALOAD_0     // Ljava/util/List; candidateMethods   (line 97)
                    INVOKEINTERFACE java.util.List.isEmpty ()Z
                    IFEQ L0
                    ACONST_NULL   (line 98)
                    ARETURN
                L0: ALOAD_1     // Ljava/lang/reflect/Method; bridgeMethod   (line 100)
                    INVOKEVIRTUAL java.lang.reflect.Method.getDeclaringClass ()Ljava/lang/Class;
                    INVOKESTATIC org.springframework.core.GenericTypeResolver.getTypeVariableMap (Ljava/lang/Class;)Ljava/util/Map;
                    ASTORE_2
                    ACONST_NULL   (line 101)
                    ASTORE_3
                    ICONST_1   (line 102)
                    ISTORE 4
                    ALOAD_0     // Ljava/util/List; candidateMethods   (line 103)
                    INVOKEINTERFACE java.util.List.iterator ()Ljava/util/Iterator;
                    ASTORE 6
                    GOTO L6
                L1: ALOAD 6
                    INVOKEINTERFACE java.util.Iterator.next ()Ljava/lang/Object;
                    CHECKCAST java.lang.reflect.Method
                    ASTORE 5
                    ALOAD_1     // Ljava/lang/reflect/Method; bridgeMethod   (line 104)
                    ALOAD 5     // Ljava/lang/reflect/Method; candidateMethod
                    ALOAD_2     // Ljava/util/Map; typeParameterMap
                    INVOKESTATIC org.springframework.core.BridgeMethodResolver.isBridgeMethodFor (Ljava/lang/reflect/Method;Ljava/lang/reflect/Method;Ljava/util/Map;)Z
                    IFEQ L2
                    ALOAD 5     // Ljava/lang/reflect/Method; candidateMethod   (line 105)
                    ARETURN
                L2: ALOAD_3     // Ljava/lang/reflect/Method; previousMethod   (line 107)
                    IFNULL L5
                    ILOAD 4     // Z sameSig   (line 108)
                    IFEQ L3
                    ALOAD 5     // Ljava/lang/reflect/Method; candidateMethod   (line 109)
                    INVOKEVIRTUAL java.lang.reflect.Method.getGenericParameterTypes ()[Ljava/lang/reflect/Type;
                    ALOAD_3     // Ljava/lang/reflect/Method; previousMethod
                    INVOKEVIRTUAL java.lang.reflect.Method.getGenericParameterTypes ()[Ljava/lang/reflect/Type;
                    INVOKESTATIC java.util.Arrays.equals ([Ljava/lang/Object;[Ljava/lang/Object;)Z
                    IFEQ L3
                    ICONST_1
                    GOTO L4
                L3: ICONST_0
                L4: ISTORE 4     // Z sameSig   (line 108)
                L5: ALOAD 5     // Ljava/lang/reflect/Method; candidateMethod   (line 111)
                    ASTORE_3     // Ljava/lang/reflect/Method; previousMethod
                L6: ALOAD 6   (line 103)
                    INVOKEINTERFACE java.util.Iterator.hasNext ()Z
                    IFNE L1
                    ILOAD 4     // Z sameSig   (line 113)
                    IFEQ L7
                    ALOAD_0     // Ljava/util/List; candidateMethods
                    ICONST_0
                    INVOKEINTERFACE java.util.List.get (I)Ljava/lang/Object;
                    CHECKCAST java.lang.reflect.Method
                    GOTO L8
                L7: ACONST_NULL
                L8: ARETURN
  end private static java.lang.reflect.Method searchCandidates(java.util.List, java.lang.reflect.Method)

  private static boolean isBridgedCandidateFor(java.lang.reflect.Method, java.lang.reflect.Method):
                    ALOAD_0     // Ljava/lang/reflect/Method; candidateMethod   (line 123)
                    INVOKEVIRTUAL java.lang.reflect.Method.isBridge ()Z
                    IFNE L0
                    ALOAD_0     // Ljava/lang/reflect/Method; candidateMethod
                    ALOAD_1     // Ljava/lang/reflect/Method; bridgeMethod
                    INVOKEVIRTUAL java.lang.reflect.Method.equals (Ljava/lang/Object;)Z
                    IFNE L0
                    ALOAD_0     // Ljava/lang/reflect/Method; candidateMethod   (line 124)
                    INVOKEVIRTUAL java.lang.reflect.Method.getName ()Ljava/lang/String;
                    ALOAD_1     // Ljava/lang/reflect/Method; bridgeMethod
                    INVOKEVIRTUAL java.lang.reflect.Method.getName ()Ljava/lang/String;
                    INVOKEVIRTUAL java.lang.String.equals (Ljava/lang/Object;)Z
                    IFEQ L0
                    ALOAD_0     // Ljava/lang/reflect/Method; candidateMethod   (line 125)
                    INVOKEVIRTUAL java.lang.reflect.Method.getParameterTypes ()[Ljava/lang/Class;
                    ARRAYLENGTH
                    ALOAD_1     // Ljava/lang/reflect/Method; bridgeMethod
                    INVOKEVIRTUAL java.lang.reflect.Method.getParameterTypes ()[Ljava/lang/Class;
                    ARRAYLENGTH
                    IF_ICMPNE L0
                    ICONST_1
                    IRETURN
                L0: ICONST_0
                    IRETURN   (line 123)
  end private static boolean isBridgedCandidateFor(java.lang.reflect.Method, java.lang.reflect.Method)

  static boolean isBridgeMethodFor(java.lang.reflect.Method, java.lang.reflect.Method, java.util.Map):
                    ALOAD_1     // Ljava/lang/reflect/Method; candidateMethod   (line 133)
                    ALOAD_0     // Ljava/lang/reflect/Method; bridgeMethod
                    ALOAD_2     // Ljava/util/Map; typeVariableMap
                    INVOKESTATIC org.springframework.core.BridgeMethodResolver.isResolvedTypeMatch (Ljava/lang/reflect/Method;Ljava/lang/reflect/Method;Ljava/util/Map;)Z
                    IFEQ L0
                    ICONST_1   (line 134)
                    IRETURN
                L0: ALOAD_0     // Ljava/lang/reflect/Method; bridgeMethod   (line 136)
                    INVOKESTATIC org.springframework.core.BridgeMethodResolver.findGenericDeclaration (Ljava/lang/reflect/Method;)Ljava/lang/reflect/Method;
                    ASTORE_3
                    ALOAD_3     // Ljava/lang/reflect/Method; method   (line 137)
                    IFNULL L1
                    ALOAD_3     // Ljava/lang/reflect/Method; method
                    ALOAD_1     // Ljava/lang/reflect/Method; candidateMethod
                    ALOAD_2     // Ljava/util/Map; typeVariableMap
                    INVOKESTATIC org.springframework.core.BridgeMethodResolver.isResolvedTypeMatch (Ljava/lang/reflect/Method;Ljava/lang/reflect/Method;Ljava/util/Map;)Z
                    IFEQ L1
                    ICONST_1
                    IRETURN
                L1: ICONST_0
                    IRETURN
  end static boolean isBridgeMethodFor(java.lang.reflect.Method, java.lang.reflect.Method, java.util.Map)

  private static java.lang.reflect.Method findGenericDeclaration(java.lang.reflect.Method):
                    ALOAD_0     // Ljava/lang/reflect/Method; bridgeMethod   (line 147)
                    INVOKEVIRTUAL java.lang.reflect.Method.getDeclaringClass ()Ljava/lang/Class;
                    INVOKEVIRTUAL java.lang.Class.getSuperclass ()Ljava/lang/Class;
                    ASTORE_1
                    GOTO L2   (line 148)
                L0: ALOAD_1     // Ljava/lang/Class; superclass   (line 149)
                    ALOAD_0     // Ljava/lang/reflect/Method; bridgeMethod
                    INVOKESTATIC org.springframework.core.BridgeMethodResolver.searchForMatch (Ljava/lang/Class;Ljava/lang/reflect/Method;)Ljava/lang/reflect/Method;
                    ASTORE_2
                    ALOAD_2     // Ljava/lang/reflect/Method; method   (line 150)
                    IFNULL L1
                    ALOAD_2     // Ljava/lang/reflect/Method; method
                    INVOKEVIRTUAL java.lang.reflect.Method.isBridge ()Z
                    IFNE L1
                    ALOAD_2     // Ljava/lang/reflect/Method; method   (line 151)
                    ARETURN
                L1: ALOAD_1     // Ljava/lang/Class; superclass   (line 153)
                    INVOKEVIRTUAL java.lang.Class.getSuperclass ()Ljava/lang/Class;
                    ASTORE_1     // Ljava/lang/Class; superclass
                L2: LDC java.lang.Object   (line 148)
                    ALOAD_1     // Ljava/lang/Class; superclass
                    INVOKEVIRTUAL java.lang.Object.equals (Ljava/lang/Object;)Z
                    IFEQ L0
                    ALOAD_0     // Ljava/lang/reflect/Method; bridgeMethod   (line 157)
                    INVOKEVIRTUAL java.lang.reflect.Method.getDeclaringClass ()Ljava/lang/Class;
                    INVOKESTATIC org.springframework.util.ClassUtils.getAllInterfacesForClass (Ljava/lang/Class;)[Ljava/lang/Class;
                    ASTORE_2
                    ALOAD_2     // [Ljava/lang/Class; interfaces   (line 158)
                    DUP
                    ASTORE 6
                    ARRAYLENGTH
                    ISTORE 5
                    ICONST_0
                    ISTORE 4
                    GOTO L5
                L3: ALOAD 6
                    ILOAD 4
                    AALOAD
                    ASTORE_3
                    ALOAD_3     // Ljava/lang/Class; ifc   (line 159)
                    ALOAD_0     // Ljava/lang/reflect/Method; bridgeMethod
                    INVOKESTATIC org.springframework.core.BridgeMethodResolver.searchForMatch (Ljava/lang/Class;Ljava/lang/reflect/Method;)Ljava/lang/reflect/Method;
                    ASTORE 7
                    ALOAD 7     // Ljava/lang/reflect/Method; method   (line 160)
                    IFNULL L4
                    ALOAD 7     // Ljava/lang/reflect/Method; method
                    INVOKEVIRTUAL java.lang.reflect.Method.isBridge ()Z
                    IFNE L4
                    ALOAD 7     // Ljava/lang/reflect/Method; method   (line 161)
                    ARETURN
                L4: IINC 4 1   (line 158)
                L5: ILOAD 4
                    ILOAD 5
                    IF_ICMPLT L3
                    ACONST_NULL   (line 165)
                    ARETURN
  end private static java.lang.reflect.Method findGenericDeclaration(java.lang.reflect.Method)

  private static boolean isResolvedTypeMatch(java.lang.reflect.Method, java.lang.reflect.Method, java.util.Map):
                    ALOAD_0     // Ljava/lang/reflect/Method; genericMethod   (line 177)
                    INVOKEVIRTUAL java.lang.reflect.Method.getGenericParameterTypes ()[Ljava/lang/reflect/Type;
                    ASTORE_3
                    ALOAD_1     // Ljava/lang/reflect/Method; candidateMethod   (line 178)
                    INVOKEVIRTUAL java.lang.reflect.Method.getParameterTypes ()[Ljava/lang/Class;
                    ASTORE 4
                    ALOAD_3     // [Ljava/lang/reflect/Type; genericParameters   (line 179)
                    ARRAYLENGTH
                    ALOAD 4     // [Ljava/lang/Class; candidateParameters
                    ARRAYLENGTH
                    IF_ICMPEQ L0
                    ICONST_0   (line 180)
                    IRETURN
                L0: ICONST_0   (line 182)
                    ISTORE 5
                    GOTO L4
                L1: ALOAD_3     // [Ljava/lang/reflect/Type; genericParameters   (line 183)
                    ILOAD 5     // I i
                    AALOAD
                    ASTORE 6
                    ALOAD 4     // [Ljava/lang/Class; candidateParameters   (line 184)
                    ILOAD 5     // I i
                    AALOAD
                    ASTORE 7
                    ALOAD 7     // Ljava/lang/Class; candidateParameter   (line 185)
                    INVOKEVIRTUAL java.lang.Class.isArray ()Z
                    IFEQ L2
                    ALOAD 6     // Ljava/lang/reflect/Type; genericParameter   (line 187)
                    ALOAD_2     // Ljava/util/Map; typeVariableMap
                    INVOKESTATIC org.springframework.core.GenericTypeResolver.getRawType (Ljava/lang/reflect/Type;Ljava/util/Map;)Ljava/lang/reflect/Type;
                    ASTORE 8
                    ALOAD 8     // Ljava/lang/reflect/Type; rawType   (line 188)
                    INSTANCEOF java.lang.reflect.GenericArrayType
                    IFEQ L2
                    ALOAD 7     // Ljava/lang/Class; candidateParameter   (line 189)
                    INVOKEVIRTUAL java.lang.Class.getComponentType ()Ljava/lang/Class;
                    ALOAD 8     // Ljava/lang/reflect/Type; rawType   (line 190)
                    CHECKCAST java.lang.reflect.GenericArrayType
                    INVOKEINTERFACE java.lang.reflect.GenericArrayType.getGenericComponentType ()Ljava/lang/reflect/Type;
                    ALOAD_2     // Ljava/util/Map; typeVariableMap
                    INVOKESTATIC org.springframework.core.GenericTypeResolver.resolveType (Ljava/lang/reflect/Type;Ljava/util/Map;)Ljava/lang/Class;
                    INVOKEVIRTUAL java.lang.Object.equals (Ljava/lang/Object;)Z   (line 189)
                    IFNE L5
                    ICONST_0   (line 191)
                    IRETURN
                L2: ALOAD 6     // Ljava/lang/reflect/Type; genericParameter   (line 197)
                    ALOAD_2     // Ljava/util/Map; typeVariableMap
                    INVOKESTATIC org.springframework.core.GenericTypeResolver.resolveType (Ljava/lang/reflect/Type;Ljava/util/Map;)Ljava/lang/Class;
                    ASTORE 8
                    ALOAD 7     // Ljava/lang/Class; candidateParameter   (line 198)
                    ALOAD 8     // Ljava/lang/Class; resolvedParameter
                    INVOKEVIRTUAL java.lang.Object.equals (Ljava/lang/Object;)Z
                    IFNE L3
                    ICONST_0   (line 199)
                    IRETURN
                L3: IINC 5 1     // I i   (line 182)
                L4: ILOAD 5     // I i
                    ALOAD_3     // [Ljava/lang/reflect/Type; genericParameters
                    ARRAYLENGTH
                    IF_ICMPLT L1
                L5: ICONST_1   (line 202)
                    IRETURN
  end private static boolean isResolvedTypeMatch(java.lang.reflect.Method, java.lang.reflect.Method, java.util.Map)

  private static java.lang.reflect.Method searchForMatch(Class, java.lang.reflect.Method):
                    ALOAD_0     // Ljava/lang/Class; type   (line 211)
                    ALOAD_1     // Ljava/lang/reflect/Method; bridgeMethod
                    INVOKEVIRTUAL java.lang.reflect.Method.getName ()Ljava/lang/String;
                    ALOAD_1     // Ljava/lang/reflect/Method; bridgeMethod
                    INVOKEVIRTUAL java.lang.reflect.Method.getParameterTypes ()[Ljava/lang/Class;
                    INVOKESTATIC org.springframework.util.ReflectionUtils.findMethod (Ljava/lang/Class;Ljava/lang/String;[Ljava/lang/Class;)Ljava/lang/reflect/Method;
                    ARETURN
  end private static java.lang.reflect.Method searchForMatch(Class, java.lang.reflect.Method)

  public static boolean isVisibilityBridgeMethodPair(java.lang.reflect.Method, java.lang.reflect.Method):
                    ALOAD_0     // Ljava/lang/reflect/Method; bridgeMethod   (line 222)
                    IFNULL L0
                    ICONST_1
                    GOTO L1
                L0: ICONST_0
                L1: INVOKESTATIC org.springframework.util.Assert.isTrue (Z)V
                    ALOAD_1     // Ljava/lang/reflect/Method; bridgedMethod   (line 223)
                    IFNULL L2
                    ICONST_1
                    GOTO L3
                L2: ICONST_0
                L3: INVOKESTATIC org.springframework.util.Assert.isTrue (Z)V
                    ALOAD_0     // Ljava/lang/reflect/Method; bridgeMethod   (line 224)
                    ALOAD_1     // Ljava/lang/reflect/Method; bridgedMethod
                    IF_ACMPNE L4
                    ICONST_1   (line 225)
                    IRETURN
                L4: ALOAD_0     // Ljava/lang/reflect/Method; bridgeMethod   (line 227)
                    INVOKEVIRTUAL java.lang.reflect.Method.getParameterTypes ()[Ljava/lang/Class;
                    ALOAD_1     // Ljava/lang/reflect/Method; bridgedMethod
                    INVOKEVIRTUAL java.lang.reflect.Method.getParameterTypes ()[Ljava/lang/Class;
                    INVOKESTATIC java.util.Arrays.equals ([Ljava/lang/Object;[Ljava/lang/Object;)Z
                    IFEQ L5
                    ALOAD_0     // Ljava/lang/reflect/Method; bridgeMethod   (line 228)
                    INVOKEVIRTUAL java.lang.reflect.Method.getReturnType ()Ljava/lang/Class;
                    ALOAD_1     // Ljava/lang/reflect/Method; bridgedMethod
                    INVOKEVIRTUAL java.lang.reflect.Method.getReturnType ()Ljava/lang/Class;
                    INVOKEVIRTUAL java.lang.Object.equals (Ljava/lang/Object;)Z
                    IFEQ L5
                    ICONST_1
                    IRETURN
                L5: ICONST_0
                    IRETURN   (line 227)
  end public static boolean isVisibilityBridgeMethodPair(java.lang.reflect.Method, java.lang.reflect.Method)

end public abstract class org.springframework.core.BridgeMethodResolver

	at org.aspectj.bridge.MessageWriter.handleMessage(MessageWriter.java:47)
	at org.aspectj.weaver.tools.WeavingAdaptor$WeavingAdaptorMessageWriter.handleMessage(WeavingAdaptor.java:665)
	at org.aspectj.weaver.tools.WeavingAdaptor$WeavingAdaptorMessageHolder.handleMessage(WeavingAdaptor.java:615)
	at org.aspectj.weaver.bcel.BcelWeaver.weave(BcelWeaver.java:1752)
	at org.aspectj.weaver.bcel.BcelWeaver.weaveWithoutDump(BcelWeaver.java:1694)
	at org.aspectj.weaver.bcel.BcelWeaver.weaveAndNotify(BcelWeaver.java:1464)
	at org.aspectj.weaver.bcel.BcelWeaver.weave(BcelWeaver.java:1273)
	at org.aspectj.weaver.tools.WeavingAdaptor.getWovenBytes(WeavingAdaptor.java:394)
	at org.aspectj.weaver.tools.WeavingAdaptor.weaveClass(WeavingAdaptor.java:281)
	at org.aspectj.weaver.loadtime.Aj.preProcess(Aj.java:95)
	at org.aspectj.weaver.loadtime.ClassPreProcessorAgentAdapter.transform(ClassPreProcessorAgentAdapter.java:52)
	at sun.instrument.TransformerManager.transform(TransformerManager.java:188)
	at sun.instrument.InstrumentationImpl.transform(InstrumentationImpl.java:428)
	at java.lang.ClassLoader.defineClass1(Native Method)
	at java.lang.ClassLoader.defineClass(ClassLoader.java:760)
	at java.security.SecureClassLoader.defineClass(SecureClassLoader.java:142)
	at java.net.URLClassLoader.defineClass(URLClassLoader.java:467)
	at java.net.URLClassLoader.access$100(URLClassLoader.java:73)
	at java.net.URLClassLoader$1.run(URLClassLoader.java:368)
	at java.net.URLClassLoader$1.run(URLClassLoader.java:362)
	at java.security.AccessController.doPrivileged(Native Method)
	at java.net.URLClassLoader.findClass(URLClassLoader.java:361)
	at java.lang.ClassLoader.loadClass(ClassLoader.java:424)
	at sun.misc.Launcher$AppClassLoader.loadClass(Launcher.java:331)
	at java.lang.ClassLoader.loadClass(ClassLoader.java:357)
	at org.springframework.beans.GenericTypeAwarePropertyDescriptor.<init>(GenericTypeAwarePropertyDescriptor.java:66)
	at org.springframework.beans.CachedIntrospectionResults.buildGenericTypeAwarePropertyDescriptor(CachedIntrospectionResults.java:300)
	at org.springframework.beans.CachedIntrospectionResults.<init>(CachedIntrospectionResults.java:256)
	at org.springframework.beans.CachedIntrospectionResults.forClass(CachedIntrospectionResults.java:149)
	at org.springframework.beans.BeanWrapperImpl.getCachedIntrospectionResults(BeanWrapperImpl.java:324)
	at org.springframework.beans.BeanWrapperImpl.getPropertyDescriptorInternal(BeanWrapperImpl.java:354)
	at org.springframework.beans.BeanWrapperImpl.isWritableProperty(BeanWrapperImpl.java:430)
	at org.springframework.beans.factory.support.AbstractAutowireCapableBeanFactory.applyPropertyValues(AbstractAutowireCapableBeanFactory.java:1362)
	at org.springframework.beans.factory.support.AbstractAutowireCapableBeanFactory.populateBean(AbstractAutowireCapableBeanFactory.java:1118)
	at org.springframework.beans.factory.support.AbstractAutowireCapableBeanFactory.doCreateBean(AbstractAutowireCapableBeanFactory.java:517)
	at org.springframework.beans.factory.support.AbstractAutowireCapableBeanFactory.createBean(AbstractAutowireCapableBeanFactory.java:456)
	at org.springframework.beans.factory.support.AbstractBeanFactory$1.getObject(AbstractBeanFactory.java:294)
	at org.springframework.beans.factory.support.DefaultSingletonBeanRegistry.getSingleton(DefaultSingletonBeanRegistry.java:225)
	at org.springframework.beans.factory.support.AbstractBeanFactory.doGetBean(AbstractBeanFactory.java:291)
	at org.springframework.beans.factory.support.AbstractBeanFactory.getBean(AbstractBeanFactory.java:197)
	at org.springframework.context.support.AbstractApplicationContext.invokeBeanFactoryPostProcessors(AbstractApplicationContext.java:649)
	at org.springframework.context.support.AbstractApplicationContext.refresh(AbstractApplicationContext.java:451)
	at org.springframework.context.support.ClassPathXmlApplicationContext.<init>(ClassPathXmlApplicationContext.java:139)
	at org.springframework.context.support.ClassPathXmlApplicationContext.<init>(ClassPathXmlApplicationContext.java:83)
	at com.curso.spring.springioc0007.Main.init(Main.java:29)
	at com.curso.spring.springioc0007.Main.main(Main.java:24)
---- System Properties ---
java.runtime.name=Java(TM) SE Runtime Environment
sun.boot.library.path=C:\Program Files\Java\jdk1.8.0_72\jre\bin
java.vm.version=25.72-b15
java.vm.vendor=Oracle Corporation
java.vendor.url=http://java.oracle.com/
path.separator=;
java.vm.name=Java HotSpot(TM) 64-Bit Server VM
file.encoding.pkg=sun.io
user.country=ES
user.script=
sun.java.launcher=SUN_STANDARD
sun.os.patch.level=
java.vm.specification.name=Java Virtual Machine Specification
user.dir=C:\Users\usuario\git\spring\aspectos\Ejemplos Relacionados\SpringIoC0007Maven
java.runtime.version=1.8.0_72-b15
java.awt.graphicsenv=sun.awt.Win32GraphicsEnvironment
java.endorsed.dirs=C:\Program Files\Java\jdk1.8.0_72\jre\lib\endorsed
os.arch=amd64
java.io.tmpdir=C:\Users\usuario\AppData\Local\Temp\
line.separator=

java.vm.specification.vendor=Oracle Corporation
user.variant=
os.name=Windows 10
sun.jnu.encoding=Cp1252
java.library.path=C:\Program Files\Java\jdk1.8.0_72\bin;C:\WINDOWS\Sun\Java\bin;C:\WINDOWS\system32;C:\WINDOWS;C:\ProgramData\Oracle\Java\javapath;C:\Program Files\CollabNet\Subversion Client;E:\bin\Sencha\Cmd\5.1.3.61;C:\Users\usuario\bin\Sencha\Cmd\5.1.3.61;C:\Program Files (x86)\Intel\iCLS Client\;C:\Program Files\Intel\iCLS Client\;C:\WINDOWS\system32;C:\WINDOWS;C:\WINDOWS\System32\Wbem;C:\WINDOWS\System32\WindowsPowerShell\v1.0\;C:\Program Files\Intel\Intel(R) Management Engine Components\DAL;C:\Program Files\Intel\Intel(R) Management Engine Components\IPT;C:\Program Files (x86)\Intel\Intel(R) Management Engine Components\DAL;C:\Program Files (x86)\Intel\Intel(R) Management Engine Components\IPT;C:\Program Files (x86)\Intel\OpenCL SDK\3.0\bin\x86;C:\Program Files (x86)\Intel\OpenCL SDK\3.0\bin\x64;C:\Program Files (x86)\sbt\\bin;C:\Program Files (x86)\Heroku\bin;C:\Program Files (x86)\git\cmd;C:\Program Files (x86)\QuickTime\QTSystem\;C:\HashiCorp\Vagrant\bin;C:\Program Files (x86)\scala\bin;C:\Program Files\nodejs\;C:\Users\usuario\AppData\Local\.meteor\;C:\Users\usuario\AppData\Roaming\npm;.
java.specification.name=Java Platform API Specification
java.class.version=52.0
sun.management.compiler=HotSpot 64-Bit Tiered Compilers
os.version=10.0
user.home=C:\Users\usuario
user.timezone=Europe/Paris
java.awt.printerjob=sun.awt.windows.WPrinterJob
file.encoding=Cp1252
java.specification.version=1.8
java.class.path=C:\Users\usuario\git\spring\aspectos\Ejemplos Relacionados\SpringIoC0007Maven\target\classes;C:\Users\usuario\.m2\repository\org\springframework\spring-context\3.1.2.RELEASE\spring-context-3.1.2.RELEASE.jar;C:\Users\usuario\.m2\repository\org\springframework\spring-aop\3.1.2.RELEASE\spring-aop-3.1.2.RELEASE.jar;C:\Users\usuario\.m2\repository\aopalliance\aopalliance\1.0\aopalliance-1.0.jar;C:\Users\usuario\.m2\repository\org\springframework\spring-beans\3.1.2.RELEASE\spring-beans-3.1.2.RELEASE.jar;C:\Users\usuario\.m2\repository\org\springframework\spring-core\3.1.2.RELEASE\spring-core-3.1.2.RELEASE.jar;C:\Users\usuario\.m2\repository\commons-logging\commons-logging\1.1.1\commons-logging-1.1.1.jar;C:\Users\usuario\.m2\repository\org\springframework\spring-expression\3.1.2.RELEASE\spring-expression-3.1.2.RELEASE.jar;C:\Users\usuario\.m2\repository\org\springframework\spring-asm\3.1.2.RELEASE\spring-asm-3.1.2.RELEASE.jar;C:\Users\usuario\.m2\repository\org\springframework\spring-aspects\3.1.2.RELEASE\spring-aspects-3.1.2.RELEASE.jar;C:\Users\usuario\.m2\repository\org\springframework\spring-context-support\3.1.2.RELEASE\spring-context-support-3.1.2.RELEASE.jar;.\..\aspectjweaver.jar
user.name=usuario
java.vm.specification.version=1.8
sun.java.command=com.curso.spring.springioc0007.Main
java.home=C:\Program Files\Java\jdk1.8.0_72\jre
sun.arch.data.model=64
user.language=es
java.specification.vendor=Oracle Corporation
awt.toolkit=sun.awt.windows.WToolkit
java.vm.info=mixed mode
java.version=1.8.0_72
java.ext.dirs=C:\Program Files\Java\jdk1.8.0_72\jre\lib\ext;C:\WINDOWS\Sun\Java\lib\ext
sun.boot.class.path=C:\Program Files\Java\jdk1.8.0_72\jre\lib\resources.jar;C:\Program Files\Java\jdk1.8.0_72\jre\lib\rt.jar;C:\Program Files\Java\jdk1.8.0_72\jre\lib\sunrsasign.jar;C:\Program Files\Java\jdk1.8.0_72\jre\lib\jsse.jar;C:\Program Files\Java\jdk1.8.0_72\jre\lib\jce.jar;C:\Program Files\Java\jdk1.8.0_72\jre\lib\charsets.jar;C:\Program Files\Java\jdk1.8.0_72\jre\lib\jfr.jar;C:\Program Files\Java\jdk1.8.0_72\jre\classes
java.vendor=Oracle Corporation
file.separator=\
java.vendor.url.bug=http://bugreport.sun.com/bugreport/
sun.io.unicode.encoding=UnicodeLittle
sun.cpu.endian=little
sun.desktop=windows
sun.cpu.isalist=amd64
---- Command Line ---
Empty
---- Full Classpath ---
Empty
---- Compiler Messages ---
Empty
---- org.aspectj.weaver.ltw.LTWWorld@28c97a5 ----
Class loader:
sun.misc.Launcher$AppClassLoader@18b4aac2
Class loader parent:
sun.misc.Launcher$ExtClassLoader@722c41f4
Shadow mungers:
(around(extraFlags: 3): ((((((((((within(@org.springframework.cache.annotation.CacheEvict *) && execution(public * @org.springframework.cache.annotation.CacheEvict *.*(..))) && this(BindingTypePattern(java.lang.Object, 0))) && persingleton(org.springframework.cache.aspectj.AnnotationCacheAspect)) || (((within(@org.springframework.cache.annotation.Caching *) && execution(public * @org.springframework.cache.annotation.Caching *.*(..))) && this(BindingTypePattern(java.lang.Object, 0))) && persingleton(org.springframework.cache.aspectj.AnnotationCacheAspect))) || (((within(@org.springframework.cache.annotation.CachePut *) && execution(public * @org.springframework.cache.annotation.CachePut *.*(..))) && this(BindingTypePattern(java.lang.Object, 0))) && persingleton(org.springframework.cache.aspectj.AnnotationCacheAspect))) || (((within(@org.springframework.cache.annotation.Cacheable *) && execution(public * @org.springframework.cache.annotation.Cacheable *.*(..))) && this(BindingTypePattern(java.lang.Object, 0))) && persingleton(org.springframework.cache.aspectj.AnnotationCacheAspect))) || ((execution(@org.springframework.cache.annotation.Caching * *(..)) && this(BindingTypePattern(java.lang.Object, 0))) && persingleton(org.springframework.cache.aspectj.AnnotationCacheAspect))) || ((execution(@org.springframework.cache.annotation.Cacheable * *(..)) && this(BindingTypePattern(java.lang.Object, 0))) && persingleton(org.springframework.cache.aspectj.AnnotationCacheAspect))) || ((execution(@org.springframework.cache.annotation.CacheEvict * *(..)) && this(BindingTypePattern(java.lang.Object, 0))) && persingleton(org.springframework.cache.aspectj.AnnotationCacheAspect))) || ((execution(@org.springframework.cache.annotation.CachePut * *(..)) && this(BindingTypePattern(java.lang.Object, 0))) && persingleton(org.springframework.cache.aspectj.AnnotationCacheAspect)))->java.lang.Object org.springframework.cache.aspectj.AbstractCacheAspect.ajc$around$org_springframework_cache_aspectj_AbstractCacheAspect$1$2bc714b5(java.lang.Object, org.aspectj.runtime.internal.AroundClosure, org.aspectj.lang.JoinPoint))
(around(extraFlags: 5): ((execution(@org.springframework.scheduling.annotation.Async (void || java.util.concurrent.Future+) *(..)) && persingleton(org.springframework.scheduling.aspectj.AnnotationAsyncExecutionAspect)) || (execution((void || java.util.concurrent.Future+) @org.springframework.scheduling.annotation.Async *.*(..)) && persingleton(org.springframework.scheduling.aspectj.AnnotationAsyncExecutionAspect)))->java.lang.Object org.springframework.scheduling.aspectj.AbstractAsyncExecutionAspect.ajc$around$org_springframework_scheduling_aspectj_AbstractAsyncExecutionAspect$1$6c004c3e(org.aspectj.runtime.internal.AroundClosure, org.aspectj.lang.JoinPoint$StaticPart))
org.aspectj.weaver.Checker@5abff562
org.aspectj.weaver.Checker@12140c1d
(before(extraFlags: 4): ((((within(@org.springframework.transaction.annotation.Transactional *) && execution(public * @org.springframework.transaction.annotation.Transactional *.*(..))) && this(BindingTypePattern(java.lang.Object, 0))) && persingleton(org.springframework.transaction.aspectj.AnnotationTransactionAspect)) || ((execution(@org.springframework.transaction.annotation.Transactional * *(..)) && this(BindingTypePattern(java.lang.Object, 0))) && persingleton(org.springframework.transaction.aspectj.AnnotationTransactionAspect)))->void org.springframework.transaction.aspectj.AbstractTransactionAspect.ajc$before$org_springframework_transaction_aspectj_AbstractTransactionAspect$1$2a73e96c(java.lang.Object, org.aspectj.lang.JoinPoint$StaticPart))
(afterThrowing(extraFlags: 1): ((((within(@org.springframework.transaction.annotation.Transactional *) && execution(public * @org.springframework.transaction.annotation.Transactional *.*(..))) && this(BindingTypePattern(java.lang.Object, 0))) && persingleton(org.springframework.transaction.aspectj.AnnotationTransactionAspect)) || ((execution(@org.springframework.transaction.annotation.Transactional * *(..)) && this(BindingTypePattern(java.lang.Object, 0))) && persingleton(org.springframework.transaction.aspectj.AnnotationTransactionAspect)))->void org.springframework.transaction.aspectj.AbstractTransactionAspect.ajc$afterThrowing$org_springframework_transaction_aspectj_AbstractTransactionAspect$2$2a73e96c(java.lang.Object, java.lang.Throwable))
(afterReturning: ((((within(@org.springframework.transaction.annotation.Transactional *) && execution(public * @org.springframework.transaction.annotation.Transactional *.*(..))) && this(BindingTypePattern(java.lang.Object, 0))) && persingleton(org.springframework.transaction.aspectj.AnnotationTransactionAspect)) || ((execution(@org.springframework.transaction.annotation.Transactional * *(..)) && this(BindingTypePattern(java.lang.Object, 0))) && persingleton(org.springframework.transaction.aspectj.AnnotationTransactionAspect)))->void org.springframework.transaction.aspectj.AbstractTransactionAspect.ajc$afterReturning$org_springframework_transaction_aspectj_AbstractTransactionAspect$3$2a73e96c(java.lang.Object))
(after: ((((within(@org.springframework.transaction.annotation.Transactional *) && execution(public * @org.springframework.transaction.annotation.Transactional *.*(..))) && this(BindingTypePattern(java.lang.Object, 0))) && persingleton(org.springframework.transaction.aspectj.AnnotationTransactionAspect)) || ((execution(@org.springframework.transaction.annotation.Transactional * *(..)) && this(BindingTypePattern(java.lang.Object, 0))) && persingleton(org.springframework.transaction.aspectj.AnnotationTransactionAspect)))->void org.springframework.transaction.aspectj.AbstractTransactionAspect.ajc$after$org_springframework_transaction_aspectj_AbstractTransactionAspect$4$2a73e96c(java.lang.Object))
(before: (((((initialization(org.springframework.beans.factory.aspectj.ConfigurableObject.new(..)) && initialization(org.springframework.beans.factory.aspectj.ConfigurableObject+.new(..))) && this(BindingTypePattern(java.lang.Object, 0))) && @this(org.springframework.beans.factory.annotation.Configurable)) && if(boolean org.springframework.beans.factory.aspectj.AnnotationBeanConfigurerAspect.ajc$if$bb0(org.springframework.beans.factory.annotation.Configurable))) && persingleton(org.springframework.beans.factory.aspectj.AnnotationBeanConfigurerAspect))->void org.springframework.beans.factory.aspectj.AbstractDependencyInjectionAspect.ajc$before$org_springframework_beans_factory_aspectj_AbstractDependencyInjectionAspect$1$e854fa65(java.lang.Object))
(afterReturning: (((((initialization(org.springframework.beans.factory.aspectj.ConfigurableObject+.new(..)) && this(BindingTypePattern(java.lang.Object, 0))) && @this(org.springframework.beans.factory.annotation.Configurable)) && !(@this(org.springframework.beans.factory.annotation.Configurable) && if(boolean org.springframework.beans.factory.aspectj.AnnotationBeanConfigurerAspect.ajc$if$bb0(org.springframework.beans.factory.annotation.Configurable)))) && if(boolean org.springframework.beans.factory.aspectj.AbstractDependencyInjectionAspect.ajc$if$6f1(org.aspectj.lang.JoinPoint))) && persingleton(org.springframework.beans.factory.aspectj.AnnotationBeanConfigurerAspect))->void org.springframework.beans.factory.aspectj.AbstractDependencyInjectionAspect.ajc$afterReturning$org_springframework_beans_factory_aspectj_AbstractDependencyInjectionAspect$2$1ea6722c(java.lang.Object))
(afterReturning: (((execution(java.lang.Object org.springframework.beans.factory.aspectj.AbstractInterfaceDrivenDependencyInjectionAspect$ConfigurableDeserializationSupport+.readResolve()) && this(BindingTypePattern(java.lang.Object, 0))) && @this(org.springframework.beans.factory.annotation.Configurable)) && persingleton(org.springframework.beans.factory.aspectj.AnnotationBeanConfigurerAspect))->void org.springframework.beans.factory.aspectj.AbstractDependencyInjectionAspect.ajc$afterReturning$org_springframework_beans_factory_aspectj_AbstractDependencyInjectionAspect$3$6aa27052(java.lang.Object))
Type mungers:
(BcelTypeMunger ResolvedTypeMunger(Method, java.lang.Object org.springframework.beans.factory.aspectj.AbstractInterfaceDrivenDependencyInjectionAspect$ConfigurableDeserializationSupport.readResolve()))
(BcelTypeMunger ExposeTypeMunger(java.lang.Object))
(BcelTypeMunger ExposeTypeMunger(java.lang.Object))
(BcelTypeMunger ExposeTypeMunger(java.lang.Object))
(BcelTypeMunger ExposeTypeMunger(org.springframework.beans.factory.aspectj.ConfigurableObject))
(BcelTypeMunger ExposeTypeMunger(org.springframework.beans.factory.aspectj.AbstractInterfaceDrivenDependencyInjectionAspect$ConfigurableDeserializationSupport))
Late Type mungers:
Empty
