---- AspectJ Properties ---
AspectJ Compiler 1.6.2 built on Saturday Oct 4, 2008 at 05:47:07 GMT
---- Dump Properties ---
Dump file: ajcore.20160604.114254.676.txt
Dump reason: org.aspectj.bridge.AbortException
Dump on exception: true
Dump at exit condition: abort
---- Exception Information ---
Message: abort trouble in: 
public class org.springframework.beans.TypeMismatchException extends org.springframework.beans.PropertyAccessException:
  public static final String ERROR_CODE = "typeMismatch"
  private transient Object value
  private Class requiredType
  public void <init>(java.beans.PropertyChangeEvent, Class):
                    ALOAD_0     // Lorg/springframework/beans/TypeMismatchException; this   (line 48)
                    ALOAD_1     // Ljava/beans/PropertyChangeEvent; propertyChangeEvent
                    ALOAD_2     // Ljava/lang/Class; requiredType
                    ACONST_NULL
                    INVOKESPECIAL org.springframework.beans.TypeMismatchException.<init> (Ljava/beans/PropertyChangeEvent;Ljava/lang/Class;Ljava/lang/Throwable;)V
    constructor-execution(void org.springframework.beans.TypeMismatchException.<init>(java.beans.PropertyChangeEvent, java.lang.Class))
    |               RETURN   (line 49)
    constructor-execution(void org.springframework.beans.TypeMismatchException.<init>(java.beans.PropertyChangeEvent, java.lang.Class))
  end public void <init>(java.beans.PropertyChangeEvent, Class)

  public void <init>(java.beans.PropertyChangeEvent, Class, Throwable):
                    ALOAD_0     // Lorg/springframework/beans/TypeMismatchException; this   (line 58)
                    ALOAD_1     // Ljava/beans/PropertyChangeEvent; propertyChangeEvent
                    NEW java.lang.StringBuilder   (line 59)
                    DUP
                    LDC "Failed to convert property value of type '"
                    INVOKESPECIAL java.lang.StringBuilder.<init> (Ljava/lang/String;)V
                    ALOAD_1     // Ljava/beans/PropertyChangeEvent; propertyChangeEvent   (line 60)
                    INVOKEVIRTUAL java.beans.PropertyChangeEvent.getNewValue ()Ljava/lang/Object;
                    INVOKESTATIC org.springframework.util.ClassUtils.getDescriptiveType (Ljava/lang/Object;)Ljava/lang/String;
                    INVOKEVIRTUAL java.lang.StringBuilder.append (Ljava/lang/String;)Ljava/lang/StringBuilder;
                    LDC "'"
                    INVOKEVIRTUAL java.lang.StringBuilder.append (Ljava/lang/String;)Ljava/lang/StringBuilder;
                    ALOAD_2     // Ljava/lang/Class; requiredType   (line 61)
                    IFNULL L0
                    NEW java.lang.StringBuilder   (line 62)
                    DUP
                    LDC " to required type '"
                    INVOKESPECIAL java.lang.StringBuilder.<init> (Ljava/lang/String;)V
                    ALOAD_2     // Ljava/lang/Class; requiredType
                    INVOKESTATIC org.springframework.util.ClassUtils.getQualifiedName (Ljava/lang/Class;)Ljava/lang/String;
                    INVOKEVIRTUAL java.lang.StringBuilder.append (Ljava/lang/String;)Ljava/lang/StringBuilder;
                    LDC "'"
                    INVOKEVIRTUAL java.lang.StringBuilder.append (Ljava/lang/String;)Ljava/lang/StringBuilder;
                    INVOKEVIRTUAL java.lang.StringBuilder.toString ()Ljava/lang/String;
                    GOTO L1
                L0: LDC ""
                L1: INVOKEVIRTUAL java.lang.StringBuilder.append (Ljava/lang/String;)Ljava/lang/StringBuilder;   (line 61)
                    ALOAD_1     // Ljava/beans/PropertyChangeEvent; propertyChangeEvent   (line 63)
                    INVOKEVIRTUAL java.beans.PropertyChangeEvent.getPropertyName ()Ljava/lang/String;
                    IFNULL L2
                    NEW java.lang.StringBuilder   (line 64)
                    DUP
                    LDC " for property '"
                    INVOKESPECIAL java.lang.StringBuilder.<init> (Ljava/lang/String;)V
                    ALOAD_1     // Ljava/beans/PropertyChangeEvent; propertyChangeEvent
                    INVOKEVIRTUAL java.beans.PropertyChangeEvent.getPropertyName ()Ljava/lang/String;
                    INVOKEVIRTUAL java.lang.StringBuilder.append (Ljava/lang/String;)Ljava/lang/StringBuilder;
                    LDC "'"
                    INVOKEVIRTUAL java.lang.StringBuilder.append (Ljava/lang/String;)Ljava/lang/StringBuilder;
                    INVOKEVIRTUAL java.lang.StringBuilder.toString ()Ljava/lang/String;
                    GOTO L3
                L2: LDC ""
                L3: INVOKEVIRTUAL java.lang.StringBuilder.append (Ljava/lang/String;)Ljava/lang/StringBuilder;   (line 63)
                    INVOKEVIRTUAL java.lang.StringBuilder.toString ()Ljava/lang/String;   (line 59)
                    ALOAD_3     // Ljava/lang/Throwable; cause   (line 65)
                    INVOKESPECIAL org.springframework.beans.PropertyAccessException.<init> (Ljava/beans/PropertyChangeEvent;Ljava/lang/String;Ljava/lang/Throwable;)V
    constructor-execution(void org.springframework.beans.TypeMismatchException.<init>(java.beans.PropertyChangeEvent, java.lang.Class, java.lang.Throwable))
    |               ALOAD_0     // Lorg/springframework/beans/TypeMismatchException; this   (line 66)
    |               ALOAD_1     // Ljava/beans/PropertyChangeEvent; propertyChangeEvent
    |               INVOKEVIRTUAL java.beans.PropertyChangeEvent.getNewValue ()Ljava/lang/Object;
    |               PUTFIELD org.springframework.beans.TypeMismatchException.value Ljava/lang/Object;
    |               ALOAD_0     // Lorg/springframework/beans/TypeMismatchException; this   (line 67)
    |               ALOAD_2     // Ljava/lang/Class; requiredType
    |               PUTFIELD org.springframework.beans.TypeMismatchException.requiredType Ljava/lang/Class;
    |               RETURN   (line 68)
    constructor-execution(void org.springframework.beans.TypeMismatchException.<init>(java.beans.PropertyChangeEvent, java.lang.Class, java.lang.Throwable))
  end public void <init>(java.beans.PropertyChangeEvent, Class, Throwable)

  public void <init>(Object, Class):
                    ALOAD_0     // Lorg/springframework/beans/TypeMismatchException; this   (line 76)
                    ALOAD_1     // Ljava/lang/Object; value
                    ALOAD_2     // Ljava/lang/Class; requiredType
                    ACONST_NULL
                    INVOKESPECIAL org.springframework.beans.TypeMismatchException.<init> (Ljava/lang/Object;Ljava/lang/Class;Ljava/lang/Throwable;)V
    constructor-execution(void org.springframework.beans.TypeMismatchException.<init>(java.lang.Object, java.lang.Class))
    |               RETURN   (line 77)
    constructor-execution(void org.springframework.beans.TypeMismatchException.<init>(java.lang.Object, java.lang.Class))
  end public void <init>(Object, Class)

  public void <init>(Object, Class, Throwable):
                    ALOAD_0     // Lorg/springframework/beans/TypeMismatchException; this   (line 86)
                    NEW java.lang.StringBuilder
                    DUP
                    LDC "Failed to convert value of type '"
                    INVOKESPECIAL java.lang.StringBuilder.<init> (Ljava/lang/String;)V
                    ALOAD_1     // Ljava/lang/Object; value
                    INVOKESTATIC org.springframework.util.ClassUtils.getDescriptiveType (Ljava/lang/Object;)Ljava/lang/String;
                    INVOKEVIRTUAL java.lang.StringBuilder.append (Ljava/lang/String;)Ljava/lang/StringBuilder;
                    LDC "'"
                    INVOKEVIRTUAL java.lang.StringBuilder.append (Ljava/lang/String;)Ljava/lang/StringBuilder;
                    ALOAD_2     // Ljava/lang/Class; requiredType   (line 87)
                    IFNULL L0
                    NEW java.lang.StringBuilder
                    DUP
                    LDC " to required type '"
                    INVOKESPECIAL java.lang.StringBuilder.<init> (Ljava/lang/String;)V
                    ALOAD_2     // Ljava/lang/Class; requiredType
                    INVOKESTATIC org.springframework.util.ClassUtils.getQualifiedName (Ljava/lang/Class;)Ljava/lang/String;
                    INVOKEVIRTUAL java.lang.StringBuilder.append (Ljava/lang/String;)Ljava/lang/StringBuilder;
                    LDC "'"
                    INVOKEVIRTUAL java.lang.StringBuilder.append (Ljava/lang/String;)Ljava/lang/StringBuilder;
                    INVOKEVIRTUAL java.lang.StringBuilder.toString ()Ljava/lang/String;
                    GOTO L1
                L0: LDC ""
                L1: INVOKEVIRTUAL java.lang.StringBuilder.append (Ljava/lang/String;)Ljava/lang/StringBuilder;
                    INVOKEVIRTUAL java.lang.StringBuilder.toString ()Ljava/lang/String;   (line 86)
                    ALOAD_3     // Ljava/lang/Throwable; cause   (line 88)
                    INVOKESPECIAL org.springframework.beans.PropertyAccessException.<init> (Ljava/lang/String;Ljava/lang/Throwable;)V
    constructor-execution(void org.springframework.beans.TypeMismatchException.<init>(java.lang.Object, java.lang.Class, java.lang.Throwable))
    |               ALOAD_0     // Lorg/springframework/beans/TypeMismatchException; this   (line 89)
    |               ALOAD_1     // Ljava/lang/Object; value
    |               PUTFIELD org.springframework.beans.TypeMismatchException.value Ljava/lang/Object;
    |               ALOAD_0     // Lorg/springframework/beans/TypeMismatchException; this   (line 90)
    |               ALOAD_2     // Ljava/lang/Class; requiredType
    |               PUTFIELD org.springframework.beans.TypeMismatchException.requiredType Ljava/lang/Class;
    |               RETURN   (line 91)
    constructor-execution(void org.springframework.beans.TypeMismatchException.<init>(java.lang.Object, java.lang.Class, java.lang.Throwable))
  end public void <init>(Object, Class, Throwable)

  public Object getValue():
                    ALOAD_0     // Lorg/springframework/beans/TypeMismatchException; this   (line 99)
                    GETFIELD org.springframework.beans.TypeMismatchException.value Ljava/lang/Object;
                    ARETURN
  end public Object getValue()

  public Class getRequiredType():
                    ALOAD_0     // Lorg/springframework/beans/TypeMismatchException; this   (line 106)
                    GETFIELD org.springframework.beans.TypeMismatchException.requiredType Ljava/lang/Class;
                    ARETURN
  end public Class getRequiredType()

  public String getErrorCode():
                    LDC "typeMismatch"   (line 110)
                    ARETURN
  end public String getErrorCode()

end public class org.springframework.beans.TypeMismatchException
 -- (NullPointerException) null
null
java.lang.NullPointerException

org.aspectj.bridge.AbortException: trouble in: 
public class org.springframework.beans.TypeMismatchException extends org.springframework.beans.PropertyAccessException:
  public static final String ERROR_CODE = "typeMismatch"
  private transient Object value
  private Class requiredType
  public void <init>(java.beans.PropertyChangeEvent, Class):
                    ALOAD_0     // Lorg/springframework/beans/TypeMismatchException; this   (line 48)
                    ALOAD_1     // Ljava/beans/PropertyChangeEvent; propertyChangeEvent
                    ALOAD_2     // Ljava/lang/Class; requiredType
                    ACONST_NULL
                    INVOKESPECIAL org.springframework.beans.TypeMismatchException.<init> (Ljava/beans/PropertyChangeEvent;Ljava/lang/Class;Ljava/lang/Throwable;)V
    constructor-execution(void org.springframework.beans.TypeMismatchException.<init>(java.beans.PropertyChangeEvent, java.lang.Class))
    |               RETURN   (line 49)
    constructor-execution(void org.springframework.beans.TypeMismatchException.<init>(java.beans.PropertyChangeEvent, java.lang.Class))
  end public void <init>(java.beans.PropertyChangeEvent, Class)

  public void <init>(java.beans.PropertyChangeEvent, Class, Throwable):
                    ALOAD_0     // Lorg/springframework/beans/TypeMismatchException; this   (line 58)
                    ALOAD_1     // Ljava/beans/PropertyChangeEvent; propertyChangeEvent
                    NEW java.lang.StringBuilder   (line 59)
                    DUP
                    LDC "Failed to convert property value of type '"
                    INVOKESPECIAL java.lang.StringBuilder.<init> (Ljava/lang/String;)V
                    ALOAD_1     // Ljava/beans/PropertyChangeEvent; propertyChangeEvent   (line 60)
                    INVOKEVIRTUAL java.beans.PropertyChangeEvent.getNewValue ()Ljava/lang/Object;
                    INVOKESTATIC org.springframework.util.ClassUtils.getDescriptiveType (Ljava/lang/Object;)Ljava/lang/String;
                    INVOKEVIRTUAL java.lang.StringBuilder.append (Ljava/lang/String;)Ljava/lang/StringBuilder;
                    LDC "'"
                    INVOKEVIRTUAL java.lang.StringBuilder.append (Ljava/lang/String;)Ljava/lang/StringBuilder;
                    ALOAD_2     // Ljava/lang/Class; requiredType   (line 61)
                    IFNULL L0
                    NEW java.lang.StringBuilder   (line 62)
                    DUP
                    LDC " to required type '"
                    INVOKESPECIAL java.lang.StringBuilder.<init> (Ljava/lang/String;)V
                    ALOAD_2     // Ljava/lang/Class; requiredType
                    INVOKESTATIC org.springframework.util.ClassUtils.getQualifiedName (Ljava/lang/Class;)Ljava/lang/String;
                    INVOKEVIRTUAL java.lang.StringBuilder.append (Ljava/lang/String;)Ljava/lang/StringBuilder;
                    LDC "'"
                    INVOKEVIRTUAL java.lang.StringBuilder.append (Ljava/lang/String;)Ljava/lang/StringBuilder;
                    INVOKEVIRTUAL java.lang.StringBuilder.toString ()Ljava/lang/String;
                    GOTO L1
                L0: LDC ""
                L1: INVOKEVIRTUAL java.lang.StringBuilder.append (Ljava/lang/String;)Ljava/lang/StringBuilder;   (line 61)
                    ALOAD_1     // Ljava/beans/PropertyChangeEvent; propertyChangeEvent   (line 63)
                    INVOKEVIRTUAL java.beans.PropertyChangeEvent.getPropertyName ()Ljava/lang/String;
                    IFNULL L2
                    NEW java.lang.StringBuilder   (line 64)
                    DUP
                    LDC " for property '"
                    INVOKESPECIAL java.lang.StringBuilder.<init> (Ljava/lang/String;)V
                    ALOAD_1     // Ljava/beans/PropertyChangeEvent; propertyChangeEvent
                    INVOKEVIRTUAL java.beans.PropertyChangeEvent.getPropertyName ()Ljava/lang/String;
                    INVOKEVIRTUAL java.lang.StringBuilder.append (Ljava/lang/String;)Ljava/lang/StringBuilder;
                    LDC "'"
                    INVOKEVIRTUAL java.lang.StringBuilder.append (Ljava/lang/String;)Ljava/lang/StringBuilder;
                    INVOKEVIRTUAL java.lang.StringBuilder.toString ()Ljava/lang/String;
                    GOTO L3
                L2: LDC ""
                L3: INVOKEVIRTUAL java.lang.StringBuilder.append (Ljava/lang/String;)Ljava/lang/StringBuilder;   (line 63)
                    INVOKEVIRTUAL java.lang.StringBuilder.toString ()Ljava/lang/String;   (line 59)
                    ALOAD_3     // Ljava/lang/Throwable; cause   (line 65)
                    INVOKESPECIAL org.springframework.beans.PropertyAccessException.<init> (Ljava/beans/PropertyChangeEvent;Ljava/lang/String;Ljava/lang/Throwable;)V
    constructor-execution(void org.springframework.beans.TypeMismatchException.<init>(java.beans.PropertyChangeEvent, java.lang.Class, java.lang.Throwable))
    |               ALOAD_0     // Lorg/springframework/beans/TypeMismatchException; this   (line 66)
    |               ALOAD_1     // Ljava/beans/PropertyChangeEvent; propertyChangeEvent
    |               INVOKEVIRTUAL java.beans.PropertyChangeEvent.getNewValue ()Ljava/lang/Object;
    |               PUTFIELD org.springframework.beans.TypeMismatchException.value Ljava/lang/Object;
    |               ALOAD_0     // Lorg/springframework/beans/TypeMismatchException; this   (line 67)
    |               ALOAD_2     // Ljava/lang/Class; requiredType
    |               PUTFIELD org.springframework.beans.TypeMismatchException.requiredType Ljava/lang/Class;
    |               RETURN   (line 68)
    constructor-execution(void org.springframework.beans.TypeMismatchException.<init>(java.beans.PropertyChangeEvent, java.lang.Class, java.lang.Throwable))
  end public void <init>(java.beans.PropertyChangeEvent, Class, Throwable)

  public void <init>(Object, Class):
                    ALOAD_0     // Lorg/springframework/beans/TypeMismatchException; this   (line 76)
                    ALOAD_1     // Ljava/lang/Object; value
                    ALOAD_2     // Ljava/lang/Class; requiredType
                    ACONST_NULL
                    INVOKESPECIAL org.springframework.beans.TypeMismatchException.<init> (Ljava/lang/Object;Ljava/lang/Class;Ljava/lang/Throwable;)V
    constructor-execution(void org.springframework.beans.TypeMismatchException.<init>(java.lang.Object, java.lang.Class))
    |               RETURN   (line 77)
    constructor-execution(void org.springframework.beans.TypeMismatchException.<init>(java.lang.Object, java.lang.Class))
  end public void <init>(Object, Class)

  public void <init>(Object, Class, Throwable):
                    ALOAD_0     // Lorg/springframework/beans/TypeMismatchException; this   (line 86)
                    NEW java.lang.StringBuilder
                    DUP
                    LDC "Failed to convert value of type '"
                    INVOKESPECIAL java.lang.StringBuilder.<init> (Ljava/lang/String;)V
                    ALOAD_1     // Ljava/lang/Object; value
                    INVOKESTATIC org.springframework.util.ClassUtils.getDescriptiveType (Ljava/lang/Object;)Ljava/lang/String;
                    INVOKEVIRTUAL java.lang.StringBuilder.append (Ljava/lang/String;)Ljava/lang/StringBuilder;
                    LDC "'"
                    INVOKEVIRTUAL java.lang.StringBuilder.append (Ljava/lang/String;)Ljava/lang/StringBuilder;
                    ALOAD_2     // Ljava/lang/Class; requiredType   (line 87)
                    IFNULL L0
                    NEW java.lang.StringBuilder
                    DUP
                    LDC " to required type '"
                    INVOKESPECIAL java.lang.StringBuilder.<init> (Ljava/lang/String;)V
                    ALOAD_2     // Ljava/lang/Class; requiredType
                    INVOKESTATIC org.springframework.util.ClassUtils.getQualifiedName (Ljava/lang/Class;)Ljava/lang/String;
                    INVOKEVIRTUAL java.lang.StringBuilder.append (Ljava/lang/String;)Ljava/lang/StringBuilder;
                    LDC "'"
                    INVOKEVIRTUAL java.lang.StringBuilder.append (Ljava/lang/String;)Ljava/lang/StringBuilder;
                    INVOKEVIRTUAL java.lang.StringBuilder.toString ()Ljava/lang/String;
                    GOTO L1
                L0: LDC ""
                L1: INVOKEVIRTUAL java.lang.StringBuilder.append (Ljava/lang/String;)Ljava/lang/StringBuilder;
                    INVOKEVIRTUAL java.lang.StringBuilder.toString ()Ljava/lang/String;   (line 86)
                    ALOAD_3     // Ljava/lang/Throwable; cause   (line 88)
                    INVOKESPECIAL org.springframework.beans.PropertyAccessException.<init> (Ljava/lang/String;Ljava/lang/Throwable;)V
    constructor-execution(void org.springframework.beans.TypeMismatchException.<init>(java.lang.Object, java.lang.Class, java.lang.Throwable))
    |               ALOAD_0     // Lorg/springframework/beans/TypeMismatchException; this   (line 89)
    |               ALOAD_1     // Ljava/lang/Object; value
    |               PUTFIELD org.springframework.beans.TypeMismatchException.value Ljava/lang/Object;
    |               ALOAD_0     // Lorg/springframework/beans/TypeMismatchException; this   (line 90)
    |               ALOAD_2     // Ljava/lang/Class; requiredType
    |               PUTFIELD org.springframework.beans.TypeMismatchException.requiredType Ljava/lang/Class;
    |               RETURN   (line 91)
    constructor-execution(void org.springframework.beans.TypeMismatchException.<init>(java.lang.Object, java.lang.Class, java.lang.Throwable))
  end public void <init>(Object, Class, Throwable)

  public Object getValue():
                    ALOAD_0     // Lorg/springframework/beans/TypeMismatchException; this   (line 99)
                    GETFIELD org.springframework.beans.TypeMismatchException.value Ljava/lang/Object;
                    ARETURN
  end public Object getValue()

  public Class getRequiredType():
                    ALOAD_0     // Lorg/springframework/beans/TypeMismatchException; this   (line 106)
                    GETFIELD org.springframework.beans.TypeMismatchException.requiredType Ljava/lang/Class;
                    ARETURN
  end public Class getRequiredType()

  public String getErrorCode():
                    LDC "typeMismatch"   (line 110)
                    ARETURN
  end public String getErrorCode()

end public class org.springframework.beans.TypeMismatchException

	at org.aspectj.bridge.MessageWriter.handleMessage(MessageWriter.java:47)
	at org.aspectj.weaver.tools.WeavingAdaptor$WeavingAdaptorMessageWriter.handleMessage(WeavingAdaptor.java:665)
	at org.aspectj.weaver.tools.WeavingAdaptor$WeavingAdaptorMessageHolder.handleMessage(WeavingAdaptor.java:615)
	at org.aspectj.weaver.bcel.BcelWeaver.weave(BcelWeaver.java:1752)
	at org.aspectj.weaver.bcel.BcelWeaver.weaveWithoutDump(BcelWeaver.java:1694)
	at org.aspectj.weaver.bcel.BcelWeaver.weaveAndNotify(BcelWeaver.java:1464)
	at org.aspectj.weaver.bcel.BcelWeaver.weave(BcelWeaver.java:1273)
	at org.aspectj.weaver.tools.WeavingAdaptor.getWovenBytes(WeavingAdaptor.java:394)
	at org.aspectj.weaver.tools.WeavingAdaptor.weaveClass(WeavingAdaptor.java:281)
	at org.aspectj.weaver.loadtime.Aj.preProcess(Aj.java:95)
	at org.aspectj.weaver.loadtime.ClassPreProcessorAgentAdapter.transform(ClassPreProcessorAgentAdapter.java:52)
	at sun.instrument.TransformerManager.transform(TransformerManager.java:188)
	at sun.instrument.InstrumentationImpl.transform(InstrumentationImpl.java:428)
	at java.lang.ClassLoader.defineClass1(Native Method)
	at java.lang.ClassLoader.defineClass(ClassLoader.java:760)
	at java.security.SecureClassLoader.defineClass(SecureClassLoader.java:142)
	at java.net.URLClassLoader.defineClass(URLClassLoader.java:467)
	at java.net.URLClassLoader.access$100(URLClassLoader.java:73)
	at java.net.URLClassLoader$1.run(URLClassLoader.java:368)
	at java.net.URLClassLoader$1.run(URLClassLoader.java:362)
	at java.security.AccessController.doPrivileged(Native Method)
	at java.net.URLClassLoader.findClass(URLClassLoader.java:361)
	at java.lang.ClassLoader.loadClass(ClassLoader.java:424)
	at sun.misc.Launcher$AppClassLoader.loadClass(Launcher.java:331)
	at java.lang.ClassLoader.loadClass(ClassLoader.java:357)
	at org.springframework.context.support.AbstractRefreshableApplicationContext.createBeanFactory(AbstractRefreshableApplicationContext.java:195)
	at org.springframework.context.support.AbstractRefreshableApplicationContext.refreshBeanFactory(AbstractRefreshableApplicationContext.java:128)
	at org.springframework.context.support.AbstractApplicationContext.obtainFreshBeanFactory(AbstractApplicationContext.java:527)
	at org.springframework.context.support.AbstractApplicationContext.refresh(AbstractApplicationContext.java:441)
	at org.springframework.context.support.ClassPathXmlApplicationContext.<init>(ClassPathXmlApplicationContext.java:139)
	at org.springframework.context.support.ClassPathXmlApplicationContext.<init>(ClassPathXmlApplicationContext.java:83)
	at com.curso.spring.springioc0007.Main.init(Main.java:29)
	at com.curso.spring.springioc0007.Main.main(Main.java:24)
---- System Properties ---
java.runtime.name=Java(TM) SE Runtime Environment
sun.boot.library.path=C:\Program Files\Java\jdk1.8.0_72\jre\bin
java.vm.version=25.72-b15
java.vm.vendor=Oracle Corporation
java.vendor.url=http://java.oracle.com/
path.separator=;
java.vm.name=Java HotSpot(TM) 64-Bit Server VM
file.encoding.pkg=sun.io
user.country=ES
user.script=
sun.java.launcher=SUN_STANDARD
sun.os.patch.level=
java.vm.specification.name=Java Virtual Machine Specification
user.dir=C:\Users\usuario\git\spring\aspectos\Ejemplos Relacionados\SpringIoC0007Maven
java.runtime.version=1.8.0_72-b15
java.awt.graphicsenv=sun.awt.Win32GraphicsEnvironment
java.endorsed.dirs=C:\Program Files\Java\jdk1.8.0_72\jre\lib\endorsed
os.arch=amd64
java.io.tmpdir=C:\Users\usuario\AppData\Local\Temp\
line.separator=

java.vm.specification.vendor=Oracle Corporation
user.variant=
os.name=Windows 10
sun.jnu.encoding=Cp1252
java.library.path=C:\Program Files\Java\jdk1.8.0_72\bin;C:\WINDOWS\Sun\Java\bin;C:\WINDOWS\system32;C:\WINDOWS;C:\ProgramData\Oracle\Java\javapath;C:\Program Files\CollabNet\Subversion Client;E:\bin\Sencha\Cmd\5.1.3.61;C:\Users\usuario\bin\Sencha\Cmd\5.1.3.61;C:\Program Files (x86)\Intel\iCLS Client\;C:\Program Files\Intel\iCLS Client\;C:\WINDOWS\system32;C:\WINDOWS;C:\WINDOWS\System32\Wbem;C:\WINDOWS\System32\WindowsPowerShell\v1.0\;C:\Program Files\Intel\Intel(R) Management Engine Components\DAL;C:\Program Files\Intel\Intel(R) Management Engine Components\IPT;C:\Program Files (x86)\Intel\Intel(R) Management Engine Components\DAL;C:\Program Files (x86)\Intel\Intel(R) Management Engine Components\IPT;C:\Program Files (x86)\Intel\OpenCL SDK\3.0\bin\x86;C:\Program Files (x86)\Intel\OpenCL SDK\3.0\bin\x64;C:\Program Files (x86)\sbt\\bin;C:\Program Files (x86)\Heroku\bin;C:\Program Files (x86)\git\cmd;C:\Program Files (x86)\QuickTime\QTSystem\;C:\HashiCorp\Vagrant\bin;C:\Program Files (x86)\scala\bin;C:\Program Files\nodejs\;C:\Users\usuario\AppData\Local\.meteor\;C:\Users\usuario\AppData\Roaming\npm;.
java.specification.name=Java Platform API Specification
java.class.version=52.0
sun.management.compiler=HotSpot 64-Bit Tiered Compilers
os.version=10.0
user.home=C:\Users\usuario
user.timezone=Europe/Paris
java.awt.printerjob=sun.awt.windows.WPrinterJob
file.encoding=Cp1252
java.specification.version=1.8
java.class.path=C:\Users\usuario\git\spring\aspectos\Ejemplos Relacionados\SpringIoC0007Maven\target\classes;C:\Users\usuario\.m2\repository\org\springframework\spring-context\3.1.2.RELEASE\spring-context-3.1.2.RELEASE.jar;C:\Users\usuario\.m2\repository\org\springframework\spring-aop\3.1.2.RELEASE\spring-aop-3.1.2.RELEASE.jar;C:\Users\usuario\.m2\repository\aopalliance\aopalliance\1.0\aopalliance-1.0.jar;C:\Users\usuario\.m2\repository\org\springframework\spring-beans\3.1.2.RELEASE\spring-beans-3.1.2.RELEASE.jar;C:\Users\usuario\.m2\repository\org\springframework\spring-core\3.1.2.RELEASE\spring-core-3.1.2.RELEASE.jar;C:\Users\usuario\.m2\repository\commons-logging\commons-logging\1.1.1\commons-logging-1.1.1.jar;C:\Users\usuario\.m2\repository\org\springframework\spring-expression\3.1.2.RELEASE\spring-expression-3.1.2.RELEASE.jar;C:\Users\usuario\.m2\repository\org\springframework\spring-asm\3.1.2.RELEASE\spring-asm-3.1.2.RELEASE.jar;C:\Users\usuario\.m2\repository\org\springframework\spring-aspects\3.1.2.RELEASE\spring-aspects-3.1.2.RELEASE.jar;C:\Users\usuario\.m2\repository\org\springframework\spring-context-support\3.1.2.RELEASE\spring-context-support-3.1.2.RELEASE.jar;.\..\aspectjweaver.jar
user.name=usuario
java.vm.specification.version=1.8
sun.java.command=com.curso.spring.springioc0007.Main
java.home=C:\Program Files\Java\jdk1.8.0_72\jre
sun.arch.data.model=64
user.language=es
java.specification.vendor=Oracle Corporation
awt.toolkit=sun.awt.windows.WToolkit
java.vm.info=mixed mode
java.version=1.8.0_72
java.ext.dirs=C:\Program Files\Java\jdk1.8.0_72\jre\lib\ext;C:\WINDOWS\Sun\Java\lib\ext
sun.boot.class.path=C:\Program Files\Java\jdk1.8.0_72\jre\lib\resources.jar;C:\Program Files\Java\jdk1.8.0_72\jre\lib\rt.jar;C:\Program Files\Java\jdk1.8.0_72\jre\lib\sunrsasign.jar;C:\Program Files\Java\jdk1.8.0_72\jre\lib\jsse.jar;C:\Program Files\Java\jdk1.8.0_72\jre\lib\jce.jar;C:\Program Files\Java\jdk1.8.0_72\jre\lib\charsets.jar;C:\Program Files\Java\jdk1.8.0_72\jre\lib\jfr.jar;C:\Program Files\Java\jdk1.8.0_72\jre\classes
java.vendor=Oracle Corporation
file.separator=\
java.vendor.url.bug=http://bugreport.sun.com/bugreport/
sun.io.unicode.encoding=UnicodeLittle
sun.cpu.endian=little
sun.desktop=windows
sun.cpu.isalist=amd64
---- Command Line ---
Empty
---- Full Classpath ---
Empty
---- Compiler Messages ---
Empty
---- org.aspectj.weaver.ltw.LTWWorld@28c97a5 ----
Class loader:
sun.misc.Launcher$AppClassLoader@18b4aac2
Class loader parent:
sun.misc.Launcher$ExtClassLoader@722c41f4
Shadow mungers:
(around(extraFlags: 3): ((((((((((within(@org.springframework.cache.annotation.CacheEvict *) && execution(public * @org.springframework.cache.annotation.CacheEvict *.*(..))) && this(BindingTypePattern(java.lang.Object, 0))) && persingleton(org.springframework.cache.aspectj.AnnotationCacheAspect)) || (((within(@org.springframework.cache.annotation.Caching *) && execution(public * @org.springframework.cache.annotation.Caching *.*(..))) && this(BindingTypePattern(java.lang.Object, 0))) && persingleton(org.springframework.cache.aspectj.AnnotationCacheAspect))) || (((within(@org.springframework.cache.annotation.CachePut *) && execution(public * @org.springframework.cache.annotation.CachePut *.*(..))) && this(BindingTypePattern(java.lang.Object, 0))) && persingleton(org.springframework.cache.aspectj.AnnotationCacheAspect))) || (((within(@org.springframework.cache.annotation.Cacheable *) && execution(public * @org.springframework.cache.annotation.Cacheable *.*(..))) && this(BindingTypePattern(java.lang.Object, 0))) && persingleton(org.springframework.cache.aspectj.AnnotationCacheAspect))) || ((execution(@org.springframework.cache.annotation.Caching * *(..)) && this(BindingTypePattern(java.lang.Object, 0))) && persingleton(org.springframework.cache.aspectj.AnnotationCacheAspect))) || ((execution(@org.springframework.cache.annotation.Cacheable * *(..)) && this(BindingTypePattern(java.lang.Object, 0))) && persingleton(org.springframework.cache.aspectj.AnnotationCacheAspect))) || ((execution(@org.springframework.cache.annotation.CacheEvict * *(..)) && this(BindingTypePattern(java.lang.Object, 0))) && persingleton(org.springframework.cache.aspectj.AnnotationCacheAspect))) || ((execution(@org.springframework.cache.annotation.CachePut * *(..)) && this(BindingTypePattern(java.lang.Object, 0))) && persingleton(org.springframework.cache.aspectj.AnnotationCacheAspect)))->java.lang.Object org.springframework.cache.aspectj.AbstractCacheAspect.ajc$around$org_springframework_cache_aspectj_AbstractCacheAspect$1$2bc714b5(java.lang.Object, org.aspectj.runtime.internal.AroundClosure, org.aspectj.lang.JoinPoint))
(around(extraFlags: 5): ((execution(@org.springframework.scheduling.annotation.Async (void || java.util.concurrent.Future+) *(..)) && persingleton(org.springframework.scheduling.aspectj.AnnotationAsyncExecutionAspect)) || (execution((void || java.util.concurrent.Future+) @org.springframework.scheduling.annotation.Async *.*(..)) && persingleton(org.springframework.scheduling.aspectj.AnnotationAsyncExecutionAspect)))->java.lang.Object org.springframework.scheduling.aspectj.AbstractAsyncExecutionAspect.ajc$around$org_springframework_scheduling_aspectj_AbstractAsyncExecutionAspect$1$6c004c3e(org.aspectj.runtime.internal.AroundClosure, org.aspectj.lang.JoinPoint$StaticPart))
org.aspectj.weaver.Checker@5abff562
org.aspectj.weaver.Checker@12140c1d
(before(extraFlags: 4): ((((within(@org.springframework.transaction.annotation.Transactional *) && execution(public * @org.springframework.transaction.annotation.Transactional *.*(..))) && this(BindingTypePattern(java.lang.Object, 0))) && persingleton(org.springframework.transaction.aspectj.AnnotationTransactionAspect)) || ((execution(@org.springframework.transaction.annotation.Transactional * *(..)) && this(BindingTypePattern(java.lang.Object, 0))) && persingleton(org.springframework.transaction.aspectj.AnnotationTransactionAspect)))->void org.springframework.transaction.aspectj.AbstractTransactionAspect.ajc$before$org_springframework_transaction_aspectj_AbstractTransactionAspect$1$2a73e96c(java.lang.Object, org.aspectj.lang.JoinPoint$StaticPart))
(afterThrowing(extraFlags: 1): ((((within(@org.springframework.transaction.annotation.Transactional *) && execution(public * @org.springframework.transaction.annotation.Transactional *.*(..))) && this(BindingTypePattern(java.lang.Object, 0))) && persingleton(org.springframework.transaction.aspectj.AnnotationTransactionAspect)) || ((execution(@org.springframework.transaction.annotation.Transactional * *(..)) && this(BindingTypePattern(java.lang.Object, 0))) && persingleton(org.springframework.transaction.aspectj.AnnotationTransactionAspect)))->void org.springframework.transaction.aspectj.AbstractTransactionAspect.ajc$afterThrowing$org_springframework_transaction_aspectj_AbstractTransactionAspect$2$2a73e96c(java.lang.Object, java.lang.Throwable))
(afterReturning: ((((within(@org.springframework.transaction.annotation.Transactional *) && execution(public * @org.springframework.transaction.annotation.Transactional *.*(..))) && this(BindingTypePattern(java.lang.Object, 0))) && persingleton(org.springframework.transaction.aspectj.AnnotationTransactionAspect)) || ((execution(@org.springframework.transaction.annotation.Transactional * *(..)) && this(BindingTypePattern(java.lang.Object, 0))) && persingleton(org.springframework.transaction.aspectj.AnnotationTransactionAspect)))->void org.springframework.transaction.aspectj.AbstractTransactionAspect.ajc$afterReturning$org_springframework_transaction_aspectj_AbstractTransactionAspect$3$2a73e96c(java.lang.Object))
(after: ((((within(@org.springframework.transaction.annotation.Transactional *) && execution(public * @org.springframework.transaction.annotation.Transactional *.*(..))) && this(BindingTypePattern(java.lang.Object, 0))) && persingleton(org.springframework.transaction.aspectj.AnnotationTransactionAspect)) || ((execution(@org.springframework.transaction.annotation.Transactional * *(..)) && this(BindingTypePattern(java.lang.Object, 0))) && persingleton(org.springframework.transaction.aspectj.AnnotationTransactionAspect)))->void org.springframework.transaction.aspectj.AbstractTransactionAspect.ajc$after$org_springframework_transaction_aspectj_AbstractTransactionAspect$4$2a73e96c(java.lang.Object))
(before: (((((initialization(org.springframework.beans.factory.aspectj.ConfigurableObject.new(..)) && initialization(org.springframework.beans.factory.aspectj.ConfigurableObject+.new(..))) && this(BindingTypePattern(java.lang.Object, 0))) && @this(org.springframework.beans.factory.annotation.Configurable)) && if(boolean org.springframework.beans.factory.aspectj.AnnotationBeanConfigurerAspect.ajc$if$bb0(org.springframework.beans.factory.annotation.Configurable))) && persingleton(org.springframework.beans.factory.aspectj.AnnotationBeanConfigurerAspect))->void org.springframework.beans.factory.aspectj.AbstractDependencyInjectionAspect.ajc$before$org_springframework_beans_factory_aspectj_AbstractDependencyInjectionAspect$1$e854fa65(java.lang.Object))
(afterReturning: (((((initialization(org.springframework.beans.factory.aspectj.ConfigurableObject+.new(..)) && this(BindingTypePattern(java.lang.Object, 0))) && @this(org.springframework.beans.factory.annotation.Configurable)) && !(@this(org.springframework.beans.factory.annotation.Configurable) && if(boolean org.springframework.beans.factory.aspectj.AnnotationBeanConfigurerAspect.ajc$if$bb0(org.springframework.beans.factory.annotation.Configurable)))) && if(boolean org.springframework.beans.factory.aspectj.AbstractDependencyInjectionAspect.ajc$if$6f1(org.aspectj.lang.JoinPoint))) && persingleton(org.springframework.beans.factory.aspectj.AnnotationBeanConfigurerAspect))->void org.springframework.beans.factory.aspectj.AbstractDependencyInjectionAspect.ajc$afterReturning$org_springframework_beans_factory_aspectj_AbstractDependencyInjectionAspect$2$1ea6722c(java.lang.Object))
(afterReturning: (((execution(java.lang.Object org.springframework.beans.factory.aspectj.AbstractInterfaceDrivenDependencyInjectionAspect$ConfigurableDeserializationSupport+.readResolve()) && this(BindingTypePattern(java.lang.Object, 0))) && @this(org.springframework.beans.factory.annotation.Configurable)) && persingleton(org.springframework.beans.factory.aspectj.AnnotationBeanConfigurerAspect))->void org.springframework.beans.factory.aspectj.AbstractDependencyInjectionAspect.ajc$afterReturning$org_springframework_beans_factory_aspectj_AbstractDependencyInjectionAspect$3$6aa27052(java.lang.Object))
Type mungers:
(BcelTypeMunger ResolvedTypeMunger(Method, java.lang.Object org.springframework.beans.factory.aspectj.AbstractInterfaceDrivenDependencyInjectionAspect$ConfigurableDeserializationSupport.readResolve()))
(BcelTypeMunger ExposeTypeMunger(java.lang.Object))
(BcelTypeMunger ExposeTypeMunger(java.lang.Object))
(BcelTypeMunger ExposeTypeMunger(java.lang.Object))
(BcelTypeMunger ExposeTypeMunger(org.springframework.beans.factory.aspectj.ConfigurableObject))
(BcelTypeMunger ExposeTypeMunger(org.springframework.beans.factory.aspectj.AbstractInterfaceDrivenDependencyInjectionAspect$ConfigurableDeserializationSupport))
Late Type mungers:
Empty
