---- AspectJ Properties ---
AspectJ Compiler 1.6.2 built on Saturday Oct 4, 2008 at 05:47:07 GMT
---- Dump Properties ---
Dump file: ajcore.20160604.114035.720.txt
Dump reason: org.aspectj.bridge.AbortException
Dump on exception: true
Dump at exit condition: abort
---- Exception Information ---
Message: abort trouble in: 
public abstract class org.springframework.core.env.AbstractPropertyResolver extends java.lang.Object implements org.springframework.core.env.ConfigurablePropertyResolver:
  protected final org.apache.commons.logging.Log logger
  protected org.springframework.core.convert.support.ConfigurableConversionService conversionService
  private org.springframework.util.PropertyPlaceholderHelper nonStrictHelper
  private org.springframework.util.PropertyPlaceholderHelper strictHelper
  private String placeholderPrefix
  private String placeholderSuffix
  private String valueSeparator
  private final java.util.Set requiredProperties [Signature(Ljava/util/Set<Ljava/lang/String;>;)]
  public void <init>():
                    ALOAD_0     // Lorg/springframework/core/env/AbstractPropertyResolver; this   (line 40)
                    INVOKESPECIAL java.lang.Object.<init> ()V
    constructor-execution(void org.springframework.core.env.AbstractPropertyResolver.<init>())
    |               ALOAD_0     // Lorg/springframework/core/env/AbstractPropertyResolver; this   (line 42)
    |               ALOAD_0     // Lorg/springframework/core/env/AbstractPropertyResolver; this
    |               INVOKEVIRTUAL java.lang.Object.getClass ()Ljava/lang/Class;
    |               INVOKESTATIC org.apache.commons.logging.LogFactory.getLog (Ljava/lang/Class;)Lorg/apache/commons/logging/Log;
    |               PUTFIELD org.springframework.core.env.AbstractPropertyResolver.logger Lorg/apache/commons/logging/Log;
    |               ALOAD_0     // Lorg/springframework/core/env/AbstractPropertyResolver; this   (line 44)
    |               NEW org.springframework.core.convert.support.DefaultConversionService
    |               DUP
    |               INVOKESPECIAL org.springframework.core.convert.support.DefaultConversionService.<init> ()V
    |               PUTFIELD org.springframework.core.env.AbstractPropertyResolver.conversionService Lorg/springframework/core/convert/support/ConfigurableConversionService;
    |               ALOAD_0     // Lorg/springframework/core/env/AbstractPropertyResolver; this   (line 49)
    |               LDC "${"
    |               PUTFIELD org.springframework.core.env.AbstractPropertyResolver.placeholderPrefix Ljava/lang/String;
    |               ALOAD_0     // Lorg/springframework/core/env/AbstractPropertyResolver; this   (line 50)
    |               LDC "}"
    |               PUTFIELD org.springframework.core.env.AbstractPropertyResolver.placeholderSuffix Ljava/lang/String;
    |               ALOAD_0     // Lorg/springframework/core/env/AbstractPropertyResolver; this   (line 51)
    |               LDC ":"
    |               PUTFIELD org.springframework.core.env.AbstractPropertyResolver.valueSeparator Ljava/lang/String;
    |               ALOAD_0     // Lorg/springframework/core/env/AbstractPropertyResolver; this   (line 53)
    |               NEW java.util.LinkedHashSet
    |               DUP
    |               INVOKESPECIAL java.util.LinkedHashSet.<init> ()V
    |               PUTFIELD org.springframework.core.env.AbstractPropertyResolver.requiredProperties Ljava/util/Set;
    |               RETURN   (line 40)
    constructor-execution(void org.springframework.core.env.AbstractPropertyResolver.<init>())
  end public void <init>()

  public org.springframework.core.convert.support.ConfigurableConversionService getConversionService():
                    ALOAD_0     // Lorg/springframework/core/env/AbstractPropertyResolver; this   (line 56)
                    GETFIELD org.springframework.core.env.AbstractPropertyResolver.conversionService Lorg/springframework/core/convert/support/ConfigurableConversionService;
                    ARETURN
  end public org.springframework.core.convert.support.ConfigurableConversionService getConversionService()

  public void setConversionService(org.springframework.core.convert.support.ConfigurableConversionService):
                    ALOAD_0     // Lorg/springframework/core/env/AbstractPropertyResolver; this   (line 60)
                    ALOAD_1     // Lorg/springframework/core/convert/support/ConfigurableConversionService; conversionService
                    PUTFIELD org.springframework.core.env.AbstractPropertyResolver.conversionService Lorg/springframework/core/convert/support/ConfigurableConversionService;
                    RETURN   (line 61)
  end public void setConversionService(org.springframework.core.convert.support.ConfigurableConversionService)

  public String getProperty(String, String):
                    ALOAD_0     // Lorg/springframework/core/env/AbstractPropertyResolver; this   (line 64)
                    ALOAD_1     // Ljava/lang/String; key
                    INVOKEVIRTUAL org.springframework.core.env.AbstractPropertyResolver.getProperty (Ljava/lang/String;)Ljava/lang/String;
                    ASTORE_3
                    ALOAD_3     // Ljava/lang/String; value   (line 65)
                    IFNONNULL L0
                    ALOAD_2     // Ljava/lang/String; defaultValue
                    GOTO L1
                L0: ALOAD_3     // Ljava/lang/String; value
                L1: ARETURN
  end public String getProperty(String, String)

  public Object getProperty(String, Class, Object):
                    ALOAD_0     // Lorg/springframework/core/env/AbstractPropertyResolver; this   (line 69)
                    ALOAD_1     // Ljava/lang/String; key
                    ALOAD_2     // Ljava/lang/Class; targetType
                    INVOKEVIRTUAL org.springframework.core.env.AbstractPropertyResolver.getProperty (Ljava/lang/String;Ljava/lang/Class;)Ljava/lang/Object;
                    ASTORE 4
                    ALOAD 4     // Ljava/lang/Object; value   (line 70)
                    IFNONNULL L0
                    ALOAD_3     // Ljava/lang/Object; defaultValue
                    GOTO L1
                L0: ALOAD 4     // Ljava/lang/Object; value
                L1: ARETURN
  end public Object getProperty(String, Class, Object)

  public transient void setRequiredProperties(String[]):
                    ALOAD_1     // [Ljava/lang/String; requiredProperties   (line 74)
                    DUP
                    ASTORE 5
                    ARRAYLENGTH
                    ISTORE 4
                    ICONST_0
                    ISTORE_3
                    GOTO L1
                L0: ALOAD 5
                    ILOAD_3
                    AALOAD
                    ASTORE_2
                    ALOAD_0     // Lorg/springframework/core/env/AbstractPropertyResolver; this   (line 75)
                    GETFIELD org.springframework.core.env.AbstractPropertyResolver.requiredProperties Ljava/util/Set;
                    ALOAD_2     // Ljava/lang/String; key
                    INVOKEINTERFACE java.util.Set.add (Ljava/lang/Object;)Z
                    POP
                    IINC_3 1   (line 74)
                L1: ILOAD_3
                    ILOAD 4
                    IF_ICMPLT L0
                    RETURN   (line 77)
  end public transient void setRequiredProperties(String[])

  public void validateRequiredProperties():
                    NEW org.springframework.core.env.MissingRequiredPropertiesException   (line 80)
                    DUP
                    INVOKESPECIAL org.springframework.core.env.MissingRequiredPropertiesException.<init> ()V
                    ASTORE_1
                    ALOAD_0     // Lorg/springframework/core/env/AbstractPropertyResolver; this   (line 81)
                    GETFIELD org.springframework.core.env.AbstractPropertyResolver.requiredProperties Ljava/util/Set;
                    INVOKEINTERFACE java.util.Set.iterator ()Ljava/util/Iterator;
                    ASTORE_3
                    GOTO L1
                L0: ALOAD_3
                    INVOKEINTERFACE java.util.Iterator.next ()Ljava/lang/Object;
                    CHECKCAST java.lang.String
                    ASTORE_2
                    ALOAD_0     // Lorg/springframework/core/env/AbstractPropertyResolver; this   (line 82)
                    ALOAD_2     // Ljava/lang/String; key
                    INVOKEVIRTUAL org.springframework.core.env.AbstractPropertyResolver.getProperty (Ljava/lang/String;)Ljava/lang/String;
                    IFNONNULL L1
                    ALOAD_1     // Lorg/springframework/core/env/MissingRequiredPropertiesException; ex   (line 83)
                    ALOAD_2     // Ljava/lang/String; key
                    INVOKEVIRTUAL org.springframework.core.env.MissingRequiredPropertiesException.addMissingRequiredProperty (Ljava/lang/String;)V
                L1: ALOAD_3   (line 81)
                    INVOKEINTERFACE java.util.Iterator.hasNext ()Z
                    IFNE L0
                    ALOAD_1     // Lorg/springframework/core/env/MissingRequiredPropertiesException; ex   (line 86)
                    INVOKEVIRTUAL org.springframework.core.env.MissingRequiredPropertiesException.getMissingRequiredProperties ()Ljava/util/Set;
                    INVOKEINTERFACE java.util.Set.isEmpty ()Z
                    IFNE L2
                    ALOAD_1     // Lorg/springframework/core/env/MissingRequiredPropertiesException; ex   (line 87)
                    ATHROW
                L2: RETURN   (line 89)
  end public void validateRequiredProperties()

  public String getRequiredProperty(String) throws java.lang.IllegalStateException:
                    ALOAD_0     // Lorg/springframework/core/env/AbstractPropertyResolver; this   (line 92)
                    ALOAD_1     // Ljava/lang/String; key
                    INVOKEVIRTUAL org.springframework.core.env.AbstractPropertyResolver.getProperty (Ljava/lang/String;)Ljava/lang/String;
                    ASTORE_2
                    ALOAD_2     // Ljava/lang/String; value   (line 93)
                    IFNONNULL L0
                    NEW java.lang.IllegalStateException   (line 94)
                    DUP
                    LDC "required key [%s] not found"
                    ICONST_1
                    ANEWARRAY java.lang.Object
                    DUP
                    ICONST_0
                    ALOAD_1     // Ljava/lang/String; key
                    AASTORE
                    INVOKESTATIC java.lang.String.format (Ljava/lang/String;[Ljava/lang/Object;)Ljava/lang/String;
                    INVOKESPECIAL java.lang.IllegalStateException.<init> (Ljava/lang/String;)V
                    ATHROW
                L0: ALOAD_2     // Ljava/lang/String; value   (line 96)
                    ARETURN
  end public String getRequiredProperty(String) throws java.lang.IllegalStateException

  public Object getRequiredProperty(String, Class) throws java.lang.IllegalStateException:
                    ALOAD_0     // Lorg/springframework/core/env/AbstractPropertyResolver; this   (line 100)
                    ALOAD_1     // Ljava/lang/String; key
                    ALOAD_2     // Ljava/lang/Class; valueType
                    INVOKEVIRTUAL org.springframework.core.env.AbstractPropertyResolver.getProperty (Ljava/lang/String;Ljava/lang/Class;)Ljava/lang/Object;
                    ASTORE_3
                    ALOAD_3     // Ljava/lang/Object; value   (line 101)
                    IFNONNULL L0
                    NEW java.lang.IllegalStateException   (line 102)
                    DUP
                    LDC "required key [%s] not found"
                    ICONST_1
                    ANEWARRAY java.lang.Object
                    DUP
                    ICONST_0
                    ALOAD_1     // Ljava/lang/String; key
                    AASTORE
                    INVOKESTATIC java.lang.String.format (Ljava/lang/String;[Ljava/lang/Object;)Ljava/lang/String;
                    INVOKESPECIAL java.lang.IllegalStateException.<init> (Ljava/lang/String;)V
                    ATHROW
                L0: ALOAD_3     // Ljava/lang/Object; value   (line 104)
                    ARETURN
  end public Object getRequiredProperty(String, Class) throws java.lang.IllegalStateException

  public void setPlaceholderPrefix(String):
                    ALOAD_0     // Lorg/springframework/core/env/AbstractPropertyResolver; this   (line 112)
                    ALOAD_1     // Ljava/lang/String; placeholderPrefix
                    PUTFIELD org.springframework.core.env.AbstractPropertyResolver.placeholderPrefix Ljava/lang/String;
                    RETURN   (line 113)
  end public void setPlaceholderPrefix(String)

  public void setPlaceholderSuffix(String):
                    ALOAD_0     // Lorg/springframework/core/env/AbstractPropertyResolver; this   (line 120)
                    ALOAD_1     // Ljava/lang/String; placeholderSuffix
                    PUTFIELD org.springframework.core.env.AbstractPropertyResolver.placeholderSuffix Ljava/lang/String;
                    RETURN   (line 121)
  end public void setPlaceholderSuffix(String)

  public void setValueSeparator(String):
                    ALOAD_0     // Lorg/springframework/core/env/AbstractPropertyResolver; this   (line 128)
                    ALOAD_1     // Ljava/lang/String; valueSeparator
                    PUTFIELD org.springframework.core.env.AbstractPropertyResolver.valueSeparator Ljava/lang/String;
                    RETURN   (line 129)
  end public void setValueSeparator(String)

  public String resolvePlaceholders(String):
                    ALOAD_0     // Lorg/springframework/core/env/AbstractPropertyResolver; this   (line 132)
                    GETFIELD org.springframework.core.env.AbstractPropertyResolver.nonStrictHelper Lorg/springframework/util/PropertyPlaceholderHelper;
                    IFNONNULL L0
                    ALOAD_0     // Lorg/springframework/core/env/AbstractPropertyResolver; this   (line 133)
                    ALOAD_0     // Lorg/springframework/core/env/AbstractPropertyResolver; this
                    ICONST_1
                    INVOKESPECIAL org.springframework.core.env.AbstractPropertyResolver.createPlaceholderHelper (Z)Lorg/springframework/util/PropertyPlaceholderHelper;
                    PUTFIELD org.springframework.core.env.AbstractPropertyResolver.nonStrictHelper Lorg/springframework/util/PropertyPlaceholderHelper;
                L0: ALOAD_0     // Lorg/springframework/core/env/AbstractPropertyResolver; this   (line 135)
                    ALOAD_1     // Ljava/lang/String; text
                    ALOAD_0     // Lorg/springframework/core/env/AbstractPropertyResolver; this
                    GETFIELD org.springframework.core.env.AbstractPropertyResolver.nonStrictHelper Lorg/springframework/util/PropertyPlaceholderHelper;
                    INVOKESPECIAL org.springframework.core.env.AbstractPropertyResolver.doResolvePlaceholders (Ljava/lang/String;Lorg/springframework/util/PropertyPlaceholderHelper;)Ljava/lang/String;
                    ARETURN
  end public String resolvePlaceholders(String)

  public String resolveRequiredPlaceholders(String) throws java.lang.IllegalArgumentException:
                    ALOAD_0     // Lorg/springframework/core/env/AbstractPropertyResolver; this   (line 139)
                    GETFIELD org.springframework.core.env.AbstractPropertyResolver.strictHelper Lorg/springframework/util/PropertyPlaceholderHelper;
                    IFNONNULL L0
                    ALOAD_0     // Lorg/springframework/core/env/AbstractPropertyResolver; this   (line 140)
                    ALOAD_0     // Lorg/springframework/core/env/AbstractPropertyResolver; this
                    ICONST_0
                    INVOKESPECIAL org.springframework.core.env.AbstractPropertyResolver.createPlaceholderHelper (Z)Lorg/springframework/util/PropertyPlaceholderHelper;
                    PUTFIELD org.springframework.core.env.AbstractPropertyResolver.strictHelper Lorg/springframework/util/PropertyPlaceholderHelper;
                L0: ALOAD_0     // Lorg/springframework/core/env/AbstractPropertyResolver; this   (line 142)
                    ALOAD_1     // Ljava/lang/String; text
                    ALOAD_0     // Lorg/springframework/core/env/AbstractPropertyResolver; this
                    GETFIELD org.springframework.core.env.AbstractPropertyResolver.strictHelper Lorg/springframework/util/PropertyPlaceholderHelper;
                    INVOKESPECIAL org.springframework.core.env.AbstractPropertyResolver.doResolvePlaceholders (Ljava/lang/String;Lorg/springframework/util/PropertyPlaceholderHelper;)Ljava/lang/String;
                    ARETURN
  end public String resolveRequiredPlaceholders(String) throws java.lang.IllegalArgumentException

  private org.springframework.util.PropertyPlaceholderHelper createPlaceholderHelper(boolean):
                    NEW org.springframework.util.PropertyPlaceholderHelper   (line 146)
                    DUP
                    ALOAD_0     // Lorg/springframework/core/env/AbstractPropertyResolver; this
                    GETFIELD org.springframework.core.env.AbstractPropertyResolver.placeholderPrefix Ljava/lang/String;
                    ALOAD_0     // Lorg/springframework/core/env/AbstractPropertyResolver; this
                    GETFIELD org.springframework.core.env.AbstractPropertyResolver.placeholderSuffix Ljava/lang/String;
                    ALOAD_0     // Lorg/springframework/core/env/AbstractPropertyResolver; this   (line 147)
                    GETFIELD org.springframework.core.env.AbstractPropertyResolver.valueSeparator Ljava/lang/String;
                    ILOAD_1     // Z ignoreUnresolvablePlaceholders
                    INVOKESPECIAL org.springframework.util.PropertyPlaceholderHelper.<init> (Ljava/lang/String;Ljava/lang/String;Ljava/lang/String;Z)V   (line 146)
                    ARETURN
  end private org.springframework.util.PropertyPlaceholderHelper createPlaceholderHelper(boolean)

  private String doResolvePlaceholders(String, org.springframework.util.PropertyPlaceholderHelper):
                    ALOAD_2     // Lorg/springframework/util/PropertyPlaceholderHelper; helper   (line 151)
                    ALOAD_1     // Ljava/lang/String; text
                    NEW org.springframework.core.env.AbstractPropertyResolver$1
                    DUP
                    ALOAD_0     // Lorg/springframework/core/env/AbstractPropertyResolver; this
                    INVOKESPECIAL org.springframework.core.env.AbstractPropertyResolver$1.<init> (Lorg/springframework/core/env/AbstractPropertyResolver;)V
                    INVOKEVIRTUAL org.springframework.util.PropertyPlaceholderHelper.replacePlaceholders (Ljava/lang/String;Lorg/springframework/util/PropertyPlaceholderHelper$PlaceholderResolver;)Ljava/lang/String;
                    ARETURN
  end private String doResolvePlaceholders(String, org.springframework.util.PropertyPlaceholderHelper)

end public abstract class org.springframework.core.env.AbstractPropertyResolver
 -- (NullPointerException) null
null
java.lang.NullPointerException

org.aspectj.bridge.AbortException: trouble in: 
public abstract class org.springframework.core.env.AbstractPropertyResolver extends java.lang.Object implements org.springframework.core.env.ConfigurablePropertyResolver:
  protected final org.apache.commons.logging.Log logger
  protected org.springframework.core.convert.support.ConfigurableConversionService conversionService
  private org.springframework.util.PropertyPlaceholderHelper nonStrictHelper
  private org.springframework.util.PropertyPlaceholderHelper strictHelper
  private String placeholderPrefix
  private String placeholderSuffix
  private String valueSeparator
  private final java.util.Set requiredProperties [Signature(Ljava/util/Set<Ljava/lang/String;>;)]
  public void <init>():
                    ALOAD_0     // Lorg/springframework/core/env/AbstractPropertyResolver; this   (line 40)
                    INVOKESPECIAL java.lang.Object.<init> ()V
    constructor-execution(void org.springframework.core.env.AbstractPropertyResolver.<init>())
    |               ALOAD_0     // Lorg/springframework/core/env/AbstractPropertyResolver; this   (line 42)
    |               ALOAD_0     // Lorg/springframework/core/env/AbstractPropertyResolver; this
    |               INVOKEVIRTUAL java.lang.Object.getClass ()Ljava/lang/Class;
    |               INVOKESTATIC org.apache.commons.logging.LogFactory.getLog (Ljava/lang/Class;)Lorg/apache/commons/logging/Log;
    |               PUTFIELD org.springframework.core.env.AbstractPropertyResolver.logger Lorg/apache/commons/logging/Log;
    |               ALOAD_0     // Lorg/springframework/core/env/AbstractPropertyResolver; this   (line 44)
    |               NEW org.springframework.core.convert.support.DefaultConversionService
    |               DUP
    |               INVOKESPECIAL org.springframework.core.convert.support.DefaultConversionService.<init> ()V
    |               PUTFIELD org.springframework.core.env.AbstractPropertyResolver.conversionService Lorg/springframework/core/convert/support/ConfigurableConversionService;
    |               ALOAD_0     // Lorg/springframework/core/env/AbstractPropertyResolver; this   (line 49)
    |               LDC "${"
    |               PUTFIELD org.springframework.core.env.AbstractPropertyResolver.placeholderPrefix Ljava/lang/String;
    |               ALOAD_0     // Lorg/springframework/core/env/AbstractPropertyResolver; this   (line 50)
    |               LDC "}"
    |               PUTFIELD org.springframework.core.env.AbstractPropertyResolver.placeholderSuffix Ljava/lang/String;
    |               ALOAD_0     // Lorg/springframework/core/env/AbstractPropertyResolver; this   (line 51)
    |               LDC ":"
    |               PUTFIELD org.springframework.core.env.AbstractPropertyResolver.valueSeparator Ljava/lang/String;
    |               ALOAD_0     // Lorg/springframework/core/env/AbstractPropertyResolver; this   (line 53)
    |               NEW java.util.LinkedHashSet
    |               DUP
    |               INVOKESPECIAL java.util.LinkedHashSet.<init> ()V
    |               PUTFIELD org.springframework.core.env.AbstractPropertyResolver.requiredProperties Ljava/util/Set;
    |               RETURN   (line 40)
    constructor-execution(void org.springframework.core.env.AbstractPropertyResolver.<init>())
  end public void <init>()

  public org.springframework.core.convert.support.ConfigurableConversionService getConversionService():
                    ALOAD_0     // Lorg/springframework/core/env/AbstractPropertyResolver; this   (line 56)
                    GETFIELD org.springframework.core.env.AbstractPropertyResolver.conversionService Lorg/springframework/core/convert/support/ConfigurableConversionService;
                    ARETURN
  end public org.springframework.core.convert.support.ConfigurableConversionService getConversionService()

  public void setConversionService(org.springframework.core.convert.support.ConfigurableConversionService):
                    ALOAD_0     // Lorg/springframework/core/env/AbstractPropertyResolver; this   (line 60)
                    ALOAD_1     // Lorg/springframework/core/convert/support/ConfigurableConversionService; conversionService
                    PUTFIELD org.springframework.core.env.AbstractPropertyResolver.conversionService Lorg/springframework/core/convert/support/ConfigurableConversionService;
                    RETURN   (line 61)
  end public void setConversionService(org.springframework.core.convert.support.ConfigurableConversionService)

  public String getProperty(String, String):
                    ALOAD_0     // Lorg/springframework/core/env/AbstractPropertyResolver; this   (line 64)
                    ALOAD_1     // Ljava/lang/String; key
                    INVOKEVIRTUAL org.springframework.core.env.AbstractPropertyResolver.getProperty (Ljava/lang/String;)Ljava/lang/String;
                    ASTORE_3
                    ALOAD_3     // Ljava/lang/String; value   (line 65)
                    IFNONNULL L0
                    ALOAD_2     // Ljava/lang/String; defaultValue
                    GOTO L1
                L0: ALOAD_3     // Ljava/lang/String; value
                L1: ARETURN
  end public String getProperty(String, String)

  public Object getProperty(String, Class, Object):
                    ALOAD_0     // Lorg/springframework/core/env/AbstractPropertyResolver; this   (line 69)
                    ALOAD_1     // Ljava/lang/String; key
                    ALOAD_2     // Ljava/lang/Class; targetType
                    INVOKEVIRTUAL org.springframework.core.env.AbstractPropertyResolver.getProperty (Ljava/lang/String;Ljava/lang/Class;)Ljava/lang/Object;
                    ASTORE 4
                    ALOAD 4     // Ljava/lang/Object; value   (line 70)
                    IFNONNULL L0
                    ALOAD_3     // Ljava/lang/Object; defaultValue
                    GOTO L1
                L0: ALOAD 4     // Ljava/lang/Object; value
                L1: ARETURN
  end public Object getProperty(String, Class, Object)

  public transient void setRequiredProperties(String[]):
                    ALOAD_1     // [Ljava/lang/String; requiredProperties   (line 74)
                    DUP
                    ASTORE 5
                    ARRAYLENGTH
                    ISTORE 4
                    ICONST_0
                    ISTORE_3
                    GOTO L1
                L0: ALOAD 5
                    ILOAD_3
                    AALOAD
                    ASTORE_2
                    ALOAD_0     // Lorg/springframework/core/env/AbstractPropertyResolver; this   (line 75)
                    GETFIELD org.springframework.core.env.AbstractPropertyResolver.requiredProperties Ljava/util/Set;
                    ALOAD_2     // Ljava/lang/String; key
                    INVOKEINTERFACE java.util.Set.add (Ljava/lang/Object;)Z
                    POP
                    IINC_3 1   (line 74)
                L1: ILOAD_3
                    ILOAD 4
                    IF_ICMPLT L0
                    RETURN   (line 77)
  end public transient void setRequiredProperties(String[])

  public void validateRequiredProperties():
                    NEW org.springframework.core.env.MissingRequiredPropertiesException   (line 80)
                    DUP
                    INVOKESPECIAL org.springframework.core.env.MissingRequiredPropertiesException.<init> ()V
                    ASTORE_1
                    ALOAD_0     // Lorg/springframework/core/env/AbstractPropertyResolver; this   (line 81)
                    GETFIELD org.springframework.core.env.AbstractPropertyResolver.requiredProperties Ljava/util/Set;
                    INVOKEINTERFACE java.util.Set.iterator ()Ljava/util/Iterator;
                    ASTORE_3
                    GOTO L1
                L0: ALOAD_3
                    INVOKEINTERFACE java.util.Iterator.next ()Ljava/lang/Object;
                    CHECKCAST java.lang.String
                    ASTORE_2
                    ALOAD_0     // Lorg/springframework/core/env/AbstractPropertyResolver; this   (line 82)
                    ALOAD_2     // Ljava/lang/String; key
                    INVOKEVIRTUAL org.springframework.core.env.AbstractPropertyResolver.getProperty (Ljava/lang/String;)Ljava/lang/String;
                    IFNONNULL L1
                    ALOAD_1     // Lorg/springframework/core/env/MissingRequiredPropertiesException; ex   (line 83)
                    ALOAD_2     // Ljava/lang/String; key
                    INVOKEVIRTUAL org.springframework.core.env.MissingRequiredPropertiesException.addMissingRequiredProperty (Ljava/lang/String;)V
                L1: ALOAD_3   (line 81)
                    INVOKEINTERFACE java.util.Iterator.hasNext ()Z
                    IFNE L0
                    ALOAD_1     // Lorg/springframework/core/env/MissingRequiredPropertiesException; ex   (line 86)
                    INVOKEVIRTUAL org.springframework.core.env.MissingRequiredPropertiesException.getMissingRequiredProperties ()Ljava/util/Set;
                    INVOKEINTERFACE java.util.Set.isEmpty ()Z
                    IFNE L2
                    ALOAD_1     // Lorg/springframework/core/env/MissingRequiredPropertiesException; ex   (line 87)
                    ATHROW
                L2: RETURN   (line 89)
  end public void validateRequiredProperties()

  public String getRequiredProperty(String) throws java.lang.IllegalStateException:
                    ALOAD_0     // Lorg/springframework/core/env/AbstractPropertyResolver; this   (line 92)
                    ALOAD_1     // Ljava/lang/String; key
                    INVOKEVIRTUAL org.springframework.core.env.AbstractPropertyResolver.getProperty (Ljava/lang/String;)Ljava/lang/String;
                    ASTORE_2
                    ALOAD_2     // Ljava/lang/String; value   (line 93)
                    IFNONNULL L0
                    NEW java.lang.IllegalStateException   (line 94)
                    DUP
                    LDC "required key [%s] not found"
                    ICONST_1
                    ANEWARRAY java.lang.Object
                    DUP
                    ICONST_0
                    ALOAD_1     // Ljava/lang/String; key
                    AASTORE
                    INVOKESTATIC java.lang.String.format (Ljava/lang/String;[Ljava/lang/Object;)Ljava/lang/String;
                    INVOKESPECIAL java.lang.IllegalStateException.<init> (Ljava/lang/String;)V
                    ATHROW
                L0: ALOAD_2     // Ljava/lang/String; value   (line 96)
                    ARETURN
  end public String getRequiredProperty(String) throws java.lang.IllegalStateException

  public Object getRequiredProperty(String, Class) throws java.lang.IllegalStateException:
                    ALOAD_0     // Lorg/springframework/core/env/AbstractPropertyResolver; this   (line 100)
                    ALOAD_1     // Ljava/lang/String; key
                    ALOAD_2     // Ljava/lang/Class; valueType
                    INVOKEVIRTUAL org.springframework.core.env.AbstractPropertyResolver.getProperty (Ljava/lang/String;Ljava/lang/Class;)Ljava/lang/Object;
                    ASTORE_3
                    ALOAD_3     // Ljava/lang/Object; value   (line 101)
                    IFNONNULL L0
                    NEW java.lang.IllegalStateException   (line 102)
                    DUP
                    LDC "required key [%s] not found"
                    ICONST_1
                    ANEWARRAY java.lang.Object
                    DUP
                    ICONST_0
                    ALOAD_1     // Ljava/lang/String; key
                    AASTORE
                    INVOKESTATIC java.lang.String.format (Ljava/lang/String;[Ljava/lang/Object;)Ljava/lang/String;
                    INVOKESPECIAL java.lang.IllegalStateException.<init> (Ljava/lang/String;)V
                    ATHROW
                L0: ALOAD_3     // Ljava/lang/Object; value   (line 104)
                    ARETURN
  end public Object getRequiredProperty(String, Class) throws java.lang.IllegalStateException

  public void setPlaceholderPrefix(String):
                    ALOAD_0     // Lorg/springframework/core/env/AbstractPropertyResolver; this   (line 112)
                    ALOAD_1     // Ljava/lang/String; placeholderPrefix
                    PUTFIELD org.springframework.core.env.AbstractPropertyResolver.placeholderPrefix Ljava/lang/String;
                    RETURN   (line 113)
  end public void setPlaceholderPrefix(String)

  public void setPlaceholderSuffix(String):
                    ALOAD_0     // Lorg/springframework/core/env/AbstractPropertyResolver; this   (line 120)
                    ALOAD_1     // Ljava/lang/String; placeholderSuffix
                    PUTFIELD org.springframework.core.env.AbstractPropertyResolver.placeholderSuffix Ljava/lang/String;
                    RETURN   (line 121)
  end public void setPlaceholderSuffix(String)

  public void setValueSeparator(String):
                    ALOAD_0     // Lorg/springframework/core/env/AbstractPropertyResolver; this   (line 128)
                    ALOAD_1     // Ljava/lang/String; valueSeparator
                    PUTFIELD org.springframework.core.env.AbstractPropertyResolver.valueSeparator Ljava/lang/String;
                    RETURN   (line 129)
  end public void setValueSeparator(String)

  public String resolvePlaceholders(String):
                    ALOAD_0     // Lorg/springframework/core/env/AbstractPropertyResolver; this   (line 132)
                    GETFIELD org.springframework.core.env.AbstractPropertyResolver.nonStrictHelper Lorg/springframework/util/PropertyPlaceholderHelper;
                    IFNONNULL L0
                    ALOAD_0     // Lorg/springframework/core/env/AbstractPropertyResolver; this   (line 133)
                    ALOAD_0     // Lorg/springframework/core/env/AbstractPropertyResolver; this
                    ICONST_1
                    INVOKESPECIAL org.springframework.core.env.AbstractPropertyResolver.createPlaceholderHelper (Z)Lorg/springframework/util/PropertyPlaceholderHelper;
                    PUTFIELD org.springframework.core.env.AbstractPropertyResolver.nonStrictHelper Lorg/springframework/util/PropertyPlaceholderHelper;
                L0: ALOAD_0     // Lorg/springframework/core/env/AbstractPropertyResolver; this   (line 135)
                    ALOAD_1     // Ljava/lang/String; text
                    ALOAD_0     // Lorg/springframework/core/env/AbstractPropertyResolver; this
                    GETFIELD org.springframework.core.env.AbstractPropertyResolver.nonStrictHelper Lorg/springframework/util/PropertyPlaceholderHelper;
                    INVOKESPECIAL org.springframework.core.env.AbstractPropertyResolver.doResolvePlaceholders (Ljava/lang/String;Lorg/springframework/util/PropertyPlaceholderHelper;)Ljava/lang/String;
                    ARETURN
  end public String resolvePlaceholders(String)

  public String resolveRequiredPlaceholders(String) throws java.lang.IllegalArgumentException:
                    ALOAD_0     // Lorg/springframework/core/env/AbstractPropertyResolver; this   (line 139)
                    GETFIELD org.springframework.core.env.AbstractPropertyResolver.strictHelper Lorg/springframework/util/PropertyPlaceholderHelper;
                    IFNONNULL L0
                    ALOAD_0     // Lorg/springframework/core/env/AbstractPropertyResolver; this   (line 140)
                    ALOAD_0     // Lorg/springframework/core/env/AbstractPropertyResolver; this
                    ICONST_0
                    INVOKESPECIAL org.springframework.core.env.AbstractPropertyResolver.createPlaceholderHelper (Z)Lorg/springframework/util/PropertyPlaceholderHelper;
                    PUTFIELD org.springframework.core.env.AbstractPropertyResolver.strictHelper Lorg/springframework/util/PropertyPlaceholderHelper;
                L0: ALOAD_0     // Lorg/springframework/core/env/AbstractPropertyResolver; this   (line 142)
                    ALOAD_1     // Ljava/lang/String; text
                    ALOAD_0     // Lorg/springframework/core/env/AbstractPropertyResolver; this
                    GETFIELD org.springframework.core.env.AbstractPropertyResolver.strictHelper Lorg/springframework/util/PropertyPlaceholderHelper;
                    INVOKESPECIAL org.springframework.core.env.AbstractPropertyResolver.doResolvePlaceholders (Ljava/lang/String;Lorg/springframework/util/PropertyPlaceholderHelper;)Ljava/lang/String;
                    ARETURN
  end public String resolveRequiredPlaceholders(String) throws java.lang.IllegalArgumentException

  private org.springframework.util.PropertyPlaceholderHelper createPlaceholderHelper(boolean):
                    NEW org.springframework.util.PropertyPlaceholderHelper   (line 146)
                    DUP
                    ALOAD_0     // Lorg/springframework/core/env/AbstractPropertyResolver; this
                    GETFIELD org.springframework.core.env.AbstractPropertyResolver.placeholderPrefix Ljava/lang/String;
                    ALOAD_0     // Lorg/springframework/core/env/AbstractPropertyResolver; this
                    GETFIELD org.springframework.core.env.AbstractPropertyResolver.placeholderSuffix Ljava/lang/String;
                    ALOAD_0     // Lorg/springframework/core/env/AbstractPropertyResolver; this   (line 147)
                    GETFIELD org.springframework.core.env.AbstractPropertyResolver.valueSeparator Ljava/lang/String;
                    ILOAD_1     // Z ignoreUnresolvablePlaceholders
                    INVOKESPECIAL org.springframework.util.PropertyPlaceholderHelper.<init> (Ljava/lang/String;Ljava/lang/String;Ljava/lang/String;Z)V   (line 146)
                    ARETURN
  end private org.springframework.util.PropertyPlaceholderHelper createPlaceholderHelper(boolean)

  private String doResolvePlaceholders(String, org.springframework.util.PropertyPlaceholderHelper):
                    ALOAD_2     // Lorg/springframework/util/PropertyPlaceholderHelper; helper   (line 151)
                    ALOAD_1     // Ljava/lang/String; text
                    NEW org.springframework.core.env.AbstractPropertyResolver$1
                    DUP
                    ALOAD_0     // Lorg/springframework/core/env/AbstractPropertyResolver; this
                    INVOKESPECIAL org.springframework.core.env.AbstractPropertyResolver$1.<init> (Lorg/springframework/core/env/AbstractPropertyResolver;)V
                    INVOKEVIRTUAL org.springframework.util.PropertyPlaceholderHelper.replacePlaceholders (Ljava/lang/String;Lorg/springframework/util/PropertyPlaceholderHelper$PlaceholderResolver;)Ljava/lang/String;
                    ARETURN
  end private String doResolvePlaceholders(String, org.springframework.util.PropertyPlaceholderHelper)

end public abstract class org.springframework.core.env.AbstractPropertyResolver

	at org.aspectj.bridge.MessageWriter.handleMessage(MessageWriter.java:47)
	at org.aspectj.weaver.tools.WeavingAdaptor$WeavingAdaptorMessageWriter.handleMessage(WeavingAdaptor.java:665)
	at org.aspectj.weaver.tools.WeavingAdaptor$WeavingAdaptorMessageHolder.handleMessage(WeavingAdaptor.java:615)
	at org.aspectj.weaver.bcel.BcelWeaver.weave(BcelWeaver.java:1752)
	at org.aspectj.weaver.bcel.BcelWeaver.weaveWithoutDump(BcelWeaver.java:1694)
	at org.aspectj.weaver.bcel.BcelWeaver.weaveAndNotify(BcelWeaver.java:1464)
	at org.aspectj.weaver.bcel.BcelWeaver.weave(BcelWeaver.java:1273)
	at org.aspectj.weaver.tools.WeavingAdaptor.getWovenBytes(WeavingAdaptor.java:394)
	at org.aspectj.weaver.tools.WeavingAdaptor.weaveClass(WeavingAdaptor.java:281)
	at org.aspectj.weaver.loadtime.Aj.preProcess(Aj.java:95)
	at org.aspectj.weaver.loadtime.ClassPreProcessorAgentAdapter.transform(ClassPreProcessorAgentAdapter.java:52)
	at sun.instrument.TransformerManager.transform(TransformerManager.java:188)
	at sun.instrument.InstrumentationImpl.transform(InstrumentationImpl.java:428)
	at java.lang.ClassLoader.defineClass1(Native Method)
	at java.lang.ClassLoader.defineClass(ClassLoader.java:760)
	at java.security.SecureClassLoader.defineClass(SecureClassLoader.java:142)
	at java.net.URLClassLoader.defineClass(URLClassLoader.java:467)
	at java.net.URLClassLoader.access$100(URLClassLoader.java:73)
	at java.net.URLClassLoader$1.run(URLClassLoader.java:368)
	at java.net.URLClassLoader$1.run(URLClassLoader.java:362)
	at java.security.AccessController.doPrivileged(Native Method)
	at java.net.URLClassLoader.findClass(URLClassLoader.java:361)
	at java.lang.ClassLoader.loadClass(ClassLoader.java:424)
	at sun.misc.Launcher$AppClassLoader.loadClass(Launcher.java:331)
	at java.lang.ClassLoader.loadClass(ClassLoader.java:357)
	at java.lang.ClassLoader.defineClass1(Native Method)
	at java.lang.ClassLoader.defineClass(ClassLoader.java:760)
	at java.security.SecureClassLoader.defineClass(SecureClassLoader.java:142)
	at java.net.URLClassLoader.defineClass(URLClassLoader.java:467)
	at java.net.URLClassLoader.access$100(URLClassLoader.java:73)
	at java.net.URLClassLoader$1.run(URLClassLoader.java:368)
	at java.net.URLClassLoader$1.run(URLClassLoader.java:362)
	at java.security.AccessController.doPrivileged(Native Method)
	at java.net.URLClassLoader.findClass(URLClassLoader.java:361)
	at java.lang.ClassLoader.loadClass(ClassLoader.java:424)
	at sun.misc.Launcher$AppClassLoader.loadClass(Launcher.java:331)
	at java.lang.ClassLoader.loadClass(ClassLoader.java:357)
	at org.springframework.core.env.AbstractEnvironment.<init>(AbstractEnvironment.java:101)
	at org.springframework.core.env.StandardEnvironment.<init>(StandardEnvironment.java:54)
	at org.springframework.context.support.AbstractApplicationContext.createEnvironment(AbstractApplicationContext.java:432)
	at org.springframework.context.support.AbstractApplicationContext.<init>(AbstractApplicationContext.java:227)
	at org.springframework.context.support.AbstractRefreshableApplicationContext.<init>(AbstractRefreshableApplicationContext.java:90)
	at org.springframework.context.support.AbstractRefreshableConfigApplicationContext.<init>(AbstractRefreshableConfigApplicationContext.java:59)
	at org.springframework.context.support.AbstractXmlApplicationContext.<init>(AbstractXmlApplicationContext.java:61)
	at org.springframework.context.support.ClassPathXmlApplicationContext.<init>(ClassPathXmlApplicationContext.java:136)
	at org.springframework.context.support.ClassPathXmlApplicationContext.<init>(ClassPathXmlApplicationContext.java:83)
	at com.curso.spring.springioc0007.Main.init(Main.java:29)
	at com.curso.spring.springioc0007.Main.main(Main.java:24)
---- System Properties ---
java.runtime.name=Java(TM) SE Runtime Environment
sun.boot.library.path=C:\Program Files\Java\jdk1.8.0_72\jre\bin
java.vm.version=25.72-b15
java.vm.vendor=Oracle Corporation
java.vendor.url=http://java.oracle.com/
path.separator=;
java.vm.name=Java HotSpot(TM) 64-Bit Server VM
file.encoding.pkg=sun.io
user.country=ES
user.script=
sun.java.launcher=SUN_STANDARD
sun.os.patch.level=
java.vm.specification.name=Java Virtual Machine Specification
user.dir=C:\Users\usuario\git\spring\aspectos\Ejemplos Relacionados\SpringIoC0007Maven
java.runtime.version=1.8.0_72-b15
java.awt.graphicsenv=sun.awt.Win32GraphicsEnvironment
java.endorsed.dirs=C:\Program Files\Java\jdk1.8.0_72\jre\lib\endorsed
os.arch=amd64
java.io.tmpdir=C:\Users\usuario\AppData\Local\Temp\
line.separator=

java.vm.specification.vendor=Oracle Corporation
user.variant=
os.name=Windows 10
sun.jnu.encoding=Cp1252
java.library.path=C:\Program Files\Java\jdk1.8.0_72\bin;C:\WINDOWS\Sun\Java\bin;C:\WINDOWS\system32;C:\WINDOWS;C:\ProgramData\Oracle\Java\javapath;C:\Program Files\CollabNet\Subversion Client;E:\bin\Sencha\Cmd\5.1.3.61;C:\Users\usuario\bin\Sencha\Cmd\5.1.3.61;C:\Program Files (x86)\Intel\iCLS Client\;C:\Program Files\Intel\iCLS Client\;C:\WINDOWS\system32;C:\WINDOWS;C:\WINDOWS\System32\Wbem;C:\WINDOWS\System32\WindowsPowerShell\v1.0\;C:\Program Files\Intel\Intel(R) Management Engine Components\DAL;C:\Program Files\Intel\Intel(R) Management Engine Components\IPT;C:\Program Files (x86)\Intel\Intel(R) Management Engine Components\DAL;C:\Program Files (x86)\Intel\Intel(R) Management Engine Components\IPT;C:\Program Files (x86)\Intel\OpenCL SDK\3.0\bin\x86;C:\Program Files (x86)\Intel\OpenCL SDK\3.0\bin\x64;C:\Program Files (x86)\sbt\\bin;C:\Program Files (x86)\Heroku\bin;C:\Program Files (x86)\git\cmd;C:\Program Files (x86)\QuickTime\QTSystem\;C:\HashiCorp\Vagrant\bin;C:\Program Files (x86)\scala\bin;C:\Program Files\nodejs\;C:\Users\usuario\AppData\Local\.meteor\;C:\Users\usuario\AppData\Roaming\npm;.
java.specification.name=Java Platform API Specification
java.class.version=52.0
sun.management.compiler=HotSpot 64-Bit Tiered Compilers
os.version=10.0
user.home=C:\Users\usuario
user.timezone=Europe/Paris
java.awt.printerjob=sun.awt.windows.WPrinterJob
file.encoding=Cp1252
java.specification.version=1.8
java.class.path=C:\Users\usuario\git\spring\aspectos\Ejemplos Relacionados\SpringIoC0007Maven\target\classes;C:\Users\usuario\.m2\repository\org\springframework\spring-context\3.1.2.RELEASE\spring-context-3.1.2.RELEASE.jar;C:\Users\usuario\.m2\repository\org\springframework\spring-aop\3.1.2.RELEASE\spring-aop-3.1.2.RELEASE.jar;C:\Users\usuario\.m2\repository\aopalliance\aopalliance\1.0\aopalliance-1.0.jar;C:\Users\usuario\.m2\repository\org\springframework\spring-beans\3.1.2.RELEASE\spring-beans-3.1.2.RELEASE.jar;C:\Users\usuario\.m2\repository\org\springframework\spring-core\3.1.2.RELEASE\spring-core-3.1.2.RELEASE.jar;C:\Users\usuario\.m2\repository\commons-logging\commons-logging\1.1.1\commons-logging-1.1.1.jar;C:\Users\usuario\.m2\repository\org\springframework\spring-expression\3.1.2.RELEASE\spring-expression-3.1.2.RELEASE.jar;C:\Users\usuario\.m2\repository\org\springframework\spring-asm\3.1.2.RELEASE\spring-asm-3.1.2.RELEASE.jar;C:\Users\usuario\.m2\repository\org\springframework\spring-aspects\3.1.2.RELEASE\spring-aspects-3.1.2.RELEASE.jar;C:\Users\usuario\.m2\repository\org\springframework\spring-context-support\3.1.2.RELEASE\spring-context-support-3.1.2.RELEASE.jar;.\..\aspectjweaver.jar
user.name=usuario
java.vm.specification.version=1.8
sun.java.command=com.curso.spring.springioc0007.Main
java.home=C:\Program Files\Java\jdk1.8.0_72\jre
sun.arch.data.model=64
user.language=es
java.specification.vendor=Oracle Corporation
awt.toolkit=sun.awt.windows.WToolkit
java.vm.info=mixed mode
java.version=1.8.0_72
java.ext.dirs=C:\Program Files\Java\jdk1.8.0_72\jre\lib\ext;C:\WINDOWS\Sun\Java\lib\ext
sun.boot.class.path=C:\Program Files\Java\jdk1.8.0_72\jre\lib\resources.jar;C:\Program Files\Java\jdk1.8.0_72\jre\lib\rt.jar;C:\Program Files\Java\jdk1.8.0_72\jre\lib\sunrsasign.jar;C:\Program Files\Java\jdk1.8.0_72\jre\lib\jsse.jar;C:\Program Files\Java\jdk1.8.0_72\jre\lib\jce.jar;C:\Program Files\Java\jdk1.8.0_72\jre\lib\charsets.jar;C:\Program Files\Java\jdk1.8.0_72\jre\lib\jfr.jar;C:\Program Files\Java\jdk1.8.0_72\jre\classes
java.vendor=Oracle Corporation
file.separator=\
java.vendor.url.bug=http://bugreport.sun.com/bugreport/
sun.io.unicode.encoding=UnicodeLittle
sun.cpu.endian=little
sun.desktop=windows
sun.cpu.isalist=amd64
---- Command Line ---
Empty
---- Full Classpath ---
Empty
---- Compiler Messages ---
Empty
---- org.aspectj.weaver.ltw.LTWWorld@28c97a5 ----
Class loader:
sun.misc.Launcher$AppClassLoader@18b4aac2
Class loader parent:
sun.misc.Launcher$ExtClassLoader@722c41f4
Shadow mungers:
(around(extraFlags: 3): ((((((((((within(@org.springframework.cache.annotation.CacheEvict *) && execution(public * @org.springframework.cache.annotation.CacheEvict *.*(..))) && this(BindingTypePattern(java.lang.Object, 0))) && persingleton(org.springframework.cache.aspectj.AnnotationCacheAspect)) || (((within(@org.springframework.cache.annotation.Caching *) && execution(public * @org.springframework.cache.annotation.Caching *.*(..))) && this(BindingTypePattern(java.lang.Object, 0))) && persingleton(org.springframework.cache.aspectj.AnnotationCacheAspect))) || (((within(@org.springframework.cache.annotation.CachePut *) && execution(public * @org.springframework.cache.annotation.CachePut *.*(..))) && this(BindingTypePattern(java.lang.Object, 0))) && persingleton(org.springframework.cache.aspectj.AnnotationCacheAspect))) || (((within(@org.springframework.cache.annotation.Cacheable *) && execution(public * @org.springframework.cache.annotation.Cacheable *.*(..))) && this(BindingTypePattern(java.lang.Object, 0))) && persingleton(org.springframework.cache.aspectj.AnnotationCacheAspect))) || ((execution(@org.springframework.cache.annotation.Caching * *(..)) && this(BindingTypePattern(java.lang.Object, 0))) && persingleton(org.springframework.cache.aspectj.AnnotationCacheAspect))) || ((execution(@org.springframework.cache.annotation.Cacheable * *(..)) && this(BindingTypePattern(java.lang.Object, 0))) && persingleton(org.springframework.cache.aspectj.AnnotationCacheAspect))) || ((execution(@org.springframework.cache.annotation.CacheEvict * *(..)) && this(BindingTypePattern(java.lang.Object, 0))) && persingleton(org.springframework.cache.aspectj.AnnotationCacheAspect))) || ((execution(@org.springframework.cache.annotation.CachePut * *(..)) && this(BindingTypePattern(java.lang.Object, 0))) && persingleton(org.springframework.cache.aspectj.AnnotationCacheAspect)))->java.lang.Object org.springframework.cache.aspectj.AbstractCacheAspect.ajc$around$org_springframework_cache_aspectj_AbstractCacheAspect$1$2bc714b5(java.lang.Object, org.aspectj.runtime.internal.AroundClosure, org.aspectj.lang.JoinPoint))
(around(extraFlags: 5): ((execution(@org.springframework.scheduling.annotation.Async (void || java.util.concurrent.Future+) *(..)) && persingleton(org.springframework.scheduling.aspectj.AnnotationAsyncExecutionAspect)) || (execution((void || java.util.concurrent.Future+) @org.springframework.scheduling.annotation.Async *.*(..)) && persingleton(org.springframework.scheduling.aspectj.AnnotationAsyncExecutionAspect)))->java.lang.Object org.springframework.scheduling.aspectj.AbstractAsyncExecutionAspect.ajc$around$org_springframework_scheduling_aspectj_AbstractAsyncExecutionAspect$1$6c004c3e(org.aspectj.runtime.internal.AroundClosure, org.aspectj.lang.JoinPoint$StaticPart))
org.aspectj.weaver.Checker@5abff562
org.aspectj.weaver.Checker@12140c1d
(before(extraFlags: 4): ((((within(@org.springframework.transaction.annotation.Transactional *) && execution(public * @org.springframework.transaction.annotation.Transactional *.*(..))) && this(BindingTypePattern(java.lang.Object, 0))) && persingleton(org.springframework.transaction.aspectj.AnnotationTransactionAspect)) || ((execution(@org.springframework.transaction.annotation.Transactional * *(..)) && this(BindingTypePattern(java.lang.Object, 0))) && persingleton(org.springframework.transaction.aspectj.AnnotationTransactionAspect)))->void org.springframework.transaction.aspectj.AbstractTransactionAspect.ajc$before$org_springframework_transaction_aspectj_AbstractTransactionAspect$1$2a73e96c(java.lang.Object, org.aspectj.lang.JoinPoint$StaticPart))
(afterThrowing(extraFlags: 1): ((((within(@org.springframework.transaction.annotation.Transactional *) && execution(public * @org.springframework.transaction.annotation.Transactional *.*(..))) && this(BindingTypePattern(java.lang.Object, 0))) && persingleton(org.springframework.transaction.aspectj.AnnotationTransactionAspect)) || ((execution(@org.springframework.transaction.annotation.Transactional * *(..)) && this(BindingTypePattern(java.lang.Object, 0))) && persingleton(org.springframework.transaction.aspectj.AnnotationTransactionAspect)))->void org.springframework.transaction.aspectj.AbstractTransactionAspect.ajc$afterThrowing$org_springframework_transaction_aspectj_AbstractTransactionAspect$2$2a73e96c(java.lang.Object, java.lang.Throwable))
(afterReturning: ((((within(@org.springframework.transaction.annotation.Transactional *) && execution(public * @org.springframework.transaction.annotation.Transactional *.*(..))) && this(BindingTypePattern(java.lang.Object, 0))) && persingleton(org.springframework.transaction.aspectj.AnnotationTransactionAspect)) || ((execution(@org.springframework.transaction.annotation.Transactional * *(..)) && this(BindingTypePattern(java.lang.Object, 0))) && persingleton(org.springframework.transaction.aspectj.AnnotationTransactionAspect)))->void org.springframework.transaction.aspectj.AbstractTransactionAspect.ajc$afterReturning$org_springframework_transaction_aspectj_AbstractTransactionAspect$3$2a73e96c(java.lang.Object))
(after: ((((within(@org.springframework.transaction.annotation.Transactional *) && execution(public * @org.springframework.transaction.annotation.Transactional *.*(..))) && this(BindingTypePattern(java.lang.Object, 0))) && persingleton(org.springframework.transaction.aspectj.AnnotationTransactionAspect)) || ((execution(@org.springframework.transaction.annotation.Transactional * *(..)) && this(BindingTypePattern(java.lang.Object, 0))) && persingleton(org.springframework.transaction.aspectj.AnnotationTransactionAspect)))->void org.springframework.transaction.aspectj.AbstractTransactionAspect.ajc$after$org_springframework_transaction_aspectj_AbstractTransactionAspect$4$2a73e96c(java.lang.Object))
(before: (((((initialization(org.springframework.beans.factory.aspectj.ConfigurableObject.new(..)) && initialization(org.springframework.beans.factory.aspectj.ConfigurableObject+.new(..))) && this(BindingTypePattern(java.lang.Object, 0))) && @this(org.springframework.beans.factory.annotation.Configurable)) && if(boolean org.springframework.beans.factory.aspectj.AnnotationBeanConfigurerAspect.ajc$if$bb0(org.springframework.beans.factory.annotation.Configurable))) && persingleton(org.springframework.beans.factory.aspectj.AnnotationBeanConfigurerAspect))->void org.springframework.beans.factory.aspectj.AbstractDependencyInjectionAspect.ajc$before$org_springframework_beans_factory_aspectj_AbstractDependencyInjectionAspect$1$e854fa65(java.lang.Object))
(afterReturning: (((((initialization(org.springframework.beans.factory.aspectj.ConfigurableObject+.new(..)) && this(BindingTypePattern(java.lang.Object, 0))) && @this(org.springframework.beans.factory.annotation.Configurable)) && !(@this(org.springframework.beans.factory.annotation.Configurable) && if(boolean org.springframework.beans.factory.aspectj.AnnotationBeanConfigurerAspect.ajc$if$bb0(org.springframework.beans.factory.annotation.Configurable)))) && if(boolean org.springframework.beans.factory.aspectj.AbstractDependencyInjectionAspect.ajc$if$6f1(org.aspectj.lang.JoinPoint))) && persingleton(org.springframework.beans.factory.aspectj.AnnotationBeanConfigurerAspect))->void org.springframework.beans.factory.aspectj.AbstractDependencyInjectionAspect.ajc$afterReturning$org_springframework_beans_factory_aspectj_AbstractDependencyInjectionAspect$2$1ea6722c(java.lang.Object))
(afterReturning: (((execution(java.lang.Object org.springframework.beans.factory.aspectj.AbstractInterfaceDrivenDependencyInjectionAspect$ConfigurableDeserializationSupport+.readResolve()) && this(BindingTypePattern(java.lang.Object, 0))) && @this(org.springframework.beans.factory.annotation.Configurable)) && persingleton(org.springframework.beans.factory.aspectj.AnnotationBeanConfigurerAspect))->void org.springframework.beans.factory.aspectj.AbstractDependencyInjectionAspect.ajc$afterReturning$org_springframework_beans_factory_aspectj_AbstractDependencyInjectionAspect$3$6aa27052(java.lang.Object))
Type mungers:
(BcelTypeMunger ResolvedTypeMunger(Method, java.lang.Object org.springframework.beans.factory.aspectj.AbstractInterfaceDrivenDependencyInjectionAspect$ConfigurableDeserializationSupport.readResolve()))
(BcelTypeMunger ExposeTypeMunger(java.lang.Object))
(BcelTypeMunger ExposeTypeMunger(java.lang.Object))
(BcelTypeMunger ExposeTypeMunger(java.lang.Object))
(BcelTypeMunger ExposeTypeMunger(org.springframework.beans.factory.aspectj.ConfigurableObject))
(BcelTypeMunger ExposeTypeMunger(org.springframework.beans.factory.aspectj.AbstractInterfaceDrivenDependencyInjectionAspect$ConfigurableDeserializationSupport))
Late Type mungers:
Empty
