---- AspectJ Properties ---
AspectJ Compiler 1.6.2 built on Saturday Oct 4, 2008 at 05:47:07 GMT
---- Dump Properties ---
Dump file: ajcore.20160604.114042.052.txt
Dump reason: org.aspectj.bridge.AbortException
Dump on exception: true
Dump at exit condition: abort
---- Exception Information ---
Message: abort trouble in: 
public abstract class org.springframework.beans.AbstractPropertyAccessor extends org.springframework.beans.PropertyEditorRegistrySupport implements org.springframework.beans.ConfigurablePropertyAccessor:
  private boolean extractOldValueForEditor
  public void <init>():
                    ALOAD_0     // Lorg/springframework/beans/AbstractPropertyAccessor; this   (line 34)
                    INVOKESPECIAL org.springframework.beans.PropertyEditorRegistrySupport.<init> ()V
    constructor-execution(void org.springframework.beans.AbstractPropertyAccessor.<init>())
    |               ALOAD_0     // Lorg/springframework/beans/AbstractPropertyAccessor; this   (line 37)
    |               ICONST_0
    |               PUTFIELD org.springframework.beans.AbstractPropertyAccessor.extractOldValueForEditor Z
    |               RETURN   (line 34)
    constructor-execution(void org.springframework.beans.AbstractPropertyAccessor.<init>())
  end public void <init>()

  public void setExtractOldValueForEditor(boolean):
                    ALOAD_0     // Lorg/springframework/beans/AbstractPropertyAccessor; this   (line 41)
                    ILOAD_1     // Z extractOldValueForEditor
                    PUTFIELD org.springframework.beans.AbstractPropertyAccessor.extractOldValueForEditor Z
                    RETURN   (line 42)
  end public void setExtractOldValueForEditor(boolean)

  public boolean isExtractOldValueForEditor():
                    ALOAD_0     // Lorg/springframework/beans/AbstractPropertyAccessor; this   (line 45)
                    GETFIELD org.springframework.beans.AbstractPropertyAccessor.extractOldValueForEditor Z
                    IRETURN
  end public boolean isExtractOldValueForEditor()

  public void setPropertyValue(org.springframework.beans.PropertyValue) throws org.springframework.beans.BeansException:
                    ALOAD_0     // Lorg/springframework/beans/AbstractPropertyAccessor; this   (line 50)
                    ALOAD_1     // Lorg/springframework/beans/PropertyValue; pv
                    INVOKEVIRTUAL org.springframework.beans.PropertyValue.getName ()Ljava/lang/String;
                    ALOAD_1     // Lorg/springframework/beans/PropertyValue; pv
                    INVOKEVIRTUAL org.springframework.beans.PropertyValue.getValue ()Ljava/lang/Object;
                    INVOKEVIRTUAL org.springframework.beans.AbstractPropertyAccessor.setPropertyValue (Ljava/lang/String;Ljava/lang/Object;)V
                    RETURN   (line 51)
  end public void setPropertyValue(org.springframework.beans.PropertyValue) throws org.springframework.beans.BeansException

  public void setPropertyValues(java.util.Map) throws org.springframework.beans.BeansException:
                    ALOAD_0     // Lorg/springframework/beans/AbstractPropertyAccessor; this   (line 54)
                    NEW org.springframework.beans.MutablePropertyValues
                    DUP
                    ALOAD_1     // Ljava/util/Map; map
                    INVOKESPECIAL org.springframework.beans.MutablePropertyValues.<init> (Ljava/util/Map;)V
                    INVOKEVIRTUAL org.springframework.beans.AbstractPropertyAccessor.setPropertyValues (Lorg/springframework/beans/PropertyValues;)V
                    RETURN   (line 55)
  end public void setPropertyValues(java.util.Map) throws org.springframework.beans.BeansException

  public void setPropertyValues(org.springframework.beans.PropertyValues) throws org.springframework.beans.BeansException:
                    ALOAD_0     // Lorg/springframework/beans/AbstractPropertyAccessor; this   (line 58)
                    ALOAD_1     // Lorg/springframework/beans/PropertyValues; pvs
                    ICONST_0
                    ICONST_0
                    INVOKEVIRTUAL org.springframework.beans.AbstractPropertyAccessor.setPropertyValues (Lorg/springframework/beans/PropertyValues;ZZ)V
                    RETURN   (line 59)
  end public void setPropertyValues(org.springframework.beans.PropertyValues) throws org.springframework.beans.BeansException

  public void setPropertyValues(org.springframework.beans.PropertyValues, boolean) throws org.springframework.beans.BeansException:
                    ALOAD_0     // Lorg/springframework/beans/AbstractPropertyAccessor; this   (line 62)
                    ALOAD_1     // Lorg/springframework/beans/PropertyValues; pvs
                    ILOAD_2     // Z ignoreUnknown
                    ICONST_0
                    INVOKEVIRTUAL org.springframework.beans.AbstractPropertyAccessor.setPropertyValues (Lorg/springframework/beans/PropertyValues;ZZ)V
                    RETURN   (line 63)
  end public void setPropertyValues(org.springframework.beans.PropertyValues, boolean) throws org.springframework.beans.BeansException

  public void setPropertyValues(org.springframework.beans.PropertyValues, boolean, boolean) throws org.springframework.beans.BeansException:
                    ACONST_NULL   (line 68)
                    ASTORE 4
                    ALOAD_1     // Lorg/springframework/beans/PropertyValues; pvs   (line 69)
                    INSTANCEOF org.springframework.beans.MutablePropertyValues
                    IFEQ L0
                    ALOAD_1     // Lorg/springframework/beans/PropertyValues; pvs   (line 70)
                    CHECKCAST org.springframework.beans.MutablePropertyValues
                    INVOKEVIRTUAL org.springframework.beans.MutablePropertyValues.getPropertyValueList ()Ljava/util/List;
                    GOTO L1
                L0: ALOAD_1     // Lorg/springframework/beans/PropertyValues; pvs
                    INVOKEINTERFACE org.springframework.beans.PropertyValues.getPropertyValues ()[Lorg/springframework/beans/PropertyValue;
                    INVOKESTATIC java.util.Arrays.asList ([Ljava/lang/Object;)Ljava/util/List;
                L1: ASTORE 5   (line 69)
                    ALOAD 5     // Ljava/util/List; propertyValues   (line 71)
                    INVOKEINTERFACE java.util.List.iterator ()Ljava/util/Iterator;
                    ASTORE 7
                    GOTO L4
                L2: ALOAD 7
                    INVOKEINTERFACE java.util.Iterator.next ()Ljava/lang/Object;
                    CHECKCAST org.springframework.beans.PropertyValue
                    ASTORE 6
    catch org.springframework.beans.PropertyAccessException -> E2
    | catch org.springframework.beans.NullValueInNestedPathException -> E1
    | | catch org.springframework.beans.NotWritablePropertyException -> E0
    | | |           ALOAD_0     // Lorg/springframework/beans/AbstractPropertyAccessor; this   (line 76)
    | | |           ALOAD 6     // Lorg/springframework/beans/PropertyValue; pv
    | | |           INVOKEVIRTUAL org.springframework.beans.AbstractPropertyAccessor.setPropertyValue (Lorg/springframework/beans/PropertyValue;)V
    | | catch org.springframework.beans.NotWritablePropertyException -> E0
    | catch org.springframework.beans.NullValueInNestedPathException -> E1
    catch org.springframework.beans.PropertyAccessException -> E2
                    GOTO L4
                E0: ASTORE 8   (line 78)
                    ILOAD_2     // Z ignoreUnknown   (line 79)
                    IFNE L4
                    ALOAD 8     // Lorg/springframework/beans/NotWritablePropertyException; ex   (line 80)
                    ATHROW
                E1: ASTORE 8   (line 84)
                    ILOAD_3     // Z ignoreInvalid   (line 85)
                    IFNE L4
                    ALOAD 8     // Lorg/springframework/beans/NullValueInNestedPathException; ex   (line 86)
                    ATHROW
                E2: ASTORE 8   (line 90)
                    ALOAD 4     // Ljava/util/List; propertyAccessExceptions   (line 91)
                    IFNONNULL L3
                    NEW java.util.LinkedList   (line 92)
                    DUP
                    INVOKESPECIAL java.util.LinkedList.<init> ()V
                    ASTORE 4     // Ljava/util/List; propertyAccessExceptions
                L3: ALOAD 4     // Ljava/util/List; propertyAccessExceptions   (line 94)
                    ALOAD 8     // Lorg/springframework/beans/PropertyAccessException; ex
                    INVOKEINTERFACE java.util.List.add (Ljava/lang/Object;)Z
                    POP
                L4: ALOAD 7   (line 71)
                    INVOKEINTERFACE java.util.Iterator.hasNext ()Z
                    IFNE L2
                    ALOAD 4     // Ljava/util/List; propertyAccessExceptions   (line 99)
                    IFNULL L5
                    ALOAD 4     // Ljava/util/List; propertyAccessExceptions   (line 101)
                    ALOAD 4     // Ljava/util/List; propertyAccessExceptions
                    INVOKEINTERFACE java.util.List.size ()I
                    ANEWARRAY org.springframework.beans.PropertyAccessException
                    INVOKEINTERFACE java.util.List.toArray ([Ljava/lang/Object;)[Ljava/lang/Object;
                    CHECKCAST [Lorg.springframework.beans.PropertyAccessException;
                    ASTORE 6   (line 100)
                    NEW org.springframework.beans.PropertyBatchUpdateException   (line 102)
                    DUP
                    ALOAD 6     // [Lorg/springframework/beans/PropertyAccessException; paeArray
                    INVOKESPECIAL org.springframework.beans.PropertyBatchUpdateException.<init> ([Lorg/springframework/beans/PropertyAccessException;)V
                    ATHROW
                L5: RETURN   (line 104)
  end public void setPropertyValues(org.springframework.beans.PropertyValues, boolean, boolean) throws org.springframework.beans.BeansException

  public Object convertIfNecessary(Object, Class) throws org.springframework.beans.TypeMismatchException:
                    ALOAD_0     // Lorg/springframework/beans/AbstractPropertyAccessor; this   (line 107)
                    ALOAD_1     // Ljava/lang/Object; value
                    ALOAD_2     // Ljava/lang/Class; requiredType
                    ACONST_NULL
                    INVOKEVIRTUAL org.springframework.beans.AbstractPropertyAccessor.convertIfNecessary (Ljava/lang/Object;Ljava/lang/Class;Lorg/springframework/core/MethodParameter;)Ljava/lang/Object;
                    ARETURN
  end public Object convertIfNecessary(Object, Class) throws org.springframework.beans.TypeMismatchException

  public Class getPropertyType(String):
                    ACONST_NULL   (line 114)
                    ARETURN
  end public Class getPropertyType(String)

  public abstract Object getPropertyValue(String) throws org.springframework.beans.BeansException;

  public abstract void setPropertyValue(String, Object) throws org.springframework.beans.BeansException;

end public abstract class org.springframework.beans.AbstractPropertyAccessor
 -- (NullPointerException) null
null
java.lang.NullPointerException

org.aspectj.bridge.AbortException: trouble in: 
public abstract class org.springframework.beans.AbstractPropertyAccessor extends org.springframework.beans.PropertyEditorRegistrySupport implements org.springframework.beans.ConfigurablePropertyAccessor:
  private boolean extractOldValueForEditor
  public void <init>():
                    ALOAD_0     // Lorg/springframework/beans/AbstractPropertyAccessor; this   (line 34)
                    INVOKESPECIAL org.springframework.beans.PropertyEditorRegistrySupport.<init> ()V
    constructor-execution(void org.springframework.beans.AbstractPropertyAccessor.<init>())
    |               ALOAD_0     // Lorg/springframework/beans/AbstractPropertyAccessor; this   (line 37)
    |               ICONST_0
    |               PUTFIELD org.springframework.beans.AbstractPropertyAccessor.extractOldValueForEditor Z
    |               RETURN   (line 34)
    constructor-execution(void org.springframework.beans.AbstractPropertyAccessor.<init>())
  end public void <init>()

  public void setExtractOldValueForEditor(boolean):
                    ALOAD_0     // Lorg/springframework/beans/AbstractPropertyAccessor; this   (line 41)
                    ILOAD_1     // Z extractOldValueForEditor
                    PUTFIELD org.springframework.beans.AbstractPropertyAccessor.extractOldValueForEditor Z
                    RETURN   (line 42)
  end public void setExtractOldValueForEditor(boolean)

  public boolean isExtractOldValueForEditor():
                    ALOAD_0     // Lorg/springframework/beans/AbstractPropertyAccessor; this   (line 45)
                    GETFIELD org.springframework.beans.AbstractPropertyAccessor.extractOldValueForEditor Z
                    IRETURN
  end public boolean isExtractOldValueForEditor()

  public void setPropertyValue(org.springframework.beans.PropertyValue) throws org.springframework.beans.BeansException:
                    ALOAD_0     // Lorg/springframework/beans/AbstractPropertyAccessor; this   (line 50)
                    ALOAD_1     // Lorg/springframework/beans/PropertyValue; pv
                    INVOKEVIRTUAL org.springframework.beans.PropertyValue.getName ()Ljava/lang/String;
                    ALOAD_1     // Lorg/springframework/beans/PropertyValue; pv
                    INVOKEVIRTUAL org.springframework.beans.PropertyValue.getValue ()Ljava/lang/Object;
                    INVOKEVIRTUAL org.springframework.beans.AbstractPropertyAccessor.setPropertyValue (Ljava/lang/String;Ljava/lang/Object;)V
                    RETURN   (line 51)
  end public void setPropertyValue(org.springframework.beans.PropertyValue) throws org.springframework.beans.BeansException

  public void setPropertyValues(java.util.Map) throws org.springframework.beans.BeansException:
                    ALOAD_0     // Lorg/springframework/beans/AbstractPropertyAccessor; this   (line 54)
                    NEW org.springframework.beans.MutablePropertyValues
                    DUP
                    ALOAD_1     // Ljava/util/Map; map
                    INVOKESPECIAL org.springframework.beans.MutablePropertyValues.<init> (Ljava/util/Map;)V
                    INVOKEVIRTUAL org.springframework.beans.AbstractPropertyAccessor.setPropertyValues (Lorg/springframework/beans/PropertyValues;)V
                    RETURN   (line 55)
  end public void setPropertyValues(java.util.Map) throws org.springframework.beans.BeansException

  public void setPropertyValues(org.springframework.beans.PropertyValues) throws org.springframework.beans.BeansException:
                    ALOAD_0     // Lorg/springframework/beans/AbstractPropertyAccessor; this   (line 58)
                    ALOAD_1     // Lorg/springframework/beans/PropertyValues; pvs
                    ICONST_0
                    ICONST_0
                    INVOKEVIRTUAL org.springframework.beans.AbstractPropertyAccessor.setPropertyValues (Lorg/springframework/beans/PropertyValues;ZZ)V
                    RETURN   (line 59)
  end public void setPropertyValues(org.springframework.beans.PropertyValues) throws org.springframework.beans.BeansException

  public void setPropertyValues(org.springframework.beans.PropertyValues, boolean) throws org.springframework.beans.BeansException:
                    ALOAD_0     // Lorg/springframework/beans/AbstractPropertyAccessor; this   (line 62)
                    ALOAD_1     // Lorg/springframework/beans/PropertyValues; pvs
                    ILOAD_2     // Z ignoreUnknown
                    ICONST_0
                    INVOKEVIRTUAL org.springframework.beans.AbstractPropertyAccessor.setPropertyValues (Lorg/springframework/beans/PropertyValues;ZZ)V
                    RETURN   (line 63)
  end public void setPropertyValues(org.springframework.beans.PropertyValues, boolean) throws org.springframework.beans.BeansException

  public void setPropertyValues(org.springframework.beans.PropertyValues, boolean, boolean) throws org.springframework.beans.BeansException:
                    ACONST_NULL   (line 68)
                    ASTORE 4
                    ALOAD_1     // Lorg/springframework/beans/PropertyValues; pvs   (line 69)
                    INSTANCEOF org.springframework.beans.MutablePropertyValues
                    IFEQ L0
                    ALOAD_1     // Lorg/springframework/beans/PropertyValues; pvs   (line 70)
                    CHECKCAST org.springframework.beans.MutablePropertyValues
                    INVOKEVIRTUAL org.springframework.beans.MutablePropertyValues.getPropertyValueList ()Ljava/util/List;
                    GOTO L1
                L0: ALOAD_1     // Lorg/springframework/beans/PropertyValues; pvs
                    INVOKEINTERFACE org.springframework.beans.PropertyValues.getPropertyValues ()[Lorg/springframework/beans/PropertyValue;
                    INVOKESTATIC java.util.Arrays.asList ([Ljava/lang/Object;)Ljava/util/List;
                L1: ASTORE 5   (line 69)
                    ALOAD 5     // Ljava/util/List; propertyValues   (line 71)
                    INVOKEINTERFACE java.util.List.iterator ()Ljava/util/Iterator;
                    ASTORE 7
                    GOTO L4
                L2: ALOAD 7
                    INVOKEINTERFACE java.util.Iterator.next ()Ljava/lang/Object;
                    CHECKCAST org.springframework.beans.PropertyValue
                    ASTORE 6
    catch org.springframework.beans.PropertyAccessException -> E2
    | catch org.springframework.beans.NullValueInNestedPathException -> E1
    | | catch org.springframework.beans.NotWritablePropertyException -> E0
    | | |           ALOAD_0     // Lorg/springframework/beans/AbstractPropertyAccessor; this   (line 76)
    | | |           ALOAD 6     // Lorg/springframework/beans/PropertyValue; pv
    | | |           INVOKEVIRTUAL org.springframework.beans.AbstractPropertyAccessor.setPropertyValue (Lorg/springframework/beans/PropertyValue;)V
    | | catch org.springframework.beans.NotWritablePropertyException -> E0
    | catch org.springframework.beans.NullValueInNestedPathException -> E1
    catch org.springframework.beans.PropertyAccessException -> E2
                    GOTO L4
                E0: ASTORE 8   (line 78)
                    ILOAD_2     // Z ignoreUnknown   (line 79)
                    IFNE L4
                    ALOAD 8     // Lorg/springframework/beans/NotWritablePropertyException; ex   (line 80)
                    ATHROW
                E1: ASTORE 8   (line 84)
                    ILOAD_3     // Z ignoreInvalid   (line 85)
                    IFNE L4
                    ALOAD 8     // Lorg/springframework/beans/NullValueInNestedPathException; ex   (line 86)
                    ATHROW
                E2: ASTORE 8   (line 90)
                    ALOAD 4     // Ljava/util/List; propertyAccessExceptions   (line 91)
                    IFNONNULL L3
                    NEW java.util.LinkedList   (line 92)
                    DUP
                    INVOKESPECIAL java.util.LinkedList.<init> ()V
                    ASTORE 4     // Ljava/util/List; propertyAccessExceptions
                L3: ALOAD 4     // Ljava/util/List; propertyAccessExceptions   (line 94)
                    ALOAD 8     // Lorg/springframework/beans/PropertyAccessException; ex
                    INVOKEINTERFACE java.util.List.add (Ljava/lang/Object;)Z
                    POP
                L4: ALOAD 7   (line 71)
                    INVOKEINTERFACE java.util.Iterator.hasNext ()Z
                    IFNE L2
                    ALOAD 4     // Ljava/util/List; propertyAccessExceptions   (line 99)
                    IFNULL L5
                    ALOAD 4     // Ljava/util/List; propertyAccessExceptions   (line 101)
                    ALOAD 4     // Ljava/util/List; propertyAccessExceptions
                    INVOKEINTERFACE java.util.List.size ()I
                    ANEWARRAY org.springframework.beans.PropertyAccessException
                    INVOKEINTERFACE java.util.List.toArray ([Ljava/lang/Object;)[Ljava/lang/Object;
                    CHECKCAST [Lorg.springframework.beans.PropertyAccessException;
                    ASTORE 6   (line 100)
                    NEW org.springframework.beans.PropertyBatchUpdateException   (line 102)
                    DUP
                    ALOAD 6     // [Lorg/springframework/beans/PropertyAccessException; paeArray
                    INVOKESPECIAL org.springframework.beans.PropertyBatchUpdateException.<init> ([Lorg/springframework/beans/PropertyAccessException;)V
                    ATHROW
                L5: RETURN   (line 104)
  end public void setPropertyValues(org.springframework.beans.PropertyValues, boolean, boolean) throws org.springframework.beans.BeansException

  public Object convertIfNecessary(Object, Class) throws org.springframework.beans.TypeMismatchException:
                    ALOAD_0     // Lorg/springframework/beans/AbstractPropertyAccessor; this   (line 107)
                    ALOAD_1     // Ljava/lang/Object; value
                    ALOAD_2     // Ljava/lang/Class; requiredType
                    ACONST_NULL
                    INVOKEVIRTUAL org.springframework.beans.AbstractPropertyAccessor.convertIfNecessary (Ljava/lang/Object;Ljava/lang/Class;Lorg/springframework/core/MethodParameter;)Ljava/lang/Object;
                    ARETURN
  end public Object convertIfNecessary(Object, Class) throws org.springframework.beans.TypeMismatchException

  public Class getPropertyType(String):
                    ACONST_NULL   (line 114)
                    ARETURN
  end public Class getPropertyType(String)

  public abstract Object getPropertyValue(String) throws org.springframework.beans.BeansException;

  public abstract void setPropertyValue(String, Object) throws org.springframework.beans.BeansException;

end public abstract class org.springframework.beans.AbstractPropertyAccessor

	at org.aspectj.bridge.MessageWriter.handleMessage(MessageWriter.java:47)
	at org.aspectj.weaver.tools.WeavingAdaptor$WeavingAdaptorMessageWriter.handleMessage(WeavingAdaptor.java:665)
	at org.aspectj.weaver.tools.WeavingAdaptor$WeavingAdaptorMessageHolder.handleMessage(WeavingAdaptor.java:615)
	at org.aspectj.weaver.bcel.BcelWeaver.weave(BcelWeaver.java:1752)
	at org.aspectj.weaver.bcel.BcelWeaver.weaveWithoutDump(BcelWeaver.java:1694)
	at org.aspectj.weaver.bcel.BcelWeaver.weaveAndNotify(BcelWeaver.java:1464)
	at org.aspectj.weaver.bcel.BcelWeaver.weave(BcelWeaver.java:1273)
	at org.aspectj.weaver.tools.WeavingAdaptor.getWovenBytes(WeavingAdaptor.java:394)
	at org.aspectj.weaver.tools.WeavingAdaptor.weaveClass(WeavingAdaptor.java:281)
	at org.aspectj.weaver.loadtime.Aj.preProcess(Aj.java:95)
	at org.aspectj.weaver.loadtime.ClassPreProcessorAgentAdapter.transform(ClassPreProcessorAgentAdapter.java:52)
	at sun.instrument.TransformerManager.transform(TransformerManager.java:188)
	at sun.instrument.InstrumentationImpl.transform(InstrumentationImpl.java:428)
	at java.lang.ClassLoader.defineClass1(Native Method)
	at java.lang.ClassLoader.defineClass(ClassLoader.java:760)
	at java.security.SecureClassLoader.defineClass(SecureClassLoader.java:142)
	at java.net.URLClassLoader.defineClass(URLClassLoader.java:467)
	at java.net.URLClassLoader.access$100(URLClassLoader.java:73)
	at java.net.URLClassLoader$1.run(URLClassLoader.java:368)
	at java.net.URLClassLoader$1.run(URLClassLoader.java:362)
	at java.security.AccessController.doPrivileged(Native Method)
	at java.net.URLClassLoader.findClass(URLClassLoader.java:361)
	at java.lang.ClassLoader.loadClass(ClassLoader.java:424)
	at sun.misc.Launcher$AppClassLoader.loadClass(Launcher.java:331)
	at java.lang.ClassLoader.loadClass(ClassLoader.java:357)
	at java.lang.ClassLoader.defineClass1(Native Method)
	at java.lang.ClassLoader.defineClass(ClassLoader.java:760)
	at java.security.SecureClassLoader.defineClass(SecureClassLoader.java:142)
	at java.net.URLClassLoader.defineClass(URLClassLoader.java:467)
	at java.net.URLClassLoader.access$100(URLClassLoader.java:73)
	at java.net.URLClassLoader$1.run(URLClassLoader.java:368)
	at java.net.URLClassLoader$1.run(URLClassLoader.java:362)
	at java.security.AccessController.doPrivileged(Native Method)
	at java.net.URLClassLoader.findClass(URLClassLoader.java:361)
	at java.lang.ClassLoader.loadClass(ClassLoader.java:424)
	at sun.misc.Launcher$AppClassLoader.loadClass(Launcher.java:331)
	at java.lang.ClassLoader.loadClass(ClassLoader.java:357)
	at org.springframework.beans.factory.support.AbstractAutowireCapableBeanFactory.instantiateBean(AbstractAutowireCapableBeanFactory.java:992)
	at org.springframework.beans.factory.support.AbstractAutowireCapableBeanFactory.createBeanInstance(AbstractAutowireCapableBeanFactory.java:943)
	at org.springframework.beans.factory.support.AbstractAutowireCapableBeanFactory.doCreateBean(AbstractAutowireCapableBeanFactory.java:485)
	at org.springframework.beans.factory.support.AbstractAutowireCapableBeanFactory.createBean(AbstractAutowireCapableBeanFactory.java:456)
	at org.springframework.beans.factory.support.AbstractBeanFactory$1.getObject(AbstractBeanFactory.java:294)
	at org.springframework.beans.factory.support.DefaultSingletonBeanRegistry.getSingleton(DefaultSingletonBeanRegistry.java:225)
	at org.springframework.beans.factory.support.AbstractBeanFactory.doGetBean(AbstractBeanFactory.java:291)
	at org.springframework.beans.factory.support.AbstractBeanFactory.getBean(AbstractBeanFactory.java:197)
	at org.springframework.context.support.AbstractApplicationContext.invokeBeanFactoryPostProcessors(AbstractApplicationContext.java:649)
	at org.springframework.context.support.AbstractApplicationContext.refresh(AbstractApplicationContext.java:451)
	at org.springframework.context.support.ClassPathXmlApplicationContext.<init>(ClassPathXmlApplicationContext.java:139)
	at org.springframework.context.support.ClassPathXmlApplicationContext.<init>(ClassPathXmlApplicationContext.java:83)
	at com.curso.spring.springioc0007.Main.init(Main.java:29)
	at com.curso.spring.springioc0007.Main.main(Main.java:24)
---- System Properties ---
java.runtime.name=Java(TM) SE Runtime Environment
sun.boot.library.path=C:\Program Files\Java\jdk1.8.0_72\jre\bin
java.vm.version=25.72-b15
java.vm.vendor=Oracle Corporation
java.vendor.url=http://java.oracle.com/
path.separator=;
java.vm.name=Java HotSpot(TM) 64-Bit Server VM
file.encoding.pkg=sun.io
user.country=ES
user.script=
sun.java.launcher=SUN_STANDARD
sun.os.patch.level=
java.vm.specification.name=Java Virtual Machine Specification
user.dir=C:\Users\usuario\git\spring\aspectos\Ejemplos Relacionados\SpringIoC0007Maven
java.runtime.version=1.8.0_72-b15
java.awt.graphicsenv=sun.awt.Win32GraphicsEnvironment
java.endorsed.dirs=C:\Program Files\Java\jdk1.8.0_72\jre\lib\endorsed
os.arch=amd64
java.io.tmpdir=C:\Users\usuario\AppData\Local\Temp\
line.separator=

java.vm.specification.vendor=Oracle Corporation
user.variant=
os.name=Windows 10
sun.jnu.encoding=Cp1252
java.library.path=C:\Program Files\Java\jdk1.8.0_72\bin;C:\WINDOWS\Sun\Java\bin;C:\WINDOWS\system32;C:\WINDOWS;C:\ProgramData\Oracle\Java\javapath;C:\Program Files\CollabNet\Subversion Client;E:\bin\Sencha\Cmd\5.1.3.61;C:\Users\usuario\bin\Sencha\Cmd\5.1.3.61;C:\Program Files (x86)\Intel\iCLS Client\;C:\Program Files\Intel\iCLS Client\;C:\WINDOWS\system32;C:\WINDOWS;C:\WINDOWS\System32\Wbem;C:\WINDOWS\System32\WindowsPowerShell\v1.0\;C:\Program Files\Intel\Intel(R) Management Engine Components\DAL;C:\Program Files\Intel\Intel(R) Management Engine Components\IPT;C:\Program Files (x86)\Intel\Intel(R) Management Engine Components\DAL;C:\Program Files (x86)\Intel\Intel(R) Management Engine Components\IPT;C:\Program Files (x86)\Intel\OpenCL SDK\3.0\bin\x86;C:\Program Files (x86)\Intel\OpenCL SDK\3.0\bin\x64;C:\Program Files (x86)\sbt\\bin;C:\Program Files (x86)\Heroku\bin;C:\Program Files (x86)\git\cmd;C:\Program Files (x86)\QuickTime\QTSystem\;C:\HashiCorp\Vagrant\bin;C:\Program Files (x86)\scala\bin;C:\Program Files\nodejs\;C:\Users\usuario\AppData\Local\.meteor\;C:\Users\usuario\AppData\Roaming\npm;.
java.specification.name=Java Platform API Specification
java.class.version=52.0
sun.management.compiler=HotSpot 64-Bit Tiered Compilers
os.version=10.0
user.home=C:\Users\usuario
user.timezone=Europe/Paris
java.awt.printerjob=sun.awt.windows.WPrinterJob
file.encoding=Cp1252
java.specification.version=1.8
java.class.path=C:\Users\usuario\git\spring\aspectos\Ejemplos Relacionados\SpringIoC0007Maven\target\classes;C:\Users\usuario\.m2\repository\org\springframework\spring-context\3.1.2.RELEASE\spring-context-3.1.2.RELEASE.jar;C:\Users\usuario\.m2\repository\org\springframework\spring-aop\3.1.2.RELEASE\spring-aop-3.1.2.RELEASE.jar;C:\Users\usuario\.m2\repository\aopalliance\aopalliance\1.0\aopalliance-1.0.jar;C:\Users\usuario\.m2\repository\org\springframework\spring-beans\3.1.2.RELEASE\spring-beans-3.1.2.RELEASE.jar;C:\Users\usuario\.m2\repository\org\springframework\spring-core\3.1.2.RELEASE\spring-core-3.1.2.RELEASE.jar;C:\Users\usuario\.m2\repository\commons-logging\commons-logging\1.1.1\commons-logging-1.1.1.jar;C:\Users\usuario\.m2\repository\org\springframework\spring-expression\3.1.2.RELEASE\spring-expression-3.1.2.RELEASE.jar;C:\Users\usuario\.m2\repository\org\springframework\spring-asm\3.1.2.RELEASE\spring-asm-3.1.2.RELEASE.jar;C:\Users\usuario\.m2\repository\org\springframework\spring-aspects\3.1.2.RELEASE\spring-aspects-3.1.2.RELEASE.jar;C:\Users\usuario\.m2\repository\org\springframework\spring-context-support\3.1.2.RELEASE\spring-context-support-3.1.2.RELEASE.jar;.\..\aspectjweaver.jar
user.name=usuario
java.vm.specification.version=1.8
sun.java.command=com.curso.spring.springioc0007.Main
java.home=C:\Program Files\Java\jdk1.8.0_72\jre
sun.arch.data.model=64
user.language=es
java.specification.vendor=Oracle Corporation
awt.toolkit=sun.awt.windows.WToolkit
java.vm.info=mixed mode
java.version=1.8.0_72
java.ext.dirs=C:\Program Files\Java\jdk1.8.0_72\jre\lib\ext;C:\WINDOWS\Sun\Java\lib\ext
sun.boot.class.path=C:\Program Files\Java\jdk1.8.0_72\jre\lib\resources.jar;C:\Program Files\Java\jdk1.8.0_72\jre\lib\rt.jar;C:\Program Files\Java\jdk1.8.0_72\jre\lib\sunrsasign.jar;C:\Program Files\Java\jdk1.8.0_72\jre\lib\jsse.jar;C:\Program Files\Java\jdk1.8.0_72\jre\lib\jce.jar;C:\Program Files\Java\jdk1.8.0_72\jre\lib\charsets.jar;C:\Program Files\Java\jdk1.8.0_72\jre\lib\jfr.jar;C:\Program Files\Java\jdk1.8.0_72\jre\classes
java.vendor=Oracle Corporation
file.separator=\
java.vendor.url.bug=http://bugreport.sun.com/bugreport/
sun.io.unicode.encoding=UnicodeLittle
sun.cpu.endian=little
sun.desktop=windows
sun.cpu.isalist=amd64
---- Command Line ---
Empty
---- Full Classpath ---
Empty
---- Compiler Messages ---
Empty
---- org.aspectj.weaver.ltw.LTWWorld@28c97a5 ----
Class loader:
sun.misc.Launcher$AppClassLoader@18b4aac2
Class loader parent:
sun.misc.Launcher$ExtClassLoader@722c41f4
Shadow mungers:
(around(extraFlags: 3): ((((((((((within(@org.springframework.cache.annotation.CacheEvict *) && execution(public * @org.springframework.cache.annotation.CacheEvict *.*(..))) && this(BindingTypePattern(java.lang.Object, 0))) && persingleton(org.springframework.cache.aspectj.AnnotationCacheAspect)) || (((within(@org.springframework.cache.annotation.Caching *) && execution(public * @org.springframework.cache.annotation.Caching *.*(..))) && this(BindingTypePattern(java.lang.Object, 0))) && persingleton(org.springframework.cache.aspectj.AnnotationCacheAspect))) || (((within(@org.springframework.cache.annotation.CachePut *) && execution(public * @org.springframework.cache.annotation.CachePut *.*(..))) && this(BindingTypePattern(java.lang.Object, 0))) && persingleton(org.springframework.cache.aspectj.AnnotationCacheAspect))) || (((within(@org.springframework.cache.annotation.Cacheable *) && execution(public * @org.springframework.cache.annotation.Cacheable *.*(..))) && this(BindingTypePattern(java.lang.Object, 0))) && persingleton(org.springframework.cache.aspectj.AnnotationCacheAspect))) || ((execution(@org.springframework.cache.annotation.Caching * *(..)) && this(BindingTypePattern(java.lang.Object, 0))) && persingleton(org.springframework.cache.aspectj.AnnotationCacheAspect))) || ((execution(@org.springframework.cache.annotation.Cacheable * *(..)) && this(BindingTypePattern(java.lang.Object, 0))) && persingleton(org.springframework.cache.aspectj.AnnotationCacheAspect))) || ((execution(@org.springframework.cache.annotation.CacheEvict * *(..)) && this(BindingTypePattern(java.lang.Object, 0))) && persingleton(org.springframework.cache.aspectj.AnnotationCacheAspect))) || ((execution(@org.springframework.cache.annotation.CachePut * *(..)) && this(BindingTypePattern(java.lang.Object, 0))) && persingleton(org.springframework.cache.aspectj.AnnotationCacheAspect)))->java.lang.Object org.springframework.cache.aspectj.AbstractCacheAspect.ajc$around$org_springframework_cache_aspectj_AbstractCacheAspect$1$2bc714b5(java.lang.Object, org.aspectj.runtime.internal.AroundClosure, org.aspectj.lang.JoinPoint))
(around(extraFlags: 5): ((execution(@org.springframework.scheduling.annotation.Async (void || java.util.concurrent.Future+) *(..)) && persingleton(org.springframework.scheduling.aspectj.AnnotationAsyncExecutionAspect)) || (execution((void || java.util.concurrent.Future+) @org.springframework.scheduling.annotation.Async *.*(..)) && persingleton(org.springframework.scheduling.aspectj.AnnotationAsyncExecutionAspect)))->java.lang.Object org.springframework.scheduling.aspectj.AbstractAsyncExecutionAspect.ajc$around$org_springframework_scheduling_aspectj_AbstractAsyncExecutionAspect$1$6c004c3e(org.aspectj.runtime.internal.AroundClosure, org.aspectj.lang.JoinPoint$StaticPart))
org.aspectj.weaver.Checker@5abff562
org.aspectj.weaver.Checker@12140c1d
(before(extraFlags: 4): ((((within(@org.springframework.transaction.annotation.Transactional *) && execution(public * @org.springframework.transaction.annotation.Transactional *.*(..))) && this(BindingTypePattern(java.lang.Object, 0))) && persingleton(org.springframework.transaction.aspectj.AnnotationTransactionAspect)) || ((execution(@org.springframework.transaction.annotation.Transactional * *(..)) && this(BindingTypePattern(java.lang.Object, 0))) && persingleton(org.springframework.transaction.aspectj.AnnotationTransactionAspect)))->void org.springframework.transaction.aspectj.AbstractTransactionAspect.ajc$before$org_springframework_transaction_aspectj_AbstractTransactionAspect$1$2a73e96c(java.lang.Object, org.aspectj.lang.JoinPoint$StaticPart))
(afterThrowing(extraFlags: 1): ((((within(@org.springframework.transaction.annotation.Transactional *) && execution(public * @org.springframework.transaction.annotation.Transactional *.*(..))) && this(BindingTypePattern(java.lang.Object, 0))) && persingleton(org.springframework.transaction.aspectj.AnnotationTransactionAspect)) || ((execution(@org.springframework.transaction.annotation.Transactional * *(..)) && this(BindingTypePattern(java.lang.Object, 0))) && persingleton(org.springframework.transaction.aspectj.AnnotationTransactionAspect)))->void org.springframework.transaction.aspectj.AbstractTransactionAspect.ajc$afterThrowing$org_springframework_transaction_aspectj_AbstractTransactionAspect$2$2a73e96c(java.lang.Object, java.lang.Throwable))
(afterReturning: ((((within(@org.springframework.transaction.annotation.Transactional *) && execution(public * @org.springframework.transaction.annotation.Transactional *.*(..))) && this(BindingTypePattern(java.lang.Object, 0))) && persingleton(org.springframework.transaction.aspectj.AnnotationTransactionAspect)) || ((execution(@org.springframework.transaction.annotation.Transactional * *(..)) && this(BindingTypePattern(java.lang.Object, 0))) && persingleton(org.springframework.transaction.aspectj.AnnotationTransactionAspect)))->void org.springframework.transaction.aspectj.AbstractTransactionAspect.ajc$afterReturning$org_springframework_transaction_aspectj_AbstractTransactionAspect$3$2a73e96c(java.lang.Object))
(after: ((((within(@org.springframework.transaction.annotation.Transactional *) && execution(public * @org.springframework.transaction.annotation.Transactional *.*(..))) && this(BindingTypePattern(java.lang.Object, 0))) && persingleton(org.springframework.transaction.aspectj.AnnotationTransactionAspect)) || ((execution(@org.springframework.transaction.annotation.Transactional * *(..)) && this(BindingTypePattern(java.lang.Object, 0))) && persingleton(org.springframework.transaction.aspectj.AnnotationTransactionAspect)))->void org.springframework.transaction.aspectj.AbstractTransactionAspect.ajc$after$org_springframework_transaction_aspectj_AbstractTransactionAspect$4$2a73e96c(java.lang.Object))
(before: (((((initialization(org.springframework.beans.factory.aspectj.ConfigurableObject.new(..)) && initialization(org.springframework.beans.factory.aspectj.ConfigurableObject+.new(..))) && this(BindingTypePattern(java.lang.Object, 0))) && @this(org.springframework.beans.factory.annotation.Configurable)) && if(boolean org.springframework.beans.factory.aspectj.AnnotationBeanConfigurerAspect.ajc$if$bb0(org.springframework.beans.factory.annotation.Configurable))) && persingleton(org.springframework.beans.factory.aspectj.AnnotationBeanConfigurerAspect))->void org.springframework.beans.factory.aspectj.AbstractDependencyInjectionAspect.ajc$before$org_springframework_beans_factory_aspectj_AbstractDependencyInjectionAspect$1$e854fa65(java.lang.Object))
(afterReturning: (((((initialization(org.springframework.beans.factory.aspectj.ConfigurableObject+.new(..)) && this(BindingTypePattern(java.lang.Object, 0))) && @this(org.springframework.beans.factory.annotation.Configurable)) && !(@this(org.springframework.beans.factory.annotation.Configurable) && if(boolean org.springframework.beans.factory.aspectj.AnnotationBeanConfigurerAspect.ajc$if$bb0(org.springframework.beans.factory.annotation.Configurable)))) && if(boolean org.springframework.beans.factory.aspectj.AbstractDependencyInjectionAspect.ajc$if$6f1(org.aspectj.lang.JoinPoint))) && persingleton(org.springframework.beans.factory.aspectj.AnnotationBeanConfigurerAspect))->void org.springframework.beans.factory.aspectj.AbstractDependencyInjectionAspect.ajc$afterReturning$org_springframework_beans_factory_aspectj_AbstractDependencyInjectionAspect$2$1ea6722c(java.lang.Object))
(afterReturning: (((execution(java.lang.Object org.springframework.beans.factory.aspectj.AbstractInterfaceDrivenDependencyInjectionAspect$ConfigurableDeserializationSupport+.readResolve()) && this(BindingTypePattern(java.lang.Object, 0))) && @this(org.springframework.beans.factory.annotation.Configurable)) && persingleton(org.springframework.beans.factory.aspectj.AnnotationBeanConfigurerAspect))->void org.springframework.beans.factory.aspectj.AbstractDependencyInjectionAspect.ajc$afterReturning$org_springframework_beans_factory_aspectj_AbstractDependencyInjectionAspect$3$6aa27052(java.lang.Object))
Type mungers:
(BcelTypeMunger ResolvedTypeMunger(Method, java.lang.Object org.springframework.beans.factory.aspectj.AbstractInterfaceDrivenDependencyInjectionAspect$ConfigurableDeserializationSupport.readResolve()))
(BcelTypeMunger ExposeTypeMunger(java.lang.Object))
(BcelTypeMunger ExposeTypeMunger(java.lang.Object))
(BcelTypeMunger ExposeTypeMunger(java.lang.Object))
(BcelTypeMunger ExposeTypeMunger(org.springframework.beans.factory.aspectj.ConfigurableObject))
(BcelTypeMunger ExposeTypeMunger(org.springframework.beans.factory.aspectj.AbstractInterfaceDrivenDependencyInjectionAspect$ConfigurableDeserializationSupport))
Late Type mungers:
Empty
