---- AspectJ Properties ---
AspectJ Compiler 1.6.2 built on Saturday Oct 4, 2008 at 05:47:07 GMT
---- Dump Properties ---
Dump file: ajcore.20160604.114036.610.txt
Dump reason: org.aspectj.bridge.AbortException
Dump on exception: true
Dump at exit condition: abort
---- Exception Information ---
Message: abort trouble in: 
public abstract class org.springframework.util.StringUtils extends java.lang.Object:
  private static final String FOLDER_SEPARATOR = "/"
  private static final String WINDOWS_FOLDER_SEPARATOR = "\\"
  private static final String TOP_PATH = ".."
  private static final String CURRENT_PATH = "."
  private static final char EXTENSION_SEPARATOR = 46
  public void <init>():
                    ALOAD_0     // Lorg/springframework/util/StringUtils; this   (line 55)
                    INVOKESPECIAL java.lang.Object.<init> ()V
    constructor-execution(void org.springframework.util.StringUtils.<init>())
    |               RETURN
    constructor-execution(void org.springframework.util.StringUtils.<init>())
  end public void <init>()

  public static boolean hasLength(CharSequence):
                    ALOAD_0     // Ljava/lang/CharSequence; str   (line 86)
                    IFNULL L0
                    ALOAD_0     // Ljava/lang/CharSequence; str
                    INVOKEINTERFACE java.lang.CharSequence.length ()I
                    IFLE L0
                    ICONST_1
                    IRETURN
                L0: ICONST_0
                    IRETURN
  end public static boolean hasLength(CharSequence)

  public static boolean hasLength(String):
                    ALOAD_0     // Ljava/lang/String; str   (line 97)
                    INVOKESTATIC org.springframework.util.StringUtils.hasLength (Ljava/lang/CharSequence;)Z
                    IRETURN
  end public static boolean hasLength(String)

  public static boolean hasText(CharSequence):
                    ALOAD_0     // Ljava/lang/CharSequence; str   (line 117)
                    INVOKESTATIC org.springframework.util.StringUtils.hasLength (Ljava/lang/CharSequence;)Z
                    IFNE L0
                    ICONST_0   (line 118)
                    IRETURN
                L0: ALOAD_0     // Ljava/lang/CharSequence; str   (line 120)
                    INVOKEINTERFACE java.lang.CharSequence.length ()I
                    ISTORE_1
                    ICONST_0   (line 121)
                    ISTORE_2
                    GOTO L3
                L1: ALOAD_0     // Ljava/lang/CharSequence; str   (line 122)
                    ILOAD_2     // I i
                    INVOKEINTERFACE java.lang.CharSequence.charAt (I)C
                    INVOKESTATIC java.lang.Character.isWhitespace (C)Z
                    IFNE L2
                    ICONST_1   (line 123)
                    IRETURN
                L2: IINC_2 1     // I i   (line 121)
                L3: ILOAD_2     // I i
                    ILOAD_1     // I strLen
                    IF_ICMPLT L1
                    ICONST_0   (line 126)
                    IRETURN
  end public static boolean hasText(CharSequence)

  public static boolean hasText(String):
                    ALOAD_0     // Ljava/lang/String; str   (line 139)
                    INVOKESTATIC org.springframework.util.StringUtils.hasText (Ljava/lang/CharSequence;)Z
                    IRETURN
  end public static boolean hasText(String)

  public static boolean containsWhitespace(CharSequence):
                    ALOAD_0     // Ljava/lang/CharSequence; str   (line 150)
                    INVOKESTATIC org.springframework.util.StringUtils.hasLength (Ljava/lang/CharSequence;)Z
                    IFNE L0
                    ICONST_0   (line 151)
                    IRETURN
                L0: ALOAD_0     // Ljava/lang/CharSequence; str   (line 153)
                    INVOKEINTERFACE java.lang.CharSequence.length ()I
                    ISTORE_1
                    ICONST_0   (line 154)
                    ISTORE_2
                    GOTO L3
                L1: ALOAD_0     // Ljava/lang/CharSequence; str   (line 155)
                    ILOAD_2     // I i
                    INVOKEINTERFACE java.lang.CharSequence.charAt (I)C
                    INVOKESTATIC java.lang.Character.isWhitespace (C)Z
                    IFEQ L2
                    ICONST_1   (line 156)
                    IRETURN
                L2: IINC_2 1     // I i   (line 154)
                L3: ILOAD_2     // I i
                    ILOAD_1     // I strLen
                    IF_ICMPLT L1
                    ICONST_0   (line 159)
                    IRETURN
  end public static boolean containsWhitespace(CharSequence)

  public static boolean containsWhitespace(String):
                    ALOAD_0     // Ljava/lang/String; str   (line 170)
                    INVOKESTATIC org.springframework.util.StringUtils.containsWhitespace (Ljava/lang/CharSequence;)Z
                    IRETURN
  end public static boolean containsWhitespace(String)

  public static String trimWhitespace(String):
                    ALOAD_0     // Ljava/lang/String; str   (line 180)
                    INVOKESTATIC org.springframework.util.StringUtils.hasLength (Ljava/lang/String;)Z
                    IFNE L0
                    ALOAD_0     // Ljava/lang/String; str   (line 181)
                    ARETURN
                L0: NEW java.lang.StringBuilder   (line 183)
                    DUP
                    ALOAD_0     // Ljava/lang/String; str
                    INVOKESPECIAL java.lang.StringBuilder.<init> (Ljava/lang/String;)V
                    ASTORE_1
                    GOTO L2   (line 184)
                L1: ALOAD_1     // Ljava/lang/StringBuilder; sb   (line 185)
                    ICONST_0
                    INVOKEVIRTUAL java.lang.StringBuilder.deleteCharAt (I)Ljava/lang/StringBuilder;
                    POP
                L2: ALOAD_1     // Ljava/lang/StringBuilder; sb   (line 184)
                    INVOKEVIRTUAL java.lang.StringBuilder.length ()I
                    IFLE L4
                    ALOAD_1     // Ljava/lang/StringBuilder; sb
                    ICONST_0
                    INVOKEVIRTUAL java.lang.StringBuilder.charAt (I)C
                    INVOKESTATIC java.lang.Character.isWhitespace (C)Z
                    IFNE L1
                    GOTO L4   (line 187)
                L3: ALOAD_1     // Ljava/lang/StringBuilder; sb   (line 188)
                    ALOAD_1     // Ljava/lang/StringBuilder; sb
                    INVOKEVIRTUAL java.lang.StringBuilder.length ()I
                    ICONST_1
                    ISUB
                    INVOKEVIRTUAL java.lang.StringBuilder.deleteCharAt (I)Ljava/lang/StringBuilder;
                    POP
                L4: ALOAD_1     // Ljava/lang/StringBuilder; sb   (line 187)
                    INVOKEVIRTUAL java.lang.StringBuilder.length ()I
                    IFLE L5
                    ALOAD_1     // Ljava/lang/StringBuilder; sb
                    ALOAD_1     // Ljava/lang/StringBuilder; sb
                    INVOKEVIRTUAL java.lang.StringBuilder.length ()I
                    ICONST_1
                    ISUB
                    INVOKEVIRTUAL java.lang.StringBuilder.charAt (I)C
                    INVOKESTATIC java.lang.Character.isWhitespace (C)Z
                    IFNE L3
                L5: ALOAD_1     // Ljava/lang/StringBuilder; sb   (line 190)
                    INVOKEVIRTUAL java.lang.StringBuilder.toString ()Ljava/lang/String;
                    ARETURN
  end public static String trimWhitespace(String)

  public static String trimAllWhitespace(String):
                    ALOAD_0     // Ljava/lang/String; str   (line 201)
                    INVOKESTATIC org.springframework.util.StringUtils.hasLength (Ljava/lang/String;)Z
                    IFNE L0
                    ALOAD_0     // Ljava/lang/String; str   (line 202)
                    ARETURN
                L0: NEW java.lang.StringBuilder   (line 204)
                    DUP
                    ALOAD_0     // Ljava/lang/String; str
                    INVOKESPECIAL java.lang.StringBuilder.<init> (Ljava/lang/String;)V
                    ASTORE_1
                    ICONST_0   (line 205)
                    ISTORE_2
                    GOTO L3   (line 206)
                L1: ALOAD_1     // Ljava/lang/StringBuilder; sb   (line 207)
                    ILOAD_2     // I index
                    INVOKEVIRTUAL java.lang.StringBuilder.charAt (I)C
                    INVOKESTATIC java.lang.Character.isWhitespace (C)Z
                    IFEQ L2
                    ALOAD_1     // Ljava/lang/StringBuilder; sb   (line 208)
                    ILOAD_2     // I index
                    INVOKEVIRTUAL java.lang.StringBuilder.deleteCharAt (I)Ljava/lang/StringBuilder;
                    POP
                    GOTO L3
                L2: IINC_2 1     // I index   (line 211)
                L3: ALOAD_1     // Ljava/lang/StringBuilder; sb   (line 206)
                    INVOKEVIRTUAL java.lang.StringBuilder.length ()I
                    ILOAD_2     // I index
                    IF_ICMPGT L1
                    ALOAD_1     // Ljava/lang/StringBuilder; sb   (line 214)
                    INVOKEVIRTUAL java.lang.StringBuilder.toString ()Ljava/lang/String;
                    ARETURN
  end public static String trimAllWhitespace(String)

  public static String trimLeadingWhitespace(String):
                    ALOAD_0     // Ljava/lang/String; str   (line 224)
                    INVOKESTATIC org.springframework.util.StringUtils.hasLength (Ljava/lang/String;)Z
                    IFNE L0
                    ALOAD_0     // Ljava/lang/String; str   (line 225)
                    ARETURN
                L0: NEW java.lang.StringBuilder   (line 227)
                    DUP
                    ALOAD_0     // Ljava/lang/String; str
                    INVOKESPECIAL java.lang.StringBuilder.<init> (Ljava/lang/String;)V
                    ASTORE_1
                    GOTO L2   (line 228)
                L1: ALOAD_1     // Ljava/lang/StringBuilder; sb   (line 229)
                    ICONST_0
                    INVOKEVIRTUAL java.lang.StringBuilder.deleteCharAt (I)Ljava/lang/StringBuilder;
                    POP
                L2: ALOAD_1     // Ljava/lang/StringBuilder; sb   (line 228)
                    INVOKEVIRTUAL java.lang.StringBuilder.length ()I
                    IFLE L3
                    ALOAD_1     // Ljava/lang/StringBuilder; sb
                    ICONST_0
                    INVOKEVIRTUAL java.lang.StringBuilder.charAt (I)C
                    INVOKESTATIC java.lang.Character.isWhitespace (C)Z
                    IFNE L1
                L3: ALOAD_1     // Ljava/lang/StringBuilder; sb   (line 231)
                    INVOKEVIRTUAL java.lang.StringBuilder.toString ()Ljava/lang/String;
                    ARETURN
  end public static String trimLeadingWhitespace(String)

  public static String trimTrailingWhitespace(String):
                    ALOAD_0     // Ljava/lang/String; str   (line 241)
                    INVOKESTATIC org.springframework.util.StringUtils.hasLength (Ljava/lang/String;)Z
                    IFNE L0
                    ALOAD_0     // Ljava/lang/String; str   (line 242)
                    ARETURN
                L0: NEW java.lang.StringBuilder   (line 244)
                    DUP
                    ALOAD_0     // Ljava/lang/String; str
                    INVOKESPECIAL java.lang.StringBuilder.<init> (Ljava/lang/String;)V
                    ASTORE_1
                    GOTO L2   (line 245)
                L1: ALOAD_1     // Ljava/lang/StringBuilder; sb   (line 246)
                    ALOAD_1     // Ljava/lang/StringBuilder; sb
                    INVOKEVIRTUAL java.lang.StringBuilder.length ()I
                    ICONST_1
                    ISUB
                    INVOKEVIRTUAL java.lang.StringBuilder.deleteCharAt (I)Ljava/lang/StringBuilder;
                    POP
                L2: ALOAD_1     // Ljava/lang/StringBuilder; sb   (line 245)
                    INVOKEVIRTUAL java.lang.StringBuilder.length ()I
                    IFLE L3
                    ALOAD_1     // Ljava/lang/StringBuilder; sb
                    ALOAD_1     // Ljava/lang/StringBuilder; sb
                    INVOKEVIRTUAL java.lang.StringBuilder.length ()I
                    ICONST_1
                    ISUB
                    INVOKEVIRTUAL java.lang.StringBuilder.charAt (I)C
                    INVOKESTATIC java.lang.Character.isWhitespace (C)Z
                    IFNE L1
                L3: ALOAD_1     // Ljava/lang/StringBuilder; sb   (line 248)
                    INVOKEVIRTUAL java.lang.StringBuilder.toString ()Ljava/lang/String;
                    ARETURN
  end public static String trimTrailingWhitespace(String)

  public static String trimLeadingCharacter(String, char):
                    ALOAD_0     // Ljava/lang/String; str   (line 258)
                    INVOKESTATIC org.springframework.util.StringUtils.hasLength (Ljava/lang/String;)Z
                    IFNE L0
                    ALOAD_0     // Ljava/lang/String; str   (line 259)
                    ARETURN
                L0: NEW java.lang.StringBuilder   (line 261)
                    DUP
                    ALOAD_0     // Ljava/lang/String; str
                    INVOKESPECIAL java.lang.StringBuilder.<init> (Ljava/lang/String;)V
                    ASTORE_2
                    GOTO L2   (line 262)
                L1: ALOAD_2     // Ljava/lang/StringBuilder; sb   (line 263)
                    ICONST_0
                    INVOKEVIRTUAL java.lang.StringBuilder.deleteCharAt (I)Ljava/lang/StringBuilder;
                    POP
                L2: ALOAD_2     // Ljava/lang/StringBuilder; sb   (line 262)
                    INVOKEVIRTUAL java.lang.StringBuilder.length ()I
                    IFLE L3
                    ALOAD_2     // Ljava/lang/StringBuilder; sb
                    ICONST_0
                    INVOKEVIRTUAL java.lang.StringBuilder.charAt (I)C
                    ILOAD_1     // C leadingCharacter
                    IF_ICMPEQ L1
                L3: ALOAD_2     // Ljava/lang/StringBuilder; sb   (line 265)
                    INVOKEVIRTUAL java.lang.StringBuilder.toString ()Ljava/lang/String;
                    ARETURN
  end public static String trimLeadingCharacter(String, char)

  public static String trimTrailingCharacter(String, char):
                    ALOAD_0     // Ljava/lang/String; str   (line 275)
                    INVOKESTATIC org.springframework.util.StringUtils.hasLength (Ljava/lang/String;)Z
                    IFNE L0
                    ALOAD_0     // Ljava/lang/String; str   (line 276)
                    ARETURN
                L0: NEW java.lang.StringBuilder   (line 278)
                    DUP
                    ALOAD_0     // Ljava/lang/String; str
                    INVOKESPECIAL java.lang.StringBuilder.<init> (Ljava/lang/String;)V
                    ASTORE_2
                    GOTO L2   (line 279)
                L1: ALOAD_2     // Ljava/lang/StringBuilder; sb   (line 280)
                    ALOAD_2     // Ljava/lang/StringBuilder; sb
                    INVOKEVIRTUAL java.lang.StringBuilder.length ()I
                    ICONST_1
                    ISUB
                    INVOKEVIRTUAL java.lang.StringBuilder.deleteCharAt (I)Ljava/lang/StringBuilder;
                    POP
                L2: ALOAD_2     // Ljava/lang/StringBuilder; sb   (line 279)
                    INVOKEVIRTUAL java.lang.StringBuilder.length ()I
                    IFLE L3
                    ALOAD_2     // Ljava/lang/StringBuilder; sb
                    ALOAD_2     // Ljava/lang/StringBuilder; sb
                    INVOKEVIRTUAL java.lang.StringBuilder.length ()I
                    ICONST_1
                    ISUB
                    INVOKEVIRTUAL java.lang.StringBuilder.charAt (I)C
                    ILOAD_1     // C trailingCharacter
                    IF_ICMPEQ L1
                L3: ALOAD_2     // Ljava/lang/StringBuilder; sb   (line 282)
                    INVOKEVIRTUAL java.lang.StringBuilder.toString ()Ljava/lang/String;
                    ARETURN
  end public static String trimTrailingCharacter(String, char)

  public static boolean startsWithIgnoreCase(String, String):
                    ALOAD_0     // Ljava/lang/String; str   (line 294)
                    IFNULL L0
                    ALOAD_1     // Ljava/lang/String; prefix
                    IFNONNULL L1
                L0: ICONST_0   (line 295)
                    IRETURN
                L1: ALOAD_0     // Ljava/lang/String; str   (line 297)
                    ALOAD_1     // Ljava/lang/String; prefix
                    INVOKEVIRTUAL java.lang.String.startsWith (Ljava/lang/String;)Z
                    IFEQ L2
                    ICONST_1   (line 298)
                    IRETURN
                L2: ALOAD_0     // Ljava/lang/String; str   (line 300)
                    INVOKEVIRTUAL java.lang.String.length ()I
                    ALOAD_1     // Ljava/lang/String; prefix
                    INVOKEVIRTUAL java.lang.String.length ()I
                    IF_ICMPGE L3
                    ICONST_0   (line 301)
                    IRETURN
                L3: ALOAD_0     // Ljava/lang/String; str   (line 303)
                    ICONST_0
                    ALOAD_1     // Ljava/lang/String; prefix
                    INVOKEVIRTUAL java.lang.String.length ()I
                    INVOKEVIRTUAL java.lang.String.substring (II)Ljava/lang/String;
                    INVOKEVIRTUAL java.lang.String.toLowerCase ()Ljava/lang/String;
                    ASTORE_2
                    ALOAD_1     // Ljava/lang/String; prefix   (line 304)
                    INVOKEVIRTUAL java.lang.String.toLowerCase ()Ljava/lang/String;
                    ASTORE_3
                    ALOAD_2     // Ljava/lang/String; lcStr   (line 305)
                    ALOAD_3     // Ljava/lang/String; lcPrefix
                    INVOKEVIRTUAL java.lang.String.equals (Ljava/lang/Object;)Z
                    IRETURN
  end public static boolean startsWithIgnoreCase(String, String)

  public static boolean endsWithIgnoreCase(String, String):
                    ALOAD_0     // Ljava/lang/String; str   (line 316)
                    IFNULL L0
                    ALOAD_1     // Ljava/lang/String; suffix
                    IFNONNULL L1
                L0: ICONST_0   (line 317)
                    IRETURN
                L1: ALOAD_0     // Ljava/lang/String; str   (line 319)
                    ALOAD_1     // Ljava/lang/String; suffix
                    INVOKEVIRTUAL java.lang.String.endsWith (Ljava/lang/String;)Z
                    IFEQ L2
                    ICONST_1   (line 320)
                    IRETURN
                L2: ALOAD_0     // Ljava/lang/String; str   (line 322)
                    INVOKEVIRTUAL java.lang.String.length ()I
                    ALOAD_1     // Ljava/lang/String; suffix
                    INVOKEVIRTUAL java.lang.String.length ()I
                    IF_ICMPGE L3
                    ICONST_0   (line 323)
                    IRETURN
                L3: ALOAD_0     // Ljava/lang/String; str   (line 326)
                    ALOAD_0     // Ljava/lang/String; str
                    INVOKEVIRTUAL java.lang.String.length ()I
                    ALOAD_1     // Ljava/lang/String; suffix
                    INVOKEVIRTUAL java.lang.String.length ()I
                    ISUB
                    INVOKEVIRTUAL java.lang.String.substring (I)Ljava/lang/String;
                    INVOKEVIRTUAL java.lang.String.toLowerCase ()Ljava/lang/String;
                    ASTORE_2
                    ALOAD_1     // Ljava/lang/String; suffix   (line 327)
                    INVOKEVIRTUAL java.lang.String.toLowerCase ()Ljava/lang/String;
                    ASTORE_3
                    ALOAD_2     // Ljava/lang/String; lcStr   (line 328)
                    ALOAD_3     // Ljava/lang/String; lcSuffix
                    INVOKEVIRTUAL java.lang.String.equals (Ljava/lang/Object;)Z
                    IRETURN
  end public static boolean endsWithIgnoreCase(String, String)

  public static boolean substringMatch(CharSequence, int, CharSequence):
                    ICONST_0   (line 339)
                    ISTORE_3
                    GOTO L3
                L0: ILOAD_1     // I index   (line 340)
                    ILOAD_3     // I j
                    IADD
                    ISTORE 4
                    ILOAD 4     // I i   (line 341)
                    ALOAD_0     // Ljava/lang/CharSequence; str
                    INVOKEINTERFACE java.lang.CharSequence.length ()I
                    IF_ICMPGE L1
                    ALOAD_0     // Ljava/lang/CharSequence; str
                    ILOAD 4     // I i
                    INVOKEINTERFACE java.lang.CharSequence.charAt (I)C
                    ALOAD_2     // Ljava/lang/CharSequence; substring
                    ILOAD_3     // I j
                    INVOKEINTERFACE java.lang.CharSequence.charAt (I)C
                    IF_ICMPEQ L2
                L1: ICONST_0   (line 342)
                    IRETURN
                L2: IINC_3 1     // I j   (line 339)
                L3: ILOAD_3     // I j
                    ALOAD_2     // Ljava/lang/CharSequence; substring
                    INVOKEINTERFACE java.lang.CharSequence.length ()I
                    IF_ICMPLT L0
                    ICONST_1   (line 345)
                    IRETURN
  end public static boolean substringMatch(CharSequence, int, CharSequence)

  public static int countOccurrencesOf(String, String):
                    ALOAD_0     // Ljava/lang/String; str   (line 354)
                    IFNULL L0
                    ALOAD_1     // Ljava/lang/String; sub
                    IFNULL L0
                    ALOAD_0     // Ljava/lang/String; str
                    INVOKEVIRTUAL java.lang.String.length ()I
                    IFEQ L0
                    ALOAD_1     // Ljava/lang/String; sub
                    INVOKEVIRTUAL java.lang.String.length ()I
                    IFNE L1
                L0: ICONST_0   (line 355)
                    IRETURN
                L1: ICONST_0   (line 357)
                    ISTORE_2
                    ICONST_0   (line 358)
                    ISTORE_3
                    GOTO L3   (line 360)
                L2: IINC_2 1     // I count   (line 361)
                    ILOAD 4     // I idx   (line 362)
                    ALOAD_1     // Ljava/lang/String; sub
                    INVOKEVIRTUAL java.lang.String.length ()I
                    IADD
                    ISTORE_3     // I pos
                L3: ALOAD_0     // Ljava/lang/String; str   (line 360)
                    ALOAD_1     // Ljava/lang/String; sub
                    ILOAD_3     // I pos
                    INVOKEVIRTUAL java.lang.String.indexOf (Ljava/lang/String;I)I
                    DUP
                    ISTORE 4
                    ICONST_M1
                    IF_ICMPNE L2
                    ILOAD_2     // I count   (line 364)
                    IRETURN
  end public static int countOccurrencesOf(String, String)

  public static String replace(String, String, String):
                    ALOAD_0     // Ljava/lang/String; inString   (line 376)
                    INVOKESTATIC org.springframework.util.StringUtils.hasLength (Ljava/lang/String;)Z
                    IFEQ L0
                    ALOAD_1     // Ljava/lang/String; oldPattern
                    INVOKESTATIC org.springframework.util.StringUtils.hasLength (Ljava/lang/String;)Z
                    IFEQ L0
                    ALOAD_2     // Ljava/lang/String; newPattern
                    IFNONNULL L1
                L0: ALOAD_0     // Ljava/lang/String; inString   (line 377)
                    ARETURN
                L1: NEW java.lang.StringBuilder   (line 379)
                    DUP
                    INVOKESPECIAL java.lang.StringBuilder.<init> ()V
                    ASTORE_3
                    ICONST_0   (line 380)
                    ISTORE 4
                    ALOAD_0     // Ljava/lang/String; inString   (line 381)
                    ALOAD_1     // Ljava/lang/String; oldPattern
                    INVOKEVIRTUAL java.lang.String.indexOf (Ljava/lang/String;)I
                    ISTORE 5
                    ALOAD_1     // Ljava/lang/String; oldPattern   (line 383)
                    INVOKEVIRTUAL java.lang.String.length ()I
                    ISTORE 6
                    GOTO L3   (line 384)
                L2: ALOAD_3     // Ljava/lang/StringBuilder; sb   (line 385)
                    ALOAD_0     // Ljava/lang/String; inString
                    ILOAD 4     // I pos
                    ILOAD 5     // I index
                    INVOKEVIRTUAL java.lang.String.substring (II)Ljava/lang/String;
                    INVOKEVIRTUAL java.lang.StringBuilder.append (Ljava/lang/String;)Ljava/lang/StringBuilder;
                    POP
                    ALOAD_3     // Ljava/lang/StringBuilder; sb   (line 386)
                    ALOAD_2     // Ljava/lang/String; newPattern
                    INVOKEVIRTUAL java.lang.StringBuilder.append (Ljava/lang/String;)Ljava/lang/StringBuilder;
                    POP
                    ILOAD 5     // I index   (line 387)
                    ILOAD 6     // I patLen
                    IADD
                    ISTORE 4     // I pos
                    ALOAD_0     // Ljava/lang/String; inString   (line 388)
                    ALOAD_1     // Ljava/lang/String; oldPattern
                    ILOAD 4     // I pos
                    INVOKEVIRTUAL java.lang.String.indexOf (Ljava/lang/String;I)I
                    ISTORE 5     // I index
                L3: ILOAD 5     // I index   (line 384)
                    IFGE L2
                    ALOAD_3     // Ljava/lang/StringBuilder; sb   (line 390)
                    ALOAD_0     // Ljava/lang/String; inString
                    ILOAD 4     // I pos
                    INVOKEVIRTUAL java.lang.String.substring (I)Ljava/lang/String;
                    INVOKEVIRTUAL java.lang.StringBuilder.append (Ljava/lang/String;)Ljava/lang/StringBuilder;
                    POP
                    ALOAD_3     // Ljava/lang/StringBuilder; sb   (line 392)
                    INVOKEVIRTUAL java.lang.StringBuilder.toString ()Ljava/lang/String;
                    ARETURN
  end public static String replace(String, String, String)

  public static String delete(String, String):
                    ALOAD_0     // Ljava/lang/String; inString   (line 402)
                    ALOAD_1     // Ljava/lang/String; pattern
                    LDC ""
                    INVOKESTATIC org.springframework.util.StringUtils.replace (Ljava/lang/String;Ljava/lang/String;Ljava/lang/String;)Ljava/lang/String;
                    ARETURN
  end public static String delete(String, String)

  public static String deleteAny(String, String):
                    ALOAD_0     // Ljava/lang/String; inString   (line 413)
                    INVOKESTATIC org.springframework.util.StringUtils.hasLength (Ljava/lang/String;)Z
                    IFEQ L0
                    ALOAD_1     // Ljava/lang/String; charsToDelete
                    INVOKESTATIC org.springframework.util.StringUtils.hasLength (Ljava/lang/String;)Z
                    IFNE L1
                L0: ALOAD_0     // Ljava/lang/String; inString   (line 414)
                    ARETURN
                L1: NEW java.lang.StringBuilder   (line 416)
                    DUP
                    INVOKESPECIAL java.lang.StringBuilder.<init> ()V
                    ASTORE_2
                    ICONST_0   (line 417)
                    ISTORE_3
                    GOTO L4
                L2: ALOAD_0     // Ljava/lang/String; inString   (line 418)
                    ILOAD_3     // I i
                    INVOKEVIRTUAL java.lang.String.charAt (I)C
                    ISTORE 4
                    ALOAD_1     // Ljava/lang/String; charsToDelete   (line 419)
                    ILOAD 4     // C c
                    INVOKEVIRTUAL java.lang.String.indexOf (I)I
                    ICONST_M1
                    IF_ICMPNE L3
                    ALOAD_2     // Ljava/lang/StringBuilder; sb   (line 420)
                    ILOAD 4     // C c
                    INVOKEVIRTUAL java.lang.StringBuilder.append (C)Ljava/lang/StringBuilder;
                    POP
                L3: IINC_3 1     // I i   (line 417)
                L4: ILOAD_3     // I i
                    ALOAD_0     // Ljava/lang/String; inString
                    INVOKEVIRTUAL java.lang.String.length ()I
                    IF_ICMPLT L2
                    ALOAD_2     // Ljava/lang/StringBuilder; sb   (line 423)
                    INVOKEVIRTUAL java.lang.StringBuilder.toString ()Ljava/lang/String;
                    ARETURN
  end public static String deleteAny(String, String)

  public static String quote(String):
                    ALOAD_0     // Ljava/lang/String; str   (line 438)
                    IFNULL L0
                    NEW java.lang.StringBuilder
                    DUP
                    LDC "'"
                    INVOKESPECIAL java.lang.StringBuilder.<init> (Ljava/lang/String;)V
                    ALOAD_0     // Ljava/lang/String; str
                    INVOKEVIRTUAL java.lang.StringBuilder.append (Ljava/lang/String;)Ljava/lang/StringBuilder;
                    LDC "'"
                    INVOKEVIRTUAL java.lang.StringBuilder.append (Ljava/lang/String;)Ljava/lang/StringBuilder;
                    INVOKEVIRTUAL java.lang.StringBuilder.toString ()Ljava/lang/String;
                    GOTO L1
                L0: ACONST_NULL
                L1: ARETURN
  end public static String quote(String)

  public static Object quoteIfString(Object):
                    ALOAD_0     // Ljava/lang/Object; obj   (line 449)
                    INSTANCEOF java.lang.String
                    IFEQ L0
                    ALOAD_0     // Ljava/lang/Object; obj
                    CHECKCAST java.lang.String
                    INVOKESTATIC org.springframework.util.StringUtils.quote (Ljava/lang/String;)Ljava/lang/String;
                    GOTO L1
                L0: ALOAD_0     // Ljava/lang/Object; obj
                L1: ARETURN
  end public static Object quoteIfString(Object)

  public static String unqualify(String):
                    ALOAD_0     // Ljava/lang/String; qualifiedName   (line 458)
                    BIPUSH 46
                    INVOKESTATIC org.springframework.util.StringUtils.unqualify (Ljava/lang/String;C)Ljava/lang/String;
                    ARETURN
  end public static String unqualify(String)

  public static String unqualify(String, char):
                    ALOAD_0     // Ljava/lang/String; qualifiedName   (line 468)
                    ALOAD_0     // Ljava/lang/String; qualifiedName
                    ILOAD_1     // C separator
                    INVOKEVIRTUAL java.lang.String.lastIndexOf (I)I
                    ICONST_1
                    IADD
                    INVOKEVIRTUAL java.lang.String.substring (I)Ljava/lang/String;
                    ARETURN
  end public static String unqualify(String, char)

  public static String capitalize(String):
                    ALOAD_0     // Ljava/lang/String; str   (line 479)
                    ICONST_1
                    INVOKESTATIC org.springframework.util.StringUtils.changeFirstCharacterCase (Ljava/lang/String;Z)Ljava/lang/String;
                    ARETURN
  end public static String capitalize(String)

  public static String uncapitalize(String):
                    ALOAD_0     // Ljava/lang/String; str   (line 490)
                    ICONST_0
                    INVOKESTATIC org.springframework.util.StringUtils.changeFirstCharacterCase (Ljava/lang/String;Z)Ljava/lang/String;
                    ARETURN
  end public static String uncapitalize(String)

  private static String changeFirstCharacterCase(String, boolean):
                    ALOAD_0     // Ljava/lang/String; str   (line 494)
                    IFNULL L0
                    ALOAD_0     // Ljava/lang/String; str
                    INVOKEVIRTUAL java.lang.String.length ()I
                    IFNE L1
                L0: ALOAD_0     // Ljava/lang/String; str   (line 495)
                    ARETURN
                L1: NEW java.lang.StringBuilder   (line 497)
                    DUP
                    ALOAD_0     // Ljava/lang/String; str
                    INVOKEVIRTUAL java.lang.String.length ()I
                    INVOKESPECIAL java.lang.StringBuilder.<init> (I)V
                    ASTORE_2
                    ILOAD_1     // Z capitalize   (line 498)
                    IFEQ L2
                    ALOAD_2     // Ljava/lang/StringBuilder; sb   (line 499)
                    ALOAD_0     // Ljava/lang/String; str
                    ICONST_0
                    INVOKEVIRTUAL java.lang.String.charAt (I)C
                    INVOKESTATIC java.lang.Character.toUpperCase (C)C
                    INVOKEVIRTUAL java.lang.StringBuilder.append (C)Ljava/lang/StringBuilder;
                    POP
                    GOTO L3
                L2: ALOAD_2     // Ljava/lang/StringBuilder; sb   (line 502)
                    ALOAD_0     // Ljava/lang/String; str
                    ICONST_0
                    INVOKEVIRTUAL java.lang.String.charAt (I)C
                    INVOKESTATIC java.lang.Character.toLowerCase (C)C
                    INVOKEVIRTUAL java.lang.StringBuilder.append (C)Ljava/lang/StringBuilder;
                    POP
                L3: ALOAD_2     // Ljava/lang/StringBuilder; sb   (line 504)
                    ALOAD_0     // Ljava/lang/String; str
                    ICONST_1
                    INVOKEVIRTUAL java.lang.String.substring (I)Ljava/lang/String;
                    INVOKEVIRTUAL java.lang.StringBuilder.append (Ljava/lang/String;)Ljava/lang/StringBuilder;
                    POP
                    ALOAD_2     // Ljava/lang/StringBuilder; sb   (line 505)
                    INVOKEVIRTUAL java.lang.StringBuilder.toString ()Ljava/lang/String;
                    ARETURN
  end private static String changeFirstCharacterCase(String, boolean)

  public static String getFilename(String):
                    ALOAD_0     // Ljava/lang/String; path   (line 515)
                    IFNONNULL L0
                    ACONST_NULL   (line 516)
                    ARETURN
                L0: ALOAD_0     // Ljava/lang/String; path   (line 518)
                    LDC "/"
                    INVOKEVIRTUAL java.lang.String.lastIndexOf (Ljava/lang/String;)I
                    ISTORE_1
                    ILOAD_1     // I separatorIndex   (line 519)
                    ICONST_M1
                    IF_ICMPEQ L1
                    ALOAD_0     // Ljava/lang/String; path
                    ILOAD_1     // I separatorIndex
                    ICONST_1
                    IADD
                    INVOKEVIRTUAL java.lang.String.substring (I)Ljava/lang/String;
                    GOTO L2
                L1: ALOAD_0     // Ljava/lang/String; path
                L2: ARETURN
  end public static String getFilename(String)

  public static String getFilenameExtension(String):
                    ALOAD_0     // Ljava/lang/String; path   (line 529)
                    IFNONNULL L0
                    ACONST_NULL   (line 530)
                    ARETURN
                L0: ALOAD_0     // Ljava/lang/String; path   (line 532)
                    BIPUSH 46
                    INVOKEVIRTUAL java.lang.String.lastIndexOf (I)I
                    ISTORE_1
                    ILOAD_1     // I extIndex   (line 533)
                    ICONST_M1
                    IF_ICMPNE L1
                    ACONST_NULL   (line 534)
                    ARETURN
                L1: ALOAD_0     // Ljava/lang/String; path   (line 536)
                    LDC "/"
                    INVOKEVIRTUAL java.lang.String.lastIndexOf (Ljava/lang/String;)I
                    ISTORE_2
                    ILOAD_2     // I folderIndex   (line 537)
                    ILOAD_1     // I extIndex
                    IF_ICMPLE L2
                    ACONST_NULL   (line 538)
                    ARETURN
                L2: ALOAD_0     // Ljava/lang/String; path   (line 540)
                    ILOAD_1     // I extIndex
                    ICONST_1
                    IADD
                    INVOKEVIRTUAL java.lang.String.substring (I)Ljava/lang/String;
                    ARETURN
  end public static String getFilenameExtension(String)

  public static String stripFilenameExtension(String):
                    ALOAD_0     // Ljava/lang/String; path   (line 551)
                    IFNONNULL L0
                    ACONST_NULL   (line 552)
                    ARETURN
                L0: ALOAD_0     // Ljava/lang/String; path   (line 554)
                    BIPUSH 46
                    INVOKEVIRTUAL java.lang.String.lastIndexOf (I)I
                    ISTORE_1
                    ILOAD_1     // I extIndex   (line 555)
                    ICONST_M1
                    IF_ICMPNE L1
                    ALOAD_0     // Ljava/lang/String; path   (line 556)
                    ARETURN
                L1: ALOAD_0     // Ljava/lang/String; path   (line 558)
                    LDC "/"
                    INVOKEVIRTUAL java.lang.String.lastIndexOf (Ljava/lang/String;)I
                    ISTORE_2
                    ILOAD_2     // I folderIndex   (line 559)
                    ILOAD_1     // I extIndex
                    IF_ICMPLE L2
                    ALOAD_0     // Ljava/lang/String; path   (line 560)
                    ARETURN
                L2: ALOAD_0     // Ljava/lang/String; path   (line 562)
                    ICONST_0
                    ILOAD_1     // I extIndex
                    INVOKEVIRTUAL java.lang.String.substring (II)Ljava/lang/String;
                    ARETURN
  end public static String stripFilenameExtension(String)

  public static String applyRelativePath(String, String):
                    ALOAD_0     // Ljava/lang/String; path   (line 574)
                    LDC "/"
                    INVOKEVIRTUAL java.lang.String.lastIndexOf (Ljava/lang/String;)I
                    ISTORE_2
                    ILOAD_2     // I separatorIndex   (line 575)
                    ICONST_M1
                    IF_ICMPEQ L1
                    ALOAD_0     // Ljava/lang/String; path   (line 576)
                    ICONST_0
                    ILOAD_2     // I separatorIndex
                    INVOKEVIRTUAL java.lang.String.substring (II)Ljava/lang/String;
                    ASTORE_3
                    ALOAD_1     // Ljava/lang/String; relativePath   (line 577)
                    LDC "/"
                    INVOKEVIRTUAL java.lang.String.startsWith (Ljava/lang/String;)Z
                    IFNE L0
                    NEW java.lang.StringBuilder   (line 578)
                    DUP
                    ALOAD_3     // Ljava/lang/String; newPath
                    INVOKESTATIC java.lang.String.valueOf (Ljava/lang/Object;)Ljava/lang/String;
                    INVOKESPECIAL java.lang.StringBuilder.<init> (Ljava/lang/String;)V
                    LDC "/"
                    INVOKEVIRTUAL java.lang.StringBuilder.append (Ljava/lang/String;)Ljava/lang/StringBuilder;
                    INVOKEVIRTUAL java.lang.StringBuilder.toString ()Ljava/lang/String;
                    ASTORE_3     // Ljava/lang/String; newPath
                L0: NEW java.lang.StringBuilder   (line 580)
                    DUP
                    ALOAD_3     // Ljava/lang/String; newPath
                    INVOKESTATIC java.lang.String.valueOf (Ljava/lang/Object;)Ljava/lang/String;
                    INVOKESPECIAL java.lang.StringBuilder.<init> (Ljava/lang/String;)V
                    ALOAD_1     // Ljava/lang/String; relativePath
                    INVOKEVIRTUAL java.lang.StringBuilder.append (Ljava/lang/String;)Ljava/lang/StringBuilder;
                    INVOKEVIRTUAL java.lang.StringBuilder.toString ()Ljava/lang/String;
                    ARETURN
                L1: ALOAD_1     // Ljava/lang/String; relativePath   (line 583)
                    ARETURN
  end public static String applyRelativePath(String, String)

  public static String cleanPath(String):
                    ALOAD_0     // Ljava/lang/String; path   (line 596)
                    IFNONNULL L0
                    ACONST_NULL   (line 597)
                    ARETURN
                L0: ALOAD_0     // Ljava/lang/String; path   (line 599)
                    LDC "\"
                    LDC "/"
                    INVOKESTATIC org.springframework.util.StringUtils.replace (Ljava/lang/String;Ljava/lang/String;Ljava/lang/String;)Ljava/lang/String;
                    ASTORE_1
                    ALOAD_1     // Ljava/lang/String; pathToUse   (line 605)
                    LDC ":"
                    INVOKEVIRTUAL java.lang.String.indexOf (Ljava/lang/String;)I
                    ISTORE_2
                    LDC ""   (line 606)
                    ASTORE_3
                    ILOAD_2     // I prefixIndex   (line 607)
                    ICONST_M1
                    IF_ICMPEQ L1
                    ALOAD_1     // Ljava/lang/String; pathToUse   (line 608)
                    ICONST_0
                    ILOAD_2     // I prefixIndex
                    ICONST_1
                    IADD
                    INVOKEVIRTUAL java.lang.String.substring (II)Ljava/lang/String;
                    ASTORE_3     // Ljava/lang/String; prefix
                    ALOAD_1     // Ljava/lang/String; pathToUse   (line 609)
                    ILOAD_2     // I prefixIndex
                    ICONST_1
                    IADD
                    INVOKEVIRTUAL java.lang.String.substring (I)Ljava/lang/String;
                    ASTORE_1     // Ljava/lang/String; pathToUse
                L1: ALOAD_1     // Ljava/lang/String; pathToUse   (line 611)
                    LDC "/"
                    INVOKEVIRTUAL java.lang.String.startsWith (Ljava/lang/String;)Z
                    IFEQ L2
                    NEW java.lang.StringBuilder   (line 612)
                    DUP
                    ALOAD_3     // Ljava/lang/String; prefix
                    INVOKESTATIC java.lang.String.valueOf (Ljava/lang/Object;)Ljava/lang/String;
                    INVOKESPECIAL java.lang.StringBuilder.<init> (Ljava/lang/String;)V
                    LDC "/"
                    INVOKEVIRTUAL java.lang.StringBuilder.append (Ljava/lang/String;)Ljava/lang/StringBuilder;
                    INVOKEVIRTUAL java.lang.StringBuilder.toString ()Ljava/lang/String;
                    ASTORE_3     // Ljava/lang/String; prefix
                    ALOAD_1     // Ljava/lang/String; pathToUse   (line 613)
                    ICONST_1
                    INVOKEVIRTUAL java.lang.String.substring (I)Ljava/lang/String;
                    ASTORE_1     // Ljava/lang/String; pathToUse
                L2: ALOAD_1     // Ljava/lang/String; pathToUse   (line 616)
                    LDC "/"
                    INVOKESTATIC org.springframework.util.StringUtils.delimitedListToStringArray (Ljava/lang/String;Ljava/lang/String;)[Ljava/lang/String;
                    ASTORE 4
                    NEW java.util.LinkedList   (line 617)
                    DUP
                    INVOKESPECIAL java.util.LinkedList.<init> ()V
                    ASTORE 5
                    ICONST_0   (line 618)
                    ISTORE 6
                    ALOAD 4     // [Ljava/lang/String; pathArray   (line 620)
                    ARRAYLENGTH
                    ICONST_1
                    ISUB
                    ISTORE 7
                    GOTO L7
                L3: ALOAD 4     // [Ljava/lang/String; pathArray   (line 621)
                    ILOAD 7     // I i
                    AALOAD
                    ASTORE 8
                    LDC "."   (line 622)
                    ALOAD 8     // Ljava/lang/String; element
                    INVOKEVIRTUAL java.lang.String.equals (Ljava/lang/Object;)Z
                    IFNE L6
                    LDC ".."   (line 625)
                    ALOAD 8     // Ljava/lang/String; element
                    INVOKEVIRTUAL java.lang.String.equals (Ljava/lang/Object;)Z
                    IFEQ L4
                    IINC 6 1     // I tops   (line 627)
                    GOTO L6
                L4: ILOAD 6     // I tops   (line 630)
                    IFLE L5
                    IINC 6 -1     // I tops   (line 632)
                    GOTO L6
                L5: ALOAD 5     // Ljava/util/List; pathElements   (line 636)
                    ICONST_0
                    ALOAD 8     // Ljava/lang/String; element
                    INVOKEINTERFACE java.util.List.add (ILjava/lang/Object;)V
                L6: IINC 7 -1     // I i   (line 620)
                L7: ILOAD 7     // I i
                    IFGE L3
                    ICONST_0   (line 642)
                    ISTORE 7
                    GOTO L9
                L8: ALOAD 5     // Ljava/util/List; pathElements   (line 643)
                    ICONST_0
                    LDC ".."
                    INVOKEINTERFACE java.util.List.add (ILjava/lang/Object;)V
                    IINC 7 1     // I i   (line 642)
                L9: ILOAD 7     // I i
                    ILOAD 6     // I tops
                    IF_ICMPLT L8
                    NEW java.lang.StringBuilder   (line 646)
                    DUP
                    ALOAD_3     // Ljava/lang/String; prefix
                    INVOKESTATIC java.lang.String.valueOf (Ljava/lang/Object;)Ljava/lang/String;
                    INVOKESPECIAL java.lang.StringBuilder.<init> (Ljava/lang/String;)V
                    ALOAD 5     // Ljava/util/List; pathElements
                    LDC "/"
                    INVOKESTATIC org.springframework.util.StringUtils.collectionToDelimitedString (Ljava/util/Collection;Ljava/lang/String;)Ljava/lang/String;
                    INVOKEVIRTUAL java.lang.StringBuilder.append (Ljava/lang/String;)Ljava/lang/StringBuilder;
                    INVOKEVIRTUAL java.lang.StringBuilder.toString ()Ljava/lang/String;
                    ARETURN
  end public static String cleanPath(String)

  public static boolean pathEquals(String, String):
                    ALOAD_0     // Ljava/lang/String; path1   (line 656)
                    INVOKESTATIC org.springframework.util.StringUtils.cleanPath (Ljava/lang/String;)Ljava/lang/String;
                    ALOAD_1     // Ljava/lang/String; path2
                    INVOKESTATIC org.springframework.util.StringUtils.cleanPath (Ljava/lang/String;)Ljava/lang/String;
                    INVOKEVIRTUAL java.lang.String.equals (Ljava/lang/Object;)Z
                    IRETURN
  end public static boolean pathEquals(String, String)

  public static java.util.Locale parseLocaleString(String):
                    ALOAD_0     // Ljava/lang/String; localeString   (line 668)
                    LDC "_ "
                    ICONST_0
                    ICONST_0
                    INVOKESTATIC org.springframework.util.StringUtils.tokenizeToStringArray (Ljava/lang/String;Ljava/lang/String;ZZ)[Ljava/lang/String;
                    ASTORE_1
                    ALOAD_1     // [Ljava/lang/String; parts   (line 669)
                    ARRAYLENGTH
                    IFLE L0
                    ALOAD_1     // [Ljava/lang/String; parts
                    ICONST_0
                    AALOAD
                    GOTO L1
                L0: LDC ""
                L1: ASTORE_2
                    ALOAD_1     // [Ljava/lang/String; parts   (line 670)
                    ARRAYLENGTH
                    ICONST_1
                    IF_ICMPLE L2
                    ALOAD_1     // [Ljava/lang/String; parts
                    ICONST_1
                    AALOAD
                    GOTO L3
                L2: LDC ""
                L3: ASTORE_3
                    ALOAD_2     // Ljava/lang/String; language   (line 671)
                    INVOKESTATIC org.springframework.util.StringUtils.validateLocalePart (Ljava/lang/String;)V
                    ALOAD_3     // Ljava/lang/String; country   (line 672)
                    INVOKESTATIC org.springframework.util.StringUtils.validateLocalePart (Ljava/lang/String;)V
                    LDC ""   (line 673)
                    ASTORE 4
                    ALOAD_1     // [Ljava/lang/String; parts   (line 674)
                    ARRAYLENGTH
                    ICONST_2
                    IF_ICMPLT L4
                    ALOAD_0     // Ljava/lang/String; localeString   (line 677)
                    ALOAD_3     // Ljava/lang/String; country
                    INVOKEVIRTUAL java.lang.String.indexOf (Ljava/lang/String;)I
                    ALOAD_3     // Ljava/lang/String; country
                    INVOKEVIRTUAL java.lang.String.length ()I
                    IADD
                    ISTORE 5
                    ALOAD_0     // Ljava/lang/String; localeString   (line 679)
                    ILOAD 5     // I endIndexOfCountryCode
                    INVOKEVIRTUAL java.lang.String.substring (I)Ljava/lang/String;
                    INVOKESTATIC org.springframework.util.StringUtils.trimLeadingWhitespace (Ljava/lang/String;)Ljava/lang/String;
                    ASTORE 4     // Ljava/lang/String; variant
                    ALOAD 4     // Ljava/lang/String; variant   (line 680)
                    LDC_W "_"
                    INVOKEVIRTUAL java.lang.String.startsWith (Ljava/lang/String;)Z
                    IFEQ L4
                    ALOAD 4     // Ljava/lang/String; variant   (line 681)
                    BIPUSH 95
                    INVOKESTATIC org.springframework.util.StringUtils.trimLeadingCharacter (Ljava/lang/String;C)Ljava/lang/String;
                    ASTORE 4     // Ljava/lang/String; variant
                L4: ALOAD_2     // Ljava/lang/String; language   (line 684)
                    INVOKEVIRTUAL java.lang.String.length ()I
                    IFLE L5
                    NEW java.util.Locale
                    DUP
                    ALOAD_2     // Ljava/lang/String; language
                    ALOAD_3     // Ljava/lang/String; country
                    ALOAD 4     // Ljava/lang/String; variant
                    INVOKESPECIAL java.util.Locale.<init> (Ljava/lang/String;Ljava/lang/String;Ljava/lang/String;)V
                    GOTO L6
                L5: ACONST_NULL
                L6: ARETURN
  end public static java.util.Locale parseLocaleString(String)

  private static void validateLocalePart(String):
                    ICONST_0   (line 688)
                    ISTORE_1
                    GOTO L2
                L0: ALOAD_0     // Ljava/lang/String; localePart   (line 689)
                    ILOAD_1     // I i
                    INVOKEVIRTUAL java.lang.String.charAt (I)C
                    ISTORE_2
                    ILOAD_2     // C ch   (line 690)
                    BIPUSH 95
                    IF_ICMPEQ L1
                    ILOAD_2     // C ch
                    BIPUSH 32
                    IF_ICMPEQ L1
                    ILOAD_2     // C ch
                    INVOKESTATIC java.lang.Character.isLetterOrDigit (C)Z
                    IFNE L1
                    NEW java.lang.IllegalArgumentException   (line 691)
                    DUP
                    NEW java.lang.StringBuilder   (line 692)
                    DUP
                    LDC_W "Locale part \""
                    INVOKESPECIAL java.lang.StringBuilder.<init> (Ljava/lang/String;)V
                    ALOAD_0     // Ljava/lang/String; localePart
                    INVOKEVIRTUAL java.lang.StringBuilder.append (Ljava/lang/String;)Ljava/lang/StringBuilder;
                    LDC_W "\" contains invalid characters"
                    INVOKEVIRTUAL java.lang.StringBuilder.append (Ljava/lang/String;)Ljava/lang/StringBuilder;
                    INVOKEVIRTUAL java.lang.StringBuilder.toString ()Ljava/lang/String;
                    INVOKESPECIAL java.lang.IllegalArgumentException.<init> (Ljava/lang/String;)V   (line 691)
                    ATHROW
                L1: IINC_1 1     // I i   (line 688)
                L2: ILOAD_1     // I i
                    ALOAD_0     // Ljava/lang/String; localePart
                    INVOKEVIRTUAL java.lang.String.length ()I
                    IF_ICMPLT L0
                    RETURN   (line 695)
  end private static void validateLocalePart(String)

  public static String toLanguageTag(java.util.Locale):
                    NEW java.lang.StringBuilder   (line 704)
                    DUP
                    ALOAD_0     // Ljava/util/Locale; locale
                    INVOKEVIRTUAL java.util.Locale.getLanguage ()Ljava/lang/String;
                    INVOKESTATIC java.lang.String.valueOf (Ljava/lang/Object;)Ljava/lang/String;
                    INVOKESPECIAL java.lang.StringBuilder.<init> (Ljava/lang/String;)V
                    ALOAD_0     // Ljava/util/Locale; locale
                    INVOKEVIRTUAL java.util.Locale.getCountry ()Ljava/lang/String;
                    INVOKESTATIC org.springframework.util.StringUtils.hasText (Ljava/lang/String;)Z
                    IFEQ L0
                    NEW java.lang.StringBuilder
                    DUP
                    LDC_W "-"
                    INVOKESPECIAL java.lang.StringBuilder.<init> (Ljava/lang/String;)V
                    ALOAD_0     // Ljava/util/Locale; locale
                    INVOKEVIRTUAL java.util.Locale.getCountry ()Ljava/lang/String;
                    INVOKEVIRTUAL java.lang.StringBuilder.append (Ljava/lang/String;)Ljava/lang/StringBuilder;
                    INVOKEVIRTUAL java.lang.StringBuilder.toString ()Ljava/lang/String;
                    GOTO L1
                L0: LDC ""
                L1: INVOKEVIRTUAL java.lang.StringBuilder.append (Ljava/lang/String;)Ljava/lang/StringBuilder;
                    INVOKEVIRTUAL java.lang.StringBuilder.toString ()Ljava/lang/String;
                    ARETURN
  end public static String toLanguageTag(java.util.Locale)

  public static String[] addStringToArray(String[], String):
                    ALOAD_0     // [Ljava/lang/String; array   (line 720)
                    INVOKESTATIC org.springframework.util.ObjectUtils.isEmpty ([Ljava/lang/Object;)Z
                    IFEQ L0
                    ICONST_1   (line 721)
                    ANEWARRAY java.lang.String
                    DUP
                    ICONST_0
                    ALOAD_1     // Ljava/lang/String; str
                    AASTORE
                    ARETURN
                L0: ALOAD_0     // [Ljava/lang/String; array   (line 723)
                    ARRAYLENGTH
                    ICONST_1
                    IADD
                    ANEWARRAY java.lang.String
                    ASTORE_2
                    ALOAD_0     // [Ljava/lang/String; array   (line 724)
                    ICONST_0
                    ALOAD_2     // [Ljava/lang/String; newArr
                    ICONST_0
                    ALOAD_0     // [Ljava/lang/String; array
                    ARRAYLENGTH
                    INVOKESTATIC java.lang.System.arraycopy (Ljava/lang/Object;ILjava/lang/Object;II)V
                    ALOAD_2     // [Ljava/lang/String; newArr   (line 725)
                    ALOAD_0     // [Ljava/lang/String; array
                    ARRAYLENGTH
                    ALOAD_1     // Ljava/lang/String; str
                    AASTORE
                    ALOAD_2     // [Ljava/lang/String; newArr   (line 726)
                    ARETURN
  end public static String[] addStringToArray(String[], String)

  public static String[] concatenateStringArrays(String[], String[]):
                    ALOAD_0     // [Ljava/lang/String; array1   (line 738)
                    INVOKESTATIC org.springframework.util.ObjectUtils.isEmpty ([Ljava/lang/Object;)Z
                    IFEQ L0
                    ALOAD_1     // [Ljava/lang/String; array2   (line 739)
                    ARETURN
                L0: ALOAD_1     // [Ljava/lang/String; array2   (line 741)
                    INVOKESTATIC org.springframework.util.ObjectUtils.isEmpty ([Ljava/lang/Object;)Z
                    IFEQ L1
                    ALOAD_0     // [Ljava/lang/String; array1   (line 742)
                    ARETURN
                L1: ALOAD_0     // [Ljava/lang/String; array1   (line 744)
                    ARRAYLENGTH
                    ALOAD_1     // [Ljava/lang/String; array2
                    ARRAYLENGTH
                    IADD
                    ANEWARRAY java.lang.String
                    ASTORE_2
                    ALOAD_0     // [Ljava/lang/String; array1   (line 745)
                    ICONST_0
                    ALOAD_2     // [Ljava/lang/String; newArr
                    ICONST_0
                    ALOAD_0     // [Ljava/lang/String; array1
                    ARRAYLENGTH
                    INVOKESTATIC java.lang.System.arraycopy (Ljava/lang/Object;ILjava/lang/Object;II)V
                    ALOAD_1     // [Ljava/lang/String; array2   (line 746)
                    ICONST_0
                    ALOAD_2     // [Ljava/lang/String; newArr
                    ALOAD_0     // [Ljava/lang/String; array1
                    ARRAYLENGTH
                    ALOAD_1     // [Ljava/lang/String; array2
                    ARRAYLENGTH
                    INVOKESTATIC java.lang.System.arraycopy (Ljava/lang/Object;ILjava/lang/Object;II)V
                    ALOAD_2     // [Ljava/lang/String; newArr   (line 747)
                    ARETURN
  end public static String[] concatenateStringArrays(String[], String[])

  public static String[] mergeStringArrays(String[], String[]):
                    ALOAD_0     // [Ljava/lang/String; array1   (line 761)
                    INVOKESTATIC org.springframework.util.ObjectUtils.isEmpty ([Ljava/lang/Object;)Z
                    IFEQ L0
                    ALOAD_1     // [Ljava/lang/String; array2   (line 762)
                    ARETURN
                L0: ALOAD_1     // [Ljava/lang/String; array2   (line 764)
                    INVOKESTATIC org.springframework.util.ObjectUtils.isEmpty ([Ljava/lang/Object;)Z
                    IFEQ L1
                    ALOAD_0     // [Ljava/lang/String; array1   (line 765)
                    ARETURN
                L1: NEW java.util.ArrayList   (line 767)
                    DUP
                    INVOKESPECIAL java.util.ArrayList.<init> ()V
                    ASTORE_2
                    ALOAD_2     // Ljava/util/List; result   (line 768)
                    ALOAD_0     // [Ljava/lang/String; array1
                    INVOKESTATIC java.util.Arrays.asList ([Ljava/lang/Object;)Ljava/util/List;
                    CHECKCAST java.util.Collection
                    INVOKEINTERFACE java.util.List.addAll (Ljava/util/Collection;)Z
                    POP
                    ALOAD_1     // [Ljava/lang/String; array2   (line 769)
                    DUP
                    ASTORE 6
                    ARRAYLENGTH
                    ISTORE 5
                    ICONST_0
                    ISTORE 4
                    GOTO L4
                L2: ALOAD 6
                    ILOAD 4
                    AALOAD
                    ASTORE_3
                    ALOAD_2     // Ljava/util/List; result   (line 770)
                    ALOAD_3     // Ljava/lang/String; str
                    INVOKEINTERFACE java.util.List.contains (Ljava/lang/Object;)Z
                    IFNE L3
                    ALOAD_2     // Ljava/util/List; result   (line 771)
                    ALOAD_3     // Ljava/lang/String; str
                    INVOKEINTERFACE java.util.List.add (Ljava/lang/Object;)Z
                    POP
                L3: IINC 4 1   (line 769)
                L4: ILOAD 4
                    ILOAD 5
                    IF_ICMPLT L2
                    ALOAD_2     // Ljava/util/List; result   (line 774)
                    INVOKESTATIC org.springframework.util.StringUtils.toStringArray (Ljava/util/Collection;)[Ljava/lang/String;
                    ARETURN
  end public static String[] mergeStringArrays(String[], String[])

  public static String[] sortStringArray(String[]):
                    ALOAD_0     // [Ljava/lang/String; array   (line 783)
                    INVOKESTATIC org.springframework.util.ObjectUtils.isEmpty ([Ljava/lang/Object;)Z
                    IFEQ L0
                    ICONST_0   (line 784)
                    ANEWARRAY java.lang.String
                    ARETURN
                L0: ALOAD_0     // [Ljava/lang/String; array   (line 786)
                    INVOKESTATIC java.util.Arrays.sort ([Ljava/lang/Object;)V
                    ALOAD_0     // [Ljava/lang/String; array   (line 787)
                    ARETURN
  end public static String[] sortStringArray(String[])

  public static String[] toStringArray(java.util.Collection):
                    ALOAD_0     // Ljava/util/Collection; collection   (line 798)
                    IFNONNULL L0
                    ACONST_NULL   (line 799)
                    ARETURN
                L0: ALOAD_0     // Ljava/util/Collection; collection   (line 801)
                    ALOAD_0     // Ljava/util/Collection; collection
                    INVOKEINTERFACE java.util.Collection.size ()I
                    ANEWARRAY java.lang.String
                    INVOKEINTERFACE java.util.Collection.toArray ([Ljava/lang/Object;)[Ljava/lang/Object;
                    CHECKCAST [Ljava.lang.String;
                    ARETURN
  end public static String[] toStringArray(java.util.Collection)

  public static String[] toStringArray(java.util.Enumeration):
                    ALOAD_0     // Ljava/util/Enumeration; enumeration   (line 812)
                    IFNONNULL L0
                    ACONST_NULL   (line 813)
                    ARETURN
                L0: ALOAD_0     // Ljava/util/Enumeration; enumeration   (line 815)
                    INVOKESTATIC java.util.Collections.list (Ljava/util/Enumeration;)Ljava/util/ArrayList;
                    CHECKCAST java.util.List
                    ASTORE_1
                    ALOAD_1     // Ljava/util/List; list   (line 816)
                    ALOAD_1     // Ljava/util/List; list
                    INVOKEINTERFACE java.util.List.size ()I
                    ANEWARRAY java.lang.String
                    INVOKEINTERFACE java.util.List.toArray ([Ljava/lang/Object;)[Ljava/lang/Object;
                    CHECKCAST [Ljava.lang.String;
                    ARETURN
  end public static String[] toStringArray(java.util.Enumeration)

  public static String[] trimArrayElements(String[]):
                    ALOAD_0     // [Ljava/lang/String; array   (line 826)
                    INVOKESTATIC org.springframework.util.ObjectUtils.isEmpty ([Ljava/lang/Object;)Z
                    IFEQ L0
                    ICONST_0   (line 827)
                    ANEWARRAY java.lang.String
                    ARETURN
                L0: ALOAD_0     // [Ljava/lang/String; array   (line 829)
                    ARRAYLENGTH
                    ANEWARRAY java.lang.String
                    ASTORE_1
                    ICONST_0   (line 830)
                    ISTORE_2
                    GOTO L4
                L1: ALOAD_0     // [Ljava/lang/String; array   (line 831)
                    ILOAD_2     // I i
                    AALOAD
                    ASTORE_3
                    ALOAD_1     // [Ljava/lang/String; result   (line 832)
                    ILOAD_2     // I i
                    ALOAD_3     // Ljava/lang/String; element
                    IFNULL L2
                    ALOAD_3     // Ljava/lang/String; element
                    INVOKEVIRTUAL java.lang.String.trim ()Ljava/lang/String;
                    GOTO L3
                L2: ACONST_NULL
                L3: AASTORE
                    IINC_2 1     // I i   (line 830)
                L4: ILOAD_2     // I i
                    ALOAD_0     // [Ljava/lang/String; array
                    ARRAYLENGTH
                    IF_ICMPLT L1
                    ALOAD_1     // [Ljava/lang/String; result   (line 834)
                    ARETURN
  end public static String[] trimArrayElements(String[])

  public static String[] removeDuplicateStrings(String[]):
                    ALOAD_0     // [Ljava/lang/String; array   (line 844)
                    INVOKESTATIC org.springframework.util.ObjectUtils.isEmpty ([Ljava/lang/Object;)Z
                    IFEQ L0
                    ALOAD_0     // [Ljava/lang/String; array   (line 845)
                    ARETURN
                L0: NEW java.util.TreeSet   (line 847)
                    DUP
                    INVOKESPECIAL java.util.TreeSet.<init> ()V
                    ASTORE_1
                    ALOAD_0     // [Ljava/lang/String; array   (line 848)
                    DUP
                    ASTORE 5
                    ARRAYLENGTH
                    ISTORE 4
                    ICONST_0
                    ISTORE_3
                    GOTO L2
                L1: ALOAD 5
                    ILOAD_3
                    AALOAD
                    ASTORE_2
                    ALOAD_1     // Ljava/util/Set; set   (line 849)
                    ALOAD_2     // Ljava/lang/String; element
                    INVOKEINTERFACE java.util.Set.add (Ljava/lang/Object;)Z
                    POP
                    IINC_3 1   (line 848)
                L2: ILOAD_3
                    ILOAD 4
                    IF_ICMPLT L1
                    ALOAD_1     // Ljava/util/Set; set   (line 851)
                    INVOKESTATIC org.springframework.util.StringUtils.toStringArray (Ljava/util/Collection;)[Ljava/lang/String;
                    ARETURN
  end public static String[] removeDuplicateStrings(String[])

  public static String[] split(String, String):
                    ALOAD_0     // Ljava/lang/String; toSplit   (line 864)
                    INVOKESTATIC org.springframework.util.StringUtils.hasLength (Ljava/lang/String;)Z
                    IFEQ L0
                    ALOAD_1     // Ljava/lang/String; delimiter
                    INVOKESTATIC org.springframework.util.StringUtils.hasLength (Ljava/lang/String;)Z
                    IFNE L1
                L0: ACONST_NULL   (line 865)
                    ARETURN
                L1: ALOAD_0     // Ljava/lang/String; toSplit   (line 867)
                    ALOAD_1     // Ljava/lang/String; delimiter
                    INVOKEVIRTUAL java.lang.String.indexOf (Ljava/lang/String;)I
                    ISTORE_2
                    ILOAD_2     // I offset   (line 868)
                    IFGE L2
                    ACONST_NULL   (line 869)
                    ARETURN
                L2: ALOAD_0     // Ljava/lang/String; toSplit   (line 871)
                    ICONST_0
                    ILOAD_2     // I offset
                    INVOKEVIRTUAL java.lang.String.substring (II)Ljava/lang/String;
                    ASTORE_3
                    ALOAD_0     // Ljava/lang/String; toSplit   (line 872)
                    ILOAD_2     // I offset
                    ALOAD_1     // Ljava/lang/String; delimiter
                    INVOKEVIRTUAL java.lang.String.length ()I
                    IADD
                    INVOKEVIRTUAL java.lang.String.substring (I)Ljava/lang/String;
                    ASTORE 4
                    ICONST_2   (line 873)
                    ANEWARRAY java.lang.String
                    DUP
                    ICONST_0
                    ALOAD_3     // Ljava/lang/String; beforeDelimiter
                    AASTORE
                    DUP
                    ICONST_1
                    ALOAD 4     // Ljava/lang/String; afterDelimiter
                    AASTORE
                    ARETURN
  end public static String[] split(String, String)

  public static java.util.Properties splitArrayElementsIntoProperties(String[], String):
                    ALOAD_0     // [Ljava/lang/String; array   (line 888)
                    ALOAD_1     // Ljava/lang/String; delimiter
                    ACONST_NULL
                    INVOKESTATIC org.springframework.util.StringUtils.splitArrayElementsIntoProperties ([Ljava/lang/String;Ljava/lang/String;Ljava/lang/String;)Ljava/util/Properties;
                    ARETURN
  end public static java.util.Properties splitArrayElementsIntoProperties(String[], String)

  public static java.util.Properties splitArrayElementsIntoProperties(String[], String, String):
                    ALOAD_0     // [Ljava/lang/String; array   (line 908)
                    INVOKESTATIC org.springframework.util.ObjectUtils.isEmpty ([Ljava/lang/Object;)Z
                    IFEQ L0
                    ACONST_NULL   (line 909)
                    ARETURN
                L0: NEW java.util.Properties   (line 911)
                    DUP
                    INVOKESPECIAL java.util.Properties.<init> ()V
                    ASTORE_3
                    ALOAD_0     // [Ljava/lang/String; array   (line 912)
                    DUP
                    ASTORE 7
                    ARRAYLENGTH
                    ISTORE 6
                    ICONST_0
                    ISTORE 5
                    GOTO L5
                L1: ALOAD 7
                    ILOAD 5
                    AALOAD
                    ASTORE 4
                    ALOAD_2     // Ljava/lang/String; charsToDelete   (line 913)
                    IFNULL L2
                    ALOAD 4     // Ljava/lang/String; element   (line 914)
                    ALOAD_2     // Ljava/lang/String; charsToDelete
                    INVOKESTATIC org.springframework.util.StringUtils.deleteAny (Ljava/lang/String;Ljava/lang/String;)Ljava/lang/String;
                    ASTORE 4     // Ljava/lang/String; element
                L2: ALOAD 4     // Ljava/lang/String; element   (line 916)
                    ALOAD_1     // Ljava/lang/String; delimiter
                    INVOKESTATIC org.springframework.util.StringUtils.split (Ljava/lang/String;Ljava/lang/String;)[Ljava/lang/String;
                    ASTORE 8
                    ALOAD 8     // [Ljava/lang/String; splittedElement   (line 917)
                    IFNONNULL L3
                    GOTO L4   (line 918)
                L3: ALOAD_3     // Ljava/util/Properties; result   (line 920)
                    ALOAD 8     // [Ljava/lang/String; splittedElement
                    ICONST_0
                    AALOAD
                    INVOKEVIRTUAL java.lang.String.trim ()Ljava/lang/String;
                    ALOAD 8     // [Ljava/lang/String; splittedElement
                    ICONST_1
                    AALOAD
                    INVOKEVIRTUAL java.lang.String.trim ()Ljava/lang/String;
                    INVOKEVIRTUAL java.util.Properties.setProperty (Ljava/lang/String;Ljava/lang/String;)Ljava/lang/Object;
                    POP
                L4: IINC 5 1   (line 912)
                L5: ILOAD 5
                    ILOAD 6
                    IF_ICMPLT L1
                    ALOAD_3     // Ljava/util/Properties; result   (line 922)
                    ARETURN
  end public static java.util.Properties splitArrayElementsIntoProperties(String[], String, String)

  public static String[] tokenizeToStringArray(String, String):
                    ALOAD_0     // Ljava/lang/String; str   (line 941)
                    ALOAD_1     // Ljava/lang/String; delimiters
                    ICONST_1
                    ICONST_1
                    INVOKESTATIC org.springframework.util.StringUtils.tokenizeToStringArray (Ljava/lang/String;Ljava/lang/String;ZZ)[Ljava/lang/String;
                    ARETURN
  end public static String[] tokenizeToStringArray(String, String)

  public static String[] tokenizeToStringArray(String, String, boolean, boolean):
                    ALOAD_0     // Ljava/lang/String; str   (line 966)
                    IFNONNULL L0
                    ACONST_NULL   (line 967)
                    ARETURN
                L0: NEW java.util.StringTokenizer   (line 969)
                    DUP
                    ALOAD_0     // Ljava/lang/String; str
                    ALOAD_1     // Ljava/lang/String; delimiters
                    INVOKESPECIAL java.util.StringTokenizer.<init> (Ljava/lang/String;Ljava/lang/String;)V
                    ASTORE 4
                    NEW java.util.ArrayList   (line 970)
                    DUP
                    INVOKESPECIAL java.util.ArrayList.<init> ()V
                    ASTORE 5
                    GOTO L4   (line 971)
                L1: ALOAD 4     // Ljava/util/StringTokenizer; st   (line 972)
                    INVOKEVIRTUAL java.util.StringTokenizer.nextToken ()Ljava/lang/String;
                    ASTORE 6
                    ILOAD_2     // Z trimTokens   (line 973)
                    IFEQ L2
                    ALOAD 6     // Ljava/lang/String; token   (line 974)
                    INVOKEVIRTUAL java.lang.String.trim ()Ljava/lang/String;
                    ASTORE 6     // Ljava/lang/String; token
                L2: ILOAD_3     // Z ignoreEmptyTokens   (line 976)
                    IFEQ L3
                    ALOAD 6     // Ljava/lang/String; token
                    INVOKEVIRTUAL java.lang.String.length ()I
                    IFLE L4
                L3: ALOAD 5     // Ljava/util/List; tokens   (line 977)
                    ALOAD 6     // Ljava/lang/String; token
                    INVOKEINTERFACE java.util.List.add (Ljava/lang/Object;)Z
                    POP
                L4: ALOAD 4     // Ljava/util/StringTokenizer; st   (line 971)
                    INVOKEVIRTUAL java.util.StringTokenizer.hasMoreTokens ()Z
                    IFNE L1
                    ALOAD 5     // Ljava/util/List; tokens   (line 980)
                    INVOKESTATIC org.springframework.util.StringUtils.toStringArray (Ljava/util/Collection;)[Ljava/lang/String;
                    ARETURN
  end public static String[] tokenizeToStringArray(String, String, boolean, boolean)

  public static String[] delimitedListToStringArray(String, String):
                    ALOAD_0     // Ljava/lang/String; str   (line 995)
                    ALOAD_1     // Ljava/lang/String; delimiter
                    ACONST_NULL
                    INVOKESTATIC org.springframework.util.StringUtils.delimitedListToStringArray (Ljava/lang/String;Ljava/lang/String;Ljava/lang/String;)[Ljava/lang/String;
                    ARETURN
  end public static String[] delimitedListToStringArray(String, String)

  public static String[] delimitedListToStringArray(String, String, String):
                    ALOAD_0     // Ljava/lang/String; str   (line 1012)
                    IFNONNULL L0
                    ICONST_0   (line 1013)
                    ANEWARRAY java.lang.String
                    ARETURN
                L0: ALOAD_1     // Ljava/lang/String; delimiter   (line 1015)
                    IFNONNULL L1
                    ICONST_1   (line 1016)
                    ANEWARRAY java.lang.String
                    DUP
                    ICONST_0
                    ALOAD_0     // Ljava/lang/String; str
                    AASTORE
                    ARETURN
                L1: NEW java.util.ArrayList   (line 1018)
                    DUP
                    INVOKESPECIAL java.util.ArrayList.<init> ()V
                    ASTORE_3
                    LDC ""   (line 1019)
                    ALOAD_1     // Ljava/lang/String; delimiter
                    INVOKEVIRTUAL java.lang.String.equals (Ljava/lang/Object;)Z
                    IFEQ L4
                    ICONST_0   (line 1020)
                    ISTORE 4
                    GOTO L3
                L2: ALOAD_3     // Ljava/util/List; result   (line 1021)
                    ALOAD_0     // Ljava/lang/String; str
                    ILOAD 4     // I i
                    ILOAD 4     // I i
                    ICONST_1
                    IADD
                    INVOKEVIRTUAL java.lang.String.substring (II)Ljava/lang/String;
                    ALOAD_2     // Ljava/lang/String; charsToDelete
                    INVOKESTATIC org.springframework.util.StringUtils.deleteAny (Ljava/lang/String;Ljava/lang/String;)Ljava/lang/String;
                    INVOKEINTERFACE java.util.List.add (Ljava/lang/Object;)Z
                    POP
                    IINC 4 1     // I i   (line 1020)
                L3: ILOAD 4     // I i
                    ALOAD_0     // Ljava/lang/String; str
                    INVOKEVIRTUAL java.lang.String.length ()I
                    IF_ICMPLT L2
                    GOTO L7
                L4: ICONST_0   (line 1025)
                    ISTORE 4
                    GOTO L6   (line 1027)
                L5: ALOAD_3     // Ljava/util/List; result   (line 1028)
                    ALOAD_0     // Ljava/lang/String; str
                    ILOAD 4     // I pos
                    ILOAD 5     // I delPos
                    INVOKEVIRTUAL java.lang.String.substring (II)Ljava/lang/String;
                    ALOAD_2     // Ljava/lang/String; charsToDelete
                    INVOKESTATIC org.springframework.util.StringUtils.deleteAny (Ljava/lang/String;Ljava/lang/String;)Ljava/lang/String;
                    INVOKEINTERFACE java.util.List.add (Ljava/lang/Object;)Z
                    POP
                    ILOAD 5     // I delPos   (line 1029)
                    ALOAD_1     // Ljava/lang/String; delimiter
                    INVOKEVIRTUAL java.lang.String.length ()I
                    IADD
                    ISTORE 4     // I pos
                L6: ALOAD_0     // Ljava/lang/String; str   (line 1027)
                    ALOAD_1     // Ljava/lang/String; delimiter
                    ILOAD 4     // I pos
                    INVOKEVIRTUAL java.lang.String.indexOf (Ljava/lang/String;I)I
                    DUP
                    ISTORE 5
                    ICONST_M1
                    IF_ICMPNE L5
                    ALOAD_0     // Ljava/lang/String; str   (line 1031)
                    INVOKEVIRTUAL java.lang.String.length ()I
                    IFLE L7
                    ILOAD 4     // I pos
                    ALOAD_0     // Ljava/lang/String; str
                    INVOKEVIRTUAL java.lang.String.length ()I
                    IF_ICMPGT L7
                    ALOAD_3     // Ljava/util/List; result   (line 1033)
                    ALOAD_0     // Ljava/lang/String; str
                    ILOAD 4     // I pos
                    INVOKEVIRTUAL java.lang.String.substring (I)Ljava/lang/String;
                    ALOAD_2     // Ljava/lang/String; charsToDelete
                    INVOKESTATIC org.springframework.util.StringUtils.deleteAny (Ljava/lang/String;Ljava/lang/String;)Ljava/lang/String;
                    INVOKEINTERFACE java.util.List.add (Ljava/lang/Object;)Z
                    POP
                L7: ALOAD_3     // Ljava/util/List; result   (line 1036)
                    INVOKESTATIC org.springframework.util.StringUtils.toStringArray (Ljava/util/Collection;)[Ljava/lang/String;
                    ARETURN
  end public static String[] delimitedListToStringArray(String, String, String)

  public static String[] commaDelimitedListToStringArray(String):
                    ALOAD_0     // Ljava/lang/String; str   (line 1045)
                    LDC_W ","
                    INVOKESTATIC org.springframework.util.StringUtils.delimitedListToStringArray (Ljava/lang/String;Ljava/lang/String;)[Ljava/lang/String;
                    ARETURN
  end public static String[] commaDelimitedListToStringArray(String)

  public static java.util.Set commaDelimitedListToSet(String):
                    NEW java.util.TreeSet   (line 1055)
                    DUP
                    INVOKESPECIAL java.util.TreeSet.<init> ()V
                    ASTORE_1
                    ALOAD_0     // Ljava/lang/String; str   (line 1056)
                    INVOKESTATIC org.springframework.util.StringUtils.commaDelimitedListToStringArray (Ljava/lang/String;)[Ljava/lang/String;
                    ASTORE_2
                    ALOAD_2     // [Ljava/lang/String; tokens   (line 1057)
                    DUP
                    ASTORE 6
                    ARRAYLENGTH
                    ISTORE 5
                    ICONST_0
                    ISTORE 4
                    GOTO L1
                L0: ALOAD 6
                    ILOAD 4
                    AALOAD
                    ASTORE_3
                    ALOAD_1     // Ljava/util/Set; set   (line 1058)
                    ALOAD_3     // Ljava/lang/String; token
                    INVOKEINTERFACE java.util.Set.add (Ljava/lang/Object;)Z
                    POP
                    IINC 4 1   (line 1057)
                L1: ILOAD 4
                    ILOAD 5
                    IF_ICMPLT L0
                    ALOAD_1     // Ljava/util/Set; set   (line 1060)
                    ARETURN
  end public static java.util.Set commaDelimitedListToSet(String)

  public static String collectionToDelimitedString(java.util.Collection, String, String, String):
                    ALOAD_0     // Ljava/util/Collection; coll   (line 1073)
                    INVOKESTATIC org.springframework.util.CollectionUtils.isEmpty (Ljava/util/Collection;)Z
                    IFEQ L0
                    LDC ""   (line 1074)
                    ARETURN
                L0: NEW java.lang.StringBuilder   (line 1076)
                    DUP
                    INVOKESPECIAL java.lang.StringBuilder.<init> ()V
                    ASTORE 4
                    ALOAD_0     // Ljava/util/Collection; coll   (line 1077)
                    INVOKEINTERFACE java.util.Collection.iterator ()Ljava/util/Iterator;
                    ASTORE 5
                    GOTO L2   (line 1078)
                L1: ALOAD 4     // Ljava/lang/StringBuilder; sb   (line 1079)
                    ALOAD_2     // Ljava/lang/String; prefix
                    INVOKEVIRTUAL java.lang.StringBuilder.append (Ljava/lang/String;)Ljava/lang/StringBuilder;
                    ALOAD 5     // Ljava/util/Iterator; it
                    INVOKEINTERFACE java.util.Iterator.next ()Ljava/lang/Object;
                    INVOKEVIRTUAL java.lang.StringBuilder.append (Ljava/lang/Object;)Ljava/lang/StringBuilder;
                    ALOAD_3     // Ljava/lang/String; suffix
                    INVOKEVIRTUAL java.lang.StringBuilder.append (Ljava/lang/String;)Ljava/lang/StringBuilder;
                    POP
                    ALOAD 5     // Ljava/util/Iterator; it   (line 1080)
                    INVOKEINTERFACE java.util.Iterator.hasNext ()Z
                    IFEQ L2
                    ALOAD 4     // Ljava/lang/StringBuilder; sb   (line 1081)
                    ALOAD_1     // Ljava/lang/String; delim
                    INVOKEVIRTUAL java.lang.StringBuilder.append (Ljava/lang/String;)Ljava/lang/StringBuilder;
                    POP
                L2: ALOAD 5     // Ljava/util/Iterator; it   (line 1078)
                    INVOKEINTERFACE java.util.Iterator.hasNext ()Z
                    IFNE L1
                    ALOAD 4     // Ljava/lang/StringBuilder; sb   (line 1084)
                    INVOKEVIRTUAL java.lang.StringBuilder.toString ()Ljava/lang/String;
                    ARETURN
  end public static String collectionToDelimitedString(java.util.Collection, String, String, String)

  public static String collectionToDelimitedString(java.util.Collection, String):
                    ALOAD_0     // Ljava/util/Collection; coll   (line 1095)
                    ALOAD_1     // Ljava/lang/String; delim
                    LDC ""
                    LDC ""
                    INVOKESTATIC org.springframework.util.StringUtils.collectionToDelimitedString (Ljava/util/Collection;Ljava/lang/String;Ljava/lang/String;Ljava/lang/String;)Ljava/lang/String;
                    ARETURN
  end public static String collectionToDelimitedString(java.util.Collection, String)

  public static String collectionToCommaDelimitedString(java.util.Collection):
                    ALOAD_0     // Ljava/util/Collection; coll   (line 1105)
                    LDC_W ","
                    INVOKESTATIC org.springframework.util.StringUtils.collectionToDelimitedString (Ljava/util/Collection;Ljava/lang/String;)Ljava/lang/String;
                    ARETURN
  end public static String collectionToCommaDelimitedString(java.util.Collection)

  public static String arrayToDelimitedString(Object[], String):
                    ALOAD_0     // [Ljava/lang/Object; arr   (line 1116)
                    INVOKESTATIC org.springframework.util.ObjectUtils.isEmpty ([Ljava/lang/Object;)Z
                    IFEQ L0
                    LDC ""   (line 1117)
                    ARETURN
                L0: ALOAD_0     // [Ljava/lang/Object; arr   (line 1119)
                    ARRAYLENGTH
                    ICONST_1
                    IF_ICMPNE L1
                    ALOAD_0     // [Ljava/lang/Object; arr   (line 1120)
                    ICONST_0
                    AALOAD
                    INVOKESTATIC org.springframework.util.ObjectUtils.nullSafeToString (Ljava/lang/Object;)Ljava/lang/String;
                    ARETURN
                L1: NEW java.lang.StringBuilder   (line 1122)
                    DUP
                    INVOKESPECIAL java.lang.StringBuilder.<init> ()V
                    ASTORE_2
                    ICONST_0   (line 1123)
                    ISTORE_3
                    GOTO L4
                L2: ILOAD_3     // I i   (line 1124)
                    IFLE L3
                    ALOAD_2     // Ljava/lang/StringBuilder; sb   (line 1125)
                    ALOAD_1     // Ljava/lang/String; delim
                    INVOKEVIRTUAL java.lang.StringBuilder.append (Ljava/lang/String;)Ljava/lang/StringBuilder;
                    POP
                L3: ALOAD_2     // Ljava/lang/StringBuilder; sb   (line 1127)
                    ALOAD_0     // [Ljava/lang/Object; arr
                    ILOAD_3     // I i
                    AALOAD
                    INVOKEVIRTUAL java.lang.StringBuilder.append (Ljava/lang/Object;)Ljava/lang/StringBuilder;
                    POP
                    IINC_3 1     // I i   (line 1123)
                L4: ILOAD_3     // I i
                    ALOAD_0     // [Ljava/lang/Object; arr
                    ARRAYLENGTH
                    IF_ICMPLT L2
                    ALOAD_2     // Ljava/lang/StringBuilder; sb   (line 1129)
                    INVOKEVIRTUAL java.lang.StringBuilder.toString ()Ljava/lang/String;
                    ARETURN
  end public static String arrayToDelimitedString(Object[], String)

  public static String arrayToCommaDelimitedString(Object[]):
                    ALOAD_0     // [Ljava/lang/Object; arr   (line 1139)
                    LDC_W ","
                    INVOKESTATIC org.springframework.util.StringUtils.arrayToDelimitedString ([Ljava/lang/Object;Ljava/lang/String;)Ljava/lang/String;
                    ARETURN
  end public static String arrayToCommaDelimitedString(Object[])

end public abstract class org.springframework.util.StringUtils
 -- (ClassFormatException) File: 'java.lang.CharSequence': Invalid byte tag in constant pool: 15
File: 'java.lang.CharSequence': Invalid byte tag in constant pool: 15
org.aspectj.apache.bcel.classfile.ClassFormatException: File: 'java.lang.CharSequence': Invalid byte tag in constant pool: 15
	at org.aspectj.apache.bcel.classfile.ClassParser.readConstantPool(ClassParser.java:192)
	at org.aspectj.apache.bcel.classfile.ClassParser.parse(ClassParser.java:131)
	at org.aspectj.apache.bcel.util.ClassLoaderRepository.loadClass(ClassLoaderRepository.java:292)
	at org.aspectj.weaver.bcel.BcelWorld.lookupJavaClass(BcelWorld.java:224)
	at org.aspectj.weaver.bcel.BcelWorld.resolveDelegate(BcelWorld.java:205)
	at org.aspectj.weaver.ltw.LTWWorld.resolveDelegate(LTWWorld.java:107)
	at org.aspectj.weaver.World.resolveToReferenceType(World.java:363)
	at org.aspectj.weaver.World.resolve(World.java:258)
	at org.aspectj.weaver.World.resolve(World.java:180)
	at org.aspectj.weaver.UnresolvedType.resolve(UnresolvedType.java:615)
	at org.aspectj.weaver.ResolvedMemberImpl.resolve(ResolvedMemberImpl.java:533)
	at org.aspectj.weaver.JoinPointSignatureIterator.addSignaturesUpToFirstDefiningMember(JoinPointSignatureIterator.java:109)
	at org.aspectj.weaver.JoinPointSignatureIterator.<init>(JoinPointSignatureIterator.java:51)
	at org.aspectj.weaver.MemberImpl.getJoinPointSignatures(MemberImpl.java:537)
	at org.aspectj.weaver.patterns.SignaturePattern.matches(SignaturePattern.java:297)
	at org.aspectj.weaver.patterns.KindedPointcut.matchInternal(KindedPointcut.java:106)
	at org.aspectj.weaver.patterns.Pointcut.match(Pointcut.java:146)
	at org.aspectj.weaver.patterns.AndPointcut.matchInternal(AndPointcut.java:52)
	at org.aspectj.weaver.patterns.Pointcut.match(Pointcut.java:146)
	at org.aspectj.weaver.patterns.AndPointcut.matchInternal(AndPointcut.java:52)
	at org.aspectj.weaver.patterns.Pointcut.match(Pointcut.java:146)
	at org.aspectj.weaver.patterns.OrPointcut.matchInternal(OrPointcut.java:53)
	at org.aspectj.weaver.patterns.Pointcut.match(Pointcut.java:146)
	at org.aspectj.weaver.patterns.OrPointcut.matchInternal(OrPointcut.java:51)
	at org.aspectj.weaver.patterns.Pointcut.match(Pointcut.java:146)
	at org.aspectj.weaver.patterns.OrPointcut.matchInternal(OrPointcut.java:51)
	at org.aspectj.weaver.patterns.Pointcut.match(Pointcut.java:146)
	at org.aspectj.weaver.patterns.OrPointcut.matchInternal(OrPointcut.java:51)
	at org.aspectj.weaver.patterns.Pointcut.match(Pointcut.java:146)
	at org.aspectj.weaver.ShadowMunger.match(ShadowMunger.java:70)
	at org.aspectj.weaver.Advice.match(Advice.java:106)
	at org.aspectj.weaver.bcel.BcelAdvice.match(BcelAdvice.java:140)
	at org.aspectj.weaver.bcel.BcelClassWeaver.match(BcelClassWeaver.java:2980)
	at org.aspectj.weaver.bcel.BcelClassWeaver.match(BcelClassWeaver.java:2489)
	at org.aspectj.weaver.bcel.BcelClassWeaver.weave(BcelClassWeaver.java:486)
	at org.aspectj.weaver.bcel.BcelClassWeaver.weave(BcelClassWeaver.java:98)
	at org.aspectj.weaver.bcel.BcelWeaver.weave(BcelWeaver.java:1733)
	at org.aspectj.weaver.bcel.BcelWeaver.weaveWithoutDump(BcelWeaver.java:1694)
	at org.aspectj.weaver.bcel.BcelWeaver.weaveAndNotify(BcelWeaver.java:1464)
	at org.aspectj.weaver.bcel.BcelWeaver.weave(BcelWeaver.java:1273)
	at org.aspectj.weaver.tools.WeavingAdaptor.getWovenBytes(WeavingAdaptor.java:394)
	at org.aspectj.weaver.tools.WeavingAdaptor.weaveClass(WeavingAdaptor.java:281)
	at org.aspectj.weaver.loadtime.Aj.preProcess(Aj.java:95)
	at org.aspectj.weaver.loadtime.ClassPreProcessorAgentAdapter.transform(ClassPreProcessorAgentAdapter.java:52)
	at sun.instrument.TransformerManager.transform(TransformerManager.java:188)
	at sun.instrument.InstrumentationImpl.transform(InstrumentationImpl.java:428)
	at java.lang.ClassLoader.defineClass1(Native Method)
	at java.lang.ClassLoader.defineClass(ClassLoader.java:760)
	at java.security.SecureClassLoader.defineClass(SecureClassLoader.java:142)
	at java.net.URLClassLoader.defineClass(URLClassLoader.java:467)
	at java.net.URLClassLoader.access$100(URLClassLoader.java:73)
	at java.net.URLClassLoader$1.run(URLClassLoader.java:368)
	at java.net.URLClassLoader$1.run(URLClassLoader.java:362)
	at java.security.AccessController.doPrivileged(Native Method)
	at java.net.URLClassLoader.findClass(URLClassLoader.java:361)
	at java.lang.ClassLoader.loadClass(ClassLoader.java:424)
	at sun.misc.Launcher$AppClassLoader.loadClass(Launcher.java:331)
	at java.lang.ClassLoader.loadClass(ClassLoader.java:357)
	at org.springframework.util.Assert.hasText(Assert.java:161)
	at org.springframework.core.env.PropertySource.<init>(PropertySource.java:68)
	at org.springframework.core.env.EnumerablePropertySource.<init>(EnumerablePropertySource.java:53)
	at org.springframework.core.env.MapPropertySource.<init>(MapPropertySource.java:31)
	at org.springframework.core.env.StandardEnvironment.customizePropertySources(StandardEnvironment.java:78)
	at org.springframework.core.env.AbstractEnvironment.<init>(AbstractEnvironment.java:117)
	at org.springframework.core.env.StandardEnvironment.<init>(StandardEnvironment.java:54)
	at org.springframework.context.support.AbstractApplicationContext.createEnvironment(AbstractApplicationContext.java:432)
	at org.springframework.context.support.AbstractApplicationContext.<init>(AbstractApplicationContext.java:227)
	at org.springframework.context.support.AbstractRefreshableApplicationContext.<init>(AbstractRefreshableApplicationContext.java:90)
	at org.springframework.context.support.AbstractRefreshableConfigApplicationContext.<init>(AbstractRefreshableConfigApplicationContext.java:59)
	at org.springframework.context.support.AbstractXmlApplicationContext.<init>(AbstractXmlApplicationContext.java:61)
	at org.springframework.context.support.ClassPathXmlApplicationContext.<init>(ClassPathXmlApplicationContext.java:136)
	at org.springframework.context.support.ClassPathXmlApplicationContext.<init>(ClassPathXmlApplicationContext.java:83)
	at com.curso.spring.springioc0007.Main.init(Main.java:29)
	at com.curso.spring.springioc0007.Main.main(Main.java:24)

org.aspectj.bridge.AbortException: trouble in: 
public abstract class org.springframework.util.StringUtils extends java.lang.Object:
  private static final String FOLDER_SEPARATOR = "/"
  private static final String WINDOWS_FOLDER_SEPARATOR = "\\"
  private static final String TOP_PATH = ".."
  private static final String CURRENT_PATH = "."
  private static final char EXTENSION_SEPARATOR = 46
  public void <init>():
                    ALOAD_0     // Lorg/springframework/util/StringUtils; this   (line 55)
                    INVOKESPECIAL java.lang.Object.<init> ()V
    constructor-execution(void org.springframework.util.StringUtils.<init>())
    |               RETURN
    constructor-execution(void org.springframework.util.StringUtils.<init>())
  end public void <init>()

  public static boolean hasLength(CharSequence):
                    ALOAD_0     // Ljava/lang/CharSequence; str   (line 86)
                    IFNULL L0
                    ALOAD_0     // Ljava/lang/CharSequence; str
                    INVOKEINTERFACE java.lang.CharSequence.length ()I
                    IFLE L0
                    ICONST_1
                    IRETURN
                L0: ICONST_0
                    IRETURN
  end public static boolean hasLength(CharSequence)

  public static boolean hasLength(String):
                    ALOAD_0     // Ljava/lang/String; str   (line 97)
                    INVOKESTATIC org.springframework.util.StringUtils.hasLength (Ljava/lang/CharSequence;)Z
                    IRETURN
  end public static boolean hasLength(String)

  public static boolean hasText(CharSequence):
                    ALOAD_0     // Ljava/lang/CharSequence; str   (line 117)
                    INVOKESTATIC org.springframework.util.StringUtils.hasLength (Ljava/lang/CharSequence;)Z
                    IFNE L0
                    ICONST_0   (line 118)
                    IRETURN
                L0: ALOAD_0     // Ljava/lang/CharSequence; str   (line 120)
                    INVOKEINTERFACE java.lang.CharSequence.length ()I
                    ISTORE_1
                    ICONST_0   (line 121)
                    ISTORE_2
                    GOTO L3
                L1: ALOAD_0     // Ljava/lang/CharSequence; str   (line 122)
                    ILOAD_2     // I i
                    INVOKEINTERFACE java.lang.CharSequence.charAt (I)C
                    INVOKESTATIC java.lang.Character.isWhitespace (C)Z
                    IFNE L2
                    ICONST_1   (line 123)
                    IRETURN
                L2: IINC_2 1     // I i   (line 121)
                L3: ILOAD_2     // I i
                    ILOAD_1     // I strLen
                    IF_ICMPLT L1
                    ICONST_0   (line 126)
                    IRETURN
  end public static boolean hasText(CharSequence)

  public static boolean hasText(String):
                    ALOAD_0     // Ljava/lang/String; str   (line 139)
                    INVOKESTATIC org.springframework.util.StringUtils.hasText (Ljava/lang/CharSequence;)Z
                    IRETURN
  end public static boolean hasText(String)

  public static boolean containsWhitespace(CharSequence):
                    ALOAD_0     // Ljava/lang/CharSequence; str   (line 150)
                    INVOKESTATIC org.springframework.util.StringUtils.hasLength (Ljava/lang/CharSequence;)Z
                    IFNE L0
                    ICONST_0   (line 151)
                    IRETURN
                L0: ALOAD_0     // Ljava/lang/CharSequence; str   (line 153)
                    INVOKEINTERFACE java.lang.CharSequence.length ()I
                    ISTORE_1
                    ICONST_0   (line 154)
                    ISTORE_2
                    GOTO L3
                L1: ALOAD_0     // Ljava/lang/CharSequence; str   (line 155)
                    ILOAD_2     // I i
                    INVOKEINTERFACE java.lang.CharSequence.charAt (I)C
                    INVOKESTATIC java.lang.Character.isWhitespace (C)Z
                    IFEQ L2
                    ICONST_1   (line 156)
                    IRETURN
                L2: IINC_2 1     // I i   (line 154)
                L3: ILOAD_2     // I i
                    ILOAD_1     // I strLen
                    IF_ICMPLT L1
                    ICONST_0   (line 159)
                    IRETURN
  end public static boolean containsWhitespace(CharSequence)

  public static boolean containsWhitespace(String):
                    ALOAD_0     // Ljava/lang/String; str   (line 170)
                    INVOKESTATIC org.springframework.util.StringUtils.containsWhitespace (Ljava/lang/CharSequence;)Z
                    IRETURN
  end public static boolean containsWhitespace(String)

  public static String trimWhitespace(String):
                    ALOAD_0     // Ljava/lang/String; str   (line 180)
                    INVOKESTATIC org.springframework.util.StringUtils.hasLength (Ljava/lang/String;)Z
                    IFNE L0
                    ALOAD_0     // Ljava/lang/String; str   (line 181)
                    ARETURN
                L0: NEW java.lang.StringBuilder   (line 183)
                    DUP
                    ALOAD_0     // Ljava/lang/String; str
                    INVOKESPECIAL java.lang.StringBuilder.<init> (Ljava/lang/String;)V
                    ASTORE_1
                    GOTO L2   (line 184)
                L1: ALOAD_1     // Ljava/lang/StringBuilder; sb   (line 185)
                    ICONST_0
                    INVOKEVIRTUAL java.lang.StringBuilder.deleteCharAt (I)Ljava/lang/StringBuilder;
                    POP
                L2: ALOAD_1     // Ljava/lang/StringBuilder; sb   (line 184)
                    INVOKEVIRTUAL java.lang.StringBuilder.length ()I
                    IFLE L4
                    ALOAD_1     // Ljava/lang/StringBuilder; sb
                    ICONST_0
                    INVOKEVIRTUAL java.lang.StringBuilder.charAt (I)C
                    INVOKESTATIC java.lang.Character.isWhitespace (C)Z
                    IFNE L1
                    GOTO L4   (line 187)
                L3: ALOAD_1     // Ljava/lang/StringBuilder; sb   (line 188)
                    ALOAD_1     // Ljava/lang/StringBuilder; sb
                    INVOKEVIRTUAL java.lang.StringBuilder.length ()I
                    ICONST_1
                    ISUB
                    INVOKEVIRTUAL java.lang.StringBuilder.deleteCharAt (I)Ljava/lang/StringBuilder;
                    POP
                L4: ALOAD_1     // Ljava/lang/StringBuilder; sb   (line 187)
                    INVOKEVIRTUAL java.lang.StringBuilder.length ()I
                    IFLE L5
                    ALOAD_1     // Ljava/lang/StringBuilder; sb
                    ALOAD_1     // Ljava/lang/StringBuilder; sb
                    INVOKEVIRTUAL java.lang.StringBuilder.length ()I
                    ICONST_1
                    ISUB
                    INVOKEVIRTUAL java.lang.StringBuilder.charAt (I)C
                    INVOKESTATIC java.lang.Character.isWhitespace (C)Z
                    IFNE L3
                L5: ALOAD_1     // Ljava/lang/StringBuilder; sb   (line 190)
                    INVOKEVIRTUAL java.lang.StringBuilder.toString ()Ljava/lang/String;
                    ARETURN
  end public static String trimWhitespace(String)

  public static String trimAllWhitespace(String):
                    ALOAD_0     // Ljava/lang/String; str   (line 201)
                    INVOKESTATIC org.springframework.util.StringUtils.hasLength (Ljava/lang/String;)Z
                    IFNE L0
                    ALOAD_0     // Ljava/lang/String; str   (line 202)
                    ARETURN
                L0: NEW java.lang.StringBuilder   (line 204)
                    DUP
                    ALOAD_0     // Ljava/lang/String; str
                    INVOKESPECIAL java.lang.StringBuilder.<init> (Ljava/lang/String;)V
                    ASTORE_1
                    ICONST_0   (line 205)
                    ISTORE_2
                    GOTO L3   (line 206)
                L1: ALOAD_1     // Ljava/lang/StringBuilder; sb   (line 207)
                    ILOAD_2     // I index
                    INVOKEVIRTUAL java.lang.StringBuilder.charAt (I)C
                    INVOKESTATIC java.lang.Character.isWhitespace (C)Z
                    IFEQ L2
                    ALOAD_1     // Ljava/lang/StringBuilder; sb   (line 208)
                    ILOAD_2     // I index
                    INVOKEVIRTUAL java.lang.StringBuilder.deleteCharAt (I)Ljava/lang/StringBuilder;
                    POP
                    GOTO L3
                L2: IINC_2 1     // I index   (line 211)
                L3: ALOAD_1     // Ljava/lang/StringBuilder; sb   (line 206)
                    INVOKEVIRTUAL java.lang.StringBuilder.length ()I
                    ILOAD_2     // I index
                    IF_ICMPGT L1
                    ALOAD_1     // Ljava/lang/StringBuilder; sb   (line 214)
                    INVOKEVIRTUAL java.lang.StringBuilder.toString ()Ljava/lang/String;
                    ARETURN
  end public static String trimAllWhitespace(String)

  public static String trimLeadingWhitespace(String):
                    ALOAD_0     // Ljava/lang/String; str   (line 224)
                    INVOKESTATIC org.springframework.util.StringUtils.hasLength (Ljava/lang/String;)Z
                    IFNE L0
                    ALOAD_0     // Ljava/lang/String; str   (line 225)
                    ARETURN
                L0: NEW java.lang.StringBuilder   (line 227)
                    DUP
                    ALOAD_0     // Ljava/lang/String; str
                    INVOKESPECIAL java.lang.StringBuilder.<init> (Ljava/lang/String;)V
                    ASTORE_1
                    GOTO L2   (line 228)
                L1: ALOAD_1     // Ljava/lang/StringBuilder; sb   (line 229)
                    ICONST_0
                    INVOKEVIRTUAL java.lang.StringBuilder.deleteCharAt (I)Ljava/lang/StringBuilder;
                    POP
                L2: ALOAD_1     // Ljava/lang/StringBuilder; sb   (line 228)
                    INVOKEVIRTUAL java.lang.StringBuilder.length ()I
                    IFLE L3
                    ALOAD_1     // Ljava/lang/StringBuilder; sb
                    ICONST_0
                    INVOKEVIRTUAL java.lang.StringBuilder.charAt (I)C
                    INVOKESTATIC java.lang.Character.isWhitespace (C)Z
                    IFNE L1
                L3: ALOAD_1     // Ljava/lang/StringBuilder; sb   (line 231)
                    INVOKEVIRTUAL java.lang.StringBuilder.toString ()Ljava/lang/String;
                    ARETURN
  end public static String trimLeadingWhitespace(String)

  public static String trimTrailingWhitespace(String):
                    ALOAD_0     // Ljava/lang/String; str   (line 241)
                    INVOKESTATIC org.springframework.util.StringUtils.hasLength (Ljava/lang/String;)Z
                    IFNE L0
                    ALOAD_0     // Ljava/lang/String; str   (line 242)
                    ARETURN
                L0: NEW java.lang.StringBuilder   (line 244)
                    DUP
                    ALOAD_0     // Ljava/lang/String; str
                    INVOKESPECIAL java.lang.StringBuilder.<init> (Ljava/lang/String;)V
                    ASTORE_1
                    GOTO L2   (line 245)
                L1: ALOAD_1     // Ljava/lang/StringBuilder; sb   (line 246)
                    ALOAD_1     // Ljava/lang/StringBuilder; sb
                    INVOKEVIRTUAL java.lang.StringBuilder.length ()I
                    ICONST_1
                    ISUB
                    INVOKEVIRTUAL java.lang.StringBuilder.deleteCharAt (I)Ljava/lang/StringBuilder;
                    POP
                L2: ALOAD_1     // Ljava/lang/StringBuilder; sb   (line 245)
                    INVOKEVIRTUAL java.lang.StringBuilder.length ()I
                    IFLE L3
                    ALOAD_1     // Ljava/lang/StringBuilder; sb
                    ALOAD_1     // Ljava/lang/StringBuilder; sb
                    INVOKEVIRTUAL java.lang.StringBuilder.length ()I
                    ICONST_1
                    ISUB
                    INVOKEVIRTUAL java.lang.StringBuilder.charAt (I)C
                    INVOKESTATIC java.lang.Character.isWhitespace (C)Z
                    IFNE L1
                L3: ALOAD_1     // Ljava/lang/StringBuilder; sb   (line 248)
                    INVOKEVIRTUAL java.lang.StringBuilder.toString ()Ljava/lang/String;
                    ARETURN
  end public static String trimTrailingWhitespace(String)

  public static String trimLeadingCharacter(String, char):
                    ALOAD_0     // Ljava/lang/String; str   (line 258)
                    INVOKESTATIC org.springframework.util.StringUtils.hasLength (Ljava/lang/String;)Z
                    IFNE L0
                    ALOAD_0     // Ljava/lang/String; str   (line 259)
                    ARETURN
                L0: NEW java.lang.StringBuilder   (line 261)
                    DUP
                    ALOAD_0     // Ljava/lang/String; str
                    INVOKESPECIAL java.lang.StringBuilder.<init> (Ljava/lang/String;)V
                    ASTORE_2
                    GOTO L2   (line 262)
                L1: ALOAD_2     // Ljava/lang/StringBuilder; sb   (line 263)
                    ICONST_0
                    INVOKEVIRTUAL java.lang.StringBuilder.deleteCharAt (I)Ljava/lang/StringBuilder;
                    POP
                L2: ALOAD_2     // Ljava/lang/StringBuilder; sb   (line 262)
                    INVOKEVIRTUAL java.lang.StringBuilder.length ()I
                    IFLE L3
                    ALOAD_2     // Ljava/lang/StringBuilder; sb
                    ICONST_0
                    INVOKEVIRTUAL java.lang.StringBuilder.charAt (I)C
                    ILOAD_1     // C leadingCharacter
                    IF_ICMPEQ L1
                L3: ALOAD_2     // Ljava/lang/StringBuilder; sb   (line 265)
                    INVOKEVIRTUAL java.lang.StringBuilder.toString ()Ljava/lang/String;
                    ARETURN
  end public static String trimLeadingCharacter(String, char)

  public static String trimTrailingCharacter(String, char):
                    ALOAD_0     // Ljava/lang/String; str   (line 275)
                    INVOKESTATIC org.springframework.util.StringUtils.hasLength (Ljava/lang/String;)Z
                    IFNE L0
                    ALOAD_0     // Ljava/lang/String; str   (line 276)
                    ARETURN
                L0: NEW java.lang.StringBuilder   (line 278)
                    DUP
                    ALOAD_0     // Ljava/lang/String; str
                    INVOKESPECIAL java.lang.StringBuilder.<init> (Ljava/lang/String;)V
                    ASTORE_2
                    GOTO L2   (line 279)
                L1: ALOAD_2     // Ljava/lang/StringBuilder; sb   (line 280)
                    ALOAD_2     // Ljava/lang/StringBuilder; sb
                    INVOKEVIRTUAL java.lang.StringBuilder.length ()I
                    ICONST_1
                    ISUB
                    INVOKEVIRTUAL java.lang.StringBuilder.deleteCharAt (I)Ljava/lang/StringBuilder;
                    POP
                L2: ALOAD_2     // Ljava/lang/StringBuilder; sb   (line 279)
                    INVOKEVIRTUAL java.lang.StringBuilder.length ()I
                    IFLE L3
                    ALOAD_2     // Ljava/lang/StringBuilder; sb
                    ALOAD_2     // Ljava/lang/StringBuilder; sb
                    INVOKEVIRTUAL java.lang.StringBuilder.length ()I
                    ICONST_1
                    ISUB
                    INVOKEVIRTUAL java.lang.StringBuilder.charAt (I)C
                    ILOAD_1     // C trailingCharacter
                    IF_ICMPEQ L1
                L3: ALOAD_2     // Ljava/lang/StringBuilder; sb   (line 282)
                    INVOKEVIRTUAL java.lang.StringBuilder.toString ()Ljava/lang/String;
                    ARETURN
  end public static String trimTrailingCharacter(String, char)

  public static boolean startsWithIgnoreCase(String, String):
                    ALOAD_0     // Ljava/lang/String; str   (line 294)
                    IFNULL L0
                    ALOAD_1     // Ljava/lang/String; prefix
                    IFNONNULL L1
                L0: ICONST_0   (line 295)
                    IRETURN
                L1: ALOAD_0     // Ljava/lang/String; str   (line 297)
                    ALOAD_1     // Ljava/lang/String; prefix
                    INVOKEVIRTUAL java.lang.String.startsWith (Ljava/lang/String;)Z
                    IFEQ L2
                    ICONST_1   (line 298)
                    IRETURN
                L2: ALOAD_0     // Ljava/lang/String; str   (line 300)
                    INVOKEVIRTUAL java.lang.String.length ()I
                    ALOAD_1     // Ljava/lang/String; prefix
                    INVOKEVIRTUAL java.lang.String.length ()I
                    IF_ICMPGE L3
                    ICONST_0   (line 301)
                    IRETURN
                L3: ALOAD_0     // Ljava/lang/String; str   (line 303)
                    ICONST_0
                    ALOAD_1     // Ljava/lang/String; prefix
                    INVOKEVIRTUAL java.lang.String.length ()I
                    INVOKEVIRTUAL java.lang.String.substring (II)Ljava/lang/String;
                    INVOKEVIRTUAL java.lang.String.toLowerCase ()Ljava/lang/String;
                    ASTORE_2
                    ALOAD_1     // Ljava/lang/String; prefix   (line 304)
                    INVOKEVIRTUAL java.lang.String.toLowerCase ()Ljava/lang/String;
                    ASTORE_3
                    ALOAD_2     // Ljava/lang/String; lcStr   (line 305)
                    ALOAD_3     // Ljava/lang/String; lcPrefix
                    INVOKEVIRTUAL java.lang.String.equals (Ljava/lang/Object;)Z
                    IRETURN
  end public static boolean startsWithIgnoreCase(String, String)

  public static boolean endsWithIgnoreCase(String, String):
                    ALOAD_0     // Ljava/lang/String; str   (line 316)
                    IFNULL L0
                    ALOAD_1     // Ljava/lang/String; suffix
                    IFNONNULL L1
                L0: ICONST_0   (line 317)
                    IRETURN
                L1: ALOAD_0     // Ljava/lang/String; str   (line 319)
                    ALOAD_1     // Ljava/lang/String; suffix
                    INVOKEVIRTUAL java.lang.String.endsWith (Ljava/lang/String;)Z
                    IFEQ L2
                    ICONST_1   (line 320)
                    IRETURN
                L2: ALOAD_0     // Ljava/lang/String; str   (line 322)
                    INVOKEVIRTUAL java.lang.String.length ()I
                    ALOAD_1     // Ljava/lang/String; suffix
                    INVOKEVIRTUAL java.lang.String.length ()I
                    IF_ICMPGE L3
                    ICONST_0   (line 323)
                    IRETURN
                L3: ALOAD_0     // Ljava/lang/String; str   (line 326)
                    ALOAD_0     // Ljava/lang/String; str
                    INVOKEVIRTUAL java.lang.String.length ()I
                    ALOAD_1     // Ljava/lang/String; suffix
                    INVOKEVIRTUAL java.lang.String.length ()I
                    ISUB
                    INVOKEVIRTUAL java.lang.String.substring (I)Ljava/lang/String;
                    INVOKEVIRTUAL java.lang.String.toLowerCase ()Ljava/lang/String;
                    ASTORE_2
                    ALOAD_1     // Ljava/lang/String; suffix   (line 327)
                    INVOKEVIRTUAL java.lang.String.toLowerCase ()Ljava/lang/String;
                    ASTORE_3
                    ALOAD_2     // Ljava/lang/String; lcStr   (line 328)
                    ALOAD_3     // Ljava/lang/String; lcSuffix
                    INVOKEVIRTUAL java.lang.String.equals (Ljava/lang/Object;)Z
                    IRETURN
  end public static boolean endsWithIgnoreCase(String, String)

  public static boolean substringMatch(CharSequence, int, CharSequence):
                    ICONST_0   (line 339)
                    ISTORE_3
                    GOTO L3
                L0: ILOAD_1     // I index   (line 340)
                    ILOAD_3     // I j
                    IADD
                    ISTORE 4
                    ILOAD 4     // I i   (line 341)
                    ALOAD_0     // Ljava/lang/CharSequence; str
                    INVOKEINTERFACE java.lang.CharSequence.length ()I
                    IF_ICMPGE L1
                    ALOAD_0     // Ljava/lang/CharSequence; str
                    ILOAD 4     // I i
                    INVOKEINTERFACE java.lang.CharSequence.charAt (I)C
                    ALOAD_2     // Ljava/lang/CharSequence; substring
                    ILOAD_3     // I j
                    INVOKEINTERFACE java.lang.CharSequence.charAt (I)C
                    IF_ICMPEQ L2
                L1: ICONST_0   (line 342)
                    IRETURN
                L2: IINC_3 1     // I j   (line 339)
                L3: ILOAD_3     // I j
                    ALOAD_2     // Ljava/lang/CharSequence; substring
                    INVOKEINTERFACE java.lang.CharSequence.length ()I
                    IF_ICMPLT L0
                    ICONST_1   (line 345)
                    IRETURN
  end public static boolean substringMatch(CharSequence, int, CharSequence)

  public static int countOccurrencesOf(String, String):
                    ALOAD_0     // Ljava/lang/String; str   (line 354)
                    IFNULL L0
                    ALOAD_1     // Ljava/lang/String; sub
                    IFNULL L0
                    ALOAD_0     // Ljava/lang/String; str
                    INVOKEVIRTUAL java.lang.String.length ()I
                    IFEQ L0
                    ALOAD_1     // Ljava/lang/String; sub
                    INVOKEVIRTUAL java.lang.String.length ()I
                    IFNE L1
                L0: ICONST_0   (line 355)
                    IRETURN
                L1: ICONST_0   (line 357)
                    ISTORE_2
                    ICONST_0   (line 358)
                    ISTORE_3
                    GOTO L3   (line 360)
                L2: IINC_2 1     // I count   (line 361)
                    ILOAD 4     // I idx   (line 362)
                    ALOAD_1     // Ljava/lang/String; sub
                    INVOKEVIRTUAL java.lang.String.length ()I
                    IADD
                    ISTORE_3     // I pos
                L3: ALOAD_0     // Ljava/lang/String; str   (line 360)
                    ALOAD_1     // Ljava/lang/String; sub
                    ILOAD_3     // I pos
                    INVOKEVIRTUAL java.lang.String.indexOf (Ljava/lang/String;I)I
                    DUP
                    ISTORE 4
                    ICONST_M1
                    IF_ICMPNE L2
                    ILOAD_2     // I count   (line 364)
                    IRETURN
  end public static int countOccurrencesOf(String, String)

  public static String replace(String, String, String):
                    ALOAD_0     // Ljava/lang/String; inString   (line 376)
                    INVOKESTATIC org.springframework.util.StringUtils.hasLength (Ljava/lang/String;)Z
                    IFEQ L0
                    ALOAD_1     // Ljava/lang/String; oldPattern
                    INVOKESTATIC org.springframework.util.StringUtils.hasLength (Ljava/lang/String;)Z
                    IFEQ L0
                    ALOAD_2     // Ljava/lang/String; newPattern
                    IFNONNULL L1
                L0: ALOAD_0     // Ljava/lang/String; inString   (line 377)
                    ARETURN
                L1: NEW java.lang.StringBuilder   (line 379)
                    DUP
                    INVOKESPECIAL java.lang.StringBuilder.<init> ()V
                    ASTORE_3
                    ICONST_0   (line 380)
                    ISTORE 4
                    ALOAD_0     // Ljava/lang/String; inString   (line 381)
                    ALOAD_1     // Ljava/lang/String; oldPattern
                    INVOKEVIRTUAL java.lang.String.indexOf (Ljava/lang/String;)I
                    ISTORE 5
                    ALOAD_1     // Ljava/lang/String; oldPattern   (line 383)
                    INVOKEVIRTUAL java.lang.String.length ()I
                    ISTORE 6
                    GOTO L3   (line 384)
                L2: ALOAD_3     // Ljava/lang/StringBuilder; sb   (line 385)
                    ALOAD_0     // Ljava/lang/String; inString
                    ILOAD 4     // I pos
                    ILOAD 5     // I index
                    INVOKEVIRTUAL java.lang.String.substring (II)Ljava/lang/String;
                    INVOKEVIRTUAL java.lang.StringBuilder.append (Ljava/lang/String;)Ljava/lang/StringBuilder;
                    POP
                    ALOAD_3     // Ljava/lang/StringBuilder; sb   (line 386)
                    ALOAD_2     // Ljava/lang/String; newPattern
                    INVOKEVIRTUAL java.lang.StringBuilder.append (Ljava/lang/String;)Ljava/lang/StringBuilder;
                    POP
                    ILOAD 5     // I index   (line 387)
                    ILOAD 6     // I patLen
                    IADD
                    ISTORE 4     // I pos
                    ALOAD_0     // Ljava/lang/String; inString   (line 388)
                    ALOAD_1     // Ljava/lang/String; oldPattern
                    ILOAD 4     // I pos
                    INVOKEVIRTUAL java.lang.String.indexOf (Ljava/lang/String;I)I
                    ISTORE 5     // I index
                L3: ILOAD 5     // I index   (line 384)
                    IFGE L2
                    ALOAD_3     // Ljava/lang/StringBuilder; sb   (line 390)
                    ALOAD_0     // Ljava/lang/String; inString
                    ILOAD 4     // I pos
                    INVOKEVIRTUAL java.lang.String.substring (I)Ljava/lang/String;
                    INVOKEVIRTUAL java.lang.StringBuilder.append (Ljava/lang/String;)Ljava/lang/StringBuilder;
                    POP
                    ALOAD_3     // Ljava/lang/StringBuilder; sb   (line 392)
                    INVOKEVIRTUAL java.lang.StringBuilder.toString ()Ljava/lang/String;
                    ARETURN
  end public static String replace(String, String, String)

  public static String delete(String, String):
                    ALOAD_0     // Ljava/lang/String; inString   (line 402)
                    ALOAD_1     // Ljava/lang/String; pattern
                    LDC ""
                    INVOKESTATIC org.springframework.util.StringUtils.replace (Ljava/lang/String;Ljava/lang/String;Ljava/lang/String;)Ljava/lang/String;
                    ARETURN
  end public static String delete(String, String)

  public static String deleteAny(String, String):
                    ALOAD_0     // Ljava/lang/String; inString   (line 413)
                    INVOKESTATIC org.springframework.util.StringUtils.hasLength (Ljava/lang/String;)Z
                    IFEQ L0
                    ALOAD_1     // Ljava/lang/String; charsToDelete
                    INVOKESTATIC org.springframework.util.StringUtils.hasLength (Ljava/lang/String;)Z
                    IFNE L1
                L0: ALOAD_0     // Ljava/lang/String; inString   (line 414)
                    ARETURN
                L1: NEW java.lang.StringBuilder   (line 416)
                    DUP
                    INVOKESPECIAL java.lang.StringBuilder.<init> ()V
                    ASTORE_2
                    ICONST_0   (line 417)
                    ISTORE_3
                    GOTO L4
                L2: ALOAD_0     // Ljava/lang/String; inString   (line 418)
                    ILOAD_3     // I i
                    INVOKEVIRTUAL java.lang.String.charAt (I)C
                    ISTORE 4
                    ALOAD_1     // Ljava/lang/String; charsToDelete   (line 419)
                    ILOAD 4     // C c
                    INVOKEVIRTUAL java.lang.String.indexOf (I)I
                    ICONST_M1
                    IF_ICMPNE L3
                    ALOAD_2     // Ljava/lang/StringBuilder; sb   (line 420)
                    ILOAD 4     // C c
                    INVOKEVIRTUAL java.lang.StringBuilder.append (C)Ljava/lang/StringBuilder;
                    POP
                L3: IINC_3 1     // I i   (line 417)
                L4: ILOAD_3     // I i
                    ALOAD_0     // Ljava/lang/String; inString
                    INVOKEVIRTUAL java.lang.String.length ()I
                    IF_ICMPLT L2
                    ALOAD_2     // Ljava/lang/StringBuilder; sb   (line 423)
                    INVOKEVIRTUAL java.lang.StringBuilder.toString ()Ljava/lang/String;
                    ARETURN
  end public static String deleteAny(String, String)

  public static String quote(String):
                    ALOAD_0     // Ljava/lang/String; str   (line 438)
                    IFNULL L0
                    NEW java.lang.StringBuilder
                    DUP
                    LDC "'"
                    INVOKESPECIAL java.lang.StringBuilder.<init> (Ljava/lang/String;)V
                    ALOAD_0     // Ljava/lang/String; str
                    INVOKEVIRTUAL java.lang.StringBuilder.append (Ljava/lang/String;)Ljava/lang/StringBuilder;
                    LDC "'"
                    INVOKEVIRTUAL java.lang.StringBuilder.append (Ljava/lang/String;)Ljava/lang/StringBuilder;
                    INVOKEVIRTUAL java.lang.StringBuilder.toString ()Ljava/lang/String;
                    GOTO L1
                L0: ACONST_NULL
                L1: ARETURN
  end public static String quote(String)

  public static Object quoteIfString(Object):
                    ALOAD_0     // Ljava/lang/Object; obj   (line 449)
                    INSTANCEOF java.lang.String
                    IFEQ L0
                    ALOAD_0     // Ljava/lang/Object; obj
                    CHECKCAST java.lang.String
                    INVOKESTATIC org.springframework.util.StringUtils.quote (Ljava/lang/String;)Ljava/lang/String;
                    GOTO L1
                L0: ALOAD_0     // Ljava/lang/Object; obj
                L1: ARETURN
  end public static Object quoteIfString(Object)

  public static String unqualify(String):
                    ALOAD_0     // Ljava/lang/String; qualifiedName   (line 458)
                    BIPUSH 46
                    INVOKESTATIC org.springframework.util.StringUtils.unqualify (Ljava/lang/String;C)Ljava/lang/String;
                    ARETURN
  end public static String unqualify(String)

  public static String unqualify(String, char):
                    ALOAD_0     // Ljava/lang/String; qualifiedName   (line 468)
                    ALOAD_0     // Ljava/lang/String; qualifiedName
                    ILOAD_1     // C separator
                    INVOKEVIRTUAL java.lang.String.lastIndexOf (I)I
                    ICONST_1
                    IADD
                    INVOKEVIRTUAL java.lang.String.substring (I)Ljava/lang/String;
                    ARETURN
  end public static String unqualify(String, char)

  public static String capitalize(String):
                    ALOAD_0     // Ljava/lang/String; str   (line 479)
                    ICONST_1
                    INVOKESTATIC org.springframework.util.StringUtils.changeFirstCharacterCase (Ljava/lang/String;Z)Ljava/lang/String;
                    ARETURN
  end public static String capitalize(String)

  public static String uncapitalize(String):
                    ALOAD_0     // Ljava/lang/String; str   (line 490)
                    ICONST_0
                    INVOKESTATIC org.springframework.util.StringUtils.changeFirstCharacterCase (Ljava/lang/String;Z)Ljava/lang/String;
                    ARETURN
  end public static String uncapitalize(String)

  private static String changeFirstCharacterCase(String, boolean):
                    ALOAD_0     // Ljava/lang/String; str   (line 494)
                    IFNULL L0
                    ALOAD_0     // Ljava/lang/String; str
                    INVOKEVIRTUAL java.lang.String.length ()I
                    IFNE L1
                L0: ALOAD_0     // Ljava/lang/String; str   (line 495)
                    ARETURN
                L1: NEW java.lang.StringBuilder   (line 497)
                    DUP
                    ALOAD_0     // Ljava/lang/String; str
                    INVOKEVIRTUAL java.lang.String.length ()I
                    INVOKESPECIAL java.lang.StringBuilder.<init> (I)V
                    ASTORE_2
                    ILOAD_1     // Z capitalize   (line 498)
                    IFEQ L2
                    ALOAD_2     // Ljava/lang/StringBuilder; sb   (line 499)
                    ALOAD_0     // Ljava/lang/String; str
                    ICONST_0
                    INVOKEVIRTUAL java.lang.String.charAt (I)C
                    INVOKESTATIC java.lang.Character.toUpperCase (C)C
                    INVOKEVIRTUAL java.lang.StringBuilder.append (C)Ljava/lang/StringBuilder;
                    POP
                    GOTO L3
                L2: ALOAD_2     // Ljava/lang/StringBuilder; sb   (line 502)
                    ALOAD_0     // Ljava/lang/String; str
                    ICONST_0
                    INVOKEVIRTUAL java.lang.String.charAt (I)C
                    INVOKESTATIC java.lang.Character.toLowerCase (C)C
                    INVOKEVIRTUAL java.lang.StringBuilder.append (C)Ljava/lang/StringBuilder;
                    POP
                L3: ALOAD_2     // Ljava/lang/StringBuilder; sb   (line 504)
                    ALOAD_0     // Ljava/lang/String; str
                    ICONST_1
                    INVOKEVIRTUAL java.lang.String.substring (I)Ljava/lang/String;
                    INVOKEVIRTUAL java.lang.StringBuilder.append (Ljava/lang/String;)Ljava/lang/StringBuilder;
                    POP
                    ALOAD_2     // Ljava/lang/StringBuilder; sb   (line 505)
                    INVOKEVIRTUAL java.lang.StringBuilder.toString ()Ljava/lang/String;
                    ARETURN
  end private static String changeFirstCharacterCase(String, boolean)

  public static String getFilename(String):
                    ALOAD_0     // Ljava/lang/String; path   (line 515)
                    IFNONNULL L0
                    ACONST_NULL   (line 516)
                    ARETURN
                L0: ALOAD_0     // Ljava/lang/String; path   (line 518)
                    LDC "/"
                    INVOKEVIRTUAL java.lang.String.lastIndexOf (Ljava/lang/String;)I
                    ISTORE_1
                    ILOAD_1     // I separatorIndex   (line 519)
                    ICONST_M1
                    IF_ICMPEQ L1
                    ALOAD_0     // Ljava/lang/String; path
                    ILOAD_1     // I separatorIndex
                    ICONST_1
                    IADD
                    INVOKEVIRTUAL java.lang.String.substring (I)Ljava/lang/String;
                    GOTO L2
                L1: ALOAD_0     // Ljava/lang/String; path
                L2: ARETURN
  end public static String getFilename(String)

  public static String getFilenameExtension(String):
                    ALOAD_0     // Ljava/lang/String; path   (line 529)
                    IFNONNULL L0
                    ACONST_NULL   (line 530)
                    ARETURN
                L0: ALOAD_0     // Ljava/lang/String; path   (line 532)
                    BIPUSH 46
                    INVOKEVIRTUAL java.lang.String.lastIndexOf (I)I
                    ISTORE_1
                    ILOAD_1     // I extIndex   (line 533)
                    ICONST_M1
                    IF_ICMPNE L1
                    ACONST_NULL   (line 534)
                    ARETURN
                L1: ALOAD_0     // Ljava/lang/String; path   (line 536)
                    LDC "/"
                    INVOKEVIRTUAL java.lang.String.lastIndexOf (Ljava/lang/String;)I
                    ISTORE_2
                    ILOAD_2     // I folderIndex   (line 537)
                    ILOAD_1     // I extIndex
                    IF_ICMPLE L2
                    ACONST_NULL   (line 538)
                    ARETURN
                L2: ALOAD_0     // Ljava/lang/String; path   (line 540)
                    ILOAD_1     // I extIndex
                    ICONST_1
                    IADD
                    INVOKEVIRTUAL java.lang.String.substring (I)Ljava/lang/String;
                    ARETURN
  end public static String getFilenameExtension(String)

  public static String stripFilenameExtension(String):
                    ALOAD_0     // Ljava/lang/String; path   (line 551)
                    IFNONNULL L0
                    ACONST_NULL   (line 552)
                    ARETURN
                L0: ALOAD_0     // Ljava/lang/String; path   (line 554)
                    BIPUSH 46
                    INVOKEVIRTUAL java.lang.String.lastIndexOf (I)I
                    ISTORE_1
                    ILOAD_1     // I extIndex   (line 555)
                    ICONST_M1
                    IF_ICMPNE L1
                    ALOAD_0     // Ljava/lang/String; path   (line 556)
                    ARETURN
                L1: ALOAD_0     // Ljava/lang/String; path   (line 558)
                    LDC "/"
                    INVOKEVIRTUAL java.lang.String.lastIndexOf (Ljava/lang/String;)I
                    ISTORE_2
                    ILOAD_2     // I folderIndex   (line 559)
                    ILOAD_1     // I extIndex
                    IF_ICMPLE L2
                    ALOAD_0     // Ljava/lang/String; path   (line 560)
                    ARETURN
                L2: ALOAD_0     // Ljava/lang/String; path   (line 562)
                    ICONST_0
                    ILOAD_1     // I extIndex
                    INVOKEVIRTUAL java.lang.String.substring (II)Ljava/lang/String;
                    ARETURN
  end public static String stripFilenameExtension(String)

  public static String applyRelativePath(String, String):
                    ALOAD_0     // Ljava/lang/String; path   (line 574)
                    LDC "/"
                    INVOKEVIRTUAL java.lang.String.lastIndexOf (Ljava/lang/String;)I
                    ISTORE_2
                    ILOAD_2     // I separatorIndex   (line 575)
                    ICONST_M1
                    IF_ICMPEQ L1
                    ALOAD_0     // Ljava/lang/String; path   (line 576)
                    ICONST_0
                    ILOAD_2     // I separatorIndex
                    INVOKEVIRTUAL java.lang.String.substring (II)Ljava/lang/String;
                    ASTORE_3
                    ALOAD_1     // Ljava/lang/String; relativePath   (line 577)
                    LDC "/"
                    INVOKEVIRTUAL java.lang.String.startsWith (Ljava/lang/String;)Z
                    IFNE L0
                    NEW java.lang.StringBuilder   (line 578)
                    DUP
                    ALOAD_3     // Ljava/lang/String; newPath
                    INVOKESTATIC java.lang.String.valueOf (Ljava/lang/Object;)Ljava/lang/String;
                    INVOKESPECIAL java.lang.StringBuilder.<init> (Ljava/lang/String;)V
                    LDC "/"
                    INVOKEVIRTUAL java.lang.StringBuilder.append (Ljava/lang/String;)Ljava/lang/StringBuilder;
                    INVOKEVIRTUAL java.lang.StringBuilder.toString ()Ljava/lang/String;
                    ASTORE_3     // Ljava/lang/String; newPath
                L0: NEW java.lang.StringBuilder   (line 580)
                    DUP
                    ALOAD_3     // Ljava/lang/String; newPath
                    INVOKESTATIC java.lang.String.valueOf (Ljava/lang/Object;)Ljava/lang/String;
                    INVOKESPECIAL java.lang.StringBuilder.<init> (Ljava/lang/String;)V
                    ALOAD_1     // Ljava/lang/String; relativePath
                    INVOKEVIRTUAL java.lang.StringBuilder.append (Ljava/lang/String;)Ljava/lang/StringBuilder;
                    INVOKEVIRTUAL java.lang.StringBuilder.toString ()Ljava/lang/String;
                    ARETURN
                L1: ALOAD_1     // Ljava/lang/String; relativePath   (line 583)
                    ARETURN
  end public static String applyRelativePath(String, String)

  public static String cleanPath(String):
                    ALOAD_0     // Ljava/lang/String; path   (line 596)
                    IFNONNULL L0
                    ACONST_NULL   (line 597)
                    ARETURN
                L0: ALOAD_0     // Ljava/lang/String; path   (line 599)
                    LDC "\"
                    LDC "/"
                    INVOKESTATIC org.springframework.util.StringUtils.replace (Ljava/lang/String;Ljava/lang/String;Ljava/lang/String;)Ljava/lang/String;
                    ASTORE_1
                    ALOAD_1     // Ljava/lang/String; pathToUse   (line 605)
                    LDC ":"
                    INVOKEVIRTUAL java.lang.String.indexOf (Ljava/lang/String;)I
                    ISTORE_2
                    LDC ""   (line 606)
                    ASTORE_3
                    ILOAD_2     // I prefixIndex   (line 607)
                    ICONST_M1
                    IF_ICMPEQ L1
                    ALOAD_1     // Ljava/lang/String; pathToUse   (line 608)
                    ICONST_0
                    ILOAD_2     // I prefixIndex
                    ICONST_1
                    IADD
                    INVOKEVIRTUAL java.lang.String.substring (II)Ljava/lang/String;
                    ASTORE_3     // Ljava/lang/String; prefix
                    ALOAD_1     // Ljava/lang/String; pathToUse   (line 609)
                    ILOAD_2     // I prefixIndex
                    ICONST_1
                    IADD
                    INVOKEVIRTUAL java.lang.String.substring (I)Ljava/lang/String;
                    ASTORE_1     // Ljava/lang/String; pathToUse
                L1: ALOAD_1     // Ljava/lang/String; pathToUse   (line 611)
                    LDC "/"
                    INVOKEVIRTUAL java.lang.String.startsWith (Ljava/lang/String;)Z
                    IFEQ L2
                    NEW java.lang.StringBuilder   (line 612)
                    DUP
                    ALOAD_3     // Ljava/lang/String; prefix
                    INVOKESTATIC java.lang.String.valueOf (Ljava/lang/Object;)Ljava/lang/String;
                    INVOKESPECIAL java.lang.StringBuilder.<init> (Ljava/lang/String;)V
                    LDC "/"
                    INVOKEVIRTUAL java.lang.StringBuilder.append (Ljava/lang/String;)Ljava/lang/StringBuilder;
                    INVOKEVIRTUAL java.lang.StringBuilder.toString ()Ljava/lang/String;
                    ASTORE_3     // Ljava/lang/String; prefix
                    ALOAD_1     // Ljava/lang/String; pathToUse   (line 613)
                    ICONST_1
                    INVOKEVIRTUAL java.lang.String.substring (I)Ljava/lang/String;
                    ASTORE_1     // Ljava/lang/String; pathToUse
                L2: ALOAD_1     // Ljava/lang/String; pathToUse   (line 616)
                    LDC "/"
                    INVOKESTATIC org.springframework.util.StringUtils.delimitedListToStringArray (Ljava/lang/String;Ljava/lang/String;)[Ljava/lang/String;
                    ASTORE 4
                    NEW java.util.LinkedList   (line 617)
                    DUP
                    INVOKESPECIAL java.util.LinkedList.<init> ()V
                    ASTORE 5
                    ICONST_0   (line 618)
                    ISTORE 6
                    ALOAD 4     // [Ljava/lang/String; pathArray   (line 620)
                    ARRAYLENGTH
                    ICONST_1
                    ISUB
                    ISTORE 7
                    GOTO L7
                L3: ALOAD 4     // [Ljava/lang/String; pathArray   (line 621)
                    ILOAD 7     // I i
                    AALOAD
                    ASTORE 8
                    LDC "."   (line 622)
                    ALOAD 8     // Ljava/lang/String; element
                    INVOKEVIRTUAL java.lang.String.equals (Ljava/lang/Object;)Z
                    IFNE L6
                    LDC ".."   (line 625)
                    ALOAD 8     // Ljava/lang/String; element
                    INVOKEVIRTUAL java.lang.String.equals (Ljava/lang/Object;)Z
                    IFEQ L4
                    IINC 6 1     // I tops   (line 627)
                    GOTO L6
                L4: ILOAD 6     // I tops   (line 630)
                    IFLE L5
                    IINC 6 -1     // I tops   (line 632)
                    GOTO L6
                L5: ALOAD 5     // Ljava/util/List; pathElements   (line 636)
                    ICONST_0
                    ALOAD 8     // Ljava/lang/String; element
                    INVOKEINTERFACE java.util.List.add (ILjava/lang/Object;)V
                L6: IINC 7 -1     // I i   (line 620)
                L7: ILOAD 7     // I i
                    IFGE L3
                    ICONST_0   (line 642)
                    ISTORE 7
                    GOTO L9
                L8: ALOAD 5     // Ljava/util/List; pathElements   (line 643)
                    ICONST_0
                    LDC ".."
                    INVOKEINTERFACE java.util.List.add (ILjava/lang/Object;)V
                    IINC 7 1     // I i   (line 642)
                L9: ILOAD 7     // I i
                    ILOAD 6     // I tops
                    IF_ICMPLT L8
                    NEW java.lang.StringBuilder   (line 646)
                    DUP
                    ALOAD_3     // Ljava/lang/String; prefix
                    INVOKESTATIC java.lang.String.valueOf (Ljava/lang/Object;)Ljava/lang/String;
                    INVOKESPECIAL java.lang.StringBuilder.<init> (Ljava/lang/String;)V
                    ALOAD 5     // Ljava/util/List; pathElements
                    LDC "/"
                    INVOKESTATIC org.springframework.util.StringUtils.collectionToDelimitedString (Ljava/util/Collection;Ljava/lang/String;)Ljava/lang/String;
                    INVOKEVIRTUAL java.lang.StringBuilder.append (Ljava/lang/String;)Ljava/lang/StringBuilder;
                    INVOKEVIRTUAL java.lang.StringBuilder.toString ()Ljava/lang/String;
                    ARETURN
  end public static String cleanPath(String)

  public static boolean pathEquals(String, String):
                    ALOAD_0     // Ljava/lang/String; path1   (line 656)
                    INVOKESTATIC org.springframework.util.StringUtils.cleanPath (Ljava/lang/String;)Ljava/lang/String;
                    ALOAD_1     // Ljava/lang/String; path2
                    INVOKESTATIC org.springframework.util.StringUtils.cleanPath (Ljava/lang/String;)Ljava/lang/String;
                    INVOKEVIRTUAL java.lang.String.equals (Ljava/lang/Object;)Z
                    IRETURN
  end public static boolean pathEquals(String, String)

  public static java.util.Locale parseLocaleString(String):
                    ALOAD_0     // Ljava/lang/String; localeString   (line 668)
                    LDC "_ "
                    ICONST_0
                    ICONST_0
                    INVOKESTATIC org.springframework.util.StringUtils.tokenizeToStringArray (Ljava/lang/String;Ljava/lang/String;ZZ)[Ljava/lang/String;
                    ASTORE_1
                    ALOAD_1     // [Ljava/lang/String; parts   (line 669)
                    ARRAYLENGTH
                    IFLE L0
                    ALOAD_1     // [Ljava/lang/String; parts
                    ICONST_0
                    AALOAD
                    GOTO L1
                L0: LDC ""
                L1: ASTORE_2
                    ALOAD_1     // [Ljava/lang/String; parts   (line 670)
                    ARRAYLENGTH
                    ICONST_1
                    IF_ICMPLE L2
                    ALOAD_1     // [Ljava/lang/String; parts
                    ICONST_1
                    AALOAD
                    GOTO L3
                L2: LDC ""
                L3: ASTORE_3
                    ALOAD_2     // Ljava/lang/String; language   (line 671)
                    INVOKESTATIC org.springframework.util.StringUtils.validateLocalePart (Ljava/lang/String;)V
                    ALOAD_3     // Ljava/lang/String; country   (line 672)
                    INVOKESTATIC org.springframework.util.StringUtils.validateLocalePart (Ljava/lang/String;)V
                    LDC ""   (line 673)
                    ASTORE 4
                    ALOAD_1     // [Ljava/lang/String; parts   (line 674)
                    ARRAYLENGTH
                    ICONST_2
                    IF_ICMPLT L4
                    ALOAD_0     // Ljava/lang/String; localeString   (line 677)
                    ALOAD_3     // Ljava/lang/String; country
                    INVOKEVIRTUAL java.lang.String.indexOf (Ljava/lang/String;)I
                    ALOAD_3     // Ljava/lang/String; country
                    INVOKEVIRTUAL java.lang.String.length ()I
                    IADD
                    ISTORE 5
                    ALOAD_0     // Ljava/lang/String; localeString   (line 679)
                    ILOAD 5     // I endIndexOfCountryCode
                    INVOKEVIRTUAL java.lang.String.substring (I)Ljava/lang/String;
                    INVOKESTATIC org.springframework.util.StringUtils.trimLeadingWhitespace (Ljava/lang/String;)Ljava/lang/String;
                    ASTORE 4     // Ljava/lang/String; variant
                    ALOAD 4     // Ljava/lang/String; variant   (line 680)
                    LDC_W "_"
                    INVOKEVIRTUAL java.lang.String.startsWith (Ljava/lang/String;)Z
                    IFEQ L4
                    ALOAD 4     // Ljava/lang/String; variant   (line 681)
                    BIPUSH 95
                    INVOKESTATIC org.springframework.util.StringUtils.trimLeadingCharacter (Ljava/lang/String;C)Ljava/lang/String;
                    ASTORE 4     // Ljava/lang/String; variant
                L4: ALOAD_2     // Ljava/lang/String; language   (line 684)
                    INVOKEVIRTUAL java.lang.String.length ()I
                    IFLE L5
                    NEW java.util.Locale
                    DUP
                    ALOAD_2     // Ljava/lang/String; language
                    ALOAD_3     // Ljava/lang/String; country
                    ALOAD 4     // Ljava/lang/String; variant
                    INVOKESPECIAL java.util.Locale.<init> (Ljava/lang/String;Ljava/lang/String;Ljava/lang/String;)V
                    GOTO L6
                L5: ACONST_NULL
                L6: ARETURN
  end public static java.util.Locale parseLocaleString(String)

  private static void validateLocalePart(String):
                    ICONST_0   (line 688)
                    ISTORE_1
                    GOTO L2
                L0: ALOAD_0     // Ljava/lang/String; localePart   (line 689)
                    ILOAD_1     // I i
                    INVOKEVIRTUAL java.lang.String.charAt (I)C
                    ISTORE_2
                    ILOAD_2     // C ch   (line 690)
                    BIPUSH 95
                    IF_ICMPEQ L1
                    ILOAD_2     // C ch
                    BIPUSH 32
                    IF_ICMPEQ L1
                    ILOAD_2     // C ch
                    INVOKESTATIC java.lang.Character.isLetterOrDigit (C)Z
                    IFNE L1
                    NEW java.lang.IllegalArgumentException   (line 691)
                    DUP
                    NEW java.lang.StringBuilder   (line 692)
                    DUP
                    LDC_W "Locale part \""
                    INVOKESPECIAL java.lang.StringBuilder.<init> (Ljava/lang/String;)V
                    ALOAD_0     // Ljava/lang/String; localePart
                    INVOKEVIRTUAL java.lang.StringBuilder.append (Ljava/lang/String;)Ljava/lang/StringBuilder;
                    LDC_W "\" contains invalid characters"
                    INVOKEVIRTUAL java.lang.StringBuilder.append (Ljava/lang/String;)Ljava/lang/StringBuilder;
                    INVOKEVIRTUAL java.lang.StringBuilder.toString ()Ljava/lang/String;
                    INVOKESPECIAL java.lang.IllegalArgumentException.<init> (Ljava/lang/String;)V   (line 691)
                    ATHROW
                L1: IINC_1 1     // I i   (line 688)
                L2: ILOAD_1     // I i
                    ALOAD_0     // Ljava/lang/String; localePart
                    INVOKEVIRTUAL java.lang.String.length ()I
                    IF_ICMPLT L0
                    RETURN   (line 695)
  end private static void validateLocalePart(String)

  public static String toLanguageTag(java.util.Locale):
                    NEW java.lang.StringBuilder   (line 704)
                    DUP
                    ALOAD_0     // Ljava/util/Locale; locale
                    INVOKEVIRTUAL java.util.Locale.getLanguage ()Ljava/lang/String;
                    INVOKESTATIC java.lang.String.valueOf (Ljava/lang/Object;)Ljava/lang/String;
                    INVOKESPECIAL java.lang.StringBuilder.<init> (Ljava/lang/String;)V
                    ALOAD_0     // Ljava/util/Locale; locale
                    INVOKEVIRTUAL java.util.Locale.getCountry ()Ljava/lang/String;
                    INVOKESTATIC org.springframework.util.StringUtils.hasText (Ljava/lang/String;)Z
                    IFEQ L0
                    NEW java.lang.StringBuilder
                    DUP
                    LDC_W "-"
                    INVOKESPECIAL java.lang.StringBuilder.<init> (Ljava/lang/String;)V
                    ALOAD_0     // Ljava/util/Locale; locale
                    INVOKEVIRTUAL java.util.Locale.getCountry ()Ljava/lang/String;
                    INVOKEVIRTUAL java.lang.StringBuilder.append (Ljava/lang/String;)Ljava/lang/StringBuilder;
                    INVOKEVIRTUAL java.lang.StringBuilder.toString ()Ljava/lang/String;
                    GOTO L1
                L0: LDC ""
                L1: INVOKEVIRTUAL java.lang.StringBuilder.append (Ljava/lang/String;)Ljava/lang/StringBuilder;
                    INVOKEVIRTUAL java.lang.StringBuilder.toString ()Ljava/lang/String;
                    ARETURN
  end public static String toLanguageTag(java.util.Locale)

  public static String[] addStringToArray(String[], String):
                    ALOAD_0     // [Ljava/lang/String; array   (line 720)
                    INVOKESTATIC org.springframework.util.ObjectUtils.isEmpty ([Ljava/lang/Object;)Z
                    IFEQ L0
                    ICONST_1   (line 721)
                    ANEWARRAY java.lang.String
                    DUP
                    ICONST_0
                    ALOAD_1     // Ljava/lang/String; str
                    AASTORE
                    ARETURN
                L0: ALOAD_0     // [Ljava/lang/String; array   (line 723)
                    ARRAYLENGTH
                    ICONST_1
                    IADD
                    ANEWARRAY java.lang.String
                    ASTORE_2
                    ALOAD_0     // [Ljava/lang/String; array   (line 724)
                    ICONST_0
                    ALOAD_2     // [Ljava/lang/String; newArr
                    ICONST_0
                    ALOAD_0     // [Ljava/lang/String; array
                    ARRAYLENGTH
                    INVOKESTATIC java.lang.System.arraycopy (Ljava/lang/Object;ILjava/lang/Object;II)V
                    ALOAD_2     // [Ljava/lang/String; newArr   (line 725)
                    ALOAD_0     // [Ljava/lang/String; array
                    ARRAYLENGTH
                    ALOAD_1     // Ljava/lang/String; str
                    AASTORE
                    ALOAD_2     // [Ljava/lang/String; newArr   (line 726)
                    ARETURN
  end public static String[] addStringToArray(String[], String)

  public static String[] concatenateStringArrays(String[], String[]):
                    ALOAD_0     // [Ljava/lang/String; array1   (line 738)
                    INVOKESTATIC org.springframework.util.ObjectUtils.isEmpty ([Ljava/lang/Object;)Z
                    IFEQ L0
                    ALOAD_1     // [Ljava/lang/String; array2   (line 739)
                    ARETURN
                L0: ALOAD_1     // [Ljava/lang/String; array2   (line 741)
                    INVOKESTATIC org.springframework.util.ObjectUtils.isEmpty ([Ljava/lang/Object;)Z
                    IFEQ L1
                    ALOAD_0     // [Ljava/lang/String; array1   (line 742)
                    ARETURN
                L1: ALOAD_0     // [Ljava/lang/String; array1   (line 744)
                    ARRAYLENGTH
                    ALOAD_1     // [Ljava/lang/String; array2
                    ARRAYLENGTH
                    IADD
                    ANEWARRAY java.lang.String
                    ASTORE_2
                    ALOAD_0     // [Ljava/lang/String; array1   (line 745)
                    ICONST_0
                    ALOAD_2     // [Ljava/lang/String; newArr
                    ICONST_0
                    ALOAD_0     // [Ljava/lang/String; array1
                    ARRAYLENGTH
                    INVOKESTATIC java.lang.System.arraycopy (Ljava/lang/Object;ILjava/lang/Object;II)V
                    ALOAD_1     // [Ljava/lang/String; array2   (line 746)
                    ICONST_0
                    ALOAD_2     // [Ljava/lang/String; newArr
                    ALOAD_0     // [Ljava/lang/String; array1
                    ARRAYLENGTH
                    ALOAD_1     // [Ljava/lang/String; array2
                    ARRAYLENGTH
                    INVOKESTATIC java.lang.System.arraycopy (Ljava/lang/Object;ILjava/lang/Object;II)V
                    ALOAD_2     // [Ljava/lang/String; newArr   (line 747)
                    ARETURN
  end public static String[] concatenateStringArrays(String[], String[])

  public static String[] mergeStringArrays(String[], String[]):
                    ALOAD_0     // [Ljava/lang/String; array1   (line 761)
                    INVOKESTATIC org.springframework.util.ObjectUtils.isEmpty ([Ljava/lang/Object;)Z
                    IFEQ L0
                    ALOAD_1     // [Ljava/lang/String; array2   (line 762)
                    ARETURN
                L0: ALOAD_1     // [Ljava/lang/String; array2   (line 764)
                    INVOKESTATIC org.springframework.util.ObjectUtils.isEmpty ([Ljava/lang/Object;)Z
                    IFEQ L1
                    ALOAD_0     // [Ljava/lang/String; array1   (line 765)
                    ARETURN
                L1: NEW java.util.ArrayList   (line 767)
                    DUP
                    INVOKESPECIAL java.util.ArrayList.<init> ()V
                    ASTORE_2
                    ALOAD_2     // Ljava/util/List; result   (line 768)
                    ALOAD_0     // [Ljava/lang/String; array1
                    INVOKESTATIC java.util.Arrays.asList ([Ljava/lang/Object;)Ljava/util/List;
                    CHECKCAST java.util.Collection
                    INVOKEINTERFACE java.util.List.addAll (Ljava/util/Collection;)Z
                    POP
                    ALOAD_1     // [Ljava/lang/String; array2   (line 769)
                    DUP
                    ASTORE 6
                    ARRAYLENGTH
                    ISTORE 5
                    ICONST_0
                    ISTORE 4
                    GOTO L4
                L2: ALOAD 6
                    ILOAD 4
                    AALOAD
                    ASTORE_3
                    ALOAD_2     // Ljava/util/List; result   (line 770)
                    ALOAD_3     // Ljava/lang/String; str
                    INVOKEINTERFACE java.util.List.contains (Ljava/lang/Object;)Z
                    IFNE L3
                    ALOAD_2     // Ljava/util/List; result   (line 771)
                    ALOAD_3     // Ljava/lang/String; str
                    INVOKEINTERFACE java.util.List.add (Ljava/lang/Object;)Z
                    POP
                L3: IINC 4 1   (line 769)
                L4: ILOAD 4
                    ILOAD 5
                    IF_ICMPLT L2
                    ALOAD_2     // Ljava/util/List; result   (line 774)
                    INVOKESTATIC org.springframework.util.StringUtils.toStringArray (Ljava/util/Collection;)[Ljava/lang/String;
                    ARETURN
  end public static String[] mergeStringArrays(String[], String[])

  public static String[] sortStringArray(String[]):
                    ALOAD_0     // [Ljava/lang/String; array   (line 783)
                    INVOKESTATIC org.springframework.util.ObjectUtils.isEmpty ([Ljava/lang/Object;)Z
                    IFEQ L0
                    ICONST_0   (line 784)
                    ANEWARRAY java.lang.String
                    ARETURN
                L0: ALOAD_0     // [Ljava/lang/String; array   (line 786)
                    INVOKESTATIC java.util.Arrays.sort ([Ljava/lang/Object;)V
                    ALOAD_0     // [Ljava/lang/String; array   (line 787)
                    ARETURN
  end public static String[] sortStringArray(String[])

  public static String[] toStringArray(java.util.Collection):
                    ALOAD_0     // Ljava/util/Collection; collection   (line 798)
                    IFNONNULL L0
                    ACONST_NULL   (line 799)
                    ARETURN
                L0: ALOAD_0     // Ljava/util/Collection; collection   (line 801)
                    ALOAD_0     // Ljava/util/Collection; collection
                    INVOKEINTERFACE java.util.Collection.size ()I
                    ANEWARRAY java.lang.String
                    INVOKEINTERFACE java.util.Collection.toArray ([Ljava/lang/Object;)[Ljava/lang/Object;
                    CHECKCAST [Ljava.lang.String;
                    ARETURN
  end public static String[] toStringArray(java.util.Collection)

  public static String[] toStringArray(java.util.Enumeration):
                    ALOAD_0     // Ljava/util/Enumeration; enumeration   (line 812)
                    IFNONNULL L0
                    ACONST_NULL   (line 813)
                    ARETURN
                L0: ALOAD_0     // Ljava/util/Enumeration; enumeration   (line 815)
                    INVOKESTATIC java.util.Collections.list (Ljava/util/Enumeration;)Ljava/util/ArrayList;
                    CHECKCAST java.util.List
                    ASTORE_1
                    ALOAD_1     // Ljava/util/List; list   (line 816)
                    ALOAD_1     // Ljava/util/List; list
                    INVOKEINTERFACE java.util.List.size ()I
                    ANEWARRAY java.lang.String
                    INVOKEINTERFACE java.util.List.toArray ([Ljava/lang/Object;)[Ljava/lang/Object;
                    CHECKCAST [Ljava.lang.String;
                    ARETURN
  end public static String[] toStringArray(java.util.Enumeration)

  public static String[] trimArrayElements(String[]):
                    ALOAD_0     // [Ljava/lang/String; array   (line 826)
                    INVOKESTATIC org.springframework.util.ObjectUtils.isEmpty ([Ljava/lang/Object;)Z
                    IFEQ L0
                    ICONST_0   (line 827)
                    ANEWARRAY java.lang.String
                    ARETURN
                L0: ALOAD_0     // [Ljava/lang/String; array   (line 829)
                    ARRAYLENGTH
                    ANEWARRAY java.lang.String
                    ASTORE_1
                    ICONST_0   (line 830)
                    ISTORE_2
                    GOTO L4
                L1: ALOAD_0     // [Ljava/lang/String; array   (line 831)
                    ILOAD_2     // I i
                    AALOAD
                    ASTORE_3
                    ALOAD_1     // [Ljava/lang/String; result   (line 832)
                    ILOAD_2     // I i
                    ALOAD_3     // Ljava/lang/String; element
                    IFNULL L2
                    ALOAD_3     // Ljava/lang/String; element
                    INVOKEVIRTUAL java.lang.String.trim ()Ljava/lang/String;
                    GOTO L3
                L2: ACONST_NULL
                L3: AASTORE
                    IINC_2 1     // I i   (line 830)
                L4: ILOAD_2     // I i
                    ALOAD_0     // [Ljava/lang/String; array
                    ARRAYLENGTH
                    IF_ICMPLT L1
                    ALOAD_1     // [Ljava/lang/String; result   (line 834)
                    ARETURN
  end public static String[] trimArrayElements(String[])

  public static String[] removeDuplicateStrings(String[]):
                    ALOAD_0     // [Ljava/lang/String; array   (line 844)
                    INVOKESTATIC org.springframework.util.ObjectUtils.isEmpty ([Ljava/lang/Object;)Z
                    IFEQ L0
                    ALOAD_0     // [Ljava/lang/String; array   (line 845)
                    ARETURN
                L0: NEW java.util.TreeSet   (line 847)
                    DUP
                    INVOKESPECIAL java.util.TreeSet.<init> ()V
                    ASTORE_1
                    ALOAD_0     // [Ljava/lang/String; array   (line 848)
                    DUP
                    ASTORE 5
                    ARRAYLENGTH
                    ISTORE 4
                    ICONST_0
                    ISTORE_3
                    GOTO L2
                L1: ALOAD 5
                    ILOAD_3
                    AALOAD
                    ASTORE_2
                    ALOAD_1     // Ljava/util/Set; set   (line 849)
                    ALOAD_2     // Ljava/lang/String; element
                    INVOKEINTERFACE java.util.Set.add (Ljava/lang/Object;)Z
                    POP
                    IINC_3 1   (line 848)
                L2: ILOAD_3
                    ILOAD 4
                    IF_ICMPLT L1
                    ALOAD_1     // Ljava/util/Set; set   (line 851)
                    INVOKESTATIC org.springframework.util.StringUtils.toStringArray (Ljava/util/Collection;)[Ljava/lang/String;
                    ARETURN
  end public static String[] removeDuplicateStrings(String[])

  public static String[] split(String, String):
                    ALOAD_0     // Ljava/lang/String; toSplit   (line 864)
                    INVOKESTATIC org.springframework.util.StringUtils.hasLength (Ljava/lang/String;)Z
                    IFEQ L0
                    ALOAD_1     // Ljava/lang/String; delimiter
                    INVOKESTATIC org.springframework.util.StringUtils.hasLength (Ljava/lang/String;)Z
                    IFNE L1
                L0: ACONST_NULL   (line 865)
                    ARETURN
                L1: ALOAD_0     // Ljava/lang/String; toSplit   (line 867)
                    ALOAD_1     // Ljava/lang/String; delimiter
                    INVOKEVIRTUAL java.lang.String.indexOf (Ljava/lang/String;)I
                    ISTORE_2
                    ILOAD_2     // I offset   (line 868)
                    IFGE L2
                    ACONST_NULL   (line 869)
                    ARETURN
                L2: ALOAD_0     // Ljava/lang/String; toSplit   (line 871)
                    ICONST_0
                    ILOAD_2     // I offset
                    INVOKEVIRTUAL java.lang.String.substring (II)Ljava/lang/String;
                    ASTORE_3
                    ALOAD_0     // Ljava/lang/String; toSplit   (line 872)
                    ILOAD_2     // I offset
                    ALOAD_1     // Ljava/lang/String; delimiter
                    INVOKEVIRTUAL java.lang.String.length ()I
                    IADD
                    INVOKEVIRTUAL java.lang.String.substring (I)Ljava/lang/String;
                    ASTORE 4
                    ICONST_2   (line 873)
                    ANEWARRAY java.lang.String
                    DUP
                    ICONST_0
                    ALOAD_3     // Ljava/lang/String; beforeDelimiter
                    AASTORE
                    DUP
                    ICONST_1
                    ALOAD 4     // Ljava/lang/String; afterDelimiter
                    AASTORE
                    ARETURN
  end public static String[] split(String, String)

  public static java.util.Properties splitArrayElementsIntoProperties(String[], String):
                    ALOAD_0     // [Ljava/lang/String; array   (line 888)
                    ALOAD_1     // Ljava/lang/String; delimiter
                    ACONST_NULL
                    INVOKESTATIC org.springframework.util.StringUtils.splitArrayElementsIntoProperties ([Ljava/lang/String;Ljava/lang/String;Ljava/lang/String;)Ljava/util/Properties;
                    ARETURN
  end public static java.util.Properties splitArrayElementsIntoProperties(String[], String)

  public static java.util.Properties splitArrayElementsIntoProperties(String[], String, String):
                    ALOAD_0     // [Ljava/lang/String; array   (line 908)
                    INVOKESTATIC org.springframework.util.ObjectUtils.isEmpty ([Ljava/lang/Object;)Z
                    IFEQ L0
                    ACONST_NULL   (line 909)
                    ARETURN
                L0: NEW java.util.Properties   (line 911)
                    DUP
                    INVOKESPECIAL java.util.Properties.<init> ()V
                    ASTORE_3
                    ALOAD_0     // [Ljava/lang/String; array   (line 912)
                    DUP
                    ASTORE 7
                    ARRAYLENGTH
                    ISTORE 6
                    ICONST_0
                    ISTORE 5
                    GOTO L5
                L1: ALOAD 7
                    ILOAD 5
                    AALOAD
                    ASTORE 4
                    ALOAD_2     // Ljava/lang/String; charsToDelete   (line 913)
                    IFNULL L2
                    ALOAD 4     // Ljava/lang/String; element   (line 914)
                    ALOAD_2     // Ljava/lang/String; charsToDelete
                    INVOKESTATIC org.springframework.util.StringUtils.deleteAny (Ljava/lang/String;Ljava/lang/String;)Ljava/lang/String;
                    ASTORE 4     // Ljava/lang/String; element
                L2: ALOAD 4     // Ljava/lang/String; element   (line 916)
                    ALOAD_1     // Ljava/lang/String; delimiter
                    INVOKESTATIC org.springframework.util.StringUtils.split (Ljava/lang/String;Ljava/lang/String;)[Ljava/lang/String;
                    ASTORE 8
                    ALOAD 8     // [Ljava/lang/String; splittedElement   (line 917)
                    IFNONNULL L3
                    GOTO L4   (line 918)
                L3: ALOAD_3     // Ljava/util/Properties; result   (line 920)
                    ALOAD 8     // [Ljava/lang/String; splittedElement
                    ICONST_0
                    AALOAD
                    INVOKEVIRTUAL java.lang.String.trim ()Ljava/lang/String;
                    ALOAD 8     // [Ljava/lang/String; splittedElement
                    ICONST_1
                    AALOAD
                    INVOKEVIRTUAL java.lang.String.trim ()Ljava/lang/String;
                    INVOKEVIRTUAL java.util.Properties.setProperty (Ljava/lang/String;Ljava/lang/String;)Ljava/lang/Object;
                    POP
                L4: IINC 5 1   (line 912)
                L5: ILOAD 5
                    ILOAD 6
                    IF_ICMPLT L1
                    ALOAD_3     // Ljava/util/Properties; result   (line 922)
                    ARETURN
  end public static java.util.Properties splitArrayElementsIntoProperties(String[], String, String)

  public static String[] tokenizeToStringArray(String, String):
                    ALOAD_0     // Ljava/lang/String; str   (line 941)
                    ALOAD_1     // Ljava/lang/String; delimiters
                    ICONST_1
                    ICONST_1
                    INVOKESTATIC org.springframework.util.StringUtils.tokenizeToStringArray (Ljava/lang/String;Ljava/lang/String;ZZ)[Ljava/lang/String;
                    ARETURN
  end public static String[] tokenizeToStringArray(String, String)

  public static String[] tokenizeToStringArray(String, String, boolean, boolean):
                    ALOAD_0     // Ljava/lang/String; str   (line 966)
                    IFNONNULL L0
                    ACONST_NULL   (line 967)
                    ARETURN
                L0: NEW java.util.StringTokenizer   (line 969)
                    DUP
                    ALOAD_0     // Ljava/lang/String; str
                    ALOAD_1     // Ljava/lang/String; delimiters
                    INVOKESPECIAL java.util.StringTokenizer.<init> (Ljava/lang/String;Ljava/lang/String;)V
                    ASTORE 4
                    NEW java.util.ArrayList   (line 970)
                    DUP
                    INVOKESPECIAL java.util.ArrayList.<init> ()V
                    ASTORE 5
                    GOTO L4   (line 971)
                L1: ALOAD 4     // Ljava/util/StringTokenizer; st   (line 972)
                    INVOKEVIRTUAL java.util.StringTokenizer.nextToken ()Ljava/lang/String;
                    ASTORE 6
                    ILOAD_2     // Z trimTokens   (line 973)
                    IFEQ L2
                    ALOAD 6     // Ljava/lang/String; token   (line 974)
                    INVOKEVIRTUAL java.lang.String.trim ()Ljava/lang/String;
                    ASTORE 6     // Ljava/lang/String; token
                L2: ILOAD_3     // Z ignoreEmptyTokens   (line 976)
                    IFEQ L3
                    ALOAD 6     // Ljava/lang/String; token
                    INVOKEVIRTUAL java.lang.String.length ()I
                    IFLE L4
                L3: ALOAD 5     // Ljava/util/List; tokens   (line 977)
                    ALOAD 6     // Ljava/lang/String; token
                    INVOKEINTERFACE java.util.List.add (Ljava/lang/Object;)Z
                    POP
                L4: ALOAD 4     // Ljava/util/StringTokenizer; st   (line 971)
                    INVOKEVIRTUAL java.util.StringTokenizer.hasMoreTokens ()Z
                    IFNE L1
                    ALOAD 5     // Ljava/util/List; tokens   (line 980)
                    INVOKESTATIC org.springframework.util.StringUtils.toStringArray (Ljava/util/Collection;)[Ljava/lang/String;
                    ARETURN
  end public static String[] tokenizeToStringArray(String, String, boolean, boolean)

  public static String[] delimitedListToStringArray(String, String):
                    ALOAD_0     // Ljava/lang/String; str   (line 995)
                    ALOAD_1     // Ljava/lang/String; delimiter
                    ACONST_NULL
                    INVOKESTATIC org.springframework.util.StringUtils.delimitedListToStringArray (Ljava/lang/String;Ljava/lang/String;Ljava/lang/String;)[Ljava/lang/String;
                    ARETURN
  end public static String[] delimitedListToStringArray(String, String)

  public static String[] delimitedListToStringArray(String, String, String):
                    ALOAD_0     // Ljava/lang/String; str   (line 1012)
                    IFNONNULL L0
                    ICONST_0   (line 1013)
                    ANEWARRAY java.lang.String
                    ARETURN
                L0: ALOAD_1     // Ljava/lang/String; delimiter   (line 1015)
                    IFNONNULL L1
                    ICONST_1   (line 1016)
                    ANEWARRAY java.lang.String
                    DUP
                    ICONST_0
                    ALOAD_0     // Ljava/lang/String; str
                    AASTORE
                    ARETURN
                L1: NEW java.util.ArrayList   (line 1018)
                    DUP
                    INVOKESPECIAL java.util.ArrayList.<init> ()V
                    ASTORE_3
                    LDC ""   (line 1019)
                    ALOAD_1     // Ljava/lang/String; delimiter
                    INVOKEVIRTUAL java.lang.String.equals (Ljava/lang/Object;)Z
                    IFEQ L4
                    ICONST_0   (line 1020)
                    ISTORE 4
                    GOTO L3
                L2: ALOAD_3     // Ljava/util/List; result   (line 1021)
                    ALOAD_0     // Ljava/lang/String; str
                    ILOAD 4     // I i
                    ILOAD 4     // I i
                    ICONST_1
                    IADD
                    INVOKEVIRTUAL java.lang.String.substring (II)Ljava/lang/String;
                    ALOAD_2     // Ljava/lang/String; charsToDelete
                    INVOKESTATIC org.springframework.util.StringUtils.deleteAny (Ljava/lang/String;Ljava/lang/String;)Ljava/lang/String;
                    INVOKEINTERFACE java.util.List.add (Ljava/lang/Object;)Z
                    POP
                    IINC 4 1     // I i   (line 1020)
                L3: ILOAD 4     // I i
                    ALOAD_0     // Ljava/lang/String; str
                    INVOKEVIRTUAL java.lang.String.length ()I
                    IF_ICMPLT L2
                    GOTO L7
                L4: ICONST_0   (line 1025)
                    ISTORE 4
                    GOTO L6   (line 1027)
                L5: ALOAD_3     // Ljava/util/List; result   (line 1028)
                    ALOAD_0     // Ljava/lang/String; str
                    ILOAD 4     // I pos
                    ILOAD 5     // I delPos
                    INVOKEVIRTUAL java.lang.String.substring (II)Ljava/lang/String;
                    ALOAD_2     // Ljava/lang/String; charsToDelete
                    INVOKESTATIC org.springframework.util.StringUtils.deleteAny (Ljava/lang/String;Ljava/lang/String;)Ljava/lang/String;
                    INVOKEINTERFACE java.util.List.add (Ljava/lang/Object;)Z
                    POP
                    ILOAD 5     // I delPos   (line 1029)
                    ALOAD_1     // Ljava/lang/String; delimiter
                    INVOKEVIRTUAL java.lang.String.length ()I
                    IADD
                    ISTORE 4     // I pos
                L6: ALOAD_0     // Ljava/lang/String; str   (line 1027)
                    ALOAD_1     // Ljava/lang/String; delimiter
                    ILOAD 4     // I pos
                    INVOKEVIRTUAL java.lang.String.indexOf (Ljava/lang/String;I)I
                    DUP
                    ISTORE 5
                    ICONST_M1
                    IF_ICMPNE L5
                    ALOAD_0     // Ljava/lang/String; str   (line 1031)
                    INVOKEVIRTUAL java.lang.String.length ()I
                    IFLE L7
                    ILOAD 4     // I pos
                    ALOAD_0     // Ljava/lang/String; str
                    INVOKEVIRTUAL java.lang.String.length ()I
                    IF_ICMPGT L7
                    ALOAD_3     // Ljava/util/List; result   (line 1033)
                    ALOAD_0     // Ljava/lang/String; str
                    ILOAD 4     // I pos
                    INVOKEVIRTUAL java.lang.String.substring (I)Ljava/lang/String;
                    ALOAD_2     // Ljava/lang/String; charsToDelete
                    INVOKESTATIC org.springframework.util.StringUtils.deleteAny (Ljava/lang/String;Ljava/lang/String;)Ljava/lang/String;
                    INVOKEINTERFACE java.util.List.add (Ljava/lang/Object;)Z
                    POP
                L7: ALOAD_3     // Ljava/util/List; result   (line 1036)
                    INVOKESTATIC org.springframework.util.StringUtils.toStringArray (Ljava/util/Collection;)[Ljava/lang/String;
                    ARETURN
  end public static String[] delimitedListToStringArray(String, String, String)

  public static String[] commaDelimitedListToStringArray(String):
                    ALOAD_0     // Ljava/lang/String; str   (line 1045)
                    LDC_W ","
                    INVOKESTATIC org.springframework.util.StringUtils.delimitedListToStringArray (Ljava/lang/String;Ljava/lang/String;)[Ljava/lang/String;
                    ARETURN
  end public static String[] commaDelimitedListToStringArray(String)

  public static java.util.Set commaDelimitedListToSet(String):
                    NEW java.util.TreeSet   (line 1055)
                    DUP
                    INVOKESPECIAL java.util.TreeSet.<init> ()V
                    ASTORE_1
                    ALOAD_0     // Ljava/lang/String; str   (line 1056)
                    INVOKESTATIC org.springframework.util.StringUtils.commaDelimitedListToStringArray (Ljava/lang/String;)[Ljava/lang/String;
                    ASTORE_2
                    ALOAD_2     // [Ljava/lang/String; tokens   (line 1057)
                    DUP
                    ASTORE 6
                    ARRAYLENGTH
                    ISTORE 5
                    ICONST_0
                    ISTORE 4
                    GOTO L1
                L0: ALOAD 6
                    ILOAD 4
                    AALOAD
                    ASTORE_3
                    ALOAD_1     // Ljava/util/Set; set   (line 1058)
                    ALOAD_3     // Ljava/lang/String; token
                    INVOKEINTERFACE java.util.Set.add (Ljava/lang/Object;)Z
                    POP
                    IINC 4 1   (line 1057)
                L1: ILOAD 4
                    ILOAD 5
                    IF_ICMPLT L0
                    ALOAD_1     // Ljava/util/Set; set   (line 1060)
                    ARETURN
  end public static java.util.Set commaDelimitedListToSet(String)

  public static String collectionToDelimitedString(java.util.Collection, String, String, String):
                    ALOAD_0     // Ljava/util/Collection; coll   (line 1073)
                    INVOKESTATIC org.springframework.util.CollectionUtils.isEmpty (Ljava/util/Collection;)Z
                    IFEQ L0
                    LDC ""   (line 1074)
                    ARETURN
                L0: NEW java.lang.StringBuilder   (line 1076)
                    DUP
                    INVOKESPECIAL java.lang.StringBuilder.<init> ()V
                    ASTORE 4
                    ALOAD_0     // Ljava/util/Collection; coll   (line 1077)
                    INVOKEINTERFACE java.util.Collection.iterator ()Ljava/util/Iterator;
                    ASTORE 5
                    GOTO L2   (line 1078)
                L1: ALOAD 4     // Ljava/lang/StringBuilder; sb   (line 1079)
                    ALOAD_2     // Ljava/lang/String; prefix
                    INVOKEVIRTUAL java.lang.StringBuilder.append (Ljava/lang/String;)Ljava/lang/StringBuilder;
                    ALOAD 5     // Ljava/util/Iterator; it
                    INVOKEINTERFACE java.util.Iterator.next ()Ljava/lang/Object;
                    INVOKEVIRTUAL java.lang.StringBuilder.append (Ljava/lang/Object;)Ljava/lang/StringBuilder;
                    ALOAD_3     // Ljava/lang/String; suffix
                    INVOKEVIRTUAL java.lang.StringBuilder.append (Ljava/lang/String;)Ljava/lang/StringBuilder;
                    POP
                    ALOAD 5     // Ljava/util/Iterator; it   (line 1080)
                    INVOKEINTERFACE java.util.Iterator.hasNext ()Z
                    IFEQ L2
                    ALOAD 4     // Ljava/lang/StringBuilder; sb   (line 1081)
                    ALOAD_1     // Ljava/lang/String; delim
                    INVOKEVIRTUAL java.lang.StringBuilder.append (Ljava/lang/String;)Ljava/lang/StringBuilder;
                    POP
                L2: ALOAD 5     // Ljava/util/Iterator; it   (line 1078)
                    INVOKEINTERFACE java.util.Iterator.hasNext ()Z
                    IFNE L1
                    ALOAD 4     // Ljava/lang/StringBuilder; sb   (line 1084)
                    INVOKEVIRTUAL java.lang.StringBuilder.toString ()Ljava/lang/String;
                    ARETURN
  end public static String collectionToDelimitedString(java.util.Collection, String, String, String)

  public static String collectionToDelimitedString(java.util.Collection, String):
                    ALOAD_0     // Ljava/util/Collection; coll   (line 1095)
                    ALOAD_1     // Ljava/lang/String; delim
                    LDC ""
                    LDC ""
                    INVOKESTATIC org.springframework.util.StringUtils.collectionToDelimitedString (Ljava/util/Collection;Ljava/lang/String;Ljava/lang/String;Ljava/lang/String;)Ljava/lang/String;
                    ARETURN
  end public static String collectionToDelimitedString(java.util.Collection, String)

  public static String collectionToCommaDelimitedString(java.util.Collection):
                    ALOAD_0     // Ljava/util/Collection; coll   (line 1105)
                    LDC_W ","
                    INVOKESTATIC org.springframework.util.StringUtils.collectionToDelimitedString (Ljava/util/Collection;Ljava/lang/String;)Ljava/lang/String;
                    ARETURN
  end public static String collectionToCommaDelimitedString(java.util.Collection)

  public static String arrayToDelimitedString(Object[], String):
                    ALOAD_0     // [Ljava/lang/Object; arr   (line 1116)
                    INVOKESTATIC org.springframework.util.ObjectUtils.isEmpty ([Ljava/lang/Object;)Z
                    IFEQ L0
                    LDC ""   (line 1117)
                    ARETURN
                L0: ALOAD_0     // [Ljava/lang/Object; arr   (line 1119)
                    ARRAYLENGTH
                    ICONST_1
                    IF_ICMPNE L1
                    ALOAD_0     // [Ljava/lang/Object; arr   (line 1120)
                    ICONST_0
                    AALOAD
                    INVOKESTATIC org.springframework.util.ObjectUtils.nullSafeToString (Ljava/lang/Object;)Ljava/lang/String;
                    ARETURN
                L1: NEW java.lang.StringBuilder   (line 1122)
                    DUP
                    INVOKESPECIAL java.lang.StringBuilder.<init> ()V
                    ASTORE_2
                    ICONST_0   (line 1123)
                    ISTORE_3
                    GOTO L4
                L2: ILOAD_3     // I i   (line 1124)
                    IFLE L3
                    ALOAD_2     // Ljava/lang/StringBuilder; sb   (line 1125)
                    ALOAD_1     // Ljava/lang/String; delim
                    INVOKEVIRTUAL java.lang.StringBuilder.append (Ljava/lang/String;)Ljava/lang/StringBuilder;
                    POP
                L3: ALOAD_2     // Ljava/lang/StringBuilder; sb   (line 1127)
                    ALOAD_0     // [Ljava/lang/Object; arr
                    ILOAD_3     // I i
                    AALOAD
                    INVOKEVIRTUAL java.lang.StringBuilder.append (Ljava/lang/Object;)Ljava/lang/StringBuilder;
                    POP
                    IINC_3 1     // I i   (line 1123)
                L4: ILOAD_3     // I i
                    ALOAD_0     // [Ljava/lang/Object; arr
                    ARRAYLENGTH
                    IF_ICMPLT L2
                    ALOAD_2     // Ljava/lang/StringBuilder; sb   (line 1129)
                    INVOKEVIRTUAL java.lang.StringBuilder.toString ()Ljava/lang/String;
                    ARETURN
  end public static String arrayToDelimitedString(Object[], String)

  public static String arrayToCommaDelimitedString(Object[]):
                    ALOAD_0     // [Ljava/lang/Object; arr   (line 1139)
                    LDC_W ","
                    INVOKESTATIC org.springframework.util.StringUtils.arrayToDelimitedString ([Ljava/lang/Object;Ljava/lang/String;)Ljava/lang/String;
                    ARETURN
  end public static String arrayToCommaDelimitedString(Object[])

end public abstract class org.springframework.util.StringUtils

	at org.aspectj.bridge.MessageWriter.handleMessage(MessageWriter.java:47)
	at org.aspectj.weaver.tools.WeavingAdaptor$WeavingAdaptorMessageWriter.handleMessage(WeavingAdaptor.java:665)
	at org.aspectj.weaver.tools.WeavingAdaptor$WeavingAdaptorMessageHolder.handleMessage(WeavingAdaptor.java:615)
	at org.aspectj.weaver.bcel.BcelWeaver.weave(BcelWeaver.java:1752)
	at org.aspectj.weaver.bcel.BcelWeaver.weaveWithoutDump(BcelWeaver.java:1694)
	at org.aspectj.weaver.bcel.BcelWeaver.weaveAndNotify(BcelWeaver.java:1464)
	at org.aspectj.weaver.bcel.BcelWeaver.weave(BcelWeaver.java:1273)
	at org.aspectj.weaver.tools.WeavingAdaptor.getWovenBytes(WeavingAdaptor.java:394)
	at org.aspectj.weaver.tools.WeavingAdaptor.weaveClass(WeavingAdaptor.java:281)
	at org.aspectj.weaver.loadtime.Aj.preProcess(Aj.java:95)
	at org.aspectj.weaver.loadtime.ClassPreProcessorAgentAdapter.transform(ClassPreProcessorAgentAdapter.java:52)
	at sun.instrument.TransformerManager.transform(TransformerManager.java:188)
	at sun.instrument.InstrumentationImpl.transform(InstrumentationImpl.java:428)
	at java.lang.ClassLoader.defineClass1(Native Method)
	at java.lang.ClassLoader.defineClass(ClassLoader.java:760)
	at java.security.SecureClassLoader.defineClass(SecureClassLoader.java:142)
	at java.net.URLClassLoader.defineClass(URLClassLoader.java:467)
	at java.net.URLClassLoader.access$100(URLClassLoader.java:73)
	at java.net.URLClassLoader$1.run(URLClassLoader.java:368)
	at java.net.URLClassLoader$1.run(URLClassLoader.java:362)
	at java.security.AccessController.doPrivileged(Native Method)
	at java.net.URLClassLoader.findClass(URLClassLoader.java:361)
	at java.lang.ClassLoader.loadClass(ClassLoader.java:424)
	at sun.misc.Launcher$AppClassLoader.loadClass(Launcher.java:331)
	at java.lang.ClassLoader.loadClass(ClassLoader.java:357)
	at org.springframework.util.Assert.hasText(Assert.java:161)
	at org.springframework.core.env.PropertySource.<init>(PropertySource.java:68)
	at org.springframework.core.env.EnumerablePropertySource.<init>(EnumerablePropertySource.java:53)
	at org.springframework.core.env.MapPropertySource.<init>(MapPropertySource.java:31)
	at org.springframework.core.env.StandardEnvironment.customizePropertySources(StandardEnvironment.java:78)
	at org.springframework.core.env.AbstractEnvironment.<init>(AbstractEnvironment.java:117)
	at org.springframework.core.env.StandardEnvironment.<init>(StandardEnvironment.java:54)
	at org.springframework.context.support.AbstractApplicationContext.createEnvironment(AbstractApplicationContext.java:432)
	at org.springframework.context.support.AbstractApplicationContext.<init>(AbstractApplicationContext.java:227)
	at org.springframework.context.support.AbstractRefreshableApplicationContext.<init>(AbstractRefreshableApplicationContext.java:90)
	at org.springframework.context.support.AbstractRefreshableConfigApplicationContext.<init>(AbstractRefreshableConfigApplicationContext.java:59)
	at org.springframework.context.support.AbstractXmlApplicationContext.<init>(AbstractXmlApplicationContext.java:61)
	at org.springframework.context.support.ClassPathXmlApplicationContext.<init>(ClassPathXmlApplicationContext.java:136)
	at org.springframework.context.support.ClassPathXmlApplicationContext.<init>(ClassPathXmlApplicationContext.java:83)
	at com.curso.spring.springioc0007.Main.init(Main.java:29)
	at com.curso.spring.springioc0007.Main.main(Main.java:24)
---- System Properties ---
java.runtime.name=Java(TM) SE Runtime Environment
sun.boot.library.path=C:\Program Files\Java\jdk1.8.0_72\jre\bin
java.vm.version=25.72-b15
java.vm.vendor=Oracle Corporation
java.vendor.url=http://java.oracle.com/
path.separator=;
java.vm.name=Java HotSpot(TM) 64-Bit Server VM
file.encoding.pkg=sun.io
user.country=ES
user.script=
sun.java.launcher=SUN_STANDARD
sun.os.patch.level=
java.vm.specification.name=Java Virtual Machine Specification
user.dir=C:\Users\usuario\git\spring\aspectos\Ejemplos Relacionados\SpringIoC0007Maven
java.runtime.version=1.8.0_72-b15
java.awt.graphicsenv=sun.awt.Win32GraphicsEnvironment
java.endorsed.dirs=C:\Program Files\Java\jdk1.8.0_72\jre\lib\endorsed
os.arch=amd64
java.io.tmpdir=C:\Users\usuario\AppData\Local\Temp\
line.separator=

java.vm.specification.vendor=Oracle Corporation
user.variant=
os.name=Windows 10
sun.jnu.encoding=Cp1252
java.library.path=C:\Program Files\Java\jdk1.8.0_72\bin;C:\WINDOWS\Sun\Java\bin;C:\WINDOWS\system32;C:\WINDOWS;C:\ProgramData\Oracle\Java\javapath;C:\Program Files\CollabNet\Subversion Client;E:\bin\Sencha\Cmd\5.1.3.61;C:\Users\usuario\bin\Sencha\Cmd\5.1.3.61;C:\Program Files (x86)\Intel\iCLS Client\;C:\Program Files\Intel\iCLS Client\;C:\WINDOWS\system32;C:\WINDOWS;C:\WINDOWS\System32\Wbem;C:\WINDOWS\System32\WindowsPowerShell\v1.0\;C:\Program Files\Intel\Intel(R) Management Engine Components\DAL;C:\Program Files\Intel\Intel(R) Management Engine Components\IPT;C:\Program Files (x86)\Intel\Intel(R) Management Engine Components\DAL;C:\Program Files (x86)\Intel\Intel(R) Management Engine Components\IPT;C:\Program Files (x86)\Intel\OpenCL SDK\3.0\bin\x86;C:\Program Files (x86)\Intel\OpenCL SDK\3.0\bin\x64;C:\Program Files (x86)\sbt\\bin;C:\Program Files (x86)\Heroku\bin;C:\Program Files (x86)\git\cmd;C:\Program Files (x86)\QuickTime\QTSystem\;C:\HashiCorp\Vagrant\bin;C:\Program Files (x86)\scala\bin;C:\Program Files\nodejs\;C:\Users\usuario\AppData\Local\.meteor\;C:\Users\usuario\AppData\Roaming\npm;.
java.specification.name=Java Platform API Specification
java.class.version=52.0
sun.management.compiler=HotSpot 64-Bit Tiered Compilers
os.version=10.0
user.home=C:\Users\usuario
user.timezone=Europe/Paris
java.awt.printerjob=sun.awt.windows.WPrinterJob
file.encoding=Cp1252
java.specification.version=1.8
java.class.path=C:\Users\usuario\git\spring\aspectos\Ejemplos Relacionados\SpringIoC0007Maven\target\classes;C:\Users\usuario\.m2\repository\org\springframework\spring-context\3.1.2.RELEASE\spring-context-3.1.2.RELEASE.jar;C:\Users\usuario\.m2\repository\org\springframework\spring-aop\3.1.2.RELEASE\spring-aop-3.1.2.RELEASE.jar;C:\Users\usuario\.m2\repository\aopalliance\aopalliance\1.0\aopalliance-1.0.jar;C:\Users\usuario\.m2\repository\org\springframework\spring-beans\3.1.2.RELEASE\spring-beans-3.1.2.RELEASE.jar;C:\Users\usuario\.m2\repository\org\springframework\spring-core\3.1.2.RELEASE\spring-core-3.1.2.RELEASE.jar;C:\Users\usuario\.m2\repository\commons-logging\commons-logging\1.1.1\commons-logging-1.1.1.jar;C:\Users\usuario\.m2\repository\org\springframework\spring-expression\3.1.2.RELEASE\spring-expression-3.1.2.RELEASE.jar;C:\Users\usuario\.m2\repository\org\springframework\spring-asm\3.1.2.RELEASE\spring-asm-3.1.2.RELEASE.jar;C:\Users\usuario\.m2\repository\org\springframework\spring-aspects\3.1.2.RELEASE\spring-aspects-3.1.2.RELEASE.jar;C:\Users\usuario\.m2\repository\org\springframework\spring-context-support\3.1.2.RELEASE\spring-context-support-3.1.2.RELEASE.jar;.\..\aspectjweaver.jar
user.name=usuario
java.vm.specification.version=1.8
sun.java.command=com.curso.spring.springioc0007.Main
java.home=C:\Program Files\Java\jdk1.8.0_72\jre
sun.arch.data.model=64
user.language=es
java.specification.vendor=Oracle Corporation
awt.toolkit=sun.awt.windows.WToolkit
java.vm.info=mixed mode
java.version=1.8.0_72
java.ext.dirs=C:\Program Files\Java\jdk1.8.0_72\jre\lib\ext;C:\WINDOWS\Sun\Java\lib\ext
sun.boot.class.path=C:\Program Files\Java\jdk1.8.0_72\jre\lib\resources.jar;C:\Program Files\Java\jdk1.8.0_72\jre\lib\rt.jar;C:\Program Files\Java\jdk1.8.0_72\jre\lib\sunrsasign.jar;C:\Program Files\Java\jdk1.8.0_72\jre\lib\jsse.jar;C:\Program Files\Java\jdk1.8.0_72\jre\lib\jce.jar;C:\Program Files\Java\jdk1.8.0_72\jre\lib\charsets.jar;C:\Program Files\Java\jdk1.8.0_72\jre\lib\jfr.jar;C:\Program Files\Java\jdk1.8.0_72\jre\classes
java.vendor=Oracle Corporation
file.separator=\
java.vendor.url.bug=http://bugreport.sun.com/bugreport/
sun.io.unicode.encoding=UnicodeLittle
sun.cpu.endian=little
sun.desktop=windows
sun.cpu.isalist=amd64
---- Command Line ---
Empty
---- Full Classpath ---
Empty
---- Compiler Messages ---
Empty
---- org.aspectj.weaver.ltw.LTWWorld@28c97a5 ----
Class loader:
sun.misc.Launcher$AppClassLoader@18b4aac2
Class loader parent:
sun.misc.Launcher$ExtClassLoader@722c41f4
Shadow mungers:
(around(extraFlags: 3): ((((((((((within(@org.springframework.cache.annotation.CacheEvict *) && execution(public * @org.springframework.cache.annotation.CacheEvict *.*(..))) && this(BindingTypePattern(java.lang.Object, 0))) && persingleton(org.springframework.cache.aspectj.AnnotationCacheAspect)) || (((within(@org.springframework.cache.annotation.Caching *) && execution(public * @org.springframework.cache.annotation.Caching *.*(..))) && this(BindingTypePattern(java.lang.Object, 0))) && persingleton(org.springframework.cache.aspectj.AnnotationCacheAspect))) || (((within(@org.springframework.cache.annotation.CachePut *) && execution(public * @org.springframework.cache.annotation.CachePut *.*(..))) && this(BindingTypePattern(java.lang.Object, 0))) && persingleton(org.springframework.cache.aspectj.AnnotationCacheAspect))) || (((within(@org.springframework.cache.annotation.Cacheable *) && execution(public * @org.springframework.cache.annotation.Cacheable *.*(..))) && this(BindingTypePattern(java.lang.Object, 0))) && persingleton(org.springframework.cache.aspectj.AnnotationCacheAspect))) || ((execution(@org.springframework.cache.annotation.Caching * *(..)) && this(BindingTypePattern(java.lang.Object, 0))) && persingleton(org.springframework.cache.aspectj.AnnotationCacheAspect))) || ((execution(@org.springframework.cache.annotation.Cacheable * *(..)) && this(BindingTypePattern(java.lang.Object, 0))) && persingleton(org.springframework.cache.aspectj.AnnotationCacheAspect))) || ((execution(@org.springframework.cache.annotation.CacheEvict * *(..)) && this(BindingTypePattern(java.lang.Object, 0))) && persingleton(org.springframework.cache.aspectj.AnnotationCacheAspect))) || ((execution(@org.springframework.cache.annotation.CachePut * *(..)) && this(BindingTypePattern(java.lang.Object, 0))) && persingleton(org.springframework.cache.aspectj.AnnotationCacheAspect)))->java.lang.Object org.springframework.cache.aspectj.AbstractCacheAspect.ajc$around$org_springframework_cache_aspectj_AbstractCacheAspect$1$2bc714b5(java.lang.Object, org.aspectj.runtime.internal.AroundClosure, org.aspectj.lang.JoinPoint))
(around(extraFlags: 5): ((execution(@org.springframework.scheduling.annotation.Async (void || java.util.concurrent.Future+) *(..)) && persingleton(org.springframework.scheduling.aspectj.AnnotationAsyncExecutionAspect)) || (execution((void || java.util.concurrent.Future+) @org.springframework.scheduling.annotation.Async *.*(..)) && persingleton(org.springframework.scheduling.aspectj.AnnotationAsyncExecutionAspect)))->java.lang.Object org.springframework.scheduling.aspectj.AbstractAsyncExecutionAspect.ajc$around$org_springframework_scheduling_aspectj_AbstractAsyncExecutionAspect$1$6c004c3e(org.aspectj.runtime.internal.AroundClosure, org.aspectj.lang.JoinPoint$StaticPart))
org.aspectj.weaver.Checker@5abff562
org.aspectj.weaver.Checker@12140c1d
(before(extraFlags: 4): ((((within(@org.springframework.transaction.annotation.Transactional *) && execution(public * @org.springframework.transaction.annotation.Transactional *.*(..))) && this(BindingTypePattern(java.lang.Object, 0))) && persingleton(org.springframework.transaction.aspectj.AnnotationTransactionAspect)) || ((execution(@org.springframework.transaction.annotation.Transactional * *(..)) && this(BindingTypePattern(java.lang.Object, 0))) && persingleton(org.springframework.transaction.aspectj.AnnotationTransactionAspect)))->void org.springframework.transaction.aspectj.AbstractTransactionAspect.ajc$before$org_springframework_transaction_aspectj_AbstractTransactionAspect$1$2a73e96c(java.lang.Object, org.aspectj.lang.JoinPoint$StaticPart))
(afterThrowing(extraFlags: 1): ((((within(@org.springframework.transaction.annotation.Transactional *) && execution(public * @org.springframework.transaction.annotation.Transactional *.*(..))) && this(BindingTypePattern(java.lang.Object, 0))) && persingleton(org.springframework.transaction.aspectj.AnnotationTransactionAspect)) || ((execution(@org.springframework.transaction.annotation.Transactional * *(..)) && this(BindingTypePattern(java.lang.Object, 0))) && persingleton(org.springframework.transaction.aspectj.AnnotationTransactionAspect)))->void org.springframework.transaction.aspectj.AbstractTransactionAspect.ajc$afterThrowing$org_springframework_transaction_aspectj_AbstractTransactionAspect$2$2a73e96c(java.lang.Object, java.lang.Throwable))
(afterReturning: ((((within(@org.springframework.transaction.annotation.Transactional *) && execution(public * @org.springframework.transaction.annotation.Transactional *.*(..))) && this(BindingTypePattern(java.lang.Object, 0))) && persingleton(org.springframework.transaction.aspectj.AnnotationTransactionAspect)) || ((execution(@org.springframework.transaction.annotation.Transactional * *(..)) && this(BindingTypePattern(java.lang.Object, 0))) && persingleton(org.springframework.transaction.aspectj.AnnotationTransactionAspect)))->void org.springframework.transaction.aspectj.AbstractTransactionAspect.ajc$afterReturning$org_springframework_transaction_aspectj_AbstractTransactionAspect$3$2a73e96c(java.lang.Object))
(after: ((((within(@org.springframework.transaction.annotation.Transactional *) && execution(public * @org.springframework.transaction.annotation.Transactional *.*(..))) && this(BindingTypePattern(java.lang.Object, 0))) && persingleton(org.springframework.transaction.aspectj.AnnotationTransactionAspect)) || ((execution(@org.springframework.transaction.annotation.Transactional * *(..)) && this(BindingTypePattern(java.lang.Object, 0))) && persingleton(org.springframework.transaction.aspectj.AnnotationTransactionAspect)))->void org.springframework.transaction.aspectj.AbstractTransactionAspect.ajc$after$org_springframework_transaction_aspectj_AbstractTransactionAspect$4$2a73e96c(java.lang.Object))
(before: (((((initialization(org.springframework.beans.factory.aspectj.ConfigurableObject.new(..)) && initialization(org.springframework.beans.factory.aspectj.ConfigurableObject+.new(..))) && this(BindingTypePattern(java.lang.Object, 0))) && @this(org.springframework.beans.factory.annotation.Configurable)) && if(boolean org.springframework.beans.factory.aspectj.AnnotationBeanConfigurerAspect.ajc$if$bb0(org.springframework.beans.factory.annotation.Configurable))) && persingleton(org.springframework.beans.factory.aspectj.AnnotationBeanConfigurerAspect))->void org.springframework.beans.factory.aspectj.AbstractDependencyInjectionAspect.ajc$before$org_springframework_beans_factory_aspectj_AbstractDependencyInjectionAspect$1$e854fa65(java.lang.Object))
(afterReturning: (((((initialization(org.springframework.beans.factory.aspectj.ConfigurableObject+.new(..)) && this(BindingTypePattern(java.lang.Object, 0))) && @this(org.springframework.beans.factory.annotation.Configurable)) && !(@this(org.springframework.beans.factory.annotation.Configurable) && if(boolean org.springframework.beans.factory.aspectj.AnnotationBeanConfigurerAspect.ajc$if$bb0(org.springframework.beans.factory.annotation.Configurable)))) && if(boolean org.springframework.beans.factory.aspectj.AbstractDependencyInjectionAspect.ajc$if$6f1(org.aspectj.lang.JoinPoint))) && persingleton(org.springframework.beans.factory.aspectj.AnnotationBeanConfigurerAspect))->void org.springframework.beans.factory.aspectj.AbstractDependencyInjectionAspect.ajc$afterReturning$org_springframework_beans_factory_aspectj_AbstractDependencyInjectionAspect$2$1ea6722c(java.lang.Object))
(afterReturning: (((execution(java.lang.Object org.springframework.beans.factory.aspectj.AbstractInterfaceDrivenDependencyInjectionAspect$ConfigurableDeserializationSupport+.readResolve()) && this(BindingTypePattern(java.lang.Object, 0))) && @this(org.springframework.beans.factory.annotation.Configurable)) && persingleton(org.springframework.beans.factory.aspectj.AnnotationBeanConfigurerAspect))->void org.springframework.beans.factory.aspectj.AbstractDependencyInjectionAspect.ajc$afterReturning$org_springframework_beans_factory_aspectj_AbstractDependencyInjectionAspect$3$6aa27052(java.lang.Object))
Type mungers:
(BcelTypeMunger ResolvedTypeMunger(Method, java.lang.Object org.springframework.beans.factory.aspectj.AbstractInterfaceDrivenDependencyInjectionAspect$ConfigurableDeserializationSupport.readResolve()))
(BcelTypeMunger ExposeTypeMunger(java.lang.Object))
(BcelTypeMunger ExposeTypeMunger(java.lang.Object))
(BcelTypeMunger ExposeTypeMunger(java.lang.Object))
(BcelTypeMunger ExposeTypeMunger(org.springframework.beans.factory.aspectj.ConfigurableObject))
(BcelTypeMunger ExposeTypeMunger(org.springframework.beans.factory.aspectj.AbstractInterfaceDrivenDependencyInjectionAspect$ConfigurableDeserializationSupport))
Late Type mungers:
Empty
