---- AspectJ Properties ---
AspectJ Compiler 1.6.2 built on Saturday Oct 4, 2008 at 05:47:07 GMT
---- Dump Properties ---
Dump file: ajcore.20160604.114035.836.txt
Dump reason: abort
Dump on exception: true
Dump at exit condition: abort
---- System Properties ---
java.runtime.name=Java(TM) SE Runtime Environment
sun.boot.library.path=C:\Program Files\Java\jdk1.8.0_72\jre\bin
java.vm.version=25.72-b15
java.vm.vendor=Oracle Corporation
java.vendor.url=http://java.oracle.com/
path.separator=;
java.vm.name=Java HotSpot(TM) 64-Bit Server VM
file.encoding.pkg=sun.io
user.country=ES
user.script=
sun.java.launcher=SUN_STANDARD
sun.os.patch.level=
java.vm.specification.name=Java Virtual Machine Specification
user.dir=C:\Users\usuario\git\spring\aspectos\Ejemplos Relacionados\SpringIoC0007Maven
java.runtime.version=1.8.0_72-b15
java.awt.graphicsenv=sun.awt.Win32GraphicsEnvironment
java.endorsed.dirs=C:\Program Files\Java\jdk1.8.0_72\jre\lib\endorsed
os.arch=amd64
java.io.tmpdir=C:\Users\usuario\AppData\Local\Temp\
line.separator=

java.vm.specification.vendor=Oracle Corporation
user.variant=
os.name=Windows 10
sun.jnu.encoding=Cp1252
java.library.path=C:\Program Files\Java\jdk1.8.0_72\bin;C:\WINDOWS\Sun\Java\bin;C:\WINDOWS\system32;C:\WINDOWS;C:\ProgramData\Oracle\Java\javapath;C:\Program Files\CollabNet\Subversion Client;E:\bin\Sencha\Cmd\5.1.3.61;C:\Users\usuario\bin\Sencha\Cmd\5.1.3.61;C:\Program Files (x86)\Intel\iCLS Client\;C:\Program Files\Intel\iCLS Client\;C:\WINDOWS\system32;C:\WINDOWS;C:\WINDOWS\System32\Wbem;C:\WINDOWS\System32\WindowsPowerShell\v1.0\;C:\Program Files\Intel\Intel(R) Management Engine Components\DAL;C:\Program Files\Intel\Intel(R) Management Engine Components\IPT;C:\Program Files (x86)\Intel\Intel(R) Management Engine Components\DAL;C:\Program Files (x86)\Intel\Intel(R) Management Engine Components\IPT;C:\Program Files (x86)\Intel\OpenCL SDK\3.0\bin\x86;C:\Program Files (x86)\Intel\OpenCL SDK\3.0\bin\x64;C:\Program Files (x86)\sbt\\bin;C:\Program Files (x86)\Heroku\bin;C:\Program Files (x86)\git\cmd;C:\Program Files (x86)\QuickTime\QTSystem\;C:\HashiCorp\Vagrant\bin;C:\Program Files (x86)\scala\bin;C:\Program Files\nodejs\;C:\Users\usuario\AppData\Local\.meteor\;C:\Users\usuario\AppData\Roaming\npm;.
java.specification.name=Java Platform API Specification
java.class.version=52.0
sun.management.compiler=HotSpot 64-Bit Tiered Compilers
os.version=10.0
user.home=C:\Users\usuario
user.timezone=Europe/Paris
java.awt.printerjob=sun.awt.windows.WPrinterJob
file.encoding=Cp1252
java.specification.version=1.8
java.class.path=C:\Users\usuario\git\spring\aspectos\Ejemplos Relacionados\SpringIoC0007Maven\target\classes;C:\Users\usuario\.m2\repository\org\springframework\spring-context\3.1.2.RELEASE\spring-context-3.1.2.RELEASE.jar;C:\Users\usuario\.m2\repository\org\springframework\spring-aop\3.1.2.RELEASE\spring-aop-3.1.2.RELEASE.jar;C:\Users\usuario\.m2\repository\aopalliance\aopalliance\1.0\aopalliance-1.0.jar;C:\Users\usuario\.m2\repository\org\springframework\spring-beans\3.1.2.RELEASE\spring-beans-3.1.2.RELEASE.jar;C:\Users\usuario\.m2\repository\org\springframework\spring-core\3.1.2.RELEASE\spring-core-3.1.2.RELEASE.jar;C:\Users\usuario\.m2\repository\commons-logging\commons-logging\1.1.1\commons-logging-1.1.1.jar;C:\Users\usuario\.m2\repository\org\springframework\spring-expression\3.1.2.RELEASE\spring-expression-3.1.2.RELEASE.jar;C:\Users\usuario\.m2\repository\org\springframework\spring-asm\3.1.2.RELEASE\spring-asm-3.1.2.RELEASE.jar;C:\Users\usuario\.m2\repository\org\springframework\spring-aspects\3.1.2.RELEASE\spring-aspects-3.1.2.RELEASE.jar;C:\Users\usuario\.m2\repository\org\springframework\spring-context-support\3.1.2.RELEASE\spring-context-support-3.1.2.RELEASE.jar;.\..\aspectjweaver.jar
user.name=usuario
java.vm.specification.version=1.8
sun.java.command=com.curso.spring.springioc0007.Main
java.home=C:\Program Files\Java\jdk1.8.0_72\jre
sun.arch.data.model=64
user.language=es
java.specification.vendor=Oracle Corporation
awt.toolkit=sun.awt.windows.WToolkit
java.vm.info=mixed mode
java.version=1.8.0_72
java.ext.dirs=C:\Program Files\Java\jdk1.8.0_72\jre\lib\ext;C:\WINDOWS\Sun\Java\lib\ext
sun.boot.class.path=C:\Program Files\Java\jdk1.8.0_72\jre\lib\resources.jar;C:\Program Files\Java\jdk1.8.0_72\jre\lib\rt.jar;C:\Program Files\Java\jdk1.8.0_72\jre\lib\sunrsasign.jar;C:\Program Files\Java\jdk1.8.0_72\jre\lib\jsse.jar;C:\Program Files\Java\jdk1.8.0_72\jre\lib\jce.jar;C:\Program Files\Java\jdk1.8.0_72\jre\lib\charsets.jar;C:\Program Files\Java\jdk1.8.0_72\jre\lib\jfr.jar;C:\Program Files\Java\jdk1.8.0_72\jre\classes
java.vendor=Oracle Corporation
file.separator=\
java.vendor.url.bug=http://bugreport.sun.com/bugreport/
sun.io.unicode.encoding=UnicodeLittle
sun.cpu.endian=little
sun.desktop=windows
sun.cpu.isalist=amd64
---- Command Line ---
Empty
---- Full Classpath ---
Empty
---- Compiler Messages ---
info AspectJ Weaver Version 1.6.2 built on Saturday Oct 4, 2008 at 05:47:07 GMT
info register classloader sun.misc.Launcher$AppClassLoader@18b4aac2
info using configuration file:/C:/Users/usuario/.m2/repository/org/springframework/spring-aspects/3.1.2.RELEASE/spring-aspects-3.1.2.RELEASE.jar!/META-INF/aop.xml
debug weaving 'org.springframework.core.convert.support.GenericConversionService'
abort trouble in: 
public class org.springframework.core.convert.support.GenericConversionService extends java.lang.Object implements org.springframework.core.convert.support.ConfigurableConversionService:
  private static final org.springframework.core.convert.converter.GenericConverter NO_OP_CONVERTER
  private static final org.springframework.core.convert.converter.GenericConverter NO_MATCH
  private final java.util.Map converters [Signature(Ljava/util/Map<Ljava/lang/Class<*>;Ljava/util/Map<Ljava/lang/Class<*>;Lorg/springframework/core/convert/support/GenericConversionService$MatchableConverters;>;>;)]
  private final java.util.Map converterCache [Signature(Ljava/util/Map<Lorg/springframework/core/convert/support/GenericConversionService$ConverterCacheKey;Lorg/springframework/core/convert/converter/GenericConverter;>;)]
  static void <clinit>():
    staticinitialization(void org.springframework.core.convert.support.GenericConversionService.<clinit>())
    |               NEW org.springframework.core.convert.support.GenericConversionService$1   (line 58)
    |               DUP
    |               INVOKESPECIAL org.springframework.core.convert.support.GenericConversionService$1.<init> ()V
    |               PUTSTATIC org.springframework.core.convert.support.GenericConversionService.NO_OP_CONVERTER Lorg/springframework/core/convert/converter/GenericConverter;
    |               NEW org.springframework.core.convert.support.GenericConversionService$2   (line 70)
    |               DUP
    |               INVOKESPECIAL org.springframework.core.convert.support.GenericConversionService$2.<init> ()V
    |               PUTSTATIC org.springframework.core.convert.support.GenericConversionService.NO_MATCH Lorg/springframework/core/convert/converter/GenericConverter;
    |               RETURN   (line 56)
    staticinitialization(void org.springframework.core.convert.support.GenericConversionService.<clinit>())
  end static void <clinit>()

  public void <init>():
                    ALOAD_0     // Lorg/springframework/core/convert/support/GenericConversionService; this   (line 56)
                    INVOKESPECIAL java.lang.Object.<init> ()V
    constructor-execution(void org.springframework.core.convert.support.GenericConversionService.<init>())
    |               ALOAD_0     // Lorg/springframework/core/convert/support/GenericConversionService; this   (line 83)
    |               NEW java.util.HashMap   (line 84)
    |               DUP
    |               BIPUSH 36
    |               INVOKESPECIAL java.util.HashMap.<init> (I)V
    |               PUTFIELD org.springframework.core.convert.support.GenericConversionService.converters Ljava/util/Map;
    |               ALOAD_0     // Lorg/springframework/core/convert/support/GenericConversionService; this   (line 86)
    |               NEW java.util.concurrent.ConcurrentHashMap   (line 87)
    |               DUP
    |               INVOKESPECIAL java.util.concurrent.ConcurrentHashMap.<init> ()V
    |               PUTFIELD org.springframework.core.convert.support.GenericConversionService.converterCache Ljava/util/Map;
    |               RETURN   (line 56)
    constructor-execution(void org.springframework.core.convert.support.GenericConversionService.<init>())
  end public void <init>()

  public void addConverter(org.springframework.core.convert.converter.Converter):
                    ALOAD_0     // Lorg/springframework/core/convert/support/GenericConversionService; this   (line 93)
                    ALOAD_1     // Lorg/springframework/core/convert/converter/Converter; converter
                    LDC org.springframework.core.convert.converter.Converter
                    INVOKESPECIAL org.springframework.core.convert.support.GenericConversionService.getRequiredTypeInfo (Ljava/lang/Object;Ljava/lang/Class;)Lorg/springframework/core/convert/converter/GenericConverter$ConvertiblePair;
                    ASTORE_2
                    ALOAD_2     // Lorg/springframework/core/convert/converter/GenericConverter$ConvertiblePair; typeInfo   (line 94)
                    IFNONNULL L0
                    NEW java.lang.IllegalArgumentException   (line 95)
                    DUP
                    LDC "Unable to the determine sourceType <S> and targetType <T> which your Converter<S, T> converts between; declare these generic types."
                    INVOKESPECIAL java.lang.IllegalArgumentException.<init> (Ljava/lang/String;)V
                    ATHROW
                L0: ALOAD_0     // Lorg/springframework/core/convert/support/GenericConversionService; this   (line 98)
                    NEW org.springframework.core.convert.support.GenericConversionService$ConverterAdapter
                    DUP
                    ALOAD_0     // Lorg/springframework/core/convert/support/GenericConversionService; this
                    ALOAD_2     // Lorg/springframework/core/convert/converter/GenericConverter$ConvertiblePair; typeInfo
                    ALOAD_1     // Lorg/springframework/core/convert/converter/Converter; converter
                    INVOKESPECIAL org.springframework.core.convert.support.GenericConversionService$ConverterAdapter.<init> (Lorg/springframework/core/convert/support/GenericConversionService;Lorg/springframework/core/convert/converter/GenericConverter$ConvertiblePair;Lorg/springframework/core/convert/converter/Converter;)V
                    INVOKEVIRTUAL org.springframework.core.convert.support.GenericConversionService.addConverter (Lorg/springframework/core/convert/converter/GenericConverter;)V
                    RETURN   (line 99)
  end public void addConverter(org.springframework.core.convert.converter.Converter)

  public void addConverter(Class, Class, org.springframework.core.convert.converter.Converter):
                    NEW org.springframework.core.convert.converter.GenericConverter$ConvertiblePair   (line 102)
                    DUP
                    ALOAD_1     // Ljava/lang/Class; sourceType
                    ALOAD_2     // Ljava/lang/Class; targetType
                    INVOKESPECIAL org.springframework.core.convert.converter.GenericConverter$ConvertiblePair.<init> (Ljava/lang/Class;Ljava/lang/Class;)V
                    ASTORE 4
                    ALOAD_0     // Lorg/springframework/core/convert/support/GenericConversionService; this   (line 103)
                    NEW org.springframework.core.convert.support.GenericConversionService$ConverterAdapter
                    DUP
                    ALOAD_0     // Lorg/springframework/core/convert/support/GenericConversionService; this
                    ALOAD 4     // Lorg/springframework/core/convert/converter/GenericConverter$ConvertiblePair; typeInfo
                    ALOAD_3     // Lorg/springframework/core/convert/converter/Converter; converter
                    INVOKESPECIAL org.springframework.core.convert.support.GenericConversionService$ConverterAdapter.<init> (Lorg/springframework/core/convert/support/GenericConversionService;Lorg/springframework/core/convert/converter/GenericConverter$ConvertiblePair;Lorg/springframework/core/convert/converter/Converter;)V
                    INVOKEVIRTUAL org.springframework.core.convert.support.GenericConversionService.addConverter (Lorg/springframework/core/convert/converter/GenericConverter;)V
                    RETURN   (line 104)
  end public void addConverter(Class, Class, org.springframework.core.convert.converter.Converter)

  public void addConverter(org.springframework.core.convert.converter.GenericConverter):
                    ALOAD_1     // Lorg/springframework/core/convert/converter/GenericConverter; converter   (line 107)
                    INVOKEINTERFACE org.springframework.core.convert.converter.GenericConverter.getConvertibleTypes ()Ljava/util/Set;
                    ASTORE_2
                    ALOAD_2     // Ljava/util/Set; convertibleTypes   (line 108)
                    INVOKEINTERFACE java.util.Set.iterator ()Ljava/util/Iterator;
                    ASTORE 4
                    GOTO L1
                L0: ALOAD 4
                    INVOKEINTERFACE java.util.Iterator.next ()Ljava/lang/Object;
                    CHECKCAST org.springframework.core.convert.converter.GenericConverter$ConvertiblePair
                    ASTORE_3
                    ALOAD_0     // Lorg/springframework/core/convert/support/GenericConversionService; this   (line 109)
                    ALOAD_3     // Lorg/springframework/core/convert/converter/GenericConverter$ConvertiblePair; convertibleType
                    INVOKEVIRTUAL org.springframework.core.convert.converter.GenericConverter$ConvertiblePair.getSourceType ()Ljava/lang/Class;
                    ALOAD_3     // Lorg/springframework/core/convert/converter/GenericConverter$ConvertiblePair; convertibleType
                    INVOKEVIRTUAL org.springframework.core.convert.converter.GenericConverter$ConvertiblePair.getTargetType ()Ljava/lang/Class;
                    INVOKESPECIAL org.springframework.core.convert.support.GenericConversionService.getMatchableConverters (Ljava/lang/Class;Ljava/lang/Class;)Lorg/springframework/core/convert/support/GenericConversionService$MatchableConverters;
                    ALOAD_1     // Lorg/springframework/core/convert/converter/GenericConverter; converter
                    INVOKEVIRTUAL org.springframework.core.convert.support.GenericConversionService$MatchableConverters.add (Lorg/springframework/core/convert/converter/GenericConverter;)V
                L1: ALOAD 4   (line 108)
                    INVOKEINTERFACE java.util.Iterator.hasNext ()Z
                    IFNE L0
                    ALOAD_0     // Lorg/springframework/core/convert/support/GenericConversionService; this   (line 111)
                    INVOKESPECIAL org.springframework.core.convert.support.GenericConversionService.invalidateCache ()V
                    RETURN   (line 112)
  end public void addConverter(org.springframework.core.convert.converter.GenericConverter)

  public void addConverterFactory(org.springframework.core.convert.converter.ConverterFactory):
                    ALOAD_0     // Lorg/springframework/core/convert/support/GenericConversionService; this   (line 115)
                    ALOAD_1     // Lorg/springframework/core/convert/converter/ConverterFactory; converterFactory
                    LDC org.springframework.core.convert.converter.ConverterFactory
                    INVOKESPECIAL org.springframework.core.convert.support.GenericConversionService.getRequiredTypeInfo (Ljava/lang/Object;Ljava/lang/Class;)Lorg/springframework/core/convert/converter/GenericConverter$ConvertiblePair;
                    ASTORE_2
                    ALOAD_2     // Lorg/springframework/core/convert/converter/GenericConverter$ConvertiblePair; typeInfo   (line 116)
                    IFNONNULL L0
                    NEW java.lang.IllegalArgumentException   (line 117)
                    DUP
                    LDC "Unable to the determine sourceType <S> and targetRangeType R which your ConverterFactory<S, R> converts between; declare these generic types."
                    INVOKESPECIAL java.lang.IllegalArgumentException.<init> (Ljava/lang/String;)V
                    ATHROW
                L0: ALOAD_0     // Lorg/springframework/core/convert/support/GenericConversionService; this   (line 120)
                    NEW org.springframework.core.convert.support.GenericConversionService$ConverterFactoryAdapter
                    DUP
                    ALOAD_0     // Lorg/springframework/core/convert/support/GenericConversionService; this
                    ALOAD_2     // Lorg/springframework/core/convert/converter/GenericConverter$ConvertiblePair; typeInfo
                    ALOAD_1     // Lorg/springframework/core/convert/converter/ConverterFactory; converterFactory
                    INVOKESPECIAL org.springframework.core.convert.support.GenericConversionService$ConverterFactoryAdapter.<init> (Lorg/springframework/core/convert/support/GenericConversionService;Lorg/springframework/core/convert/converter/GenericConverter$ConvertiblePair;Lorg/springframework/core/convert/converter/ConverterFactory;)V
                    INVOKEVIRTUAL org.springframework.core.convert.support.GenericConversionService.addConverter (Lorg/springframework/core/convert/converter/GenericConverter;)V
                    RETURN   (line 121)
  end public void addConverterFactory(org.springframework.core.convert.converter.ConverterFactory)

  public void removeConvertible(Class, Class):
                    ALOAD_0     // Lorg/springframework/core/convert/support/GenericConversionService; this   (line 124)
                    ALOAD_1     // Ljava/lang/Class; sourceType
                    INVOKESPECIAL org.springframework.core.convert.support.GenericConversionService.getSourceConverterMap (Ljava/lang/Class;)Ljava/util/Map;
                    ALOAD_2     // Ljava/lang/Class; targetType
                    INVOKEINTERFACE java.util.Map.remove (Ljava/lang/Object;)Ljava/lang/Object;
                    POP
                    ALOAD_0     // Lorg/springframework/core/convert/support/GenericConversionService; this   (line 125)
                    INVOKESPECIAL org.springframework.core.convert.support.GenericConversionService.invalidateCache ()V
                    RETURN   (line 126)
  end public void removeConvertible(Class, Class)

  public boolean canConvert(Class, Class):
                    ALOAD_2     // Ljava/lang/Class; targetType   (line 132)
                    IFNONNULL L0
                    NEW java.lang.IllegalArgumentException   (line 133)
                    DUP
                    LDC "The targetType to convert to cannot be null"
                    INVOKESPECIAL java.lang.IllegalArgumentException.<init> (Ljava/lang/String;)V
                    ATHROW
                L0: ALOAD_0     // Lorg/springframework/core/convert/support/GenericConversionService; this   (line 135)
                    ALOAD_1     // Ljava/lang/Class; sourceType
                    IFNULL L1
                    ALOAD_1     // Ljava/lang/Class; sourceType
                    INVOKESTATIC org.springframework.core.convert.TypeDescriptor.valueOf (Ljava/lang/Class;)Lorg/springframework/core/convert/TypeDescriptor;
                    GOTO L2
                L1: ACONST_NULL
                L2: ALOAD_2     // Ljava/lang/Class; targetType
                    INVOKESTATIC org.springframework.core.convert.TypeDescriptor.valueOf (Ljava/lang/Class;)Lorg/springframework/core/convert/TypeDescriptor;
                    INVOKEVIRTUAL org.springframework.core.convert.support.GenericConversionService.canConvert (Lorg/springframework/core/convert/TypeDescriptor;Lorg/springframework/core/convert/TypeDescriptor;)Z
                    IRETURN
  end public boolean canConvert(Class, Class)

  public boolean canConvert(org.springframework.core.convert.TypeDescriptor, org.springframework.core.convert.TypeDescriptor):
                    ALOAD_2     // Lorg/springframework/core/convert/TypeDescriptor; targetType   (line 139)
                    IFNONNULL L0
                    NEW java.lang.IllegalArgumentException   (line 140)
                    DUP
                    LDC "The targetType to convert to cannot be null"
                    INVOKESPECIAL java.lang.IllegalArgumentException.<init> (Ljava/lang/String;)V
                    ATHROW
                L0: ALOAD_1     // Lorg/springframework/core/convert/TypeDescriptor; sourceType   (line 142)
                    IFNONNULL L1
                    ICONST_1   (line 143)
                    IRETURN
                L1: ALOAD_0     // Lorg/springframework/core/convert/support/GenericConversionService; this   (line 145)
                    ALOAD_1     // Lorg/springframework/core/convert/TypeDescriptor; sourceType
                    ALOAD_2     // Lorg/springframework/core/convert/TypeDescriptor; targetType
                    INVOKEVIRTUAL org.springframework.core.convert.support.GenericConversionService.getConverter (Lorg/springframework/core/convert/TypeDescriptor;Lorg/springframework/core/convert/TypeDescriptor;)Lorg/springframework/core/convert/converter/GenericConverter;
                    ASTORE_3
                    ALOAD_3     // Lorg/springframework/core/convert/converter/GenericConverter; converter   (line 146)
                    IFNULL L2
                    ICONST_1
                    IRETURN
                L2: ICONST_0
                    IRETURN
  end public boolean canConvert(org.springframework.core.convert.TypeDescriptor, org.springframework.core.convert.TypeDescriptor)

  public Object convert(Object, Class):
                    ALOAD_2     // Ljava/lang/Class; targetType   (line 151)
                    IFNONNULL L0
                    NEW java.lang.IllegalArgumentException   (line 152)
                    DUP
                    LDC "The targetType to convert to cannot be null"
                    INVOKESPECIAL java.lang.IllegalArgumentException.<init> (Ljava/lang/String;)V
                    ATHROW
                L0: ALOAD_0     // Lorg/springframework/core/convert/support/GenericConversionService; this   (line 154)
                    ALOAD_1     // Ljava/lang/Object; source
                    ALOAD_1     // Ljava/lang/Object; source
                    INVOKESTATIC org.springframework.core.convert.TypeDescriptor.forObject (Ljava/lang/Object;)Lorg/springframework/core/convert/TypeDescriptor;
                    ALOAD_2     // Ljava/lang/Class; targetType
                    INVOKESTATIC org.springframework.core.convert.TypeDescriptor.valueOf (Ljava/lang/Class;)Lorg/springframework/core/convert/TypeDescriptor;
                    INVOKEVIRTUAL org.springframework.core.convert.support.GenericConversionService.convert (Ljava/lang/Object;Lorg/springframework/core/convert/TypeDescriptor;Lorg/springframework/core/convert/TypeDescriptor;)Ljava/lang/Object;
                    ARETURN
  end public Object convert(Object, Class)

  public Object convert(Object, org.springframework.core.convert.TypeDescriptor, org.springframework.core.convert.TypeDescriptor):
                    ALOAD_3     // Lorg/springframework/core/convert/TypeDescriptor; targetType   (line 158)
                    IFNONNULL L0
                    NEW java.lang.IllegalArgumentException   (line 159)
                    DUP
                    LDC "The targetType to convert to cannot be null"
                    INVOKESPECIAL java.lang.IllegalArgumentException.<init> (Ljava/lang/String;)V
                    ATHROW
                L0: ALOAD_2     // Lorg/springframework/core/convert/TypeDescriptor; sourceType   (line 161)
                    IFNONNULL L3
                    ALOAD_1     // Ljava/lang/Object; source   (line 162)
                    IFNONNULL L1
                    ICONST_1
                    GOTO L2
                L1: ICONST_0
                L2: LDC "The source must be [null] if sourceType == [null]"
                    INVOKESTATIC org.springframework.util.Assert.isTrue (ZLjava/lang/String;)V
                    ALOAD_0     // Lorg/springframework/core/convert/support/GenericConversionService; this   (line 163)
                    ALOAD_2     // Lorg/springframework/core/convert/TypeDescriptor; sourceType
                    ALOAD_3     // Lorg/springframework/core/convert/TypeDescriptor; targetType
                    ALOAD_0     // Lorg/springframework/core/convert/support/GenericConversionService; this
                    ALOAD_2     // Lorg/springframework/core/convert/TypeDescriptor; sourceType
                    ALOAD_3     // Lorg/springframework/core/convert/TypeDescriptor; targetType
                    INVOKEVIRTUAL org.springframework.core.convert.support.GenericConversionService.convertNullSource (Lorg/springframework/core/convert/TypeDescriptor;Lorg/springframework/core/convert/TypeDescriptor;)Ljava/lang/Object;
                    INVOKESPECIAL org.springframework.core.convert.support.GenericConversionService.handleResult (Lorg/springframework/core/convert/TypeDescriptor;Lorg/springframework/core/convert/TypeDescriptor;Ljava/lang/Object;)Ljava/lang/Object;
                    ARETURN
                L3: ALOAD_1     // Ljava/lang/Object; source   (line 165)
                    IFNULL L4
                    ALOAD_2     // Lorg/springframework/core/convert/TypeDescriptor; sourceType
                    INVOKEVIRTUAL org.springframework.core.convert.TypeDescriptor.getObjectType ()Ljava/lang/Class;
                    ALOAD_1     // Ljava/lang/Object; source
                    INVOKEVIRTUAL java.lang.Class.isInstance (Ljava/lang/Object;)Z
                    IFNE L4
                    NEW java.lang.IllegalArgumentException   (line 166)
                    DUP
                    NEW java.lang.StringBuilder
                    DUP
                    LDC "The source to convert from must be an instance of "
                    INVOKESPECIAL java.lang.StringBuilder.<init> (Ljava/lang/String;)V
                    ALOAD_2     // Lorg/springframework/core/convert/TypeDescriptor; sourceType   (line 167)
                    INVOKEVIRTUAL java.lang.StringBuilder.append (Ljava/lang/Object;)Ljava/lang/StringBuilder;
                    LDC "; instead it was a "
                    INVOKEVIRTUAL java.lang.StringBuilder.append (Ljava/lang/String;)Ljava/lang/StringBuilder;
                    ALOAD_1     // Ljava/lang/Object; source
                    INVOKEVIRTUAL java.lang.Object.getClass ()Ljava/lang/Class;
                    INVOKEVIRTUAL java.lang.Class.getName ()Ljava/lang/String;
                    INVOKEVIRTUAL java.lang.StringBuilder.append (Ljava/lang/String;)Ljava/lang/StringBuilder;
                    INVOKEVIRTUAL java.lang.StringBuilder.toString ()Ljava/lang/String;
                    INVOKESPECIAL java.lang.IllegalArgumentException.<init> (Ljava/lang/String;)V   (line 166)
                    ATHROW
                L4: ALOAD_0     // Lorg/springframework/core/convert/support/GenericConversionService; this   (line 169)
                    ALOAD_2     // Lorg/springframework/core/convert/TypeDescriptor; sourceType
                    ALOAD_3     // Lorg/springframework/core/convert/TypeDescriptor; targetType
                    INVOKEVIRTUAL org.springframework.core.convert.support.GenericConversionService.getConverter (Lorg/springframework/core/convert/TypeDescriptor;Lorg/springframework/core/convert/TypeDescriptor;)Lorg/springframework/core/convert/converter/GenericConverter;
                    ASTORE 4
                    ALOAD 4     // Lorg/springframework/core/convert/converter/GenericConverter; converter   (line 170)
                    IFNULL L5
                    ALOAD 4     // Lorg/springframework/core/convert/converter/GenericConverter; converter   (line 171)
                    ALOAD_1     // Ljava/lang/Object; source
                    ALOAD_2     // Lorg/springframework/core/convert/TypeDescriptor; sourceType
                    ALOAD_3     // Lorg/springframework/core/convert/TypeDescriptor; targetType
                    INVOKESTATIC org.springframework.core.convert.support.ConversionUtils.invokeConverter (Lorg/springframework/core/convert/converter/GenericConverter;Ljava/lang/Object;Lorg/springframework/core/convert/TypeDescriptor;Lorg/springframework/core/convert/TypeDescriptor;)Ljava/lang/Object;
                    ASTORE 5
                    ALOAD_0     // Lorg/springframework/core/convert/support/GenericConversionService; this   (line 172)
                    ALOAD_2     // Lorg/springframework/core/convert/TypeDescriptor; sourceType
                    ALOAD_3     // Lorg/springframework/core/convert/TypeDescriptor; targetType
                    ALOAD 5     // Ljava/lang/Object; result
                    INVOKESPECIAL org.springframework.core.convert.support.GenericConversionService.handleResult (Lorg/springframework/core/convert/TypeDescriptor;Lorg/springframework/core/convert/TypeDescriptor;Ljava/lang/Object;)Ljava/lang/Object;
                    ARETURN
                L5: ALOAD_0     // Lorg/springframework/core/convert/support/GenericConversionService; this   (line 175)
                    ALOAD_1     // Ljava/lang/Object; source
                    ALOAD_2     // Lorg/springframework/core/convert/TypeDescriptor; sourceType
                    ALOAD_3     // Lorg/springframework/core/convert/TypeDescriptor; targetType
                    INVOKESPECIAL org.springframework.core.convert.support.GenericConversionService.handleConverterNotFound (Ljava/lang/Object;Lorg/springframework/core/convert/TypeDescriptor;Lorg/springframework/core/convert/TypeDescriptor;)Ljava/lang/Object;
                    ARETURN
  end public Object convert(Object, org.springframework.core.convert.TypeDescriptor, org.springframework.core.convert.TypeDescriptor)

  public Object convert(Object, org.springframework.core.convert.TypeDescriptor):
                    ALOAD_0     // Lorg/springframework/core/convert/support/GenericConversionService; this   (line 190)
                    ALOAD_1     // Ljava/lang/Object; source
                    ALOAD_1     // Ljava/lang/Object; source
                    INVOKESTATIC org.springframework.core.convert.TypeDescriptor.forObject (Ljava/lang/Object;)Lorg/springframework/core/convert/TypeDescriptor;
                    ALOAD_2     // Lorg/springframework/core/convert/TypeDescriptor; targetType
                    INVOKEVIRTUAL org.springframework.core.convert.support.GenericConversionService.convert (Ljava/lang/Object;Lorg/springframework/core/convert/TypeDescriptor;Lorg/springframework/core/convert/TypeDescriptor;)Ljava/lang/Object;
                    ARETURN
  end public Object convert(Object, org.springframework.core.convert.TypeDescriptor)

  public String toString():
                    NEW java.util.ArrayList   (line 194)
                    DUP
                    INVOKESPECIAL java.util.ArrayList.<init> ()V
                    ASTORE_1
                    ALOAD_0     // Lorg/springframework/core/convert/support/GenericConversionService; this   (line 195)
                    GETFIELD org.springframework.core.convert.support.GenericConversionService.converters Ljava/util/Map;
                    INVOKEINTERFACE java.util.Map.values ()Ljava/util/Collection;
                    INVOKEINTERFACE java.util.Collection.iterator ()Ljava/util/Iterator;
                    ASTORE_3
                    GOTO L3
                L0: ALOAD_3
                    INVOKEINTERFACE java.util.Iterator.next ()Ljava/lang/Object;
                    CHECKCAST java.util.Map
                    ASTORE_2
                    ALOAD_2     // Ljava/util/Map; targetConverters   (line 196)
                    INVOKEINTERFACE java.util.Map.values ()Ljava/util/Collection;
                    INVOKEINTERFACE java.util.Collection.iterator ()Ljava/util/Iterator;
                    ASTORE 5
                    GOTO L2
                L1: ALOAD 5
                    INVOKEINTERFACE java.util.Iterator.next ()Ljava/lang/Object;
                    CHECKCAST org.springframework.core.convert.support.GenericConversionService$MatchableConverters
                    ASTORE 4
                    ALOAD_1     // Ljava/util/List; converterStrings   (line 197)
                    ALOAD 4     // Lorg/springframework/core/convert/support/GenericConversionService$MatchableConverters; matchable
                    INVOKEVIRTUAL org.springframework.core.convert.support.GenericConversionService$MatchableConverters.toString ()Ljava/lang/String;
                    INVOKEINTERFACE java.util.List.add (Ljava/lang/Object;)Z
                    POP
                L2: ALOAD 5   (line 196)
                    INVOKEINTERFACE java.util.Iterator.hasNext ()Z
                    IFNE L1
                L3: ALOAD_3   (line 195)
                    INVOKEINTERFACE java.util.Iterator.hasNext ()Z
                    IFNE L0
                    ALOAD_1     // Ljava/util/List; converterStrings   (line 200)
                    INVOKESTATIC java.util.Collections.sort (Ljava/util/List;)V
                    NEW java.lang.StringBuilder   (line 201)
                    DUP
                    INVOKESPECIAL java.lang.StringBuilder.<init> ()V
                    ASTORE_2
                    ALOAD_2     // Ljava/lang/StringBuilder; builder   (line 202)
                    LDC_W "ConversionService converters = "
                    INVOKEVIRTUAL java.lang.StringBuilder.append (Ljava/lang/String;)Ljava/lang/StringBuilder;
                    LDC_W "\n"
                    INVOKEVIRTUAL java.lang.StringBuilder.append (Ljava/lang/String;)Ljava/lang/StringBuilder;
                    POP
                    ALOAD_1     // Ljava/util/List; converterStrings   (line 203)
                    INVOKEINTERFACE java.util.List.iterator ()Ljava/util/Iterator;
                    ASTORE 4
                    GOTO L5
                L4: ALOAD 4
                    INVOKEINTERFACE java.util.Iterator.next ()Ljava/lang/Object;
                    CHECKCAST java.lang.String
                    ASTORE_3
                    ALOAD_2     // Ljava/lang/StringBuilder; builder   (line 204)
                    LDC_W "\t"
                    INVOKEVIRTUAL java.lang.StringBuilder.append (Ljava/lang/String;)Ljava/lang/StringBuilder;
                    POP
                    ALOAD_2     // Ljava/lang/StringBuilder; builder   (line 205)
                    ALOAD_3     // Ljava/lang/String; converterString
                    INVOKEVIRTUAL java.lang.StringBuilder.append (Ljava/lang/String;)Ljava/lang/StringBuilder;
                    POP
                    ALOAD_2     // Ljava/lang/StringBuilder; builder   (line 206)
                    LDC_W "\n"
                    INVOKEVIRTUAL java.lang.StringBuilder.append (Ljava/lang/String;)Ljava/lang/StringBuilder;
                    POP
                L5: ALOAD 4   (line 203)
                    INVOKEINTERFACE java.util.Iterator.hasNext ()Z
                    IFNE L4
                    ALOAD_2     // Ljava/lang/StringBuilder; builder   (line 208)
                    INVOKEVIRTUAL java.lang.StringBuilder.toString ()Ljava/lang/String;
                    ARETURN
  end public String toString()

  protected Object convertNullSource(org.springframework.core.convert.TypeDescriptor, org.springframework.core.convert.TypeDescriptor):
                    ACONST_NULL   (line 223)
                    ARETURN
  end protected Object convertNullSource(org.springframework.core.convert.TypeDescriptor, org.springframework.core.convert.TypeDescriptor)

  protected org.springframework.core.convert.converter.GenericConverter getConverter(org.springframework.core.convert.TypeDescriptor, org.springframework.core.convert.TypeDescriptor):
                    NEW org.springframework.core.convert.support.GenericConversionService$ConverterCacheKey   (line 238)
                    DUP
                    ALOAD_1     // Lorg/springframework/core/convert/TypeDescriptor; sourceType
                    ALOAD_2     // Lorg/springframework/core/convert/TypeDescriptor; targetType
                    INVOKESPECIAL org.springframework.core.convert.support.GenericConversionService$ConverterCacheKey.<init> (Lorg/springframework/core/convert/TypeDescriptor;Lorg/springframework/core/convert/TypeDescriptor;)V
                    ASTORE_3
                    ALOAD_0     // Lorg/springframework/core/convert/support/GenericConversionService; this   (line 239)
                    GETFIELD org.springframework.core.convert.support.GenericConversionService.converterCache Ljava/util/Map;
                    ALOAD_3     // Lorg/springframework/core/convert/support/GenericConversionService$ConverterCacheKey; key
                    INVOKEINTERFACE java.util.Map.get (Ljava/lang/Object;)Ljava/lang/Object;
                    CHECKCAST org.springframework.core.convert.converter.GenericConverter
                    ASTORE 4
                    ALOAD 4     // Lorg/springframework/core/convert/converter/GenericConverter; converter   (line 240)
                    IFNULL L2
                    ALOAD 4     // Lorg/springframework/core/convert/converter/GenericConverter; converter   (line 241)
                    GETSTATIC org.springframework.core.convert.support.GenericConversionService.NO_MATCH Lorg/springframework/core/convert/converter/GenericConverter;
                    IF_ACMPEQ L0
                    ALOAD 4     // Lorg/springframework/core/convert/converter/GenericConverter; converter
                    GOTO L1
                L0: ACONST_NULL
                L1: ARETURN
                L2: ALOAD_0     // Lorg/springframework/core/convert/support/GenericConversionService; this   (line 244)
                    ALOAD_1     // Lorg/springframework/core/convert/TypeDescriptor; sourceType
                    ALOAD_2     // Lorg/springframework/core/convert/TypeDescriptor; targetType
                    INVOKESPECIAL org.springframework.core.convert.support.GenericConversionService.findConverterForClassPair (Lorg/springframework/core/convert/TypeDescriptor;Lorg/springframework/core/convert/TypeDescriptor;)Lorg/springframework/core/convert/converter/GenericConverter;
                    ASTORE 4     // Lorg/springframework/core/convert/converter/GenericConverter; converter
                    ALOAD 4     // Lorg/springframework/core/convert/converter/GenericConverter; converter   (line 245)
                    IFNONNULL L3
                    ALOAD_0     // Lorg/springframework/core/convert/support/GenericConversionService; this   (line 246)
                    ALOAD_1     // Lorg/springframework/core/convert/TypeDescriptor; sourceType
                    ALOAD_2     // Lorg/springframework/core/convert/TypeDescriptor; targetType
                    INVOKEVIRTUAL org.springframework.core.convert.support.GenericConversionService.getDefaultConverter (Lorg/springframework/core/convert/TypeDescriptor;Lorg/springframework/core/convert/TypeDescriptor;)Lorg/springframework/core/convert/converter/GenericConverter;
                    ASTORE 4     // Lorg/springframework/core/convert/converter/GenericConverter; converter
                L3: ALOAD 4     // Lorg/springframework/core/convert/converter/GenericConverter; converter   (line 248)
                    IFNULL L4
                    ALOAD_0     // Lorg/springframework/core/convert/support/GenericConversionService; this   (line 249)
                    GETFIELD org.springframework.core.convert.support.GenericConversionService.converterCache Ljava/util/Map;
                    ALOAD_3     // Lorg/springframework/core/convert/support/GenericConversionService$ConverterCacheKey; key
                    ALOAD 4     // Lorg/springframework/core/convert/converter/GenericConverter; converter
                    INVOKEINTERFACE java.util.Map.put (Ljava/lang/Object;Ljava/lang/Object;)Ljava/lang/Object;
                    POP
                    ALOAD 4     // Lorg/springframework/core/convert/converter/GenericConverter; converter   (line 250)
                    ARETURN
                L4: ALOAD_0     // Lorg/springframework/core/convert/support/GenericConversionService; this   (line 253)
                    GETFIELD org.springframework.core.convert.support.GenericConversionService.converterCache Ljava/util/Map;
                    ALOAD_3     // Lorg/springframework/core/convert/support/GenericConversionService$ConverterCacheKey; key
                    GETSTATIC org.springframework.core.convert.support.GenericConversionService.NO_MATCH Lorg/springframework/core/convert/converter/GenericConverter;
                    INVOKEINTERFACE java.util.Map.put (Ljava/lang/Object;Ljava/lang/Object;)Ljava/lang/Object;
                    POP
                    ACONST_NULL   (line 254)
                    ARETURN
  end protected org.springframework.core.convert.converter.GenericConverter getConverter(org.springframework.core.convert.TypeDescriptor, org.springframework.core.convert.TypeDescriptor)

  protected org.springframework.core.convert.converter.GenericConverter getDefaultConverter(org.springframework.core.convert.TypeDescriptor, org.springframework.core.convert.TypeDescriptor):
                    ALOAD_1     // Lorg/springframework/core/convert/TypeDescriptor; sourceType   (line 269)
                    ALOAD_2     // Lorg/springframework/core/convert/TypeDescriptor; targetType
                    INVOKEVIRTUAL org.springframework.core.convert.TypeDescriptor.isAssignableTo (Lorg/springframework/core/convert/TypeDescriptor;)Z
                    IFEQ L0
                    GETSTATIC org.springframework.core.convert.support.GenericConversionService.NO_OP_CONVERTER Lorg/springframework/core/convert/converter/GenericConverter;
                    GOTO L1
                L0: ACONST_NULL
                L1: ARETURN
  end protected org.springframework.core.convert.converter.GenericConverter getDefaultConverter(org.springframework.core.convert.TypeDescriptor, org.springframework.core.convert.TypeDescriptor)

  private org.springframework.core.convert.converter.GenericConverter$ConvertiblePair getRequiredTypeInfo(Object, Class):
                    ALOAD_1     // Ljava/lang/Object; converter   (line 275)
                    INVOKEVIRTUAL java.lang.Object.getClass ()Ljava/lang/Class;
                    ALOAD_2     // Ljava/lang/Class; genericIfc
                    INVOKESTATIC org.springframework.core.GenericTypeResolver.resolveTypeArguments (Ljava/lang/Class;Ljava/lang/Class;)[Ljava/lang/Class;
                    ASTORE_3
                    ALOAD_3     // [Ljava/lang/Class; args   (line 276)
                    IFNULL L0
                    NEW org.springframework.core.convert.converter.GenericConverter$ConvertiblePair
                    DUP
                    ALOAD_3     // [Ljava/lang/Class; args
                    ICONST_0
                    AALOAD
                    ALOAD_3     // [Ljava/lang/Class; args
                    ICONST_1
                    AALOAD
                    INVOKESPECIAL org.springframework.core.convert.converter.GenericConverter$ConvertiblePair.<init> (Ljava/lang/Class;Ljava/lang/Class;)V
                    GOTO L1
                L0: ACONST_NULL
                L1: ARETURN
  end private org.springframework.core.convert.converter.GenericConverter$ConvertiblePair getRequiredTypeInfo(Object, Class)

  private org.springframework.core.convert.support.GenericConversionService$MatchableConverters getMatchableConverters(Class, Class):
                    ALOAD_0     // Lorg/springframework/core/convert/support/GenericConversionService; this   (line 280)
                    ALOAD_1     // Ljava/lang/Class; sourceType
                    INVOKESPECIAL org.springframework.core.convert.support.GenericConversionService.getSourceConverterMap (Ljava/lang/Class;)Ljava/util/Map;
                    ASTORE_3
                    ALOAD_3     // Ljava/util/Map; sourceMap   (line 281)
                    ALOAD_2     // Ljava/lang/Class; targetType
                    INVOKEINTERFACE java.util.Map.get (Ljava/lang/Object;)Ljava/lang/Object;
                    CHECKCAST org.springframework.core.convert.support.GenericConversionService$MatchableConverters
                    ASTORE 4
                    ALOAD 4     // Lorg/springframework/core/convert/support/GenericConversionService$MatchableConverters; matchable   (line 282)
                    IFNONNULL L0
                    NEW org.springframework.core.convert.support.GenericConversionService$MatchableConverters   (line 283)
                    DUP
                    ACONST_NULL
                    INVOKESPECIAL org.springframework.core.convert.support.GenericConversionService$MatchableConverters.<init> (Lorg/springframework/core/convert/support/GenericConversionService$MatchableConverters;)V
                    ASTORE 4     // Lorg/springframework/core/convert/support/GenericConversionService$MatchableConverters; matchable
                    ALOAD_3     // Ljava/util/Map; sourceMap   (line 284)
                    ALOAD_2     // Ljava/lang/Class; targetType
                    ALOAD 4     // Lorg/springframework/core/convert/support/GenericConversionService$MatchableConverters; matchable
                    INVOKEINTERFACE java.util.Map.put (Ljava/lang/Object;Ljava/lang/Object;)Ljava/lang/Object;
                    POP
                L0: ALOAD 4     // Lorg/springframework/core/convert/support/GenericConversionService$MatchableConverters; matchable   (line 286)
                    ARETURN
  end private org.springframework.core.convert.support.GenericConversionService$MatchableConverters getMatchableConverters(Class, Class)

  private void invalidateCache():
                    ALOAD_0     // Lorg/springframework/core/convert/support/GenericConversionService; this   (line 290)
                    GETFIELD org.springframework.core.convert.support.GenericConversionService.converterCache Ljava/util/Map;
                    INVOKEINTERFACE java.util.Map.clear ()V
                    RETURN   (line 291)
  end private void invalidateCache()

  private java.util.Map getSourceConverterMap(Class):
                    ALOAD_0     // Lorg/springframework/core/convert/support/GenericConversionService; this   (line 294)
                    GETFIELD org.springframework.core.convert.support.GenericConversionService.converters Ljava/util/Map;
                    ALOAD_1     // Ljava/lang/Class; sourceType
                    INVOKEINTERFACE java.util.Map.get (Ljava/lang/Object;)Ljava/lang/Object;
                    CHECKCAST java.util.Map
                    ASTORE_2
                    ALOAD_2     // Ljava/util/Map; sourceMap   (line 295)
                    IFNONNULL L0
                    NEW java.util.HashMap   (line 296)
                    DUP
                    INVOKESPECIAL java.util.HashMap.<init> ()V
                    ASTORE_2     // Ljava/util/Map; sourceMap
                    ALOAD_0     // Lorg/springframework/core/convert/support/GenericConversionService; this   (line 297)
                    GETFIELD org.springframework.core.convert.support.GenericConversionService.converters Ljava/util/Map;
                    ALOAD_1     // Ljava/lang/Class; sourceType
                    ALOAD_2     // Ljava/util/Map; sourceMap
                    INVOKEINTERFACE java.util.Map.put (Ljava/lang/Object;Ljava/lang/Object;)Ljava/lang/Object;
                    POP
                L0: ALOAD_2     // Ljava/util/Map; sourceMap   (line 299)
                    ARETURN
  end private java.util.Map getSourceConverterMap(Class)

  private org.springframework.core.convert.converter.GenericConverter findConverterForClassPair(org.springframework.core.convert.TypeDescriptor, org.springframework.core.convert.TypeDescriptor):
                    ALOAD_1     // Lorg/springframework/core/convert/TypeDescriptor; sourceType   (line 303)
                    INVOKEVIRTUAL org.springframework.core.convert.TypeDescriptor.getObjectType ()Ljava/lang/Class;
                    ASTORE_3
                    ALOAD_3     // Ljava/lang/Class; sourceObjectType   (line 304)
                    INVOKEVIRTUAL java.lang.Class.isInterface ()Z
                    IFEQ L5
                    NEW java.util.LinkedList   (line 305)
                    DUP
                    INVOKESPECIAL java.util.LinkedList.<init> ()V
                    ASTORE 4
                    ALOAD 4     // Ljava/util/LinkedList; classQueue   (line 306)
                    ALOAD_3     // Ljava/lang/Class; sourceObjectType
                    INVOKEVIRTUAL java.util.LinkedList.addFirst (Ljava/lang/Object;)V
                    GOTO L4   (line 307)
                L0: ALOAD 4     // Ljava/util/LinkedList; classQueue   (line 308)
                    INVOKEVIRTUAL java.util.LinkedList.removeLast ()Ljava/lang/Object;
                    CHECKCAST java.lang.Class
                    ASTORE 5
                    ALOAD_0     // Lorg/springframework/core/convert/support/GenericConversionService; this   (line 309)
                    ALOAD 5     // Ljava/lang/Class; currentClass
                    INVOKESPECIAL org.springframework.core.convert.support.GenericConversionService.getTargetConvertersForSource (Ljava/lang/Class;)Ljava/util/Map;
                    ASTORE 6
                    ALOAD_0     // Lorg/springframework/core/convert/support/GenericConversionService; this   (line 310)
                    ALOAD_1     // Lorg/springframework/core/convert/TypeDescriptor; sourceType
                    ALOAD_2     // Lorg/springframework/core/convert/TypeDescriptor; targetType
                    ALOAD 6     // Ljava/util/Map; converters
                    INVOKESPECIAL org.springframework.core.convert.support.GenericConversionService.getMatchingConverterForTarget (Lorg/springframework/core/convert/TypeDescriptor;Lorg/springframework/core/convert/TypeDescriptor;Ljava/util/Map;)Lorg/springframework/core/convert/converter/GenericConverter;
                    ASTORE 7
                    ALOAD 7     // Lorg/springframework/core/convert/converter/GenericConverter; converter   (line 311)
                    IFNULL L1
                    ALOAD 7     // Lorg/springframework/core/convert/converter/GenericConverter; converter   (line 312)
                    ARETURN
                L1: ALOAD 5     // Ljava/lang/Class; currentClass   (line 314)
                    INVOKEVIRTUAL java.lang.Class.getInterfaces ()[Ljava/lang/Class;
                    ASTORE 8
                    ALOAD 8     // [Ljava/lang/Class; interfaces   (line 315)
                    DUP
                    ASTORE 12
                    ARRAYLENGTH
                    ISTORE 11
                    ICONST_0
                    ISTORE 10
                    GOTO L3
                L2: ALOAD 12
                    ILOAD 10
                    AALOAD
                    ASTORE 9
                    ALOAD 4     // Ljava/util/LinkedList; classQueue   (line 316)
                    ALOAD 9     // Ljava/lang/Class; ifc
                    INVOKEVIRTUAL java.util.LinkedList.addFirst (Ljava/lang/Object;)V
                    IINC 10 1   (line 315)
                L3: ILOAD 10
                    ILOAD 11
                    IF_ICMPLT L2
                L4: ALOAD 4     // Ljava/util/LinkedList; classQueue   (line 307)
                    INVOKEVIRTUAL java.util.LinkedList.isEmpty ()Z
                    IFEQ L0
                    ALOAD_0     // Lorg/springframework/core/convert/support/GenericConversionService; this   (line 319)
                    LDC java.lang.Object
                    INVOKESPECIAL org.springframework.core.convert.support.GenericConversionService.getTargetConvertersForSource (Ljava/lang/Class;)Ljava/util/Map;
                    ASTORE 5
                    ALOAD_0     // Lorg/springframework/core/convert/support/GenericConversionService; this   (line 320)
                    ALOAD_1     // Lorg/springframework/core/convert/TypeDescriptor; sourceType
                    ALOAD_2     // Lorg/springframework/core/convert/TypeDescriptor; targetType
                    ALOAD 5     // Ljava/util/Map; objectConverters
                    INVOKESPECIAL org.springframework.core.convert.support.GenericConversionService.getMatchingConverterForTarget (Lorg/springframework/core/convert/TypeDescriptor;Lorg/springframework/core/convert/TypeDescriptor;Ljava/util/Map;)Lorg/springframework/core/convert/converter/GenericConverter;
                    ARETURN
                L5: ALOAD_3     // Ljava/lang/Class; sourceObjectType   (line 322)
                    INVOKEVIRTUAL java.lang.Class.isArray ()Z
                    IFEQ L10
                    NEW java.util.LinkedList   (line 323)
                    DUP
                    INVOKESPECIAL java.util.LinkedList.<init> ()V
                    ASTORE 4
                    ALOAD 4     // Ljava/util/LinkedList; classQueue   (line 324)
                    ALOAD_3     // Ljava/lang/Class; sourceObjectType
                    INVOKEVIRTUAL java.util.LinkedList.addFirst (Ljava/lang/Object;)V
                    GOTO L9   (line 325)
                L6: ALOAD 4     // Ljava/util/LinkedList; classQueue   (line 326)
                    INVOKEVIRTUAL java.util.LinkedList.removeLast ()Ljava/lang/Object;
                    CHECKCAST java.lang.Class
                    ASTORE 5
                    ALOAD_0     // Lorg/springframework/core/convert/support/GenericConversionService; this   (line 327)
                    ALOAD 5     // Ljava/lang/Class; currentClass
                    INVOKESPECIAL org.springframework.core.convert.support.GenericConversionService.getTargetConvertersForSource (Ljava/lang/Class;)Ljava/util/Map;
                    ASTORE 6
                    ALOAD_0     // Lorg/springframework/core/convert/support/GenericConversionService; this   (line 328)
                    ALOAD_1     // Lorg/springframework/core/convert/TypeDescriptor; sourceType
                    ALOAD_2     // Lorg/springframework/core/convert/TypeDescriptor; targetType
                    ALOAD 6     // Ljava/util/Map; converters
                    INVOKESPECIAL org.springframework.core.convert.support.GenericConversionService.getMatchingConverterForTarget (Lorg/springframework/core/convert/TypeDescriptor;Lorg/springframework/core/convert/TypeDescriptor;Ljava/util/Map;)Lorg/springframework/core/convert/converter/GenericConverter;
                    ASTORE 7
                    ALOAD 7     // Lorg/springframework/core/convert/converter/GenericConverter; converter   (line 329)
                    IFNULL L7
                    ALOAD 7     // Lorg/springframework/core/convert/converter/GenericConverter; converter   (line 330)
                    ARETURN
                L7: ALOAD 5     // Ljava/lang/Class; currentClass   (line 332)
                    INVOKEVIRTUAL java.lang.Class.getComponentType ()Ljava/lang/Class;
                    INVOKESTATIC org.springframework.util.ClassUtils.resolvePrimitiveIfNecessary (Ljava/lang/Class;)Ljava/lang/Class;
                    ASTORE 8
                    ALOAD 8     // Ljava/lang/Class; componentType   (line 333)
                    INVOKEVIRTUAL java.lang.Class.getSuperclass ()Ljava/lang/Class;
                    IFNULL L8
                    ALOAD 4     // Ljava/util/LinkedList; classQueue   (line 334)
                    ALOAD 8     // Ljava/lang/Class; componentType
                    INVOKEVIRTUAL java.lang.Class.getSuperclass ()Ljava/lang/Class;
                    ICONST_0
                    INVOKESTATIC java.lang.reflect.Array.newInstance (Ljava/lang/Class;I)Ljava/lang/Object;
                    INVOKEVIRTUAL java.lang.Object.getClass ()Ljava/lang/Class;
                    INVOKEVIRTUAL java.util.LinkedList.addFirst (Ljava/lang/Object;)V
                    GOTO L9
                L8: ALOAD 8     // Ljava/lang/Class; componentType   (line 336)
                    INVOKEVIRTUAL java.lang.Class.isInterface ()Z
                    IFEQ L9
                    ALOAD 4     // Ljava/util/LinkedList; classQueue   (line 337)
                    LDC_W [Ljava.lang.Object;
                    INVOKEVIRTUAL java.util.LinkedList.addFirst (Ljava/lang/Object;)V
                L9: ALOAD 4     // Ljava/util/LinkedList; classQueue   (line 325)
                    INVOKEVIRTUAL java.util.LinkedList.isEmpty ()Z
                    IFEQ L6
                    ACONST_NULL   (line 340)
                    ARETURN
               L10: NEW java.util.LinkedHashSet   (line 343)
                    DUP
                    INVOKESPECIAL java.util.LinkedHashSet.<init> ()V
                    ASTORE 4
                    NEW java.util.LinkedList   (line 344)
                    DUP
                    INVOKESPECIAL java.util.LinkedList.<init> ()V
                    ASTORE 5
                    ALOAD 5     // Ljava/util/LinkedList; classQueue   (line 345)
                    ALOAD_3     // Ljava/lang/Class; sourceObjectType
                    INVOKEVIRTUAL java.util.LinkedList.addFirst (Ljava/lang/Object;)V
                    GOTO L16   (line 346)
               L11: ALOAD 5     // Ljava/util/LinkedList; classQueue   (line 347)
                    INVOKEVIRTUAL java.util.LinkedList.removeLast ()Ljava/lang/Object;
                    CHECKCAST java.lang.Class
                    ASTORE 6
                    ALOAD_0     // Lorg/springframework/core/convert/support/GenericConversionService; this   (line 348)
                    ALOAD 6     // Ljava/lang/Class; currentClass
                    INVOKESPECIAL org.springframework.core.convert.support.GenericConversionService.getTargetConvertersForSource (Ljava/lang/Class;)Ljava/util/Map;
                    ASTORE 7
                    ALOAD_0     // Lorg/springframework/core/convert/support/GenericConversionService; this   (line 349)
                    ALOAD_1     // Lorg/springframework/core/convert/TypeDescriptor; sourceType
                    ALOAD_2     // Lorg/springframework/core/convert/TypeDescriptor; targetType
                    ALOAD 7     // Ljava/util/Map; converters
                    INVOKESPECIAL org.springframework.core.convert.support.GenericConversionService.getMatchingConverterForTarget (Lorg/springframework/core/convert/TypeDescriptor;Lorg/springframework/core/convert/TypeDescriptor;Ljava/util/Map;)Lorg/springframework/core/convert/converter/GenericConverter;
                    ASTORE 8
                    ALOAD 8     // Lorg/springframework/core/convert/converter/GenericConverter; converter   (line 350)
                    IFNULL L12
                    ALOAD 8     // Lorg/springframework/core/convert/converter/GenericConverter; converter   (line 351)
                    ARETURN
               L12: ALOAD 6     // Ljava/lang/Class; currentClass   (line 353)
                    INVOKEVIRTUAL java.lang.Class.getSuperclass ()Ljava/lang/Class;
                    ASTORE 9
                    ALOAD 9     // Ljava/lang/Class; superClass   (line 354)
                    IFNULL L13
                    ALOAD 9     // Ljava/lang/Class; superClass
                    LDC java.lang.Object
                    IF_ACMPEQ L13
                    ALOAD 5     // Ljava/util/LinkedList; classQueue   (line 355)
                    ALOAD 9     // Ljava/lang/Class; superClass
                    INVOKEVIRTUAL java.util.LinkedList.addFirst (Ljava/lang/Object;)V
               L13: ALOAD 6     // Ljava/lang/Class; currentClass   (line 357)
                    INVOKEVIRTUAL java.lang.Class.getInterfaces ()[Ljava/lang/Class;
                    DUP
                    ASTORE 13
                    ARRAYLENGTH
                    ISTORE 12
                    ICONST_0
                    ISTORE 11
                    GOTO L15
               L14: ALOAD 13
                    ILOAD 11
                    AALOAD
                    ASTORE 10
                    ALOAD_0     // Lorg/springframework/core/convert/support/GenericConversionService; this   (line 358)
                    ALOAD 10     // Ljava/lang/Class; interfaceType
                    ALOAD 4     // Ljava/util/HashSet; interfaces
                    INVOKESPECIAL org.springframework.core.convert.support.GenericConversionService.addInterfaceHierarchy (Ljava/lang/Class;Ljava/util/Set;)V
                    IINC 11 1   (line 357)
               L15: ILOAD 11
                    ILOAD 12
                    IF_ICMPLT L14
               L16: ALOAD 5     // Ljava/util/LinkedList; classQueue   (line 346)
                    INVOKEVIRTUAL java.util.LinkedList.isEmpty ()Z
                    IFEQ L11
                    ALOAD 4     // Ljava/util/HashSet; interfaces   (line 361)
                    INVOKEVIRTUAL java.util.HashSet.iterator ()Ljava/util/Iterator;
                    ASTORE 7
                    GOTO L18
               L17: ALOAD 7
                    INVOKEINTERFACE java.util.Iterator.next ()Ljava/lang/Object;
                    CHECKCAST java.lang.Class
                    ASTORE 6
                    ALOAD_0     // Lorg/springframework/core/convert/support/GenericConversionService; this   (line 362)
                    ALOAD 6     // Ljava/lang/Class; interfaceType
                    INVOKESPECIAL org.springframework.core.convert.support.GenericConversionService.getTargetConvertersForSource (Ljava/lang/Class;)Ljava/util/Map;
                    ASTORE 8
                    ALOAD_0     // Lorg/springframework/core/convert/support/GenericConversionService; this   (line 363)
                    ALOAD_1     // Lorg/springframework/core/convert/TypeDescriptor; sourceType
                    ALOAD_2     // Lorg/springframework/core/convert/TypeDescriptor; targetType
                    ALOAD 8     // Ljava/util/Map; converters
                    INVOKESPECIAL org.springframework.core.convert.support.GenericConversionService.getMatchingConverterForTarget (Lorg/springframework/core/convert/TypeDescriptor;Lorg/springframework/core/convert/TypeDescriptor;Ljava/util/Map;)Lorg/springframework/core/convert/converter/GenericConverter;
                    ASTORE 9
                    ALOAD 9     // Lorg/springframework/core/convert/converter/GenericConverter; converter   (line 364)
                    IFNULL L18
                    ALOAD 9     // Lorg/springframework/core/convert/converter/GenericConverter; converter   (line 365)
                    ARETURN
               L18: ALOAD 7   (line 361)
                    INVOKEINTERFACE java.util.Iterator.hasNext ()Z
                    IFNE L17
                    ALOAD_0     // Lorg/springframework/core/convert/support/GenericConversionService; this   (line 368)
                    LDC java.lang.Object
                    INVOKESPECIAL org.springframework.core.convert.support.GenericConversionService.getTargetConvertersForSource (Ljava/lang/Class;)Ljava/util/Map;
                    ASTORE 6
                    ALOAD_0     // Lorg/springframework/core/convert/support/GenericConversionService; this   (line 369)
                    ALOAD_1     // Lorg/springframework/core/convert/TypeDescriptor; sourceType
                    ALOAD_2     // Lorg/springframework/core/convert/TypeDescriptor; targetType
                    ALOAD 6     // Ljava/util/Map; objectConverters
                    INVOKESPECIAL org.springframework.core.convert.support.GenericConversionService.getMatchingConverterForTarget (Lorg/springframework/core/convert/TypeDescriptor;Lorg/springframework/core/convert/TypeDescriptor;Ljava/util/Map;)Lorg/springframework/core/convert/converter/GenericConverter;
                    ARETURN
  end private org.springframework.core.convert.converter.GenericConverter findConverterForClassPair(org.springframework.core.convert.TypeDescriptor, org.springframework.core.convert.TypeDescriptor)

  private java.util.Map getTargetConvertersForSource(Class):
                    ALOAD_0     // Lorg/springframework/core/convert/support/GenericConversionService; this   (line 374)
                    GETFIELD org.springframework.core.convert.support.GenericConversionService.converters Ljava/util/Map;
                    ALOAD_1     // Ljava/lang/Class; sourceType
                    INVOKEINTERFACE java.util.Map.get (Ljava/lang/Object;)Ljava/lang/Object;
                    CHECKCAST java.util.Map
                    ASTORE_2
                    ALOAD_2     // Ljava/util/Map; converters   (line 375)
                    IFNONNULL L0
                    INVOKESTATIC java.util.Collections.emptyMap ()Ljava/util/Map;   (line 376)
                    ASTORE_2     // Ljava/util/Map; converters
                L0: ALOAD_2     // Ljava/util/Map; converters   (line 378)
                    ARETURN
  end private java.util.Map getTargetConvertersForSource(Class)

  private org.springframework.core.convert.converter.GenericConverter getMatchingConverterForTarget(org.springframework.core.convert.TypeDescriptor, org.springframework.core.convert.TypeDescriptor, java.util.Map):
                    ALOAD_2     // Lorg/springframework/core/convert/TypeDescriptor; targetType   (line 383)
                    INVOKEVIRTUAL org.springframework.core.convert.TypeDescriptor.getObjectType ()Ljava/lang/Class;
                    ASTORE 4
                    ALOAD 4     // Ljava/lang/Class; targetObjectType   (line 384)
                    INVOKEVIRTUAL java.lang.Class.isInterface ()Z
                    IFEQ L5
                    NEW java.util.LinkedList   (line 385)
                    DUP
                    INVOKESPECIAL java.util.LinkedList.<init> ()V
                    ASTORE 5
                    ALOAD 5     // Ljava/util/LinkedList; classQueue   (line 386)
                    ALOAD 4     // Ljava/lang/Class; targetObjectType
                    INVOKEVIRTUAL java.util.LinkedList.addFirst (Ljava/lang/Object;)V
                    GOTO L4   (line 387)
                L0: ALOAD 5     // Ljava/util/LinkedList; classQueue   (line 388)
                    INVOKEVIRTUAL java.util.LinkedList.removeLast ()Ljava/lang/Object;
                    CHECKCAST java.lang.Class
                    ASTORE 6
                    ALOAD_3     // Ljava/util/Map; converters   (line 389)
                    ALOAD 6     // Ljava/lang/Class; currentClass
                    INVOKEINTERFACE java.util.Map.get (Ljava/lang/Object;)Ljava/lang/Object;
                    CHECKCAST org.springframework.core.convert.support.GenericConversionService$MatchableConverters
                    ASTORE 7
                    ALOAD_0     // Lorg/springframework/core/convert/support/GenericConversionService; this   (line 390)
                    ALOAD 7     // Lorg/springframework/core/convert/support/GenericConversionService$MatchableConverters; matchable
                    ALOAD_1     // Lorg/springframework/core/convert/TypeDescriptor; sourceType
                    ALOAD_2     // Lorg/springframework/core/convert/TypeDescriptor; targetType
                    INVOKESPECIAL org.springframework.core.convert.support.GenericConversionService.matchConverter (Lorg/springframework/core/convert/support/GenericConversionService$MatchableConverters;Lorg/springframework/core/convert/TypeDescriptor;Lorg/springframework/core/convert/TypeDescriptor;)Lorg/springframework/core/convert/converter/GenericConverter;
                    ASTORE 8
                    ALOAD 8     // Lorg/springframework/core/convert/converter/GenericConverter; converter   (line 391)
                    IFNULL L1
                    ALOAD 8     // Lorg/springframework/core/convert/converter/GenericConverter; converter   (line 392)
                    ARETURN
                L1: ALOAD 6     // Ljava/lang/Class; currentClass   (line 394)
                    INVOKEVIRTUAL java.lang.Class.getInterfaces ()[Ljava/lang/Class;
                    ASTORE 9
                    ALOAD 9     // [Ljava/lang/Class; interfaces   (line 395)
                    DUP
                    ASTORE 13
                    ARRAYLENGTH
                    ISTORE 12
                    ICONST_0
                    ISTORE 11
                    GOTO L3
                L2: ALOAD 13
                    ILOAD 11
                    AALOAD
                    ASTORE 10
                    ALOAD 5     // Ljava/util/LinkedList; classQueue   (line 396)
                    ALOAD 10     // Ljava/lang/Class; ifc
                    INVOKEVIRTUAL java.util.LinkedList.addFirst (Ljava/lang/Object;)V
                    IINC 11 1   (line 395)
                L3: ILOAD 11
                    ILOAD 12
                    IF_ICMPLT L2
                L4: ALOAD 5     // Ljava/util/LinkedList; classQueue   (line 387)
                    INVOKEVIRTUAL java.util.LinkedList.isEmpty ()Z
                    IFEQ L0
                    ALOAD_0     // Lorg/springframework/core/convert/support/GenericConversionService; this   (line 399)
                    ALOAD_3     // Ljava/util/Map; converters
                    LDC java.lang.Object
                    INVOKEINTERFACE java.util.Map.get (Ljava/lang/Object;)Ljava/lang/Object;
                    CHECKCAST org.springframework.core.convert.support.GenericConversionService$MatchableConverters
                    ALOAD_1     // Lorg/springframework/core/convert/TypeDescriptor; sourceType
                    ALOAD_2     // Lorg/springframework/core/convert/TypeDescriptor; targetType
                    INVOKESPECIAL org.springframework.core.convert.support.GenericConversionService.matchConverter (Lorg/springframework/core/convert/support/GenericConversionService$MatchableConverters;Lorg/springframework/core/convert/TypeDescriptor;Lorg/springframework/core/convert/TypeDescriptor;)Lorg/springframework/core/convert/converter/GenericConverter;
                    ARETURN
                L5: ALOAD 4     // Ljava/lang/Class; targetObjectType   (line 401)
                    INVOKEVIRTUAL java.lang.Class.isArray ()Z
                    IFEQ L10
                    NEW java.util.LinkedList   (line 402)
                    DUP
                    INVOKESPECIAL java.util.LinkedList.<init> ()V
                    ASTORE 5
                    ALOAD 5     // Ljava/util/LinkedList; classQueue   (line 403)
                    ALOAD 4     // Ljava/lang/Class; targetObjectType
                    INVOKEVIRTUAL java.util.LinkedList.addFirst (Ljava/lang/Object;)V
                    GOTO L9   (line 404)
                L6: ALOAD 5     // Ljava/util/LinkedList; classQueue   (line 405)
                    INVOKEVIRTUAL java.util.LinkedList.removeLast ()Ljava/lang/Object;
                    CHECKCAST java.lang.Class
                    ASTORE 6
                    ALOAD_3     // Ljava/util/Map; converters   (line 406)
                    ALOAD 6     // Ljava/lang/Class; currentClass
                    INVOKEINTERFACE java.util.Map.get (Ljava/lang/Object;)Ljava/lang/Object;
                    CHECKCAST org.springframework.core.convert.support.GenericConversionService$MatchableConverters
                    ASTORE 7
                    ALOAD_0     // Lorg/springframework/core/convert/support/GenericConversionService; this   (line 407)
                    ALOAD 7     // Lorg/springframework/core/convert/support/GenericConversionService$MatchableConverters; matchable
                    ALOAD_1     // Lorg/springframework/core/convert/TypeDescriptor; sourceType
                    ALOAD_2     // Lorg/springframework/core/convert/TypeDescriptor; targetType
                    INVOKESPECIAL org.springframework.core.convert.support.GenericConversionService.matchConverter (Lorg/springframework/core/convert/support/GenericConversionService$MatchableConverters;Lorg/springframework/core/convert/TypeDescriptor;Lorg/springframework/core/convert/TypeDescriptor;)Lorg/springframework/core/convert/converter/GenericConverter;
                    ASTORE 8
                    ALOAD 8     // Lorg/springframework/core/convert/converter/GenericConverter; converter   (line 408)
                    IFNULL L7
                    ALOAD 8     // Lorg/springframework/core/convert/converter/GenericConverter; converter   (line 409)
                    ARETURN
                L7: ALOAD 6     // Ljava/lang/Class; currentClass   (line 411)
                    INVOKEVIRTUAL java.lang.Class.getComponentType ()Ljava/lang/Class;
                    INVOKESTATIC org.springframework.util.ClassUtils.resolvePrimitiveIfNecessary (Ljava/lang/Class;)Ljava/lang/Class;
                    ASTORE 9
                    ALOAD 9     // Ljava/lang/Class; componentType   (line 412)
                    INVOKEVIRTUAL java.lang.Class.getSuperclass ()Ljava/lang/Class;
                    IFNULL L8
                    ALOAD 5     // Ljava/util/LinkedList; classQueue   (line 413)
                    ALOAD 9     // Ljava/lang/Class; componentType
                    INVOKEVIRTUAL java.lang.Class.getSuperclass ()Ljava/lang/Class;
                    ICONST_0
                    INVOKESTATIC java.lang.reflect.Array.newInstance (Ljava/lang/Class;I)Ljava/lang/Object;
                    INVOKEVIRTUAL java.lang.Object.getClass ()Ljava/lang/Class;
                    INVOKEVIRTUAL java.util.LinkedList.addFirst (Ljava/lang/Object;)V
                    GOTO L9
                L8: ALOAD 9     // Ljava/lang/Class; componentType   (line 415)
                    INVOKEVIRTUAL java.lang.Class.isInterface ()Z
                    IFEQ L9
                    ALOAD 5     // Ljava/util/LinkedList; classQueue   (line 416)
                    LDC_W [Ljava.lang.Object;
                    INVOKEVIRTUAL java.util.LinkedList.addFirst (Ljava/lang/Object;)V
                L9: ALOAD 5     // Ljava/util/LinkedList; classQueue   (line 404)
                    INVOKEVIRTUAL java.util.LinkedList.isEmpty ()Z
                    IFEQ L6
                    ACONST_NULL   (line 419)
                    ARETURN
               L10: NEW java.util.LinkedHashSet   (line 422)
                    DUP
                    INVOKESPECIAL java.util.LinkedHashSet.<init> ()V
                    ASTORE 5
                    NEW java.util.LinkedList   (line 423)
                    DUP
                    INVOKESPECIAL java.util.LinkedList.<init> ()V
                    ASTORE 6
                    ALOAD 6     // Ljava/util/LinkedList; classQueue   (line 424)
                    ALOAD 4     // Ljava/lang/Class; targetObjectType
                    INVOKEVIRTUAL java.util.LinkedList.addFirst (Ljava/lang/Object;)V
                    GOTO L16   (line 425)
               L11: ALOAD 6     // Ljava/util/LinkedList; classQueue   (line 426)
                    INVOKEVIRTUAL java.util.LinkedList.removeLast ()Ljava/lang/Object;
                    CHECKCAST java.lang.Class
                    ASTORE 7
                    ALOAD_3     // Ljava/util/Map; converters   (line 427)
                    ALOAD 7     // Ljava/lang/Class; currentClass
                    INVOKEINTERFACE java.util.Map.get (Ljava/lang/Object;)Ljava/lang/Object;
                    CHECKCAST org.springframework.core.convert.support.GenericConversionService$MatchableConverters
                    ASTORE 8
                    ALOAD_0     // Lorg/springframework/core/convert/support/GenericConversionService; this   (line 428)
                    ALOAD 8     // Lorg/springframework/core/convert/support/GenericConversionService$MatchableConverters; matchable
                    ALOAD_1     // Lorg/springframework/core/convert/TypeDescriptor; sourceType
                    ALOAD_2     // Lorg/springframework/core/convert/TypeDescriptor; targetType
                    INVOKESPECIAL org.springframework.core.convert.support.GenericConversionService.matchConverter (Lorg/springframework/core/convert/support/GenericConversionService$MatchableConverters;Lorg/springframework/core/convert/TypeDescriptor;Lorg/springframework/core/convert/TypeDescriptor;)Lorg/springframework/core/convert/converter/GenericConverter;
                    ASTORE 9
                    ALOAD 9     // Lorg/springframework/core/convert/converter/GenericConverter; converter   (line 429)
                    IFNULL L12
                    ALOAD 9     // Lorg/springframework/core/convert/converter/GenericConverter; converter   (line 430)
                    ARETURN
               L12: ALOAD 7     // Ljava/lang/Class; currentClass   (line 432)
                    INVOKEVIRTUAL java.lang.Class.getSuperclass ()Ljava/lang/Class;
                    ASTORE 10
                    ALOAD 10     // Ljava/lang/Class; superClass   (line 433)
                    IFNULL L13
                    ALOAD 10     // Ljava/lang/Class; superClass
                    LDC java.lang.Object
                    IF_ACMPEQ L13
                    ALOAD 6     // Ljava/util/LinkedList; classQueue   (line 434)
                    ALOAD 10     // Ljava/lang/Class; superClass
                    INVOKEVIRTUAL java.util.LinkedList.addFirst (Ljava/lang/Object;)V
               L13: ALOAD 7     // Ljava/lang/Class; currentClass   (line 436)
                    INVOKEVIRTUAL java.lang.Class.getInterfaces ()[Ljava/lang/Class;
                    DUP
                    ASTORE 14
                    ARRAYLENGTH
                    ISTORE 13
                    ICONST_0
                    ISTORE 12
                    GOTO L15
               L14: ALOAD 14
                    ILOAD 12
                    AALOAD
                    ASTORE 11
                    ALOAD_0     // Lorg/springframework/core/convert/support/GenericConversionService; this   (line 437)
                    ALOAD 11     // Ljava/lang/Class; interfaceType
                    ALOAD 5     // Ljava/util/Set; interfaces
                    INVOKESPECIAL org.springframework.core.convert.support.GenericConversionService.addInterfaceHierarchy (Ljava/lang/Class;Ljava/util/Set;)V
                    IINC 12 1   (line 436)
               L15: ILOAD 12
                    ILOAD 13
                    IF_ICMPLT L14
               L16: ALOAD 6     // Ljava/util/LinkedList; classQueue   (line 425)
                    INVOKEVIRTUAL java.util.LinkedList.isEmpty ()Z
                    IFEQ L11
                    ALOAD 5     // Ljava/util/Set; interfaces   (line 440)
                    INVOKEINTERFACE java.util.Set.iterator ()Ljava/util/Iterator;
                    ASTORE 8
                    GOTO L18
               L17: ALOAD 8
                    INVOKEINTERFACE java.util.Iterator.next ()Ljava/lang/Object;
                    CHECKCAST java.lang.Class
                    ASTORE 7
                    ALOAD_3     // Ljava/util/Map; converters   (line 441)
                    ALOAD 7     // Ljava/lang/Class; interfaceType
                    INVOKEINTERFACE java.util.Map.get (Ljava/lang/Object;)Ljava/lang/Object;
                    CHECKCAST org.springframework.core.convert.support.GenericConversionService$MatchableConverters
                    ASTORE 9
                    ALOAD_0     // Lorg/springframework/core/convert/support/GenericConversionService; this   (line 442)
                    ALOAD 9     // Lorg/springframework/core/convert/support/GenericConversionService$MatchableConverters; matchable
                    ALOAD_1     // Lorg/springframework/core/convert/TypeDescriptor; sourceType
                    ALOAD_2     // Lorg/springframework/core/convert/TypeDescriptor; targetType
                    INVOKESPECIAL org.springframework.core.convert.support.GenericConversionService.matchConverter (Lorg/springframework/core/convert/support/GenericConversionService$MatchableConverters;Lorg/springframework/core/convert/TypeDescriptor;Lorg/springframework/core/convert/TypeDescriptor;)Lorg/springframework/core/convert/converter/GenericConverter;
                    ASTORE 10
                    ALOAD 10     // Lorg/springframework/core/convert/converter/GenericConverter; converter   (line 443)
                    IFNULL L18
                    ALOAD 10     // Lorg/springframework/core/convert/converter/GenericConverter; converter   (line 444)
                    ARETURN
               L18: ALOAD 8   (line 440)
                    INVOKEINTERFACE java.util.Iterator.hasNext ()Z
                    IFNE L17
                    ALOAD_0     // Lorg/springframework/core/convert/support/GenericConversionService; this   (line 447)
                    ALOAD_3     // Ljava/util/Map; converters
                    LDC java.lang.Object
                    INVOKEINTERFACE java.util.Map.get (Ljava/lang/Object;)Ljava/lang/Object;
                    CHECKCAST org.springframework.core.convert.support.GenericConversionService$MatchableConverters
                    ALOAD_1     // Lorg/springframework/core/convert/TypeDescriptor; sourceType
                    ALOAD_2     // Lorg/springframework/core/convert/TypeDescriptor; targetType
                    INVOKESPECIAL org.springframework.core.convert.support.GenericConversionService.matchConverter (Lorg/springframework/core/convert/support/GenericConversionService$MatchableConverters;Lorg/springframework/core/convert/TypeDescriptor;Lorg/springframework/core/convert/TypeDescriptor;)Lorg/springframework/core/convert/converter/GenericConverter;
                    ARETURN
  end private org.springframework.core.convert.converter.GenericConverter getMatchingConverterForTarget(org.springframework.core.convert.TypeDescriptor, org.springframework.core.convert.TypeDescriptor, java.util.Map)

  private void addInterfaceHierarchy(Class, java.util.Set):
                    ALOAD_2     // Ljava/util/Set; interfaces   (line 452)
                    ALOAD_1     // Ljava/lang/Class; interfaceType
                    INVOKEINTERFACE java.util.Set.add (Ljava/lang/Object;)Z
                    POP
                    ALOAD_1     // Ljava/lang/Class; interfaceType   (line 453)
                    INVOKEVIRTUAL java.lang.Class.getInterfaces ()[Ljava/lang/Class;
                    DUP
                    ASTORE 6
                    ARRAYLENGTH
                    ISTORE 5
                    ICONST_0
                    ISTORE 4
                    GOTO L1
                L0: ALOAD 6
                    ILOAD 4
                    AALOAD
                    ASTORE_3
                    ALOAD_0     // Lorg/springframework/core/convert/support/GenericConversionService; this   (line 454)
                    ALOAD_3     // Ljava/lang/Class; inheritedInterface
                    ALOAD_2     // Ljava/util/Set; interfaces
                    INVOKESPECIAL org.springframework.core.convert.support.GenericConversionService.addInterfaceHierarchy (Ljava/lang/Class;Ljava/util/Set;)V
                    IINC 4 1   (line 453)
                L1: ILOAD 4
                    ILOAD 5
                    IF_ICMPLT L0
                    RETURN   (line 456)
  end private void addInterfaceHierarchy(Class, java.util.Set)

  private org.springframework.core.convert.converter.GenericConverter matchConverter(org.springframework.core.convert.support.GenericConversionService$MatchableConverters, org.springframework.core.convert.TypeDescriptor, org.springframework.core.convert.TypeDescriptor):
                    ALOAD_1     // Lorg/springframework/core/convert/support/GenericConversionService$MatchableConverters; matchable   (line 460)
                    IFNONNULL L0
                    ACONST_NULL   (line 461)
                    ARETURN
                L0: ALOAD_1     // Lorg/springframework/core/convert/support/GenericConversionService$MatchableConverters; matchable   (line 463)
                    ALOAD_2     // Lorg/springframework/core/convert/TypeDescriptor; sourceFieldType
                    ALOAD_3     // Lorg/springframework/core/convert/TypeDescriptor; targetFieldType
                    INVOKEVIRTUAL org.springframework.core.convert.support.GenericConversionService$MatchableConverters.matchConverter (Lorg/springframework/core/convert/TypeDescriptor;Lorg/springframework/core/convert/TypeDescriptor;)Lorg/springframework/core/convert/converter/GenericConverter;
                    ARETURN
  end private org.springframework.core.convert.converter.GenericConverter matchConverter(org.springframework.core.convert.support.GenericConversionService$MatchableConverters, org.springframework.core.convert.TypeDescriptor, org.springframework.core.convert.TypeDescriptor)

  private Object handleConverterNotFound(Object, org.springframework.core.convert.TypeDescriptor, org.springframework.core.convert.TypeDescriptor):
                    ALOAD_1     // Ljava/lang/Object; source   (line 467)
                    IFNONNULL L0
                    ALOAD_0     // Lorg/springframework/core/convert/support/GenericConversionService; this   (line 468)
                    ALOAD_2     // Lorg/springframework/core/convert/TypeDescriptor; sourceType
                    ALOAD_3     // Lorg/springframework/core/convert/TypeDescriptor; targetType
                    INVOKESPECIAL org.springframework.core.convert.support.GenericConversionService.assertNotPrimitiveTargetType (Lorg/springframework/core/convert/TypeDescriptor;Lorg/springframework/core/convert/TypeDescriptor;)V
                    ALOAD_1     // Ljava/lang/Object; source   (line 469)
                    ARETURN
                L0: ALOAD_2     // Lorg/springframework/core/convert/TypeDescriptor; sourceType   (line 471)
                    ALOAD_3     // Lorg/springframework/core/convert/TypeDescriptor; targetType
                    INVOKEVIRTUAL org.springframework.core.convert.TypeDescriptor.isAssignableTo (Lorg/springframework/core/convert/TypeDescriptor;)Z
                    IFEQ L1
                    ALOAD_3     // Lorg/springframework/core/convert/TypeDescriptor; targetType
                    INVOKEVIRTUAL org.springframework.core.convert.TypeDescriptor.getObjectType ()Ljava/lang/Class;
                    ALOAD_1     // Ljava/lang/Object; source
                    INVOKEVIRTUAL java.lang.Class.isInstance (Ljava/lang/Object;)Z
                    IFEQ L1
                    ALOAD_1     // Ljava/lang/Object; source   (line 472)
                    ARETURN
                L1: NEW org.springframework.core.convert.ConverterNotFoundException   (line 475)
                    DUP
                    ALOAD_2     // Lorg/springframework/core/convert/TypeDescriptor; sourceType
                    ALOAD_3     // Lorg/springframework/core/convert/TypeDescriptor; targetType
                    INVOKESPECIAL org.springframework.core.convert.ConverterNotFoundException.<init> (Lorg/springframework/core/convert/TypeDescriptor;Lorg/springframework/core/convert/TypeDescriptor;)V
                    ATHROW
  end private Object handleConverterNotFound(Object, org.springframework.core.convert.TypeDescriptor, org.springframework.core.convert.TypeDescriptor)

  private Object handleResult(org.springframework.core.convert.TypeDescriptor, org.springframework.core.convert.TypeDescriptor, Object):
                    ALOAD_3     // Ljava/lang/Object; result   (line 480)
                    IFNONNULL L0
                    ALOAD_0     // Lorg/springframework/core/convert/support/GenericConversionService; this   (line 481)
                    ALOAD_1     // Lorg/springframework/core/convert/TypeDescriptor; sourceType
                    ALOAD_2     // Lorg/springframework/core/convert/TypeDescriptor; targetType
                    INVOKESPECIAL org.springframework.core.convert.support.GenericConversionService.assertNotPrimitiveTargetType (Lorg/springframework/core/convert/TypeDescriptor;Lorg/springframework/core/convert/TypeDescriptor;)V
                L0: ALOAD_3     // Ljava/lang/Object; result   (line 483)
                    ARETURN
  end private Object handleResult(org.springframework.core.convert.TypeDescriptor, org.springframework.core.convert.TypeDescriptor, Object)

  private void assertNotPrimitiveTargetType(org.springframework.core.convert.TypeDescriptor, org.springframework.core.convert.TypeDescriptor):
                    ALOAD_2     // Lorg/springframework/core/convert/TypeDescriptor; targetType   (line 486)
                    INVOKEVIRTUAL org.springframework.core.convert.TypeDescriptor.isPrimitive ()Z
                    IFEQ L0
                    NEW org.springframework.core.convert.ConversionFailedException   (line 487)
                    DUP
                    ALOAD_1     // Lorg/springframework/core/convert/TypeDescriptor; sourceType
                    ALOAD_2     // Lorg/springframework/core/convert/TypeDescriptor; targetType
                    ACONST_NULL
                    NEW java.lang.IllegalArgumentException   (line 488)
                    DUP
                    LDC_W "A null value cannot be assigned to a primitive type"
                    INVOKESPECIAL java.lang.IllegalArgumentException.<init> (Ljava/lang/String;)V
                    INVOKESPECIAL org.springframework.core.convert.ConversionFailedException.<init> (Lorg/springframework/core/convert/TypeDescriptor;Lorg/springframework/core/convert/TypeDescriptor;Ljava/lang/Object;Ljava/lang/Throwable;)V   (line 487)
                    ATHROW
                L0: RETURN   (line 490)
  end private void assertNotPrimitiveTargetType(org.springframework.core.convert.TypeDescriptor, org.springframework.core.convert.TypeDescriptor)
end public class org.springframework.core.convert.support.GenericConversionService
 -- (NullPointerException) null
null
java.lang.NullPointerException

debug weaving 'org.springframework.core.convert.converter.GenericConverter'
---- org.aspectj.weaver.ltw.LTWWorld@28c97a5 ----
Class loader:
sun.misc.Launcher$AppClassLoader@18b4aac2
Class loader parent:
sun.misc.Launcher$ExtClassLoader@722c41f4
Shadow mungers:
(around(extraFlags: 3): ((((((((((within(@org.springframework.cache.annotation.CacheEvict *) && execution(public * @org.springframework.cache.annotation.CacheEvict *.*(..))) && this(BindingTypePattern(java.lang.Object, 0))) && persingleton(org.springframework.cache.aspectj.AnnotationCacheAspect)) || (((within(@org.springframework.cache.annotation.Caching *) && execution(public * @org.springframework.cache.annotation.Caching *.*(..))) && this(BindingTypePattern(java.lang.Object, 0))) && persingleton(org.springframework.cache.aspectj.AnnotationCacheAspect))) || (((within(@org.springframework.cache.annotation.CachePut *) && execution(public * @org.springframework.cache.annotation.CachePut *.*(..))) && this(BindingTypePattern(java.lang.Object, 0))) && persingleton(org.springframework.cache.aspectj.AnnotationCacheAspect))) || (((within(@org.springframework.cache.annotation.Cacheable *) && execution(public * @org.springframework.cache.annotation.Cacheable *.*(..))) && this(BindingTypePattern(java.lang.Object, 0))) && persingleton(org.springframework.cache.aspectj.AnnotationCacheAspect))) || ((execution(@org.springframework.cache.annotation.Caching * *(..)) && this(BindingTypePattern(java.lang.Object, 0))) && persingleton(org.springframework.cache.aspectj.AnnotationCacheAspect))) || ((execution(@org.springframework.cache.annotation.Cacheable * *(..)) && this(BindingTypePattern(java.lang.Object, 0))) && persingleton(org.springframework.cache.aspectj.AnnotationCacheAspect))) || ((execution(@org.springframework.cache.annotation.CacheEvict * *(..)) && this(BindingTypePattern(java.lang.Object, 0))) && persingleton(org.springframework.cache.aspectj.AnnotationCacheAspect))) || ((execution(@org.springframework.cache.annotation.CachePut * *(..)) && this(BindingTypePattern(java.lang.Object, 0))) && persingleton(org.springframework.cache.aspectj.AnnotationCacheAspect)))->java.lang.Object org.springframework.cache.aspectj.AbstractCacheAspect.ajc$around$org_springframework_cache_aspectj_AbstractCacheAspect$1$2bc714b5(java.lang.Object, org.aspectj.runtime.internal.AroundClosure, org.aspectj.lang.JoinPoint))
(around(extraFlags: 5): ((execution(@org.springframework.scheduling.annotation.Async (void || java.util.concurrent.Future+) *(..)) && persingleton(org.springframework.scheduling.aspectj.AnnotationAsyncExecutionAspect)) || (execution((void || java.util.concurrent.Future+) @org.springframework.scheduling.annotation.Async *.*(..)) && persingleton(org.springframework.scheduling.aspectj.AnnotationAsyncExecutionAspect)))->java.lang.Object org.springframework.scheduling.aspectj.AbstractAsyncExecutionAspect.ajc$around$org_springframework_scheduling_aspectj_AbstractAsyncExecutionAspect$1$6c004c3e(org.aspectj.runtime.internal.AroundClosure, org.aspectj.lang.JoinPoint$StaticPart))
org.aspectj.weaver.Checker@5abff562
org.aspectj.weaver.Checker@12140c1d
(before(extraFlags: 4): ((((within(@org.springframework.transaction.annotation.Transactional *) && execution(public * @org.springframework.transaction.annotation.Transactional *.*(..))) && this(BindingTypePattern(java.lang.Object, 0))) && persingleton(org.springframework.transaction.aspectj.AnnotationTransactionAspect)) || ((execution(@org.springframework.transaction.annotation.Transactional * *(..)) && this(BindingTypePattern(java.lang.Object, 0))) && persingleton(org.springframework.transaction.aspectj.AnnotationTransactionAspect)))->void org.springframework.transaction.aspectj.AbstractTransactionAspect.ajc$before$org_springframework_transaction_aspectj_AbstractTransactionAspect$1$2a73e96c(java.lang.Object, org.aspectj.lang.JoinPoint$StaticPart))
(afterThrowing(extraFlags: 1): ((((within(@org.springframework.transaction.annotation.Transactional *) && execution(public * @org.springframework.transaction.annotation.Transactional *.*(..))) && this(BindingTypePattern(java.lang.Object, 0))) && persingleton(org.springframework.transaction.aspectj.AnnotationTransactionAspect)) || ((execution(@org.springframework.transaction.annotation.Transactional * *(..)) && this(BindingTypePattern(java.lang.Object, 0))) && persingleton(org.springframework.transaction.aspectj.AnnotationTransactionAspect)))->void org.springframework.transaction.aspectj.AbstractTransactionAspect.ajc$afterThrowing$org_springframework_transaction_aspectj_AbstractTransactionAspect$2$2a73e96c(java.lang.Object, java.lang.Throwable))
(afterReturning: ((((within(@org.springframework.transaction.annotation.Transactional *) && execution(public * @org.springframework.transaction.annotation.Transactional *.*(..))) && this(BindingTypePattern(java.lang.Object, 0))) && persingleton(org.springframework.transaction.aspectj.AnnotationTransactionAspect)) || ((execution(@org.springframework.transaction.annotation.Transactional * *(..)) && this(BindingTypePattern(java.lang.Object, 0))) && persingleton(org.springframework.transaction.aspectj.AnnotationTransactionAspect)))->void org.springframework.transaction.aspectj.AbstractTransactionAspect.ajc$afterReturning$org_springframework_transaction_aspectj_AbstractTransactionAspect$3$2a73e96c(java.lang.Object))
(after: ((((within(@org.springframework.transaction.annotation.Transactional *) && execution(public * @org.springframework.transaction.annotation.Transactional *.*(..))) && this(BindingTypePattern(java.lang.Object, 0))) && persingleton(org.springframework.transaction.aspectj.AnnotationTransactionAspect)) || ((execution(@org.springframework.transaction.annotation.Transactional * *(..)) && this(BindingTypePattern(java.lang.Object, 0))) && persingleton(org.springframework.transaction.aspectj.AnnotationTransactionAspect)))->void org.springframework.transaction.aspectj.AbstractTransactionAspect.ajc$after$org_springframework_transaction_aspectj_AbstractTransactionAspect$4$2a73e96c(java.lang.Object))
(before: (((((initialization(org.springframework.beans.factory.aspectj.ConfigurableObject.new(..)) && initialization(org.springframework.beans.factory.aspectj.ConfigurableObject+.new(..))) && this(BindingTypePattern(java.lang.Object, 0))) && @this(org.springframework.beans.factory.annotation.Configurable)) && if(boolean org.springframework.beans.factory.aspectj.AnnotationBeanConfigurerAspect.ajc$if$bb0(org.springframework.beans.factory.annotation.Configurable))) && persingleton(org.springframework.beans.factory.aspectj.AnnotationBeanConfigurerAspect))->void org.springframework.beans.factory.aspectj.AbstractDependencyInjectionAspect.ajc$before$org_springframework_beans_factory_aspectj_AbstractDependencyInjectionAspect$1$e854fa65(java.lang.Object))
(afterReturning: (((((initialization(org.springframework.beans.factory.aspectj.ConfigurableObject+.new(..)) && this(BindingTypePattern(java.lang.Object, 0))) && @this(org.springframework.beans.factory.annotation.Configurable)) && !(@this(org.springframework.beans.factory.annotation.Configurable) && if(boolean org.springframework.beans.factory.aspectj.AnnotationBeanConfigurerAspect.ajc$if$bb0(org.springframework.beans.factory.annotation.Configurable)))) && if(boolean org.springframework.beans.factory.aspectj.AbstractDependencyInjectionAspect.ajc$if$6f1(org.aspectj.lang.JoinPoint))) && persingleton(org.springframework.beans.factory.aspectj.AnnotationBeanConfigurerAspect))->void org.springframework.beans.factory.aspectj.AbstractDependencyInjectionAspect.ajc$afterReturning$org_springframework_beans_factory_aspectj_AbstractDependencyInjectionAspect$2$1ea6722c(java.lang.Object))
(afterReturning: (((execution(java.lang.Object org.springframework.beans.factory.aspectj.AbstractInterfaceDrivenDependencyInjectionAspect$ConfigurableDeserializationSupport+.readResolve()) && this(BindingTypePattern(java.lang.Object, 0))) && @this(org.springframework.beans.factory.annotation.Configurable)) && persingleton(org.springframework.beans.factory.aspectj.AnnotationBeanConfigurerAspect))->void org.springframework.beans.factory.aspectj.AbstractDependencyInjectionAspect.ajc$afterReturning$org_springframework_beans_factory_aspectj_AbstractDependencyInjectionAspect$3$6aa27052(java.lang.Object))
Type mungers:
(BcelTypeMunger ResolvedTypeMunger(Method, java.lang.Object org.springframework.beans.factory.aspectj.AbstractInterfaceDrivenDependencyInjectionAspect$ConfigurableDeserializationSupport.readResolve()))
(BcelTypeMunger ExposeTypeMunger(java.lang.Object))
(BcelTypeMunger ExposeTypeMunger(java.lang.Object))
(BcelTypeMunger ExposeTypeMunger(java.lang.Object))
(BcelTypeMunger ExposeTypeMunger(org.springframework.beans.factory.aspectj.ConfigurableObject))
(BcelTypeMunger ExposeTypeMunger(org.springframework.beans.factory.aspectj.AbstractInterfaceDrivenDependencyInjectionAspect$ConfigurableDeserializationSupport))
Late Type mungers:
Empty
