---- AspectJ Properties ---
AspectJ Compiler 1.6.2 built on Saturday Oct 4, 2008 at 05:47:07 GMT
---- Dump Properties ---
Dump file: ajcore.20160604.114257.970.txt
Dump reason: org.aspectj.bridge.AbortException
Dump on exception: true
Dump at exit condition: abort
---- Exception Information ---
Message: abort trouble in: 
public abstract class org.springframework.beans.factory.BeanFactoryUtils extends java.lang.Object:
  public static final String GENERATED_BEAN_NAME_SEPARATOR = "#"
  public void <init>():
                    ALOAD_0     // Lorg/springframework/beans/factory/BeanFactoryUtils; this   (line 44)
                    INVOKESPECIAL java.lang.Object.<init> ()V
    constructor-execution(void org.springframework.beans.factory.BeanFactoryUtils.<init>())
    |               RETURN
    constructor-execution(void org.springframework.beans.factory.BeanFactoryUtils.<init>())
  end public void <init>()

  public static boolean isFactoryDereference(String):
                    ALOAD_0     // Ljava/lang/String; name   (line 61)
                    IFNULL L0
                    ALOAD_0     // Ljava/lang/String; name
                    LDC "&"
                    INVOKEVIRTUAL java.lang.String.startsWith (Ljava/lang/String;)Z
                    IFEQ L0
                    ICONST_1
                    IRETURN
                L0: ICONST_0
                    IRETURN
  end public static boolean isFactoryDereference(String)

  public static String transformedBeanName(String):
                    ALOAD_0     // Ljava/lang/String; name   (line 72)
                    LDC "'name' must not be null"
                    INVOKESTATIC org.springframework.util.Assert.notNull (Ljava/lang/Object;Ljava/lang/String;)V
                    ALOAD_0     // Ljava/lang/String; name   (line 73)
                    ASTORE_1
                    GOTO L1   (line 74)
                L0: ALOAD_1     // Ljava/lang/String; beanName   (line 75)
                    LDC "&"
                    INVOKEVIRTUAL java.lang.String.length ()I
                    INVOKEVIRTUAL java.lang.String.substring (I)Ljava/lang/String;
                    ASTORE_1     // Ljava/lang/String; beanName
                L1: ALOAD_1     // Ljava/lang/String; beanName   (line 74)
                    LDC "&"
                    INVOKEVIRTUAL java.lang.String.startsWith (Ljava/lang/String;)Z
                    IFNE L0
                    ALOAD_1     // Ljava/lang/String; beanName   (line 77)
                    ARETURN
  end public static String transformedBeanName(String)

  public static boolean isGeneratedBeanName(String):
                    ALOAD_0     // Ljava/lang/String; name   (line 90)
                    IFNULL L0
                    ALOAD_0     // Ljava/lang/String; name
                    LDC "#"
                    INVOKEVIRTUAL java.lang.String.contains (Ljava/lang/CharSequence;)Z
                    IFEQ L0
                    ICONST_1
                    IRETURN
                L0: ICONST_0
                    IRETURN
  end public static boolean isGeneratedBeanName(String)

  public static String originalBeanName(String):
                    ALOAD_0     // Ljava/lang/String; name   (line 101)
                    LDC "'name' must not be null"
                    INVOKESTATIC org.springframework.util.Assert.notNull (Ljava/lang/Object;Ljava/lang/String;)V
                    ALOAD_0     // Ljava/lang/String; name   (line 102)
                    LDC "#"
                    INVOKEVIRTUAL java.lang.String.indexOf (Ljava/lang/String;)I
                    ISTORE_1
                    ILOAD_1     // I separatorIndex   (line 103)
                    ICONST_M1
                    IF_ICMPEQ L0
                    ALOAD_0     // Ljava/lang/String; name
                    ICONST_0
                    ILOAD_1     // I separatorIndex
                    INVOKEVIRTUAL java.lang.String.substring (II)Ljava/lang/String;
                    GOTO L1
                L0: ALOAD_0     // Ljava/lang/String; name
                L1: ARETURN
  end public static String originalBeanName(String)

  public static int countBeansIncludingAncestors(org.springframework.beans.factory.ListableBeanFactory):
                    ALOAD_0     // Lorg/springframework/beans/factory/ListableBeanFactory; lbf   (line 116)
                    INVOKESTATIC org.springframework.beans.factory.BeanFactoryUtils.beanNamesIncludingAncestors (Lorg/springframework/beans/factory/ListableBeanFactory;)[Ljava/lang/String;
                    ARRAYLENGTH
                    IRETURN
  end public static int countBeansIncludingAncestors(org.springframework.beans.factory.ListableBeanFactory)

  public static String[] beanNamesIncludingAncestors(org.springframework.beans.factory.ListableBeanFactory):
                    ALOAD_0     // Lorg/springframework/beans/factory/ListableBeanFactory; lbf   (line 126)
                    LDC java.lang.Object
                    INVOKESTATIC org.springframework.beans.factory.BeanFactoryUtils.beanNamesForTypeIncludingAncestors (Lorg/springframework/beans/factory/ListableBeanFactory;Ljava/lang/Class;)[Ljava/lang/String;
                    ARETURN
  end public static String[] beanNamesIncludingAncestors(org.springframework.beans.factory.ListableBeanFactory)

  public static String[] beanNamesForTypeIncludingAncestors(org.springframework.beans.factory.ListableBeanFactory, Class):
                    ALOAD_0     // Lorg/springframework/beans/factory/ListableBeanFactory; lbf   (line 143)
                    LDC "ListableBeanFactory must not be null"
                    INVOKESTATIC org.springframework.util.Assert.notNull (Ljava/lang/Object;Ljava/lang/String;)V
                    ALOAD_0     // Lorg/springframework/beans/factory/ListableBeanFactory; lbf   (line 144)
                    ALOAD_1     // Ljava/lang/Class; type
                    INVOKEINTERFACE org.springframework.beans.factory.ListableBeanFactory.getBeanNamesForType (Ljava/lang/Class;)[Ljava/lang/String;
                    ASTORE_2
                    ALOAD_0     // Lorg/springframework/beans/factory/ListableBeanFactory; lbf   (line 145)
                    INSTANCEOF org.springframework.beans.factory.HierarchicalBeanFactory
                    IFEQ L3
                    ALOAD_0     // Lorg/springframework/beans/factory/ListableBeanFactory; lbf   (line 146)
                    CHECKCAST org.springframework.beans.factory.HierarchicalBeanFactory
                    ASTORE_3
                    ALOAD_3     // Lorg/springframework/beans/factory/HierarchicalBeanFactory; hbf   (line 147)
                    INVOKEINTERFACE org.springframework.beans.factory.HierarchicalBeanFactory.getParentBeanFactory ()Lorg/springframework/beans/factory/BeanFactory;
                    INSTANCEOF org.springframework.beans.factory.ListableBeanFactory
                    IFEQ L3
                    ALOAD_3     // Lorg/springframework/beans/factory/HierarchicalBeanFactory; hbf   (line 149)
                    INVOKEINTERFACE org.springframework.beans.factory.HierarchicalBeanFactory.getParentBeanFactory ()Lorg/springframework/beans/factory/BeanFactory;
                    CHECKCAST org.springframework.beans.factory.ListableBeanFactory
                    ALOAD_1     // Ljava/lang/Class; type
                    INVOKESTATIC org.springframework.beans.factory.BeanFactoryUtils.beanNamesForTypeIncludingAncestors (Lorg/springframework/beans/factory/ListableBeanFactory;Ljava/lang/Class;)[Ljava/lang/String;   (line 148)
                    ASTORE 4
                    NEW java.util.ArrayList   (line 150)
                    DUP
                    INVOKESPECIAL java.util.ArrayList.<init> ()V
                    ASTORE 5
                    ALOAD 5     // Ljava/util/List; resultList   (line 151)
                    ALOAD_2     // [Ljava/lang/String; result
                    INVOKESTATIC java.util.Arrays.asList ([Ljava/lang/Object;)Ljava/util/List;
                    CHECKCAST java.util.Collection
                    INVOKEINTERFACE java.util.List.addAll (Ljava/util/Collection;)Z
                    POP
                    ALOAD 4     // [Ljava/lang/String; parentResult   (line 152)
                    DUP
                    ASTORE 9
                    ARRAYLENGTH
                    ISTORE 8
                    ICONST_0
                    ISTORE 7
                    GOTO L2
                L0: ALOAD 9
                    ILOAD 7
                    AALOAD
                    ASTORE 6
                    ALOAD 5     // Ljava/util/List; resultList   (line 153)
                    ALOAD 6     // Ljava/lang/String; beanName
                    INVOKEINTERFACE java.util.List.contains (Ljava/lang/Object;)Z
                    IFNE L1
                    ALOAD_3     // Lorg/springframework/beans/factory/HierarchicalBeanFactory; hbf
                    ALOAD 6     // Ljava/lang/String; beanName
                    INVOKEINTERFACE org.springframework.beans.factory.HierarchicalBeanFactory.containsLocalBean (Ljava/lang/String;)Z
                    IFNE L1
                    ALOAD 5     // Ljava/util/List; resultList   (line 154)
                    ALOAD 6     // Ljava/lang/String; beanName
                    INVOKEINTERFACE java.util.List.add (Ljava/lang/Object;)Z
                    POP
                L1: IINC 7 1   (line 152)
                L2: ILOAD 7
                    ILOAD 8
                    IF_ICMPLT L0
                    ALOAD 5     // Ljava/util/List; resultList   (line 157)
                    INVOKESTATIC org.springframework.util.StringUtils.toStringArray (Ljava/util/Collection;)[Ljava/lang/String;
                    ASTORE_2     // [Ljava/lang/String; result
                L3: ALOAD_2     // [Ljava/lang/String; result   (line 160)
                    ARETURN
  end public static String[] beanNamesForTypeIncludingAncestors(org.springframework.beans.factory.ListableBeanFactory, Class)

  public static String[] beanNamesForTypeIncludingAncestors(org.springframework.beans.factory.ListableBeanFactory, Class, boolean, boolean):
                    ALOAD_0     // Lorg/springframework/beans/factory/ListableBeanFactory; lbf   (line 186)
                    LDC "ListableBeanFactory must not be null"
                    INVOKESTATIC org.springframework.util.Assert.notNull (Ljava/lang/Object;Ljava/lang/String;)V
                    ALOAD_0     // Lorg/springframework/beans/factory/ListableBeanFactory; lbf   (line 187)
                    ALOAD_1     // Ljava/lang/Class; type
                    ILOAD_2     // Z includeNonSingletons
                    ILOAD_3     // Z allowEagerInit
                    INVOKEINTERFACE org.springframework.beans.factory.ListableBeanFactory.getBeanNamesForType (Ljava/lang/Class;ZZ)[Ljava/lang/String;
                    ASTORE 4
                    ALOAD_0     // Lorg/springframework/beans/factory/ListableBeanFactory; lbf   (line 188)
                    INSTANCEOF org.springframework.beans.factory.HierarchicalBeanFactory
                    IFEQ L3
                    ALOAD_0     // Lorg/springframework/beans/factory/ListableBeanFactory; lbf   (line 189)
                    CHECKCAST org.springframework.beans.factory.HierarchicalBeanFactory
                    ASTORE 5
                    ALOAD 5     // Lorg/springframework/beans/factory/HierarchicalBeanFactory; hbf   (line 190)
                    INVOKEINTERFACE org.springframework.beans.factory.HierarchicalBeanFactory.getParentBeanFactory ()Lorg/springframework/beans/factory/BeanFactory;
                    INSTANCEOF org.springframework.beans.factory.ListableBeanFactory
                    IFEQ L3
                    ALOAD 5     // Lorg/springframework/beans/factory/HierarchicalBeanFactory; hbf   (line 192)
                    INVOKEINTERFACE org.springframework.beans.factory.HierarchicalBeanFactory.getParentBeanFactory ()Lorg/springframework/beans/factory/BeanFactory;
                    CHECKCAST org.springframework.beans.factory.ListableBeanFactory
                    ALOAD_1     // Ljava/lang/Class; type
                    ILOAD_2     // Z includeNonSingletons
                    ILOAD_3     // Z allowEagerInit
                    INVOKESTATIC org.springframework.beans.factory.BeanFactoryUtils.beanNamesForTypeIncludingAncestors (Lorg/springframework/beans/factory/ListableBeanFactory;Ljava/lang/Class;ZZ)[Ljava/lang/String;   (line 191)
                    ASTORE 6
                    NEW java.util.ArrayList   (line 193)
                    DUP
                    INVOKESPECIAL java.util.ArrayList.<init> ()V
                    ASTORE 7
                    ALOAD 7     // Ljava/util/List; resultList   (line 194)
                    ALOAD 4     // [Ljava/lang/String; result
                    INVOKESTATIC java.util.Arrays.asList ([Ljava/lang/Object;)Ljava/util/List;
                    CHECKCAST java.util.Collection
                    INVOKEINTERFACE java.util.List.addAll (Ljava/util/Collection;)Z
                    POP
                    ALOAD 6     // [Ljava/lang/String; parentResult   (line 195)
                    DUP
                    ASTORE 11
                    ARRAYLENGTH
                    ISTORE 10
                    ICONST_0
                    ISTORE 9
                    GOTO L2
                L0: ALOAD 11
                    ILOAD 9
                    AALOAD
                    ASTORE 8
                    ALOAD 7     // Ljava/util/List; resultList   (line 196)
                    ALOAD 8     // Ljava/lang/String; beanName
                    INVOKEINTERFACE java.util.List.contains (Ljava/lang/Object;)Z
                    IFNE L1
                    ALOAD 5     // Lorg/springframework/beans/factory/HierarchicalBeanFactory; hbf
                    ALOAD 8     // Ljava/lang/String; beanName
                    INVOKEINTERFACE org.springframework.beans.factory.HierarchicalBeanFactory.containsLocalBean (Ljava/lang/String;)Z
                    IFNE L1
                    ALOAD 7     // Ljava/util/List; resultList   (line 197)
                    ALOAD 8     // Ljava/lang/String; beanName
                    INVOKEINTERFACE java.util.List.add (Ljava/lang/Object;)Z
                    POP
                L1: IINC 9 1   (line 195)
                L2: ILOAD 9
                    ILOAD 10
                    IF_ICMPLT L0
                    ALOAD 7     // Ljava/util/List; resultList   (line 200)
                    INVOKESTATIC org.springframework.util.StringUtils.toStringArray (Ljava/util/Collection;)[Ljava/lang/String;
                    ASTORE 4     // [Ljava/lang/String; result
                L3: ALOAD 4     // [Ljava/lang/String; result   (line 203)
                    ARETURN
  end public static String[] beanNamesForTypeIncludingAncestors(org.springframework.beans.factory.ListableBeanFactory, Class, boolean, boolean)

  public static java.util.Map beansOfTypeIncludingAncestors(org.springframework.beans.factory.ListableBeanFactory, Class) throws org.springframework.beans.BeansException:
                    ALOAD_0     // Lorg/springframework/beans/factory/ListableBeanFactory; lbf   (line 226)
                    LDC "ListableBeanFactory must not be null"
                    INVOKESTATIC org.springframework.util.Assert.notNull (Ljava/lang/Object;Ljava/lang/String;)V
                    NEW java.util.LinkedHashMap   (line 227)
                    DUP
                    ICONST_4
                    INVOKESPECIAL java.util.LinkedHashMap.<init> (I)V
                    ASTORE_2
                    ALOAD_2     // Ljava/util/Map; result   (line 228)
                    ALOAD_0     // Lorg/springframework/beans/factory/ListableBeanFactory; lbf
                    ALOAD_1     // Ljava/lang/Class; type
                    INVOKEINTERFACE org.springframework.beans.factory.ListableBeanFactory.getBeansOfType (Ljava/lang/Class;)Ljava/util/Map;
                    INVOKEINTERFACE java.util.Map.putAll (Ljava/util/Map;)V
                    ALOAD_0     // Lorg/springframework/beans/factory/ListableBeanFactory; lbf   (line 229)
                    INSTANCEOF org.springframework.beans.factory.HierarchicalBeanFactory
                    IFEQ L2
                    ALOAD_0     // Lorg/springframework/beans/factory/ListableBeanFactory; lbf   (line 230)
                    CHECKCAST org.springframework.beans.factory.HierarchicalBeanFactory
                    ASTORE_3
                    ALOAD_3     // Lorg/springframework/beans/factory/HierarchicalBeanFactory; hbf   (line 231)
                    INVOKEINTERFACE org.springframework.beans.factory.HierarchicalBeanFactory.getParentBeanFactory ()Lorg/springframework/beans/factory/BeanFactory;
                    INSTANCEOF org.springframework.beans.factory.ListableBeanFactory
                    IFEQ L2
                    ALOAD_3     // Lorg/springframework/beans/factory/HierarchicalBeanFactory; hbf   (line 233)
                    INVOKEINTERFACE org.springframework.beans.factory.HierarchicalBeanFactory.getParentBeanFactory ()Lorg/springframework/beans/factory/BeanFactory;
                    CHECKCAST org.springframework.beans.factory.ListableBeanFactory
                    ALOAD_1     // Ljava/lang/Class; type
                    INVOKESTATIC org.springframework.beans.factory.BeanFactoryUtils.beansOfTypeIncludingAncestors (Lorg/springframework/beans/factory/ListableBeanFactory;Ljava/lang/Class;)Ljava/util/Map;   (line 232)
                    ASTORE 4
                    ALOAD 4     // Ljava/util/Map; parentResult   (line 234)
                    INVOKEINTERFACE java.util.Map.entrySet ()Ljava/util/Set;
                    INVOKEINTERFACE java.util.Set.iterator ()Ljava/util/Iterator;
                    ASTORE 6
                    GOTO L1
                L0: ALOAD 6
                    INVOKEINTERFACE java.util.Iterator.next ()Ljava/lang/Object;
                    CHECKCAST java.util.Map$Entry
                    ASTORE 5
                    ALOAD 5     // Ljava/util/Map$Entry; entry   (line 235)
                    INVOKEINTERFACE java.util.Map$Entry.getKey ()Ljava/lang/Object;
                    CHECKCAST java.lang.String
                    ASTORE 7
                    ALOAD_2     // Ljava/util/Map; result   (line 236)
                    ALOAD 7     // Ljava/lang/String; beanName
                    INVOKEINTERFACE java.util.Map.containsKey (Ljava/lang/Object;)Z
                    IFNE L1
                    ALOAD_3     // Lorg/springframework/beans/factory/HierarchicalBeanFactory; hbf
                    ALOAD 7     // Ljava/lang/String; beanName
                    INVOKEINTERFACE org.springframework.beans.factory.HierarchicalBeanFactory.containsLocalBean (Ljava/lang/String;)Z
                    IFNE L1
                    ALOAD_2     // Ljava/util/Map; result   (line 237)
                    ALOAD 7     // Ljava/lang/String; beanName
                    ALOAD 5     // Ljava/util/Map$Entry; entry
                    INVOKEINTERFACE java.util.Map$Entry.getValue ()Ljava/lang/Object;
                    INVOKEINTERFACE java.util.Map.put (Ljava/lang/Object;Ljava/lang/Object;)Ljava/lang/Object;
                    POP
                L1: ALOAD 6   (line 234)
                    INVOKEINTERFACE java.util.Iterator.hasNext ()Z
                    IFNE L0
                L2: ALOAD_2     // Ljava/util/Map; result   (line 242)
                    ARETURN
  end public static java.util.Map beansOfTypeIncludingAncestors(org.springframework.beans.factory.ListableBeanFactory, Class) throws org.springframework.beans.BeansException

  public static java.util.Map beansOfTypeIncludingAncestors(org.springframework.beans.factory.ListableBeanFactory, Class, boolean, boolean) throws org.springframework.beans.BeansException:
                    ALOAD_0     // Lorg/springframework/beans/factory/ListableBeanFactory; lbf   (line 275)
                    LDC "ListableBeanFactory must not be null"
                    INVOKESTATIC org.springframework.util.Assert.notNull (Ljava/lang/Object;Ljava/lang/String;)V
                    NEW java.util.LinkedHashMap   (line 276)
                    DUP
                    ICONST_4
                    INVOKESPECIAL java.util.LinkedHashMap.<init> (I)V
                    ASTORE 4
                    ALOAD 4     // Ljava/util/Map; result   (line 277)
                    ALOAD_0     // Lorg/springframework/beans/factory/ListableBeanFactory; lbf
                    ALOAD_1     // Ljava/lang/Class; type
                    ILOAD_2     // Z includeNonSingletons
                    ILOAD_3     // Z allowEagerInit
                    INVOKEINTERFACE org.springframework.beans.factory.ListableBeanFactory.getBeansOfType (Ljava/lang/Class;ZZ)Ljava/util/Map;
                    INVOKEINTERFACE java.util.Map.putAll (Ljava/util/Map;)V
                    ALOAD_0     // Lorg/springframework/beans/factory/ListableBeanFactory; lbf   (line 278)
                    INSTANCEOF org.springframework.beans.factory.HierarchicalBeanFactory
                    IFEQ L2
                    ALOAD_0     // Lorg/springframework/beans/factory/ListableBeanFactory; lbf   (line 279)
                    CHECKCAST org.springframework.beans.factory.HierarchicalBeanFactory
                    ASTORE 5
                    ALOAD 5     // Lorg/springframework/beans/factory/HierarchicalBeanFactory; hbf   (line 280)
                    INVOKEINTERFACE org.springframework.beans.factory.HierarchicalBeanFactory.getParentBeanFactory ()Lorg/springframework/beans/factory/BeanFactory;
                    INSTANCEOF org.springframework.beans.factory.ListableBeanFactory
                    IFEQ L2
                    ALOAD 5     // Lorg/springframework/beans/factory/HierarchicalBeanFactory; hbf   (line 282)
                    INVOKEINTERFACE org.springframework.beans.factory.HierarchicalBeanFactory.getParentBeanFactory ()Lorg/springframework/beans/factory/BeanFactory;
                    CHECKCAST org.springframework.beans.factory.ListableBeanFactory
                    ALOAD_1     // Ljava/lang/Class; type
                    ILOAD_2     // Z includeNonSingletons
                    ILOAD_3     // Z allowEagerInit
                    INVOKESTATIC org.springframework.beans.factory.BeanFactoryUtils.beansOfTypeIncludingAncestors (Lorg/springframework/beans/factory/ListableBeanFactory;Ljava/lang/Class;ZZ)Ljava/util/Map;   (line 281)
                    ASTORE 6
                    ALOAD 6     // Ljava/util/Map; parentResult   (line 283)
                    INVOKEINTERFACE java.util.Map.entrySet ()Ljava/util/Set;
                    INVOKEINTERFACE java.util.Set.iterator ()Ljava/util/Iterator;
                    ASTORE 8
                    GOTO L1
                L0: ALOAD 8
                    INVOKEINTERFACE java.util.Iterator.next ()Ljava/lang/Object;
                    CHECKCAST java.util.Map$Entry
                    ASTORE 7
                    ALOAD 7     // Ljava/util/Map$Entry; entry   (line 284)
                    INVOKEINTERFACE java.util.Map$Entry.getKey ()Ljava/lang/Object;
                    CHECKCAST java.lang.String
                    ASTORE 9
                    ALOAD 4     // Ljava/util/Map; result   (line 285)
                    ALOAD 9     // Ljava/lang/String; beanName
                    INVOKEINTERFACE java.util.Map.containsKey (Ljava/lang/Object;)Z
                    IFNE L1
                    ALOAD 5     // Lorg/springframework/beans/factory/HierarchicalBeanFactory; hbf
                    ALOAD 9     // Ljava/lang/String; beanName
                    INVOKEINTERFACE org.springframework.beans.factory.HierarchicalBeanFactory.containsLocalBean (Ljava/lang/String;)Z
                    IFNE L1
                    ALOAD 4     // Ljava/util/Map; result   (line 286)
                    ALOAD 9     // Ljava/lang/String; beanName
                    ALOAD 7     // Ljava/util/Map$Entry; entry
                    INVOKEINTERFACE java.util.Map$Entry.getValue ()Ljava/lang/Object;
                    INVOKEINTERFACE java.util.Map.put (Ljava/lang/Object;Ljava/lang/Object;)Ljava/lang/Object;
                    POP
                L1: ALOAD 8   (line 283)
                    INVOKEINTERFACE java.util.Iterator.hasNext ()Z
                    IFNE L0
                L2: ALOAD 4     // Ljava/util/Map; result   (line 291)
                    ARETURN
  end public static java.util.Map beansOfTypeIncludingAncestors(org.springframework.beans.factory.ListableBeanFactory, Class, boolean, boolean) throws org.springframework.beans.BeansException

  public static Object beanOfTypeIncludingAncestors(org.springframework.beans.factory.ListableBeanFactory, Class) throws org.springframework.beans.BeansException:
                    ALOAD_0     // Lorg/springframework/beans/factory/ListableBeanFactory; lbf   (line 320)
                    ALOAD_1     // Ljava/lang/Class; type
                    INVOKESTATIC org.springframework.beans.factory.BeanFactoryUtils.beansOfTypeIncludingAncestors (Lorg/springframework/beans/factory/ListableBeanFactory;Ljava/lang/Class;)Ljava/util/Map;
                    ASTORE_2
                    ALOAD_2     // Ljava/util/Map; beansOfType   (line 321)
                    INVOKEINTERFACE java.util.Map.size ()I
                    ICONST_1
                    IF_ICMPNE L0
                    ALOAD_2     // Ljava/util/Map; beansOfType   (line 322)
                    INVOKEINTERFACE java.util.Map.values ()Ljava/util/Collection;
                    INVOKEINTERFACE java.util.Collection.iterator ()Ljava/util/Iterator;
                    INVOKEINTERFACE java.util.Iterator.next ()Ljava/lang/Object;
                    ARETURN
                L0: NEW org.springframework.beans.factory.NoSuchBeanDefinitionException   (line 325)
                    DUP
                    ALOAD_1     // Ljava/lang/Class; type
                    NEW java.lang.StringBuilder
                    DUP
                    LDC "expected single bean but found "
                    INVOKESPECIAL java.lang.StringBuilder.<init> (Ljava/lang/String;)V
                    ALOAD_2     // Ljava/util/Map; beansOfType
                    INVOKEINTERFACE java.util.Map.size ()I
                    INVOKEVIRTUAL java.lang.StringBuilder.append (I)Ljava/lang/StringBuilder;
                    INVOKEVIRTUAL java.lang.StringBuilder.toString ()Ljava/lang/String;
                    INVOKESPECIAL org.springframework.beans.factory.NoSuchBeanDefinitionException.<init> (Ljava/lang/Class;Ljava/lang/String;)V
                    ATHROW
  end public static Object beanOfTypeIncludingAncestors(org.springframework.beans.factory.ListableBeanFactory, Class) throws org.springframework.beans.BeansException

  public static Object beanOfTypeIncludingAncestors(org.springframework.beans.factory.ListableBeanFactory, Class, boolean, boolean) throws org.springframework.beans.BeansException:
                    ALOAD_0     // Lorg/springframework/beans/factory/ListableBeanFactory; lbf   (line 362)
                    ALOAD_1     // Ljava/lang/Class; type
                    ILOAD_2     // Z includeNonSingletons
                    ILOAD_3     // Z allowEagerInit
                    INVOKESTATIC org.springframework.beans.factory.BeanFactoryUtils.beansOfTypeIncludingAncestors (Lorg/springframework/beans/factory/ListableBeanFactory;Ljava/lang/Class;ZZ)Ljava/util/Map;
                    ASTORE 4
                    ALOAD 4     // Ljava/util/Map; beansOfType   (line 363)
                    INVOKEINTERFACE java.util.Map.size ()I
                    ICONST_1
                    IF_ICMPNE L0
                    ALOAD 4     // Ljava/util/Map; beansOfType   (line 364)
                    INVOKEINTERFACE java.util.Map.values ()Ljava/util/Collection;
                    INVOKEINTERFACE java.util.Collection.iterator ()Ljava/util/Iterator;
                    INVOKEINTERFACE java.util.Iterator.next ()Ljava/lang/Object;
                    ARETURN
                L0: NEW org.springframework.beans.factory.NoSuchBeanDefinitionException   (line 367)
                    DUP
                    ALOAD_1     // Ljava/lang/Class; type
                    NEW java.lang.StringBuilder
                    DUP
                    LDC "expected single bean but found "
                    INVOKESPECIAL java.lang.StringBuilder.<init> (Ljava/lang/String;)V
                    ALOAD 4     // Ljava/util/Map; beansOfType
                    INVOKEINTERFACE java.util.Map.size ()I
                    INVOKEVIRTUAL java.lang.StringBuilder.append (I)Ljava/lang/StringBuilder;
                    INVOKEVIRTUAL java.lang.StringBuilder.toString ()Ljava/lang/String;
                    INVOKESPECIAL org.springframework.beans.factory.NoSuchBeanDefinitionException.<init> (Ljava/lang/Class;Ljava/lang/String;)V
                    ATHROW
  end public static Object beanOfTypeIncludingAncestors(org.springframework.beans.factory.ListableBeanFactory, Class, boolean, boolean) throws org.springframework.beans.BeansException

  public static Object beanOfType(org.springframework.beans.factory.ListableBeanFactory, Class) throws org.springframework.beans.BeansException:
                    ALOAD_0     // Lorg/springframework/beans/factory/ListableBeanFactory; lbf   (line 388)
                    LDC "ListableBeanFactory must not be null"
                    INVOKESTATIC org.springframework.util.Assert.notNull (Ljava/lang/Object;Ljava/lang/String;)V
                    ALOAD_0     // Lorg/springframework/beans/factory/ListableBeanFactory; lbf   (line 389)
                    ALOAD_1     // Ljava/lang/Class; type
                    INVOKEINTERFACE org.springframework.beans.factory.ListableBeanFactory.getBeansOfType (Ljava/lang/Class;)Ljava/util/Map;
                    ASTORE_2
                    ALOAD_2     // Ljava/util/Map; beansOfType   (line 390)
                    INVOKEINTERFACE java.util.Map.size ()I
                    ICONST_1
                    IF_ICMPNE L0
                    ALOAD_2     // Ljava/util/Map; beansOfType   (line 391)
                    INVOKEINTERFACE java.util.Map.values ()Ljava/util/Collection;
                    INVOKEINTERFACE java.util.Collection.iterator ()Ljava/util/Iterator;
                    INVOKEINTERFACE java.util.Iterator.next ()Ljava/lang/Object;
                    ARETURN
                L0: NEW org.springframework.beans.factory.NoSuchBeanDefinitionException   (line 394)
                    DUP
                    ALOAD_1     // Ljava/lang/Class; type
                    NEW java.lang.StringBuilder
                    DUP
                    LDC "expected single bean but found "
                    INVOKESPECIAL java.lang.StringBuilder.<init> (Ljava/lang/String;)V
                    ALOAD_2     // Ljava/util/Map; beansOfType
                    INVOKEINTERFACE java.util.Map.size ()I
                    INVOKEVIRTUAL java.lang.StringBuilder.append (I)Ljava/lang/StringBuilder;
                    INVOKEVIRTUAL java.lang.StringBuilder.toString ()Ljava/lang/String;
                    INVOKESPECIAL org.springframework.beans.factory.NoSuchBeanDefinitionException.<init> (Ljava/lang/Class;Ljava/lang/String;)V
                    ATHROW
  end public static Object beanOfType(org.springframework.beans.factory.ListableBeanFactory, Class) throws org.springframework.beans.BeansException

  public static Object beanOfType(org.springframework.beans.factory.ListableBeanFactory, Class, boolean, boolean) throws org.springframework.beans.BeansException:
                    ALOAD_0     // Lorg/springframework/beans/factory/ListableBeanFactory; lbf   (line 426)
                    LDC "ListableBeanFactory must not be null"
                    INVOKESTATIC org.springframework.util.Assert.notNull (Ljava/lang/Object;Ljava/lang/String;)V
                    ALOAD_0     // Lorg/springframework/beans/factory/ListableBeanFactory; lbf   (line 427)
                    ALOAD_1     // Ljava/lang/Class; type
                    ILOAD_2     // Z includeNonSingletons
                    ILOAD_3     // Z allowEagerInit
                    INVOKEINTERFACE org.springframework.beans.factory.ListableBeanFactory.getBeansOfType (Ljava/lang/Class;ZZ)Ljava/util/Map;
                    ASTORE 4
                    ALOAD 4     // Ljava/util/Map; beansOfType   (line 428)
                    INVOKEINTERFACE java.util.Map.size ()I
                    ICONST_1
                    IF_ICMPNE L0
                    ALOAD 4     // Ljava/util/Map; beansOfType   (line 429)
                    INVOKEINTERFACE java.util.Map.values ()Ljava/util/Collection;
                    INVOKEINTERFACE java.util.Collection.iterator ()Ljava/util/Iterator;
                    INVOKEINTERFACE java.util.Iterator.next ()Ljava/lang/Object;
                    ARETURN
                L0: NEW org.springframework.beans.factory.NoSuchBeanDefinitionException   (line 432)
                    DUP
                    ALOAD_1     // Ljava/lang/Class; type
                    NEW java.lang.StringBuilder
                    DUP
                    LDC "expected single bean but found "
                    INVOKESPECIAL java.lang.StringBuilder.<init> (Ljava/lang/String;)V
                    ALOAD 4     // Ljava/util/Map; beansOfType
                    INVOKEINTERFACE java.util.Map.size ()I
                    INVOKEVIRTUAL java.lang.StringBuilder.append (I)Ljava/lang/StringBuilder;
                    INVOKEVIRTUAL java.lang.StringBuilder.toString ()Ljava/lang/String;
                    INVOKESPECIAL org.springframework.beans.factory.NoSuchBeanDefinitionException.<init> (Ljava/lang/Class;Ljava/lang/String;)V
                    ATHROW
  end public static Object beanOfType(org.springframework.beans.factory.ListableBeanFactory, Class, boolean, boolean) throws org.springframework.beans.BeansException

end public abstract class org.springframework.beans.factory.BeanFactoryUtils
 -- (NullPointerException) null
null
java.lang.NullPointerException

org.aspectj.bridge.AbortException: trouble in: 
public abstract class org.springframework.beans.factory.BeanFactoryUtils extends java.lang.Object:
  public static final String GENERATED_BEAN_NAME_SEPARATOR = "#"
  public void <init>():
                    ALOAD_0     // Lorg/springframework/beans/factory/BeanFactoryUtils; this   (line 44)
                    INVOKESPECIAL java.lang.Object.<init> ()V
    constructor-execution(void org.springframework.beans.factory.BeanFactoryUtils.<init>())
    |               RETURN
    constructor-execution(void org.springframework.beans.factory.BeanFactoryUtils.<init>())
  end public void <init>()

  public static boolean isFactoryDereference(String):
                    ALOAD_0     // Ljava/lang/String; name   (line 61)
                    IFNULL L0
                    ALOAD_0     // Ljava/lang/String; name
                    LDC "&"
                    INVOKEVIRTUAL java.lang.String.startsWith (Ljava/lang/String;)Z
                    IFEQ L0
                    ICONST_1
                    IRETURN
                L0: ICONST_0
                    IRETURN
  end public static boolean isFactoryDereference(String)

  public static String transformedBeanName(String):
                    ALOAD_0     // Ljava/lang/String; name   (line 72)
                    LDC "'name' must not be null"
                    INVOKESTATIC org.springframework.util.Assert.notNull (Ljava/lang/Object;Ljava/lang/String;)V
                    ALOAD_0     // Ljava/lang/String; name   (line 73)
                    ASTORE_1
                    GOTO L1   (line 74)
                L0: ALOAD_1     // Ljava/lang/String; beanName   (line 75)
                    LDC "&"
                    INVOKEVIRTUAL java.lang.String.length ()I
                    INVOKEVIRTUAL java.lang.String.substring (I)Ljava/lang/String;
                    ASTORE_1     // Ljava/lang/String; beanName
                L1: ALOAD_1     // Ljava/lang/String; beanName   (line 74)
                    LDC "&"
                    INVOKEVIRTUAL java.lang.String.startsWith (Ljava/lang/String;)Z
                    IFNE L0
                    ALOAD_1     // Ljava/lang/String; beanName   (line 77)
                    ARETURN
  end public static String transformedBeanName(String)

  public static boolean isGeneratedBeanName(String):
                    ALOAD_0     // Ljava/lang/String; name   (line 90)
                    IFNULL L0
                    ALOAD_0     // Ljava/lang/String; name
                    LDC "#"
                    INVOKEVIRTUAL java.lang.String.contains (Ljava/lang/CharSequence;)Z
                    IFEQ L0
                    ICONST_1
                    IRETURN
                L0: ICONST_0
                    IRETURN
  end public static boolean isGeneratedBeanName(String)

  public static String originalBeanName(String):
                    ALOAD_0     // Ljava/lang/String; name   (line 101)
                    LDC "'name' must not be null"
                    INVOKESTATIC org.springframework.util.Assert.notNull (Ljava/lang/Object;Ljava/lang/String;)V
                    ALOAD_0     // Ljava/lang/String; name   (line 102)
                    LDC "#"
                    INVOKEVIRTUAL java.lang.String.indexOf (Ljava/lang/String;)I
                    ISTORE_1
                    ILOAD_1     // I separatorIndex   (line 103)
                    ICONST_M1
                    IF_ICMPEQ L0
                    ALOAD_0     // Ljava/lang/String; name
                    ICONST_0
                    ILOAD_1     // I separatorIndex
                    INVOKEVIRTUAL java.lang.String.substring (II)Ljava/lang/String;
                    GOTO L1
                L0: ALOAD_0     // Ljava/lang/String; name
                L1: ARETURN
  end public static String originalBeanName(String)

  public static int countBeansIncludingAncestors(org.springframework.beans.factory.ListableBeanFactory):
                    ALOAD_0     // Lorg/springframework/beans/factory/ListableBeanFactory; lbf   (line 116)
                    INVOKESTATIC org.springframework.beans.factory.BeanFactoryUtils.beanNamesIncludingAncestors (Lorg/springframework/beans/factory/ListableBeanFactory;)[Ljava/lang/String;
                    ARRAYLENGTH
                    IRETURN
  end public static int countBeansIncludingAncestors(org.springframework.beans.factory.ListableBeanFactory)

  public static String[] beanNamesIncludingAncestors(org.springframework.beans.factory.ListableBeanFactory):
                    ALOAD_0     // Lorg/springframework/beans/factory/ListableBeanFactory; lbf   (line 126)
                    LDC java.lang.Object
                    INVOKESTATIC org.springframework.beans.factory.BeanFactoryUtils.beanNamesForTypeIncludingAncestors (Lorg/springframework/beans/factory/ListableBeanFactory;Ljava/lang/Class;)[Ljava/lang/String;
                    ARETURN
  end public static String[] beanNamesIncludingAncestors(org.springframework.beans.factory.ListableBeanFactory)

  public static String[] beanNamesForTypeIncludingAncestors(org.springframework.beans.factory.ListableBeanFactory, Class):
                    ALOAD_0     // Lorg/springframework/beans/factory/ListableBeanFactory; lbf   (line 143)
                    LDC "ListableBeanFactory must not be null"
                    INVOKESTATIC org.springframework.util.Assert.notNull (Ljava/lang/Object;Ljava/lang/String;)V
                    ALOAD_0     // Lorg/springframework/beans/factory/ListableBeanFactory; lbf   (line 144)
                    ALOAD_1     // Ljava/lang/Class; type
                    INVOKEINTERFACE org.springframework.beans.factory.ListableBeanFactory.getBeanNamesForType (Ljava/lang/Class;)[Ljava/lang/String;
                    ASTORE_2
                    ALOAD_0     // Lorg/springframework/beans/factory/ListableBeanFactory; lbf   (line 145)
                    INSTANCEOF org.springframework.beans.factory.HierarchicalBeanFactory
                    IFEQ L3
                    ALOAD_0     // Lorg/springframework/beans/factory/ListableBeanFactory; lbf   (line 146)
                    CHECKCAST org.springframework.beans.factory.HierarchicalBeanFactory
                    ASTORE_3
                    ALOAD_3     // Lorg/springframework/beans/factory/HierarchicalBeanFactory; hbf   (line 147)
                    INVOKEINTERFACE org.springframework.beans.factory.HierarchicalBeanFactory.getParentBeanFactory ()Lorg/springframework/beans/factory/BeanFactory;
                    INSTANCEOF org.springframework.beans.factory.ListableBeanFactory
                    IFEQ L3
                    ALOAD_3     // Lorg/springframework/beans/factory/HierarchicalBeanFactory; hbf   (line 149)
                    INVOKEINTERFACE org.springframework.beans.factory.HierarchicalBeanFactory.getParentBeanFactory ()Lorg/springframework/beans/factory/BeanFactory;
                    CHECKCAST org.springframework.beans.factory.ListableBeanFactory
                    ALOAD_1     // Ljava/lang/Class; type
                    INVOKESTATIC org.springframework.beans.factory.BeanFactoryUtils.beanNamesForTypeIncludingAncestors (Lorg/springframework/beans/factory/ListableBeanFactory;Ljava/lang/Class;)[Ljava/lang/String;   (line 148)
                    ASTORE 4
                    NEW java.util.ArrayList   (line 150)
                    DUP
                    INVOKESPECIAL java.util.ArrayList.<init> ()V
                    ASTORE 5
                    ALOAD 5     // Ljava/util/List; resultList   (line 151)
                    ALOAD_2     // [Ljava/lang/String; result
                    INVOKESTATIC java.util.Arrays.asList ([Ljava/lang/Object;)Ljava/util/List;
                    CHECKCAST java.util.Collection
                    INVOKEINTERFACE java.util.List.addAll (Ljava/util/Collection;)Z
                    POP
                    ALOAD 4     // [Ljava/lang/String; parentResult   (line 152)
                    DUP
                    ASTORE 9
                    ARRAYLENGTH
                    ISTORE 8
                    ICONST_0
                    ISTORE 7
                    GOTO L2
                L0: ALOAD 9
                    ILOAD 7
                    AALOAD
                    ASTORE 6
                    ALOAD 5     // Ljava/util/List; resultList   (line 153)
                    ALOAD 6     // Ljava/lang/String; beanName
                    INVOKEINTERFACE java.util.List.contains (Ljava/lang/Object;)Z
                    IFNE L1
                    ALOAD_3     // Lorg/springframework/beans/factory/HierarchicalBeanFactory; hbf
                    ALOAD 6     // Ljava/lang/String; beanName
                    INVOKEINTERFACE org.springframework.beans.factory.HierarchicalBeanFactory.containsLocalBean (Ljava/lang/String;)Z
                    IFNE L1
                    ALOAD 5     // Ljava/util/List; resultList   (line 154)
                    ALOAD 6     // Ljava/lang/String; beanName
                    INVOKEINTERFACE java.util.List.add (Ljava/lang/Object;)Z
                    POP
                L1: IINC 7 1   (line 152)
                L2: ILOAD 7
                    ILOAD 8
                    IF_ICMPLT L0
                    ALOAD 5     // Ljava/util/List; resultList   (line 157)
                    INVOKESTATIC org.springframework.util.StringUtils.toStringArray (Ljava/util/Collection;)[Ljava/lang/String;
                    ASTORE_2     // [Ljava/lang/String; result
                L3: ALOAD_2     // [Ljava/lang/String; result   (line 160)
                    ARETURN
  end public static String[] beanNamesForTypeIncludingAncestors(org.springframework.beans.factory.ListableBeanFactory, Class)

  public static String[] beanNamesForTypeIncludingAncestors(org.springframework.beans.factory.ListableBeanFactory, Class, boolean, boolean):
                    ALOAD_0     // Lorg/springframework/beans/factory/ListableBeanFactory; lbf   (line 186)
                    LDC "ListableBeanFactory must not be null"
                    INVOKESTATIC org.springframework.util.Assert.notNull (Ljava/lang/Object;Ljava/lang/String;)V
                    ALOAD_0     // Lorg/springframework/beans/factory/ListableBeanFactory; lbf   (line 187)
                    ALOAD_1     // Ljava/lang/Class; type
                    ILOAD_2     // Z includeNonSingletons
                    ILOAD_3     // Z allowEagerInit
                    INVOKEINTERFACE org.springframework.beans.factory.ListableBeanFactory.getBeanNamesForType (Ljava/lang/Class;ZZ)[Ljava/lang/String;
                    ASTORE 4
                    ALOAD_0     // Lorg/springframework/beans/factory/ListableBeanFactory; lbf   (line 188)
                    INSTANCEOF org.springframework.beans.factory.HierarchicalBeanFactory
                    IFEQ L3
                    ALOAD_0     // Lorg/springframework/beans/factory/ListableBeanFactory; lbf   (line 189)
                    CHECKCAST org.springframework.beans.factory.HierarchicalBeanFactory
                    ASTORE 5
                    ALOAD 5     // Lorg/springframework/beans/factory/HierarchicalBeanFactory; hbf   (line 190)
                    INVOKEINTERFACE org.springframework.beans.factory.HierarchicalBeanFactory.getParentBeanFactory ()Lorg/springframework/beans/factory/BeanFactory;
                    INSTANCEOF org.springframework.beans.factory.ListableBeanFactory
                    IFEQ L3
                    ALOAD 5     // Lorg/springframework/beans/factory/HierarchicalBeanFactory; hbf   (line 192)
                    INVOKEINTERFACE org.springframework.beans.factory.HierarchicalBeanFactory.getParentBeanFactory ()Lorg/springframework/beans/factory/BeanFactory;
                    CHECKCAST org.springframework.beans.factory.ListableBeanFactory
                    ALOAD_1     // Ljava/lang/Class; type
                    ILOAD_2     // Z includeNonSingletons
                    ILOAD_3     // Z allowEagerInit
                    INVOKESTATIC org.springframework.beans.factory.BeanFactoryUtils.beanNamesForTypeIncludingAncestors (Lorg/springframework/beans/factory/ListableBeanFactory;Ljava/lang/Class;ZZ)[Ljava/lang/String;   (line 191)
                    ASTORE 6
                    NEW java.util.ArrayList   (line 193)
                    DUP
                    INVOKESPECIAL java.util.ArrayList.<init> ()V
                    ASTORE 7
                    ALOAD 7     // Ljava/util/List; resultList   (line 194)
                    ALOAD 4     // [Ljava/lang/String; result
                    INVOKESTATIC java.util.Arrays.asList ([Ljava/lang/Object;)Ljava/util/List;
                    CHECKCAST java.util.Collection
                    INVOKEINTERFACE java.util.List.addAll (Ljava/util/Collection;)Z
                    POP
                    ALOAD 6     // [Ljava/lang/String; parentResult   (line 195)
                    DUP
                    ASTORE 11
                    ARRAYLENGTH
                    ISTORE 10
                    ICONST_0
                    ISTORE 9
                    GOTO L2
                L0: ALOAD 11
                    ILOAD 9
                    AALOAD
                    ASTORE 8
                    ALOAD 7     // Ljava/util/List; resultList   (line 196)
                    ALOAD 8     // Ljava/lang/String; beanName
                    INVOKEINTERFACE java.util.List.contains (Ljava/lang/Object;)Z
                    IFNE L1
                    ALOAD 5     // Lorg/springframework/beans/factory/HierarchicalBeanFactory; hbf
                    ALOAD 8     // Ljava/lang/String; beanName
                    INVOKEINTERFACE org.springframework.beans.factory.HierarchicalBeanFactory.containsLocalBean (Ljava/lang/String;)Z
                    IFNE L1
                    ALOAD 7     // Ljava/util/List; resultList   (line 197)
                    ALOAD 8     // Ljava/lang/String; beanName
                    INVOKEINTERFACE java.util.List.add (Ljava/lang/Object;)Z
                    POP
                L1: IINC 9 1   (line 195)
                L2: ILOAD 9
                    ILOAD 10
                    IF_ICMPLT L0
                    ALOAD 7     // Ljava/util/List; resultList   (line 200)
                    INVOKESTATIC org.springframework.util.StringUtils.toStringArray (Ljava/util/Collection;)[Ljava/lang/String;
                    ASTORE 4     // [Ljava/lang/String; result
                L3: ALOAD 4     // [Ljava/lang/String; result   (line 203)
                    ARETURN
  end public static String[] beanNamesForTypeIncludingAncestors(org.springframework.beans.factory.ListableBeanFactory, Class, boolean, boolean)

  public static java.util.Map beansOfTypeIncludingAncestors(org.springframework.beans.factory.ListableBeanFactory, Class) throws org.springframework.beans.BeansException:
                    ALOAD_0     // Lorg/springframework/beans/factory/ListableBeanFactory; lbf   (line 226)
                    LDC "ListableBeanFactory must not be null"
                    INVOKESTATIC org.springframework.util.Assert.notNull (Ljava/lang/Object;Ljava/lang/String;)V
                    NEW java.util.LinkedHashMap   (line 227)
                    DUP
                    ICONST_4
                    INVOKESPECIAL java.util.LinkedHashMap.<init> (I)V
                    ASTORE_2
                    ALOAD_2     // Ljava/util/Map; result   (line 228)
                    ALOAD_0     // Lorg/springframework/beans/factory/ListableBeanFactory; lbf
                    ALOAD_1     // Ljava/lang/Class; type
                    INVOKEINTERFACE org.springframework.beans.factory.ListableBeanFactory.getBeansOfType (Ljava/lang/Class;)Ljava/util/Map;
                    INVOKEINTERFACE java.util.Map.putAll (Ljava/util/Map;)V
                    ALOAD_0     // Lorg/springframework/beans/factory/ListableBeanFactory; lbf   (line 229)
                    INSTANCEOF org.springframework.beans.factory.HierarchicalBeanFactory
                    IFEQ L2
                    ALOAD_0     // Lorg/springframework/beans/factory/ListableBeanFactory; lbf   (line 230)
                    CHECKCAST org.springframework.beans.factory.HierarchicalBeanFactory
                    ASTORE_3
                    ALOAD_3     // Lorg/springframework/beans/factory/HierarchicalBeanFactory; hbf   (line 231)
                    INVOKEINTERFACE org.springframework.beans.factory.HierarchicalBeanFactory.getParentBeanFactory ()Lorg/springframework/beans/factory/BeanFactory;
                    INSTANCEOF org.springframework.beans.factory.ListableBeanFactory
                    IFEQ L2
                    ALOAD_3     // Lorg/springframework/beans/factory/HierarchicalBeanFactory; hbf   (line 233)
                    INVOKEINTERFACE org.springframework.beans.factory.HierarchicalBeanFactory.getParentBeanFactory ()Lorg/springframework/beans/factory/BeanFactory;
                    CHECKCAST org.springframework.beans.factory.ListableBeanFactory
                    ALOAD_1     // Ljava/lang/Class; type
                    INVOKESTATIC org.springframework.beans.factory.BeanFactoryUtils.beansOfTypeIncludingAncestors (Lorg/springframework/beans/factory/ListableBeanFactory;Ljava/lang/Class;)Ljava/util/Map;   (line 232)
                    ASTORE 4
                    ALOAD 4     // Ljava/util/Map; parentResult   (line 234)
                    INVOKEINTERFACE java.util.Map.entrySet ()Ljava/util/Set;
                    INVOKEINTERFACE java.util.Set.iterator ()Ljava/util/Iterator;
                    ASTORE 6
                    GOTO L1
                L0: ALOAD 6
                    INVOKEINTERFACE java.util.Iterator.next ()Ljava/lang/Object;
                    CHECKCAST java.util.Map$Entry
                    ASTORE 5
                    ALOAD 5     // Ljava/util/Map$Entry; entry   (line 235)
                    INVOKEINTERFACE java.util.Map$Entry.getKey ()Ljava/lang/Object;
                    CHECKCAST java.lang.String
                    ASTORE 7
                    ALOAD_2     // Ljava/util/Map; result   (line 236)
                    ALOAD 7     // Ljava/lang/String; beanName
                    INVOKEINTERFACE java.util.Map.containsKey (Ljava/lang/Object;)Z
                    IFNE L1
                    ALOAD_3     // Lorg/springframework/beans/factory/HierarchicalBeanFactory; hbf
                    ALOAD 7     // Ljava/lang/String; beanName
                    INVOKEINTERFACE org.springframework.beans.factory.HierarchicalBeanFactory.containsLocalBean (Ljava/lang/String;)Z
                    IFNE L1
                    ALOAD_2     // Ljava/util/Map; result   (line 237)
                    ALOAD 7     // Ljava/lang/String; beanName
                    ALOAD 5     // Ljava/util/Map$Entry; entry
                    INVOKEINTERFACE java.util.Map$Entry.getValue ()Ljava/lang/Object;
                    INVOKEINTERFACE java.util.Map.put (Ljava/lang/Object;Ljava/lang/Object;)Ljava/lang/Object;
                    POP
                L1: ALOAD 6   (line 234)
                    INVOKEINTERFACE java.util.Iterator.hasNext ()Z
                    IFNE L0
                L2: ALOAD_2     // Ljava/util/Map; result   (line 242)
                    ARETURN
  end public static java.util.Map beansOfTypeIncludingAncestors(org.springframework.beans.factory.ListableBeanFactory, Class) throws org.springframework.beans.BeansException

  public static java.util.Map beansOfTypeIncludingAncestors(org.springframework.beans.factory.ListableBeanFactory, Class, boolean, boolean) throws org.springframework.beans.BeansException:
                    ALOAD_0     // Lorg/springframework/beans/factory/ListableBeanFactory; lbf   (line 275)
                    LDC "ListableBeanFactory must not be null"
                    INVOKESTATIC org.springframework.util.Assert.notNull (Ljava/lang/Object;Ljava/lang/String;)V
                    NEW java.util.LinkedHashMap   (line 276)
                    DUP
                    ICONST_4
                    INVOKESPECIAL java.util.LinkedHashMap.<init> (I)V
                    ASTORE 4
                    ALOAD 4     // Ljava/util/Map; result   (line 277)
                    ALOAD_0     // Lorg/springframework/beans/factory/ListableBeanFactory; lbf
                    ALOAD_1     // Ljava/lang/Class; type
                    ILOAD_2     // Z includeNonSingletons
                    ILOAD_3     // Z allowEagerInit
                    INVOKEINTERFACE org.springframework.beans.factory.ListableBeanFactory.getBeansOfType (Ljava/lang/Class;ZZ)Ljava/util/Map;
                    INVOKEINTERFACE java.util.Map.putAll (Ljava/util/Map;)V
                    ALOAD_0     // Lorg/springframework/beans/factory/ListableBeanFactory; lbf   (line 278)
                    INSTANCEOF org.springframework.beans.factory.HierarchicalBeanFactory
                    IFEQ L2
                    ALOAD_0     // Lorg/springframework/beans/factory/ListableBeanFactory; lbf   (line 279)
                    CHECKCAST org.springframework.beans.factory.HierarchicalBeanFactory
                    ASTORE 5
                    ALOAD 5     // Lorg/springframework/beans/factory/HierarchicalBeanFactory; hbf   (line 280)
                    INVOKEINTERFACE org.springframework.beans.factory.HierarchicalBeanFactory.getParentBeanFactory ()Lorg/springframework/beans/factory/BeanFactory;
                    INSTANCEOF org.springframework.beans.factory.ListableBeanFactory
                    IFEQ L2
                    ALOAD 5     // Lorg/springframework/beans/factory/HierarchicalBeanFactory; hbf   (line 282)
                    INVOKEINTERFACE org.springframework.beans.factory.HierarchicalBeanFactory.getParentBeanFactory ()Lorg/springframework/beans/factory/BeanFactory;
                    CHECKCAST org.springframework.beans.factory.ListableBeanFactory
                    ALOAD_1     // Ljava/lang/Class; type
                    ILOAD_2     // Z includeNonSingletons
                    ILOAD_3     // Z allowEagerInit
                    INVOKESTATIC org.springframework.beans.factory.BeanFactoryUtils.beansOfTypeIncludingAncestors (Lorg/springframework/beans/factory/ListableBeanFactory;Ljava/lang/Class;ZZ)Ljava/util/Map;   (line 281)
                    ASTORE 6
                    ALOAD 6     // Ljava/util/Map; parentResult   (line 283)
                    INVOKEINTERFACE java.util.Map.entrySet ()Ljava/util/Set;
                    INVOKEINTERFACE java.util.Set.iterator ()Ljava/util/Iterator;
                    ASTORE 8
                    GOTO L1
                L0: ALOAD 8
                    INVOKEINTERFACE java.util.Iterator.next ()Ljava/lang/Object;
                    CHECKCAST java.util.Map$Entry
                    ASTORE 7
                    ALOAD 7     // Ljava/util/Map$Entry; entry   (line 284)
                    INVOKEINTERFACE java.util.Map$Entry.getKey ()Ljava/lang/Object;
                    CHECKCAST java.lang.String
                    ASTORE 9
                    ALOAD 4     // Ljava/util/Map; result   (line 285)
                    ALOAD 9     // Ljava/lang/String; beanName
                    INVOKEINTERFACE java.util.Map.containsKey (Ljava/lang/Object;)Z
                    IFNE L1
                    ALOAD 5     // Lorg/springframework/beans/factory/HierarchicalBeanFactory; hbf
                    ALOAD 9     // Ljava/lang/String; beanName
                    INVOKEINTERFACE org.springframework.beans.factory.HierarchicalBeanFactory.containsLocalBean (Ljava/lang/String;)Z
                    IFNE L1
                    ALOAD 4     // Ljava/util/Map; result   (line 286)
                    ALOAD 9     // Ljava/lang/String; beanName
                    ALOAD 7     // Ljava/util/Map$Entry; entry
                    INVOKEINTERFACE java.util.Map$Entry.getValue ()Ljava/lang/Object;
                    INVOKEINTERFACE java.util.Map.put (Ljava/lang/Object;Ljava/lang/Object;)Ljava/lang/Object;
                    POP
                L1: ALOAD 8   (line 283)
                    INVOKEINTERFACE java.util.Iterator.hasNext ()Z
                    IFNE L0
                L2: ALOAD 4     // Ljava/util/Map; result   (line 291)
                    ARETURN
  end public static java.util.Map beansOfTypeIncludingAncestors(org.springframework.beans.factory.ListableBeanFactory, Class, boolean, boolean) throws org.springframework.beans.BeansException

  public static Object beanOfTypeIncludingAncestors(org.springframework.beans.factory.ListableBeanFactory, Class) throws org.springframework.beans.BeansException:
                    ALOAD_0     // Lorg/springframework/beans/factory/ListableBeanFactory; lbf   (line 320)
                    ALOAD_1     // Ljava/lang/Class; type
                    INVOKESTATIC org.springframework.beans.factory.BeanFactoryUtils.beansOfTypeIncludingAncestors (Lorg/springframework/beans/factory/ListableBeanFactory;Ljava/lang/Class;)Ljava/util/Map;
                    ASTORE_2
                    ALOAD_2     // Ljava/util/Map; beansOfType   (line 321)
                    INVOKEINTERFACE java.util.Map.size ()I
                    ICONST_1
                    IF_ICMPNE L0
                    ALOAD_2     // Ljava/util/Map; beansOfType   (line 322)
                    INVOKEINTERFACE java.util.Map.values ()Ljava/util/Collection;
                    INVOKEINTERFACE java.util.Collection.iterator ()Ljava/util/Iterator;
                    INVOKEINTERFACE java.util.Iterator.next ()Ljava/lang/Object;
                    ARETURN
                L0: NEW org.springframework.beans.factory.NoSuchBeanDefinitionException   (line 325)
                    DUP
                    ALOAD_1     // Ljava/lang/Class; type
                    NEW java.lang.StringBuilder
                    DUP
                    LDC "expected single bean but found "
                    INVOKESPECIAL java.lang.StringBuilder.<init> (Ljava/lang/String;)V
                    ALOAD_2     // Ljava/util/Map; beansOfType
                    INVOKEINTERFACE java.util.Map.size ()I
                    INVOKEVIRTUAL java.lang.StringBuilder.append (I)Ljava/lang/StringBuilder;
                    INVOKEVIRTUAL java.lang.StringBuilder.toString ()Ljava/lang/String;
                    INVOKESPECIAL org.springframework.beans.factory.NoSuchBeanDefinitionException.<init> (Ljava/lang/Class;Ljava/lang/String;)V
                    ATHROW
  end public static Object beanOfTypeIncludingAncestors(org.springframework.beans.factory.ListableBeanFactory, Class) throws org.springframework.beans.BeansException

  public static Object beanOfTypeIncludingAncestors(org.springframework.beans.factory.ListableBeanFactory, Class, boolean, boolean) throws org.springframework.beans.BeansException:
                    ALOAD_0     // Lorg/springframework/beans/factory/ListableBeanFactory; lbf   (line 362)
                    ALOAD_1     // Ljava/lang/Class; type
                    ILOAD_2     // Z includeNonSingletons
                    ILOAD_3     // Z allowEagerInit
                    INVOKESTATIC org.springframework.beans.factory.BeanFactoryUtils.beansOfTypeIncludingAncestors (Lorg/springframework/beans/factory/ListableBeanFactory;Ljava/lang/Class;ZZ)Ljava/util/Map;
                    ASTORE 4
                    ALOAD 4     // Ljava/util/Map; beansOfType   (line 363)
                    INVOKEINTERFACE java.util.Map.size ()I
                    ICONST_1
                    IF_ICMPNE L0
                    ALOAD 4     // Ljava/util/Map; beansOfType   (line 364)
                    INVOKEINTERFACE java.util.Map.values ()Ljava/util/Collection;
                    INVOKEINTERFACE java.util.Collection.iterator ()Ljava/util/Iterator;
                    INVOKEINTERFACE java.util.Iterator.next ()Ljava/lang/Object;
                    ARETURN
                L0: NEW org.springframework.beans.factory.NoSuchBeanDefinitionException   (line 367)
                    DUP
                    ALOAD_1     // Ljava/lang/Class; type
                    NEW java.lang.StringBuilder
                    DUP
                    LDC "expected single bean but found "
                    INVOKESPECIAL java.lang.StringBuilder.<init> (Ljava/lang/String;)V
                    ALOAD 4     // Ljava/util/Map; beansOfType
                    INVOKEINTERFACE java.util.Map.size ()I
                    INVOKEVIRTUAL java.lang.StringBuilder.append (I)Ljava/lang/StringBuilder;
                    INVOKEVIRTUAL java.lang.StringBuilder.toString ()Ljava/lang/String;
                    INVOKESPECIAL org.springframework.beans.factory.NoSuchBeanDefinitionException.<init> (Ljava/lang/Class;Ljava/lang/String;)V
                    ATHROW
  end public static Object beanOfTypeIncludingAncestors(org.springframework.beans.factory.ListableBeanFactory, Class, boolean, boolean) throws org.springframework.beans.BeansException

  public static Object beanOfType(org.springframework.beans.factory.ListableBeanFactory, Class) throws org.springframework.beans.BeansException:
                    ALOAD_0     // Lorg/springframework/beans/factory/ListableBeanFactory; lbf   (line 388)
                    LDC "ListableBeanFactory must not be null"
                    INVOKESTATIC org.springframework.util.Assert.notNull (Ljava/lang/Object;Ljava/lang/String;)V
                    ALOAD_0     // Lorg/springframework/beans/factory/ListableBeanFactory; lbf   (line 389)
                    ALOAD_1     // Ljava/lang/Class; type
                    INVOKEINTERFACE org.springframework.beans.factory.ListableBeanFactory.getBeansOfType (Ljava/lang/Class;)Ljava/util/Map;
                    ASTORE_2
                    ALOAD_2     // Ljava/util/Map; beansOfType   (line 390)
                    INVOKEINTERFACE java.util.Map.size ()I
                    ICONST_1
                    IF_ICMPNE L0
                    ALOAD_2     // Ljava/util/Map; beansOfType   (line 391)
                    INVOKEINTERFACE java.util.Map.values ()Ljava/util/Collection;
                    INVOKEINTERFACE java.util.Collection.iterator ()Ljava/util/Iterator;
                    INVOKEINTERFACE java.util.Iterator.next ()Ljava/lang/Object;
                    ARETURN
                L0: NEW org.springframework.beans.factory.NoSuchBeanDefinitionException   (line 394)
                    DUP
                    ALOAD_1     // Ljava/lang/Class; type
                    NEW java.lang.StringBuilder
                    DUP
                    LDC "expected single bean but found "
                    INVOKESPECIAL java.lang.StringBuilder.<init> (Ljava/lang/String;)V
                    ALOAD_2     // Ljava/util/Map; beansOfType
                    INVOKEINTERFACE java.util.Map.size ()I
                    INVOKEVIRTUAL java.lang.StringBuilder.append (I)Ljava/lang/StringBuilder;
                    INVOKEVIRTUAL java.lang.StringBuilder.toString ()Ljava/lang/String;
                    INVOKESPECIAL org.springframework.beans.factory.NoSuchBeanDefinitionException.<init> (Ljava/lang/Class;Ljava/lang/String;)V
                    ATHROW
  end public static Object beanOfType(org.springframework.beans.factory.ListableBeanFactory, Class) throws org.springframework.beans.BeansException

  public static Object beanOfType(org.springframework.beans.factory.ListableBeanFactory, Class, boolean, boolean) throws org.springframework.beans.BeansException:
                    ALOAD_0     // Lorg/springframework/beans/factory/ListableBeanFactory; lbf   (line 426)
                    LDC "ListableBeanFactory must not be null"
                    INVOKESTATIC org.springframework.util.Assert.notNull (Ljava/lang/Object;Ljava/lang/String;)V
                    ALOAD_0     // Lorg/springframework/beans/factory/ListableBeanFactory; lbf   (line 427)
                    ALOAD_1     // Ljava/lang/Class; type
                    ILOAD_2     // Z includeNonSingletons
                    ILOAD_3     // Z allowEagerInit
                    INVOKEINTERFACE org.springframework.beans.factory.ListableBeanFactory.getBeansOfType (Ljava/lang/Class;ZZ)Ljava/util/Map;
                    ASTORE 4
                    ALOAD 4     // Ljava/util/Map; beansOfType   (line 428)
                    INVOKEINTERFACE java.util.Map.size ()I
                    ICONST_1
                    IF_ICMPNE L0
                    ALOAD 4     // Ljava/util/Map; beansOfType   (line 429)
                    INVOKEINTERFACE java.util.Map.values ()Ljava/util/Collection;
                    INVOKEINTERFACE java.util.Collection.iterator ()Ljava/util/Iterator;
                    INVOKEINTERFACE java.util.Iterator.next ()Ljava/lang/Object;
                    ARETURN
                L0: NEW org.springframework.beans.factory.NoSuchBeanDefinitionException   (line 432)
                    DUP
                    ALOAD_1     // Ljava/lang/Class; type
                    NEW java.lang.StringBuilder
                    DUP
                    LDC "expected single bean but found "
                    INVOKESPECIAL java.lang.StringBuilder.<init> (Ljava/lang/String;)V
                    ALOAD 4     // Ljava/util/Map; beansOfType
                    INVOKEINTERFACE java.util.Map.size ()I
                    INVOKEVIRTUAL java.lang.StringBuilder.append (I)Ljava/lang/StringBuilder;
                    INVOKEVIRTUAL java.lang.StringBuilder.toString ()Ljava/lang/String;
                    INVOKESPECIAL org.springframework.beans.factory.NoSuchBeanDefinitionException.<init> (Ljava/lang/Class;Ljava/lang/String;)V
                    ATHROW
  end public static Object beanOfType(org.springframework.beans.factory.ListableBeanFactory, Class, boolean, boolean) throws org.springframework.beans.BeansException

end public abstract class org.springframework.beans.factory.BeanFactoryUtils

	at org.aspectj.bridge.MessageWriter.handleMessage(MessageWriter.java:47)
	at org.aspectj.weaver.tools.WeavingAdaptor$WeavingAdaptorMessageWriter.handleMessage(WeavingAdaptor.java:665)
	at org.aspectj.weaver.tools.WeavingAdaptor$WeavingAdaptorMessageHolder.handleMessage(WeavingAdaptor.java:615)
	at org.aspectj.weaver.bcel.BcelWeaver.weave(BcelWeaver.java:1752)
	at org.aspectj.weaver.bcel.BcelWeaver.weaveWithoutDump(BcelWeaver.java:1694)
	at org.aspectj.weaver.bcel.BcelWeaver.weaveAndNotify(BcelWeaver.java:1464)
	at org.aspectj.weaver.bcel.BcelWeaver.weave(BcelWeaver.java:1273)
	at org.aspectj.weaver.tools.WeavingAdaptor.getWovenBytes(WeavingAdaptor.java:394)
	at org.aspectj.weaver.tools.WeavingAdaptor.weaveClass(WeavingAdaptor.java:281)
	at org.aspectj.weaver.loadtime.Aj.preProcess(Aj.java:95)
	at org.aspectj.weaver.loadtime.ClassPreProcessorAgentAdapter.transform(ClassPreProcessorAgentAdapter.java:52)
	at sun.instrument.TransformerManager.transform(TransformerManager.java:188)
	at sun.instrument.InstrumentationImpl.transform(InstrumentationImpl.java:428)
	at java.lang.ClassLoader.defineClass1(Native Method)
	at java.lang.ClassLoader.defineClass(ClassLoader.java:760)
	at java.security.SecureClassLoader.defineClass(SecureClassLoader.java:142)
	at java.net.URLClassLoader.defineClass(URLClassLoader.java:467)
	at java.net.URLClassLoader.access$100(URLClassLoader.java:73)
	at java.net.URLClassLoader$1.run(URLClassLoader.java:368)
	at java.net.URLClassLoader$1.run(URLClassLoader.java:362)
	at java.security.AccessController.doPrivileged(Native Method)
	at java.net.URLClassLoader.findClass(URLClassLoader.java:361)
	at java.lang.ClassLoader.loadClass(ClassLoader.java:424)
	at sun.misc.Launcher$AppClassLoader.loadClass(Launcher.java:331)
	at java.lang.ClassLoader.loadClass(ClassLoader.java:357)
	at org.springframework.beans.factory.support.AbstractBeanFactory.transformedBeanName(AbstractBeanFactory.java:1005)
	at org.springframework.beans.factory.support.AbstractBeanFactory.containsLocalBean(AbstractBeanFactory.java:628)
	at org.springframework.beans.factory.support.AbstractBeanFactory.isBeanNameInUse(AbstractBeanFactory.java:1454)
	at org.springframework.beans.factory.xml.BeanDefinitionParserDelegate.parseBeanDefinitionElement(BeanDefinitionParserDelegate.java:492)
	at org.springframework.beans.factory.xml.BeanDefinitionParserDelegate.parseBeanDefinitionElement(BeanDefinitionParserDelegate.java:445)
	at org.springframework.beans.factory.xml.DefaultBeanDefinitionDocumentReader.processBeanDefinition(DefaultBeanDefinitionDocumentReader.java:311)
	at org.springframework.beans.factory.xml.DefaultBeanDefinitionDocumentReader.parseDefaultElement(DefaultBeanDefinitionDocumentReader.java:202)
	at org.springframework.beans.factory.xml.DefaultBeanDefinitionDocumentReader.parseBeanDefinitions(DefaultBeanDefinitionDocumentReader.java:181)
	at org.springframework.beans.factory.xml.DefaultBeanDefinitionDocumentReader.doRegisterBeanDefinitions(DefaultBeanDefinitionDocumentReader.java:140)
	at org.springframework.beans.factory.xml.DefaultBeanDefinitionDocumentReader.registerBeanDefinitions(DefaultBeanDefinitionDocumentReader.java:111)
	at org.springframework.beans.factory.xml.XmlBeanDefinitionReader.registerBeanDefinitions(XmlBeanDefinitionReader.java:493)
	at org.springframework.beans.factory.xml.XmlBeanDefinitionReader.doLoadBeanDefinitions(XmlBeanDefinitionReader.java:390)
	at org.springframework.beans.factory.xml.XmlBeanDefinitionReader.loadBeanDefinitions(XmlBeanDefinitionReader.java:334)
	at org.springframework.beans.factory.xml.XmlBeanDefinitionReader.loadBeanDefinitions(XmlBeanDefinitionReader.java:302)
	at org.springframework.beans.factory.support.AbstractBeanDefinitionReader.loadBeanDefinitions(AbstractBeanDefinitionReader.java:174)
	at org.springframework.beans.factory.support.AbstractBeanDefinitionReader.loadBeanDefinitions(AbstractBeanDefinitionReader.java:209)
	at org.springframework.beans.factory.support.AbstractBeanDefinitionReader.loadBeanDefinitions(AbstractBeanDefinitionReader.java:180)
	at org.springframework.beans.factory.support.AbstractBeanDefinitionReader.loadBeanDefinitions(AbstractBeanDefinitionReader.java:243)
	at org.springframework.context.support.AbstractXmlApplicationContext.loadBeanDefinitions(AbstractXmlApplicationContext.java:127)
	at org.springframework.context.support.AbstractXmlApplicationContext.loadBeanDefinitions(AbstractXmlApplicationContext.java:93)
	at org.springframework.context.support.AbstractRefreshableApplicationContext.refreshBeanFactory(AbstractRefreshableApplicationContext.java:131)
	at org.springframework.context.support.AbstractApplicationContext.obtainFreshBeanFactory(AbstractApplicationContext.java:527)
	at org.springframework.context.support.AbstractApplicationContext.refresh(AbstractApplicationContext.java:441)
	at org.springframework.context.support.ClassPathXmlApplicationContext.<init>(ClassPathXmlApplicationContext.java:139)
	at org.springframework.context.support.ClassPathXmlApplicationContext.<init>(ClassPathXmlApplicationContext.java:83)
	at com.curso.spring.springioc0007.Main.init(Main.java:29)
	at com.curso.spring.springioc0007.Main.main(Main.java:24)
---- System Properties ---
java.runtime.name=Java(TM) SE Runtime Environment
sun.boot.library.path=C:\Program Files\Java\jdk1.8.0_72\jre\bin
java.vm.version=25.72-b15
java.vm.vendor=Oracle Corporation
java.vendor.url=http://java.oracle.com/
path.separator=;
java.vm.name=Java HotSpot(TM) 64-Bit Server VM
file.encoding.pkg=sun.io
user.country=ES
user.script=
sun.java.launcher=SUN_STANDARD
sun.os.patch.level=
java.vm.specification.name=Java Virtual Machine Specification
user.dir=C:\Users\usuario\git\spring\aspectos\Ejemplos Relacionados\SpringIoC0007Maven
java.runtime.version=1.8.0_72-b15
java.awt.graphicsenv=sun.awt.Win32GraphicsEnvironment
java.endorsed.dirs=C:\Program Files\Java\jdk1.8.0_72\jre\lib\endorsed
os.arch=amd64
java.io.tmpdir=C:\Users\usuario\AppData\Local\Temp\
line.separator=

java.vm.specification.vendor=Oracle Corporation
user.variant=
os.name=Windows 10
sun.jnu.encoding=Cp1252
java.library.path=C:\Program Files\Java\jdk1.8.0_72\bin;C:\WINDOWS\Sun\Java\bin;C:\WINDOWS\system32;C:\WINDOWS;C:\ProgramData\Oracle\Java\javapath;C:\Program Files\CollabNet\Subversion Client;E:\bin\Sencha\Cmd\5.1.3.61;C:\Users\usuario\bin\Sencha\Cmd\5.1.3.61;C:\Program Files (x86)\Intel\iCLS Client\;C:\Program Files\Intel\iCLS Client\;C:\WINDOWS\system32;C:\WINDOWS;C:\WINDOWS\System32\Wbem;C:\WINDOWS\System32\WindowsPowerShell\v1.0\;C:\Program Files\Intel\Intel(R) Management Engine Components\DAL;C:\Program Files\Intel\Intel(R) Management Engine Components\IPT;C:\Program Files (x86)\Intel\Intel(R) Management Engine Components\DAL;C:\Program Files (x86)\Intel\Intel(R) Management Engine Components\IPT;C:\Program Files (x86)\Intel\OpenCL SDK\3.0\bin\x86;C:\Program Files (x86)\Intel\OpenCL SDK\3.0\bin\x64;C:\Program Files (x86)\sbt\\bin;C:\Program Files (x86)\Heroku\bin;C:\Program Files (x86)\git\cmd;C:\Program Files (x86)\QuickTime\QTSystem\;C:\HashiCorp\Vagrant\bin;C:\Program Files (x86)\scala\bin;C:\Program Files\nodejs\;C:\Users\usuario\AppData\Local\.meteor\;C:\Users\usuario\AppData\Roaming\npm;.
java.specification.name=Java Platform API Specification
java.class.version=52.0
sun.management.compiler=HotSpot 64-Bit Tiered Compilers
os.version=10.0
user.home=C:\Users\usuario
user.timezone=Europe/Paris
java.awt.printerjob=sun.awt.windows.WPrinterJob
file.encoding=Cp1252
java.specification.version=1.8
java.class.path=C:\Users\usuario\git\spring\aspectos\Ejemplos Relacionados\SpringIoC0007Maven\target\classes;C:\Users\usuario\.m2\repository\org\springframework\spring-context\3.1.2.RELEASE\spring-context-3.1.2.RELEASE.jar;C:\Users\usuario\.m2\repository\org\springframework\spring-aop\3.1.2.RELEASE\spring-aop-3.1.2.RELEASE.jar;C:\Users\usuario\.m2\repository\aopalliance\aopalliance\1.0\aopalliance-1.0.jar;C:\Users\usuario\.m2\repository\org\springframework\spring-beans\3.1.2.RELEASE\spring-beans-3.1.2.RELEASE.jar;C:\Users\usuario\.m2\repository\org\springframework\spring-core\3.1.2.RELEASE\spring-core-3.1.2.RELEASE.jar;C:\Users\usuario\.m2\repository\commons-logging\commons-logging\1.1.1\commons-logging-1.1.1.jar;C:\Users\usuario\.m2\repository\org\springframework\spring-expression\3.1.2.RELEASE\spring-expression-3.1.2.RELEASE.jar;C:\Users\usuario\.m2\repository\org\springframework\spring-asm\3.1.2.RELEASE\spring-asm-3.1.2.RELEASE.jar;C:\Users\usuario\.m2\repository\org\springframework\spring-aspects\3.1.2.RELEASE\spring-aspects-3.1.2.RELEASE.jar;C:\Users\usuario\.m2\repository\org\springframework\spring-context-support\3.1.2.RELEASE\spring-context-support-3.1.2.RELEASE.jar;.\..\aspectjweaver.jar
user.name=usuario
java.vm.specification.version=1.8
sun.java.command=com.curso.spring.springioc0007.Main
java.home=C:\Program Files\Java\jdk1.8.0_72\jre
sun.arch.data.model=64
user.language=es
java.specification.vendor=Oracle Corporation
awt.toolkit=sun.awt.windows.WToolkit
java.vm.info=mixed mode
java.version=1.8.0_72
java.ext.dirs=C:\Program Files\Java\jdk1.8.0_72\jre\lib\ext;C:\WINDOWS\Sun\Java\lib\ext
sun.boot.class.path=C:\Program Files\Java\jdk1.8.0_72\jre\lib\resources.jar;C:\Program Files\Java\jdk1.8.0_72\jre\lib\rt.jar;C:\Program Files\Java\jdk1.8.0_72\jre\lib\sunrsasign.jar;C:\Program Files\Java\jdk1.8.0_72\jre\lib\jsse.jar;C:\Program Files\Java\jdk1.8.0_72\jre\lib\jce.jar;C:\Program Files\Java\jdk1.8.0_72\jre\lib\charsets.jar;C:\Program Files\Java\jdk1.8.0_72\jre\lib\jfr.jar;C:\Program Files\Java\jdk1.8.0_72\jre\classes
java.vendor=Oracle Corporation
file.separator=\
java.vendor.url.bug=http://bugreport.sun.com/bugreport/
sun.io.unicode.encoding=UnicodeLittle
sun.cpu.endian=little
sun.desktop=windows
sun.cpu.isalist=amd64
---- Command Line ---
Empty
---- Full Classpath ---
Empty
---- Compiler Messages ---
Empty
---- org.aspectj.weaver.ltw.LTWWorld@28c97a5 ----
Class loader:
sun.misc.Launcher$AppClassLoader@18b4aac2
Class loader parent:
sun.misc.Launcher$ExtClassLoader@722c41f4
Shadow mungers:
(around(extraFlags: 3): ((((((((((within(@org.springframework.cache.annotation.CacheEvict *) && execution(public * @org.springframework.cache.annotation.CacheEvict *.*(..))) && this(BindingTypePattern(java.lang.Object, 0))) && persingleton(org.springframework.cache.aspectj.AnnotationCacheAspect)) || (((within(@org.springframework.cache.annotation.Caching *) && execution(public * @org.springframework.cache.annotation.Caching *.*(..))) && this(BindingTypePattern(java.lang.Object, 0))) && persingleton(org.springframework.cache.aspectj.AnnotationCacheAspect))) || (((within(@org.springframework.cache.annotation.CachePut *) && execution(public * @org.springframework.cache.annotation.CachePut *.*(..))) && this(BindingTypePattern(java.lang.Object, 0))) && persingleton(org.springframework.cache.aspectj.AnnotationCacheAspect))) || (((within(@org.springframework.cache.annotation.Cacheable *) && execution(public * @org.springframework.cache.annotation.Cacheable *.*(..))) && this(BindingTypePattern(java.lang.Object, 0))) && persingleton(org.springframework.cache.aspectj.AnnotationCacheAspect))) || ((execution(@org.springframework.cache.annotation.Caching * *(..)) && this(BindingTypePattern(java.lang.Object, 0))) && persingleton(org.springframework.cache.aspectj.AnnotationCacheAspect))) || ((execution(@org.springframework.cache.annotation.Cacheable * *(..)) && this(BindingTypePattern(java.lang.Object, 0))) && persingleton(org.springframework.cache.aspectj.AnnotationCacheAspect))) || ((execution(@org.springframework.cache.annotation.CacheEvict * *(..)) && this(BindingTypePattern(java.lang.Object, 0))) && persingleton(org.springframework.cache.aspectj.AnnotationCacheAspect))) || ((execution(@org.springframework.cache.annotation.CachePut * *(..)) && this(BindingTypePattern(java.lang.Object, 0))) && persingleton(org.springframework.cache.aspectj.AnnotationCacheAspect)))->java.lang.Object org.springframework.cache.aspectj.AbstractCacheAspect.ajc$around$org_springframework_cache_aspectj_AbstractCacheAspect$1$2bc714b5(java.lang.Object, org.aspectj.runtime.internal.AroundClosure, org.aspectj.lang.JoinPoint))
(around(extraFlags: 5): ((execution(@org.springframework.scheduling.annotation.Async (void || java.util.concurrent.Future+) *(..)) && persingleton(org.springframework.scheduling.aspectj.AnnotationAsyncExecutionAspect)) || (execution((void || java.util.concurrent.Future+) @org.springframework.scheduling.annotation.Async *.*(..)) && persingleton(org.springframework.scheduling.aspectj.AnnotationAsyncExecutionAspect)))->java.lang.Object org.springframework.scheduling.aspectj.AbstractAsyncExecutionAspect.ajc$around$org_springframework_scheduling_aspectj_AbstractAsyncExecutionAspect$1$6c004c3e(org.aspectj.runtime.internal.AroundClosure, org.aspectj.lang.JoinPoint$StaticPart))
org.aspectj.weaver.Checker@5abff562
org.aspectj.weaver.Checker@12140c1d
(before(extraFlags: 4): ((((within(@org.springframework.transaction.annotation.Transactional *) && execution(public * @org.springframework.transaction.annotation.Transactional *.*(..))) && this(BindingTypePattern(java.lang.Object, 0))) && persingleton(org.springframework.transaction.aspectj.AnnotationTransactionAspect)) || ((execution(@org.springframework.transaction.annotation.Transactional * *(..)) && this(BindingTypePattern(java.lang.Object, 0))) && persingleton(org.springframework.transaction.aspectj.AnnotationTransactionAspect)))->void org.springframework.transaction.aspectj.AbstractTransactionAspect.ajc$before$org_springframework_transaction_aspectj_AbstractTransactionAspect$1$2a73e96c(java.lang.Object, org.aspectj.lang.JoinPoint$StaticPart))
(afterThrowing(extraFlags: 1): ((((within(@org.springframework.transaction.annotation.Transactional *) && execution(public * @org.springframework.transaction.annotation.Transactional *.*(..))) && this(BindingTypePattern(java.lang.Object, 0))) && persingleton(org.springframework.transaction.aspectj.AnnotationTransactionAspect)) || ((execution(@org.springframework.transaction.annotation.Transactional * *(..)) && this(BindingTypePattern(java.lang.Object, 0))) && persingleton(org.springframework.transaction.aspectj.AnnotationTransactionAspect)))->void org.springframework.transaction.aspectj.AbstractTransactionAspect.ajc$afterThrowing$org_springframework_transaction_aspectj_AbstractTransactionAspect$2$2a73e96c(java.lang.Object, java.lang.Throwable))
(afterReturning: ((((within(@org.springframework.transaction.annotation.Transactional *) && execution(public * @org.springframework.transaction.annotation.Transactional *.*(..))) && this(BindingTypePattern(java.lang.Object, 0))) && persingleton(org.springframework.transaction.aspectj.AnnotationTransactionAspect)) || ((execution(@org.springframework.transaction.annotation.Transactional * *(..)) && this(BindingTypePattern(java.lang.Object, 0))) && persingleton(org.springframework.transaction.aspectj.AnnotationTransactionAspect)))->void org.springframework.transaction.aspectj.AbstractTransactionAspect.ajc$afterReturning$org_springframework_transaction_aspectj_AbstractTransactionAspect$3$2a73e96c(java.lang.Object))
(after: ((((within(@org.springframework.transaction.annotation.Transactional *) && execution(public * @org.springframework.transaction.annotation.Transactional *.*(..))) && this(BindingTypePattern(java.lang.Object, 0))) && persingleton(org.springframework.transaction.aspectj.AnnotationTransactionAspect)) || ((execution(@org.springframework.transaction.annotation.Transactional * *(..)) && this(BindingTypePattern(java.lang.Object, 0))) && persingleton(org.springframework.transaction.aspectj.AnnotationTransactionAspect)))->void org.springframework.transaction.aspectj.AbstractTransactionAspect.ajc$after$org_springframework_transaction_aspectj_AbstractTransactionAspect$4$2a73e96c(java.lang.Object))
(before: (((((initialization(org.springframework.beans.factory.aspectj.ConfigurableObject.new(..)) && initialization(org.springframework.beans.factory.aspectj.ConfigurableObject+.new(..))) && this(BindingTypePattern(java.lang.Object, 0))) && @this(org.springframework.beans.factory.annotation.Configurable)) && if(boolean org.springframework.beans.factory.aspectj.AnnotationBeanConfigurerAspect.ajc$if$bb0(org.springframework.beans.factory.annotation.Configurable))) && persingleton(org.springframework.beans.factory.aspectj.AnnotationBeanConfigurerAspect))->void org.springframework.beans.factory.aspectj.AbstractDependencyInjectionAspect.ajc$before$org_springframework_beans_factory_aspectj_AbstractDependencyInjectionAspect$1$e854fa65(java.lang.Object))
(afterReturning: (((((initialization(org.springframework.beans.factory.aspectj.ConfigurableObject+.new(..)) && this(BindingTypePattern(java.lang.Object, 0))) && @this(org.springframework.beans.factory.annotation.Configurable)) && !(@this(org.springframework.beans.factory.annotation.Configurable) && if(boolean org.springframework.beans.factory.aspectj.AnnotationBeanConfigurerAspect.ajc$if$bb0(org.springframework.beans.factory.annotation.Configurable)))) && if(boolean org.springframework.beans.factory.aspectj.AbstractDependencyInjectionAspect.ajc$if$6f1(org.aspectj.lang.JoinPoint))) && persingleton(org.springframework.beans.factory.aspectj.AnnotationBeanConfigurerAspect))->void org.springframework.beans.factory.aspectj.AbstractDependencyInjectionAspect.ajc$afterReturning$org_springframework_beans_factory_aspectj_AbstractDependencyInjectionAspect$2$1ea6722c(java.lang.Object))
(afterReturning: (((execution(java.lang.Object org.springframework.beans.factory.aspectj.AbstractInterfaceDrivenDependencyInjectionAspect$ConfigurableDeserializationSupport+.readResolve()) && this(BindingTypePattern(java.lang.Object, 0))) && @this(org.springframework.beans.factory.annotation.Configurable)) && persingleton(org.springframework.beans.factory.aspectj.AnnotationBeanConfigurerAspect))->void org.springframework.beans.factory.aspectj.AbstractDependencyInjectionAspect.ajc$afterReturning$org_springframework_beans_factory_aspectj_AbstractDependencyInjectionAspect$3$6aa27052(java.lang.Object))
Type mungers:
(BcelTypeMunger ResolvedTypeMunger(Method, java.lang.Object org.springframework.beans.factory.aspectj.AbstractInterfaceDrivenDependencyInjectionAspect$ConfigurableDeserializationSupport.readResolve()))
(BcelTypeMunger ExposeTypeMunger(java.lang.Object))
(BcelTypeMunger ExposeTypeMunger(java.lang.Object))
(BcelTypeMunger ExposeTypeMunger(java.lang.Object))
(BcelTypeMunger ExposeTypeMunger(org.springframework.beans.factory.aspectj.ConfigurableObject))
(BcelTypeMunger ExposeTypeMunger(org.springframework.beans.factory.aspectj.AbstractInterfaceDrivenDependencyInjectionAspect$ConfigurableDeserializationSupport))
Late Type mungers:
Empty
