---- AspectJ Properties ---
AspectJ Compiler 1.6.2 built on Saturday Oct 4, 2008 at 05:47:07 GMT
---- Dump Properties ---
Dump file: ajcore.20160604.114036.541.txt
Dump reason: abort
Dump on exception: true
Dump at exit condition: abort
---- System Properties ---
java.runtime.name=Java(TM) SE Runtime Environment
sun.boot.library.path=C:\Program Files\Java\jdk1.8.0_72\jre\bin
java.vm.version=25.72-b15
java.vm.vendor=Oracle Corporation
java.vendor.url=http://java.oracle.com/
path.separator=;
java.vm.name=Java HotSpot(TM) 64-Bit Server VM
file.encoding.pkg=sun.io
user.country=ES
user.script=
sun.java.launcher=SUN_STANDARD
sun.os.patch.level=
java.vm.specification.name=Java Virtual Machine Specification
user.dir=C:\Users\usuario\git\spring\aspectos\Ejemplos Relacionados\SpringIoC0007Maven
java.runtime.version=1.8.0_72-b15
java.awt.graphicsenv=sun.awt.Win32GraphicsEnvironment
java.endorsed.dirs=C:\Program Files\Java\jdk1.8.0_72\jre\lib\endorsed
os.arch=amd64
java.io.tmpdir=C:\Users\usuario\AppData\Local\Temp\
line.separator=

java.vm.specification.vendor=Oracle Corporation
user.variant=
os.name=Windows 10
sun.jnu.encoding=Cp1252
java.library.path=C:\Program Files\Java\jdk1.8.0_72\bin;C:\WINDOWS\Sun\Java\bin;C:\WINDOWS\system32;C:\WINDOWS;C:\ProgramData\Oracle\Java\javapath;C:\Program Files\CollabNet\Subversion Client;E:\bin\Sencha\Cmd\5.1.3.61;C:\Users\usuario\bin\Sencha\Cmd\5.1.3.61;C:\Program Files (x86)\Intel\iCLS Client\;C:\Program Files\Intel\iCLS Client\;C:\WINDOWS\system32;C:\WINDOWS;C:\WINDOWS\System32\Wbem;C:\WINDOWS\System32\WindowsPowerShell\v1.0\;C:\Program Files\Intel\Intel(R) Management Engine Components\DAL;C:\Program Files\Intel\Intel(R) Management Engine Components\IPT;C:\Program Files (x86)\Intel\Intel(R) Management Engine Components\DAL;C:\Program Files (x86)\Intel\Intel(R) Management Engine Components\IPT;C:\Program Files (x86)\Intel\OpenCL SDK\3.0\bin\x86;C:\Program Files (x86)\Intel\OpenCL SDK\3.0\bin\x64;C:\Program Files (x86)\sbt\\bin;C:\Program Files (x86)\Heroku\bin;C:\Program Files (x86)\git\cmd;C:\Program Files (x86)\QuickTime\QTSystem\;C:\HashiCorp\Vagrant\bin;C:\Program Files (x86)\scala\bin;C:\Program Files\nodejs\;C:\Users\usuario\AppData\Local\.meteor\;C:\Users\usuario\AppData\Roaming\npm;.
java.specification.name=Java Platform API Specification
java.class.version=52.0
sun.management.compiler=HotSpot 64-Bit Tiered Compilers
os.version=10.0
user.home=C:\Users\usuario
user.timezone=Europe/Paris
java.awt.printerjob=sun.awt.windows.WPrinterJob
file.encoding=Cp1252
java.specification.version=1.8
java.class.path=C:\Users\usuario\git\spring\aspectos\Ejemplos Relacionados\SpringIoC0007Maven\target\classes;C:\Users\usuario\.m2\repository\org\springframework\spring-context\3.1.2.RELEASE\spring-context-3.1.2.RELEASE.jar;C:\Users\usuario\.m2\repository\org\springframework\spring-aop\3.1.2.RELEASE\spring-aop-3.1.2.RELEASE.jar;C:\Users\usuario\.m2\repository\aopalliance\aopalliance\1.0\aopalliance-1.0.jar;C:\Users\usuario\.m2\repository\org\springframework\spring-beans\3.1.2.RELEASE\spring-beans-3.1.2.RELEASE.jar;C:\Users\usuario\.m2\repository\org\springframework\spring-core\3.1.2.RELEASE\spring-core-3.1.2.RELEASE.jar;C:\Users\usuario\.m2\repository\commons-logging\commons-logging\1.1.1\commons-logging-1.1.1.jar;C:\Users\usuario\.m2\repository\org\springframework\spring-expression\3.1.2.RELEASE\spring-expression-3.1.2.RELEASE.jar;C:\Users\usuario\.m2\repository\org\springframework\spring-asm\3.1.2.RELEASE\spring-asm-3.1.2.RELEASE.jar;C:\Users\usuario\.m2\repository\org\springframework\spring-aspects\3.1.2.RELEASE\spring-aspects-3.1.2.RELEASE.jar;C:\Users\usuario\.m2\repository\org\springframework\spring-context-support\3.1.2.RELEASE\spring-context-support-3.1.2.RELEASE.jar;.\..\aspectjweaver.jar
user.name=usuario
java.vm.specification.version=1.8
sun.java.command=com.curso.spring.springioc0007.Main
java.home=C:\Program Files\Java\jdk1.8.0_72\jre
sun.arch.data.model=64
user.language=es
java.specification.vendor=Oracle Corporation
awt.toolkit=sun.awt.windows.WToolkit
java.vm.info=mixed mode
java.version=1.8.0_72
java.ext.dirs=C:\Program Files\Java\jdk1.8.0_72\jre\lib\ext;C:\WINDOWS\Sun\Java\lib\ext
sun.boot.class.path=C:\Program Files\Java\jdk1.8.0_72\jre\lib\resources.jar;C:\Program Files\Java\jdk1.8.0_72\jre\lib\rt.jar;C:\Program Files\Java\jdk1.8.0_72\jre\lib\sunrsasign.jar;C:\Program Files\Java\jdk1.8.0_72\jre\lib\jsse.jar;C:\Program Files\Java\jdk1.8.0_72\jre\lib\jce.jar;C:\Program Files\Java\jdk1.8.0_72\jre\lib\charsets.jar;C:\Program Files\Java\jdk1.8.0_72\jre\lib\jfr.jar;C:\Program Files\Java\jdk1.8.0_72\jre\classes
java.vendor=Oracle Corporation
file.separator=\
java.vendor.url.bug=http://bugreport.sun.com/bugreport/
sun.io.unicode.encoding=UnicodeLittle
sun.cpu.endian=little
sun.desktop=windows
sun.cpu.isalist=amd64
---- Command Line ---
Empty
---- Full Classpath ---
Empty
---- Compiler Messages ---
info AspectJ Weaver Version 1.6.2 built on Saturday Oct 4, 2008 at 05:47:07 GMT
info register classloader sun.misc.Launcher$AppClassLoader@18b4aac2
info using configuration file:/C:/Users/usuario/.m2/repository/org/springframework/spring-aspects/3.1.2.RELEASE/spring-aspects-3.1.2.RELEASE.jar!/META-INF/aop.xml
debug weaving 'org.springframework.core.convert.support.ObjectToObjectConverter'
abort trouble in: 
final class org.springframework.core.convert.support.ObjectToObjectConverter extends java.lang.Object implements org.springframework.core.convert.converter.ConditionalGenericConverter:
  void <init>():
                    ALOAD_0     // Lorg/springframework/core/convert/support/ObjectToObjectConverter; this   (line 44)
                    INVOKESPECIAL java.lang.Object.<init> ()V
    constructor-execution(void org.springframework.core.convert.support.ObjectToObjectConverter.<init>())
    |               RETURN
    constructor-execution(void org.springframework.core.convert.support.ObjectToObjectConverter.<init>())
  end void <init>()

  public java.util.Set getConvertibleTypes():
                    NEW org.springframework.core.convert.converter.GenericConverter$ConvertiblePair   (line 47)
                    DUP
                    LDC java.lang.Object
                    LDC java.lang.Object
                    INVOKESPECIAL org.springframework.core.convert.converter.GenericConverter$ConvertiblePair.<init> (Ljava/lang/Class;Ljava/lang/Class;)V
                    INVOKESTATIC java.util.Collections.singleton (Ljava/lang/Object;)Ljava/util/Set;
                    ARETURN
  end public java.util.Set getConvertibleTypes()

  public boolean matches(org.springframework.core.convert.TypeDescriptor, org.springframework.core.convert.TypeDescriptor):
                    ALOAD_1     // Lorg/springframework/core/convert/TypeDescriptor; sourceType   (line 51)
                    ALOAD_2     // Lorg/springframework/core/convert/TypeDescriptor; targetType
                    INVOKEVIRTUAL org.springframework.core.convert.TypeDescriptor.equals (Ljava/lang/Object;)Z
                    IFNE L0
                    ALOAD_2     // Lorg/springframework/core/convert/TypeDescriptor; targetType
                    INVOKEVIRTUAL org.springframework.core.convert.TypeDescriptor.getType ()Ljava/lang/Class;
                    ALOAD_1     // Lorg/springframework/core/convert/TypeDescriptor; sourceType
                    INVOKEVIRTUAL org.springframework.core.convert.TypeDescriptor.getType ()Ljava/lang/Class;
                    INVOKESTATIC org.springframework.core.convert.support.ObjectToObjectConverter.hasValueOfMethodOrConstructor (Ljava/lang/Class;Ljava/lang/Class;)Z
                    IFEQ L0
                    ICONST_1
                    IRETURN
                L0: ICONST_0
                    IRETURN
  end public boolean matches(org.springframework.core.convert.TypeDescriptor, org.springframework.core.convert.TypeDescriptor)

  public Object convert(Object, org.springframework.core.convert.TypeDescriptor, org.springframework.core.convert.TypeDescriptor):
                    ALOAD_2     // Lorg/springframework/core/convert/TypeDescriptor; sourceType   (line 55)
                    INVOKEVIRTUAL org.springframework.core.convert.TypeDescriptor.getType ()Ljava/lang/Class;
                    ASTORE 4
                    ALOAD_3     // Lorg/springframework/core/convert/TypeDescriptor; targetType   (line 56)
                    INVOKEVIRTUAL org.springframework.core.convert.TypeDescriptor.getType ()Ljava/lang/Class;
                    ASTORE 5
                    ALOAD 5     // Ljava/lang/Class; targetClass   (line 57)
                    ALOAD 4     // Ljava/lang/Class; sourceClass
                    INVOKESTATIC org.springframework.core.convert.support.ObjectToObjectConverter.getValueOfMethodOn (Ljava/lang/Class;Ljava/lang/Class;)Ljava/lang/reflect/Method;
                    ASTORE 6
    catch java.lang.Throwable -> E3
    | catch java.lang.reflect.InvocationTargetException -> E1
    | |             ALOAD 6     // Ljava/lang/reflect/Method; method   (line 59)
    | |             IFNULL L0
    | |             ALOAD 6     // Ljava/lang/reflect/Method; method   (line 60)
    | |             INVOKESTATIC org.springframework.util.ReflectionUtils.makeAccessible (Ljava/lang/reflect/Method;)V
    | |             ALOAD 6     // Ljava/lang/reflect/Method; method   (line 61)
    | |             ACONST_NULL
    | |             ICONST_1
    | |             ANEWARRAY java.lang.Object
    | |             DUP
    | |             ICONST_0
    | |             ALOAD_1     // Ljava/lang/Object; source
    | |             AASTORE
    | |             INVOKEVIRTUAL java.lang.reflect.Method.invoke (Ljava/lang/Object;[Ljava/lang/Object;)Ljava/lang/Object;
    | catch java.lang.reflect.InvocationTargetException -> E1
    catch java.lang.Throwable -> E3
                    ARETURN
    catch java.lang.Throwable -> E3
    | catch java.lang.reflect.InvocationTargetException -> E1
    | |         L0: ALOAD 5     // Ljava/lang/Class; targetClass   (line 64)
    | |             ALOAD 4     // Ljava/lang/Class; sourceClass
    | |             INVOKESTATIC org.springframework.core.convert.support.ObjectToObjectConverter.getConstructor (Ljava/lang/Class;Ljava/lang/Class;)Ljava/lang/reflect/Constructor;
    | |             ASTORE 7
    | |             ALOAD 7     // Ljava/lang/reflect/Constructor; constructor   (line 65)
    | |             IFNULL L1
    | |             ALOAD 7     // Ljava/lang/reflect/Constructor; constructor   (line 66)
    | |             ICONST_1
    | |             ANEWARRAY java.lang.Object
    | |             DUP
    | |             ICONST_0
    | |             ALOAD_1     // Ljava/lang/Object; source
    | |             AASTORE
    | |             INVOKEVIRTUAL java.lang.reflect.Constructor.newInstance ([Ljava/lang/Object;)Ljava/lang/Object;
    | catch java.lang.reflect.InvocationTargetException -> E1
    catch java.lang.Throwable -> E3
                    ARETURN
                E1: ASTORE 7   (line 70)
                    NEW org.springframework.core.convert.ConversionFailedException   (line 71)
                    DUP
                    ALOAD_2     // Lorg/springframework/core/convert/TypeDescriptor; sourceType
                    ALOAD_3     // Lorg/springframework/core/convert/TypeDescriptor; targetType
                    ALOAD_1     // Ljava/lang/Object; source
                    ALOAD 7     // Ljava/lang/reflect/InvocationTargetException; ex
                    INVOKEVIRTUAL java.lang.reflect.InvocationTargetException.getTargetException ()Ljava/lang/Throwable;
                    INVOKESPECIAL org.springframework.core.convert.ConversionFailedException.<init> (Lorg/springframework/core/convert/TypeDescriptor;Lorg/springframework/core/convert/TypeDescriptor;Ljava/lang/Object;Ljava/lang/Throwable;)V
                    ATHROW
                E3: ASTORE 7   (line 73)
                    NEW org.springframework.core.convert.ConversionFailedException   (line 74)
                    DUP
                    ALOAD_2     // Lorg/springframework/core/convert/TypeDescriptor; sourceType
                    ALOAD_3     // Lorg/springframework/core/convert/TypeDescriptor; targetType
                    ALOAD_1     // Ljava/lang/Object; source
                    ALOAD 7     // Ljava/lang/Throwable; ex
                    INVOKESPECIAL org.springframework.core.convert.ConversionFailedException.<init> (Lorg/springframework/core/convert/TypeDescriptor;Lorg/springframework/core/convert/TypeDescriptor;Ljava/lang/Object;Ljava/lang/Throwable;)V
                    ATHROW
                L1: NEW java.lang.IllegalStateException   (line 76)
                    DUP
                    NEW java.lang.StringBuilder
                    DUP
                    LDC "No static valueOf("
                    INVOKESPECIAL java.lang.StringBuilder.<init> (Ljava/lang/String;)V
                    ALOAD 4     // Ljava/lang/Class; sourceClass
                    INVOKEVIRTUAL java.lang.Class.getName ()Ljava/lang/String;
                    INVOKEVIRTUAL java.lang.StringBuilder.append (Ljava/lang/String;)Ljava/lang/StringBuilder;
                    LDC ") method or Constructor("   (line 77)
                    INVOKEVIRTUAL java.lang.StringBuilder.append (Ljava/lang/String;)Ljava/lang/StringBuilder;
                    ALOAD 4     // Ljava/lang/Class; sourceClass
                    INVOKEVIRTUAL java.lang.Class.getName ()Ljava/lang/String;
                    INVOKEVIRTUAL java.lang.StringBuilder.append (Ljava/lang/String;)Ljava/lang/StringBuilder;
                    LDC ") exists on "
                    INVOKEVIRTUAL java.lang.StringBuilder.append (Ljava/lang/String;)Ljava/lang/StringBuilder;
                    ALOAD 5     // Ljava/lang/Class; targetClass
                    INVOKEVIRTUAL java.lang.Class.getName ()Ljava/lang/String;
                    INVOKEVIRTUAL java.lang.StringBuilder.append (Ljava/lang/String;)Ljava/lang/StringBuilder;
                    INVOKEVIRTUAL java.lang.StringBuilder.toString ()Ljava/lang/String;
                    INVOKESPECIAL java.lang.IllegalStateException.<init> (Ljava/lang/String;)V   (line 76)
                    ATHROW
  end public Object convert(Object, org.springframework.core.convert.TypeDescriptor, org.springframework.core.convert.TypeDescriptor)

  static boolean hasValueOfMethodOrConstructor(Class, Class):
                    ALOAD_0     // Ljava/lang/Class; clazz   (line 81)
                    ALOAD_1     // Ljava/lang/Class; sourceParameterType
                    INVOKESTATIC org.springframework.core.convert.support.ObjectToObjectConverter.getValueOfMethodOn (Ljava/lang/Class;Ljava/lang/Class;)Ljava/lang/reflect/Method;
                    IFNONNULL L0
                    ALOAD_0     // Ljava/lang/Class; clazz
                    ALOAD_1     // Ljava/lang/Class; sourceParameterType
                    INVOKESTATIC org.springframework.core.convert.support.ObjectToObjectConverter.getConstructor (Ljava/lang/Class;Ljava/lang/Class;)Ljava/lang/reflect/Constructor;
                    IFNONNULL L0
                    ICONST_0
                    IRETURN
                L0: ICONST_1
                    IRETURN
  end static boolean hasValueOfMethodOrConstructor(Class, Class)

  private static java.lang.reflect.Method getValueOfMethodOn(Class, Class):
                    ALOAD_0     // Ljava/lang/Class; clazz   (line 85)
                    LDC "valueOf"
                    ICONST_1
                    ANEWARRAY java.lang.Class
                    DUP
                    ICONST_0
                    ALOAD_1     // Ljava/lang/Class; sourceParameterType
                    AASTORE
                    INVOKESTATIC org.springframework.util.ClassUtils.getStaticMethod (Ljava/lang/Class;Ljava/lang/String;[Ljava/lang/Class;)Ljava/lang/reflect/Method;
                    ARETURN
  end private static java.lang.reflect.Method getValueOfMethodOn(Class, Class)

  private static java.lang.reflect.Constructor getConstructor(Class, Class):
                    ALOAD_0     // Ljava/lang/Class; clazz   (line 89)
                    ICONST_1
                    ANEWARRAY java.lang.Class
                    DUP
                    ICONST_0
                    ALOAD_1     // Ljava/lang/Class; sourceParameterType
                    AASTORE
                    INVOKESTATIC org.springframework.util.ClassUtils.getConstructorIfAvailable (Ljava/lang/Class;[Ljava/lang/Class;)Ljava/lang/reflect/Constructor;
                    ARETURN
  end private static java.lang.reflect.Constructor getConstructor(Class, Class)

end final class org.springframework.core.convert.support.ObjectToObjectConverter
 -- (ClassFormatException) File: 'java.lang.reflect.AnnotatedElement': Invalid byte tag in constant pool: 15
File: 'java.lang.reflect.AnnotatedElement': Invalid byte tag in constant pool: 15
org.aspectj.apache.bcel.classfile.ClassFormatException: File: 'java.lang.reflect.AnnotatedElement': Invalid byte tag in constant pool: 15
	at org.aspectj.apache.bcel.classfile.ClassParser.readConstantPool(ClassParser.java:192)
	at org.aspectj.apache.bcel.classfile.ClassParser.parse(ClassParser.java:131)
	at org.aspectj.apache.bcel.util.ClassLoaderRepository.loadClass(ClassLoaderRepository.java:292)
	at org.aspectj.weaver.bcel.BcelWorld.lookupJavaClass(BcelWorld.java:224)
	at org.aspectj.weaver.bcel.BcelWorld.resolveDelegate(BcelWorld.java:205)
	at org.aspectj.weaver.ltw.LTWWorld.resolveDelegate(LTWWorld.java:107)
	at org.aspectj.weaver.World.resolveToReferenceType(World.java:363)
	at org.aspectj.weaver.World.resolve(World.java:258)
	at org.aspectj.weaver.World.resolve(World.java:180)
	at org.aspectj.weaver.bcel.BcelObjectType.getDeclaredInterfaces(BcelObjectType.java:238)
	at org.aspectj.weaver.ReferenceType.getDeclaredInterfaces(ReferenceType.java:484)
	at org.aspectj.weaver.ResolvedType.getDirectSupertypes(ResolvedType.java:70)
	at org.aspectj.weaver.patterns.TypePattern.matchesSubtypes(TypePattern.java:189)
	at org.aspectj.weaver.patterns.TypePattern.matchesSubtypes(TypePattern.java:191)
	at org.aspectj.weaver.patterns.TypePattern.matchesSubtypes(TypePattern.java:173)
	at org.aspectj.weaver.patterns.TypePattern.matchesStatically(TypePattern.java:119)
	at org.aspectj.weaver.patterns.OrTypePattern.matchesStatically(OrTypePattern.java:74)
	at org.aspectj.weaver.patterns.SignaturePattern.matchesExactlyMethod(SignaturePattern.java:391)
	at org.aspectj.weaver.patterns.SignaturePattern.matchesExactly(SignaturePattern.java:336)
	at org.aspectj.weaver.patterns.SignaturePattern.matches(SignaturePattern.java:300)
	at org.aspectj.weaver.patterns.KindedPointcut.matchInternal(KindedPointcut.java:106)
	at org.aspectj.weaver.patterns.Pointcut.match(Pointcut.java:146)
	at org.aspectj.weaver.patterns.AndPointcut.matchInternal(AndPointcut.java:52)
	at org.aspectj.weaver.patterns.Pointcut.match(Pointcut.java:146)
	at org.aspectj.weaver.patterns.OrPointcut.matchInternal(OrPointcut.java:51)
	at org.aspectj.weaver.patterns.Pointcut.match(Pointcut.java:146)
	at org.aspectj.weaver.ShadowMunger.match(ShadowMunger.java:70)
	at org.aspectj.weaver.Advice.match(Advice.java:106)
	at org.aspectj.weaver.bcel.BcelAdvice.match(BcelAdvice.java:140)
	at org.aspectj.weaver.bcel.BcelClassWeaver.match(BcelClassWeaver.java:2980)
	at org.aspectj.weaver.bcel.BcelClassWeaver.match(BcelClassWeaver.java:2489)
	at org.aspectj.weaver.bcel.BcelClassWeaver.weave(BcelClassWeaver.java:486)
	at org.aspectj.weaver.bcel.BcelClassWeaver.weave(BcelClassWeaver.java:98)
	at org.aspectj.weaver.bcel.BcelWeaver.weave(BcelWeaver.java:1733)
	at org.aspectj.weaver.bcel.BcelWeaver.weaveWithoutDump(BcelWeaver.java:1694)
	at org.aspectj.weaver.bcel.BcelWeaver.weaveAndNotify(BcelWeaver.java:1464)
	at org.aspectj.weaver.bcel.BcelWeaver.weave(BcelWeaver.java:1273)
	at org.aspectj.weaver.tools.WeavingAdaptor.getWovenBytes(WeavingAdaptor.java:394)
	at org.aspectj.weaver.tools.WeavingAdaptor.weaveClass(WeavingAdaptor.java:281)
	at org.aspectj.weaver.loadtime.Aj.preProcess(Aj.java:95)
	at org.aspectj.weaver.loadtime.ClassPreProcessorAgentAdapter.transform(ClassPreProcessorAgentAdapter.java:52)
	at sun.instrument.TransformerManager.transform(TransformerManager.java:188)
	at sun.instrument.InstrumentationImpl.transform(InstrumentationImpl.java:428)
	at java.lang.ClassLoader.defineClass1(Native Method)
	at java.lang.ClassLoader.defineClass(ClassLoader.java:760)
	at java.security.SecureClassLoader.defineClass(SecureClassLoader.java:142)
	at java.net.URLClassLoader.defineClass(URLClassLoader.java:467)
	at java.net.URLClassLoader.access$100(URLClassLoader.java:73)
	at java.net.URLClassLoader$1.run(URLClassLoader.java:368)
	at java.net.URLClassLoader$1.run(URLClassLoader.java:362)
	at java.security.AccessController.doPrivileged(Native Method)
	at java.net.URLClassLoader.findClass(URLClassLoader.java:361)
	at java.lang.ClassLoader.loadClass(ClassLoader.java:424)
	at sun.misc.Launcher$AppClassLoader.loadClass(Launcher.java:331)
	at java.lang.ClassLoader.loadClass(ClassLoader.java:357)
	at org.springframework.core.convert.support.DefaultConversionService.addFallbackConverters(DefaultConversionService.java:109)
	at org.springframework.core.convert.support.DefaultConversionService.addDefaultConverters(DefaultConversionService.java:55)
	at org.springframework.core.convert.support.DefaultConversionService.<init>(DefaultConversionService.java:42)
	at org.springframework.core.env.AbstractPropertyResolver.<init>(AbstractPropertyResolver.java:44)
	at org.springframework.core.env.PropertySourcesPropertyResolver.<init>(PropertySourcesPropertyResolver.java:42)
	at org.springframework.core.env.AbstractEnvironment.<init>(AbstractEnvironment.java:101)
	at org.springframework.core.env.StandardEnvironment.<init>(StandardEnvironment.java:54)
	at org.springframework.context.support.AbstractApplicationContext.createEnvironment(AbstractApplicationContext.java:432)
	at org.springframework.context.support.AbstractApplicationContext.<init>(AbstractApplicationContext.java:227)
	at org.springframework.context.support.AbstractRefreshableApplicationContext.<init>(AbstractRefreshableApplicationContext.java:90)
	at org.springframework.context.support.AbstractRefreshableConfigApplicationContext.<init>(AbstractRefreshableConfigApplicationContext.java:59)
	at org.springframework.context.support.AbstractXmlApplicationContext.<init>(AbstractXmlApplicationContext.java:61)
	at org.springframework.context.support.ClassPathXmlApplicationContext.<init>(ClassPathXmlApplicationContext.java:136)
	at org.springframework.context.support.ClassPathXmlApplicationContext.<init>(ClassPathXmlApplicationContext.java:83)
	at com.curso.spring.springioc0007.Main.init(Main.java:29)
	at com.curso.spring.springioc0007.Main.main(Main.java:24)

debug weaving 'org.springframework.core.convert.support.IdToEntityConverter'
abort trouble in: 
final class org.springframework.core.convert.support.IdToEntityConverter extends java.lang.Object implements org.springframework.core.convert.converter.ConditionalGenericConverter:
  private final org.springframework.core.convert.ConversionService conversionService
  public void <init>(org.springframework.core.convert.ConversionService):
                    ALOAD_0     // Lorg/springframework/core/convert/support/IdToEntityConverter; this   (line 44)
                    INVOKESPECIAL java.lang.Object.<init> ()V
    constructor-execution(void org.springframework.core.convert.support.IdToEntityConverter.<init>(org.springframework.core.convert.ConversionService))
    |               ALOAD_0     // Lorg/springframework/core/convert/support/IdToEntityConverter; this   (line 45)
    |               ALOAD_1     // Lorg/springframework/core/convert/ConversionService; conversionService
    |               PUTFIELD org.springframework.core.convert.support.IdToEntityConverter.conversionService Lorg/springframework/core/convert/ConversionService;
    |               RETURN   (line 46)
    constructor-execution(void org.springframework.core.convert.support.IdToEntityConverter.<init>(org.springframework.core.convert.ConversionService))
  end public void <init>(org.springframework.core.convert.ConversionService)

  public java.util.Set getConvertibleTypes():
                    NEW org.springframework.core.convert.converter.GenericConverter$ConvertiblePair   (line 49)
                    DUP
                    LDC java.lang.Object
                    LDC java.lang.Object
                    INVOKESPECIAL org.springframework.core.convert.converter.GenericConverter$ConvertiblePair.<init> (Ljava/lang/Class;Ljava/lang/Class;)V
                    INVOKESTATIC java.util.Collections.singleton (Ljava/lang/Object;)Ljava/util/Set;
                    ARETURN
  end public java.util.Set getConvertibleTypes()

  public boolean matches(org.springframework.core.convert.TypeDescriptor, org.springframework.core.convert.TypeDescriptor):
                    ALOAD_0     // Lorg/springframework/core/convert/support/IdToEntityConverter; this   (line 53)
                    ALOAD_2     // Lorg/springframework/core/convert/TypeDescriptor; targetType
                    INVOKEVIRTUAL org.springframework.core.convert.TypeDescriptor.getType ()Ljava/lang/Class;
                    INVOKESPECIAL org.springframework.core.convert.support.IdToEntityConverter.getFinder (Ljava/lang/Class;)Ljava/lang/reflect/Method;
                    ASTORE_3
                    ALOAD_3     // Ljava/lang/reflect/Method; finder   (line 54)
                    IFNULL L0
                    ALOAD_0     // Lorg/springframework/core/convert/support/IdToEntityConverter; this
                    GETFIELD org.springframework.core.convert.support.IdToEntityConverter.conversionService Lorg/springframework/core/convert/ConversionService;
                    ALOAD_1     // Lorg/springframework/core/convert/TypeDescriptor; sourceType
                    ALOAD_3     // Ljava/lang/reflect/Method; finder
                    INVOKEVIRTUAL java.lang.reflect.Method.getParameterTypes ()[Ljava/lang/Class;
                    ICONST_0
                    AALOAD
                    INVOKESTATIC org.springframework.core.convert.TypeDescriptor.valueOf (Ljava/lang/Class;)Lorg/springframework/core/convert/TypeDescriptor;
                    INVOKEINTERFACE org.springframework.core.convert.ConversionService.canConvert (Lorg/springframework/core/convert/TypeDescriptor;Lorg/springframework/core/convert/TypeDescriptor;)Z
                    IFEQ L0
                    ICONST_1
                    IRETURN
                L0: ICONST_0
                    IRETURN
  end public boolean matches(org.springframework.core.convert.TypeDescriptor, org.springframework.core.convert.TypeDescriptor)

  public Object convert(Object, org.springframework.core.convert.TypeDescriptor, org.springframework.core.convert.TypeDescriptor):
                    ALOAD_1     // Ljava/lang/Object; source   (line 58)
                    IFNONNULL L0
                    ACONST_NULL   (line 59)
                    ARETURN
                L0: ALOAD_0     // Lorg/springframework/core/convert/support/IdToEntityConverter; this   (line 61)
                    ALOAD_3     // Lorg/springframework/core/convert/TypeDescriptor; targetType
                    INVOKEVIRTUAL org.springframework.core.convert.TypeDescriptor.getType ()Ljava/lang/Class;
                    INVOKESPECIAL org.springframework.core.convert.support.IdToEntityConverter.getFinder (Ljava/lang/Class;)Ljava/lang/reflect/Method;
                    ASTORE 4
                    ALOAD_0     // Lorg/springframework/core/convert/support/IdToEntityConverter; this   (line 62)
                    GETFIELD org.springframework.core.convert.support.IdToEntityConverter.conversionService Lorg/springframework/core/convert/ConversionService;
                    ALOAD_1     // Ljava/lang/Object; source
                    ALOAD_2     // Lorg/springframework/core/convert/TypeDescriptor; sourceType
                    ALOAD 4     // Ljava/lang/reflect/Method; finder
                    INVOKEVIRTUAL java.lang.reflect.Method.getParameterTypes ()[Ljava/lang/Class;
                    ICONST_0
                    AALOAD
                    INVOKESTATIC org.springframework.core.convert.TypeDescriptor.valueOf (Ljava/lang/Class;)Lorg/springframework/core/convert/TypeDescriptor;
                    INVOKEINTERFACE org.springframework.core.convert.ConversionService.convert (Ljava/lang/Object;Lorg/springframework/core/convert/TypeDescriptor;Lorg/springframework/core/convert/TypeDescriptor;)Ljava/lang/Object;
                    ASTORE 5
                    ALOAD 4     // Ljava/lang/reflect/Method; finder   (line 63)
                    ALOAD_1     // Ljava/lang/Object; source
                    ICONST_1
                    ANEWARRAY java.lang.Object
                    DUP
                    ICONST_0
                    ALOAD 5     // Ljava/lang/Object; id
                    AASTORE
                    INVOKESTATIC org.springframework.util.ReflectionUtils.invokeMethod (Ljava/lang/reflect/Method;Ljava/lang/Object;[Ljava/lang/Object;)Ljava/lang/Object;
                    ARETURN
  end public Object convert(Object, org.springframework.core.convert.TypeDescriptor, org.springframework.core.convert.TypeDescriptor)

  private java.lang.reflect.Method getFinder(Class):
                    NEW java.lang.StringBuilder   (line 67)
                    DUP
                    LDC "find"
                    INVOKESPECIAL java.lang.StringBuilder.<init> (Ljava/lang/String;)V
                    ALOAD_0     // Lorg/springframework/core/convert/support/IdToEntityConverter; this
                    ALOAD_1     // Ljava/lang/Class; entityClass
                    INVOKESPECIAL org.springframework.core.convert.support.IdToEntityConverter.getEntityName (Ljava/lang/Class;)Ljava/lang/String;
                    INVOKEVIRTUAL java.lang.StringBuilder.append (Ljava/lang/String;)Ljava/lang/StringBuilder;
                    INVOKEVIRTUAL java.lang.StringBuilder.toString ()Ljava/lang/String;
                    ASTORE_2
                    ALOAD_1     // Ljava/lang/Class; entityClass   (line 68)
                    INVOKEVIRTUAL java.lang.Class.getDeclaredMethods ()[Ljava/lang/reflect/Method;
                    ASTORE_3
                    ALOAD_3     // [Ljava/lang/reflect/Method; methods   (line 69)
                    DUP
                    ASTORE 7
                    ARRAYLENGTH
                    ISTORE 6
                    ICONST_0
                    ISTORE 5
                    GOTO L2
                L0: ALOAD 7
                    ILOAD 5
                    AALOAD
                    ASTORE 4
                    ALOAD 4     // Ljava/lang/reflect/Method; method   (line 70)
                    INVOKEVIRTUAL java.lang.reflect.Method.getModifiers ()I
                    INVOKESTATIC java.lang.reflect.Modifier.isStatic (I)Z
                    IFEQ L1
                    ALOAD 4     // Ljava/lang/reflect/Method; method
                    INVOKEVIRTUAL java.lang.reflect.Method.getParameterTypes ()[Ljava/lang/Class;
                    ARRAYLENGTH
                    ICONST_1
                    IF_ICMPNE L1
                    ALOAD 4     // Ljava/lang/reflect/Method; method
                    INVOKEVIRTUAL java.lang.reflect.Method.getReturnType ()Ljava/lang/Class;
                    ALOAD_1     // Ljava/lang/Class; entityClass
                    INVOKEVIRTUAL java.lang.Object.equals (Ljava/lang/Object;)Z
                    IFEQ L1
                    ALOAD 4     // Ljava/lang/reflect/Method; method   (line 71)
                    INVOKEVIRTUAL java.lang.reflect.Method.getName ()Ljava/lang/String;
                    ALOAD_2     // Ljava/lang/String; finderMethod
                    INVOKEVIRTUAL java.lang.String.equals (Ljava/lang/Object;)Z
                    IFEQ L1
                    ALOAD 4     // Ljava/lang/reflect/Method; method   (line 72)
                    ARETURN
                L1: IINC 5 1   (line 69)
                L2: ILOAD 5
                    ILOAD 6
                    IF_ICMPLT L0
                    ACONST_NULL   (line 76)
                    ARETURN
  end private java.lang.reflect.Method getFinder(Class)

  private String getEntityName(Class):
                    ALOAD_1     // Ljava/lang/Class; entityClass   (line 80)
                    INVOKESTATIC org.springframework.util.ClassUtils.getShortName (Ljava/lang/Class;)Ljava/lang/String;
                    ASTORE_2
                    ALOAD_2     // Ljava/lang/String; shortName   (line 81)
                    BIPUSH 46
                    INVOKEVIRTUAL java.lang.String.lastIndexOf (I)I
                    ISTORE_3
                    ILOAD_3     // I lastDot   (line 82)
                    ICONST_M1
                    IF_ICMPEQ L0
                    ALOAD_2     // Ljava/lang/String; shortName   (line 83)
                    ILOAD_3     // I lastDot
                    ICONST_1
                    IADD
                    INVOKEVIRTUAL java.lang.String.substring (I)Ljava/lang/String;
                    ARETURN
                L0: ALOAD_2     // Ljava/lang/String; shortName   (line 86)
                    ARETURN
  end private String getEntityName(Class)

end final class org.springframework.core.convert.support.IdToEntityConverter
 -- (NullPointerException) null
null
java.lang.NullPointerException

debug weaving 'org.springframework.core.convert.support.FallbackObjectToStringConverter'
---- org.aspectj.weaver.ltw.LTWWorld@28c97a5 ----
Class loader:
sun.misc.Launcher$AppClassLoader@18b4aac2
Class loader parent:
sun.misc.Launcher$ExtClassLoader@722c41f4
Shadow mungers:
(around(extraFlags: 3): ((((((((((within(@org.springframework.cache.annotation.CacheEvict *) && execution(public * @org.springframework.cache.annotation.CacheEvict *.*(..))) && this(BindingTypePattern(java.lang.Object, 0))) && persingleton(org.springframework.cache.aspectj.AnnotationCacheAspect)) || (((within(@org.springframework.cache.annotation.Caching *) && execution(public * @org.springframework.cache.annotation.Caching *.*(..))) && this(BindingTypePattern(java.lang.Object, 0))) && persingleton(org.springframework.cache.aspectj.AnnotationCacheAspect))) || (((within(@org.springframework.cache.annotation.CachePut *) && execution(public * @org.springframework.cache.annotation.CachePut *.*(..))) && this(BindingTypePattern(java.lang.Object, 0))) && persingleton(org.springframework.cache.aspectj.AnnotationCacheAspect))) || (((within(@org.springframework.cache.annotation.Cacheable *) && execution(public * @org.springframework.cache.annotation.Cacheable *.*(..))) && this(BindingTypePattern(java.lang.Object, 0))) && persingleton(org.springframework.cache.aspectj.AnnotationCacheAspect))) || ((execution(@org.springframework.cache.annotation.Caching * *(..)) && this(BindingTypePattern(java.lang.Object, 0))) && persingleton(org.springframework.cache.aspectj.AnnotationCacheAspect))) || ((execution(@org.springframework.cache.annotation.Cacheable * *(..)) && this(BindingTypePattern(java.lang.Object, 0))) && persingleton(org.springframework.cache.aspectj.AnnotationCacheAspect))) || ((execution(@org.springframework.cache.annotation.CacheEvict * *(..)) && this(BindingTypePattern(java.lang.Object, 0))) && persingleton(org.springframework.cache.aspectj.AnnotationCacheAspect))) || ((execution(@org.springframework.cache.annotation.CachePut * *(..)) && this(BindingTypePattern(java.lang.Object, 0))) && persingleton(org.springframework.cache.aspectj.AnnotationCacheAspect)))->java.lang.Object org.springframework.cache.aspectj.AbstractCacheAspect.ajc$around$org_springframework_cache_aspectj_AbstractCacheAspect$1$2bc714b5(java.lang.Object, org.aspectj.runtime.internal.AroundClosure, org.aspectj.lang.JoinPoint))
(around(extraFlags: 5): ((execution(@org.springframework.scheduling.annotation.Async (void || java.util.concurrent.Future+) *(..)) && persingleton(org.springframework.scheduling.aspectj.AnnotationAsyncExecutionAspect)) || (execution((void || java.util.concurrent.Future+) @org.springframework.scheduling.annotation.Async *.*(..)) && persingleton(org.springframework.scheduling.aspectj.AnnotationAsyncExecutionAspect)))->java.lang.Object org.springframework.scheduling.aspectj.AbstractAsyncExecutionAspect.ajc$around$org_springframework_scheduling_aspectj_AbstractAsyncExecutionAspect$1$6c004c3e(org.aspectj.runtime.internal.AroundClosure, org.aspectj.lang.JoinPoint$StaticPart))
org.aspectj.weaver.Checker@5abff562
org.aspectj.weaver.Checker@12140c1d
(before(extraFlags: 4): ((((within(@org.springframework.transaction.annotation.Transactional *) && execution(public * @org.springframework.transaction.annotation.Transactional *.*(..))) && this(BindingTypePattern(java.lang.Object, 0))) && persingleton(org.springframework.transaction.aspectj.AnnotationTransactionAspect)) || ((execution(@org.springframework.transaction.annotation.Transactional * *(..)) && this(BindingTypePattern(java.lang.Object, 0))) && persingleton(org.springframework.transaction.aspectj.AnnotationTransactionAspect)))->void org.springframework.transaction.aspectj.AbstractTransactionAspect.ajc$before$org_springframework_transaction_aspectj_AbstractTransactionAspect$1$2a73e96c(java.lang.Object, org.aspectj.lang.JoinPoint$StaticPart))
(afterThrowing(extraFlags: 1): ((((within(@org.springframework.transaction.annotation.Transactional *) && execution(public * @org.springframework.transaction.annotation.Transactional *.*(..))) && this(BindingTypePattern(java.lang.Object, 0))) && persingleton(org.springframework.transaction.aspectj.AnnotationTransactionAspect)) || ((execution(@org.springframework.transaction.annotation.Transactional * *(..)) && this(BindingTypePattern(java.lang.Object, 0))) && persingleton(org.springframework.transaction.aspectj.AnnotationTransactionAspect)))->void org.springframework.transaction.aspectj.AbstractTransactionAspect.ajc$afterThrowing$org_springframework_transaction_aspectj_AbstractTransactionAspect$2$2a73e96c(java.lang.Object, java.lang.Throwable))
(afterReturning: ((((within(@org.springframework.transaction.annotation.Transactional *) && execution(public * @org.springframework.transaction.annotation.Transactional *.*(..))) && this(BindingTypePattern(java.lang.Object, 0))) && persingleton(org.springframework.transaction.aspectj.AnnotationTransactionAspect)) || ((execution(@org.springframework.transaction.annotation.Transactional * *(..)) && this(BindingTypePattern(java.lang.Object, 0))) && persingleton(org.springframework.transaction.aspectj.AnnotationTransactionAspect)))->void org.springframework.transaction.aspectj.AbstractTransactionAspect.ajc$afterReturning$org_springframework_transaction_aspectj_AbstractTransactionAspect$3$2a73e96c(java.lang.Object))
(after: ((((within(@org.springframework.transaction.annotation.Transactional *) && execution(public * @org.springframework.transaction.annotation.Transactional *.*(..))) && this(BindingTypePattern(java.lang.Object, 0))) && persingleton(org.springframework.transaction.aspectj.AnnotationTransactionAspect)) || ((execution(@org.springframework.transaction.annotation.Transactional * *(..)) && this(BindingTypePattern(java.lang.Object, 0))) && persingleton(org.springframework.transaction.aspectj.AnnotationTransactionAspect)))->void org.springframework.transaction.aspectj.AbstractTransactionAspect.ajc$after$org_springframework_transaction_aspectj_AbstractTransactionAspect$4$2a73e96c(java.lang.Object))
(before: (((((initialization(org.springframework.beans.factory.aspectj.ConfigurableObject.new(..)) && initialization(org.springframework.beans.factory.aspectj.ConfigurableObject+.new(..))) && this(BindingTypePattern(java.lang.Object, 0))) && @this(org.springframework.beans.factory.annotation.Configurable)) && if(boolean org.springframework.beans.factory.aspectj.AnnotationBeanConfigurerAspect.ajc$if$bb0(org.springframework.beans.factory.annotation.Configurable))) && persingleton(org.springframework.beans.factory.aspectj.AnnotationBeanConfigurerAspect))->void org.springframework.beans.factory.aspectj.AbstractDependencyInjectionAspect.ajc$before$org_springframework_beans_factory_aspectj_AbstractDependencyInjectionAspect$1$e854fa65(java.lang.Object))
(afterReturning: (((((initialization(org.springframework.beans.factory.aspectj.ConfigurableObject+.new(..)) && this(BindingTypePattern(java.lang.Object, 0))) && @this(org.springframework.beans.factory.annotation.Configurable)) && !(@this(org.springframework.beans.factory.annotation.Configurable) && if(boolean org.springframework.beans.factory.aspectj.AnnotationBeanConfigurerAspect.ajc$if$bb0(org.springframework.beans.factory.annotation.Configurable)))) && if(boolean org.springframework.beans.factory.aspectj.AbstractDependencyInjectionAspect.ajc$if$6f1(org.aspectj.lang.JoinPoint))) && persingleton(org.springframework.beans.factory.aspectj.AnnotationBeanConfigurerAspect))->void org.springframework.beans.factory.aspectj.AbstractDependencyInjectionAspect.ajc$afterReturning$org_springframework_beans_factory_aspectj_AbstractDependencyInjectionAspect$2$1ea6722c(java.lang.Object))
(afterReturning: (((execution(java.lang.Object org.springframework.beans.factory.aspectj.AbstractInterfaceDrivenDependencyInjectionAspect$ConfigurableDeserializationSupport+.readResolve()) && this(BindingTypePattern(java.lang.Object, 0))) && @this(org.springframework.beans.factory.annotation.Configurable)) && persingleton(org.springframework.beans.factory.aspectj.AnnotationBeanConfigurerAspect))->void org.springframework.beans.factory.aspectj.AbstractDependencyInjectionAspect.ajc$afterReturning$org_springframework_beans_factory_aspectj_AbstractDependencyInjectionAspect$3$6aa27052(java.lang.Object))
Type mungers:
(BcelTypeMunger ResolvedTypeMunger(Method, java.lang.Object org.springframework.beans.factory.aspectj.AbstractInterfaceDrivenDependencyInjectionAspect$ConfigurableDeserializationSupport.readResolve()))
(BcelTypeMunger ExposeTypeMunger(java.lang.Object))
(BcelTypeMunger ExposeTypeMunger(java.lang.Object))
(BcelTypeMunger ExposeTypeMunger(java.lang.Object))
(BcelTypeMunger ExposeTypeMunger(org.springframework.beans.factory.aspectj.ConfigurableObject))
(BcelTypeMunger ExposeTypeMunger(org.springframework.beans.factory.aspectj.AbstractInterfaceDrivenDependencyInjectionAspect$ConfigurableDeserializationSupport))
Late Type mungers:
Empty
