---- AspectJ Properties ---
AspectJ Compiler 1.6.2 built on Saturday Oct 4, 2008 at 05:47:07 GMT
---- Dump Properties ---
Dump file: ajcore.20160604.114040.157.txt
Dump reason: abort
Dump on exception: true
Dump at exit condition: abort
---- System Properties ---
java.runtime.name=Java(TM) SE Runtime Environment
sun.boot.library.path=C:\Program Files\Java\jdk1.8.0_72\jre\bin
java.vm.version=25.72-b15
java.vm.vendor=Oracle Corporation
java.vendor.url=http://java.oracle.com/
path.separator=;
java.vm.name=Java HotSpot(TM) 64-Bit Server VM
file.encoding.pkg=sun.io
user.country=ES
user.script=
sun.java.launcher=SUN_STANDARD
sun.os.patch.level=
java.vm.specification.name=Java Virtual Machine Specification
user.dir=C:\Users\usuario\git\spring\aspectos\Ejemplos Relacionados\SpringIoC0007Maven
java.runtime.version=1.8.0_72-b15
java.awt.graphicsenv=sun.awt.Win32GraphicsEnvironment
java.endorsed.dirs=C:\Program Files\Java\jdk1.8.0_72\jre\lib\endorsed
os.arch=amd64
java.io.tmpdir=C:\Users\usuario\AppData\Local\Temp\
line.separator=

java.vm.specification.vendor=Oracle Corporation
user.variant=
os.name=Windows 10
sun.jnu.encoding=Cp1252
java.library.path=C:\Program Files\Java\jdk1.8.0_72\bin;C:\WINDOWS\Sun\Java\bin;C:\WINDOWS\system32;C:\WINDOWS;C:\ProgramData\Oracle\Java\javapath;C:\Program Files\CollabNet\Subversion Client;E:\bin\Sencha\Cmd\5.1.3.61;C:\Users\usuario\bin\Sencha\Cmd\5.1.3.61;C:\Program Files (x86)\Intel\iCLS Client\;C:\Program Files\Intel\iCLS Client\;C:\WINDOWS\system32;C:\WINDOWS;C:\WINDOWS\System32\Wbem;C:\WINDOWS\System32\WindowsPowerShell\v1.0\;C:\Program Files\Intel\Intel(R) Management Engine Components\DAL;C:\Program Files\Intel\Intel(R) Management Engine Components\IPT;C:\Program Files (x86)\Intel\Intel(R) Management Engine Components\DAL;C:\Program Files (x86)\Intel\Intel(R) Management Engine Components\IPT;C:\Program Files (x86)\Intel\OpenCL SDK\3.0\bin\x86;C:\Program Files (x86)\Intel\OpenCL SDK\3.0\bin\x64;C:\Program Files (x86)\sbt\\bin;C:\Program Files (x86)\Heroku\bin;C:\Program Files (x86)\git\cmd;C:\Program Files (x86)\QuickTime\QTSystem\;C:\HashiCorp\Vagrant\bin;C:\Program Files (x86)\scala\bin;C:\Program Files\nodejs\;C:\Users\usuario\AppData\Local\.meteor\;C:\Users\usuario\AppData\Roaming\npm;.
java.specification.name=Java Platform API Specification
java.class.version=52.0
sun.management.compiler=HotSpot 64-Bit Tiered Compilers
os.version=10.0
user.home=C:\Users\usuario
user.timezone=Europe/Paris
java.awt.printerjob=sun.awt.windows.WPrinterJob
file.encoding=Cp1252
java.specification.version=1.8
java.class.path=C:\Users\usuario\git\spring\aspectos\Ejemplos Relacionados\SpringIoC0007Maven\target\classes;C:\Users\usuario\.m2\repository\org\springframework\spring-context\3.1.2.RELEASE\spring-context-3.1.2.RELEASE.jar;C:\Users\usuario\.m2\repository\org\springframework\spring-aop\3.1.2.RELEASE\spring-aop-3.1.2.RELEASE.jar;C:\Users\usuario\.m2\repository\aopalliance\aopalliance\1.0\aopalliance-1.0.jar;C:\Users\usuario\.m2\repository\org\springframework\spring-beans\3.1.2.RELEASE\spring-beans-3.1.2.RELEASE.jar;C:\Users\usuario\.m2\repository\org\springframework\spring-core\3.1.2.RELEASE\spring-core-3.1.2.RELEASE.jar;C:\Users\usuario\.m2\repository\commons-logging\commons-logging\1.1.1\commons-logging-1.1.1.jar;C:\Users\usuario\.m2\repository\org\springframework\spring-expression\3.1.2.RELEASE\spring-expression-3.1.2.RELEASE.jar;C:\Users\usuario\.m2\repository\org\springframework\spring-asm\3.1.2.RELEASE\spring-asm-3.1.2.RELEASE.jar;C:\Users\usuario\.m2\repository\org\springframework\spring-aspects\3.1.2.RELEASE\spring-aspects-3.1.2.RELEASE.jar;C:\Users\usuario\.m2\repository\org\springframework\spring-context-support\3.1.2.RELEASE\spring-context-support-3.1.2.RELEASE.jar;.\..\aspectjweaver.jar
user.name=usuario
java.vm.specification.version=1.8
sun.java.command=com.curso.spring.springioc0007.Main
java.home=C:\Program Files\Java\jdk1.8.0_72\jre
sun.arch.data.model=64
user.language=es
java.specification.vendor=Oracle Corporation
awt.toolkit=sun.awt.windows.WToolkit
java.vm.info=mixed mode
java.version=1.8.0_72
java.ext.dirs=C:\Program Files\Java\jdk1.8.0_72\jre\lib\ext;C:\WINDOWS\Sun\Java\lib\ext
sun.boot.class.path=C:\Program Files\Java\jdk1.8.0_72\jre\lib\resources.jar;C:\Program Files\Java\jdk1.8.0_72\jre\lib\rt.jar;C:\Program Files\Java\jdk1.8.0_72\jre\lib\sunrsasign.jar;C:\Program Files\Java\jdk1.8.0_72\jre\lib\jsse.jar;C:\Program Files\Java\jdk1.8.0_72\jre\lib\jce.jar;C:\Program Files\Java\jdk1.8.0_72\jre\lib\charsets.jar;C:\Program Files\Java\jdk1.8.0_72\jre\lib\jfr.jar;C:\Program Files\Java\jdk1.8.0_72\jre\classes
java.vendor=Oracle Corporation
file.separator=\
java.vendor.url.bug=http://bugreport.sun.com/bugreport/
sun.io.unicode.encoding=UnicodeLittle
sun.cpu.endian=little
sun.desktop=windows
sun.cpu.isalist=amd64
---- Command Line ---
Empty
---- Full Classpath ---
Empty
---- Compiler Messages ---
info AspectJ Weaver Version 1.6.2 built on Saturday Oct 4, 2008 at 05:47:07 GMT
info register classloader sun.misc.Launcher$AppClassLoader@18b4aac2
info using configuration file:/C:/Users/usuario/.m2/repository/org/springframework/spring-aspects/3.1.2.RELEASE/spring-aspects-3.1.2.RELEASE.jar!/META-INF/aop.xml
debug weaving 'org.springframework.beans.BeanUtils'
abort trouble in: 
public abstract class org.springframework.beans.BeanUtils extends java.lang.Object:
  private static final org.apache.commons.logging.Log logger
  private static final java.util.Map unknownEditorTypes [Signature(Ljava/util/Map<Ljava/lang/Class<*>;Ljava/lang/Boolean;>;)]
  static void <clinit>():
    staticinitialization(void org.springframework.beans.BeanUtils.<clinit>())
    |               LDC org.springframework.beans.BeanUtils   (line 58)
    |               INVOKESTATIC org.apache.commons.logging.LogFactory.getLog (Ljava/lang/Class;)Lorg/apache/commons/logging/Log;
    |               PUTSTATIC org.springframework.beans.BeanUtils.logger Lorg/apache/commons/logging/Log;
    |               NEW java.util.WeakHashMap   (line 61)
    |               DUP
    |               INVOKESPECIAL java.util.WeakHashMap.<init> ()V
    |               INVOKESTATIC java.util.Collections.synchronizedMap (Ljava/util/Map;)Ljava/util/Map;
    |               PUTSTATIC org.springframework.beans.BeanUtils.unknownEditorTypes Ljava/util/Map;   (line 60)
    |               RETURN   (line 56)
    staticinitialization(void org.springframework.beans.BeanUtils.<clinit>())
  end static void <clinit>()

  public void <init>():
                    ALOAD_0     // Lorg/springframework/beans/BeanUtils; this   (line 56)
                    INVOKESPECIAL java.lang.Object.<init> ()V
    constructor-execution(void org.springframework.beans.BeanUtils.<init>())
    |               RETURN
    constructor-execution(void org.springframework.beans.BeanUtils.<init>())
  end public void <init>()

  public static Object instantiate(Class) throws org.springframework.beans.BeanInstantiationException:
                    ALOAD_0     // Ljava/lang/Class; clazz   (line 73)
                    LDC "Class must not be null"
                    INVOKESTATIC org.springframework.util.Assert.notNull (Ljava/lang/Object;Ljava/lang/String;)V
                    ALOAD_0     // Ljava/lang/Class; clazz   (line 74)
                    INVOKEVIRTUAL java.lang.Class.isInterface ()Z
                    IFEQ L0
                    NEW org.springframework.beans.BeanInstantiationException   (line 75)
                    DUP
                    ALOAD_0     // Ljava/lang/Class; clazz
                    LDC "Specified class is an interface"
                    INVOKESPECIAL org.springframework.beans.BeanInstantiationException.<init> (Ljava/lang/Class;Ljava/lang/String;)V
                    ATHROW
    catch java.lang.IllegalAccessException -> E1
    | catch java.lang.InstantiationException -> E0
    | |         L0: ALOAD_0     // Ljava/lang/Class; clazz   (line 78)
    | |             INVOKEVIRTUAL java.lang.Class.newInstance ()Ljava/lang/Object;
    | catch java.lang.InstantiationException -> E0
    catch java.lang.IllegalAccessException -> E1
                    ARETURN
                E0: ASTORE_1   (line 80)
                    NEW org.springframework.beans.BeanInstantiationException   (line 81)
                    DUP
                    ALOAD_0     // Ljava/lang/Class; clazz
                    LDC "Is it an abstract class?"
                    ALOAD_1     // Ljava/lang/InstantiationException; ex
                    INVOKESPECIAL org.springframework.beans.BeanInstantiationException.<init> (Ljava/lang/Class;Ljava/lang/String;Ljava/lang/Throwable;)V
                    ATHROW
                E1: ASTORE_1   (line 83)
                    NEW org.springframework.beans.BeanInstantiationException   (line 84)
                    DUP
                    ALOAD_0     // Ljava/lang/Class; clazz
                    LDC "Is the constructor accessible?"
                    ALOAD_1     // Ljava/lang/IllegalAccessException; ex
                    INVOKESPECIAL org.springframework.beans.BeanInstantiationException.<init> (Ljava/lang/Class;Ljava/lang/String;Ljava/lang/Throwable;)V
                    ATHROW
  end public static Object instantiate(Class) throws org.springframework.beans.BeanInstantiationException

  public static Object instantiateClass(Class) throws org.springframework.beans.BeanInstantiationException:
                    ALOAD_0     // Ljava/lang/Class; clazz   (line 99)
                    LDC "Class must not be null"
                    INVOKESTATIC org.springframework.util.Assert.notNull (Ljava/lang/Object;Ljava/lang/String;)V
                    ALOAD_0     // Ljava/lang/Class; clazz   (line 100)
                    INVOKEVIRTUAL java.lang.Class.isInterface ()Z
                    IFEQ L0
                    NEW org.springframework.beans.BeanInstantiationException   (line 101)
                    DUP
                    ALOAD_0     // Ljava/lang/Class; clazz
                    LDC "Specified class is an interface"
                    INVOKESPECIAL org.springframework.beans.BeanInstantiationException.<init> (Ljava/lang/Class;Ljava/lang/String;)V
                    ATHROW
    catch java.lang.NoSuchMethodException -> E0
    |           L0: ALOAD_0     // Ljava/lang/Class; clazz   (line 104)
    |               ICONST_0
    |               ANEWARRAY java.lang.Class
    |               INVOKEVIRTUAL java.lang.Class.getDeclaredConstructor ([Ljava/lang/Class;)Ljava/lang/reflect/Constructor;
    |               ICONST_0
    |               ANEWARRAY java.lang.Object
    |               INVOKESTATIC org.springframework.beans.BeanUtils.instantiateClass (Ljava/lang/reflect/Constructor;[Ljava/lang/Object;)Ljava/lang/Object;
    catch java.lang.NoSuchMethodException -> E0
                    ARETURN
                E0: ASTORE_1   (line 106)
                    NEW org.springframework.beans.BeanInstantiationException   (line 107)
                    DUP
                    ALOAD_0     // Ljava/lang/Class; clazz
                    LDC "No default constructor found"
                    ALOAD_1     // Ljava/lang/NoSuchMethodException; ex
                    INVOKESPECIAL org.springframework.beans.BeanInstantiationException.<init> (Ljava/lang/Class;Ljava/lang/String;Ljava/lang/Throwable;)V
                    ATHROW
  end public static Object instantiateClass(Class) throws org.springframework.beans.BeanInstantiationException

  public static Object instantiateClass(Class, Class) throws org.springframework.beans.BeanInstantiationException:
                    ALOAD_1     // Ljava/lang/Class; assignableTo   (line 128)
                    ALOAD_0     // Ljava/lang/Class; clazz
                    INVOKESTATIC org.springframework.util.Assert.isAssignable (Ljava/lang/Class;Ljava/lang/Class;)V
                    ALOAD_0     // Ljava/lang/Class; clazz   (line 129)
                    INVOKESTATIC org.springframework.beans.BeanUtils.instantiateClass (Ljava/lang/Class;)Ljava/lang/Object;
                    ARETURN
  end public static Object instantiateClass(Class, Class) throws org.springframework.beans.BeanInstantiationException

  public static transient Object instantiateClass(java.lang.reflect.Constructor, Object[]) throws org.springframework.beans.BeanInstantiationException:
                    ALOAD_0     // Ljava/lang/reflect/Constructor; ctor   (line 144)
                    LDC "Constructor must not be null"
                    INVOKESTATIC org.springframework.util.Assert.notNull (Ljava/lang/Object;Ljava/lang/String;)V
    catch java.lang.reflect.InvocationTargetException -> E3
    | catch java.lang.IllegalArgumentException -> E2
    | | catch java.lang.IllegalAccessException -> E1
    | | | catch java.lang.InstantiationException -> E0
    | | | |         ALOAD_0     // Ljava/lang/reflect/Constructor; ctor   (line 146)
    | | | |         INVOKESTATIC org.springframework.util.ReflectionUtils.makeAccessible (Ljava/lang/reflect/Constructor;)V
    | | | |         ALOAD_0     // Ljava/lang/reflect/Constructor; ctor   (line 147)
    | | | |         ALOAD_1     // [Ljava/lang/Object; args
    | | | |         INVOKEVIRTUAL java.lang.reflect.Constructor.newInstance ([Ljava/lang/Object;)Ljava/lang/Object;
    | | | catch java.lang.InstantiationException -> E0
    | | catch java.lang.IllegalAccessException -> E1
    | catch java.lang.IllegalArgumentException -> E2
    catch java.lang.reflect.InvocationTargetException -> E3
                    ARETURN
                E0: ASTORE_2   (line 149)
                    NEW org.springframework.beans.BeanInstantiationException   (line 150)
                    DUP
                    ALOAD_0     // Ljava/lang/reflect/Constructor; ctor
                    INVOKEVIRTUAL java.lang.reflect.Constructor.getDeclaringClass ()Ljava/lang/Class;
                    LDC "Is it an abstract class?"   (line 151)
                    ALOAD_2     // Ljava/lang/InstantiationException; ex
                    INVOKESPECIAL org.springframework.beans.BeanInstantiationException.<init> (Ljava/lang/Class;Ljava/lang/String;Ljava/lang/Throwable;)V   (line 150)
                    ATHROW
                E1: ASTORE_2   (line 153)
                    NEW org.springframework.beans.BeanInstantiationException   (line 154)
                    DUP
                    ALOAD_0     // Ljava/lang/reflect/Constructor; ctor
                    INVOKEVIRTUAL java.lang.reflect.Constructor.getDeclaringClass ()Ljava/lang/Class;
                    LDC "Is the constructor accessible?"   (line 155)
                    ALOAD_2     // Ljava/lang/IllegalAccessException; ex
                    INVOKESPECIAL org.springframework.beans.BeanInstantiationException.<init> (Ljava/lang/Class;Ljava/lang/String;Ljava/lang/Throwable;)V   (line 154)
                    ATHROW
                E2: ASTORE_2   (line 157)
                    NEW org.springframework.beans.BeanInstantiationException   (line 158)
                    DUP
                    ALOAD_0     // Ljava/lang/reflect/Constructor; ctor
                    INVOKEVIRTUAL java.lang.reflect.Constructor.getDeclaringClass ()Ljava/lang/Class;
                    LDC "Illegal arguments for constructor"   (line 159)
                    ALOAD_2     // Ljava/lang/IllegalArgumentException; ex
                    INVOKESPECIAL org.springframework.beans.BeanInstantiationException.<init> (Ljava/lang/Class;Ljava/lang/String;Ljava/lang/Throwable;)V   (line 158)
                    ATHROW
                E3: ASTORE_2   (line 161)
                    NEW org.springframework.beans.BeanInstantiationException   (line 162)
                    DUP
                    ALOAD_0     // Ljava/lang/reflect/Constructor; ctor
                    INVOKEVIRTUAL java.lang.reflect.Constructor.getDeclaringClass ()Ljava/lang/Class;
                    LDC "Constructor threw exception"   (line 163)
                    ALOAD_2     // Ljava/lang/reflect/InvocationTargetException; ex
                    INVOKEVIRTUAL java.lang.reflect.InvocationTargetException.getTargetException ()Ljava/lang/Throwable;
                    INVOKESPECIAL org.springframework.beans.BeanInstantiationException.<init> (Ljava/lang/Class;Ljava/lang/String;Ljava/lang/Throwable;)V   (line 162)
                    ATHROW
  end public static transient Object instantiateClass(java.lang.reflect.Constructor, Object[]) throws org.springframework.beans.BeanInstantiationException

  public static transient java.lang.reflect.Method findMethod(Class, String, Class[]):
    catch java.lang.NoSuchMethodException -> E0
    |               ALOAD_0     // Ljava/lang/Class; clazz   (line 183)
    |               ALOAD_1     // Ljava/lang/String; methodName
    |               ALOAD_2     // [Ljava/lang/Class; paramTypes
    |               INVOKEVIRTUAL java.lang.Class.getMethod (Ljava/lang/String;[Ljava/lang/Class;)Ljava/lang/reflect/Method;
    catch java.lang.NoSuchMethodException -> E0
                    ARETURN
                E0: POP   (line 185)
                    ALOAD_0     // Ljava/lang/Class; clazz   (line 186)
                    ALOAD_1     // Ljava/lang/String; methodName
                    ALOAD_2     // [Ljava/lang/Class; paramTypes
                    INVOKESTATIC org.springframework.beans.BeanUtils.findDeclaredMethod (Ljava/lang/Class;Ljava/lang/String;[Ljava/lang/Class;)Ljava/lang/reflect/Method;
                    ARETURN
  end public static transient java.lang.reflect.Method findMethod(Class, String, Class[])

  public static java.lang.reflect.Method findDeclaredMethod(Class, String, Class[]):
    catch java.lang.NoSuchMethodException -> E0
    |               ALOAD_0     // Ljava/lang/Class; clazz   (line 203)
    |               ALOAD_1     // Ljava/lang/String; methodName
    |               ALOAD_2     // [Ljava/lang/Class; paramTypes
    |               INVOKEVIRTUAL java.lang.Class.getDeclaredMethod (Ljava/lang/String;[Ljava/lang/Class;)Ljava/lang/reflect/Method;
    catch java.lang.NoSuchMethodException -> E0
                    ARETURN
                E0: POP   (line 205)
                    ALOAD_0     // Ljava/lang/Class; clazz   (line 206)
                    INVOKEVIRTUAL java.lang.Class.getSuperclass ()Ljava/lang/Class;
                    IFNULL L0
                    ALOAD_0     // Ljava/lang/Class; clazz   (line 207)
                    INVOKEVIRTUAL java.lang.Class.getSuperclass ()Ljava/lang/Class;
                    ALOAD_1     // Ljava/lang/String; methodName
                    ALOAD_2     // [Ljava/lang/Class; paramTypes
                    INVOKESTATIC org.springframework.beans.BeanUtils.findDeclaredMethod (Ljava/lang/Class;Ljava/lang/String;[Ljava/lang/Class;)Ljava/lang/reflect/Method;
                    ARETURN
                L0: ACONST_NULL   (line 209)
                    ARETURN
  end public static java.lang.reflect.Method findDeclaredMethod(Class, String, Class[])

  public static java.lang.reflect.Method findMethodWithMinimalParameters(Class, String) throws java.lang.IllegalArgumentException:
                    ALOAD_0     // Ljava/lang/Class; clazz   (line 231)
                    INVOKEVIRTUAL java.lang.Class.getMethods ()[Ljava/lang/reflect/Method;
                    ALOAD_1     // Ljava/lang/String; methodName
                    INVOKESTATIC org.springframework.beans.BeanUtils.findMethodWithMinimalParameters ([Ljava/lang/reflect/Method;Ljava/lang/String;)Ljava/lang/reflect/Method;
                    ASTORE_2
                    ALOAD_2     // Ljava/lang/reflect/Method; targetMethod   (line 232)
                    IFNONNULL L0
                    ALOAD_0     // Ljava/lang/Class; clazz   (line 233)
                    ALOAD_1     // Ljava/lang/String; methodName
                    INVOKESTATIC org.springframework.beans.BeanUtils.findDeclaredMethodWithMinimalParameters (Ljava/lang/Class;Ljava/lang/String;)Ljava/lang/reflect/Method;
                    ASTORE_2     // Ljava/lang/reflect/Method; targetMethod
                L0: ALOAD_2     // Ljava/lang/reflect/Method; targetMethod   (line 235)
                    ARETURN
  end public static java.lang.reflect.Method findMethodWithMinimalParameters(Class, String) throws java.lang.IllegalArgumentException

  public static java.lang.reflect.Method findDeclaredMethodWithMinimalParameters(Class, String) throws java.lang.IllegalArgumentException:
                    ALOAD_0     // Ljava/lang/Class; clazz   (line 253)
                    INVOKEVIRTUAL java.lang.Class.getDeclaredMethods ()[Ljava/lang/reflect/Method;
                    ALOAD_1     // Ljava/lang/String; methodName
                    INVOKESTATIC org.springframework.beans.BeanUtils.findMethodWithMinimalParameters ([Ljava/lang/reflect/Method;Ljava/lang/String;)Ljava/lang/reflect/Method;
                    ASTORE_2
                    ALOAD_2     // Ljava/lang/reflect/Method; targetMethod   (line 254)
                    IFNONNULL L0
                    ALOAD_0     // Ljava/lang/Class; clazz
                    INVOKEVIRTUAL java.lang.Class.getSuperclass ()Ljava/lang/Class;
                    IFNULL L0
                    ALOAD_0     // Ljava/lang/Class; clazz   (line 255)
                    INVOKEVIRTUAL java.lang.Class.getSuperclass ()Ljava/lang/Class;
                    ALOAD_1     // Ljava/lang/String; methodName
                    INVOKESTATIC org.springframework.beans.BeanUtils.findDeclaredMethodWithMinimalParameters (Ljava/lang/Class;Ljava/lang/String;)Ljava/lang/reflect/Method;
                    ASTORE_2     // Ljava/lang/reflect/Method; targetMethod
                L0: ALOAD_2     // Ljava/lang/reflect/Method; targetMethod   (line 257)
                    ARETURN
  end public static java.lang.reflect.Method findDeclaredMethodWithMinimalParameters(Class, String) throws java.lang.IllegalArgumentException

  public static java.lang.reflect.Method findMethodWithMinimalParameters(java.lang.reflect.Method[], String) throws java.lang.IllegalArgumentException:
                    ACONST_NULL   (line 272)
                    ASTORE_2
                    ICONST_0   (line 273)
                    ISTORE_3
                    ALOAD_0     // [Ljava/lang/reflect/Method; methods   (line 274)
                    DUP
                    ASTORE 7
                    ARRAYLENGTH
                    ISTORE 6
                    ICONST_0
                    ISTORE 5
                    GOTO L4
                L0: ALOAD 7
                    ILOAD 5
                    AALOAD
                    ASTORE 4
                    ALOAD 4     // Ljava/lang/reflect/Method; method   (line 275)
                    INVOKEVIRTUAL java.lang.reflect.Method.getName ()Ljava/lang/String;
                    ALOAD_1     // Ljava/lang/String; methodName
                    INVOKEVIRTUAL java.lang.String.equals (Ljava/lang/Object;)Z
                    IFEQ L3
                    ALOAD 4     // Ljava/lang/reflect/Method; method   (line 276)
                    INVOKEVIRTUAL java.lang.reflect.Method.getParameterTypes ()[Ljava/lang/Class;
                    ARRAYLENGTH
                    ISTORE 8
                    ALOAD_2     // Ljava/lang/reflect/Method; targetMethod   (line 277)
                    IFNULL L1
                    ILOAD 8     // I numParams
                    ALOAD_2     // Ljava/lang/reflect/Method; targetMethod
                    INVOKEVIRTUAL java.lang.reflect.Method.getParameterTypes ()[Ljava/lang/Class;
                    ARRAYLENGTH
                    IF_ICMPGE L2
                L1: ALOAD 4     // Ljava/lang/reflect/Method; method   (line 278)
                    ASTORE_2     // Ljava/lang/reflect/Method; targetMethod
                    ICONST_1   (line 279)
                    ISTORE_3     // I numMethodsFoundWithCurrentMinimumArgs
                    GOTO L3
                L2: ALOAD_2     // Ljava/lang/reflect/Method; targetMethod   (line 282)
                    INVOKEVIRTUAL java.lang.reflect.Method.getParameterTypes ()[Ljava/lang/Class;
                    ARRAYLENGTH
                    ILOAD 8     // I numParams
                    IF_ICMPNE L3
                    IINC_3 1     // I numMethodsFoundWithCurrentMinimumArgs   (line 284)
                L3: IINC 5 1   (line 274)
                L4: ILOAD 5
                    ILOAD 6
                    IF_ICMPLT L0
                    ILOAD_3     // I numMethodsFoundWithCurrentMinimumArgs   (line 289)
                    ICONST_1
                    IF_ICMPLE L5
                    NEW java.lang.IllegalArgumentException   (line 290)
                    DUP
                    NEW java.lang.StringBuilder
                    DUP
                    LDC "Cannot resolve method '"
                    INVOKESPECIAL java.lang.StringBuilder.<init> (Ljava/lang/String;)V
                    ALOAD_1     // Ljava/lang/String; methodName
                    INVOKEVIRTUAL java.lang.StringBuilder.append (Ljava/lang/String;)Ljava/lang/StringBuilder;
                    LDC "' to a unique method. Attempted to resolve to overloaded method with "   (line 291)
                    INVOKEVIRTUAL java.lang.StringBuilder.append (Ljava/lang/String;)Ljava/lang/StringBuilder;
                    LDC "the least number of parameters, but there were "   (line 292)
                    INVOKEVIRTUAL java.lang.StringBuilder.append (Ljava/lang/String;)Ljava/lang/StringBuilder;
                    ILOAD_3     // I numMethodsFoundWithCurrentMinimumArgs   (line 293)
                    INVOKEVIRTUAL java.lang.StringBuilder.append (I)Ljava/lang/StringBuilder;
                    LDC " candidates."
                    INVOKEVIRTUAL java.lang.StringBuilder.append (Ljava/lang/String;)Ljava/lang/StringBuilder;
                    INVOKEVIRTUAL java.lang.StringBuilder.toString ()Ljava/lang/String;
                    INVOKESPECIAL java.lang.IllegalArgumentException.<init> (Ljava/lang/String;)V   (line 290)
                    ATHROW
                L5: ALOAD_2     // Ljava/lang/reflect/Method; targetMethod   (line 295)
                    ARETURN
  end public static java.lang.reflect.Method findMethodWithMinimalParameters(java.lang.reflect.Method[], String) throws java.lang.IllegalArgumentException

  public static java.lang.reflect.Method resolveSignature(String, Class):
                    ALOAD_0     // Ljava/lang/String; signature   (line 317)
                    LDC "'signature' must not be empty"
                    INVOKESTATIC org.springframework.util.Assert.hasText (Ljava/lang/String;Ljava/lang/String;)V
                    ALOAD_1     // Ljava/lang/Class; clazz   (line 318)
                    LDC "Class must not be null"
                    INVOKESTATIC org.springframework.util.Assert.notNull (Ljava/lang/Object;Ljava/lang/String;)V
                    ALOAD_0     // Ljava/lang/String; signature   (line 320)
                    LDC "("
                    INVOKEVIRTUAL java.lang.String.indexOf (Ljava/lang/String;)I
                    ISTORE_2
                    ALOAD_0     // Ljava/lang/String; signature   (line 321)
                    LDC ")"
                    INVOKEVIRTUAL java.lang.String.indexOf (Ljava/lang/String;)I
                    ISTORE_3
                    ILOAD_2     // I firstParen   (line 323)
                    ICONST_M1
                    IF_ICMPLE L0
                    ILOAD_3     // I lastParen
                    ICONST_M1
                    IF_ICMPNE L0
                    NEW java.lang.IllegalArgumentException   (line 324)
                    DUP
                    NEW java.lang.StringBuilder
                    DUP
                    LDC "Invalid method signature '"
                    INVOKESPECIAL java.lang.StringBuilder.<init> (Ljava/lang/String;)V
                    ALOAD_0     // Ljava/lang/String; signature
                    INVOKEVIRTUAL java.lang.StringBuilder.append (Ljava/lang/String;)Ljava/lang/StringBuilder;
                    LDC "': expected closing ')' for args list"   (line 325)
                    INVOKEVIRTUAL java.lang.StringBuilder.append (Ljava/lang/String;)Ljava/lang/StringBuilder;
                    INVOKEVIRTUAL java.lang.StringBuilder.toString ()Ljava/lang/String;
                    INVOKESPECIAL java.lang.IllegalArgumentException.<init> (Ljava/lang/String;)V   (line 324)
                    ATHROW
                L0: ILOAD_3     // I lastParen   (line 327)
                    ICONST_M1
                    IF_ICMPLE L1
                    ILOAD_2     // I firstParen
                    ICONST_M1
                    IF_ICMPNE L1
                    NEW java.lang.IllegalArgumentException   (line 328)
                    DUP
                    NEW java.lang.StringBuilder
                    DUP
                    LDC "Invalid method signature '"
                    INVOKESPECIAL java.lang.StringBuilder.<init> (Ljava/lang/String;)V
                    ALOAD_0     // Ljava/lang/String; signature
                    INVOKEVIRTUAL java.lang.StringBuilder.append (Ljava/lang/String;)Ljava/lang/StringBuilder;
                    LDC "': expected opening '(' for args list"   (line 329)
                    INVOKEVIRTUAL java.lang.StringBuilder.append (Ljava/lang/String;)Ljava/lang/StringBuilder;
                    INVOKEVIRTUAL java.lang.StringBuilder.toString ()Ljava/lang/String;
                    INVOKESPECIAL java.lang.IllegalArgumentException.<init> (Ljava/lang/String;)V   (line 328)
                    ATHROW
                L1: ILOAD_2     // I firstParen   (line 331)
                    ICONST_M1
                    IF_ICMPNE L2
                    ILOAD_3     // I lastParen
                    ICONST_M1
                    IF_ICMPNE L2
                    ALOAD_1     // Ljava/lang/Class; clazz   (line 332)
                    ALOAD_0     // Ljava/lang/String; signature
                    INVOKESTATIC org.springframework.beans.BeanUtils.findMethodWithMinimalParameters (Ljava/lang/Class;Ljava/lang/String;)Ljava/lang/reflect/Method;
                    ARETURN
                L2: ALOAD_0     // Ljava/lang/String; signature   (line 335)
                    ICONST_0
                    ILOAD_2     // I firstParen
                    INVOKEVIRTUAL java.lang.String.substring (II)Ljava/lang/String;
                    ASTORE 4
                    ALOAD_0     // Ljava/lang/String; signature   (line 337)
                    ILOAD_2     // I firstParen
                    ICONST_1
                    IADD
                    ILOAD_3     // I lastParen
                    INVOKEVIRTUAL java.lang.String.substring (II)Ljava/lang/String;
                    INVOKESTATIC org.springframework.util.StringUtils.commaDelimitedListToStringArray (Ljava/lang/String;)[Ljava/lang/String;
                    ASTORE 5   (line 336)
                    ALOAD 5     // [Ljava/lang/String; parameterTypeNames   (line 338)
                    ARRAYLENGTH
                    ANEWARRAY java.lang.Class
                    ASTORE 6
                    ICONST_0   (line 339)
                    ISTORE 7
                    GOTO L5
                L3: ALOAD 5     // [Ljava/lang/String; parameterTypeNames   (line 340)
                    ILOAD 7     // I i
                    AALOAD
                    INVOKEVIRTUAL java.lang.String.trim ()Ljava/lang/String;
                    ASTORE 8
    catch java.lang.Throwable -> E0
    |               ALOAD 6     // [Ljava/lang/Class; parameterTypes   (line 342)
    |               ILOAD 7     // I i
    |               ALOAD 8     // Ljava/lang/String; parameterTypeName
    |               ALOAD_1     // Ljava/lang/Class; clazz
    |               INVOKEVIRTUAL java.lang.Class.getClassLoader ()Ljava/lang/ClassLoader;
    |               INVOKESTATIC org.springframework.util.ClassUtils.forName (Ljava/lang/String;Ljava/lang/ClassLoader;)Ljava/lang/Class;
    |               AASTORE
    catch java.lang.Throwable -> E0
                    GOTO L4
                E0: ASTORE 9   (line 344)
                    NEW java.lang.IllegalArgumentException   (line 345)
                    DUP
                    NEW java.lang.StringBuilder
                    DUP
                    LDC_W "Invalid method signature: unable to resolve type ["
                    INVOKESPECIAL java.lang.StringBuilder.<init> (Ljava/lang/String;)V
                    ALOAD 8     // Ljava/lang/String; parameterTypeName   (line 346)
                    INVOKEVIRTUAL java.lang.StringBuilder.append (Ljava/lang/String;)Ljava/lang/StringBuilder;
                    LDC_W "] for argument "
                    INVOKEVIRTUAL java.lang.StringBuilder.append (Ljava/lang/String;)Ljava/lang/StringBuilder;
                    ILOAD 7     // I i
                    INVOKEVIRTUAL java.lang.StringBuilder.append (I)Ljava/lang/StringBuilder;
                    LDC_W ". Root cause: "
                    INVOKEVIRTUAL java.lang.StringBuilder.append (Ljava/lang/String;)Ljava/lang/StringBuilder;
                    ALOAD 9     // Ljava/lang/Throwable; ex
                    INVOKEVIRTUAL java.lang.StringBuilder.append (Ljava/lang/Object;)Ljava/lang/StringBuilder;
                    INVOKEVIRTUAL java.lang.StringBuilder.toString ()Ljava/lang/String;
                    INVOKESPECIAL java.lang.IllegalArgumentException.<init> (Ljava/lang/String;)V   (line 345)
                    ATHROW
                L4: IINC 7 1     // I i   (line 339)
                L5: ILOAD 7     // I i
                    ALOAD 5     // [Ljava/lang/String; parameterTypeNames
                    ARRAYLENGTH
                    IF_ICMPLT L3
                    ALOAD_1     // Ljava/lang/Class; clazz   (line 349)
                    ALOAD 4     // Ljava/lang/String; methodName
                    ALOAD 6     // [Ljava/lang/Class; parameterTypes
                    INVOKESTATIC org.springframework.beans.BeanUtils.findMethod (Ljava/lang/Class;Ljava/lang/String;[Ljava/lang/Class;)Ljava/lang/reflect/Method;
                    ARETURN
  end public static java.lang.reflect.Method resolveSignature(String, Class)

  public static java.beans.PropertyDescriptor[] getPropertyDescriptors(Class) throws org.springframework.beans.BeansException:
                    ALOAD_0     // Ljava/lang/Class; clazz   (line 361)
                    INVOKESTATIC org.springframework.beans.CachedIntrospectionResults.forClass (Ljava/lang/Class;)Lorg/springframework/beans/CachedIntrospectionResults;
                    ASTORE_1
                    ALOAD_1     // Lorg/springframework/beans/CachedIntrospectionResults; cr   (line 362)
                    INVOKEVIRTUAL org.springframework.beans.CachedIntrospectionResults.getPropertyDescriptors ()[Ljava/beans/PropertyDescriptor;
                    ARETURN
  end public static java.beans.PropertyDescriptor[] getPropertyDescriptors(Class) throws org.springframework.beans.BeansException

  public static java.beans.PropertyDescriptor getPropertyDescriptor(Class, String) throws org.springframework.beans.BeansException:
                    ALOAD_0     // Ljava/lang/Class; clazz   (line 375)
                    INVOKESTATIC org.springframework.beans.CachedIntrospectionResults.forClass (Ljava/lang/Class;)Lorg/springframework/beans/CachedIntrospectionResults;
                    ASTORE_2
                    ALOAD_2     // Lorg/springframework/beans/CachedIntrospectionResults; cr   (line 376)
                    ALOAD_1     // Ljava/lang/String; propertyName
                    INVOKEVIRTUAL org.springframework.beans.CachedIntrospectionResults.getPropertyDescriptor (Ljava/lang/String;)Ljava/beans/PropertyDescriptor;
                    ARETURN
  end public static java.beans.PropertyDescriptor getPropertyDescriptor(Class, String) throws org.springframework.beans.BeansException

  public static java.beans.PropertyDescriptor findPropertyForMethod(java.lang.reflect.Method) throws org.springframework.beans.BeansException:
                    ALOAD_0     // Ljava/lang/reflect/Method; method   (line 388)
                    LDC_W "Method must not be null"
                    INVOKESTATIC org.springframework.util.Assert.notNull (Ljava/lang/Object;Ljava/lang/String;)V
                    ALOAD_0     // Ljava/lang/reflect/Method; method   (line 389)
                    INVOKEVIRTUAL java.lang.reflect.Method.getDeclaringClass ()Ljava/lang/Class;
                    INVOKESTATIC org.springframework.beans.BeanUtils.getPropertyDescriptors (Ljava/lang/Class;)[Ljava/beans/PropertyDescriptor;
                    ASTORE_1
                    ALOAD_1     // [Ljava/beans/PropertyDescriptor; pds   (line 390)
                    DUP
                    ASTORE 5
                    ARRAYLENGTH
                    ISTORE 4
                    ICONST_0
                    ISTORE_3
                    GOTO L3
                L0: ALOAD 5
                    ILOAD_3
                    AALOAD
                    ASTORE_2
                    ALOAD_0     // Ljava/lang/reflect/Method; method   (line 391)
                    ALOAD_2     // Ljava/beans/PropertyDescriptor; pd
                    INVOKEVIRTUAL java.beans.PropertyDescriptor.getReadMethod ()Ljava/lang/reflect/Method;
                    INVOKEVIRTUAL java.lang.reflect.Method.equals (Ljava/lang/Object;)Z
                    IFNE L1
                    ALOAD_0     // Ljava/lang/reflect/Method; method
                    ALOAD_2     // Ljava/beans/PropertyDescriptor; pd
                    INVOKEVIRTUAL java.beans.PropertyDescriptor.getWriteMethod ()Ljava/lang/reflect/Method;
                    INVOKEVIRTUAL java.lang.reflect.Method.equals (Ljava/lang/Object;)Z
                    IFEQ L2
                L1: ALOAD_2     // Ljava/beans/PropertyDescriptor; pd   (line 392)
                    ARETURN
                L2: IINC_3 1   (line 390)
                L3: ILOAD_3
                    ILOAD 4
                    IF_ICMPLT L0
                    ACONST_NULL   (line 395)
                    ARETURN
  end public static java.beans.PropertyDescriptor findPropertyForMethod(java.lang.reflect.Method) throws org.springframework.beans.BeansException

  public static java.beans.PropertyEditor findEditorByConvention(Class):
                    ALOAD_0     // Ljava/lang/Class; targetType   (line 408)
                    IFNULL L0
                    ALOAD_0     // Ljava/lang/Class; targetType
                    INVOKEVIRTUAL java.lang.Class.isArray ()Z
                    IFNE L0
                    GETSTATIC org.springframework.beans.BeanUtils.unknownEditorTypes Ljava/util/Map;
                    ALOAD_0     // Ljava/lang/Class; targetType
                    INVOKEINTERFACE java.util.Map.containsKey (Ljava/lang/Object;)Z
                    IFEQ L1
                L0: ACONST_NULL   (line 409)
                    ARETURN
                L1: ALOAD_0     // Ljava/lang/Class; targetType   (line 411)
                    INVOKEVIRTUAL java.lang.Class.getClassLoader ()Ljava/lang/ClassLoader;
                    ASTORE_1
                    ALOAD_1     // Ljava/lang/ClassLoader; cl   (line 412)
                    IFNONNULL L3
    catch java.lang.Throwable -> E0
    |               INVOKESTATIC java.lang.ClassLoader.getSystemClassLoader ()Ljava/lang/ClassLoader;   (line 414)
    |               ASTORE_1     // Ljava/lang/ClassLoader; cl
    |               ALOAD_1     // Ljava/lang/ClassLoader; cl   (line 415)
    |               IFNONNULL L3
    catch java.lang.Throwable -> E0
                    ACONST_NULL   (line 416)
                    ARETURN
                E0: ASTORE_2   (line 419)
                    GETSTATIC org.springframework.beans.BeanUtils.logger Lorg/apache/commons/logging/Log;   (line 421)
                    INVOKEINTERFACE org.apache.commons.logging.Log.isDebugEnabled ()Z
                    IFEQ L2
                    GETSTATIC org.springframework.beans.BeanUtils.logger Lorg/apache/commons/logging/Log;   (line 422)
                    NEW java.lang.StringBuilder
                    DUP
                    LDC_W "Could not access system ClassLoader: "
                    INVOKESPECIAL java.lang.StringBuilder.<init> (Ljava/lang/String;)V
                    ALOAD_2     // Ljava/lang/Throwable; ex
                    INVOKEVIRTUAL java.lang.StringBuilder.append (Ljava/lang/Object;)Ljava/lang/StringBuilder;
                    INVOKEVIRTUAL java.lang.StringBuilder.toString ()Ljava/lang/String;
                    INVOKEINTERFACE org.apache.commons.logging.Log.debug (Ljava/lang/Object;)V
                L2: ACONST_NULL   (line 424)
                    ARETURN
                L3: NEW java.lang.StringBuilder   (line 427)
                    DUP
                    ALOAD_0     // Ljava/lang/Class; targetType
                    INVOKEVIRTUAL java.lang.Class.getName ()Ljava/lang/String;
                    INVOKESTATIC java.lang.String.valueOf (Ljava/lang/Object;)Ljava/lang/String;
                    INVOKESPECIAL java.lang.StringBuilder.<init> (Ljava/lang/String;)V
                    LDC_W "Editor"
                    INVOKEVIRTUAL java.lang.StringBuilder.append (Ljava/lang/String;)Ljava/lang/StringBuilder;
                    INVOKEVIRTUAL java.lang.StringBuilder.toString ()Ljava/lang/String;
                    ASTORE_2
    catch java.lang.ClassNotFoundException -> E2
    |               ALOAD_1     // Ljava/lang/ClassLoader; cl   (line 429)
    |               ALOAD_2     // Ljava/lang/String; editorName
    |               INVOKEVIRTUAL java.lang.ClassLoader.loadClass (Ljava/lang/String;)Ljava/lang/Class;
    |               ASTORE_3
    |               LDC_W java.beans.PropertyEditor   (line 430)
    |               ALOAD_3     // Ljava/lang/Class; editorClass
    |               INVOKEVIRTUAL java.lang.Class.isAssignableFrom (Ljava/lang/Class;)Z
    |               IFNE L5
    |               GETSTATIC org.springframework.beans.BeanUtils.logger Lorg/apache/commons/logging/Log;   (line 431)
    |               INVOKEINTERFACE org.apache.commons.logging.Log.isWarnEnabled ()Z
    |               IFEQ L4
    |               GETSTATIC org.springframework.beans.BeanUtils.logger Lorg/apache/commons/logging/Log;   (line 432)
    |               NEW java.lang.StringBuilder
    |               DUP
    |               LDC_W "Editor class ["
    |               INVOKESPECIAL java.lang.StringBuilder.<init> (Ljava/lang/String;)V
    |               ALOAD_2     // Ljava/lang/String; editorName
    |               INVOKEVIRTUAL java.lang.StringBuilder.append (Ljava/lang/String;)Ljava/lang/StringBuilder;
    |               LDC_W "] does not implement [java.beans.PropertyEditor] interface"   (line 433)
    |               INVOKEVIRTUAL java.lang.StringBuilder.append (Ljava/lang/String;)Ljava/lang/StringBuilder;
    |               INVOKEVIRTUAL java.lang.StringBuilder.toString ()Ljava/lang/String;
    |               INVOKEINTERFACE org.apache.commons.logging.Log.warn (Ljava/lang/Object;)V   (line 432)
    |           L4: GETSTATIC org.springframework.beans.BeanUtils.unknownEditorTypes Ljava/util/Map;   (line 435)
    |               ALOAD_0     // Ljava/lang/Class; targetType
    |               GETSTATIC java.lang.Boolean.TRUE Ljava/lang/Boolean;
    |               INVOKEINTERFACE java.util.Map.put (Ljava/lang/Object;Ljava/lang/Object;)Ljava/lang/Object;
    |               POP
    catch java.lang.ClassNotFoundException -> E2
                    ACONST_NULL   (line 436)
                    ARETURN
    catch java.lang.ClassNotFoundException -> E2
    |           L5: ALOAD_3     // Ljava/lang/Class; editorClass   (line 438)
    |               INVOKESTATIC org.springframework.beans.BeanUtils.instantiateClass (Ljava/lang/Class;)Ljava/lang/Object;
    |               CHECKCAST java.beans.PropertyEditor
    catch java.lang.ClassNotFoundException -> E2
                    ARETURN
                E2: POP   (line 440)
                    GETSTATIC org.springframework.beans.BeanUtils.logger Lorg/apache/commons/logging/Log;   (line 441)
                    INVOKEINTERFACE org.apache.commons.logging.Log.isDebugEnabled ()Z
                    IFEQ L6
                    GETSTATIC org.springframework.beans.BeanUtils.logger Lorg/apache/commons/logging/Log;   (line 442)
                    NEW java.lang.StringBuilder
                    DUP
                    LDC_W "No property editor ["
                    INVOKESPECIAL java.lang.StringBuilder.<init> (Ljava/lang/String;)V
                    ALOAD_2     // Ljava/lang/String; editorName
                    INVOKEVIRTUAL java.lang.StringBuilder.append (Ljava/lang/String;)Ljava/lang/StringBuilder;
                    LDC_W "] found for type "
                    INVOKEVIRTUAL java.lang.StringBuilder.append (Ljava/lang/String;)Ljava/lang/StringBuilder;
                    ALOAD_0     // Ljava/lang/Class; targetType   (line 443)
                    INVOKEVIRTUAL java.lang.Class.getName ()Ljava/lang/String;
                    INVOKEVIRTUAL java.lang.StringBuilder.append (Ljava/lang/String;)Ljava/lang/StringBuilder;
                    LDC_W " according to 'Editor' suffix convention"
                    INVOKEVIRTUAL java.lang.StringBuilder.append (Ljava/lang/String;)Ljava/lang/StringBuilder;
                    INVOKEVIRTUAL java.lang.StringBuilder.toString ()Ljava/lang/String;
                    INVOKEINTERFACE org.apache.commons.logging.Log.debug (Ljava/lang/Object;)V   (line 442)
                L6: GETSTATIC org.springframework.beans.BeanUtils.unknownEditorTypes Ljava/util/Map;   (line 445)
                    ALOAD_0     // Ljava/lang/Class; targetType
                    GETSTATIC java.lang.Boolean.TRUE Ljava/lang/Boolean;
                    INVOKEINTERFACE java.util.Map.put (Ljava/lang/Object;Ljava/lang/Object;)Ljava/lang/Object;
                    POP
                    ACONST_NULL   (line 446)
                    ARETURN
  end public static java.beans.PropertyEditor findEditorByConvention(Class)

  public static Class findPropertyType(String, Class[]):
                    ALOAD_1     // [Ljava/lang/Class; beanClasses   (line 458)
                    IFNULL L3
                    ALOAD_1     // [Ljava/lang/Class; beanClasses   (line 459)
                    DUP
                    ASTORE 5
                    ARRAYLENGTH
                    ISTORE 4
                    ICONST_0
                    ISTORE_3
                    GOTO L2
                L0: ALOAD 5
                    ILOAD_3
                    AALOAD
                    ASTORE_2
                    ALOAD_2     // Ljava/lang/Class; beanClass   (line 460)
                    ALOAD_0     // Ljava/lang/String; propertyName
                    INVOKESTATIC org.springframework.beans.BeanUtils.getPropertyDescriptor (Ljava/lang/Class;Ljava/lang/String;)Ljava/beans/PropertyDescriptor;
                    ASTORE 6
                    ALOAD 6     // Ljava/beans/PropertyDescriptor; pd   (line 461)
                    IFNULL L1
                    ALOAD 6     // Ljava/beans/PropertyDescriptor; pd   (line 462)
                    INVOKEVIRTUAL java.beans.PropertyDescriptor.getPropertyType ()Ljava/lang/Class;
                    ARETURN
                L1: IINC_3 1   (line 459)
                L2: ILOAD_3
                    ILOAD 4
                    IF_ICMPLT L0
                L3: LDC java.lang.Object   (line 466)
                    ARETURN
  end public static Class findPropertyType(String, Class[])

  public static org.springframework.core.MethodParameter getWriteMethodParameter(java.beans.PropertyDescriptor):
                    ALOAD_0     // Ljava/beans/PropertyDescriptor; pd   (line 476)
                    INSTANCEOF org.springframework.beans.GenericTypeAwarePropertyDescriptor
                    IFEQ L0
                    NEW org.springframework.core.MethodParameter   (line 477)
                    DUP
                    ALOAD_0     // Ljava/beans/PropertyDescriptor; pd   (line 478)
                    CHECKCAST org.springframework.beans.GenericTypeAwarePropertyDescriptor
                    INVOKEVIRTUAL org.springframework.beans.GenericTypeAwarePropertyDescriptor.getWriteMethodParameter ()Lorg/springframework/core/MethodParameter;
                    INVOKESPECIAL org.springframework.core.MethodParameter.<init> (Lorg/springframework/core/MethodParameter;)V   (line 477)
                    ARETURN
                L0: NEW org.springframework.core.MethodParameter   (line 481)
                    DUP
                    ALOAD_0     // Ljava/beans/PropertyDescriptor; pd
                    INVOKEVIRTUAL java.beans.PropertyDescriptor.getWriteMethod ()Ljava/lang/reflect/Method;
                    ICONST_0
                    INVOKESPECIAL org.springframework.core.MethodParameter.<init> (Ljava/lang/reflect/Method;I)V
                    ARETURN
  end public static org.springframework.core.MethodParameter getWriteMethodParameter(java.beans.PropertyDescriptor)

  public static boolean isSimpleProperty(Class):
                    ALOAD_0     // Ljava/lang/Class; clazz   (line 496)
                    LDC "Class must not be null"
                    INVOKESTATIC org.springframework.util.Assert.notNull (Ljava/lang/Object;Ljava/lang/String;)V
                    ALOAD_0     // Ljava/lang/Class; clazz   (line 497)
                    INVOKESTATIC org.springframework.beans.BeanUtils.isSimpleValueType (Ljava/lang/Class;)Z
                    IFNE L1
                    ALOAD_0     // Ljava/lang/Class; clazz
                    INVOKEVIRTUAL java.lang.Class.isArray ()Z
                    IFEQ L0
                    ALOAD_0     // Ljava/lang/Class; clazz
                    INVOKEVIRTUAL java.lang.Class.getComponentType ()Ljava/lang/Class;
                    INVOKESTATIC org.springframework.beans.BeanUtils.isSimpleValueType (Ljava/lang/Class;)Z
                    IFNE L1
                L0: ICONST_0
                    IRETURN
                L1: ICONST_1
                    IRETURN
  end public static boolean isSimpleProperty(Class)

  public static boolean isSimpleValueType(Class):
                    ALOAD_0     // Ljava/lang/Class; clazz   (line 508)
                    INVOKESTATIC org.springframework.util.ClassUtils.isPrimitiveOrWrapper (Ljava/lang/Class;)Z
                    IFNE L0
                    ALOAD_0     // Ljava/lang/Class; clazz
                    INVOKEVIRTUAL java.lang.Class.isEnum ()Z
                    IFNE L0
                    LDC_W java.lang.CharSequence   (line 509)
                    ALOAD_0     // Ljava/lang/Class; clazz
                    INVOKEVIRTUAL java.lang.Class.isAssignableFrom (Ljava/lang/Class;)Z
                    IFNE L0
                    LDC_W java.lang.Number   (line 510)
                    ALOAD_0     // Ljava/lang/Class; clazz
                    INVOKEVIRTUAL java.lang.Class.isAssignableFrom (Ljava/lang/Class;)Z
                    IFNE L0
                    LDC_W java.util.Date   (line 511)
                    ALOAD_0     // Ljava/lang/Class; clazz
                    INVOKEVIRTUAL java.lang.Class.isAssignableFrom (Ljava/lang/Class;)Z
                    IFNE L0
                    ALOAD_0     // Ljava/lang/Class; clazz   (line 512)
                    LDC_W java.net.URI
                    INVOKEVIRTUAL java.lang.Object.equals (Ljava/lang/Object;)Z
                    IFNE L0
                    ALOAD_0     // Ljava/lang/Class; clazz
                    LDC_W java.net.URL
                    INVOKEVIRTUAL java.lang.Object.equals (Ljava/lang/Object;)Z
                    IFNE L0
                    ALOAD_0     // Ljava/lang/Class; clazz   (line 513)
                    LDC_W java.util.Locale
                    INVOKEVIRTUAL java.lang.Object.equals (Ljava/lang/Object;)Z
                    IFNE L0
                    ALOAD_0     // Ljava/lang/Class; clazz
                    LDC java.lang.Class
                    INVOKEVIRTUAL java.lang.Object.equals (Ljava/lang/Object;)Z
                    IFNE L0
                    ICONST_0
                    IRETURN
                L0: ICONST_1
                    IRETURN   (line 508)
  end public static boolean isSimpleValueType(Class)

  public static void copyProperties(Object, Object) throws org.springframework.beans.BeansException:
                    ALOAD_0     // Ljava/lang/Object; source   (line 530)
                    ALOAD_1     // Ljava/lang/Object; target
                    ACONST_NULL
                    ACONST_NULL
                    INVOKESTATIC org.springframework.beans.BeanUtils.copyProperties (Ljava/lang/Object;Ljava/lang/Object;Ljava/lang/Class;[Ljava/lang/String;)V
                    RETURN   (line 531)
  end public static void copyProperties(Object, Object) throws org.springframework.beans.BeansException

  public static void copyProperties(Object, Object, Class) throws org.springframework.beans.BeansException:
                    ALOAD_0     // Ljava/lang/Object; source   (line 550)
                    ALOAD_1     // Ljava/lang/Object; target
                    ALOAD_2     // Ljava/lang/Class; editable
                    ACONST_NULL
                    INVOKESTATIC org.springframework.beans.BeanUtils.copyProperties (Ljava/lang/Object;Ljava/lang/Object;Ljava/lang/Class;[Ljava/lang/String;)V
                    RETURN   (line 551)
  end public static void copyProperties(Object, Object, Class) throws org.springframework.beans.BeansException

  public static void copyProperties(Object, Object, String[]) throws org.springframework.beans.BeansException:
                    ALOAD_0     // Ljava/lang/Object; source   (line 570)
                    ALOAD_1     // Ljava/lang/Object; target
                    ACONST_NULL
                    ALOAD_2     // [Ljava/lang/String; ignoreProperties
                    INVOKESTATIC org.springframework.beans.BeanUtils.copyProperties (Ljava/lang/Object;Ljava/lang/Object;Ljava/lang/Class;[Ljava/lang/String;)V
                    RETURN   (line 571)
  end public static void copyProperties(Object, Object, String[]) throws org.springframework.beans.BeansException

  private static void copyProperties(Object, Object, Class, String[]) throws org.springframework.beans.BeansException:
                    ALOAD_0     // Ljava/lang/Object; source   (line 588)
                    LDC_W "Source must not be null"
                    INVOKESTATIC org.springframework.util.Assert.notNull (Ljava/lang/Object;Ljava/lang/String;)V
                    ALOAD_1     // Ljava/lang/Object; target   (line 589)
                    LDC_W "Target must not be null"
                    INVOKESTATIC org.springframework.util.Assert.notNull (Ljava/lang/Object;Ljava/lang/String;)V
                    ALOAD_1     // Ljava/lang/Object; target   (line 591)
                    INVOKEVIRTUAL java.lang.Object.getClass ()Ljava/lang/Class;
                    ASTORE 4
                    ALOAD_2     // Ljava/lang/Class; editable   (line 592)
                    IFNULL L1
                    ALOAD_2     // Ljava/lang/Class; editable   (line 593)
                    ALOAD_1     // Ljava/lang/Object; target
                    INVOKEVIRTUAL java.lang.Class.isInstance (Ljava/lang/Object;)Z
                    IFNE L0
                    NEW java.lang.IllegalArgumentException   (line 594)
                    DUP
                    NEW java.lang.StringBuilder
                    DUP
                    LDC_W "Target class ["
                    INVOKESPECIAL java.lang.StringBuilder.<init> (Ljava/lang/String;)V
                    ALOAD_1     // Ljava/lang/Object; target
                    INVOKEVIRTUAL java.lang.Object.getClass ()Ljava/lang/Class;
                    INVOKEVIRTUAL java.lang.Class.getName ()Ljava/lang/String;
                    INVOKEVIRTUAL java.lang.StringBuilder.append (Ljava/lang/String;)Ljava/lang/StringBuilder;
                    LDC_W "] not assignable to Editable class ["   (line 595)
                    INVOKEVIRTUAL java.lang.StringBuilder.append (Ljava/lang/String;)Ljava/lang/StringBuilder;
                    ALOAD_2     // Ljava/lang/Class; editable
                    INVOKEVIRTUAL java.lang.Class.getName ()Ljava/lang/String;
                    INVOKEVIRTUAL java.lang.StringBuilder.append (Ljava/lang/String;)Ljava/lang/StringBuilder;
                    LDC_W "]"
                    INVOKEVIRTUAL java.lang.StringBuilder.append (Ljava/lang/String;)Ljava/lang/StringBuilder;
                    INVOKEVIRTUAL java.lang.StringBuilder.toString ()Ljava/lang/String;
                    INVOKESPECIAL java.lang.IllegalArgumentException.<init> (Ljava/lang/String;)V   (line 594)
                    ATHROW
                L0: ALOAD_2     // Ljava/lang/Class; editable   (line 597)
                    ASTORE 4     // Ljava/lang/Class; actualEditable
                L1: ALOAD 4     // Ljava/lang/Class; actualEditable   (line 599)
                    INVOKESTATIC org.springframework.beans.BeanUtils.getPropertyDescriptors (Ljava/lang/Class;)[Ljava/beans/PropertyDescriptor;
                    ASTORE 5
                    ALOAD_3     // [Ljava/lang/String; ignoreProperties   (line 600)
                    IFNULL L2
                    ALOAD_3     // [Ljava/lang/String; ignoreProperties
                    INVOKESTATIC java.util.Arrays.asList ([Ljava/lang/Object;)Ljava/util/List;
                    GOTO L3
                L2: ACONST_NULL
                L3: ASTORE 6
                    ALOAD 5     // [Ljava/beans/PropertyDescriptor; targetPds   (line 602)
                    DUP
                    ASTORE 10
                    ARRAYLENGTH
                    ISTORE 9
                    ICONST_0
                    ISTORE 8
                    GOTO L9
                L4: ALOAD 10
                    ILOAD 8
                    AALOAD
                    ASTORE 7
                    ALOAD 7     // Ljava/beans/PropertyDescriptor; targetPd   (line 603)
                    INVOKEVIRTUAL java.beans.PropertyDescriptor.getWriteMethod ()Ljava/lang/reflect/Method;
                    IFNULL L8
                    ALOAD_3     // [Ljava/lang/String; ignoreProperties   (line 604)
                    IFNULL L5
                    ALOAD 6     // Ljava/util/List; ignoreList
                    ALOAD 7     // Ljava/beans/PropertyDescriptor; targetPd
                    INVOKEVIRTUAL java.beans.PropertyDescriptor.getName ()Ljava/lang/String;
                    INVOKEINTERFACE java.util.List.contains (Ljava/lang/Object;)Z
                    IFNE L8
                L5: ALOAD_0     // Ljava/lang/Object; source   (line 605)
                    INVOKEVIRTUAL java.lang.Object.getClass ()Ljava/lang/Class;
                    ALOAD 7     // Ljava/beans/PropertyDescriptor; targetPd
                    INVOKEVIRTUAL java.beans.PropertyDescriptor.getName ()Ljava/lang/String;
                    INVOKESTATIC org.springframework.beans.BeanUtils.getPropertyDescriptor (Ljava/lang/Class;Ljava/lang/String;)Ljava/beans/PropertyDescriptor;
                    ASTORE 11
                    ALOAD 11     // Ljava/beans/PropertyDescriptor; sourcePd   (line 606)
                    IFNULL L8
                    ALOAD 11     // Ljava/beans/PropertyDescriptor; sourcePd
                    INVOKEVIRTUAL java.beans.PropertyDescriptor.getReadMethod ()Ljava/lang/reflect/Method;
                    IFNULL L8
    catch java.lang.Throwable -> E0
    |               ALOAD 11     // Ljava/beans/PropertyDescriptor; sourcePd   (line 608)
    |               INVOKEVIRTUAL java.beans.PropertyDescriptor.getReadMethod ()Ljava/lang/reflect/Method;
    |               ASTORE 12
    |               ALOAD 12     // Ljava/lang/reflect/Method; readMethod   (line 609)
    |               INVOKEVIRTUAL java.lang.reflect.Method.getDeclaringClass ()Ljava/lang/Class;
    |               INVOKEVIRTUAL java.lang.Class.getModifiers ()I
    |               INVOKESTATIC java.lang.reflect.Modifier.isPublic (I)Z
    |               IFNE L6
    |               ALOAD 12     // Ljava/lang/reflect/Method; readMethod   (line 610)
    |               ICONST_1
    |               INVOKEVIRTUAL java.lang.reflect.Method.setAccessible (Z)V
    |           L6: ALOAD 12     // Ljava/lang/reflect/Method; readMethod   (line 612)
    |               ALOAD_0     // Ljava/lang/Object; source
    |               ICONST_0
    |               ANEWARRAY java.lang.Object
    |               INVOKEVIRTUAL java.lang.reflect.Method.invoke (Ljava/lang/Object;[Ljava/lang/Object;)Ljava/lang/Object;
    |               ASTORE 13
    |               ALOAD 7     // Ljava/beans/PropertyDescriptor; targetPd   (line 613)
    |               INVOKEVIRTUAL java.beans.PropertyDescriptor.getWriteMethod ()Ljava/lang/reflect/Method;
    |               ASTORE 14
    |               ALOAD 14     // Ljava/lang/reflect/Method; writeMethod   (line 614)
    |               INVOKEVIRTUAL java.lang.reflect.Method.getDeclaringClass ()Ljava/lang/Class;
    |               INVOKEVIRTUAL java.lang.Class.getModifiers ()I
    |               INVOKESTATIC java.lang.reflect.Modifier.isPublic (I)Z
    |               IFNE L7
    |               ALOAD 14     // Ljava/lang/reflect/Method; writeMethod   (line 615)
    |               ICONST_1
    |               INVOKEVIRTUAL java.lang.reflect.Method.setAccessible (Z)V
    |           L7: ALOAD 14     // Ljava/lang/reflect/Method; writeMethod   (line 617)
    |               ALOAD_1     // Ljava/lang/Object; target
    |               ICONST_1
    |               ANEWARRAY java.lang.Object
    |               DUP
    |               ICONST_0
    |               ALOAD 13     // Ljava/lang/Object; value
    |               AASTORE
    |               INVOKEVIRTUAL java.lang.reflect.Method.invoke (Ljava/lang/Object;[Ljava/lang/Object;)Ljava/lang/Object;
    |               POP
    catch java.lang.Throwable -> E0
                    GOTO L8
                E0: ASTORE 12   (line 619)
                    NEW org.springframework.beans.FatalBeanException   (line 620)
                    DUP
                    LDC_W "Could not copy properties from source to target"
                    ALOAD 12     // Ljava/lang/Throwable; ex
                    INVOKESPECIAL org.springframework.beans.FatalBeanException.<init> (Ljava/lang/String;Ljava/lang/Throwable;)V
                    ATHROW
                L8: IINC 8 1   (line 602)
                L9: ILOAD 8
                    ILOAD 9
                    IF_ICMPLT L4
                    RETURN   (line 625)
  end private static void copyProperties(Object, Object, Class, String[]) throws org.springframework.beans.BeansException
end public abstract class org.springframework.beans.BeanUtils
 -- (NullPointerException) null
null
java.lang.NullPointerException

debug weaving 'org.springframework.beans.factory.parsing.ComponentDefinition'
---- org.aspectj.weaver.ltw.LTWWorld@28c97a5 ----
Class loader:
sun.misc.Launcher$AppClassLoader@18b4aac2
Class loader parent:
sun.misc.Launcher$ExtClassLoader@722c41f4
Shadow mungers:
(around(extraFlags: 3): ((((((((((within(@org.springframework.cache.annotation.CacheEvict *) && execution(public * @org.springframework.cache.annotation.CacheEvict *.*(..))) && this(BindingTypePattern(java.lang.Object, 0))) && persingleton(org.springframework.cache.aspectj.AnnotationCacheAspect)) || (((within(@org.springframework.cache.annotation.Caching *) && execution(public * @org.springframework.cache.annotation.Caching *.*(..))) && this(BindingTypePattern(java.lang.Object, 0))) && persingleton(org.springframework.cache.aspectj.AnnotationCacheAspect))) || (((within(@org.springframework.cache.annotation.CachePut *) && execution(public * @org.springframework.cache.annotation.CachePut *.*(..))) && this(BindingTypePattern(java.lang.Object, 0))) && persingleton(org.springframework.cache.aspectj.AnnotationCacheAspect))) || (((within(@org.springframework.cache.annotation.Cacheable *) && execution(public * @org.springframework.cache.annotation.Cacheable *.*(..))) && this(BindingTypePattern(java.lang.Object, 0))) && persingleton(org.springframework.cache.aspectj.AnnotationCacheAspect))) || ((execution(@org.springframework.cache.annotation.Caching * *(..)) && this(BindingTypePattern(java.lang.Object, 0))) && persingleton(org.springframework.cache.aspectj.AnnotationCacheAspect))) || ((execution(@org.springframework.cache.annotation.Cacheable * *(..)) && this(BindingTypePattern(java.lang.Object, 0))) && persingleton(org.springframework.cache.aspectj.AnnotationCacheAspect))) || ((execution(@org.springframework.cache.annotation.CacheEvict * *(..)) && this(BindingTypePattern(java.lang.Object, 0))) && persingleton(org.springframework.cache.aspectj.AnnotationCacheAspect))) || ((execution(@org.springframework.cache.annotation.CachePut * *(..)) && this(BindingTypePattern(java.lang.Object, 0))) && persingleton(org.springframework.cache.aspectj.AnnotationCacheAspect)))->java.lang.Object org.springframework.cache.aspectj.AbstractCacheAspect.ajc$around$org_springframework_cache_aspectj_AbstractCacheAspect$1$2bc714b5(java.lang.Object, org.aspectj.runtime.internal.AroundClosure, org.aspectj.lang.JoinPoint))
(around(extraFlags: 5): ((execution(@org.springframework.scheduling.annotation.Async (void || java.util.concurrent.Future+) *(..)) && persingleton(org.springframework.scheduling.aspectj.AnnotationAsyncExecutionAspect)) || (execution((void || java.util.concurrent.Future+) @org.springframework.scheduling.annotation.Async *.*(..)) && persingleton(org.springframework.scheduling.aspectj.AnnotationAsyncExecutionAspect)))->java.lang.Object org.springframework.scheduling.aspectj.AbstractAsyncExecutionAspect.ajc$around$org_springframework_scheduling_aspectj_AbstractAsyncExecutionAspect$1$6c004c3e(org.aspectj.runtime.internal.AroundClosure, org.aspectj.lang.JoinPoint$StaticPart))
org.aspectj.weaver.Checker@5abff562
org.aspectj.weaver.Checker@12140c1d
(before(extraFlags: 4): ((((within(@org.springframework.transaction.annotation.Transactional *) && execution(public * @org.springframework.transaction.annotation.Transactional *.*(..))) && this(BindingTypePattern(java.lang.Object, 0))) && persingleton(org.springframework.transaction.aspectj.AnnotationTransactionAspect)) || ((execution(@org.springframework.transaction.annotation.Transactional * *(..)) && this(BindingTypePattern(java.lang.Object, 0))) && persingleton(org.springframework.transaction.aspectj.AnnotationTransactionAspect)))->void org.springframework.transaction.aspectj.AbstractTransactionAspect.ajc$before$org_springframework_transaction_aspectj_AbstractTransactionAspect$1$2a73e96c(java.lang.Object, org.aspectj.lang.JoinPoint$StaticPart))
(afterThrowing(extraFlags: 1): ((((within(@org.springframework.transaction.annotation.Transactional *) && execution(public * @org.springframework.transaction.annotation.Transactional *.*(..))) && this(BindingTypePattern(java.lang.Object, 0))) && persingleton(org.springframework.transaction.aspectj.AnnotationTransactionAspect)) || ((execution(@org.springframework.transaction.annotation.Transactional * *(..)) && this(BindingTypePattern(java.lang.Object, 0))) && persingleton(org.springframework.transaction.aspectj.AnnotationTransactionAspect)))->void org.springframework.transaction.aspectj.AbstractTransactionAspect.ajc$afterThrowing$org_springframework_transaction_aspectj_AbstractTransactionAspect$2$2a73e96c(java.lang.Object, java.lang.Throwable))
(afterReturning: ((((within(@org.springframework.transaction.annotation.Transactional *) && execution(public * @org.springframework.transaction.annotation.Transactional *.*(..))) && this(BindingTypePattern(java.lang.Object, 0))) && persingleton(org.springframework.transaction.aspectj.AnnotationTransactionAspect)) || ((execution(@org.springframework.transaction.annotation.Transactional * *(..)) && this(BindingTypePattern(java.lang.Object, 0))) && persingleton(org.springframework.transaction.aspectj.AnnotationTransactionAspect)))->void org.springframework.transaction.aspectj.AbstractTransactionAspect.ajc$afterReturning$org_springframework_transaction_aspectj_AbstractTransactionAspect$3$2a73e96c(java.lang.Object))
(after: ((((within(@org.springframework.transaction.annotation.Transactional *) && execution(public * @org.springframework.transaction.annotation.Transactional *.*(..))) && this(BindingTypePattern(java.lang.Object, 0))) && persingleton(org.springframework.transaction.aspectj.AnnotationTransactionAspect)) || ((execution(@org.springframework.transaction.annotation.Transactional * *(..)) && this(BindingTypePattern(java.lang.Object, 0))) && persingleton(org.springframework.transaction.aspectj.AnnotationTransactionAspect)))->void org.springframework.transaction.aspectj.AbstractTransactionAspect.ajc$after$org_springframework_transaction_aspectj_AbstractTransactionAspect$4$2a73e96c(java.lang.Object))
(before: (((((initialization(org.springframework.beans.factory.aspectj.ConfigurableObject.new(..)) && initialization(org.springframework.beans.factory.aspectj.ConfigurableObject+.new(..))) && this(BindingTypePattern(java.lang.Object, 0))) && @this(org.springframework.beans.factory.annotation.Configurable)) && if(boolean org.springframework.beans.factory.aspectj.AnnotationBeanConfigurerAspect.ajc$if$bb0(org.springframework.beans.factory.annotation.Configurable))) && persingleton(org.springframework.beans.factory.aspectj.AnnotationBeanConfigurerAspect))->void org.springframework.beans.factory.aspectj.AbstractDependencyInjectionAspect.ajc$before$org_springframework_beans_factory_aspectj_AbstractDependencyInjectionAspect$1$e854fa65(java.lang.Object))
(afterReturning: (((((initialization(org.springframework.beans.factory.aspectj.ConfigurableObject+.new(..)) && this(BindingTypePattern(java.lang.Object, 0))) && @this(org.springframework.beans.factory.annotation.Configurable)) && !(@this(org.springframework.beans.factory.annotation.Configurable) && if(boolean org.springframework.beans.factory.aspectj.AnnotationBeanConfigurerAspect.ajc$if$bb0(org.springframework.beans.factory.annotation.Configurable)))) && if(boolean org.springframework.beans.factory.aspectj.AbstractDependencyInjectionAspect.ajc$if$6f1(org.aspectj.lang.JoinPoint))) && persingleton(org.springframework.beans.factory.aspectj.AnnotationBeanConfigurerAspect))->void org.springframework.beans.factory.aspectj.AbstractDependencyInjectionAspect.ajc$afterReturning$org_springframework_beans_factory_aspectj_AbstractDependencyInjectionAspect$2$1ea6722c(java.lang.Object))
(afterReturning: (((execution(java.lang.Object org.springframework.beans.factory.aspectj.AbstractInterfaceDrivenDependencyInjectionAspect$ConfigurableDeserializationSupport+.readResolve()) && this(BindingTypePattern(java.lang.Object, 0))) && @this(org.springframework.beans.factory.annotation.Configurable)) && persingleton(org.springframework.beans.factory.aspectj.AnnotationBeanConfigurerAspect))->void org.springframework.beans.factory.aspectj.AbstractDependencyInjectionAspect.ajc$afterReturning$org_springframework_beans_factory_aspectj_AbstractDependencyInjectionAspect$3$6aa27052(java.lang.Object))
Type mungers:
(BcelTypeMunger ResolvedTypeMunger(Method, java.lang.Object org.springframework.beans.factory.aspectj.AbstractInterfaceDrivenDependencyInjectionAspect$ConfigurableDeserializationSupport.readResolve()))
(BcelTypeMunger ExposeTypeMunger(java.lang.Object))
(BcelTypeMunger ExposeTypeMunger(java.lang.Object))
(BcelTypeMunger ExposeTypeMunger(java.lang.Object))
(BcelTypeMunger ExposeTypeMunger(org.springframework.beans.factory.aspectj.ConfigurableObject))
(BcelTypeMunger ExposeTypeMunger(org.springframework.beans.factory.aspectj.AbstractInterfaceDrivenDependencyInjectionAspect$ConfigurableDeserializationSupport))
Late Type mungers:
Empty
